Workbook

Sheet Competitors
A1: Name | B1: URL | C1: Type (local / pan-EU / marketplace) | D1: B2B or B2C focus | E1: Prices shown incl./excl. VAT | F1: Shipping to Slovakia | G1: Shipping to Austria | H1: Shipping VAT treatment | I1: Free-shipping threshold | J1: Minimum order value | K1: Shipping/terms source URL | L1: Distinct basket items found (with price) | M1: Counted (yes/no) | N1: Notes | O1: of which EXACT/CLOSE
A2: METRO Slovakia | B2: https://www.metro.sk/ | C2: local | D2: B2B (cash & carry, registered business customers) | E2: Not readable (site blocked) | F2: Not readable | G2: Not readable | H2: Not readable | I2: Not readable | J2: Not readable | K2: https://www.metro.sk/ | L2: =SUMPRODUCT(--(COUNTIFS(Prices!$B$2:$B$35,A2,Prices!$A$2:$A$35,ROW($1:$17),Prices!$F$2:$F$35,">0")>0)) -> 0 | M2: =IF(L2>=6,"yes","no") -> no | N2: Every www.metro.sk URL (home page, robots.txt) returned HTTP 403 from a METRO-branded block page to scripts and to the web-fetch tool; shop.metro.sk / produkty.metro.sk did not resolve through the proxy. No prices recorded. Needs a manual check in a normal browser (METRO online shop typically needs a customer card login). | O2: =SUMPRODUCT(--(COUNTIFS(Prices!$B$2:$B$35,A2,Prices!$A$2:$A$35,ROW($1:$17),Prices!$M$2:$M$35,"EXACT")+COUNTIFS(Prices!$B$2:$B$35,A2,Prices!$A$2:$A$35,ROW($1:$17),Prices!$M$2:$M$35,"CLOSE")>0)) -> 0
A3: Gastromania.sk (GASTROMANIA CZ s.r.o., CZ) | B3: https://gastromania.sk/ | C3: pan-EU | D3: B2B + B2C (HORECA specialist; B2B contract customers) | E3: Both shown on product pages: 'Cena bez DPH' (shown first) and 'Cena s DPH' (23%). T&Cs state prices include VAT. | F3: SPS courier 8 EUR (bank transfer / online payment) or 9 EUR (cash on delivery), parcels max 31.5 kg and 60x60x120 cm; oversized parcels and pallet freight priced individually at order confirmation. | G3: Not offered publicly: T&Cs state published delivery costs apply only within the Slovak Republic; no Austria option or price shown. | H3: Not explicitly stated for shipping; T&Cs say listed prices include VAT | I3: Free delivery from 300 EUR (incl./excl. VAT not stated) | J3: None stated | K3: https://gastromania.sk/sposoby-dorucenia.html ; https://gastromania.sk/obchodne-podmienky.html ; https://gastromania.sk/b2b.html | L3: =SUMPRODUCT(--(COUNTIFS(Prices!$B$2:$B$35,A3,Prices!$A$2:$A$35,ROW($1:$17),Prices!$F$2:$F$35,">0")>0)) -> 15 | M3: =IF(L3>=6,"yes","no") -> yes | N3: Czech company (Český Těšín, IČ 28654684) with a Slovak storefront; large HORECA range (Contacto, HENDI, Stalgast, Bartscher, Cambro, APS). B2B customers sign a contract and get individual offers after login (not recorded). Many items show promotional prices with a crossed-out base price and 'lowest price in last 30 days'; the current (first-shown) price is recorded. Scripted access was repeatedly rate-limited (CAPTCHA), so product pages were read through the web-fetch tool on the same date. | O3: =SUMPRODUCT(--(COUNTIFS(Prices!$B$2:$B$35,A3,Prices!$A$2:$A$35,ROW($1:$17),Prices!$M$2:$M$35,"EXACT")+COUNTIFS(Prices!$B$2:$B$35,A3,Prices!$A$2:$A$35,ROW($1:$17),Prices!$M$2:$M$35,"CLOSE")>0)) -> 12
A4: GastroMarket.sk | B4: https://www.gastromarket.sk/ | C4: local | D4: Not determined (site not readable) | E4: Not readable (Cloudflare challenge) | F4: Not readable | G4: Not readable | H4: Not readable | I4: Not readable | J4: Not readable | K4: https://www.gastromarket.sk/ | L4: =SUMPRODUCT(--(COUNTIFS(Prices!$B$2:$B$35,A4,Prices!$A$2:$A$35,ROW($1:$17),Prices!$F$2:$F$35,">0")>0)) -> 0 | M4: =IF(L4>=6,"yes","no") -> no | N4: All URLs (home, robots.txt, sitemap.xml, search) return HTTP 403 with a Cloudflare 'Len chvíľu...' JavaScript challenge, both to scripts and to the web-fetch tool. No prices recorded. Web-search results associate GastroMarket with Linorex s.r.o. (Bratislava) through public-procurement contract PDFs on crz.gov.sk; those tender prices were NOT used (not current webshop prices). Needs a manual check in a normal browser. | O4: =SUMPRODUCT(--(COUNTIFS(Prices!$B$2:$B$35,A4,Prices!$A$2:$A$35,ROW($1:$17),Prices!$M$2:$M$35,"EXACT")+COUNTIFS(Prices!$B$2:$B$35,A4,Prices!$A$2:$A$35,ROW($1:$17),Prices!$M$2:$M$35,"CLOSE")>0)) -> 0
A5: Gastrozone.sk (GASTROZONE, spol. s r.o., CZ) | B5: https://www.gastrozone.sk/ | C5: pan-EU | D5: B2C (B2B account available) | E5: incl. VAT (23% SK DPH) shown first; net 'bez DPH' also shown on product pages | F5: Home delivery (courier) 4.90 EUR; pick-up points (Packeta, GLS ParcelShop) 3.90 EUR; DPD Pickup / Express One 4.20 EUR. Cash on delivery +1.80 EUR. | G5: Not offered publicly: the shop's T&Cs state published delivery costs apply only to delivery within the Slovak Republic; no Austria option shown (storefronts only SK/CZ/HU). | H5: Shipping prices shown incl. VAT with net in brackets (e.g. 4.90 EUR = 3.98 EUR bez DPH) | I5: Free delivery and pick-up for orders over 120 EUR incl. VAT (SK) | J5: None stated | K5: https://www.gastrozone.sk/informacie/doprava-a-platba/ ; https://www.gastrozone.sk/informacie/obchodne-podmienky/ | L5: =SUMPRODUCT(--(COUNTIFS(Prices!$B$2:$B$35,A5,Prices!$A$2:$A$35,ROW($1:$17),Prices!$F$2:$F$35,">0")>0)) -> 16 | M5: =IF(L5>=6,"yes","no") -> yes | N5: Czech company (Tábor/Hajany, VAT ID CZ29181747) running a Slovak-language storefront; general gastro + household range (Araven, Pujadas, HENDI, APS, Cambro, Schneider). Public prices are retail; registered B2B customers see wholesale prices after login (not recorded). Slovak T&Cs apply to consumers only. Several items shown 'Na objednávku (3-5 týždňov)' (to order, 3-5 weeks). | O5: =SUMPRODUCT(--(COUNTIFS(Prices!$B$2:$B$35,A5,Prices!$A$2:$A$35,ROW($1:$17),Prices!$M$2:$M$35,"EXACT")+COUNTIFS(Prices!$B$2:$B$35,A5,Prices!$A$2:$A$35,ROW($1:$17),Prices!$M$2:$M$35,"CLOSE")>0)) -> 9

Sheet Prices
A1: Basket item no. | B1: Competitor | C1: Product name | D1: Brand | E1: Product URL | F1: Listed price | G1: Currency | H1: Incl./excl. VAT | I1: VAT rate used | J1: Pack size | K1: Price basis (per pack / per piece) | L1: Net price per piece EUR | M1: Match quality | N1: Notes | O1: Date checked | P1: Summary value (EXACT/CLOSE from counted competitor)
A2: 1 | B2: Gastromania.sk (GASTROMANIA CZ s.r.o., CZ) | C2: Polykarbonátová gastronádoba GN1/1 65 mm | CONTACTO, 8211/065 | D2: Contacto | E2: https://gastromania.sk/gastronadoby-polykarbonatove/polykarbonatova-gastronadoba-gn1-1-65-mm-contacto-8211-065 | F2: 20.48 | G2: EUR | H2: excl. | I2: n/a | J2: 1 | K2: per piece | L2: =IF(ISNUMBER(F2),IF(H2="incl.",F2/(1+I2),F2)/IF(K2="per pack",J2,1),"") -> 20.48 | M2: EXACT | N2: Listed 'Cena bez DPH' 20.48 EUR / 'Cena s DPH' 25.19 EUR. PC, GN 1/1, 65 mm, 8,5 l. Promo price; base 22,75 bez DPH / 27,98 s DPH. Availability 30 days. | O2: 2026-09-30 | P2: =IF(AND(OR(M2="EXACT",M2="CLOSE"),ISNUMBER(L2),IFERROR(INDEX(Competitors!$M:$M,MATCH(B2,Competitors!$A:$A,0)),"no")="yes"),L2,"") -> 20.48
A3: 1 | B3: Gastrozone.sk (GASTROZONE, spol. s r.o., CZ) | C3: ARAVEN Gastronádoba GN 1/1, polykarbonát, Hĺbka: 65 mm, Objem: 8,6 L | D3: Araven | E3: https://www.gastrozone.sk/araven-gn-box-1-1-polykarbonat-hloubka-65-mm-objem-8-6-l.html | F3: 20.24 | G3: EUR | H3: incl. | I3: 0.23 | J3: 1 | K3: per piece | L3: =IF(ISNUMBER(F3),IF(H3="incl.",F3/(1+I3),F3)/IF(K3="per pack",J3,1),"") -> 16.455285 | M3: EXACT | N3: Page shows 20,24 EUR / 16,46 EUR bez DPH. Availability: to order (3-5 weeks). | O3: 2026-09-30 | P3: =IF(AND(OR(M3="EXACT",M3="CLOSE"),ISNUMBER(L3),IFERROR(INDEX(Competitors!$M:$M,MATCH(B3,Competitors!$A:$A,0)),"no")="yes"),L3,"") -> 16.455285
A4: 2 | B4: Gastromania.sk (GASTROMANIA CZ s.r.o., CZ) | C4: Polykarbonátová gastronádoba GN1/2 150 mm | CONTACTO, 8212/150 | D4: Contacto | E4: https://gastromania.sk/gastronadoby-polykarbonatove/polykarbonatova-gastronadoba-gn1-2-150-mm-contacto-8212-150 | F4: 16.15 | G4: EUR | H4: excl. | I4: n/a | J4: 1 | K4: per piece | L4: =IF(ISNUMBER(F4),IF(H4="incl.",F4/(1+I4),F4)/IF(K4="per pack",J4,1),"") -> 16.15 | M4: EXACT | N4: Listed 'Cena bez DPH' 16.15 EUR / 'Cena s DPH' 19.86 EUR. PC, GN 1/2, 150 mm, 9 l. Promo price; base 17,94 / 22,07. Availability 30 days. | O4: 2026-09-30 | P4: =IF(AND(OR(M4="EXACT",M4="CLOSE"),ISNUMBER(L4),IFERROR(INDEX(Competitors!$M:$M,MATCH(B4,Competitors!$A:$A,0)),"no")="yes"),L4,"") -> 16.15
A5: 2 | B5: Gastrozone.sk (GASTROZONE, spol. s r.o., CZ) | C5: ARAVEN Gastronádoba GN 1/2, polykarbonát, hĺbka: 150 mm, objem: 8 L | D5: Araven | E5: https://www.gastrozone.sk/araven-gn-nadoba-1-2-polykarbonat-hloubka-150-mm-objem-8-l.html | F5: 18.73 | G5: EUR | H5: incl. | I5: 0.23 | J5: 1 | K5: per piece | L5: =IF(ISNUMBER(F5),IF(H5="incl.",F5/(1+I5),F5)/IF(K5="per pack",J5,1),"") -> 15.227642 | M5: EXACT | N5: Page shows 18,73 EUR / 15,23 EUR bez DPH. Availability: to order (3-5 weeks). | O5: 2026-09-30 | P5: =IF(AND(OR(M5="EXACT",M5="CLOSE"),ISNUMBER(L5),IFERROR(INDEX(Competitors!$M:$M,MATCH(B5,Competitors!$A:$A,0)),"no")="yes"),L5,"") -> 15.227642
A6: 3 | B6: Gastromania.sk (GASTROMANIA CZ s.r.o., CZ) | C6: Gastronádoba z polypropylénu GN 1/3, 100 mm | CONTACTO, 5013/100 | D6: Contacto | E6: https://gastromania.sk/gastronadoby-polypropylenove/gastronadoba-z-polypropylenu-gn-1-3-100-mm-contacto-5013-100 | F6: 17.61 | G6: EUR | H6: excl. | I6: n/a | J6: 1 | K6: per piece | L6: =IF(ISNUMBER(F6),IF(H6="incl.",F6/(1+I6),F6)/IF(K6="per pack",J6,1),"") -> 17.61 | M6: CLOSE | N6: Listed 'Cena bez DPH' 17.61 EUR / 'Cena s DPH' 21.66 EUR. PP, GN 1/3, 100 mm, 4 l, but sold WITH lid and colour clips (container-only price not shown). Promo; base 19,57 / 24,07. Stock 1-2 pcs. | O6: 2026-09-30 | P6: =IF(AND(OR(M6="EXACT",M6="CLOSE"),ISNUMBER(L6),IFERROR(INDEX(Competitors!$M:$M,MATCH(B6,Competitors!$A:$A,0)),"no")="yes"),L6,"") -> 17.61
A7: 3 | B7: Gastrozone.sk (GASTROZONE, spol. s r.o., CZ) | C7: Gastro nádoba GN 1/3 176x325 mm, polypropylén, výška 100 mm | D7: Vollrath Pujadas | E7: https://www.gastrozone.sk/pujadas-gastro-nadoba-gn-1-3-polyprepylen-v-100-mm-176x325-mm.html | F7: 7.84 | G7: EUR | H7: incl. | I7: 0.23 | J7: 1 | K7: per piece | L7: =IF(ISNUMBER(F7),IF(H7="incl.",F7/(1+I7),F7)/IF(K7="per pack",J7,1),"") -> 6.3739837 | M7: EXACT | N7: White PP, 100 mm high per description. Page shows 7,84 EUR / 6,37 EUR bez DPH. In stock. | O7: 2026-09-30 | P7: =IF(AND(OR(M7="EXACT",M7="CLOSE"),ISNUMBER(L7),IFERROR(INDEX(Competitors!$M:$M,MATCH(B7,Competitors!$A:$A,0)),"no")="yes"),L7,"") -> 6.3739837
A8: 4 | B8: Gastromania.sk (GASTROMANIA CZ s.r.o., CZ) | C8: Veko z polypropylénu pre GN1/1 5511 | CONTACTO, 5511/532 | D8: Contacto | E8: https://gastromania.sk/veka-gn-polypropylenove/veko-z-polypropylenu-pre-gn1-1-5511-contacto-5511-532 | F8: 8.46 | G8: EUR | H8: excl. | I8: n/a | J8: 1 | K8: per piece | L8: =IF(ISNUMBER(F8),IF(H8="incl.",F8/(1+I8),F8)/IF(K8="per pack",J8,1),"") -> 8.46 | M8: EXACT | N8: Listed 'Cena bez DPH' 8.46 EUR / 'Cena s DPH' 10.41 EUR. PP lid GN 1/1, no seal/cut-outs. Promo; base 9,10 / 11,19. In stock 5-9 pcs. | O8: 2026-09-30 | P8: =IF(AND(OR(M8="EXACT",M8="CLOSE"),ISNUMBER(L8),IFERROR(INDEX(Competitors!$M:$M,MATCH(B8,Competitors!$A:$A,0)),"no")="yes"),L8,"") -> 8.46
A9: 4 | B9: Gastrozone.sk (GASTROZONE, spol. s r.o., CZ) | C9: Veko ku gastronádobe 1/1 polypropylén | D9: Vollrath Pujadas | E9: https://www.gastrozone.sk/pujadas-veko-ku-gastronadobe-1-1-polyprepylen.html | F9: 14.06 | G9: EUR | H9: incl. | I9: 0.23 | J9: 1 | K9: per piece | L9: =IF(ISNUMBER(F9),IF(H9="incl.",F9/(1+I9),F9)/IF(K9="per pack",J9,1),"") -> 11.430894 | M9: EXACT | N9: PP lid for GN 1/1. Page shows 14,06 EUR / 11,43 EUR bez DPH. In stock. | O9: 2026-09-30 | P9: =IF(AND(OR(M9="EXACT",M9="CLOSE"),ISNUMBER(L9),IFERROR(INDEX(Competitors!$M:$M,MATCH(B9,Competitors!$A:$A,0)),"no")="yes"),L9,"") -> 11.430894
A10: 5 | B10: Gastromania.sk (GASTROMANIA CZ s.r.o., CZ) | C10: Fľaša na omáčky, 0,475 ml | NEUMARKER, FIFO | D10: Neumarker | E10: https://gastromania.sk/davkovace-omacok/flasa-na-omacky-0-475-ml-neumarker-fifo | F10: 13.68 | G10: EUR | H10: excl. | I10: n/a | J10: 1 | K10: per piece | L10: =IF(ISNUMBER(F10),IF(H10="incl.",F10/(1+I10),F10)/IF(K10="per pack",J10,1),"") -> 13.68 | M10: APPROX | N10: Listed 'Cena bez DPH' 13.68 EUR / 'Cena s DPH' 16.83 EUR. 475 ml FIFO squeeze bottle (refilled from the bottom); MATERIAL AND TIP TYPE NOT STATED. No 500 ml PP single-tip bottle found (HENDI/Stalgast bottles are 0,35/0,7 l). Promo; base 14,40 / 17,71. Availability 40 days. | O10: 2026-09-30 | P10: =IF(AND(OR(M10="EXACT",M10="CLOSE"),ISNUMBER(L10),IFERROR(INDEX(Competitors!$M:$M,MATCH(B10,Competitors!$A:$A,0)),"no")="yes"),L10,"")
A11: 5 | B11: Gastrozone.sk (GASTROZONE, spol. s r.o., CZ) | C11: Dávkovacia mačkacia fľaša Schneider 500 ml | D11: Schneider | E11: https://www.gastrozone.sk/fasa-mackacie-s-uzatvaranim-0-5-l-odolna-od-40c-do-95c-transparentne-pre-styk-s-potravinama-schneider-10313.html | F11: 13.16 | G11: EUR | H11: incl. | I11: 0.23 | J11: 1 | K11: per piece | L11: =IF(ISNUMBER(F11),IF(H11="incl.",F11/(1+I11),F11)/IF(K11="per pack",J11,1),"") -> 10.699187 | M11: APPROX | N11: Material polyethylene (not PP); single nozzle with cap. No PP 500 ml squeeze bottle found. Page shows 13,16 / 10,70 bez DPH. | O11: 2026-09-30 | P11: =IF(AND(OR(M11="EXACT",M11="CLOSE"),ISNUMBER(L11),IFERROR(INDEX(Competitors!$M:$M,MATCH(B11,Competitors!$A:$A,0)),"no")="yes"),L11,"")
A12: 6 | B12: Gastromania.sk (GASTROMANIA CZ s.r.o., CZ) | C12: Dávkovač omáčok 1025 ml, žltý | TOM-GAST, MA-957 | D12: Tom-Gast | E12: https://gastromania.sk/davkovace-omacok/davkovac-omacok-1025-ml-zlty-tom-gast-ma-957 | F12: 1.28 | G12: EUR | H12: excl. | I12: n/a | J12: 1 | K12: per piece | L12: =IF(ISNUMBER(F12),IF(H12="incl.",F12/(1+I12),F12)/IF(K12="per pack",J12,1),"") -> 1.28 | M12: CLOSE | N12: Listed 'Cena bez DPH' 1.28 EUR / 'Cena s DPH' 1.57 EUR. Squeeze bottle 1025 ml, 275 x ø80 mm; MATERIAL NOT STATED (only 'plast'). Alternative: Contacto 1465/104 PE bottle 1 l (price not checked). In stock 25-99 pcs. | O12: 2026-09-30 | P12: =IF(AND(OR(M12="EXACT",M12="CLOSE"),ISNUMBER(L12),IFERROR(INDEX(Competitors!$M:$M,MATCH(B12,Competitors!$A:$A,0)),"no")="yes"),L12,"") -> 1.28
A13: 6 | B13: Gastrozone.sk (GASTROZONE, spol. s r.o., CZ) | C13: Dávkovacia mačkacia fľaša Schneider 1000 ml, transparentná | D13: Schneider | E13: https://www.gastrozone.sk/schneider-davkovaci-mackaci-lahev-1000-ml-transparentni.html | F13: 18.72 | G13: EUR | H13: incl. | I13: 0.23 | J13: 1 | K13: per piece | L13: =IF(ISNUMBER(F13),IF(H13="incl.",F13/(1+I13),F13)/IF(K13="per pack",J13,1),"") -> 15.219512 | M13: APPROX | N13: Material polyethylene (not PP). Cheaper alternative: APS 1,025 l squeeze bottle 4,50 EUR (material not stated, to order). Page shows 18,72 / 15,22 bez DPH. | O13: 2026-09-30 | P13: =IF(AND(OR(M13="EXACT",M13="CLOSE"),ISNUMBER(L13),IFERROR(INDEX(Competitors!$M:$M,MATCH(B13,Competitors!$A:$A,0)),"no")="yes"),L13,"")
A14: 7 | B14: Gastromania.sk (GASTROMANIA CZ s.r.o., CZ) | C14: Not found | E14: https://gastromania.sk/products/search/language:slo?q=d%C3%A1vkova%C4%8D+om%C3%A1%C4%8Dok+3+otvory | L14: =IF(ISNUMBER(F14),IF(H14="incl.",F14/(1+I14),F14)/IF(K14="per pack",J14,1),"") | N14: No triple-tip squeeze bottle found (searches 'dávkovač omáčok 3 trysky', '3 otvory' returned no products). | O14: 2026-09-30 | P14: =IF(AND(OR(M14="EXACT",M14="CLOSE"),ISNUMBER(L14),IFERROR(INDEX(Competitors!$M:$M,MATCH(B14,Competitors!$A:$A,0)),"no")="yes"),L14,"")
A15: 7 | B15: Gastrozone.sk (GASTROZONE, spol. s r.o., CZ) | C15: ARAVEN Stláčacia fľaša, LDPE, ø 80 mm, výška 253 mm, objem 0,75 L, 3 trysky | D15: Araven | E15: https://www.gastrozone.sk/araven-lahvicka-na-stlaceni-ldpe-o-80-mm-vyska-253-mm-objem-0-75-l-3-trysky.html | F15: 6.54 | G15: EUR | H15: incl. | I15: 0.23 | J15: 1 | K15: per piece | L15: =IF(ISNUMBER(F15),IF(H15="incl.",F15/(1+I15),F15)/IF(K15="per pack",J15,1),"") -> 5.3170732 | M15: APPROX | N15: Triple tip, but 750 ml instead of 500 ml; LDPE. No 500 ml triple-tip bottle found. Page shows 6,54 / 5,32 bez DPH. | O15: 2026-09-30 | P15: =IF(AND(OR(M15="EXACT",M15="CLOSE"),ISNUMBER(L15),IFERROR(INDEX(Competitors!$M:$M,MATCH(B15,Competitors!$A:$A,0)),"no")="yes"),L15,"")
A16: 8 | B16: Gastromania.sk (GASTROMANIA CZ s.r.o., CZ) | C16: Polyproplylénový dávkovač omáčok, 1,5 l, 130x90x290 mm | CONTACTO, 1324/150 | D16: Contacto | E16: https://gastromania.sk/davkovace-omacok/polyproplylenovy-davkovac-omacok-1-5-l-130x90x290-mm-contacto-1324-150 | F16: 19.42 | G16: EUR | H16: excl. | I16: n/a | J16: 1 | K16: per piece | L16: =IF(ISNUMBER(F16),IF(H16="incl.",F16/(1+I16),F16)/IF(K16="per pack",J16,1),"") -> 19.42 | M16: APPROX | N16: Listed 'Cena bez DPH' 19.42 EUR / 'Cena s DPH' 23.89 EUR. PP pump sauce dispenser 1,5 l; no stand mentioned. (HENDI 557983 'Držiak na dávkovač omáčok 3x 0,7 l' is a stand for bottles, sold separately, not priced here.) Stock 1-2 pcs. | O16: 2026-09-30 | P16: =IF(AND(OR(M16="EXACT",M16="CLOSE"),ISNUMBER(L16),IFERROR(INDEX(Competitors!$M:$M,MATCH(B16,Competitors!$A:$A,0)),"no")="yes"),L16,"")
A17: 8 | B17: Gastrozone.sk (GASTROZONE, spol. s r.o., CZ) | C17: ARAVEN Dávkovač omáčok GN 1/6, polypropylén, objem 2,6 L | D17: Araven | E17: https://www.gastrozone.sk/araven-gn-davkovac-omacek-1-6-polypropylen-obsah-2-6-l.html | F17: 26.69 | G17: EUR | H17: incl. | I17: 0.23 | J17: 1 | K17: per piece | L17: =IF(ISNUMBER(F17),IF(H17="incl.",F17/(1+I17),F17)/IF(K17="per pack",J17,1),"") -> 21.699187 | M17: APPROX | N17: PP pump dispenser in a GN 1/6 container (2,6 l); no stand. Page shows 26,69 / 21,70 bez DPH. Alternative: Contacto 3 l free-standing PE portion dispenser for ketchup/mustard, 75,35 EUR. | O17: 2026-09-30 | P17: =IF(AND(OR(M17="EXACT",M17="CLOSE"),ISNUMBER(L17),IFERROR(INDEX(Competitors!$M:$M,MATCH(B17,Competitors!$A:$A,0)),"no")="yes"),L17,"")
A18: 9 | B18: Gastromania.sk (GASTROMANIA CZ s.r.o., CZ) | C18: Doska na krájanie HACCP GN 1/1 fialová | HENDI, 826065 | D18: Hendi | E18: https://gastromania.sk/plastove-krajacie-dosky-haccp/doska-na-krajanie-haccp-gn-1-1-fialova-hendi-826065 | F18: 20.35 | G18: EUR | H18: excl. | I18: n/a | J18: 1 | K18: per piece | L18: =IF(ISNUMBER(F18),IF(H18="incl.",F18/(1+I18),F18)/IF(K18="per pack",J18,1),"") -> 20.35 | M18: CLOSE | N18: Listed 'Cena bez DPH' 20.35 EUR / 'Cena s DPH' 25.03 EUR. HDPE 500, 530x325 mm, HACCP (purple/allergen); thickness 15 mm per parameters (18 mm per description) instead of 20 mm; not dishwasher-safe. Alternative: Contacto 1515/530 HDPE 530x325x25 mm (price not checked). | O18: 2026-09-30 | P18: =IF(AND(OR(M18="EXACT",M18="CLOSE"),ISNUMBER(L18),IFERROR(INDEX(Competitors!$M:$M,MATCH(B18,Competitors!$A:$A,0)),"no")="yes"),L18,"") -> 20.35
A19: 9 | B19: Gastrozone.sk (GASTROZONE, spol. s r.o., CZ) | C19: Doštička na krájanie plastová 53x32,5x2 cm GN 1/1, s drážkou, biela | D19: Gastro | E19: https://www.gastrozone.sk/gastro-dosticka-na-krajanie-plastova-53x32-5x2-cm-gn-1-1-s-drazkou-biela.html | F19: 63.91 | G19: EUR | H19: incl. | I19: 0.23 | J19: 1 | K19: per piece | L19: =IF(ISNUMBER(F19),IF(H19="incl.",F19/(1+I19),F19)/IF(K19="per pack",J19,1),"") -> 51.95935 | M19: CLOSE | N19: Size and thickness match; HACCP, sold in HACCP colours (white/yellow/red/blue/green/brown). MATERIAL NOT STATED (only 'plast') - PE not confirmed. Has juice groove and rubber feet. Board without groove/feet: 82,21 EUR. | O19: 2026-09-30 | P19: =IF(AND(OR(M19="EXACT",M19="CLOSE"),ISNUMBER(L19),IFERROR(INDEX(Competitors!$M:$M,MATCH(B19,Competitors!$A:$A,0)),"no")="yes"),L19,"") -> 51.95935
A20: 10 | B20: Gastromania.sk (GASTROMANIA CZ s.r.o., CZ) | C20: Doska na krájanie 600x400x20 mm, červená | BARTSCHER, 60x40 R | D20: Bartscher | E20: https://gastromania.sk/plastove-krajacie-dosky-haccp/doska-na-krajanie-600x400x20-mm-cervena-bartscher-60x40-r | F20: 32.85 | G20: EUR | H20: excl. | I20: n/a | J20: 1 | K20: per piece | L20: =IF(ISNUMBER(F20),IF(H20="incl.",F20/(1+I20),F20)/IF(K20="per pack",J20,1),"") -> 32.85 | M20: EXACT | N20: Listed 'Cena bez DPH' 32.85 EUR / 'Cena s DPH' 40.41 EUR. PE, 600x400x20 mm, HACCP colour range (red/yellow/green/blue/brown/purple/white). Promo; base 36,50 / 44,90; lowest price in 30 days 41,03 s DPH. Availability 14 days. | O20: 2026-09-30 | P20: =IF(AND(OR(M20="EXACT",M20="CLOSE"),ISNUMBER(L20),IFERROR(INDEX(Competitors!$M:$M,MATCH(B20,Competitors!$A:$A,0)),"no")="yes"),L20,"") -> 32.85
A21: 10 | B21: Gastrozone.sk (GASTROZONE, spol. s r.o., CZ) | C21: Doštička na krájanie plastová 60x40x3 cm, s drážkou, biela | D21: Gastro | E21: https://www.gastrozone.sk/gastrodosticka-na-krajanie-plastova-60x40x3-cm-s-drazkou-biela.html | F21: 93.51 | G21: EUR | H21: incl. | I21: 0.23 | J21: 1 | K21: per piece | L21: =IF(ISNUMBER(F21),IF(H21="incl.",F21/(1+I21),F21)/IF(K21="per pack",J21,1),"") -> 76.02439 | M21: APPROX | N21: 30 mm thick instead of 20 mm AND material not stated (only 'plast'); HACCP colours available. No 600x400x20 board found. | O21: 2026-09-30 | P21: =IF(AND(OR(M21="EXACT",M21="CLOSE"),ISNUMBER(L21),IFERROR(INDEX(Competitors!$M:$M,MATCH(B21,Competitors!$A:$A,0)),"no")="yes"),L21,"")
A22: 11 | B22: Gastromania.sk (GASTROMANIA CZ s.r.o., CZ) | C22: Doska na krájanie s držadlom 300x200x10 mm, biela | HENDI, 826355 | D22: Hendi | E22: https://gastromania.sk/plastove-krajacie-dosky-biele/doska-na-krajanie-s-drzadlom-300x200x10-mm-biela-hendi-826355 | F22: 6.18 | G22: EUR | H22: excl. | I22: n/a | J22: 1 | K22: per piece | L22: =IF(ISNUMBER(F22),IF(H22="incl.",F22/(1+I22),F22)/IF(K22="per pack",J22,1),"") -> 6.18 | M22: CLOSE | N22: Listed 'Cena bez DPH' 6.18 EUR / 'Cena s DPH' 7.60 EUR. HDPE 300x200x10 mm with integrated handle; white only (not a HACCP colour set); not dishwasher-safe. In stock 100+. | O22: 2026-09-30 | P22: =IF(AND(OR(M22="EXACT",M22="CLOSE"),ISNUMBER(L22),IFERROR(INDEX(Competitors!$M:$M,MATCH(B22,Competitors!$A:$A,0)),"no")="yes"),L22,"") -> 6.18
A23: 11 | B23: Gastrozone.sk (GASTROZONE, spol. s r.o., CZ) | C23: Doska na krájanie HENDI s rukoväťou, 300 × 200 mm, biela | D23: Hendi | E23: https://www.gastrozone.sk/viceucelove-krajeci-prkenko-s-rukojeti-hendi-bila-300x200mm-obdelnikove.html | F23: 8.61 | G23: EUR | H23: incl. | I23: 0.23 | J23: 1 | K23: per piece | L23: =IF(ISNUMBER(F23),IF(H23="incl.",F23/(1+I23),F23)/IF(K23="per pack",J23,1),"") -> 7 | M23: CLOSE | N23: HDPE, 300x200x10 mm; integrated handle and only white/black offered (not a full HACCP colour set); not dishwasher-safe per spec. Page shows 8,61 / 7,00 bez DPH. | O23: 2026-09-30 | P23: =IF(AND(OR(M23="EXACT",M23="CLOSE"),ISNUMBER(L23),IFERROR(INDEX(Competitors!$M:$M,MATCH(B23,Competitors!$A:$A,0)),"no")="yes"),L23,"") -> 7
A24: 12 | B24: Gastromania.sk (GASTROMANIA CZ s.r.o., CZ) | C24: Nádoba na cesto na pizzu, 600x400x95 mm | HENDI, 880913 | D24: Hendi | E24: https://gastromania.sk/nadoby-na-pizza-cesto/nadoba-na-cesto-na-pizzu-600x400x95-mm-hendi-880913 | F24: 12.65 | G24: EUR | H24: excl. | I24: n/a | J24: 1 | K24: per piece | L24: =IF(ISNUMBER(F24),IF(H24="incl.",F24/(1+I24),F24)/IF(K24="per pack",J24,1),"") -> 12.65 | M24: CLOSE | N24: Listed 'Cena bez DPH' 12.65 EUR / 'Cena s DPH' 15.56 EUR. Stated PP, 600x400 mm, 95 mm high (5 mm lower), 18 l. NOTE: Gastrozone lists the same 18 l HENDI/AmerBox box as PET - material conflict between sites. Alternative: Stalgast 563410 600x400x100 mm 18,04 bez DPH (title says polyethylene, parameters say PP). | O24: 2026-09-30 | P24: =IF(AND(OR(M24="EXACT",M24="CLOSE"),ISNUMBER(L24),IFERROR(INDEX(Competitors!$M:$M,MATCH(B24,Competitors!$A:$A,0)),"no")="yes"),L24,"") -> 12.65
A25: 12 | B25: Gastrozone.sk (GASTROZONE, spol. s r.o., CZ) | C25: Araven Pizzabox na cesto PP, polypropylén, výška 100 mm, 600 x 400 mm | D25: Araven | E25: https://www.gastrozone.sk/araven-pizzabox-pp-vyska-100-mm-delka-600-mm-sirka-400-mm.html | F25: 22.96 | G25: EUR | H25: incl. | I25: 0.23 | J25: 1 | K25: per piece | L25: =IF(ISNUMBER(F25),IF(H25="incl.",F25/(1+I25),F25)/IF(K25="per pack",J25,1),"") -> 18.666667 | M25: EXACT | N25: PP, 600x400x100 mm. Page shows 22,96 / 18,67 bez DPH. In stock. | O25: 2026-09-30 | P25: =IF(AND(OR(M25="EXACT",M25="CLOSE"),ISNUMBER(L25),IFERROR(INDEX(Competitors!$M:$M,MATCH(B25,Competitors!$A:$A,0)),"no")="yes"),L25,"") -> 18.666667
A26: 13 | B26: Gastromania.sk (GASTROMANIA CZ s.r.o., CZ) | C26: Veko na nádobu 2510/600 | CONTACTO, 2510/601 | D26: Contacto | E26: https://gastromania.sk/veka-na-nadoby-na-cesto/veko-na-nadobu-2510-600-contacto-2510-601 | F26: 11.7 | G26: EUR | H26: excl. | I26: n/a | J26: 1 | K26: per piece | L26: =IF(ISNUMBER(F26),IF(H26="incl.",F26/(1+I26),F26)/IF(K26="per pack",J26,1),"") -> 11.7 | M26: EXACT | N26: Listed 'Cena bez DPH' 11.70 EUR / 'Cena s DPH' 14.39 EUR. PE lid for Contacto 600x400 dough box. Promo; base 13,00 / 15,99. Availability 30 days. | O26: 2026-09-30 | P26: =IF(AND(OR(M26="EXACT",M26="CLOSE"),ISNUMBER(L26),IFERROR(INDEX(Competitors!$M:$M,MATCH(B26,Competitors!$A:$A,0)),"no")="yes"),L26,"") -> 11.7
A27: 13 | B27: Gastrozone.sk (GASTROZONE, spol. s r.o., CZ) | C27: Araven Veko na pizzabox na cesto PP, 600 x 400 mm | D27: Araven | E27: https://www.gastrozone.sk/araven-viko-k-pizzove-krabici-z-pp-delka-600-mm-sirka-400-mm.html | F27: 13.61 | G27: EUR | H27: incl. | I27: 0.23 | J27: 1 | K27: per piece | L27: =IF(ISNUMBER(F27),IF(H27="incl.",F27/(1+I27),F27)/IF(K27="per pack",J27,1),"") -> 11.065041 | M27: EXACT | N27: PP lid for 600x400 dough box. Page shows 13,61 / 11,07 bez DPH. AmerBox PET-box lid 11,50 EUR also listed. | O27: 2026-09-30 | P27: =IF(AND(OR(M27="EXACT",M27="CLOSE"),ISNUMBER(L27),IFERROR(INDEX(Competitors!$M:$M,MATCH(B27,Competitors!$A:$A,0)),"no")="yes"),L27,"") -> 11.065041
A28: 14 | B28: Gastromania.sk (GASTROMANIA CZ s.r.o., CZ) | C28: Nádoba na pizza cesto 600x400x75 mm | CONTACTO, 2510/600 | D28: Contacto | E28: https://gastromania.sk/nadoby-na-pizza-cesto/nadoba-na-pizza-cesto-600x400x75-mm-contacto-2510-600 | F28: 15.21 | G28: EUR | H28: excl. | I28: n/a | J28: 1 | K28: per piece | L28: =IF(ISNUMBER(F28),IF(H28="incl.",F28/(1+I28),F28)/IF(K28="per pack",J28,1),"") -> 15.21 | M28: EXACT | N28: Listed 'Cena bez DPH' 15.21 EUR / 'Cena s DPH' 18.71 EUR. White polyethylene, 600x400x75 mm. Promo; base 16,90 / 20,79. Availability 30 days. | O28: 2026-09-30 | P28: =IF(AND(OR(M28="EXACT",M28="CLOSE"),ISNUMBER(L28),IFERROR(INDEX(Competitors!$M:$M,MATCH(B28,Competitors!$A:$A,0)),"no")="yes"),L28,"") -> 15.21
A29: 14 | B29: Gastrozone.sk (GASTROZONE, spol. s r.o., CZ) | C29: Nádoba AmerBox Kitchen Line na cesto na pizzu, 600 × 400 mm, 14 l (výška 75 mm) | D29: AmerBox (HENDI) | E29: https://www.gastrozone.sk/nadoba-na-pizza-testo-600x400-amerbox-kitchen-line-14l-600x400x-h-75mm.html | F29: 12.3 | G29: EUR | H29: incl. | I29: 0.23 | J29: 1 | K29: per piece | L29: =IF(ISNUMBER(F29),IF(H29="incl.",F29/(1+I29),F29)/IF(K29="per pack",J29,1),"") -> 10 | M29: APPROX | N29: 600x400x75 mm but PET (polyethylene terephthalate), not PE. Page shows 12,30 / 10,00 bez DPH. | O29: 2026-09-30 | P29: =IF(AND(OR(M29="EXACT",M29="CLOSE"),ISNUMBER(L29),IFERROR(INDEX(Competitors!$M:$M,MATCH(B29,Competitors!$A:$A,0)),"no")="yes"),L29,"")
A30: 15 | B30: Gastromania.sk (GASTROMANIA CZ s.r.o., CZ) | C30: Termobox s predným plnením pre GN | CAMBRO, R-EPP400 | D30: Cambro | E30: https://gastromania.sk/termoizolacne/termobox-s-prednym-plnenim-pre-gn-cambro-r-epp400 | F30: 228.24 | G30: EUR | H30: excl. | I30: n/a | J30: 1 | K30: per piece | L30: =IF(ISNUMBER(F30),IF(H30="incl.",F30/(1+I30),F30)/IF(K30="per pack",J30,1),"") -> 228.24 | M30: EXACT | N30: Listed 'Cena bez DPH' 228.24 EUR / 'Cena s DPH' 280.74 EUR. Front-loading, GN 1/1, 86 l, expanded polypropylene. In stock 5-9 pcs. | O30: 2026-09-30 | P30: =IF(AND(OR(M30="EXACT",M30="CLOSE"),ISNUMBER(L30),IFERROR(INDEX(Competitors!$M:$M,MATCH(B30,Competitors!$A:$A,0)),"no")="yes"),L30,"") -> 228.24
A31: 15 | B31: Gastrozone.sk (GASTROZONE, spol. s r.o., CZ) | C31: Termoizolačný box Cambro Cam GoBox, GN 1/1, 86 l, čierny | D31: Cambro | E31: https://www.gastrozone.sk/cambro-termoport-86-l-bocni-plneni.html | F31: 228.78 | G31: EUR | H31: incl. | I31: 0.23 | J31: 1 | K31: per piece | L31: =IF(ISNUMBER(F31),IF(H31="incl.",F31/(1+I31),F31)/IF(K31="per pack",J31,1),"") -> 186 | M31: CLOSE | N31: 86 l GN 1/1, EPP. Listing inconsistent: title says 's horným plnením' (top-loading) but URL and description say front loading with 270° door. Page shows 228,78 / 186,00 bez DPH. Cambro Ultra Pan Carrier front-loader (PE) 271,83 EUR, volume not stated. | O31: 2026-09-30 | P31: =IF(AND(OR(M31="EXACT",M31="CLOSE"),ISNUMBER(L31),IFERROR(INDEX(Competitors!$M:$M,MATCH(B31,Competitors!$A:$A,0)),"no")="yes"),L31,"") -> 186
A32: 16 | B32: Gastromania.sk (GASTROMANIA CZ s.r.o., CZ) | C32: Tácka z polypropylénu Fast Food 350x450 mm šedá | HENDI, 878804 | D32: Hendi | E32: https://gastromania.sk/obdlznikove-jedalne-podnosy/tacka-z-polypropylenu-fast-food-350x450-mm-seda-hendi-878804 | F32: 4.88 | G32: EUR | H32: excl. | I32: n/a | J32: 1 | K32: per piece | L32: =IF(ISNUMBER(F32),IF(H32="incl.",F32/(1+I32),F32)/IF(K32="per pack",J32,1),"") -> 4.88 | M32: APPROX | N32: Listed 'Cena bez DPH' 4.88 EUR / 'Cena s DPH' 6.00 EUR. PP, but 350x450 mm instead of approx. 370x530 mm. 530x370 trays found are polyester/laminate/laminated wood (e.g. Contacto 4411 polyester EN 1/1, HENDI 507117 laminated wood 18,70 bez DPH). | O32: 2026-09-30 | P32: =IF(AND(OR(M32="EXACT",M32="CLOSE"),ISNUMBER(L32),IFERROR(INDEX(Competitors!$M:$M,MATCH(B32,Competitors!$A:$A,0)),"no")="yes"),L32,"")
A33: 16 | B33: Gastrozone.sk (GASTROZONE, spol. s r.o., CZ) | C33: APS Fast Food podnos, GN 1/1, hnedý, 530 x 325 x 20 mm | D33: APS | E33: https://www.gastrozone.sk/aps-fast-food-tablett-gn-1-1-hnede-vyska-20-mm-delka-530-mm-sirka-325-mm.html | F33: 11.47 | G33: EUR | H33: incl. | I33: 0.23 | J33: 1 | K33: per piece | L33: =IF(ISNUMBER(F33),IF(H33="incl.",F33/(1+I33),F33)/IF(K33="per pack",J33,1),"") -> 9.3252033 | M33: APPROX | N33: PP, but 530x325 mm (GN 1/1) instead of approx. 530x370 mm. 530x370 trays found are other plastics: Roltex PYE (polyethylene) 40,32 EUR, Cambro fibreglass 35,31 EUR. To order (3-5 weeks). | O33: 2026-09-30 | P33: =IF(AND(OR(M33="EXACT",M33="CLOSE"),ISNUMBER(L33),IFERROR(INDEX(Competitors!$M:$M,MATCH(B33,Competitors!$A:$A,0)),"no")="yes"),L33,"")
A34: 17 | B34: Gastromania.sk (GASTROMANIA CZ s.r.o., CZ) | C34: Not found | E34: https://gastromania.sk/products/search/language:slo?q=termoizola%C4%8Dn%C3%BD+podnos | L34: =IF(ISNUMBER(F34),IF(H34="incl.",F34/(1+I34),F34)/IF(K34="per pack",J34,1),"") | N34: No insulated compartment tray found; search 'termoizolačný podnos' returns only trolleys/racks for thermo trays (DORA METAL), 'podnos s priehradkami' only wooden boxes. | O34: 2026-09-30 | P34: =IF(AND(OR(M34="EXACT",M34="CLOSE"),ISNUMBER(L34),IFERROR(INDEX(Competitors!$M:$M,MATCH(B34,Competitors!$A:$A,0)),"no")="yes"),L34,"")
A35: 17 | B35: Gastrozone.sk (GASTROZONE, spol. s r.o., CZ) | C35: Not found | E35: https://www.gastrozone.sk/vyhladavanie/?text=termoizola%C4%8Dn%C3%BD+podnos | L35: =IF(ISNUMBER(F35),IF(H35="incl.",F35/(1+I35),F35)/IF(K35="per pack",J35,1),"") | N35: No insulated compartment tray with lid found (searched 'termoizolačný podnos', 'termo tácka priehradky', 'podnos s priehradkami veko', 'menu box termo'). | O35: 2026-09-30 | P35: =IF(AND(OR(M35="EXACT",M35="CLOSE"),ISNUMBER(L35),IFERROR(INDEX(Competitors!$M:$M,MATCH(B35,Competitors!$A:$A,0)),"no")="yes"),L35,"")

Sheet Summary
A1: Basket item no. | B1: Item description | C1: Qualifying prices found | D1: Min net price per piece EUR | E1: Median net price per piece EUR | F1: Max net price per piece EUR
A2: 1 | B2: GN 1/1 polycarbonate container, 65 mm deep | C2: =COUNTIFS(Prices!$A$2:$A$35,A2,Prices!$P$2:$P$35,">0") -> 2 | D2: =IF(C2=0,"",_xlfn.MINIFS(Prices!$P$2:$P$35,Prices!$A$2:$A$35,A2)) -> 16.455285 | E2: {=IF(C2=0,"",MEDIAN(IF((Prices!$A$2:$A$35=A2)*ISNUMBER(Prices!$P$2:$P$35),Prices!$P$2:$P$35)))} -> 18.467642 | F2: =IF(C2=0,"",_xlfn.MAXIFS(Prices!$P$2:$P$35,Prices!$A$2:$A$35,A2)) -> 20.48
A3: 2 | B3: GN 1/2 polycarbonate container, 150 mm deep | C3: =COUNTIFS(Prices!$A$2:$A$35,A3,Prices!$P$2:$P$35,">0") -> 2 | D3: =IF(C3=0,"",_xlfn.MINIFS(Prices!$P$2:$P$35,Prices!$A$2:$A$35,A3)) -> 15.227642 | E3: {=IF(C3=0,"",MEDIAN(IF((Prices!$A$2:$A$35=A3)*ISNUMBER(Prices!$P$2:$P$35),Prices!$P$2:$P$35)))} -> 15.688821 | F3: =IF(C3=0,"",_xlfn.MAXIFS(Prices!$P$2:$P$35,Prices!$A$2:$A$35,A3)) -> 16.15
A4: 3 | B4: GN 1/3 polypropylene container, 100 mm deep | C4: =COUNTIFS(Prices!$A$2:$A$35,A4,Prices!$P$2:$P$35,">0") -> 2 | D4: =IF(C4=0,"",_xlfn.MINIFS(Prices!$P$2:$P$35,Prices!$A$2:$A$35,A4)) -> 6.3739837 | E4: {=IF(C4=0,"",MEDIAN(IF((Prices!$A$2:$A$35=A4)*ISNUMBER(Prices!$P$2:$P$35),Prices!$P$2:$P$35)))} -> 11.991992 | F4: =IF(C4=0,"",_xlfn.MAXIFS(Prices!$P$2:$P$35,Prices!$A$2:$A$35,A4)) -> 17.61
A5: 4 | B5: GN 1/1 polypropylene lid | C5: =COUNTIFS(Prices!$A$2:$A$35,A5,Prices!$P$2:$P$35,">0") -> 2 | D5: =IF(C5=0,"",_xlfn.MINIFS(Prices!$P$2:$P$35,Prices!$A$2:$A$35,A5)) -> 8.46 | E5: {=IF(C5=0,"",MEDIAN(IF((Prices!$A$2:$A$35=A5)*ISNUMBER(Prices!$P$2:$P$35),Prices!$P$2:$P$35)))} -> 9.9454472 | F5: =IF(C5=0,"",_xlfn.MAXIFS(Prices!$P$2:$P$35,Prices!$A$2:$A$35,A5)) -> 11.430894
A6: 5 | B6: Squeeze bottle 500 ml, polypropylene, single tip | C6: =COUNTIFS(Prices!$A$2:$A$35,A6,Prices!$P$2:$P$35,">0") -> 0 | D6: =IF(C6=0,"",_xlfn.MINIFS(Prices!$P$2:$P$35,Prices!$A$2:$A$35,A6)) | E6: {=IF(C6=0,"",MEDIAN(IF((Prices!$A$2:$A$35=A6)*ISNUMBER(Prices!$P$2:$P$35),Prices!$P$2:$P$35)))} | F6: =IF(C6=0,"",_xlfn.MAXIFS(Prices!$P$2:$P$35,Prices!$A$2:$A$35,A6))
A7: 6 | B7: Squeeze bottle 1000 ml, polypropylene, single tip | C7: =COUNTIFS(Prices!$A$2:$A$35,A7,Prices!$P$2:$P$35,">0") -> 1 | D7: =IF(C7=0,"",_xlfn.MINIFS(Prices!$P$2:$P$35,Prices!$A$2:$A$35,A7)) -> 1.28 | E7: {=IF(C7=0,"",MEDIAN(IF((Prices!$A$2:$A$35=A7)*ISNUMBER(Prices!$P$2:$P$35),Prices!$P$2:$P$35)))} -> 1.28 | F7: =IF(C7=0,"",_xlfn.MAXIFS(Prices!$P$2:$P$35,Prices!$A$2:$A$35,A7)) -> 1.28
A8: 7 | B8: Squeeze bottle 500 ml with triple tip | C8: =COUNTIFS(Prices!$A$2:$A$35,A8,Prices!$P$2:$P$35,">0") -> 0 | D8: =IF(C8=0,"",_xlfn.MINIFS(Prices!$P$2:$P$35,Prices!$A$2:$A$35,A8)) | E8: {=IF(C8=0,"",MEDIAN(IF((Prices!$A$2:$A$35=A8)*ISNUMBER(Prices!$P$2:$P$35),Prices!$P$2:$P$35)))} | F8: =IF(C8=0,"",_xlfn.MAXIFS(Prices!$P$2:$P$35,Prices!$A$2:$A$35,A8))
A9: 8 | B9: Ketchup/sauce pump dispenser with stand | C9: =COUNTIFS(Prices!$A$2:$A$35,A9,Prices!$P$2:$P$35,">0") -> 0 | D9: =IF(C9=0,"",_xlfn.MINIFS(Prices!$P$2:$P$35,Prices!$A$2:$A$35,A9)) | E9: {=IF(C9=0,"",MEDIAN(IF((Prices!$A$2:$A$35=A9)*ISNUMBER(Prices!$P$2:$P$35),Prices!$P$2:$P$35)))} | F9: =IF(C9=0,"",_xlfn.MAXIFS(Prices!$P$2:$P$35,Prices!$A$2:$A$35,A9))
A10: 9 | B10: HACCP colour-coded PE cutting board 530 x 325 x 20 mm (GN 1/1) | C10: =COUNTIFS(Prices!$A$2:$A$35,A10,Prices!$P$2:$P$35,">0") -> 2 | D10: =IF(C10=0,"",_xlfn.MINIFS(Prices!$P$2:$P$35,Prices!$A$2:$A$35,A10)) -> 20.35 | E10: {=IF(C10=0,"",MEDIAN(IF((Prices!$A$2:$A$35=A10)*ISNUMBER(Prices!$P$2:$P$35),Prices!$P$2:$P$35)))} -> 36.154675 | F10: =IF(C10=0,"",_xlfn.MAXIFS(Prices!$P$2:$P$35,Prices!$A$2:$A$35,A10)) -> 51.95935
A11: 10 | B11: HACCP colour-coded PE cutting board 600 x 400 x 20 mm | C11: =COUNTIFS(Prices!$A$2:$A$35,A11,Prices!$P$2:$P$35,">0") -> 1 | D11: =IF(C11=0,"",_xlfn.MINIFS(Prices!$P$2:$P$35,Prices!$A$2:$A$35,A11)) -> 32.85 | E11: {=IF(C11=0,"",MEDIAN(IF((Prices!$A$2:$A$35=A11)*ISNUMBER(Prices!$P$2:$P$35),Prices!$P$2:$P$35)))} -> 32.85 | F11: =IF(C11=0,"",_xlfn.MAXIFS(Prices!$P$2:$P$35,Prices!$A$2:$A$35,A11)) -> 32.85
A12: 11 | B12: HACCP colour-coded PE cutting board 300 x 200 x 10 mm | C12: =COUNTIFS(Prices!$A$2:$A$35,A12,Prices!$P$2:$P$35,">0") -> 2 | D12: =IF(C12=0,"",_xlfn.MINIFS(Prices!$P$2:$P$35,Prices!$A$2:$A$35,A12)) -> 6.18 | E12: {=IF(C12=0,"",MEDIAN(IF((Prices!$A$2:$A$35=A12)*ISNUMBER(Prices!$P$2:$P$35),Prices!$P$2:$P$35)))} -> 6.59 | F12: =IF(C12=0,"",_xlfn.MAXIFS(Prices!$P$2:$P$35,Prices!$A$2:$A$35,A12)) -> 7
A13: 12 | B13: Pizza dough proofing box 600 x 400 x 100 mm, polypropylene | C13: =COUNTIFS(Prices!$A$2:$A$35,A13,Prices!$P$2:$P$35,">0") -> 2 | D13: =IF(C13=0,"",_xlfn.MINIFS(Prices!$P$2:$P$35,Prices!$A$2:$A$35,A13)) -> 12.65 | E13: {=IF(C13=0,"",MEDIAN(IF((Prices!$A$2:$A$35=A13)*ISNUMBER(Prices!$P$2:$P$35),Prices!$P$2:$P$35)))} -> 15.658333 | F13: =IF(C13=0,"",_xlfn.MAXIFS(Prices!$P$2:$P$35,Prices!$A$2:$A$35,A13)) -> 18.666667
... A18: 17 | B18: Insulated thermo tray with lid, 5-6 compartments | C18: =COUNTIFS(Prices!$A$2:$A$35,A18,Prices!$P$2:$P$35,">0") -> 0 | D18: =IF(C18=0,"",_xlfn.MINIFS(Prices!$P$2:$P$35,Prices!$A$2:$A$35,A18)) | E18: {=IF(C18=0,"",MEDIAN(IF((Prices!$A$2:$A$35=A18)*ISNUMBER(Prices!$P$2:$P$35),Prices!$P$2:$P$35)))} | F18: =IF(C18=0,"",_xlfn.MAXIFS(Prices!$P$2:$P$35,Prices!$A$2:$A$35,A18))
A20: Statistics use only EXACT and CLOSE primary observations from counted competitors (Prices column P), one per competitor per item.
A21: Net price per piece = listed price / 1.23 when the listed price includes Slovak VAT (23%), divided by pack size when priced per pack.
A22: Blank statistics = no qualifying observation. APPROX matches are listed on the Prices sheet but excluded here.

Sheet Not accessible
A1: Competitor / page | B1: URL | C1: Reason | D1: Date checked | E1: Notes
A2: METRO Slovakia | B2: https://www.metro.sk/ | C2: Access error: HTTP 403 block page on all www.metro.sk URLs (scripts and web-fetch tool); shop.metro.sk and produkty.metro.sk unreachable. METRO online prices are normally shown only to registered customers. | D2: 2026-09-30 | E2: Not counted. No price evidence gathered; no search-snippet prices used.
A3: GastroMarket.sk | B3: https://www.gastromarket.sk/ | C3: Access error: Cloudflare JavaScript bot challenge (HTTP 403 'Len chvíľu...') on every URL incl. robots.txt, sitemap and search. | D3: 2026-09-30 | E3: Not counted. No prices could be read; web search found only public-procurement PDFs (crz.gov.sk), not used as price evidence.
A4: Gastromania.sk (scripted access only) | B4: https://gastromania.sk/ | C4: Partial access issue: after about 20 scripted requests the site returned a 'Security check' CAPTCHA page (IP rate limit). Listing pages load prices by JavaScript; product pages show prices in HTML. | D4: 2026-09-30 | E4: Competitor IS counted: prices were read from the live product pages via the web-fetch tool on the same date. Listed here only to document the access limitation.
