Workbook

Sheet Competitors
A1: Name | B1: URL | C1: Type (local / pan-EU / marketplace) | D1: B2B / B2C focus | E1: Prices shown incl./excl. VAT | F1: Shipping to Czechia | G1: Shipping to Austria (business address) | H1: Shipping VAT treatment | I1: Free-shipping threshold | J1: Minimum order value | K1: Shipping / terms source URL(s) | L1: Distinct basket items with price (any match) | M1: of which EXACT/CLOSE | N1: Counted (yes/no) | O1: Notes
A2: TOMGAST | B2: https://www.tomgast.cz/ | C2: local | D2: B2B + B2C (HORECA specialist; sells to consumers and businesses) | E2: Both shown: incl. 21% VAT as main price, "bez DPH" (excl. VAT) shown alongside | F2: GLS 149 CZK or PPL to address 149 CZK; personal pick-up Karviná free; cash on delivery +39 CZK | G2: Not offered: checkout country list contains only Czech Republic and Slovakia (checked in cart 2026-09-30). No Austrian shipping rate published. | H2: Shipping incl. 21% VAT (checkout: 1,440 CZK item + 149 CZK shipping = 1,589 CZK total, 1,313.22 CZK excl. VAT) | I2: Over 6,000 CZK (shipping page says "nad 6 000 Kč"; site header says "Objednávky nad 6 000 Kč bez DPH doručíme zdarma" i.e. 6,000 CZK excl. VAT) | J2: Not stated | K2: https://www.tomgast.cz/doprava-a-platba/ ; https://www.tomgast.cz/obchodni-podminky/ ; checkout https://www.tomgast.cz/objednavka/krok-1/ | L2: =COUNTIFS(Prices!$C$2:$C$600,A2,Prices!$G$2:$G$600,"<>") | M2: =COUNTIFS(Prices!$C$2:$C$600,A2,Prices!$G$2:$G$600,"<>",Prices!$N$2:$N$600,"EXACT")+COUNTIFS(Prices!$C$2:$C$600,A2,Prices!$G$2:$G$600,"<>",Prices!$N$2:$N$600,"CLOSE") | N2: =IF(L2>=6,"yes","no") | O2: Karviná-based HORECA wholesaler (TOMGAST Czech Republic s.r.o.), large Cambro range. Prices public without login. Stock status shown per item; some chosen items are "Očekáváme naskladnění" (awaiting stock).
A3: Gastro Novotný | B3: https://eshop.gastronovotny.cz/ | C3: local | D3: B2B-oriented wholesale ("Velkoobchod s gastro vybavením"), also sells to consumers (consumer withdrawal rights in T&C) | E3: Main price excl. VAT; "včetně DPH" (incl. 21% VAT) shown alongside | F3: Checkout options: PPL up to 20 kg 275 CZK; TopTrans (large/atypical items) 990 CZK; personal pick-up Brno free; cash on delivery +45 CZK | G3: Not offered: checkout step 2 offers only "Česká republika" as billing/delivery country (checked 2026-09-30). No Austrian rate published. | H3: Shipping prices shown excl. VAT (PPL 275 CZK = 332.75 CZK incl. VAT in checkout) | I3: No general free-shipping threshold published; some individual products (e.g. Liebherr appliances) flagged "Doprava ZDARMA" | J3: 500 CZK excl. VAT (cart: "Minimální cena objednávky je 500 Kč bez DPH") | K3: https://eshop.gastronovotny.cz/obchodni-podminky/ ; checkout https://eshop.gastronovotny.cz/objednavka/krok-1/ | L3: =COUNTIFS(Prices!$C$2:$C$600,A3,Prices!$G$2:$G$600,"<>") | M3: =COUNTIFS(Prices!$C$2:$C$600,A3,Prices!$G$2:$G$600,"<>",Prices!$N$2:$N$600,"EXACT")+COUNTIFS(Prices!$C$2:$C$600,A3,Prices!$G$2:$G$600,"<>",Prices!$N$2:$N$600,"CLOSE") | N3: =IF(L3>=6,"yes","no") | O3: GASTRO NOVOTNÝ, družstvo, Brno. Prices public without login. Many items show availability "Na dotaz" (availability on request) while the price is displayed - recorded as listed prices; noted per item. No squeeze bottle near 1,000 ml, no triple-tip bottle, no pump dispenser, no 300 x 200 board, no dough-box lid, no thermo tray found.
A4: Gastrozone | B4: https://www.gastrozone.cz/ | C4: local | D4: B2C + B2B (gastro and household range; published T&C are written for consumers and state they do not apply to business buyers) | E4: Main price incl. 21% VAT; "bez DPH" (excl. VAT) shown below on product pages | F4: Address delivery (DPD/GLS/PPL, carrier chosen by shop) 95 CZK; pick-up points 49-79 CZK (GLS ParcelShop 49, Balíkovna 59, Zásilkovna 65, PPL Smart 69, DPD Pickup 79); cash on delivery +35 CZK approx.; pick-up Tábor warehouse free. Bulky goods: special transport agreed individually. | G4: No published rate: "Doprava do zahraničí" - price set individually from carriers' tariffs and quoted on request before order confirmation; invoiced under destination-country VAT rules. Quote required. | H4: Shipping prices shown incl. VAT ("s DPH") | I4: All CZ delivery and pick-up options free for orders over 3,000 CZK incl. VAT (CZ only) | J4: Not stated | K4: https://www.gastrozone.cz/informace/doprava-a-platba/ ; https://www.gastrozone.cz/informace/obchodni-podminky/ | L4: =COUNTIFS(Prices!$C$2:$C$600,A4,Prices!$G$2:$G$600,"<>") | M4: =COUNTIFS(Prices!$C$2:$C$600,A4,Prices!$G$2:$G$600,"<>",Prices!$N$2:$N$600,"EXACT")+COUNTIFS(Prices!$C$2:$C$600,A4,Prices!$G$2:$G$600,"<>",Prices!$N$2:$N$600,"CLOSE") | N4: =IF(L4>=6,"yes","no") | O4: GASTROZONE, spol. s r.o., Tábor. Broad multi-brand range (Araven, APS, Pujadas, Cambro, Hendi, Schneider, Contacto). Prices public without login. Several chosen items are "Na objednávku (3-5 týdnů)" (to order); noted per item.
A5: Gastromania | B5: https://www.gastromania.cz/ | C5: local | D5: B2B + B2C (HORECA equipment "velkoobchod"; consumer T&C; separate B2B reseller programme) | E5: Both shown: "bez DPH" (excl.) and "s DPH" (incl. 21% VAT); prices injected by JavaScript (read with a rendering browser) | F5: PPL: 109 CZK with bank transfer/online payment, 169 CZK cash on delivery (parcels up to 31.5 kg, max 60x60x120 cm); oversize, >31.5 kg or pallet shipments priced individually at order confirmation | G5: Not published: T&C state that published delivery costs apply only to delivery within the Czech Republic; no Austrian rate or foreign-delivery terms found (quote would be needed). | H5: Shipping VAT treatment not stated explicitly for the 109/169 CZK fees (free-shipping threshold is stated incl. VAT) | I5: Over 7,000 CZK incl. VAT ("Při nákupu nad 7000 Kč s DPH je doprava zdarma") | J5: Not stated (20% deposit required for orders over 10,000 CZK incl. VAT and made-to-order goods) | K5: https://www.gastromania.cz/zpusoby-dopravy.html ; https://www.gastromania.cz/obchodni-podminky.html | L5: =COUNTIFS(Prices!$C$2:$C$600,A5,Prices!$G$2:$G$600,"<>") | M5: =COUNTIFS(Prices!$C$2:$C$600,A5,Prices!$G$2:$G$600,"<>",Prices!$N$2:$N$600,"EXACT")+COUNTIFS(Prices!$C$2:$C$600,A5,Prices!$G$2:$G$600,"<>",Prices!$N$2:$N$600,"CLOSE") | N5: =IF(L5>=6,"yes","no") | O5: Ostrava-area HORECA shop with CZ/SK storefronts. Multi-brand (Hendi, Contacto, Stalgast, APS, Redfox, Cambro, Yato) and also lists TOMGAST-branded items at identical prices to tomgast.cz. Many items show a crossed-out base price with a current discounted price; the current price for 1 pc is recorded and discounts noted. Where several variants match equally, the lowest current price was taken.
A6: GGM Gastro (CZ storefront) | B6: https://www.ggmgastro.com/cs-cz-czk/ | C6: pan-EU | D6: B2B only (site footer: offers aimed exclusively at commercial customers per §14 BGB, not consumers) | E6: Excl. VAT (net CZK) shown as main price; gross shown "vč. 19% DPH" - the CZ storefront applies German 19% VAT, not Czech 21% | F6: Product pages show "Doprava zdarma**" and footnote "Všechny ceny plus DPH 19 %, včetně dodávky" (prices include delivery); site banner "Doprava zdarma po celé Evropě na všechny objednávky". ** = mainland only; island surcharge. | G6: No specific Austrian rate on the CZ storefront; site banner claims free delivery across Europe on all orders, but the shipping-cost page (English text) says its listed rates (free from 30 EUR net; insured 9.90 EUR, lifting platform 19.90/29.90 EUR, express from 49.90 EUR) apply to the German mainland only and other European countries must request a quote. Austrian customers are normally served via the de-at-eur storefront. | H6: Shipping stated as included in prices (net); where charged, rates on shipping-cost page are in EUR net | I6: Free shipping claimed on all orders (Europe-wide banner); shipping-cost page: free from 30 EUR net purchase value (German mainland) | J6: Not stated (free-shipping reference value 30 EUR net) | K6: https://www.ggmgastro.com/cs-cz-czk/shipping-cost ; https://www.ggmgastro.com/cs-cz-czk/terms | L6: =COUNTIFS(Prices!$C$2:$C$600,A6,Prices!$G$2:$G$600,"<>") | M6: =COUNTIFS(Prices!$C$2:$C$600,A6,Prices!$G$2:$G$600,"<>",Prices!$N$2:$N$600,"EXACT")+COUNTIFS(Prices!$C$2:$C$600,A6,Prices!$G$2:$G$600,"<>",Prices!$N$2:$N$600,"CLOSE") | N6: =IF(L6>=6,"yes","no") | O6: GGM Gastro International GmbH (Germany), Czech-language CZK storefront. Site search and pages are JavaScript-rendered and block headless browsers; products were located via the public product sitemap and read in a full (non-headless) browser. Many products are sold in multi-packs (price per pack; per-piece net computed). Some pages show odd bulk banners (e.g. "30 929,19 Kč Sleva-10%") not used. No 300 x 200 board, no triple-tip bottle (only a 3-hole membrane accessory FFO-055), no separate 600x400 dough-box lid and no thermo tray found.
A7: MAKRO Czechia | B7: https://www.makro.cz/ | C7: local | D7: B2B (cash & carry wholesaler; makro customer card / registration) | E7: Hidden: product listings on sortiment.makro.cz show "Pro zobrazení cen se prosím přihlaste" (log in to see prices) | F7: "makro distribuce" delivery service (m-objednávka) for registered customers; only requirement stated is a minimum order value (amount not published publicly). Otherwise in-store purchase ("Nakoupíte v obchodě"). | G7: Not offered / not published | H7: Not published | I7: Not published | J7: Minimum order value required for makro distribuce - amount not shown publicly | K7: https://www.makro.cz/makro-distribuce ; https://sortiment.makro.cz/shop/search?q=gastron%C3%A1doba%20polykarbon%C3%A1t | L7: =COUNTIFS(Prices!$C$2:$C$600,A7,Prices!$G$2:$G$600,"<>") | M7: =COUNTIFS(Prices!$C$2:$C$600,A7,Prices!$G$2:$G$600,"<>",Prices!$N$2:$N$600,"EXACT")+COUNTIFS(Prices!$C$2:$C$600,A7,Prices!$G$2:$G$600,"<>",Prices!$N$2:$N$600,"CLOSE") | N7: no | O7: Login-only prices - NOT COUNTED. Relevant items exist in the catalogue (e.g. METRO PROFESSIONAL polycarbonate GN 1/1 and 1/2 150 mm containers, APS and Hendi GN containers) but no price is publicly readable. www.makro.cz returns HTTP 403 to plain scripts; readable in a browser.
A8: A GASTRO | B8: https://agastro.cz/ | C8: local | D8: Unknown (HORECA equipment shop per search-engine snippets) | E8: Not readable - site blocked (Cloudflare security check / HTTP 403) | F8: Not readable | G8: Not readable | H8: Not readable | I8: Not readable | J8: Not readable | K8: https://agastro.cz/ | L8: =COUNTIFS(Prices!$C$2:$C$600,A8,Prices!$G$2:$G$600,"<>") | M8: =COUNTIFS(Prices!$C$2:$C$600,A8,Prices!$G$2:$G$600,"<>",Prices!$N$2:$N$600,"EXACT")+COUNTIFS(Prices!$C$2:$C$600,A8,Prices!$G$2:$G$600,"<>",Prices!$N$2:$N$600,"CLOSE") | N8: no | O8: NOT COUNTED - access error. Every URL tried (home, robots.txt, sitemap.xml, www/eshop subdomains, category pages) returns HTTP 403 or a Cloudflare "Provádění bezpečnostního ověření" challenge, both to scripts and to a full browser; the web-fetch tool also gets 403. Search-engine results show category pages such as /gastronadoby-vacbox/, /gastronadoby-zmrlinove/ and /detail/21689/, but no price could be verified, so none recorded. Needs a manual check in a normal browser.

Sheet Prices
A1: Basket item no. | B1: Basket item | C1: Competitor | D1: Product name | E1: Brand | F1: Product URL | G1: Listed price | H1: Currency | I1: Incl./excl. VAT | J1: VAT rate used | K1: Pack size (pcs) | L1: Price basis (per pack / per piece) | M1: Net price per piece CZK | N1: Match quality | O1: Notes | P1: Date checked | Q1: Competitor counted? | R1: Used in Summary?
A2: 1 | B2: GN 1/1 polycarbonate container, 65 mm deep | C2: GGM Gastro (CZ storefront) | D2: (6 ks) Gastronádoba GN GN 1/1 - polykarbonát - čirá - Výška: 65 mm | E2: GGM | F2: https://www.ggmgastro.com/cs-cz-czk/6-ks-gastronadoba-gn-gn-1-1-polykarbonat-cira-vyska-65-mm-gpcp1165 | G2: 1143.69 | H2: CZK | I2: excl. | J2: 0.19 | K2: 6 | L2: per pack | M2: =IF(OR(G2="",J2="",K2=""),"",ROUND(IF(I2="incl.",G2/(1+J2),G2)/IF(L2="per pack",K2,1),2)) | N2: EXACT | O2: Net CZK price as displayed; page footnote: "* čistá cena | hrubá cena vč. 19% DPH" (German VAT 19% used on the CZ storefront). SKU GPCP1165, pack of 6; gross 1,360.99 CZK; delivery 5-6 weeks. | P2: 2026-09-30 | Q2: =IFERROR(INDEX(Competitors!$N$2:$N$50,MATCH(C2,Competitors!$A$2:$A$50,0)),"no") | R2: =IF(AND(Q2="yes",OR(N2="EXACT",N2="CLOSE"),ISNUMBER(M2)),"yes","no")
A3: 1 | B3: GN 1/1 polycarbonate container, 65 mm deep | C3: Gastro Novotný | D3: Gastronádoba PC 1/1 100 | F3: https://eshop.gastronovotny.cz/gastronadoba-pc-1-1-100--0835126/ | G3: 289 | H3: CZK | I3: excl. | J3: 0.21 | K3: 1 | L3: per piece | M3: =IF(OR(G3="",J3="",K3=""),"",ROUND(IF(I3="incl.",G3/(1+J3),G3)/IF(L3="per pack",K3,1),2)) | N3: APPROX | O3: Polycarbonate GN 1/1 but 100 mm deep (no 65 mm PC listed; PC range 1/1 = 100 and 200 mm only). 349.69 CZK incl. VAT. Availability "Na dotaz". | P3: 2026-09-30 | Q3: =IFERROR(INDEX(Competitors!$N$2:$N$50,MATCH(C3,Competitors!$A$2:$A$50,0)),"no") | R3: =IF(AND(Q3="yes",OR(N3="EXACT",N3="CLOSE"),ISNUMBER(M3)),"yes","no")
A4: 1 | B4: GN 1/1 polycarbonate container, 65 mm deep | C4: Gastromania | D4: Gastronádoba z polykarbonátu GN 1/1 65 mm | HENDI, Profi Line | E4: Hendi | F4: https://www.gastromania.cz/gastronadoby-polykarbonatove/gastronadoba-z-polykarbonatu-gn-1-1-65-mm-hendi-profi-line | G4: 262 | H4: CZK | I4: excl. | J4: 0.21 | K4: 1 | L4: per piece | M4: =IF(OR(G4="",J4="",K4=""),"",ROUND(IF(I4="incl.",G4/(1+J4),G4)/IF(L4="per pack",K4,1),2)) | N4: EXACT | O4: PC, 9 l. Current price 262 CZK excl. / 317 incl. is an "Outlet" discount from 368 excl. / 445 incl. (30-day low shown 445). Regular-priced alternative: Stalgast Bufet PC GN 1/1 65 mm 286 excl. / 346 incl. | P4: 2026-09-30 | Q4: =IFERROR(INDEX(Competitors!$N$2:$N$50,MATCH(C4,Competitors!$A$2:$A$50,0)),"no") | R4: =IF(AND(Q4="yes",OR(N4="EXACT",N4="CLOSE"),ISNUMBER(M4)),"yes","no")
A5: 1 | B5: GN 1/1 polycarbonate container, 65 mm deep | C5: Gastrozone | D5: ARAVEN Gastronádoba GN 1/1, polykarbonát, hloubka: 65 mm, objem: 8,6 L | E5: Araven | F5: https://www.gastrozone.cz/araven-gn-box-1-1-polykarbonat-hloubka-65-mm-objem-8-6-l.html | G5: 502 | H5: CZK | I5: incl. | J5: 0.21 | K5: 1 | L5: per piece | M5: =IF(OR(G5="",J5="",K5=""),"",ROUND(IF(I5="incl.",G5/(1+J5),G5)/IF(L5="per pack",K5,1),2)) | N5: EXACT | O5: 414.88 CZK bez DPH; availability "Na objednávku (3-5 týdnů)". In-stock alternative: ARAVEN PC GN 1/1 65 mm with integrated label 601 CZK. | P5: 2026-09-30 | Q5: =IFERROR(INDEX(Competitors!$N$2:$N$50,MATCH(C5,Competitors!$A$2:$A$50,0)),"no") | R5: =IF(AND(Q5="yes",OR(N5="EXACT",N5="CLOSE"),ISNUMBER(M5)),"yes","no")
A6: 1 | B6: GN 1/1 polycarbonate container, 65 mm deep | C6: TOMGAST | D6: Gastronádoba polykarbonátová GN 1/1 65 mm | E6: Cambro | F6: https://www.tomgast.cz/gastronadoba-polykarbonatova-gn-1-1-65-mm/ | G6: 401 | H6: CZK | I6: incl. | J6: 0.21 | K6: 1 | L6: per piece | M6: =IF(OR(G6="",J6="",K6=""),"",ROUND(IF(I6="incl.",G6/(1+J6),G6)/IF(L6="per pack",K6,1),2)) | N6: EXACT | O6: Code R-M211065; site shows 331 CZK bez DPH; in stock | P6: 2026-09-30 | Q6: =IFERROR(INDEX(Competitors!$N$2:$N$50,MATCH(C6,Competitors!$A$2:$A$50,0)),"no") | R6: =IF(AND(Q6="yes",OR(N6="EXACT",N6="CLOSE"),ISNUMBER(M6)),"yes","no")
A7: 2 | B7: GN 1/2 polycarbonate container, 150 mm deep | C7: GGM Gastro (CZ storefront) | D7: (6 ks) CAMBRO Camview – kopolymerové nádoby GN 1/2 – průhledné – výška: 150 mm – bez BPA | E7: Cambro | F7: https://www.ggmgastro.com/cs-cz-czk/6-ks-cambro-camview-r-kopolymerove-nadoby-gn-1-2-pruhledne-vyska-150-mm-bez-bpa-26cv135 | G7: 1460.1 | H7: CZK | I7: excl. | J7: 0.19 | K7: 6 | L7: per pack | M7: =IF(OR(G7="",J7="",K7=""),"",ROUND(IF(I7="incl.",G7/(1+J7),G7)/IF(L7="per pack",K7,1),2)) | N7: CLOSE | O7: Net CZK price as displayed; page footnote: "* čistá cena | hrubá cena vč. 19% DPH" (German VAT 19% used on the CZ storefront). SKU 26CV135, pack of 6; copolymer (Camview), not polycarbonate - no clear PC GN 1/2 150 mm listed. Gross 1,737.52 CZK; in stock 3-5 days. | P7: 2026-09-30 | Q7: =IFERROR(INDEX(Competitors!$N$2:$N$50,MATCH(C7,Competitors!$A$2:$A$50,0)),"no") | R7: =IF(AND(Q7="yes",OR(N7="EXACT",N7="CLOSE"),ISNUMBER(M7)),"yes","no")
A8: 2 | B8: GN 1/2 polycarbonate container, 150 mm deep | C8: Gastro Novotný | D8: Gastronádoba PC 1/2 150 | F8: https://eshop.gastronovotny.cz/gastronadoba-pc-1-2-150--0835123/ | G8: 270 | H8: CZK | I8: excl. | J8: 0.21 | K8: 1 | L8: per piece | M8: =IF(OR(G8="",J8="",K8=""),"",ROUND(IF(I8="incl.",G8/(1+J8),G8)/IF(L8="per pack",K8,1),2)) | N8: EXACT | O8: Code 0835123; 326.70 CZK incl. VAT; availability "Na dotaz" | P8: 2026-09-30 | Q8: =IFERROR(INDEX(Competitors!$N$2:$N$50,MATCH(C8,Competitors!$A$2:$A$50,0)),"no") | R8: =IF(AND(Q8="yes",OR(N8="EXACT",N8="CLOSE"),ISNUMBER(M8)),"yes","no")
A9: 2 | B9: GN 1/2 polycarbonate container, 150 mm deep | C9: Gastromania | D9: Gastronádoba GN 1/2 polykarbonátová 150 mm | REDFOX, GNP-1/2-150 | E9: Redfox | F9: https://www.gastromania.cz/kuchynsky-inventar/gastronadoba-gn-1-2-polykarbonatova-150-mm-redfox-gnp-1-2-150 | G9: 239 | H9: CZK | I9: excl. | J9: 0.21 | K9: 1 | L9: per piece | M9: =IF(OR(G9="",J9="",K9=""),"",ROUND(IF(I9="incl.",G9/(1+J9),G9)/IF(L9="per pack",K9,1),2)) | N9: EXACT | O9: PC, 9.2 l; 289 CZK incl.; availability 5 days. (APS 82116 at 132 excl. is named polycarbonate but its parameters say polypropylene - conflicting, not used.) | P9: 2026-09-30 | Q9: =IFERROR(INDEX(Competitors!$N$2:$N$50,MATCH(C9,Competitors!$A$2:$A$50,0)),"no") | R9: =IF(AND(Q9="yes",OR(N9="EXACT",N9="CLOSE"),ISNUMBER(M9)),"yes","no")
A10: 2 | B10: GN 1/2 polycarbonate container, 150 mm deep | C10: Gastrozone | D10: ARAVEN Gastronádoba GN 1/2, polykarbonát, Hloubka: 150 mm, Objem: 8 L | E10: Araven | F10: https://www.gastrozone.cz/araven-gn-nadoba-1-2-polykarbonat-hloubka-150-mm-objem-8-l.html | G10: 464 | H10: CZK | I10: incl. | J10: 0.21 | K10: 1 | L10: per piece | M10: =IF(OR(G10="",J10="",K10=""),"",ROUND(IF(I10="incl.",G10/(1+J10),G10)/IF(L10="per pack",K10,1),2)) | N10: EXACT | O10: 383.47 CZK bez DPH; to order 3-5 weeks. In-stock alternative: Pujadas GN 1/2 PC 150 mm 630 CZK. | P10: 2026-09-30 | Q10: =IFERROR(INDEX(Competitors!$N$2:$N$50,MATCH(C10,Competitors!$A$2:$A$50,0)),"no") | R10: =IF(AND(Q10="yes",OR(N10="EXACT",N10="CLOSE"),ISNUMBER(M10)),"yes","no")
A11: 2 | B11: GN 1/2 polycarbonate container, 150 mm deep | C11: TOMGAST | D11: Gastronádoba polykarbonátová GN 1/2 150 mm | E11: Cambro | F11: https://www.tomgast.cz/gastronadoba-polykarbonatova-gn-1-2-150-mm-2/ | G11: 356 | H11: CZK | I11: incl. | J11: 0.21 | K11: 1 | L11: per piece | M11: =IF(OR(G11="",J11="",K11=""),"",ROUND(IF(I11="incl.",G11/(1+J11),G11)/IF(L11="per pack",K11,1),2)) | N11: EXACT | O11: Code R-M212150; 294 CZK bez DPH; in stock | P11: 2026-09-30 | Q11: =IFERROR(INDEX(Competitors!$N$2:$N$50,MATCH(C11,Competitors!$A$2:$A$50,0)),"no") | R11: =IF(AND(Q11="yes",OR(N11="EXACT",N11="CLOSE"),ISNUMBER(M11)),"yes","no")
A12: 3 | B12: GN 1/3 polypropylene container, 100 mm deep | C12: GGM Gastro (CZ storefront) | D12: (12 ks) Gastronádoba polypropylen GN 1/3 - Mléčná - Výška: 100 mm | E12: GGM | F12: https://www.ggmgastro.com/cs-cz-czk/12-ks-gastronadoba-polypropylen-gn-1-3-mlecna-vyska-100-mm-gpp13100 | G12: 973.32 | H12: CZK | I12: excl. | J12: 0.19 | K12: 12 | L12: per pack | M12: =IF(OR(G12="",J12="",K12=""),"",ROUND(IF(I12="incl.",G12/(1+J12),G12)/IF(L12="per pack",K12,1),2)) | N12: EXACT | O12: Net CZK price as displayed; page footnote: "* čistá cena | hrubá cena vč. 19% DPH" (German VAT 19% used on the CZ storefront). SKU GPP13100, pack of 12 (3.6 l); gross 1,158.25 CZK. A 6-pack SKU GPP13100#6 is listed at 4,040.03 CZK net (anomalous, ~8x the per-piece price) - not used. | P12: 2026-09-30 | Q12: =IFERROR(INDEX(Competitors!$N$2:$N$50,MATCH(C12,Competitors!$A$2:$A$50,0)),"no") | R12: =IF(AND(Q12="yes",OR(N12="EXACT",N12="CLOSE"),ISNUMBER(M12)),"yes","no")
A13: 3 | B13: GN 1/3 polypropylene container, 100 mm deep | C13: Gastro Novotný | D13: Gastronádoba 1/3 100 polypropylen | F13: https://eshop.gastronovotny.cz/gastronadoba-1-3-100-polypropylen-/ | G13: 100 | H13: CZK | I13: excl. | J13: 0.21 | K13: 1 | L13: per piece | M13: =IF(OR(G13="",J13="",K13=""),"",ROUND(IF(I13="incl.",G13/(1+J13),G13)/IF(L13="per pack",K13,1),2)) | N13: EXACT | O13: Code 1814707-10; 325x180x100 mm, 3.6 l; 121 CZK incl. VAT; in stock | P13: 2026-09-30 | Q13: =IFERROR(INDEX(Competitors!$N$2:$N$50,MATCH(C13,Competitors!$A$2:$A$50,0)),"no") | R13: =IF(AND(Q13="yes",OR(N13="EXACT",N13="CLOSE"),ISNUMBER(M13)),"yes","no")
A14: 3 | B14: GN 1/3 polypropylene container, 100 mm deep | C14: Gastromania | D14: Gastronádoba GN 1/3 - 100 polypropylenová | REDFOX, GNPP 1/3-100 | E14: Redfox | F14: https://www.gastromania.cz/gastronadoby-polypropylenove/gastronadoba-gn-1-3-100-polypropylenova-redfox-gnpp-1-3-100 | G14: 99 | H14: CZK | I14: excl. | J14: 0.21 | K14: 1 | L14: per piece | M14: =IF(OR(G14="",J14="",K14=""),"",ROUND(IF(I14="incl.",G14/(1+J14),G14)/IF(L14="per pack",K14,1),2)) | N14: EXACT | O14: PP, 4 l; 120 CZK incl.; availability 5 days; new item. | P14: 2026-09-30 | Q14: =IFERROR(INDEX(Competitors!$N$2:$N$50,MATCH(C14,Competitors!$A$2:$A$50,0)),"no") | R14: =IF(AND(Q14="yes",OR(N14="EXACT",N14="CLOSE"),ISNUMBER(M14)),"yes","no")
A15: 3 | B15: GN 1/3 polypropylene container, 100 mm deep | C15: Gastrozone | D15: APS GN-nádoba polypropylen, GN 1/3, objem: 3,60 litru, hloubka: 100 mm | E15: APS | F15: https://www.gastrozone.cz/aps-gn-nadoba-z-polypropylenu-gn-1-3-objem-3-60-litru-hloubka-100-mm.html | G15: 180 | H15: CZK | I15: incl. | J15: 0.21 | K15: 1 | L15: per piece | M15: =IF(OR(G15="",J15="",K15=""),"",ROUND(IF(I15="incl.",G15/(1+J15),G15)/IF(L15="per pack",K15,1),2)) | N15: EXACT | O15: 148.76 CZK bez DPH; to order 3-5 weeks. In-stock alternative: Pujadas GN 1/3 PP 100 mm 196 CZK. | P15: 2026-09-30 | Q15: =IFERROR(INDEX(Competitors!$N$2:$N$50,MATCH(C15,Competitors!$A$2:$A$50,0)),"no") | R15: =IF(AND(Q15="yes",OR(N15="EXACT",N15="CLOSE"),ISNUMBER(M15)),"yes","no")
A16: 3 | B16: GN 1/3 polypropylene container, 100 mm deep | C16: TOMGAST | D16: Gastronádoba polypropylenová GN 1/3 100 mm | E16: Cambro | F16: https://www.tomgast.cz/gastronadoba-polypropylenova-gn-1-3-100-mm-2/ | G16: 143 | H16: CZK | I16: incl. | J16: 0.21 | K16: 1 | L16: per piece | M16: =IF(OR(G16="",J16="",K16=""),"",ROUND(IF(I16="incl.",G16/(1+J16),G16)/IF(L16="per pack",K16,1),2)) | N16: EXACT | O16: Code R-MP13100; 118 CZK bez DPH; in stock | P16: 2026-09-30 | Q16: =IFERROR(INDEX(Competitors!$N$2:$N$50,MATCH(C16,Competitors!$A$2:$A$50,0)),"no") | R16: =IF(AND(Q16="yes",OR(N16="EXACT",N16="CLOSE"),ISNUMBER(M16)),"yes","no")
A17: 4 | B17: GN 1/1 polypropylene lid | C17: GGM Gastro (CZ storefront) | D17: (6 kusů) CAMBRO SafeTrak - Polypropylenové víko GN 1/1 - červené | E17: Cambro | F17: https://www.ggmgastro.com/cs-cz-czk/6-kusu-cambro-safetrak-polypropylenove-viko-gn-1-1-cervene-10ppcwsc544 | G17: 802.94 | H17: CZK | I17: excl. | J17: 0.19 | K17: 6 | L17: per pack | M17: =IF(OR(G17="",J17="",K17=""),"",ROUND(IF(I17="incl.",G17/(1+J17),G17)/IF(L17="per pack",K17,1),2)) | N17: EXACT | O17: Net CZK price as displayed; page footnote: "* čistá cena | hrubá cena vč. 19% DPH" (German VAT 19% used on the CZ storefront). SKU 10PPCWSC544, PP, pack of 6; gross 955.50 CZK; in stock. GGM own-brand PP lid GPPL11-12 (717.76 CZK) has conflicting pack size (title 12 pcs, specs 6 pcs) and is available only from 19.10.2026 - not used. | P17: 2026-09-30 | Q17: =IFERROR(INDEX(Competitors!$N$2:$N$50,MATCH(C17,Competitors!$A$2:$A$50,0)),"no") | R17: =IF(AND(Q17="yes",OR(N17="EXACT",N17="CLOSE"),ISNUMBER(M17)),"yes","no")
A18: 4 | B18: GN 1/1 polypropylene lid | C18: Gastro Novotný | D18: Víko 1/1 polypropylen barevné | F18: https://eshop.gastronovotny.cz/viko-1-1-polypropylen-barevne--1814722-11/ | G18: 105 | H18: CZK | I18: excl. | J18: 0.21 | K18: 1 | L18: per piece | M18: =IF(OR(G18="",J18="",K18=""),"",ROUND(IF(I18="incl.",G18/(1+J18),G18)/IF(L18="per pack",K18,1),2)) | N18: EXACT | O18: Code 1814722-11; PP lid 530x325 mm, coloured; 127.05 CZK incl. VAT. Alternative: Víko 1/1 polypropylen PIAZZA 119.01 CZK excl. | P18: 2026-09-30 | Q18: =IFERROR(INDEX(Competitors!$N$2:$N$50,MATCH(C18,Competitors!$A$2:$A$50,0)),"no") | R18: =IF(AND(Q18="yes",OR(N18="EXACT",N18="CLOSE"),ISNUMBER(M18)),"yes","no")
A19: 4 | B19: GN 1/1 polypropylene lid | C19: Gastromania | D19: Víko na nádobu GN 1/1 | APS, 82101 | E19: APS | F19: https://www.gastromania.cz/vika-gn-polypropylenove/viko-na-nadobu-gn-1-1-aps-82101 | G19: 97 | H19: CZK | I19: excl. | J19: 0.21 | K19: 1 | L19: per piece | M19: =IF(OR(G19="",J19="",K19=""),"",ROUND(IF(I19="incl.",G19/(1+J19),G19)/IF(L19="per pack",K19,1),2)) | N19: EXACT | O19: PP lid 530x325; 117 CZK incl. Discounted from 190 excl. / 230 incl. (30-day low 207); availability 21 days. Regular-priced alternative: Redfox VPP 1/1 99 excl. / 120 incl. | P19: 2026-09-30 | Q19: =IFERROR(INDEX(Competitors!$N$2:$N$50,MATCH(C19,Competitors!$A$2:$A$50,0)),"no") | R19: =IF(AND(Q19="yes",OR(N19="EXACT",N19="CLOSE"),ISNUMBER(M19)),"yes","no")
A20: 4 | B20: GN 1/1 polypropylene lid | C20: Gastrozone | D20: víko na gastronádobu GN 1/1 polypropylen Pujadas | E20: Vollrath Pujadas | F20: https://www.gastrozone.cz/viko-na-gastronadobu-gn-1-1-polypropylen-pujadas.html | G20: 350 | H20: CZK | I20: incl. | J20: 0.21 | K20: 1 | L20: per piece | M20: =IF(OR(G20="",J20="",K20=""),"",ROUND(IF(I20="incl.",G20/(1+J20),G20)/IF(L20="per pack",K20,1),2)) | N20: EXACT | O20: 289.26 CZK bez DPH; in stock | P20: 2026-09-30 | Q20: =IFERROR(INDEX(Competitors!$N$2:$N$50,MATCH(C20,Competitors!$A$2:$A$50,0)),"no") | R20: =IF(AND(Q20="yes",OR(N20="EXACT",N20="CLOSE"),ISNUMBER(M20)),"yes","no")
A21: 4 | B21: GN 1/1 polypropylene lid | C21: TOMGAST | D21: Těsnící víko pro gastronádobu GN 1/1 | E21: Cambro | F21: https://www.tomgast.cz/tesnici-viko-pro-gastronadobu-gn-1-1/ | G21: 204 | H21: CZK | I21: incl. | J21: 0.21 | K21: 1 | L21: per piece | M21: =IF(OR(G21="",J21="",K21=""),"",ROUND(IF(I21="incl.",G21/(1+J21),G21)/IF(L21="per pack",K21,1),2)) | N21: CLOSE | O21: Code R-MP11001 (seal cover for PC and PP containers). Product page states material "polykarbonát", not polypropylene - material differs/unclear. Page text "Cena uvedena za 1 kus/6 ks v balení": price read as per piece. 169 CZK bez DPH. No PP GN 1/1 lid found. | P21: 2026-09-30 | Q21: =IFERROR(INDEX(Competitors!$N$2:$N$50,MATCH(C21,Competitors!$A$2:$A$50,0)),"no") | R21: =IF(AND(Q21="yes",OR(N21="EXACT",N21="CLOSE"),ISNUMBER(M21)),"yes","no")
A22: 5 | B22: Squeeze bottle 500 ml, polypropylene, single tip | C22: GGM Gastro (CZ storefront) | D22: (12 ks) Stlačovací lahev na omáčky se středovou membránou - 473 ml | E22: GGM | F22: https://www.ggmgastro.com/cs-cz-czk/12-ks-stlacovaci-lahev-na-omacky-se-stredovou-membranou-473-ml-ffo-002 | G22: 1241.05 | H22: CZK | I22: excl. | J22: 0.19 | K22: 12 | L22: per pack | M22: =IF(OR(G22="",J22="",K22=""),"",ROUND(IF(I22="incl.",G22/(1+J22),G22)/IF(L22="per pack",K22,1),2)) | N22: CLOSE | O22: Net CZK price as displayed; page footnote: "* čistá cena | hrubá cena vč. 19% DPH" (German VAT 19% used on the CZ storefront). SKU FFO-002, 473 ml, pack of 12, valve (membrane) nozzle; material NOT stated (flagged). Gross 1,476.85 CZK. 3-pack version with screw cap FFO-007: 486.54 CZK. | P22: 2026-09-30 | Q22: =IFERROR(INDEX(Competitors!$N$2:$N$50,MATCH(C22,Competitors!$A$2:$A$50,0)),"no") | R22: =IF(AND(Q22="yes",OR(N22="EXACT",N22="CLOSE"),ISNUMBER(M22)),"yes","no")
A23: 5 | B23: Squeeze bottle 500 ml, polypropylene, single tip | C23: Gastro Novotný | D23: Láhev plastová dávkovací čirá 354ml | F23: https://eshop.gastronovotny.cz/lahev-plastova-davkovaci-cira-354ml--255046026/ | G23: 29 | H23: CZK | I23: excl. | J23: 0.21 | K23: 1 | L23: per piece | M23: =IF(OR(G23="",J23="",K23=""),"",ROUND(IF(I23="incl.",G23/(1+J23),G23)/IF(L23="per pack",K23,1),2)) | N23: APPROX | O23: 354 ml instead of 500 ml; plastic type not stated. 35.09 CZK incl. VAT. Red variant same price. Largest squeeze bottle is a 708 ml "zdobící" (decorating) bottle, 39 CZK excl. | P23: 2026-09-30 | Q23: =IFERROR(INDEX(Competitors!$N$2:$N$50,MATCH(C23,Competitors!$A$2:$A$50,0)),"no") | R23: =IF(AND(Q23="yes",OR(N23="EXACT",N23="CLOSE"),ISNUMBER(M23)),"yes","no")
A24: 5 | B24: Squeeze bottle 500 ml, polypropylene, single tip | C24: Gastromania | D24: Láhev na omáčky, 0,475 ml | NEUMARKER, FIFO | E24: Neumarker | F24: https://www.gastromania.cz/davkovace-omacek/lahev-na-omacky-0-475-ml-neumarker-fifo | G24: 352 | H24: CZK | I24: excl. | J24: 0.21 | K24: 1 | L24: per piece | M24: =IF(OR(G24="",J24="",K24=""),"",ROUND(IF(I24="incl.",G24/(1+J24),G24)/IF(L24="per pack",K24,1),2)) | N24: CLOSE | O24: 475 ml FIFO squeeze bottle (refilled from the bottom); material NOT stated (flagged). 425 CZK incl.; discounted from 370 excl.; availability 40 days. Standard PE bottles only in 350/400/700 ml (e.g. Tomgast 400 ml PE 48 excl.). | P24: 2026-09-30 | Q24: =IFERROR(INDEX(Competitors!$N$2:$N$50,MATCH(C24,Competitors!$A$2:$A$50,0)),"no") | R24: =IF(AND(Q24="yes",OR(N24="EXACT",N24="CLOSE"),ISNUMBER(M24)),"yes","no")
A25: 5 | B25: Squeeze bottle 500 ml, polypropylene, single tip | C25: Gastrozone | D25: Dávkovací mačkací láhev Schneider 500 ml | E25: Schneider | F25: https://www.gastrozone.cz/lahev-mackaci-s-uzaviranim-0-5-l-odolna-od-40c-do-95c-transparentni-pro-styk-s-potravinama-schneider-10134.html | G25: 313 | H25: CZK | I25: incl. | J25: 0.21 | K25: 1 | L25: per piece | M25: =IF(OR(G25="",J25="",K25=""),"",ROUND(IF(I25="incl.",G25/(1+J25),G25)/IF(L25="per pack",K25,1),2)) | N25: CLOSE | O25: 500 ml, single nozzle with closure; material polyethylene (not PP). 259 CZK bez DPH. Cheaper non-500 ml options exist (Hendi 0.35/0.7 l from 67 CZK). | P25: 2026-09-30 | Q25: =IFERROR(INDEX(Competitors!$N$2:$N$50,MATCH(C25,Competitors!$A$2:$A$50,0)),"no") | R25: =IF(AND(Q25="yes",OR(N25="EXACT",N25="CLOSE"),ISNUMBER(M25)),"yes","no")
A26: 5 | B26: Squeeze bottle 500 ml, polypropylene, single tip | C26: TOMGAST | D26: Dávkovač na omáčky 400 ml | E26: Laco | F26: https://www.tomgast.cz/davkovac-na-omacky-400-ml/ | G26: 58 | H26: CZK | I26: incl. | J26: 0.21 | K26: 1 | L26: per piece | M26: =IF(OR(G26="",J26="",K26=""),"",ROUND(IF(I26="incl.",G26/(1+J26),G26)/IF(L26="per pack",K26,1),2)) | N26: APPROX | O26: 400 ml instead of 500 ml AND polyethylene instead of PP. 48 CZK bez DPH. No 500 ml bottle listed (sizes 250/360/400/700/720/1025 ml). | P26: 2026-09-30 | Q26: =IFERROR(INDEX(Competitors!$N$2:$N$50,MATCH(C26,Competitors!$A$2:$A$50,0)),"no") | R26: =IF(AND(Q26="yes",OR(N26="EXACT",N26="CLOSE"),ISNUMBER(M26)),"yes","no")
A27: 6 | B27: Squeeze bottle 1000 ml, polypropylene, single tip | C27: GGM Gastro (CZ storefront) | D27: (6 ks) Stlačovací lahev na omáčky se středovou membránou - 946 ml - se šroubovacím uzávěrem a uzavírací čepičkou | E27: GGM | F27: https://www.ggmgastro.com/cs-cz-czk/6-ks-stlacovaci-lahev-na-omacky-se-stredovou-membranou-946-ml-se-sroubovacim-uzaverem-a-uzaviraci-cepickou-ffo-005 | G27: 851.62 | H27: CZK | I27: excl. | J27: 0.19 | K27: 6 | L27: per pack | M27: =IF(OR(G27="",J27="",K27=""),"",ROUND(IF(I27="incl.",G27/(1+J27),G27)/IF(L27="per pack",K27,1),2)) | N27: CLOSE | O27: Net CZK price as displayed; page footnote: "* čistá cena | hrubá cena vč. 19% DPH" (German VAT 19% used on the CZ storefront). SKU FFO-005, 946 ml, pack of 6; material NOT stated (flagged). Gross 1,013.43 CZK. (APS 1,020 ml PE 6-pack 93259#6 shown as not available for the selected delivery country.) | P27: 2026-09-30 | Q27: =IFERROR(INDEX(Competitors!$N$2:$N$50,MATCH(C27,Competitors!$A$2:$A$50,0)),"no") | R27: =IF(AND(Q27="yes",OR(N27="EXACT",N27="CLOSE"),ISNUMBER(M27)),"yes","no")
A28: 6 | B28: Squeeze bottle 1000 ml, polypropylene, single tip | C28: Gastromania | D28: Zásobník na omáčku 1,025 l, bílý | APS, 93259 | E28: APS | F28: https://www.gastromania.cz/davkovace-omacek/zasobnik-na-omacku-1-025-l-bily-aps-93259 | G28: 73 | H28: CZK | I28: excl. | J28: 0.21 | K28: 1 | L28: per piece | M28: =IF(OR(G28="",J28="",K28=""),"",ROUND(IF(I28="incl.",G28/(1+J28),G28)/IF(L28="per pack",K28,1),2)) | N28: CLOSE | O28: 1.025 l squeeze bottle with screw cap; polyethylene, not PP. 88 CZK incl.; discounted from 77 excl.; in stock. | P28: 2026-09-30 | Q28: =IFERROR(INDEX(Competitors!$N$2:$N$50,MATCH(C28,Competitors!$A$2:$A$50,0)),"no") | R28: =IF(AND(Q28="yes",OR(N28="EXACT",N28="CLOSE"),ISNUMBER(M28)),"yes","no")
A29: 6 | B29: Squeeze bottle 1000 ml, polypropylene, single tip | C29: Gastrozone | D29: Dávkovací mačkací láhev Schneider 1000 ml, transparentní | E29: Schneider | F29: https://www.gastrozone.cz/schneider-davkovaci-mackaci-lahev-1000-ml-transparentni.html | G29: 446 | H29: CZK | I29: incl. | J29: 0.21 | K29: 1 | L29: per piece | M29: =IF(OR(G29="",J29="",K29=""),"",ROUND(IF(I29="incl.",G29/(1+J29),G29)/IF(L29="per pack",K29,1),2)) | N29: CLOSE | O29: 1000 ml; material polyethylene (not PP). 369 CZK bez DPH. | P29: 2026-09-30 | Q29: =IFERROR(INDEX(Competitors!$N$2:$N$50,MATCH(C29,Competitors!$A$2:$A$50,0)),"no") | R29: =IF(AND(Q29="yes",OR(N29="EXACT",N29="CLOSE"),ISNUMBER(M29)),"yes","no")
A30: 6 | B30: Squeeze bottle 1000 ml, polypropylene, single tip | C30: TOMGAST | D30: Dávkovač na omáčky 1025 ml, žlutý | E30: TOMGAST | F30: https://www.tomgast.cz/davkovac-na-omacky-1025-ml--zluty/ | G30: 48 | H30: CZK | I30: incl. | J30: 0.21 | K30: 1 | L30: per piece | M30: =IF(OR(G30="",J30="",K30=""),"",ROUND(IF(I30="incl.",G30/(1+J30),G30)/IF(L30="per pack",K30,1),2)) | N30: CLOSE | O30: 1025 ml; material only "plast" (plastic type not stated - flagged); single thin nozzle. 40 CZK bez DPH. Transparent/red variants same price but awaiting stock. | P30: 2026-09-30 | Q30: =IFERROR(INDEX(Competitors!$N$2:$N$50,MATCH(C30,Competitors!$A$2:$A$50,0)),"no") | R30: =IF(AND(Q30="yes",OR(N30="EXACT",N30="CLOSE"),ISNUMBER(M30)),"yes","no")
A31: 7 | B31: Squeeze bottle 500 ml with triple tip | C31: Gastrozone | D31: ARAVEN Mačkací láhev, LDPE, průměr: 80 mm, výška: 253 mm, objem: 0,75 L, 3 trysky | E31: Araven | F31: https://www.gastrozone.cz/araven-lahvicka-na-stlaceni-ldpe-o-80-mm-vyska-253-mm-objem-0-75-l-3-trysky.html | G31: 156 | H31: CZK | I31: incl. | J31: 0.21 | K31: 1 | L31: per piece | M31: =IF(OR(G31="",J31="",K31=""),"",ROUND(IF(I31="incl.",G31/(1+J31),G31)/IF(L31="per pack",K31,1),2)) | N31: APPROX | O31: Triple-tip squeeze bottle but 750 ml (not 500 ml); LDPE. 129 CZK bez DPH. | P31: 2026-09-30 | Q31: =IFERROR(INDEX(Competitors!$N$2:$N$50,MATCH(C31,Competitors!$A$2:$A$50,0)),"no") | R31: =IF(AND(Q31="yes",OR(N31="EXACT",N31="CLOSE"),ISNUMBER(M31)),"yes","no")
A32: 8 | B32: Ketchup/sauce pump dispenser with stand | C32: GGM Gastro (CZ storefront) | D32: Dávkovač omáčky - 2 L - Vč. nerezového podstavce | E32: GGM | F32: https://www.ggmgastro.com/cs-cz-czk/davkovac-omacky-2-l-vc-nerezoveho-podstavce-ssh12 | G32: 997.66 | H32: CZK | I32: excl. | J32: 0.19 | K32: 1 | L32: per piece | M32: =IF(OR(G32="",J32="",K32=""),"",ROUND(IF(I32="incl.",G32/(1+J32),G32)/IF(L32="per pack",K32,1),2)) | N32: EXACT | O32: Net CZK price as displayed; page footnote: "* čistá cena | hrubá cena vč. 19% DPH" (German VAT 19% used on the CZ storefront). SKU SSH12: PP container with portion pump (30 ml adjustable) on stainless-steel stand. Gross 1,187.22 CZK. Stand-less pump dispenser KSP2 2 l: 681.25 CZK. | P32: 2026-09-30 | Q32: =IFERROR(INDEX(Competitors!$N$2:$N$50,MATCH(C32,Competitors!$A$2:$A$50,0)),"no") | R32: =IF(AND(Q32="yes",OR(N32="EXACT",N32="CLOSE"),ISNUMBER(M32)),"yes","no")
A33: 8 | B33: Ketchup/sauce pump dispenser with stand | C33: Gastromania | D33: Dávkovač na omáčky s pumpičkou 2,5 l, červený | HENDI, 203521 | E33: Hendi | F33: https://www.gastromania.cz/davkovace-omacek/davkovac-na-omacky-s-pumpickou-2-5-l-cerveny-hendi-203521 | G33: 636 | H33: CZK | I33: excl. | J33: 0.21 | K33: 1 | L33: per piece | M33: =IF(OR(G33="",J33="",K33=""),"",ROUND(IF(I33="incl.",G33/(1+J33),G33)/IF(L33="per pack",K33,1),2)) | N33: CLOSE | O33: Free-standing pump dispenser: ABS housing, PP inner container and removable pump, 2.5 l, 20 ml dose; separate stand not mentioned. 770 CZK incl.; in stock. | P33: 2026-09-30 | Q33: =IFERROR(INDEX(Competitors!$N$2:$N$50,MATCH(C33,Competitors!$A$2:$A$50,0)),"no") | R33: =IF(AND(Q33="yes",OR(N33="EXACT",N33="CLOSE"),ISNUMBER(M33)),"yes","no")
A34: 8 | B34: Ketchup/sauce pump dispenser with stand | C34: Gastrozone | D34: Dávkovač omáčky Contacto 3 l | E34: Contacto | F34: https://www.gastrozone.cz/contacto-davkovac-omacky-3-l.html | G34: 1446 | H34: CZK | I34: incl. | J34: 0.21 | K34: 1 | L34: per piece | M34: =IF(OR(G34="",J34="",K34=""),"",ROUND(IF(I34="incl.",G34/(1+J34),G34)/IF(L34="per pack",K34,1),2)) | N34: CLOSE | O34: Countertop pump dispenser for ketchup/mustard, white PE, ~30 ml portion, sliding cover, removable pump; free-standing unit - separate stand not mentioned. 1,195 CZK bez DPH. | P34: 2026-09-30 | Q34: =IFERROR(INDEX(Competitors!$N$2:$N$50,MATCH(C34,Competitors!$A$2:$A$50,0)),"no") | R34: =IF(AND(Q34="yes",OR(N34="EXACT",N34="CLOSE"),ISNUMBER(M34)),"yes","no")
A35: 8 | B35: Ketchup/sauce pump dispenser with stand | C35: TOMGAST | D35: Dávkovač 1,5 l | E35: TOMGAST | F35: https://www.tomgast.cz/davkovac-1-5-l/ | G35: 877 | H35: CZK | I35: incl. | J35: 0.21 | K35: 1 | L35: per piece | M35: =IF(OR(G35="",J35="",K35=""),"",ROUND(IF(I35="incl.",G35/(1+J35),G35)/IF(L35="per pack",K35,1),2)) | N35: APPROX | O35: Push-button portion dispenser (30 ml dose), polyethylene, 1.5 l; no stand/base mentioned - not a pump-on-stand unit. 725 CZK bez DPH. | P35: 2026-09-30 | Q35: =IFERROR(INDEX(Competitors!$N$2:$N$50,MATCH(C35,Competitors!$A$2:$A$50,0)),"no") | R35: =IF(AND(Q35="yes",OR(N35="EXACT",N35="CLOSE"),ISNUMBER(M35)),"yes","no")
A36: 9 | B36: HACCP PE cutting board 530 x 325 x 20 mm (GN 1/1) | C36: GGM Gastro (CZ storefront) | D36: Krájecí deska - 325x530 mm - Dle HACCP - Bílá | E36: GGM | F36: https://www.ggmgastro.com/cs-cz-czk/krajeci-deska-325x530-mm-dle-haccp-bila-sbp53w | G36: 632.57 | H36: CZK | I36: excl. | J36: 0.19 | K36: 1 | L36: per piece | M36: =IF(OR(G36="",J36="",K36=""),"",ROUND(IF(I36="incl.",G36/(1+J36),G36)/IF(L36="per pack",K36,1),2)) | N36: EXACT | O36: Net CZK price as displayed; page footnote: "* čistá cena | hrubá cena vč. 19% DPH" (German VAT 19% used on the CZ storefront). SKU SBP53W, PE, 325 x 530 x 20 mm, HACCP colours (same price red etc.). Gross 752.76 CZK. | P36: 2026-09-30 | Q36: =IFERROR(INDEX(Competitors!$N$2:$N$50,MATCH(C36,Competitors!$A$2:$A$50,0)),"no") | R36: =IF(AND(Q36="yes",OR(N36="EXACT",N36="CLOSE"),ISNUMBER(M36)),"yes","no")
A37: 9 | B37: HACCP PE cutting board 530 x 325 x 20 mm (GN 1/1) | C37: Gastro Novotný | D37: Deska polyethylen GN 1/1 53x32,5x2cm nožičky, PE-HD červená | F37: https://eshop.gastronovotny.cz/deska-polyethylen-gn-1-1--53x32-5x2cm--nozicky-pe-hd--cervena/ | G37: 1090 | H37: CZK | I37: excl. | J37: 0.21 | K37: 1 | L37: per piece | M37: =IF(OR(G37="",J37="",K37=""),"",ROUND(IF(I37="incl.",G37/(1+J37),G37)/IF(L37="per pack",K37,1),2)) | N37: EXACT | O37: HDPE, feet, colours white/yellow/red/blue/green/brown/black; 1,318.90 CZK incl. VAT; availability "Na dotaz" (some colours 3-6 weeks) | P37: 2026-09-30 | Q37: =IFERROR(INDEX(Competitors!$N$2:$N$50,MATCH(C37,Competitors!$A$2:$A$50,0)),"no") | R37: =IF(AND(Q37="yes",OR(N37="EXACT",N37="CLOSE"),ISNUMBER(M37)),"yes","no")
A38: 9 | B38: HACCP PE cutting board 530 x 325 x 20 mm (GN 1/1) | C38: Gastromania | D38: Deska na krájení HACCP 530x325x25 mm, červená | CONTACTO, 1524/539 | E38: Contacto | F38: https://www.gastromania.cz/plastove-krajeci-desky-haccp/deska-na-krajeni-haccp-530x325x25-mm-cervena-contacto-1524-539 | G38: 1172 | H38: CZK | I38: excl. | J38: 0.21 | K38: 1 | L38: per piece | M38: =IF(OR(G38="",J38="",K38=""),"",ROUND(IF(I38="incl.",G38/(1+J38),G38)/IF(L38="per pack",K38,1),2)) | N38: CLOSE | O38: PE, HACCP colours, anti-slip feet; 25 mm thick (no 20 mm PE GN 1/1 board found). 1,418 CZK incl.; availability 30 days. Thinner options: Hendi 530x325x15 (PE/PP conflicting) 523 excl.; Hendi 10 mm 297 excl. | P38: 2026-09-30 | Q38: =IFERROR(INDEX(Competitors!$N$2:$N$50,MATCH(C38,Competitors!$A$2:$A$50,0)),"no") | R38: =IF(AND(Q38="yes",OR(N38="EXACT",N38="CLOSE"),ISNUMBER(M38)),"yes","no")
A39: 9 | B39: HACCP PE cutting board 530 x 325 x 20 mm (GN 1/1) | C39: Gastrozone | D39: Prkénko krájecí plastové 53x32,5x2 cm GN 1/1, s drážkou, červené | E39: Gastro | F39: https://www.gastrozone.cz/gastro-prkenko-krajeci-plastove-53x32-5x2-cm-gn-1-1-s-drazkou-cervene.html | G39: 1531 | H39: CZK | I39: incl. | J39: 0.21 | K39: 1 | L39: per piece | M39: =IF(OR(G39="",J39="",K39=""),"",ROUND(IF(I39="incl.",G39/(1+J39),G39)/IF(L39="per pack",K39,1),2)) | N39: CLOSE | O39: 530 x 325 x 20 mm, HACCP colours; material only "plast" (plastic type not stated - flagged); has juice groove and rubber feet. 1,265 CZK bez DPH. | P39: 2026-09-30 | Q39: =IFERROR(INDEX(Competitors!$N$2:$N$50,MATCH(C39,Competitors!$A$2:$A$50,0)),"no") | R39: =IF(AND(Q39="yes",OR(N39="EXACT",N39="CLOSE"),ISNUMBER(M39)),"yes","no")
A40: 9 | B40: HACCP PE cutting board 530 x 325 x 20 mm (GN 1/1) | C40: TOMGAST | D40: Deska 500 × 325 × 20 mm, červená | E40: TOMGAST | F40: https://www.tomgast.cz/deska-500--325--20-mm--cervena/ | G40: 1016 | H40: CZK | I40: incl. | J40: 0.21 | K40: 1 | L40: per piece | M40: =IF(OR(G40="",J40="",K40=""),"",ROUND(IF(I40="incl.",G40/(1+J40),G40)/IF(L40="per pack",K40,1),2)) | N40: APPROX | O40: PE, colour range (white/red/blue/green/yellow/brown), anti-slip feet; 500 mm long, not GN 1/1 530 mm. 840 CZK bez DPH. No 530 x 325 PE board listed. | P40: 2026-09-30 | Q40: =IFERROR(INDEX(Competitors!$N$2:$N$50,MATCH(C40,Competitors!$A$2:$A$50,0)),"no") | R40: =IF(AND(Q40="yes",OR(N40="EXACT",N40="CLOSE"),ISNUMBER(M40)),"yes","no")
A41: 10 | B41: HACCP PE cutting board 600 x 400 x 20 mm | C41: GGM Gastro (CZ storefront) | D41: Krájecí deska - EN 600x400 - Dle HACCP - Bílá | E41: GGM | F41: https://www.ggmgastro.com/cs-cz-czk/krajeci-deska-en-600x400-dle-haccp-bila-sbp46w | G41: 717.76 | H41: CZK | I41: excl. | J41: 0.19 | K41: 1 | L41: per piece | M41: =IF(OR(G41="",J41="",K41=""),"",ROUND(IF(I41="incl.",G41/(1+J41),G41)/IF(L41="per pack",K41,1),2)) | N41: EXACT | O41: Net CZK price as displayed; page footnote: "* čistá cena | hrubá cena vč. 19% DPH" (German VAT 19% used on the CZ storefront). SKU SBP46W, PE, 600 x 400 x 20 mm, HACCP colours. Gross 854.13 CZK. | P41: 2026-09-30 | Q41: =IFERROR(INDEX(Competitors!$N$2:$N$50,MATCH(C41,Competitors!$A$2:$A$50,0)),"no") | R41: =IF(AND(Q41="yes",OR(N41="EXACT",N41="CLOSE"),ISNUMBER(M41)),"yes","no")
A42: 10 | B42: HACCP PE cutting board 600 x 400 x 20 mm | C42: Gastro Novotný | D42: Deska polyethylen 60x40x2cm nožičky PE-HD -bílá | F42: https://eshop.gastronovotny.cz/deska-polyethylen-60x40x2cm-nozicky-pe-hd-bila/ | G42: 1350 | H42: CZK | I42: excl. | J42: 0.21 | K42: 1 | L42: per piece | M42: =IF(OR(G42="",J42="",K42=""),"",ROUND(IF(I42="incl.",G42/(1+J42),G42)/IF(L42="per pack",K42,1),2)) | N42: EXACT | O42: HDPE, feet; colour range (white/yellow/red/green/brown/black); white is the lowest-priced colour; 1,633.50 CZK incl. VAT; white on order 3-6 weeks (red 1,460 CZK excl., in stock). | P42: 2026-09-30 | Q42: =IFERROR(INDEX(Competitors!$N$2:$N$50,MATCH(C42,Competitors!$A$2:$A$50,0)),"no") | R42: =IF(AND(Q42="yes",OR(N42="EXACT",N42="CLOSE"),ISNUMBER(M42)),"yes","no")
A43: 10 | B43: HACCP PE cutting board 600 x 400 x 20 mm | C43: Gastromania | D43: Krájecí deska 600x400x20 mm, červená | YATO, YG-02180 | E43: Yato | F43: https://www.gastromania.cz/plastove-krajeci-desky-haccp/krajeci-deska-600x400x20-mm-cervena-yato-yg-02180 | G43: 574 | H43: CZK | I43: excl. | J43: 0.21 | K43: 1 | L43: per piece | M43: =IF(OR(G43="",J43="",K43=""),"",ROUND(IF(I43="incl.",G43/(1+J43),G43)/IF(L43="per pack",K43,1),2)) | N43: EXACT | O43: PE, 20 mm, HACCP colours (white/red/blue/green/yellow/brown); 695 CZK incl.; availability 5 days. | P43: 2026-09-30 | Q43: =IFERROR(INDEX(Competitors!$N$2:$N$50,MATCH(C43,Competitors!$A$2:$A$50,0)),"no") | R43: =IF(AND(Q43="yes",OR(N43="EXACT",N43="CLOSE"),ISNUMBER(M43)),"yes","no")
A44: 10 | B44: HACCP PE cutting board 600 x 400 x 20 mm | C44: Gastrozone | D44: Prkénko krájecí plastové 60x40x3 cm, s drážkou, červené | E44: Gastro | F44: https://www.gastrozone.cz/gastro-prkenko-krajeci-plastove-60x40x3-cm-s-drazkou-cervene.html | G44: 2225 | H44: CZK | I44: incl. | J44: 0.21 | K44: 1 | L44: per piece | M44: =IF(OR(G44="",J44="",K44=""),"",ROUND(IF(I44="incl.",G44/(1+J44),G44)/IF(L44="per pack",K44,1),2)) | N44: CLOSE | O44: 600 x 400 but 30 mm thick (no 20 mm version); material only "plast" (flagged); HACCP colours; white 2,003 CZK. 1,839 CZK bez DPH. | P44: 2026-09-30 | Q44: =IFERROR(INDEX(Competitors!$N$2:$N$50,MATCH(C44,Competitors!$A$2:$A$50,0)),"no") | R44: =IF(AND(Q44="yes",OR(N44="EXACT",N44="CLOSE"),ISNUMBER(M44)),"yes","no")
A45: 10 | B45: HACCP PE cutting board 600 x 400 x 20 mm | C45: TOMGAST | D45: Deska 600 × 400 × 20 mm, červená | E45: TOMGAST | F45: https://www.tomgast.cz/deska-600--400--20-mm--cervena/ | G45: 1440 | H45: CZK | I45: incl. | J45: 0.21 | K45: 1 | L45: per piece | M45: =IF(OR(G45="",J45="",K45=""),"",ROUND(IF(I45="incl.",G45/(1+J45),G45)/IF(L45="per pack",K45,1),2)) | N45: EXACT | O45: PE, colours white/red/blue/green/yellow/brown; 1,190 CZK bez DPH | P45: 2026-09-30 | Q45: =IFERROR(INDEX(Competitors!$N$2:$N$50,MATCH(C45,Competitors!$A$2:$A$50,0)),"no") | R45: =IF(AND(Q45="yes",OR(N45="EXACT",N45="CLOSE"),ISNUMBER(M45)),"yes","no")
A46: 11 | B46: HACCP PE cutting board 300 x 200 x 10 mm | C46: GGM Gastro (CZ storefront) | D46: Krájecí deska - EN 250x400 - Dle HACCP - Bílá | E46: GGM | F46: https://www.ggmgastro.com/cs-cz-czk/krajeci-deska-en-250x400-dle-haccp-bila-sbp25w | G46: 437.86 | H46: CZK | I46: excl. | J46: 0.19 | K46: 1 | L46: per piece | M46: =IF(OR(G46="",J46="",K46=""),"",ROUND(IF(I46="incl.",G46/(1+J46),G46)/IF(L46="per pack",K46,1),2)) | N46: APPROX | O46: Net CZK price as displayed; page footnote: "* čistá cena | hrubá cena vč. 19% DPH" (German VAT 19% used on the CZ storefront). Smallest HACCP board: 250 x 400 x 20 mm PE (vs 300 x 200 x 10). Gross 521.05 CZK. | P46: 2026-09-30 | Q46: =IFERROR(INDEX(Competitors!$N$2:$N$50,MATCH(C46,Competitors!$A$2:$A$50,0)),"no") | R46: =IF(AND(Q46="yes",OR(N46="EXACT",N46="CLOSE"),ISNUMBER(M46)),"yes","no")
A47: 11 | B47: HACCP PE cutting board 300 x 200 x 10 mm | C47: Gastromania | D47: Prkénko na krájení s úchytem 30x20x1 cm, černé | HENDI, 826485 | E47: Hendi | F47: https://www.gastromania.cz/plastove-krajeci-desky-haccp/prkenko-na-krajeni-s-uchytem-30x20x1-cm-cerne-hendi-826485 | G47: 159 | H47: CZK | I47: excl. | J47: 0.21 | K47: 1 | L47: per piece | M47: =IF(OR(G47="",J47="",K47=""),"",ROUND(IF(I47="incl.",G47/(1+J47),G47)/IF(L47="per pack",K47,1),2)) | N47: CLOSE | O47: HDPE 300 x 200 x 10 mm with handle; black only (not HACCP colour set). 192 CZK incl. Parameter list says "cena za: sadu" (price per set) while title/description describe one board - unit unclear, treated as 1 piece. | P47: 2026-09-30 | Q47: =IFERROR(INDEX(Competitors!$N$2:$N$50,MATCH(C47,Competitors!$A$2:$A$50,0)),"no") | R47: =IF(AND(Q47="yes",OR(N47="EXACT",N47="CLOSE"),ISNUMBER(M47)),"yes","no")
A48: 11 | B48: HACCP PE cutting board 300 x 200 x 10 mm | C48: Gastrozone | D48: Krájecí prkénko HENDI s rukojetí, 300 × 200 mm, bílé | E48: Hendi | F48: https://www.gastrozone.cz/viceucelove-krajeci-prkenko-s-rukojeti-hendi-bila-300x200mm-obdelnikove.html | G48: 183 | H48: CZK | I48: incl. | J48: 0.21 | K48: 1 | L48: per piece | M48: =IF(OR(G48="",J48="",K48=""),"",ROUND(IF(I48="incl.",G48/(1+J48),G48)/IF(L48="per pack",K48,1),2)) | N48: CLOSE | O48: HDPE 300 x 200 x 10 mm with integrated handle; only white/black (no full HACCP colour set). 151 CZK bez DPH. | P48: 2026-09-30 | Q48: =IFERROR(INDEX(Competitors!$N$2:$N$50,MATCH(C48,Competitors!$A$2:$A$50,0)),"no") | R48: =IF(AND(Q48="yes",OR(N48="EXACT",N48="CLOSE"),ISNUMBER(M48)),"yes","no")
A49: 11 | B49: HACCP PE cutting board 300 x 200 x 10 mm | C49: TOMGAST | D49: Deska krájecí 20 × 30 × 1,2 cm | E49: TOMGAST | F49: https://www.tomgast.cz/deska-krajeci-20--30--1-2-cm/ | G49: 115 | H49: CZK | I49: incl. | J49: 0.21 | K49: 1 | L49: per piece | M49: =IF(OR(G49="",J49="",K49=""),"",ROUND(IF(I49="incl.",G49/(1+J49),G49)/IF(L49="per pack",K49,1),2)) | N49: CLOSE | O49: PE 300 x 200 mm but 12 mm thick; white only (no colour range). 95 CZK bez DPH. | P49: 2026-09-30 | Q49: =IFERROR(INDEX(Competitors!$N$2:$N$50,MATCH(C49,Competitors!$A$2:$A$50,0)),"no") | R49: =IF(AND(Q49="yes",OR(N49="EXACT",N49="CLOSE"),ISNUMBER(M49)),"yes","no")
A50: 12 | B50: Pizza dough proofing box 600 x 400 x 100 mm, polypropylene | C50: GGM Gastro (CZ storefront) | D50: (9 tlg) Přepravka na těsto-set - 8 nádob & 1 víko - EN 600x400 - Výška: 100 mm - Polypropylen - bílá | E50: GGM | F50: https://www.ggmgastro.com/cs-cz-czk/9-tlg-prepravka-na-testo-set-8-nadob-und-1-viko-en-600x400-vyska-100-mm-polypropylen-bila-tbpp6410 | G50: 2044.23 | H50: CZK | I50: excl. | J50: 0.19 | K50: 8 | L50: per pack | M50: =IF(OR(G50="",J50="",K50=""),"",ROUND(IF(I50="incl.",G50/(1+J50),G50)/IF(L50="per pack",K50,1),2)) | N50: CLOSE | O50: Net CZK price as displayed; page footnote: "* čistá cena | hrubá cena vč. 19% DPH" (German VAT 19% used on the CZ storefront). SKU TBPP6410: set of 8 PP boxes 600x400x100 + 1 lid (not sold singly); per-piece value = set price / 8 boxes and therefore includes the lid - flagged. Gross 2,432.63 CZK. | P50: 2026-09-30 | Q50: =IFERROR(INDEX(Competitors!$N$2:$N$50,MATCH(C50,Competitors!$A$2:$A$50,0)),"no") | R50: =IF(AND(Q50="yes",OR(N50="EXACT",N50="CLOSE"),ISNUMBER(M50)),"yes","no")
A51: 12 | B51: Pizza dough proofing box 600 x 400 x 100 mm, polypropylene | C51: Gastro Novotný | D51: Přepravka na pizzu 60x40x9cm | F51: https://eshop.gastronovotny.cz/prepravka-na-pizzu-60x40x9cm--1841762-09/ | G51: 390 | H51: CZK | I51: excl. | J51: 0.21 | K51: 1 | L51: per piece | M51: =IF(OR(G51="",J51="",K51=""),"",ROUND(IF(I51="incl.",G51/(1+J51),G51)/IF(L51="per pack",K51,1),2)) | N51: CLOSE | O51: 600 x 400 x 90 mm (not 100 mm); material NOT stated on page (flagged). 471.90 CZK incl. VAT. Availability "Na dotaz". No lid listed. | P51: 2026-09-30 | Q51: =IFERROR(INDEX(Competitors!$N$2:$N$50,MATCH(C51,Competitors!$A$2:$A$50,0)),"no") | R51: =IF(AND(Q51="yes",OR(N51="EXACT",N51="CLOSE"),ISNUMBER(M51)),"yes","no")
A52: 12 | B52: Pizza dough proofing box 600 x 400 x 100 mm, polypropylene | C52: Gastromania | D52: Nádoba na těsto na pizzu, polyetylenová, 600x400x100 mm | STALGAST, 563410 | E52: Stalgast | F52: https://www.gastromania.cz/kose-na-pizza-testo/nadoba-na-testo-na-pizzu-polyetylenova-600x400x100-mm-stalgast-563410 | G52: 463 | H52: CZK | I52: excl. | J52: 0.21 | K52: 1 | L52: per piece | M52: =IF(OR(G52="",J52="",K52=""),"",ROUND(IF(I52="incl.",G52/(1+J52),G52)/IF(L52="per pack",K52,1),2)) | N52: CLOSE | O52: 600 x 400 x 100 mm; material conflicting: title says polyethylene, parameters say polypropylene (flagged). 560 CZK incl.; in stock. | P52: 2026-09-30 | Q52: =IFERROR(INDEX(Competitors!$N$2:$N$50,MATCH(C52,Competitors!$A$2:$A$50,0)),"no") | R52: =IF(AND(Q52="yes",OR(N52="EXACT",N52="CLOSE"),ISNUMBER(M52)),"yes","no")
A53: 12 | B53: Pizza dough proofing box 600 x 400 x 100 mm, polypropylene | C53: Gastrozone | D53: Araven Pizzabox na těsto PP, polypropylen, výška: 100 mm, délka: 600 mm, šířka: 400 mm | E53: Araven | F53: https://www.gastrozone.cz/araven-pizzabox-pp-vyska-100-mm-delka-600-mm-sirka-400-mm.html | G53: 546 | H53: CZK | I53: incl. | J53: 0.21 | K53: 1 | L53: per piece | M53: =IF(OR(G53="",J53="",K53=""),"",ROUND(IF(I53="incl.",G53/(1+J53),G53)/IF(L53="per pack",K53,1),2)) | N53: EXACT | O53: 451 CZK bez DPH | P53: 2026-09-30 | Q53: =IFERROR(INDEX(Competitors!$N$2:$N$50,MATCH(C53,Competitors!$A$2:$A$50,0)),"no") | R53: =IF(AND(Q53="yes",OR(N53="EXACT",N53="CLOSE"),ISNUMBER(M53)),"yes","no")
A54: 12 | B54: Pizza dough proofing box 600 x 400 x 100 mm, polypropylene | C54: TOMGAST | D54: Přepravka na pizzu 60 × 40 × 7,5 cm | E54: TOMGAST | F54: https://www.tomgast.cz/prepravka-na-pizzu-60--40--7-5-cm/ | G54: 339 | H54: CZK | I54: incl. | J54: 0.21 | K54: 1 | L54: per piece | M54: =IF(OR(G54="",J54="",K54=""),"",ROUND(IF(I54="incl.",G54/(1+J54),G54)/IF(L54="per pack",K54,1),2)) | N54: APPROX | O54: PP dough box but 75 mm deep, not 100 mm (15 l). Parameter table inconsistently says 60 x 40 x 2 cm. 280 CZK bez DPH. Lid sold separately. | P54: 2026-09-30 | Q54: =IFERROR(INDEX(Competitors!$N$2:$N$50,MATCH(C54,Competitors!$A$2:$A$50,0)),"no") | R54: =IF(AND(Q54="yes",OR(N54="EXACT",N54="CLOSE"),ISNUMBER(M54)),"yes","no")
A55: 13 | B55: Lid for 600 x 400 mm dough box | C55: Gastromania | D55: Víko k přepravce na pizzu 60x40 cm | TOM-GAST, ZT-6040-1 | E55: TOMGAST | F55: https://www.gastromania.cz/vika-na-kose-na-testo/viko-k-prepravce-na-pizzu-60x40-cm-tom-gast-zt-6040-1 | G55: 195 | H55: CZK | I55: excl. | J55: 0.21 | K55: 1 | L55: per piece | M55: =IF(OR(G55="",J55="",K55=""),"",ROUND(IF(I55="incl.",G55/(1+J55),G55)/IF(L55="per pack",K55,1),2)) | N55: EXACT | O55: Lid for 600x400 dough box; 236 CZK incl. (same item/price as tomgast.cz). | P55: 2026-09-30 | Q55: =IFERROR(INDEX(Competitors!$N$2:$N$50,MATCH(C55,Competitors!$A$2:$A$50,0)),"no") | R55: =IF(AND(Q55="yes",OR(N55="EXACT",N55="CLOSE"),ISNUMBER(M55)),"yes","no")
A56: 13 | B56: Lid for 600 x 400 mm dough box | C56: Gastrozone | D56: Araven Víko na pizzabox na těsto PP, polypropylen, délka: 600 mm, šířka: 400 mm | E56: Araven | F56: https://www.gastrozone.cz/araven-viko-k-pizzove-krabici-z-pp-delka-600-mm-sirka-400-mm.html | G56: 324 | H56: CZK | I56: incl. | J56: 0.21 | K56: 1 | L56: per piece | M56: =IF(OR(G56="",J56="",K56=""),"",ROUND(IF(I56="incl.",G56/(1+J56),G56)/IF(L56="per pack",K56,1),2)) | N56: EXACT | O56: 268 CZK bez DPH. Cheaper AmerBox 600x400 lid 228 CZK. | P56: 2026-09-30 | Q56: =IFERROR(INDEX(Competitors!$N$2:$N$50,MATCH(C56,Competitors!$A$2:$A$50,0)),"no") | R56: =IF(AND(Q56="yes",OR(N56="EXACT",N56="CLOSE"),ISNUMBER(M56)),"yes","no")
A57: 13 | B57: Lid for 600 x 400 mm dough box | C57: TOMGAST | D57: Víko k přepravce na pizzu 60 × 40 cm | E57: TOMGAST | F57: https://www.tomgast.cz/viko-k-prepravce-na-pizzu-60--40-cm/ | G57: 236 | H57: CZK | I57: incl. | J57: 0.21 | K57: 1 | L57: per piece | M57: =IF(OR(G57="",J57="",K57=""),"",ROUND(IF(I57="incl.",G57/(1+J57),G57)/IF(L57="per pack",K57,1),2)) | N57: EXACT | O57: Lid for ZT-6040 dough box; material "plast". 195 CZK bez DPH. | P57: 2026-09-30 | Q57: =IFERROR(INDEX(Competitors!$N$2:$N$50,MATCH(C57,Competitors!$A$2:$A$50,0)),"no") | R57: =IF(AND(Q57="yes",OR(N57="EXACT",N57="CLOSE"),ISNUMBER(M57)),"yes","no")
A58: 14 | B58: Pizza dough proofing box 600 x 400 x 75 mm, polyethylene | C58: GGM Gastro (CZ storefront) | D58: (9 tlg) Přepravka na těsto-set - 8 nádob & 1 víko - EN 600x400 - Výška: 75 mm - Polypropylen - bílá | E58: GGM | F58: https://www.ggmgastro.com/cs-cz-czk/9-tlg-prepravka-na-testo-set-8-nadob-und-1-viko-en-600x400-vyska-75-mm-polypropylen-bila-tbpp647 | G58: 1752.16 | H58: CZK | I58: excl. | J58: 0.19 | K58: 8 | L58: per pack | M58: =IF(OR(G58="",J58="",K58=""),"",ROUND(IF(I58="incl.",G58/(1+J58),G58)/IF(L58="per pack",K58,1),2)) | N58: CLOSE | O58: Net CZK price as displayed; page footnote: "* čistá cena | hrubá cena vč. 19% DPH" (German VAT 19% used on the CZ storefront). SKU TBPP647: set of 8 boxes 600x400x75 + 1 lid; polypropylene, not polyethylene; per-piece = set / 8 (includes lid) - flagged. Gross 2,085.07 CZK. Alternative 8-pack TBP647 (70 mm, no lid) 1,873.86 CZK. | P58: 2026-09-30 | Q58: =IFERROR(INDEX(Competitors!$N$2:$N$50,MATCH(C58,Competitors!$A$2:$A$50,0)),"no") | R58: =IF(AND(Q58="yes",OR(N58="EXACT",N58="CLOSE"),ISNUMBER(M58)),"yes","no")
A59: 14 | B59: Pizza dough proofing box 600 x 400 x 75 mm, polyethylene | C59: Gastro Novotný | D59: Přepravka na pizzu 60x40x9cm | F59: https://eshop.gastronovotny.cz/prepravka-na-pizzu-60x40x9cm--1841762-09/ | G59: 390 | H59: CZK | I59: excl. | J59: 0.21 | K59: 1 | L59: per piece | M59: =IF(OR(G59="",J59="",K59=""),"",ROUND(IF(I59="incl.",G59/(1+J59),G59)/IF(L59="per pack",K59,1),2)) | N59: APPROX | O59: 90 mm deep instead of 75 mm and material not stated. 471.90 CZK incl. VAT. | P59: 2026-09-30 | Q59: =IFERROR(INDEX(Competitors!$N$2:$N$50,MATCH(C59,Competitors!$A$2:$A$50,0)),"no") | R59: =IF(AND(Q59="yes",OR(N59="EXACT",N59="CLOSE"),ISNUMBER(M59)),"yes","no")
A60: 14 | B60: Pizza dough proofing box 600 x 400 x 75 mm, polyethylene | C60: Gastromania | D60: Nádoba na pizza těsto 600x400x75 mm | CONTACTO, 2510/600 | E60: Contacto | F60: https://www.gastromania.cz/kose-na-pizza-testo/nadoba-na-pizza-testo-600x400x75-mm-contacto-2510-600 | G60: 391 | H60: CZK | I60: excl. | J60: 0.21 | K60: 1 | L60: per piece | M60: =IF(OR(G60="",J60="",K60=""),"",ROUND(IF(I60="incl.",G60/(1+J60),G60)/IF(L60="per pack",K60,1),2)) | N60: EXACT | O60: PE, 600 x 400 x 75 mm; 473 CZK incl.; discounted from 434 excl. / 526 incl.; availability 30 days. | P60: 2026-09-30 | Q60: =IFERROR(INDEX(Competitors!$N$2:$N$50,MATCH(C60,Competitors!$A$2:$A$50,0)),"no") | R60: =IF(AND(Q60="yes",OR(N60="EXACT",N60="CLOSE"),ISNUMBER(M60)),"yes","no")
A61: 14 | B61: Pizza dough proofing box 600 x 400 x 75 mm, polyethylene | C61: Gastrozone | D61: Nádoba AmerBox Kitchen Line na pizza těsto, 600 × 400 mm, 14 l | E61: AmerBox (Hendi) | F61: https://www.gastrozone.cz/nadoba-na-pizza-testo-600x400-amerbox-kitchen-line-14l-600x400x-h-75mm.html | G61: 285 | H61: CZK | I61: incl. | J61: 0.21 | K61: 1 | L61: per piece | M61: =IF(OR(G61="",J61="",K61=""),"",ROUND(IF(I61="incl.",G61/(1+J61),G61)/IF(L61="per pack",K61,1),2)) | N61: CLOSE | O61: 600 x 400 x 75 mm, 14 l, but PET (polyethylene terephthalate), not PE. 236 CZK bez DPH. | P61: 2026-09-30 | Q61: =IFERROR(INDEX(Competitors!$N$2:$N$50,MATCH(C61,Competitors!$A$2:$A$50,0)),"no") | R61: =IF(AND(Q61="yes",OR(N61="EXACT",N61="CLOSE"),ISNUMBER(M61)),"yes","no")
A62: 14 | B62: Pizza dough proofing box 600 x 400 x 75 mm, polyethylene | C62: TOMGAST | D62: Přepravka na pizzu 60 × 40 × 7,5 cm | E62: TOMGAST | F62: https://www.tomgast.cz/prepravka-na-pizzu-60--40--7-5-cm/ | G62: 339 | H62: CZK | I62: incl. | J62: 0.21 | K62: 1 | L62: per piece | M62: =IF(OR(G62="",J62="",K62=""),"",ROUND(IF(I62="incl.",G62/(1+J62),G62)/IF(L62="per pack",K62,1),2)) | N62: CLOSE | O62: 600 x 400 x 75 mm but polypropylene, not polyethylene. 280 CZK bez DPH. | P62: 2026-09-30 | Q62: =IFERROR(INDEX(Competitors!$N$2:$N$50,MATCH(C62,Competitors!$A$2:$A$50,0)),"no") | R62: =IF(AND(Q62="yes",OR(N62="EXACT",N62="CLOSE"),ISNUMBER(M62)),"yes","no")
A63: 15 | B63: Front-loading insulated thermobox for GN 1/1, approx. 80-90 l | C63: GGM Gastro (CZ storefront) | D63: CAMBRO | CAM GOBOX - Termobox - Frontloader s předním plněním GN 1/1 - černý | E63: Cambro | F63: https://www.ggmgastro.com/cs-cz-czk/cambro-cam-gobox-r-termobox-frontloader-s-prednim-plnenim-gn-1-1-cerny-epp400110 | G63: 4088.71 | H63: CZK | I63: excl. | J63: 0.19 | K63: 1 | L63: per piece | M63: =IF(OR(G63="",J63="",K63=""),"",ROUND(IF(I63="incl.",G63/(1+J63),G63)/IF(L63="per pack",K63,1),2)) | N63: EXACT | O63: Net CZK price as displayed; page footnote: "* čistá cena | hrubá cena vč. 19% DPH" (German VAT 19% used on the CZ storefront). SKU EPP400110, EPP, 86 l, front loading. Gross 4,865.56 CZK; in stock 3-5 days. Alternative Porter PLB-300 83 l: 6,936.37 CZK. | P63: 2026-09-30 | Q63: =IFERROR(INDEX(Competitors!$N$2:$N$50,MATCH(C63,Competitors!$A$2:$A$50,0)),"no") | R63: =IF(AND(Q63="yes",OR(N63="EXACT",N63="CLOSE"),ISNUMBER(M63)),"yes","no")
A64: 15 | B64: Front-loading insulated thermobox for GN 1/1, approx. 80-90 l | C64: Gastro Novotný | D64: Termoport přední plnění 6xGN1/1 65 | E64: Thermo Case P-600M | F64: https://eshop.gastronovotny.cz/termoport-predni-plneni-6xgn1-1-65--403191201/ | G64: 5900 | H64: CZK | I64: excl. | J64: 0.21 | K64: 1 | L64: per piece | M64: =IF(OR(G64="",J64="",K64=""),"",ROUND(IF(I64="incl.",G64/(1+J64),G64)/IF(L64="per pack",K64,1),2)) | N64: CLOSE | O64: Front-loading, polypropylene, holds 6 x GN 1/1 65 mm; volume in litres NOT stated (flagged). 7,139 CZK incl. VAT. Availability "Na dotaz". Alternative: Termoport GN 1/1 Front 20-TERMOP-F 7,089.26 CZK excl. (smaller: 3 x GN 1/1 65). | P64: 2026-09-30 | Q64: =IFERROR(INDEX(Competitors!$N$2:$N$50,MATCH(C64,Competitors!$A$2:$A$50,0)),"no") | R64: =IF(AND(Q64="yes",OR(N64="EXACT",N64="CLOSE"),ISNUMBER(M64)),"yes","no")
A65: 15 | B65: Front-loading insulated thermobox for GN 1/1, approx. 80-90 l | C65: Gastromania | D65: Termobox s předním plněním pro GN | CAMBRO, R-EPP400 | E65: Cambro | F65: https://www.gastromania.cz/termoizolacni/termobox-s-prednim-plnenim-pro-gn-cambro-r-epp400 | G65: 5706 | H65: CZK | I65: excl. | J65: 0.21 | K65: 1 | L65: per piece | M65: =IF(OR(G65="",J65="",K65=""),"",ROUND(IF(I65="incl.",G65/(1+J65),G65)/IF(L65="per pack",K65,1),2)) | N65: EXACT | O65: Same Cambro EPP400 front-loader (86 l) as TOMGAST, same price; 6,904 CZK incl.; in stock. | P65: 2026-09-30 | Q65: =IFERROR(INDEX(Competitors!$N$2:$N$50,MATCH(C65,Competitors!$A$2:$A$50,0)),"no") | R65: =IF(AND(Q65="yes",OR(N65="EXACT",N65="CLOSE"),ISNUMBER(M65)),"yes","no")
A66: 15 | B66: Front-loading insulated thermobox for GN 1/1, approx. 80-90 l | C66: Gastrozone | D66: Termoizolační box Cambro Cam GoBox s horním plněním, GN 1/1, 86 l, černý | E66: Cambro | F66: https://www.gastrozone.cz/cambro-termoport-86-l-bocni-plneni.html | G66: 5446 | H66: CZK | I66: incl. | J66: 0.21 | K66: 1 | L66: per piece | M66: =IF(OR(G66="",J66="",K66=""),"",ROUND(IF(I66="incl.",G66/(1+J66),G66)/IF(L66="per pack",K66,1),2)) | N66: CLOSE | O66: 86 l, GN 1/1, EPP; product title says "s horním plněním" (top loading) but description and URL say side/front loading ("boční plnění", door) - conflicting, flagged. Promotional price (-42%, was 9,455 CZK). 4,501 CZK bez DPH. Alternative: Cambro Ultra Pan Carrier front-loading GN 1/1 (PE) 6,536 CZK, volume not stated. | P66: 2026-09-30 | Q66: =IFERROR(INDEX(Competitors!$N$2:$N$50,MATCH(C66,Competitors!$A$2:$A$50,0)),"no") | R66: =IF(AND(Q66="yes",OR(N66="EXACT",N66="CLOSE"),ISNUMBER(M66)),"yes","no")
A67: 15 | B67: Front-loading insulated thermobox for GN 1/1, approx. 80-90 l | C67: TOMGAST | D67: Termobox s předním plněním pro GN | E67: Cambro | F67: https://www.tomgast.cz/termobox-s-prednim-plnenim-pro-gn/ | G67: 6904 | H67: CZK | I67: incl. | J67: 0.21 | K67: 1 | L67: per piece | M67: =IF(OR(G67="",J67="",K67=""),"",ROUND(IF(I67="incl.",G67/(1+J67),G67)/IF(L67="per pack",K67,1),2)) | N67: EXACT | O67: Code R-EPP400, EPP, front loading, 86 l, GN 1/1, 12 fixed rails. 5,706 CZK bez DPH. | P67: 2026-09-30 | Q67: =IFERROR(INDEX(Competitors!$N$2:$N$50,MATCH(C67,Competitors!$A$2:$A$50,0)),"no") | R67: =IF(AND(Q67="yes",OR(N67="EXACT",N67="CLOSE"),ISNUMBER(M67)),"yes","no")
A68: 16 | B68: Service tray approx. 370 x 530 mm, ABS/polypropylene | C68: GGM Gastro (CZ storefront) | D68: (10 ks) Jídelní podnos - ABS plast - 370x530 mm - Hnědý | E68: GGM | F68: https://www.ggmgastro.com/cs-cz-czk/10-ks-jidelni-podnos-abs-plast-370x530-mm-hnedy-gst3753-10 | G68: 1825.18 | H68: CZK | I68: excl. | J68: 0.19 | K68: 10 | L68: per pack | M68: =IF(OR(G68="",J68="",K68=""),"",ROUND(IF(I68="incl.",G68/(1+J68),G68)/IF(L68="per pack",K68,1),2)) | N68: EXACT | O68: Net CZK price as displayed; page footnote: "* čistá cena | hrubá cena vč. 19% DPH" (German VAT 19% used on the CZ storefront). SKU GST3753#10, ABS, 370 x 530 mm, pack of 10. Gross 2,171.96 CZK. | P68: 2026-09-30 | Q68: =IFERROR(INDEX(Competitors!$N$2:$N$50,MATCH(C68,Competitors!$A$2:$A$50,0)),"no") | R68: =IF(AND(Q68="yes",OR(N68="EXACT",N68="CLOSE"),ISNUMBER(M68)),"yes","no")
A69: 16 | B69: Service tray approx. 370 x 530 mm, ABS/polypropylene | C69: Gastro Novotný | D69: Podnos EURONORM 530x370mm | F69: https://eshop.gastronovotny.cz/podnos-euronorm-530x370mm--14100503/ | G69: 300 | H69: CZK | I69: excl. | J69: 0.21 | K69: 1 | L69: per piece | M69: =IF(OR(G69="",J69="",K69=""),"",ROUND(IF(I69="incl.",G69/(1+J69),G69)/IF(L69="per pack",K69,1),2)) | N69: EXACT | O69: 100% PP, 530 x 370 mm, 30 colours; 363 CZK incl. VAT. Description mentions "balení 20ks" (carton of 20) but price/stock are shown per piece ("ks") - treated as per piece. Availability "Na dotaz". | P69: 2026-09-30 | Q69: =IFERROR(INDEX(Competitors!$N$2:$N$50,MATCH(C69,Competitors!$A$2:$A$50,0)),"no") | R69: =IF(AND(Q69="yes",OR(N69="EXACT",N69="CLOSE"),ISNUMBER(M69)),"yes","no")
A70: 16 | B70: Service tray approx. 370 x 530 mm, ABS/polypropylene | C70: Gastromania | D70: Podnos jídelní 37x53 cm, šedá | CAMBRO, Versa | E70: Cambro | F70: https://www.gastromania.cz/obdelnikove-jidelni-podnosy/podnos-jidelni-37x53-cm-seda-cambro-versa | G70: 239 | H70: CZK | I70: excl. | J70: 0.21 | K70: 1 | L70: per piece | M70: =IF(OR(G70="",J70="",K70=""),"",ROUND(IF(I70="incl.",G70/(1+J70),G70)/IF(L70="per pack",K70,1),2)) | N70: APPROX | O70: 370 x 530 mm but polyester/fibreglass, not ABS/PP. 289 CZK incl. PP trays listed only up to 350 x 450 mm and GN 1/1 530 x 325. | P70: 2026-09-30 | Q70: =IFERROR(INDEX(Competitors!$N$2:$N$50,MATCH(C70,Competitors!$A$2:$A$50,0)),"no") | R70: =IF(AND(Q70="yes",OR(N70="EXACT",N70="CLOSE"),ISNUMBER(M70)),"yes","no")
A71: 16 | B71: Service tray approx. 370 x 530 mm, ABS/polypropylene | C71: Gastrozone | D71: CAMBRO Versa Podnos ze sklolaminátu 53 x 37 cm, černý | E71: Cambro | F71: https://www.gastrozone.cz/versa-1.html | G71: 575 | H71: CZK | I71: incl. | J71: 0.21 | K71: 1 | L71: per piece | M71: =IF(OR(G71="",J71="",K71=""),"",ROUND(IF(I71="incl.",G71/(1+J71),G71)/IF(L71="per pack",K71,1),2)) | N71: APPROX | O71: 530 x 370 mm but fibreglass-reinforced polyester, not ABS/PP (parameter table inconsistently shows width 265 mm). 475 CZK bez DPH. PP fast-food trays only up to 530 x 325 / 450 x 355 mm. | P71: 2026-09-30 | Q71: =IFERROR(INDEX(Competitors!$N$2:$N$50,MATCH(C71,Competitors!$A$2:$A$50,0)),"no") | R71: =IF(AND(Q71="yes",OR(N71="EXACT",N71="CLOSE"),ISNUMBER(M71)),"yes","no")
A72: 16 | B72: Service tray approx. 370 x 530 mm, ABS/polypropylene | C72: TOMGAST | D72: Versa podnos jídelní 37 × 53 cm, šedá | E72: Cambro | F72: https://www.tomgast.cz/versa-podnos-jidelni-37--53-cm--seda/ | G72: 289 | H72: CZK | I72: incl. | J72: 0.21 | K72: 1 | L72: per piece | M72: =IF(OR(G72="",J72="",K72=""),"",ROUND(IF(I72="incl.",G72/(1+J72),G72)/IF(L72="per pack",K72,1),2)) | N72: APPROX | O72: 370 x 530 mm but polyester + fibreglass, not ABS/PP. 239 CZK bez DPH. No ABS/PP 37 x 53 tray listed. | P72: 2026-09-30 | Q72: =IFERROR(INDEX(Competitors!$N$2:$N$50,MATCH(C72,Competitors!$A$2:$A$50,0)),"no") | R72: =IF(AND(Q72="yes",OR(N72="EXACT",N72="CLOSE"),ISNUMBER(M72)),"yes","no")
A73: 17 | B73: Insulated thermo tray with lid, 5-6 compartments | C73: Gastrozone | D73: MENÜMOBIL ECO-Classic-Box EPP | E73: MENÜMOBIL | F73: https://www.gastrozone.cz/menumobil-eco-classic-box-epp.html | G73: 2150 | H73: CZK | I73: incl. | J73: 0.21 | K73: 1 | L73: per piece | M73: =IF(OR(G73="",J73="",K73=""),"",ROUND(IF(I73="incl.",G73/(1+J73),G73)/IF(L73="per pack",K73,1),2)) | N73: APPROX | O73: Insulated EPP meal-tray transport box (400 x 310 x 110 mm) for plates/bowls; number of compartments not stated and dishes sold separately - not a moulded 5-6 compartment thermo tray. 1,777 CZK bez DPH. | P73: 2026-09-30 | Q73: =IFERROR(INDEX(Competitors!$N$2:$N$50,MATCH(C73,Competitors!$A$2:$A$50,0)),"no") | R73: =IF(AND(Q73="yes",OR(N73="EXACT",N73="CLOSE"),ISNUMBER(M73)),"yes","no")
A74: 18 | B74: GN 1/1 container, PP, 65 mm | C74: GGM Gastro (CZ storefront) | D74: (6 ks) Polypropylenová nádoba GN 1/1 - Mléčná - Výška: 65 mm | E74: GGM | F74: https://www.ggmgastro.com/cs-cz-czk/6-ks-polypropylenova-nadoba-gn-1-1-mlecna-vyska-65-mm-gpp1165-6 | G74: 1046.33 | H74: CZK | I74: excl. | J74: 0.19 | K74: 6 | L74: per pack | M74: =IF(OR(G74="",J74="",K74=""),"",ROUND(IF(I74="incl.",G74/(1+J74),G74)/IF(L74="per pack",K74,1),2)) | N74: EXACT | O74: Net CZK as displayed (gross 1,245.13 at German 19%); SKU GPP1165-6 | P74: 2026-09-30 | Q74: =IFERROR(INDEX(Competitors!$N$2:$N$50,MATCH(C74,Competitors!$A$2:$A$50,0)),"no") | R74: =IF(AND(Q74="yes",OR(N74="EXACT",N74="CLOSE"),ISNUMBER(M74)),"yes","no")
A75: 18 | B75: GN 1/1 container, PP, 65 mm | C75: Gastro Novotný | D75: Gastronádoba 1/1 100 polypropylen | F75: https://eshop.gastronovotny.cz/gastronadoba-1-1-100-polypropylen--1814702-10/ | G75: 220 | H75: CZK | I75: excl. | J75: 0.21 | K75: 1 | L75: per piece | M75: =IF(OR(G75="",J75="",K75=""),"",ROUND(IF(I75="incl.",G75/(1+J75),G75)/IF(L75="per pack",K75,1),2)) | N75: APPROX | O75: Code 1814702-10; PP GN 1/1 but 100 mm deep (PP 1/1 range is 100/150/200 mm only, no 65 mm); 266.20 CZK incl. VAT | P75: 2026-09-30 | Q75: =IFERROR(INDEX(Competitors!$N$2:$N$50,MATCH(C75,Competitors!$A$2:$A$50,0)),"no") | R75: =IF(AND(Q75="yes",OR(N75="EXACT",N75="CLOSE"),ISNUMBER(M75)),"yes","no")
A76: 18 | B76: GN 1/1 container, PP, 65 mm | C76: Gastromania | D76: Nádoba z polypropylenu, GN 1/1, 65 mm | STALGAST, Bufet | E76: Stalgast | F76: https://www.gastromania.cz/gastronadoby-polypropylenove/nadoba-z-polypropylenu-gn-1-1-65-mm-stalgast-bufet | G76: 215 | H76: CZK | I76: incl. | J76: 0.21 | K76: 1 | L76: per piece | M76: =IF(OR(G76="",J76="",K76=""),"",ROUND(IF(I76="incl.",G76/(1+J76),G76)/IF(L76="per pack",K76,1),2)) | N76: EXACT | O76: Lowest PP GN 1/1 65 listed; Cambro R-MP11065 234 CZK. (APS 82104 207 CZK named polycarbonate but listed under PP - conflicting, not used); price incl. 21% VAT as published in product data (current price, in stock) | P76: 2026-09-30 | Q76: =IFERROR(INDEX(Competitors!$N$2:$N$50,MATCH(C76,Competitors!$A$2:$A$50,0)),"no") | R76: =IF(AND(Q76="yes",OR(N76="EXACT",N76="CLOSE"),ISNUMBER(M76)),"yes","no")
A77: 18 | B77: GN 1/1 container, PP, 65 mm | C77: Gastrozone | D77: Pujadas gastro nádoba GN 1/1 530x325 mm polypropylen v=65 mm | E77: Pujadas | F77: https://www.gastrozone.cz/pujadas-gastro-nadoba-gn-1-1-530x325-mm-polypropylen-v-65-mm.html | G77: 443 | H77: CZK | I77: incl. | J77: 0.21 | K77: 1 | L77: per piece | M77: =IF(OR(G77="",J77="",K77=""),"",ROUND(IF(I77="incl.",G77/(1+J77),G77)/IF(L77="per pack",K77,1),2)) | N77: EXACT | O77: 366.12 CZK bez DPH; code 227705320; in stock (central warehouse) | P77: 2026-09-30 | Q77: =IFERROR(INDEX(Competitors!$N$2:$N$50,MATCH(C77,Competitors!$A$2:$A$50,0)),"no") | R77: =IF(AND(Q77="yes",OR(N77="EXACT",N77="CLOSE"),ISNUMBER(M77)),"yes","no")
A78: 18 | B78: GN 1/1 container, PP, 65 mm | C78: TOMGAST | D78: Gastronádoba polypropylenová GN 1/1 65 mm | E78: Cambro | F78: https://www.tomgast.cz/gastronadoba-polypropylenova-gn-1-1-65-mm/ | G78: 234 | H78: CZK | I78: incl. | J78: 0.21 | K78: 1 | L78: per piece | M78: =IF(OR(G78="",J78="",K78=""),"",ROUND(IF(I78="incl.",G78/(1+J78),G78)/IF(L78="per pack",K78,1),2)) | N78: EXACT | O78: Code R-MP11065; 193 CZK bez DPH; in stock | P78: 2026-09-30 | Q78: =IFERROR(INDEX(Competitors!$N$2:$N$50,MATCH(C78,Competitors!$A$2:$A$50,0)),"no") | R78: =IF(AND(Q78="yes",OR(N78="EXACT",N78="CLOSE"),ISNUMBER(M78)),"yes","no")
A79: 19 | B79: GN 1/3 container, PC, 100 mm | C79: GGM Gastro (CZ storefront) | D79: (12 ks) Gastronádoba GN 1/3 - polykarbonát - čirá - Výška: 100 mm | E79: GGM | F79: https://www.ggmgastro.com/cs-cz-czk/12-ks-gastronadoba-gn-1-3-polykarbonat-cira-vyska-100-mm-gpcp13100s | G79: 1606.13 | H79: CZK | I79: excl. | J79: 0.19 | K79: 12 | L79: per pack | M79: =IF(OR(G79="",J79="",K79=""),"",ROUND(IF(I79="incl.",G79/(1+J79),G79)/IF(L79="per pack",K79,1),2)) | N79: EXACT | O79: SKU GPCP13100S; CZ title says 'čirá' (clear) while the same SKU is 'schwarz' on the German/Austrian storefronts | P79: 2026-09-30 | Q79: =IFERROR(INDEX(Competitors!$N$2:$N$50,MATCH(C79,Competitors!$A$2:$A$50,0)),"no") | R79: =IF(AND(Q79="yes",OR(N79="EXACT",N79="CLOSE"),ISNUMBER(M79)),"yes","no")
A80: 19 | B80: GN 1/3 container, PC, 100 mm | C80: Gastro Novotný | D80: Gastronádoba PC 1/3 100 | F80: https://eshop.gastronovotny.cz/gastronadoba-pc-1-3-100--0835131/ | G80: 159 | H80: CZK | I80: excl. | J80: 0.21 | K80: 1 | L80: per piece | M80: =IF(OR(G80="",J80="",K80=""),"",ROUND(IF(I80="incl.",G80/(1+J80),G80)/IF(L80="per pack",K80,1),2)) | N80: EXACT | O80: Code 0835131; 192.39 CZK incl. VAT | P80: 2026-09-30 | Q80: =IFERROR(INDEX(Competitors!$N$2:$N$50,MATCH(C80,Competitors!$A$2:$A$50,0)),"no") | R80: =IF(AND(Q80="yes",OR(N80="EXACT",N80="CLOSE"),ISNUMBER(M80)),"yes","no")
A81: 19 | B81: GN 1/3 container, PC, 100 mm | C81: Gastromania | D81: Gastro nádoba GN 1/3 100 mm, polykarbonát | YATO, YG-00411 | E81: Yato | F81: https://www.gastromania.cz/gastronadoby-polykarbonatove/gastro-nadoba-gn-1-3-100-mm-polykarbonat-yato-yg-00411 | G81: 134 | H81: CZK | I81: incl. | J81: 0.21 | K81: 1 | L81: per piece | M81: =IF(OR(G81="",J81="",K81=""),"",ROUND(IF(I81="incl.",G81/(1+J81),G81)/IF(L81="per pack",K81,1),2)) | N81: EXACT | O81: Lowest PC GN 1/3 100; Stalgast Bufet PC 191, Cambro 229 CZK; price incl. 21% VAT as published in product data (current price, in stock) | P81: 2026-09-30 | Q81: =IFERROR(INDEX(Competitors!$N$2:$N$50,MATCH(C81,Competitors!$A$2:$A$50,0)),"no") | R81: =IF(AND(Q81="yes",OR(N81="EXACT",N81="CLOSE"),ISNUMBER(M81)),"yes","no")
A82: 19 | B82: GN 1/3 container, PC, 100 mm | C82: Gastrozone | D82: ARAVEN Gastronádoba GN 1/3, polykarbonát, hloubka: 100 mm, objem: 3,7 L | E82: Araven | F82: https://www.gastrozone.cz/araven-gn-nadoba-1-3-polykarbonat-hloubka-100-mm-objem-3-7-l.html | G82: 283 | H82: CZK | I82: incl. | J82: 0.21 | K82: 1 | L82: per piece | M82: =IF(OR(G82="",J82="",K82=""),"",ROUND(IF(I82="incl.",G82/(1+J82),G82)/IF(L82="per pack",K82,1),2)) | N82: EXACT | O82: 233.88 CZK bez DPH; lowest PC GN 1/3 100; alternatives APS 295, Pujadas 381 CZK | P82: 2026-09-30 | Q82: =IFERROR(INDEX(Competitors!$N$2:$N$50,MATCH(C82,Competitors!$A$2:$A$50,0)),"no") | R82: =IF(AND(Q82="yes",OR(N82="EXACT",N82="CLOSE"),ISNUMBER(M82)),"yes","no")
A83: 19 | B83: GN 1/3 container, PC, 100 mm | C83: TOMGAST | D83: Gastronádoba polykarbonátová GN 1/3 100 mm | E83: Cambro | F83: https://www.tomgast.cz/gastronadoba-polykarbonatova-gn-1-3-100-mm-2/ | G83: 229 | H83: CZK | I83: incl. | J83: 0.21 | K83: 1 | L83: per piece | M83: =IF(OR(G83="",J83="",K83=""),"",ROUND(IF(I83="incl.",G83/(1+J83),G83)/IF(L83="per pack",K83,1),2)) | N83: EXACT | O83: Code R-M213100; 189 CZK bez DPH | P83: 2026-09-30 | Q83: =IFERROR(INDEX(Competitors!$N$2:$N$50,MATCH(C83,Competitors!$A$2:$A$50,0)),"no") | R83: =IF(AND(Q83="yes",OR(N83="EXACT",N83="CLOSE"),ISNUMBER(M83)),"yes","no")
A84: 20 | B84: GN 1/2 container, PP, 150 mm | C84: GGM Gastro (CZ storefront) | D84: (12 ks) Gastronádoba GN 1/2 - polypropylen - mléčná - Výška: 150 mm | E84: GGM | F84: https://www.ggmgastro.com/cs-cz-czk/12-ks-gastronadoba-gn-1-2-polypropylen-mlecna-vyska-150-mm-gpp12150 | G84: 1216.71 | H84: CZK | I84: excl. | J84: 0.19 | K84: 12 | L84: per pack | M84: =IF(OR(G84="",J84="",K84=""),"",ROUND(IF(I84="incl.",G84/(1+J84),G84)/IF(L84="per pack",K84,1),2)) | N84: EXACT | O84: SKU GPP12150 | P84: 2026-09-30 | Q84: =IFERROR(INDEX(Competitors!$N$2:$N$50,MATCH(C84,Competitors!$A$2:$A$50,0)),"no") | R84: =IF(AND(Q84="yes",OR(N84="EXACT",N84="CLOSE"),ISNUMBER(M84)),"yes","no")
A85: 20 | B85: GN 1/2 container, PP, 150 mm | C85: Gastro Novotný | D85: Gastronádoba 1/2 150 polypropylen | F85: https://eshop.gastronovotny.cz/gastronadoba-1-2-150-polypropylen--1814705-15/ | G85: 140 | H85: CZK | I85: excl. | J85: 0.21 | K85: 1 | L85: per piece | M85: =IF(OR(G85="",J85="",K85=""),"",ROUND(IF(I85="incl.",G85/(1+J85),G85)/IF(L85="per pack",K85,1),2)) | N85: EXACT | O85: Code 1814705-15; 169.40 CZK incl. VAT | P85: 2026-09-30 | Q85: =IFERROR(INDEX(Competitors!$N$2:$N$50,MATCH(C85,Competitors!$A$2:$A$50,0)),"no") | R85: =IF(AND(Q85="yes",OR(N85="EXACT",N85="CLOSE"),ISNUMBER(M85)),"yes","no")
A86: 20 | B86: GN 1/2 container, PP, 150 mm | C86: Gastromania | D86: Nádoba z polypropylenu, GN 1/2, 150 mm | STALGAST, Bufet | E86: Stalgast | F86: https://www.gastromania.cz/gastronadoby-polypropylenove/nadoba-z-polypropylenu-gn-1-2-150-mm-stalgast-bufet | G86: 162 | H86: CZK | I86: incl. | J86: 0.21 | K86: 1 | L86: per piece | M86: =IF(OR(G86="",J86="",K86=""),"",ROUND(IF(I86="incl.",G86/(1+J86),G86)/IF(L86="per pack",K86,1),2)) | N86: EXACT | O86: Cambro R-MP12150 227 CZK; price incl. 21% VAT as published in product data (current price, in stock) | P86: 2026-09-30 | Q86: =IFERROR(INDEX(Competitors!$N$2:$N$50,MATCH(C86,Competitors!$A$2:$A$50,0)),"no") | R86: =IF(AND(Q86="yes",OR(N86="EXACT",N86="CLOSE"),ISNUMBER(M86)),"yes","no")
A87: 20 | B87: GN 1/2 container, PP, 150 mm | C87: Gastrozone | D87: gastro nádoba GN 1/2 polypropylen v=150 mm Pujadas | E87: Pujadas | F87: https://www.gastrozone.cz/gastro-nadoba-gn-1-2-polypropylen-v-150-mm-pujadas.html | G87: 334 | H87: CZK | I87: incl. | J87: 0.21 | K87: 1 | L87: per piece | M87: =IF(OR(G87="",J87="",K87=""),"",ROUND(IF(I87="incl.",G87/(1+J87),G87)/IF(L87="per pack",K87,1),2)) | N87: EXACT | O87: 276.03 CZK bez DPH; in stock | P87: 2026-09-30 | Q87: =IFERROR(INDEX(Competitors!$N$2:$N$50,MATCH(C87,Competitors!$A$2:$A$50,0)),"no") | R87: =IF(AND(Q87="yes",OR(N87="EXACT",N87="CLOSE"),ISNUMBER(M87)),"yes","no")
A88: 20 | B88: GN 1/2 container, PP, 150 mm | C88: TOMGAST | D88: Gastronádoba polypropylenová GN 1/2 150 mm | E88: Cambro | F88: https://www.tomgast.cz/gastronadoba-polypropylenova-gn-1-2-150-mm-2/ | G88: 227 | H88: CZK | I88: incl. | J88: 0.21 | K88: 1 | L88: per piece | M88: =IF(OR(G88="",J88="",K88=""),"",ROUND(IF(I88="incl.",G88/(1+J88),G88)/IF(L88="per pack",K88,1),2)) | N88: EXACT | O88: Code R-MP12150; 188 CZK bez DPH | P88: 2026-09-30 | Q88: =IFERROR(INDEX(Competitors!$N$2:$N$50,MATCH(C88,Competitors!$A$2:$A$50,0)),"no") | R88: =IF(AND(Q88="yes",OR(N88="EXACT",N88="CLOSE"),ISNUMBER(M88)),"yes","no")
A89: 21 | B89: GN 1/1 PC lid, standard | C89: GGM Gastro (CZ storefront) | D89: (6 ks) GN kryt GN 1/1 - Polykarbonát - Výška: 35 mm | E89: GGM | F89: https://www.ggmgastro.com/cs-cz-czk/6-ks-gn-kryt-gn-1-1-polykarbonat-vyska-35-mm-82001-6 | G89: 1679.15 | H89: CZK | I89: excl. | J89: 0.19 | K89: 6 | L89: per pack | M89: =IF(OR(G89="",J89="",K89=""),"",ROUND(IF(I89="incl.",G89/(1+J89),G89)/IF(L89="per pack",K89,1),2)) | N89: CLOSE | O89: PC lid 35 mm high (raised rather than flat standard lid) | P89: 2026-09-30 | Q89: =IFERROR(INDEX(Competitors!$N$2:$N$50,MATCH(C89,Competitors!$A$2:$A$50,0)),"no") | R89: =IF(AND(Q89="yes",OR(N89="EXACT",N89="CLOSE"),ISNUMBER(M89)),"yes","no")
A90: 21 | B90: GN 1/1 PC lid, standard | C90: Gastro Novotný | D90: Víko PC GN 1/1 | F90: https://eshop.gastronovotny.cz/viko-pc-gn-1-1--0835161/ | G90: 249 | H90: CZK | I90: excl. | J90: 0.21 | K90: 1 | L90: per piece | M90: =IF(OR(G90="",J90="",K90=""),"",ROUND(IF(I90="incl.",G90/(1+J90),G90)/IF(L90="per pack",K90,1),2)) | N90: EXACT | O90: Code 0835161; polycarbonate plain lid; 301.29 CZK incl. VAT | P90: 2026-09-30 | Q90: =IFERROR(INDEX(Competitors!$N$2:$N$50,MATCH(C90,Competitors!$A$2:$A$50,0)),"no") | R90: =IF(AND(Q90="yes",OR(N90="EXACT",N90="CLOSE"),ISNUMBER(M90)),"yes","no")
A91: 21 | B91: GN 1/1 PC lid, standard | C91: Gastromania | D91: Polykarbonátové víko, GN 1/1 | STALGAST, Bufet | E91: Stalgast | F91: https://www.gastromania.cz/vika-gn-polykarbonatove/polykarbonatove-viko-gn-1-1-stalgast-bufet | G91: 293 | H91: CZK | I91: incl. | J91: 0.21 | K91: 1 | L91: per piece | M91: =IF(OR(G91="",J91="",K91=""),"",ROUND(IF(I91="incl.",G91/(1+J91),G91)/IF(L91="per pack",K91,1),2)) | N91: EXACT | O91: Plain PC lid; Stalgast Premium clear lid 269 CZK (material not in name), Cambro R-M211001 357 CZK; price incl. 21% VAT as published in product data (current price, in stock) | P91: 2026-09-30 | Q91: =IFERROR(INDEX(Competitors!$N$2:$N$50,MATCH(C91,Competitors!$A$2:$A$50,0)),"no") | R91: =IF(AND(Q91="yes",OR(N91="EXACT",N91="CLOSE"),ISNUMBER(M91)),"yes","no")
A92: 21 | B92: GN 1/1 PC lid, standard | C92: Gastrozone | D92: ARAVEN Víko na gastronádobu GN 1/1, polykarbonát, volné | E92: Araven | F92: https://www.gastrozone.cz/araven-gn-deckel-1-1-polykarbonat-volny.html | G92: 380 | H92: CZK | I92: incl. | J92: 0.21 | K92: 1 | L92: per piece | M92: =IF(OR(G92="",J92="",K92=""),"",ROUND(IF(I92="incl.",G92/(1+J92),G92)/IF(L92="per pack",K92,1),2)) | N92: EXACT | O92: 314.05 CZK bez DPH; plain loose PC lid; APS PC lid 394 CZK | P92: 2026-09-30 | Q92: =IFERROR(INDEX(Competitors!$N$2:$N$50,MATCH(C92,Competitors!$A$2:$A$50,0)),"no") | R92: =IF(AND(Q92="yes",OR(N92="EXACT",N92="CLOSE"),ISNUMBER(M92)),"yes","no")
A93: 21 | B93: GN 1/1 PC lid, standard | C93: TOMGAST | D93: Víko pro gastronádobu GN 1/1 | E93: Cambro | F93: https://www.tomgast.cz/viko-pro-gastronadobu-gn-1-1/ | G93: 357 | H93: CZK | I93: incl. | J93: 0.21 | K93: 1 | L93: per piece | M93: =IF(OR(G93="",J93="",K93=""),"",ROUND(IF(I93="incl.",G93/(1+J93),G93)/IF(L93="per pack",K93,1),2)) | N93: EXACT | O93: Code R-M211001; material polykarbonát, plain lid, price per 1 piece; 295 CZK bez DPH | P93: 2026-09-30 | Q93: =IFERROR(INDEX(Competitors!$N$2:$N$50,MATCH(C93,Competitors!$A$2:$A$50,0)),"no") | R93: =IF(AND(Q93="yes",OR(N93="EXACT",N93="CLOSE"),ISNUMBER(M93)),"yes","no")
A94: 22 | B94: GN 1/6 container, PP, 100 mm | C94: GGM Gastro (CZ storefront) | D94: (12 ks) Polypropylenová nádoba GN 1/6 - Mléčná - Výška: 100 mm | E94: GGM | F94: https://www.ggmgastro.com/cs-cz-czk/12-ks-polypropylenova-nadoba-gn-1-6-mlecna-vyska-100-mm-gpp16100-12 | G94: 1070.67 | H94: CZK | I94: excl. | J94: 0.19 | K94: 12 | L94: per pack | M94: =IF(OR(G94="",J94="",K94=""),"",ROUND(IF(I94="incl.",G94/(1+J94),G94)/IF(L94="per pack",K94,1),2)) | N94: EXACT | P94: 2026-09-30 | Q94: =IFERROR(INDEX(Competitors!$N$2:$N$50,MATCH(C94,Competitors!$A$2:$A$50,0)),"no") | R94: =IF(AND(Q94="yes",OR(N94="EXACT",N94="CLOSE"),ISNUMBER(M94)),"yes","no")
A95: 22 | B95: GN 1/6 container, PP, 100 mm | C95: Gastro Novotný | D95: Gastronádoba 1/6 100 polypropylen | F95: https://eshop.gastronovotny.cz/gastronadoba-1-6-100-polypropylen/ | G95: 75 | H95: CZK | I95: excl. | J95: 0.21 | K95: 1 | L95: per piece | M95: =IF(OR(G95="",J95="",K95=""),"",ROUND(IF(I95="incl.",G95/(1+J95),G95)/IF(L95="per pack",K95,1),2)) | N95: EXACT | O95: Code 1814709-10; 90.75 CZK incl. VAT | P95: 2026-09-30 | Q95: =IFERROR(INDEX(Competitors!$N$2:$N$50,MATCH(C95,Competitors!$A$2:$A$50,0)),"no") | R95: =IF(AND(Q95="yes",OR(N95="EXACT",N95="CLOSE"),ISNUMBER(M95)),"yes","no")
A96: 22 | B96: GN 1/6 container, PP, 100 mm | C96: Gastromania | D96: Nádoba z polypropylenu, GN 1/6, 100 mm | STALGAST, Bufet | E96: Stalgast | F96: https://www.gastromania.cz/gastronadoby-polypropylenove/nadoba-z-polypropylenu-gn-1-6-100-mm-stalgast-bufet | G96: 57 | H96: CZK | I96: incl. | J96: 0.21 | K96: 1 | L96: per piece | M96: =IF(OR(G96="",J96="",K96=""),"",ROUND(IF(I96="incl.",G96/(1+J96),G96)/IF(L96="per pack",K96,1),2)) | N96: EXACT | O96: Cambro R-MP16100 94 CZK; price incl. 21% VAT as published in product data (current price, in stock) | P96: 2026-09-30 | Q96: =IFERROR(INDEX(Competitors!$N$2:$N$50,MATCH(C96,Competitors!$A$2:$A$50,0)),"no") | R96: =IF(AND(Q96="yes",OR(N96="EXACT",N96="CLOSE"),ISNUMBER(M96)),"yes","no")
A97: 22 | B97: GN 1/6 container, PP, 100 mm | C97: Gastrozone | D97: Pujadas gastro nádoba GN 1/6 176x162 mm polypropylen v=100 mm | E97: Pujadas | F97: https://www.gastrozone.cz/pujadas-gastro-nadoba-gn-1-6-176x162-mm-polypropylen-v-100-mm.html | G97: 130 | H97: CZK | I97: incl. | J97: 0.21 | K97: 1 | L97: per piece | M97: =IF(OR(G97="",J97="",K97=""),"",ROUND(IF(I97="incl.",G97/(1+J97),G97)/IF(L97="per pack",K97,1),2)) | N97: EXACT | O97: 107.44 CZK bez DPH; APS PP alternative 137 CZK | P97: 2026-09-30 | Q97: =IFERROR(INDEX(Competitors!$N$2:$N$50,MATCH(C97,Competitors!$A$2:$A$50,0)),"no") | R97: =IF(AND(Q97="yes",OR(N97="EXACT",N97="CLOSE"),ISNUMBER(M97)),"yes","no")
A98: 22 | B98: GN 1/6 container, PP, 100 mm | C98: TOMGAST | D98: Gastronádoba polypropylenová GN 1/6 100 mm | E98: Cambro | F98: https://www.tomgast.cz/gastronadoba-polypropylenova-gn-1-6-100-mm-2/ | G98: 94 | H98: CZK | I98: incl. | J98: 0.21 | K98: 1 | L98: per piece | M98: =IF(OR(G98="",J98="",K98=""),"",ROUND(IF(I98="incl.",G98/(1+J98),G98)/IF(L98="per pack",K98,1),2)) | N98: EXACT | O98: Code R-MP16100; 78 CZK bez DPH | P98: 2026-09-30 | Q98: =IFERROR(INDEX(Competitors!$N$2:$N$50,MATCH(C98,Competitors!$A$2:$A$50,0)),"no") | R98: =IF(AND(Q98="yes",OR(N98="EXACT",N98="CLOSE"),ISNUMBER(M98)),"yes","no")
A99: 23 | B99: GN 1/9 container, PP, 100 mm | C99: GGM Gastro (CZ storefront) | D99: (12 ks) Polypropylenová nádoba GN 1/9 - Mléčná - Výška: 100 mm | E99: GGM | F99: https://www.ggmgastro.com/cs-cz-czk/12-ks-polypropylenova-nadoba-gn-1-9-mlecna-vyska-100-mm-gpp19100-12 | G99: 997.66 | H99: CZK | I99: excl. | J99: 0.19 | K99: 12 | L99: per pack | M99: =IF(OR(G99="",J99="",K99=""),"",ROUND(IF(I99="incl.",G99/(1+J99),G99)/IF(L99="per pack",K99,1),2)) | N99: EXACT | P99: 2026-09-30 | Q99: =IFERROR(INDEX(Competitors!$N$2:$N$50,MATCH(C99,Competitors!$A$2:$A$50,0)),"no") | R99: =IF(AND(Q99="yes",OR(N99="EXACT",N99="CLOSE"),ISNUMBER(M99)),"yes","no")
A100: 23 | B100: GN 1/9 container, PP, 100 mm | C100: Gastromania | D100: Nádoba z polypropylénu GN 1/9, 100 mm | STALGAST, Bufet Safe | E100: Stalgast | F100: https://www.gastromania.cz/gastronadoby-polypropylenove/nadoba-z-polypropylenu-gn-1-9-100-mm-stalgast-bufet-safe | G100: 83 | H100: CZK | I100: incl. | J100: 0.21 | K100: 1 | L100: per piece | M100: =IF(OR(G100="",J100="",K100=""),"",ROUND(IF(I100="incl.",G100/(1+J100),G100)/IF(L100="per pack",K100,1),2)) | N100: EXACT | O100: HENDI Profi Line PP 95, Cambro 105 CZK; price incl. 21% VAT as published in product data (current price, in stock) | P100: 2026-09-30 | Q100: =IFERROR(INDEX(Competitors!$N$2:$N$50,MATCH(C100,Competitors!$A$2:$A$50,0)),"no") | R100: =IF(AND(Q100="yes",OR(N100="EXACT",N100="CLOSE"),ISNUMBER(M100)),"yes","no")
...

Sheet Summary
A1: Basket item no. | B1: Item description | C1: Qualifying prices (EXACT+CLOSE, counted competitors) | D1: Min net/pc CZK | E1: Median net/pc CZK | F1: Max net/pc CZK | G1: Competitors in statistics | H1: APPROX observations (not in stats) | I1: All observations (any competitor)
A2: 1 | B2: GN 1/1 polycarbonate container, 65 mm deep | C2: =COUNTIFS(Prices!$A$2:$A$600,A2,Prices!$R$2:$R$600,"yes") | D2: {=IF(C2=0,"",MIN(IF((Prices!$A$2:$A$600=A2)*(Prices!$R$2:$R$600="yes"),Prices!$M$2:$M$600)))} | E2: {=IF(C2=0,"",MEDIAN(IF((Prices!$A$2:$A$600=A2)*(Prices!$R$2:$R$600="yes"),Prices!$M$2:$M$600)))} | F2: {=IF(C2=0,"",MAX(IF((Prices!$A$2:$A$600=A2)*(Prices!$R$2:$R$600="yes"),Prices!$M$2:$M$600)))} | G2: {=IF(C2=0,"",_xlfn.TEXTJOIN(", ",TRUE,IF((Prices!$A$2:$A$600=A2)*(Prices!$R$2:$R$600="yes"),Prices!$C$2:$C$600,"")))} | H2: =COUNTIFS(Prices!$A$2:$A$600,A2,Prices!$N$2:$N$600,"APPROX") | I2: =COUNTIFS(Prices!$A$2:$A$600,A2)
A3: 2 | B3: GN 1/2 polycarbonate container, 150 mm deep | C3: =COUNTIFS(Prices!$A$2:$A$600,A3,Prices!$R$2:$R$600,"yes") | D3: {=IF(C3=0,"",MIN(IF((Prices!$A$2:$A$600=A3)*(Prices!$R$2:$R$600="yes"),Prices!$M$2:$M$600)))} | E3: {=IF(C3=0,"",MEDIAN(IF((Prices!$A$2:$A$600=A3)*(Prices!$R$2:$R$600="yes"),Prices!$M$2:$M$600)))} | F3: {=IF(C3=0,"",MAX(IF((Prices!$A$2:$A$600=A3)*(Prices!$R$2:$R$600="yes"),Prices!$M$2:$M$600)))} | G3: {=IF(C3=0,"",_xlfn.TEXTJOIN(", ",TRUE,IF((Prices!$A$2:$A$600=A3)*(Prices!$R$2:$R$600="yes"),Prices!$C$2:$C$600,"")))} | H3: =COUNTIFS(Prices!$A$2:$A$600,A3,Prices!$N$2:$N$600,"APPROX") | I3: =COUNTIFS(Prices!$A$2:$A$600,A3)
A4: 3 | B4: GN 1/3 polypropylene container, 100 mm deep | C4: =COUNTIFS(Prices!$A$2:$A$600,A4,Prices!$R$2:$R$600,"yes") | D4: {=IF(C4=0,"",MIN(IF((Prices!$A$2:$A$600=A4)*(Prices!$R$2:$R$600="yes"),Prices!$M$2:$M$600)))} | E4: {=IF(C4=0,"",MEDIAN(IF((Prices!$A$2:$A$600=A4)*(Prices!$R$2:$R$600="yes"),Prices!$M$2:$M$600)))} | F4: {=IF(C4=0,"",MAX(IF((Prices!$A$2:$A$600=A4)*(Prices!$R$2:$R$600="yes"),Prices!$M$2:$M$600)))} | G4: {=IF(C4=0,"",_xlfn.TEXTJOIN(", ",TRUE,IF((Prices!$A$2:$A$600=A4)*(Prices!$R$2:$R$600="yes"),Prices!$C$2:$C$600,"")))} | H4: =COUNTIFS(Prices!$A$2:$A$600,A4,Prices!$N$2:$N$600,"APPROX") | I4: =COUNTIFS(Prices!$A$2:$A$600,A4)
A5: 4 | B5: GN 1/1 polypropylene lid | C5: =COUNTIFS(Prices!$A$2:$A$600,A5,Prices!$R$2:$R$600,"yes") | D5: {=IF(C5=0,"",MIN(IF((Prices!$A$2:$A$600=A5)*(Prices!$R$2:$R$600="yes"),Prices!$M$2:$M$600)))} | E5: {=IF(C5=0,"",MEDIAN(IF((Prices!$A$2:$A$600=A5)*(Prices!$R$2:$R$600="yes"),Prices!$M$2:$M$600)))} | F5: {=IF(C5=0,"",MAX(IF((Prices!$A$2:$A$600=A5)*(Prices!$R$2:$R$600="yes"),Prices!$M$2:$M$600)))} | G5: {=IF(C5=0,"",_xlfn.TEXTJOIN(", ",TRUE,IF((Prices!$A$2:$A$600=A5)*(Prices!$R$2:$R$600="yes"),Prices!$C$2:$C$600,"")))} | H5: =COUNTIFS(Prices!$A$2:$A$600,A5,Prices!$N$2:$N$600,"APPROX") | I5: =COUNTIFS(Prices!$A$2:$A$600,A5)
A6: 5 | B6: Squeeze bottle 500 ml, polypropylene, single tip | C6: =COUNTIFS(Prices!$A$2:$A$600,A6,Prices!$R$2:$R$600,"yes") | D6: {=IF(C6=0,"",MIN(IF((Prices!$A$2:$A$600=A6)*(Prices!$R$2:$R$600="yes"),Prices!$M$2:$M$600)))} | E6: {=IF(C6=0,"",MEDIAN(IF((Prices!$A$2:$A$600=A6)*(Prices!$R$2:$R$600="yes"),Prices!$M$2:$M$600)))} | F6: {=IF(C6=0,"",MAX(IF((Prices!$A$2:$A$600=A6)*(Prices!$R$2:$R$600="yes"),Prices!$M$2:$M$600)))} | G6: {=IF(C6=0,"",_xlfn.TEXTJOIN(", ",TRUE,IF((Prices!$A$2:$A$600=A6)*(Prices!$R$2:$R$600="yes"),Prices!$C$2:$C$600,"")))} | H6: =COUNTIFS(Prices!$A$2:$A$600,A6,Prices!$N$2:$N$600,"APPROX") | I6: =COUNTIFS(Prices!$A$2:$A$600,A6)
A7: 6 | B7: Squeeze bottle 1000 ml, polypropylene, single tip | C7: =COUNTIFS(Prices!$A$2:$A$600,A7,Prices!$R$2:$R$600,"yes") | D7: {=IF(C7=0,"",MIN(IF((Prices!$A$2:$A$600=A7)*(Prices!$R$2:$R$600="yes"),Prices!$M$2:$M$600)))} | E7: {=IF(C7=0,"",MEDIAN(IF((Prices!$A$2:$A$600=A7)*(Prices!$R$2:$R$600="yes"),Prices!$M$2:$M$600)))} | F7: {=IF(C7=0,"",MAX(IF((Prices!$A$2:$A$600=A7)*(Prices!$R$2:$R$600="yes"),Prices!$M$2:$M$600)))} | G7: {=IF(C7=0,"",_xlfn.TEXTJOIN(", ",TRUE,IF((Prices!$A$2:$A$600=A7)*(Prices!$R$2:$R$600="yes"),Prices!$C$2:$C$600,"")))} | H7: =COUNTIFS(Prices!$A$2:$A$600,A7,Prices!$N$2:$N$600,"APPROX") | I7: =COUNTIFS(Prices!$A$2:$A$600,A7)
A8: 7 | B8: Squeeze bottle 500 ml with triple tip | C8: =COUNTIFS(Prices!$A$2:$A$600,A8,Prices!$R$2:$R$600,"yes") | D8: {=IF(C8=0,"",MIN(IF((Prices!$A$2:$A$600=A8)*(Prices!$R$2:$R$600="yes"),Prices!$M$2:$M$600)))} | E8: {=IF(C8=0,"",MEDIAN(IF((Prices!$A$2:$A$600=A8)*(Prices!$R$2:$R$600="yes"),Prices!$M$2:$M$600)))} | F8: {=IF(C8=0,"",MAX(IF((Prices!$A$2:$A$600=A8)*(Prices!$R$2:$R$600="yes"),Prices!$M$2:$M$600)))} | G8: {=IF(C8=0,"",_xlfn.TEXTJOIN(", ",TRUE,IF((Prices!$A$2:$A$600=A8)*(Prices!$R$2:$R$600="yes"),Prices!$C$2:$C$600,"")))} | H8: =COUNTIFS(Prices!$A$2:$A$600,A8,Prices!$N$2:$N$600,"APPROX") | I8: =COUNTIFS(Prices!$A$2:$A$600,A8)
A9: 8 | B9: Ketchup/sauce pump dispenser with stand | C9: =COUNTIFS(Prices!$A$2:$A$600,A9,Prices!$R$2:$R$600,"yes") | D9: {=IF(C9=0,"",MIN(IF((Prices!$A$2:$A$600=A9)*(Prices!$R$2:$R$600="yes"),Prices!$M$2:$M$600)))} | E9: {=IF(C9=0,"",MEDIAN(IF((Prices!$A$2:$A$600=A9)*(Prices!$R$2:$R$600="yes"),Prices!$M$2:$M$600)))} | F9: {=IF(C9=0,"",MAX(IF((Prices!$A$2:$A$600=A9)*(Prices!$R$2:$R$600="yes"),Prices!$M$2:$M$600)))} | G9: {=IF(C9=0,"",_xlfn.TEXTJOIN(", ",TRUE,IF((Prices!$A$2:$A$600=A9)*(Prices!$R$2:$R$600="yes"),Prices!$C$2:$C$600,"")))} | H9: =COUNTIFS(Prices!$A$2:$A$600,A9,Prices!$N$2:$N$600,"APPROX") | I9: =COUNTIFS(Prices!$A$2:$A$600,A9)
A10: 9 | B10: HACCP PE cutting board 530 x 325 x 20 mm (GN 1/1) | C10: =COUNTIFS(Prices!$A$2:$A$600,A10,Prices!$R$2:$R$600,"yes") | D10: {=IF(C10=0,"",MIN(IF((Prices!$A$2:$A$600=A10)*(Prices!$R$2:$R$600="yes"),Prices!$M$2:$M$600)))} | E10: {=IF(C10=0,"",MEDIAN(IF((Prices!$A$2:$A$600=A10)*(Prices!$R$2:$R$600="yes"),Prices!$M$2:$M$600)))} | F10: {=IF(C10=0,"",MAX(IF((Prices!$A$2:$A$600=A10)*(Prices!$R$2:$R$600="yes"),Prices!$M$2:$M$600)))} | G10: {=IF(C10=0,"",_xlfn.TEXTJOIN(", ",TRUE,IF((Prices!$A$2:$A$600=A10)*(Prices!$R$2:$R$600="yes"),Prices!$C$2:$C$600,"")))} | H10: =COUNTIFS(Prices!$A$2:$A$600,A10,Prices!$N$2:$N$600,"APPROX") | I10: =COUNTIFS(Prices!$A$2:$A$600,A10)
A11: 10 | B11: HACCP PE cutting board 600 x 400 x 20 mm | C11: =COUNTIFS(Prices!$A$2:$A$600,A11,Prices!$R$2:$R$600,"yes") | D11: {=IF(C11=0,"",MIN(IF((Prices!$A$2:$A$600=A11)*(Prices!$R$2:$R$600="yes"),Prices!$M$2:$M$600)))} | E11: {=IF(C11=0,"",MEDIAN(IF((Prices!$A$2:$A$600=A11)*(Prices!$R$2:$R$600="yes"),Prices!$M$2:$M$600)))} | F11: {=IF(C11=0,"",MAX(IF((Prices!$A$2:$A$600=A11)*(Prices!$R$2:$R$600="yes"),Prices!$M$2:$M$600)))} | G11: {=IF(C11=0,"",_xlfn.TEXTJOIN(", ",TRUE,IF((Prices!$A$2:$A$600=A11)*(Prices!$R$2:$R$600="yes"),Prices!$C$2:$C$600,"")))} | H11: =COUNTIFS(Prices!$A$2:$A$600,A11,Prices!$N$2:$N$600,"APPROX") | I11: =COUNTIFS(Prices!$A$2:$A$600,A11)
A12: 11 | B12: HACCP PE cutting board 300 x 200 x 10 mm | C12: =COUNTIFS(Prices!$A$2:$A$600,A12,Prices!$R$2:$R$600,"yes") | D12: {=IF(C12=0,"",MIN(IF((Prices!$A$2:$A$600=A12)*(Prices!$R$2:$R$600="yes"),Prices!$M$2:$M$600)))} | E12: {=IF(C12=0,"",MEDIAN(IF((Prices!$A$2:$A$600=A12)*(Prices!$R$2:$R$600="yes"),Prices!$M$2:$M$600)))} | F12: {=IF(C12=0,"",MAX(IF((Prices!$A$2:$A$600=A12)*(Prices!$R$2:$R$600="yes"),Prices!$M$2:$M$600)))} | G12: {=IF(C12=0,"",_xlfn.TEXTJOIN(", ",TRUE,IF((Prices!$A$2:$A$600=A12)*(Prices!$R$2:$R$600="yes"),Prices!$C$2:$C$600,"")))} | H12: =COUNTIFS(Prices!$A$2:$A$600,A12,Prices!$N$2:$N$600,"APPROX") | I12: =COUNTIFS(Prices!$A$2:$A$600,A12)
A13: 12 | B13: Pizza dough proofing box 600 x 400 x 100 mm, polypropylene | C13: =COUNTIFS(Prices!$A$2:$A$600,A13,Prices!$R$2:$R$600,"yes") | D13: {=IF(C13=0,"",MIN(IF((Prices!$A$2:$A$600=A13)*(Prices!$R$2:$R$600="yes"),Prices!$M$2:$M$600)))} | E13: {=IF(C13=0,"",MEDIAN(IF((Prices!$A$2:$A$600=A13)*(Prices!$R$2:$R$600="yes"),Prices!$M$2:$M$600)))} | F13: {=IF(C13=0,"",MAX(IF((Prices!$A$2:$A$600=A13)*(Prices!$R$2:$R$600="yes"),Prices!$M$2:$M$600)))} | G13: {=IF(C13=0,"",_xlfn.TEXTJOIN(", ",TRUE,IF((Prices!$A$2:$A$600=A13)*(Prices!$R$2:$R$600="yes"),Prices!$C$2:$C$600,"")))} | H13: =COUNTIFS(Prices!$A$2:$A$600,A13,Prices!$N$2:$N$600,"APPROX") | I13: =COUNTIFS(Prices!$A$2:$A$600,A13)
... A35: 34 | B35: Dough box 400x300x100 mm, PP, without lid | C35: =COUNTIFS(Prices!$A$2:$A$600,A35,Prices!$R$2:$R$600,"yes") | D35: {=IF(C35=0,"",MIN(IF((Prices!$A$2:$A$600=A35)*(Prices!$R$2:$R$600="yes"),Prices!$M$2:$M$600)))} | E35: {=IF(C35=0,"",MEDIAN(IF((Prices!$A$2:$A$600=A35)*(Prices!$R$2:$R$600="yes"),Prices!$M$2:$M$600)))} | F35: {=IF(C35=0,"",MAX(IF((Prices!$A$2:$A$600=A35)*(Prices!$R$2:$R$600="yes"),Prices!$M$2:$M$600)))} | G35: {=IF(C35=0,"",_xlfn.TEXTJOIN(", ",TRUE,IF((Prices!$A$2:$A$600=A35)*(Prices!$R$2:$R$600="yes"),Prices!$C$2:$C$600,"")))} | H35: =COUNTIFS(Prices!$A$2:$A$600,A35,Prices!$N$2:$N$600,"APPROX") | I35: =COUNTIFS(Prices!$A$2:$A$600,A35)
A37: Notes:
A38: Statistics use only primary observations with match quality EXACT or CLOSE from competitors marked Counted = yes on the Competitors sheet (max one observation per competitor per item).
A39: Net price per piece = listed price / (1 + VAT rate) when the listed price includes VAT, divided by pack size when the price is per pack. Czech VAT 21%.
A40: Blank statistics = no qualifying observation. APPROX matches are listed on the Prices sheet but excluded from statistics.
A41: Where several products matched equally well, the lowest current 1-unit price was taken as primary; alternatives, promotions and pack sizes are in the Prices notes.
A42: GGM Gastro prices are shown net on its CZ storefront (gross uses German 19% VAT, recorded in the VAT-rate column); net per piece is taken directly from the displayed net price. All other shops use Czech 21% VAT.
A43: Prices checked 2026-09-30. All prices in CZK from Czech storefronts. MAKRO (login-only prices) and A GASTRO (site blocked) are not counted - see Not accessible.
A44: Items 18-34 (additional variants) added 2026-09-30 for the same competitors; same rules (EXACT/CLOSE only in statistics, net = gross/1.21 for Czech VAT, GGM uses its own net CZK).

Sheet Not accessible
A1: Competitor | B1: URL | C1: Reason | D1: Date checked | E1: Notes
A2: MAKRO Czechia | B2: https://sortiment.makro.cz/shop/search?q=gastron%C3%A1doba%20polykarbon%C3%A1t | C2: Login required: every product tile shows "Pro zobrazení cen se prosím přihlaste" (please log in to view prices). Checked GN containers (METRO PROFESSIONAL, APS, Hendi). | D2: 2026-09-30 | E2: Competitor not counted. Homepage www.makro.cz returns HTTP 403 to non-browser clients.
A3: MAKRO Czechia | B3: https://www.makro.cz/metro/services/idamstream/login?returnUrl=/ | C3: Price display link on homepage product teasers ("Přihlaste se pro zobrazení ceny") leads to login. | D3: 2026-09-30
A4: A GASTRO | B4: https://agastro.cz/ | C4: Access error: Cloudflare bot challenge / HTTP 403 on all pages (home, robots.txt, sitemap.xml, category pages), in scripts, a full browser and the web-fetch tool. | D4: 2026-09-30 | E4: Competitor not counted. Search snippets only (e.g. https://agastro.cz/gastronadoby-vacbox/, https://agastro.cz/detail/21689/) - not used as price evidence.
A5: A GASTRO | B5: https://agastro.cz/gastronadoby-vacbox/ | C5: HTTP 403 (Cloudflare) - category page found via search engine could not be opened. | D5: 2026-09-30
A6: GGM Gastro (CZ storefront) | B6: https://www.ggmgastro.com/cs-cz-czk/search?q=polykarbon%C3%A1t | C6: Search results are JavaScript-loaded and the site returns "403 FORBIDDEN - This request was blocked" to headless browsers. | D6: 2026-09-30 | E6: Worked around: products located via the public product sitemap and read in a full (non-headless) browser; prices recorded from product pages.
A7: GGM Gastro (CZ storefront) | B7: https://www.ggmgastro.com/cs-cz-czk/6-ks-stlacovaci-lahev-na-omacky-1-020-ml-o-80-mm-se-sroubovacim-uzaverem-a-uzaviraci-cepickou-transparentni-93259-6 | C7: Product shows "Není k dispozici pro vybranou zemi dodání" (not available for the selected delivery country). | D7: 2026-09-30 | E7: Not used as primary observation for item 6.
A8: Gastromania | B8: https://www.gastromania.cz/products/search/language:cze?q=polykarbon%C3%A1t+GN+1%2F1 | C8: Prices are injected by JavaScript (empty in raw HTML). | D8: 2026-09-30 | E8: Worked around: read with a rendering browser; all recorded prices verified on rendered product pages/listings.
