Workbook

Sheet Compare
B2: YES Gastro market comparison
B3: Original benchmark basket plus Austria and Czechia additions; Austria/Germany expansion and corrections of 2 Oct 2026; GN container and lid expansion of 2 Oct 2026 (45 further GN variants, AT/DE/CZ/SK/RO; see Change log). Net prices per piece.
B5: Statistic | C5: Median | D5: View | E5: Net per piece EUR | G5: Match | H5: EXACT + CLOSE | J5: Product detail
J6: GN 1/1 PC container, 65 mm
B7: =IF(E5="Local prices","Local net prices per piece. Currency differs by country.","EUR net prices per piece. Erste Bank mid-rates published 30 Sep 2026 at 18:00 CEST.") -> EUR net prices per piece. Erste Bank mid-rates published 30 Sep 2026 at 18:00 CEST.
B8: A dash means no qualifying price. Green marks the lowest available EUR price for each product.
J9: Net price per piece in EUR
B10: Product | C10: Hungary | D10: Romania | E10: Austria | F10: Germany | G10: Czech | H10: Slovakia
C11: =IF($E$5="Local prices","HUF net/pc","EUR net/pc") -> EUR net/pc | D11: =IF($E$5="Local prices","RON net/pc","EUR net/pc") -> EUR net/pc | E11: =IF($E$5="Local prices","EUR net/pc","EUR net/pc") -> EUR net/pc | F11: =IF($E$5="Local prices","EUR net/pc","EUR net/pc") -> EUR net/pc | G11: =IF($E$5="Local prices","CZK net/pc","EUR net/pc") -> EUR net/pc | H11: =IF($E$5="Local prices","EUR net/pc","EUR net/pc") -> EUR net/pc | J11: Market | K11: Minimum | L11: Median | M11: Maximum
B12: GN 1/1 PC container, 65 mm | C12: =IF(IF($E$5="Local prices",COUNTIFS(Offers!$B$7:$B$3000,$B12,Offers!$C$7:$C$3000,C$10,Offers!$AH$7:$AH$3000,"yes"),COUNTIFS(Offers!$B$7:$B$3000,$B12,Offers!$C$7:$C$3000,C$10,Offers!$AI$7:$AI$3000,"yes"))=0,"—",SUMIFS(Review!$O$7:$O$600,Review!$B$7:$B$600,$B12,Review!$C$7:$C$600,C$10)) -> 10.912021 | D12: =IF(IF($E$5="Local prices",COUNTIFS(Offers!$B$7:$B$3000,$B12,Offers!$C$7:$C$3000,D$10,Offers!$AH$7:$AH$3000,"yes"),COUNTIFS(Offers!$B$7:$B$3000,$B12,Offers!$C$7:$C$3000,D$10,Offers!$AI$7:$AI$3000,"yes"))=0,"—",SUMIFS(Review!$O$7:$O$600,Review!$B$7:$B$600,$B12,Review!$C$7:$C$600,D$10)) -> 10.029101 | E12: =IF(IF($E$5="Local prices",COUNTIFS(Offers!$B$7:$B$3000,$B12,Offers!$C$7:$C$3000,E$10,Offers!$AH$7:$AH$3000,"yes"),COUNTIFS(Offers!$B$7:$B$3000,$B12,Offers!$C$7:$C$3000,E$10,Offers!$AI$7:$AI$3000,"yes"))=0,"—",SUMIFS(Review!$O$7:$O$600,Review!$B$7:$B$600,$B12,Review!$C$7:$C$600,E$10)) -> 14.07 | F12: =IF(IF($E$5="Local prices",COUNTIFS(Offers!$B$7:$B$3000,$B12,Offers!$C$7:$C$3000,F$10,Offers!$AH$7:$AH$3000,"yes"),COUNTIFS(Offers!$B$7:$B$3000,$B12,Offers!$C$7:$C$3000,F$10,Offers!$AI$7:$AI$3000,"yes"))=0,"—",SUMIFS(Review!$O$7:$O$600,Review!$B$7:$B$600,$B12,Review!$C$7:$C$600,F$10)) -> 13.11 | G12: =IF(IF($E$5="Local prices",COUNTIFS(Offers!$B$7:$B$3000,$B12,Offers!$C$7:$C$3000,G$10,Offers!$AH$7:$AH$3000,"yes"),COUNTIFS(Offers!$B$7:$B$3000,$B12,Offers!$C$7:$C$3000,G$10,Offers!$AI$7:$AI$3000,"yes"))=0,"—",SUMIFS(Review!$O$7:$O$600,Review!$B$7:$B$600,$B12,Review!$C$7:$C$600,G$10)) -> 12.148079 | H12: =IF(IF($E$5="Local prices",COUNTIFS(Offers!$B$7:$B$3000,$B12,Offers!$C$7:$C$3000,H$10,Offers!$AH$7:$AH$3000,"yes"),COUNTIFS(Offers!$B$7:$B$3000,$B12,Offers!$C$7:$C$3000,H$10,Offers!$AI$7:$AI$3000,"yes"))=0,"—",SUMIFS(Review!$O$7:$O$600,Review!$B$7:$B$600,$B12,Review!$C$7:$C$600,H$10)) -> 18.467643 | J12: Hungary | K12: =IF(COUNTIFS(Offers!$B$7:$B$3000,$J$6,Offers!$C$7:$C$3000,$J12,Offers!$AI$7:$AI$3000,"yes")=0,"—",SUMIFS(Review!$I$7:$I$600,Review!$B$7:$B$600,$J$6,Review!$C$7:$C$600,$J12)) -> 6.883177 | L12: =IF(COUNTIFS(Offers!$B$7:$B$3000,$J$6,Offers!$C$7:$C$3000,$J12,Offers!$AI$7:$AI$3000,"yes")=0,"—",SUMIFS(Review!$J$7:$J$600,Review!$B$7:$B$600,$J$6,Review!$C$7:$C$600,$J12)) -> 10.912021 | M12: =IF(COUNTIFS(Offers!$B$7:$B$3000,$J$6,Offers!$C$7:$C$3000,$J12,Offers!$AI$7:$AI$3000,"yes")=0,"—",SUMIFS(Review!$K$7:$K$600,Review!$B$7:$B$600,$J$6,Review!$C$7:$C$600,$J12)) -> 19.764552
B13: GN 1/2 PC container, 150 mm | C13: =IF(IF($E$5="Local prices",COUNTIFS(Offers!$B$7:$B$3000,$B13,Offers!$C$7:$C$3000,C$10,Offers!$AH$7:$AH$3000,"yes"),COUNTIFS(Offers!$B$7:$B$3000,$B13,Offers!$C$7:$C$3000,C$10,Offers!$AI$7:$AI$3000,"yes"))=0,"—",SUMIFS(Review!$O$7:$O$600,Review!$B$7:$B$600,$B13,Review!$C$7:$C$600,C$10)) -> 9.607768 | D13: =IF(IF($E$5="Local prices",COUNTIFS(Offers!$B$7:$B$3000,$B13,Offers!$C$7:$C$3000,D$10,Offers!$AH$7:$AH$3000,"yes"),COUNTIFS(Offers!$B$7:$B$3000,$B13,Offers!$C$7:$C$3000,D$10,Offers!$AI$7:$AI$3000,"yes"))=0,"—",SUMIFS(Review!$O$7:$O$600,Review!$B$7:$B$600,$B13,Review!$C$7:$C$600,D$10)) -> 10.87228 | E13: =IF(IF($E$5="Local prices",COUNTIFS(Offers!$B$7:$B$3000,$B13,Offers!$C$7:$C$3000,E$10,Offers!$AH$7:$AH$3000,"yes"),COUNTIFS(Offers!$B$7:$B$3000,$B13,Offers!$C$7:$C$3000,E$10,Offers!$AI$7:$AI$3000,"yes"))=0,"—",SUMIFS(Review!$O$7:$O$600,Review!$B$7:$B$600,$B13,Review!$C$7:$C$600,E$10)) -> 10.9 | F13: =IF(IF($E$5="Local prices",COUNTIFS(Offers!$B$7:$B$3000,$B13,Offers!$C$7:$C$3000,F$10,Offers!$AH$7:$AH$3000,"yes"),COUNTIFS(Offers!$B$7:$B$3000,$B13,Offers!$C$7:$C$3000,F$10,Offers!$AI$7:$AI$3000,"yes"))=0,"—",SUMIFS(Review!$O$7:$O$600,Review!$B$7:$B$600,$B13,Review!$C$7:$C$600,F$10)) -> 9.35 | G13: =IF(IF($E$5="Local prices",COUNTIFS(Offers!$B$7:$B$3000,$B13,Offers!$C$7:$C$3000,G$10,Offers!$AH$7:$AH$3000,"yes"),COUNTIFS(Offers!$B$7:$B$3000,$B13,Offers!$C$7:$C$3000,G$10,Offers!$AI$7:$AI$3000,"yes"))=0,"—",SUMIFS(Review!$O$7:$O$600,Review!$B$7:$B$600,$B13,Review!$C$7:$C$600,G$10)) -> 10.509296 | H13: =IF(IF($E$5="Local prices",COUNTIFS(Offers!$B$7:$B$3000,$B13,Offers!$C$7:$C$3000,H$10,Offers!$AH$7:$AH$3000,"yes"),COUNTIFS(Offers!$B$7:$B$3000,$B13,Offers!$C$7:$C$3000,H$10,Offers!$AI$7:$AI$3000,"yes"))=0,"—",SUMIFS(Review!$O$7:$O$600,Review!$B$7:$B$600,$B13,Review!$C$7:$C$600,H$10)) -> 15.688821 | J13: Romania | K13: =IF(COUNTIFS(Offers!$B$7:$B$3000,$J$6,Offers!$C$7:$C$3000,$J13,Offers!$AI$7:$AI$3000,"yes")=0,"—",SUMIFS(Review!$I$7:$I$600,Review!$B$7:$B$600,$J$6,Review!$C$7:$C$600,$J13)) -> 8 | L13: =IF(COUNTIFS(Offers!$B$7:$B$3000,$J$6,Offers!$C$7:$C$3000,$J13,Offers!$AI$7:$AI$3000,"yes")=0,"—",SUMIFS(Review!$J$7:$J$600,Review!$B$7:$B$600,$J$6,Review!$C$7:$C$600,$J13)) -> 10.029101 | M13: =IF(COUNTIFS(Offers!$B$7:$B$3000,$J$6,Offers!$C$7:$C$3000,$J13,Offers!$AI$7:$AI$3000,"yes")=0,"—",SUMIFS(Review!$K$7:$K$600,Review!$B$7:$B$600,$J$6,Review!$C$7:$C$600,$J13)) -> 17.413081
B14: GN 1/3 PP container, 100 mm | C14: =IF(IF($E$5="Local prices",COUNTIFS(Offers!$B$7:$B$3000,$B14,Offers!$C$7:$C$3000,C$10,Offers!$AH$7:$AH$3000,"yes"),COUNTIFS(Offers!$B$7:$B$3000,$B14,Offers!$C$7:$C$3000,C$10,Offers!$AI$7:$AI$3000,"yes"))=0,"—",SUMIFS(Review!$O$7:$O$600,Review!$B$7:$B$600,$B14,Review!$C$7:$C$600,C$10)) -> 4.247357 | D14: =IF(IF($E$5="Local prices",COUNTIFS(Offers!$B$7:$B$3000,$B14,Offers!$C$7:$C$3000,D$10,Offers!$AH$7:$AH$3000,"yes"),COUNTIFS(Offers!$B$7:$B$3000,$B14,Offers!$C$7:$C$3000,D$10,Offers!$AI$7:$AI$3000,"yes"))=0,"—",SUMIFS(Review!$O$7:$O$600,Review!$B$7:$B$600,$B14,Review!$C$7:$C$600,D$10)) -> 6.404376 | E14: =IF(IF($E$5="Local prices",COUNTIFS(Offers!$B$7:$B$3000,$B14,Offers!$C$7:$C$3000,E$10,Offers!$AH$7:$AH$3000,"yes"),COUNTIFS(Offers!$B$7:$B$3000,$B14,Offers!$C$7:$C$3000,E$10,Offers!$AI$7:$AI$3000,"yes"))=0,"—",SUMIFS(Review!$O$7:$O$600,Review!$B$7:$B$600,$B14,Review!$C$7:$C$600,E$10)) -> 5.305 | F14: =IF(IF($E$5="Local prices",COUNTIFS(Offers!$B$7:$B$3000,$B14,Offers!$C$7:$C$3000,F$10,Offers!$AH$7:$AH$3000,"yes"),COUNTIFS(Offers!$B$7:$B$3000,$B14,Offers!$C$7:$C$3000,F$10,Offers!$AI$7:$AI$3000,"yes"))=0,"—",SUMIFS(Review!$O$7:$O$600,Review!$B$7:$B$600,$B14,Review!$C$7:$C$600,F$10)) -> 6.93 | G14: =IF(IF($E$5="Local prices",COUNTIFS(Offers!$B$7:$B$3000,$B14,Offers!$C$7:$C$3000,G$10,Offers!$AH$7:$AH$3000,"yes"),COUNTIFS(Offers!$B$7:$B$3000,$B14,Offers!$C$7:$C$3000,G$10,Offers!$AI$7:$AI$3000,"yes"))=0,"—",SUMIFS(Review!$O$7:$O$600,Review!$B$7:$B$600,$B14,Review!$C$7:$C$600,G$10)) -> 4.15868 | H14: =IF(IF($E$5="Local prices",COUNTIFS(Offers!$B$7:$B$3000,$B14,Offers!$C$7:$C$3000,H$10,Offers!$AH$7:$AH$3000,"yes"),COUNTIFS(Offers!$B$7:$B$3000,$B14,Offers!$C$7:$C$3000,H$10,Offers!$AI$7:$AI$3000,"yes"))=0,"—",SUMIFS(Review!$O$7:$O$600,Review!$B$7:$B$600,$B14,Review!$C$7:$C$600,H$10)) -> 11.991992 | J14: Austria | K14: =IF(COUNTIFS(Offers!$B$7:$B$3000,$J$6,Offers!$C$7:$C$3000,$J14,Offers!$AI$7:$AI$3000,"yes")=0,"—",SUMIFS(Review!$I$7:$I$600,Review!$B$7:$B$600,$J$6,Review!$C$7:$C$600,$J14)) -> 7.83 | L14: =IF(COUNTIFS(Offers!$B$7:$B$3000,$J$6,Offers!$C$7:$C$3000,$J14,Offers!$AI$7:$AI$3000,"yes")=0,"—",SUMIFS(Review!$J$7:$J$600,Review!$B$7:$B$600,$J$6,Review!$C$7:$C$600,$J14)) -> 14.07 | M14: =IF(COUNTIFS(Offers!$B$7:$B$3000,$J$6,Offers!$C$7:$C$3000,$J14,Offers!$AI$7:$AI$3000,"yes")=0,"—",SUMIFS(Review!$K$7:$K$600,Review!$B$7:$B$600,$J$6,Review!$C$7:$C$600,$J14)) -> 23
B15: GN 1/1 PP lid | C15: =IF(IF($E$5="Local prices",COUNTIFS(Offers!$B$7:$B$3000,$B15,Offers!$C$7:$C$3000,C$10,Offers!$AH$7:$AH$3000,"yes"),COUNTIFS(Offers!$B$7:$B$3000,$B15,Offers!$C$7:$C$3000,C$10,Offers!$AI$7:$AI$3000,"yes"))=0,"—",SUMIFS(Review!$O$7:$O$600,Review!$B$7:$B$600,$B15,Review!$C$7:$C$600,C$10)) -> — | D15: =IF(IF($E$5="Local prices",COUNTIFS(Offers!$B$7:$B$3000,$B15,Offers!$C$7:$C$3000,D$10,Offers!$AH$7:$AH$3000,"yes"),COUNTIFS(Offers!$B$7:$B$3000,$B15,Offers!$C$7:$C$3000,D$10,Offers!$AI$7:$AI$3000,"yes"))=0,"—",SUMIFS(Review!$O$7:$O$600,Review!$B$7:$B$600,$B15,Review!$C$7:$C$600,D$10)) -> 4.50959 | E15: =IF(IF($E$5="Local prices",COUNTIFS(Offers!$B$7:$B$3000,$B15,Offers!$C$7:$C$3000,E$10,Offers!$AH$7:$AH$3000,"yes"),COUNTIFS(Offers!$B$7:$B$3000,$B15,Offers!$C$7:$C$3000,E$10,Offers!$AI$7:$AI$3000,"yes"))=0,"—",SUMIFS(Review!$O$7:$O$600,Review!$B$7:$B$600,$B15,Review!$C$7:$C$600,E$10)) -> 6.525 | F15: =IF(IF($E$5="Local prices",COUNTIFS(Offers!$B$7:$B$3000,$B15,Offers!$C$7:$C$3000,F$10,Offers!$AH$7:$AH$3000,"yes"),COUNTIFS(Offers!$B$7:$B$3000,$B15,Offers!$C$7:$C$3000,F$10,Offers!$AI$7:$AI$3000,"yes"))=0,"—",SUMIFS(Review!$O$7:$O$600,Review!$B$7:$B$600,$B15,Review!$C$7:$C$600,F$10)) -> 7.5 | G15: =IF(IF($E$5="Local prices",COUNTIFS(Offers!$B$7:$B$3000,$B15,Offers!$C$7:$C$3000,G$10,Offers!$AH$7:$AH$3000,"yes"),COUNTIFS(Offers!$B$7:$B$3000,$B15,Offers!$C$7:$C$3000,G$10,Offers!$AI$7:$AI$3000,"yes"))=0,"—",SUMIFS(Review!$O$7:$O$600,Review!$B$7:$B$600,$B15,Review!$C$7:$C$600,G$10)) -> 5.040613 | H15: =IF(IF($E$5="Local prices",COUNTIFS(Offers!$B$7:$B$3000,$B15,Offers!$C$7:$C$3000,H$10,Offers!$AH$7:$AH$3000,"yes"),COUNTIFS(Offers!$B$7:$B$3000,$B15,Offers!$C$7:$C$3000,H$10,Offers!$AI$7:$AI$3000,"yes"))=0,"—",SUMIFS(Review!$O$7:$O$600,Review!$B$7:$B$600,$B15,Review!$C$7:$C$600,H$10)) -> 9.945447 | J15: Germany | K15: =IF(COUNTIFS(Offers!$B$7:$B$3000,$J$6,Offers!$C$7:$C$3000,$J15,Offers!$AI$7:$AI$3000,"yes")=0,"—",SUMIFS(Review!$I$7:$I$600,Review!$B$7:$B$600,$J$6,Review!$C$7:$C$600,$J15)) -> 7.26 | L15: =IF(COUNTIFS(Offers!$B$7:$B$3000,$J$6,Offers!$C$7:$C$3000,$J15,Offers!$AI$7:$AI$3000,"yes")=0,"—",SUMIFS(Review!$J$7:$J$600,Review!$B$7:$B$600,$J$6,Review!$C$7:$C$600,$J15)) -> 13.11 | M15: =IF(COUNTIFS(Offers!$B$7:$B$3000,$J$6,Offers!$C$7:$C$3000,$J15,Offers!$AI$7:$AI$3000,"yes")=0,"—",SUMIFS(Review!$K$7:$K$600,Review!$B$7:$B$600,$J$6,Review!$C$7:$C$600,$J15)) -> 22.43
B16: Squeeze bottle 500 ml, PP, single tip | C16: =IF(IF($E$5="Local prices",COUNTIFS(Offers!$B$7:$B$3000,$B16,Offers!$C$7:$C$3000,C$10,Offers!$AH$7:$AH$3000,"yes"),COUNTIFS(Offers!$B$7:$B$3000,$B16,Offers!$C$7:$C$3000,C$10,Offers!$AI$7:$AI$3000,"yes"))=0,"—",SUMIFS(Review!$O$7:$O$600,Review!$B$7:$B$600,$B16,Review!$C$7:$C$600,C$10)) -> — | D16: =IF(IF($E$5="Local prices",COUNTIFS(Offers!$B$7:$B$3000,$B16,Offers!$C$7:$C$3000,D$10,Offers!$AH$7:$AH$3000,"yes"),COUNTIFS(Offers!$B$7:$B$3000,$B16,Offers!$C$7:$C$3000,D$10,Offers!$AI$7:$AI$3000,"yes"))=0,"—",SUMIFS(Review!$O$7:$O$600,Review!$B$7:$B$600,$B16,Review!$C$7:$C$600,D$10)) -> — | E16: =IF(IF($E$5="Local prices",COUNTIFS(Offers!$B$7:$B$3000,$B16,Offers!$C$7:$C$3000,E$10,Offers!$AH$7:$AH$3000,"yes"),COUNTIFS(Offers!$B$7:$B$3000,$B16,Offers!$C$7:$C$3000,E$10,Offers!$AI$7:$AI$3000,"yes"))=0,"—",SUMIFS(Review!$O$7:$O$600,Review!$B$7:$B$600,$B16,Review!$C$7:$C$600,E$10)) -> 2.32 | F16: =IF(IF($E$5="Local prices",COUNTIFS(Offers!$B$7:$B$3000,$B16,Offers!$C$7:$C$3000,F$10,Offers!$AH$7:$AH$3000,"yes"),COUNTIFS(Offers!$B$7:$B$3000,$B16,Offers!$C$7:$C$3000,F$10,Offers!$AI$7:$AI$3000,"yes"))=0,"—",SUMIFS(Review!$O$7:$O$600,Review!$B$7:$B$600,$B16,Review!$C$7:$C$600,F$10)) -> 2.055 | G16: =IF(IF($E$5="Local prices",COUNTIFS(Offers!$B$7:$B$3000,$B16,Offers!$C$7:$C$3000,G$10,Offers!$AH$7:$AH$3000,"yes"),COUNTIFS(Offers!$B$7:$B$3000,$B16,Offers!$C$7:$C$3000,G$10,Offers!$AI$7:$AI$3000,"yes"))=0,"—",SUMIFS(Review!$O$7:$O$600,Review!$B$7:$B$600,$B16,Review!$C$7:$C$600,G$10)) -> 4.708558 | H16: =IF(IF($E$5="Local prices",COUNTIFS(Offers!$B$7:$B$3000,$B16,Offers!$C$7:$C$3000,H$10,Offers!$AH$7:$AH$3000,"yes"),COUNTIFS(Offers!$B$7:$B$3000,$B16,Offers!$C$7:$C$3000,H$10,Offers!$AI$7:$AI$3000,"yes"))=0,"—",SUMIFS(Review!$O$7:$O$600,Review!$B$7:$B$600,$B16,Review!$C$7:$C$600,H$10)) -> — | J16: Czech | K16: =IF(COUNTIFS(Offers!$B$7:$B$3000,$J$6,Offers!$C$7:$C$3000,$J16,Offers!$AI$7:$AI$3000,"yes")=0,"—",SUMIFS(Review!$I$7:$I$600,Review!$B$7:$B$600,$J$6,Review!$C$7:$C$600,$J16)) -> 7.804741 | L16: =IF(COUNTIFS(Offers!$B$7:$B$3000,$J$6,Offers!$C$7:$C$3000,$J16,Offers!$AI$7:$AI$3000,"yes")=0,"—",SUMIFS(Review!$J$7:$J$600,Review!$B$7:$B$600,$J$6,Review!$C$7:$C$600,$J16)) -> 12.148079 | M16: =IF(COUNTIFS(Offers!$B$7:$B$3000,$J$6,Offers!$C$7:$C$3000,$J16,Offers!$AI$7:$AI$3000,"yes")=0,"—",SUMIFS(Review!$K$7:$K$600,Review!$B$7:$B$600,$J$6,Review!$C$7:$C$600,$J16)) -> 16.986838
B17: Squeeze bottle 1,000 ml, PP, single tip | C17: =IF(IF($E$5="Local prices",COUNTIFS(Offers!$B$7:$B$3000,$B17,Offers!$C$7:$C$3000,C$10,Offers!$AH$7:$AH$3000,"yes"),COUNTIFS(Offers!$B$7:$B$3000,$B17,Offers!$C$7:$C$3000,C$10,Offers!$AI$7:$AI$3000,"yes"))=0,"—",SUMIFS(Review!$O$7:$O$600,Review!$B$7:$B$600,$B17,Review!$C$7:$C$600,C$10)) -> — | D17: =IF(IF($E$5="Local prices",COUNTIFS(Offers!$B$7:$B$3000,$B17,Offers!$C$7:$C$3000,D$10,Offers!$AH$7:$AH$3000,"yes"),COUNTIFS(Offers!$B$7:$B$3000,$B17,Offers!$C$7:$C$3000,D$10,Offers!$AI$7:$AI$3000,"yes"))=0,"—",SUMIFS(Review!$O$7:$O$600,Review!$B$7:$B$600,$B17,Review!$C$7:$C$600,D$10)) -> — | E17: =IF(IF($E$5="Local prices",COUNTIFS(Offers!$B$7:$B$3000,$B17,Offers!$C$7:$C$3000,E$10,Offers!$AH$7:$AH$3000,"yes"),COUNTIFS(Offers!$B$7:$B$3000,$B17,Offers!$C$7:$C$3000,E$10,Offers!$AI$7:$AI$3000,"yes"))=0,"—",SUMIFS(Review!$O$7:$O$600,Review!$B$7:$B$600,$B17,Review!$C$7:$C$600,E$10)) -> 2.96 | F17: =IF(IF($E$5="Local prices",COUNTIFS(Offers!$B$7:$B$3000,$B17,Offers!$C$7:$C$3000,F$10,Offers!$AH$7:$AH$3000,"yes"),COUNTIFS(Offers!$B$7:$B$3000,$B17,Offers!$C$7:$C$3000,F$10,Offers!$AI$7:$AI$3000,"yes"))=0,"—",SUMIFS(Review!$O$7:$O$600,Review!$B$7:$B$600,$B17,Review!$C$7:$C$600,F$10)) -> 1.97 | G17: =IF(IF($E$5="Local prices",COUNTIFS(Offers!$B$7:$B$3000,$B17,Offers!$C$7:$C$3000,G$10,Offers!$AH$7:$AH$3000,"yes"),COUNTIFS(Offers!$B$7:$B$3000,$B17,Offers!$C$7:$C$3000,G$10,Offers!$AI$7:$AI$3000,"yes"))=0,"—",SUMIFS(Review!$O$7:$O$600,Review!$B$7:$B$600,$B17,Review!$C$7:$C$600,G$10)) -> 3.80779 | H17: =IF(IF($E$5="Local prices",COUNTIFS(Offers!$B$7:$B$3000,$B17,Offers!$C$7:$C$3000,H$10,Offers!$AH$7:$AH$3000,"yes"),COUNTIFS(Offers!$B$7:$B$3000,$B17,Offers!$C$7:$C$3000,H$10,Offers!$AI$7:$AI$3000,"yes"))=0,"—",SUMIFS(Review!$O$7:$O$600,Review!$B$7:$B$600,$B17,Review!$C$7:$C$600,H$10)) -> 1.28 | J17: Slovakia | K17: =IF(COUNTIFS(Offers!$B$7:$B$3000,$J$6,Offers!$C$7:$C$3000,$J17,Offers!$AI$7:$AI$3000,"yes")=0,"—",SUMIFS(Review!$I$7:$I$600,Review!$B$7:$B$600,$J$6,Review!$C$7:$C$600,$J17)) -> 16.455285 | L17: =IF(COUNTIFS(Offers!$B$7:$B$3000,$J$6,Offers!$C$7:$C$3000,$J17,Offers!$AI$7:$AI$3000,"yes")=0,"—",SUMIFS(Review!$J$7:$J$600,Review!$B$7:$B$600,$J$6,Review!$C$7:$C$600,$J17)) -> 18.467643 | M17: =IF(COUNTIFS(Offers!$B$7:$B$3000,$J$6,Offers!$C$7:$C$3000,$J17,Offers!$AI$7:$AI$3000,"yes")=0,"—",SUMIFS(Review!$K$7:$K$600,Review!$B$7:$B$600,$J$6,Review!$C$7:$C$600,$J17)) -> 20.48
B18: Squeeze bottle 500 ml, triple tip | C18: =IF(IF($E$5="Local prices",COUNTIFS(Offers!$B$7:$B$3000,$B18,Offers!$C$7:$C$3000,C$10,Offers!$AH$7:$AH$3000,"yes"),COUNTIFS(Offers!$B$7:$B$3000,$B18,Offers!$C$7:$C$3000,C$10,Offers!$AI$7:$AI$3000,"yes"))=0,"—",SUMIFS(Review!$O$7:$O$600,Review!$B$7:$B$600,$B18,Review!$C$7:$C$600,C$10)) -> — | D18: =IF(IF($E$5="Local prices",COUNTIFS(Offers!$B$7:$B$3000,$B18,Offers!$C$7:$C$3000,D$10,Offers!$AH$7:$AH$3000,"yes"),COUNTIFS(Offers!$B$7:$B$3000,$B18,Offers!$C$7:$C$3000,D$10,Offers!$AI$7:$AI$3000,"yes"))=0,"—",SUMIFS(Review!$O$7:$O$600,Review!$B$7:$B$600,$B18,Review!$C$7:$C$600,D$10)) -> — | E18: =IF(IF($E$5="Local prices",COUNTIFS(Offers!$B$7:$B$3000,$B18,Offers!$C$7:$C$3000,E$10,Offers!$AH$7:$AH$3000,"yes"),COUNTIFS(Offers!$B$7:$B$3000,$B18,Offers!$C$7:$C$3000,E$10,Offers!$AI$7:$AI$3000,"yes"))=0,"—",SUMIFS(Review!$O$7:$O$600,Review!$B$7:$B$600,$B18,Review!$C$7:$C$600,E$10)) -> — | F18: =IF(IF($E$5="Local prices",COUNTIFS(Offers!$B$7:$B$3000,$B18,Offers!$C$7:$C$3000,F$10,Offers!$AH$7:$AH$3000,"yes"),COUNTIFS(Offers!$B$7:$B$3000,$B18,Offers!$C$7:$C$3000,F$10,Offers!$AI$7:$AI$3000,"yes"))=0,"—",SUMIFS(Review!$O$7:$O$600,Review!$B$7:$B$600,$B18,Review!$C$7:$C$600,F$10)) -> — | G18: =IF(IF($E$5="Local prices",COUNTIFS(Offers!$B$7:$B$3000,$B18,Offers!$C$7:$C$3000,G$10,Offers!$AH$7:$AH$3000,"yes"),COUNTIFS(Offers!$B$7:$B$3000,$B18,Offers!$C$7:$C$3000,G$10,Offers!$AI$7:$AI$3000,"yes"))=0,"—",SUMIFS(Review!$O$7:$O$600,Review!$B$7:$B$600,$B18,Review!$C$7:$C$600,G$10)) -> — | H18: =IF(IF($E$5="Local prices",COUNTIFS(Offers!$B$7:$B$3000,$B18,Offers!$C$7:$C$3000,H$10,Offers!$AH$7:$AH$3000,"yes"),COUNTIFS(Offers!$B$7:$B$3000,$B18,Offers!$C$7:$C$3000,H$10,Offers!$AI$7:$AI$3000,"yes"))=0,"—",SUMIFS(Review!$O$7:$O$600,Review!$B$7:$B$600,$B18,Review!$C$7:$C$600,H$10)) -> —
B19: Sauce pump dispenser with stand | C19: =IF(IF($E$5="Local prices",COUNTIFS(Offers!$B$7:$B$3000,$B19,Offers!$C$7:$C$3000,C$10,Offers!$AH$7:$AH$3000,"yes"),COUNTIFS(Offers!$B$7:$B$3000,$B19,Offers!$C$7:$C$3000,C$10,Offers!$AI$7:$AI$3000,"yes"))=0,"—",SUMIFS(Review!$O$7:$O$600,Review!$B$7:$B$600,$B19,Review!$C$7:$C$600,C$10)) -> — | D19: =IF(IF($E$5="Local prices",COUNTIFS(Offers!$B$7:$B$3000,$B19,Offers!$C$7:$C$3000,D$10,Offers!$AH$7:$AH$3000,"yes"),COUNTIFS(Offers!$B$7:$B$3000,$B19,Offers!$C$7:$C$3000,D$10,Offers!$AI$7:$AI$3000,"yes"))=0,"—",SUMIFS(Review!$O$7:$O$600,Review!$B$7:$B$600,$B19,Review!$C$7:$C$600,D$10)) -> 16.641903 | E19: =IF(IF($E$5="Local prices",COUNTIFS(Offers!$B$7:$B$3000,$B19,Offers!$C$7:$C$3000,E$10,Offers!$AH$7:$AH$3000,"yes"),COUNTIFS(Offers!$B$7:$B$3000,$B19,Offers!$C$7:$C$3000,E$10,Offers!$AI$7:$AI$3000,"yes"))=0,"—",SUMIFS(Review!$O$7:$O$600,Review!$B$7:$B$600,$B19,Review!$C$7:$C$600,E$10)) -> 30.5 | F19: =IF(IF($E$5="Local prices",COUNTIFS(Offers!$B$7:$B$3000,$B19,Offers!$C$7:$C$3000,F$10,Offers!$AH$7:$AH$3000,"yes"),COUNTIFS(Offers!$B$7:$B$3000,$B19,Offers!$C$7:$C$3000,F$10,Offers!$AI$7:$AI$3000,"yes"))=0,"—",SUMIFS(Review!$O$7:$O$600,Review!$B$7:$B$600,$B19,Review!$C$7:$C$600,F$10)) -> 27.49 | G19: =IF(IF($E$5="Local prices",COUNTIFS(Offers!$B$7:$B$3000,$B19,Offers!$C$7:$C$3000,G$10,Offers!$AH$7:$AH$3000,"yes"),COUNTIFS(Offers!$B$7:$B$3000,$B19,Offers!$C$7:$C$3000,G$10,Offers!$AI$7:$AI$3000,"yes"))=0,"—",SUMIFS(Review!$O$7:$O$600,Review!$B$7:$B$600,$B19,Review!$C$7:$C$600,G$10)) -> 40.84817 | H19: =IF(IF($E$5="Local prices",COUNTIFS(Offers!$B$7:$B$3000,$B19,Offers!$C$7:$C$3000,H$10,Offers!$AH$7:$AH$3000,"yes"),COUNTIFS(Offers!$B$7:$B$3000,$B19,Offers!$C$7:$C$3000,H$10,Offers!$AI$7:$AI$3000,"yes"))=0,"—",SUMIFS(Review!$O$7:$O$600,Review!$B$7:$B$600,$B19,Review!$C$7:$C$600,H$10)) -> —
B20: PE cutting board 530 × 325 × 20 mm | C20: =IF(IF($E$5="Local prices",COUNTIFS(Offers!$B$7:$B$3000,$B20,Offers!$C$7:$C$3000,C$10,Offers!$AH$7:$AH$3000,"yes"),COUNTIFS(Offers!$B$7:$B$3000,$B20,Offers!$C$7:$C$3000,C$10,Offers!$AI$7:$AI$3000,"yes"))=0,"—",SUMIFS(Review!$O$7:$O$600,Review!$B$7:$B$600,$B20,Review!$C$7:$C$600,C$10)) -> — | D20: =IF(IF($E$5="Local prices",COUNTIFS(Offers!$B$7:$B$3000,$B20,Offers!$C$7:$C$3000,D$10,Offers!$AH$7:$AH$3000,"yes"),COUNTIFS(Offers!$B$7:$B$3000,$B20,Offers!$C$7:$C$3000,D$10,Offers!$AI$7:$AI$3000,"yes"))=0,"—",SUMIFS(Review!$O$7:$O$600,Review!$B$7:$B$600,$B20,Review!$C$7:$C$600,D$10)) -> — | E20: =IF(IF($E$5="Local prices",COUNTIFS(Offers!$B$7:$B$3000,$B20,Offers!$C$7:$C$3000,E$10,Offers!$AH$7:$AH$3000,"yes"),COUNTIFS(Offers!$B$7:$B$3000,$B20,Offers!$C$7:$C$3000,E$10,Offers!$AI$7:$AI$3000,"yes"))=0,"—",SUMIFS(Review!$O$7:$O$600,Review!$B$7:$B$600,$B20,Review!$C$7:$C$600,E$10)) -> 24.57 | F20: =IF(IF($E$5="Local prices",COUNTIFS(Offers!$B$7:$B$3000,$B20,Offers!$C$7:$C$3000,F$10,Offers!$AH$7:$AH$3000,"yes"),COUNTIFS(Offers!$B$7:$B$3000,$B20,Offers!$C$7:$C$3000,F$10,Offers!$AI$7:$AI$3000,"yes"))=0,"—",SUMIFS(Review!$O$7:$O$600,Review!$B$7:$B$600,$B20,Review!$C$7:$C$600,F$10)) -> 22.79 | G20: =IF(IF($E$5="Local prices",COUNTIFS(Offers!$B$7:$B$3000,$B20,Offers!$C$7:$C$3000,G$10,Offers!$AH$7:$AH$3000,"yes"),COUNTIFS(Offers!$B$7:$B$3000,$B20,Offers!$C$7:$C$3000,G$10,Offers!$AI$7:$AI$3000,"yes"))=0,"—",SUMIFS(Review!$O$7:$O$600,Review!$B$7:$B$600,$B20,Review!$C$7:$C$600,G$10)) -> 44.628937 | H20: =IF(IF($E$5="Local prices",COUNTIFS(Offers!$B$7:$B$3000,$B20,Offers!$C$7:$C$3000,H$10,Offers!$AH$7:$AH$3000,"yes"),COUNTIFS(Offers!$B$7:$B$3000,$B20,Offers!$C$7:$C$3000,H$10,Offers!$AI$7:$AI$3000,"yes"))=0,"—",SUMIFS(Review!$O$7:$O$600,Review!$B$7:$B$600,$B20,Review!$C$7:$C$600,H$10)) -> 36.154675 | J20: Price basis
B21: PE cutting board 600 × 400 × 20 mm | C21: =IF(IF($E$5="Local prices",COUNTIFS(Offers!$B$7:$B$3000,$B21,Offers!$C$7:$C$3000,C$10,Offers!$AH$7:$AH$3000,"yes"),COUNTIFS(Offers!$B$7:$B$3000,$B21,Offers!$C$7:$C$3000,C$10,Offers!$AI$7:$AI$3000,"yes"))=0,"—",SUMIFS(Review!$O$7:$O$600,Review!$B$7:$B$600,$B21,Review!$C$7:$C$600,C$10)) -> — | D21: =IF(IF($E$5="Local prices",COUNTIFS(Offers!$B$7:$B$3000,$B21,Offers!$C$7:$C$3000,D$10,Offers!$AH$7:$AH$3000,"yes"),COUNTIFS(Offers!$B$7:$B$3000,$B21,Offers!$C$7:$C$3000,D$10,Offers!$AI$7:$AI$3000,"yes"))=0,"—",SUMIFS(Review!$O$7:$O$600,Review!$B$7:$B$600,$B21,Review!$C$7:$C$600,D$10)) -> — | E21: =IF(IF($E$5="Local prices",COUNTIFS(Offers!$B$7:$B$3000,$B21,Offers!$C$7:$C$3000,E$10,Offers!$AH$7:$AH$3000,"yes"),COUNTIFS(Offers!$B$7:$B$3000,$B21,Offers!$C$7:$C$3000,E$10,Offers!$AI$7:$AI$3000,"yes"))=0,"—",SUMIFS(Review!$O$7:$O$600,Review!$B$7:$B$600,$B21,Review!$C$7:$C$600,E$10)) -> 33.5 | F21: =IF(IF($E$5="Local prices",COUNTIFS(Offers!$B$7:$B$3000,$B21,Offers!$C$7:$C$3000,F$10,Offers!$AH$7:$AH$3000,"yes"),COUNTIFS(Offers!$B$7:$B$3000,$B21,Offers!$C$7:$C$3000,F$10,Offers!$AI$7:$AI$3000,"yes"))=0,"—",SUMIFS(Review!$O$7:$O$600,Review!$B$7:$B$600,$B21,Review!$C$7:$C$600,F$10)) -> 34.275 | G21: =IF(IF($E$5="Local prices",COUNTIFS(Offers!$B$7:$B$3000,$B21,Offers!$C$7:$C$3000,G$10,Offers!$AH$7:$AH$3000,"yes"),COUNTIFS(Offers!$B$7:$B$3000,$B21,Offers!$C$7:$C$3000,G$10,Offers!$AI$7:$AI$3000,"yes"))=0,"—",SUMIFS(Review!$O$7:$O$600,Review!$B$7:$B$600,$B21,Review!$C$7:$C$600,G$10)) -> 40.597592 | H21: =IF(IF($E$5="Local prices",COUNTIFS(Offers!$B$7:$B$3000,$B21,Offers!$C$7:$C$3000,H$10,Offers!$AH$7:$AH$3000,"yes"),COUNTIFS(Offers!$B$7:$B$3000,$B21,Offers!$C$7:$C$3000,H$10,Offers!$AI$7:$AI$3000,"yes"))=0,"—",SUMIFS(Review!$O$7:$O$600,Review!$B$7:$B$600,$B21,Review!$C$7:$C$600,H$10)) -> 32.85 | J21: Hungary and Romania prices are net per piece, as confirmed by you.
B22: PE cutting board 300 × 200 × 10 mm | C22: =IF(IF($E$5="Local prices",COUNTIFS(Offers!$B$7:$B$3000,$B22,Offers!$C$7:$C$3000,C$10,Offers!$AH$7:$AH$3000,"yes"),COUNTIFS(Offers!$B$7:$B$3000,$B22,Offers!$C$7:$C$3000,C$10,Offers!$AI$7:$AI$3000,"yes"))=0,"—",SUMIFS(Review!$O$7:$O$600,Review!$B$7:$B$600,$B22,Review!$C$7:$C$600,C$10)) -> — | D22: =IF(IF($E$5="Local prices",COUNTIFS(Offers!$B$7:$B$3000,$B22,Offers!$C$7:$C$3000,D$10,Offers!$AH$7:$AH$3000,"yes"),COUNTIFS(Offers!$B$7:$B$3000,$B22,Offers!$C$7:$C$3000,D$10,Offers!$AI$7:$AI$3000,"yes"))=0,"—",SUMIFS(Review!$O$7:$O$600,Review!$B$7:$B$600,$B22,Review!$C$7:$C$600,D$10)) -> — | E22: =IF(IF($E$5="Local prices",COUNTIFS(Offers!$B$7:$B$3000,$B22,Offers!$C$7:$C$3000,E$10,Offers!$AH$7:$AH$3000,"yes"),COUNTIFS(Offers!$B$7:$B$3000,$B22,Offers!$C$7:$C$3000,E$10,Offers!$AI$7:$AI$3000,"yes"))=0,"—",SUMIFS(Review!$O$7:$O$600,Review!$B$7:$B$600,$B22,Review!$C$7:$C$600,E$10)) -> 8.12 | F22: =IF(IF($E$5="Local prices",COUNTIFS(Offers!$B$7:$B$3000,$B22,Offers!$C$7:$C$3000,F$10,Offers!$AH$7:$AH$3000,"yes"),COUNTIFS(Offers!$B$7:$B$3000,$B22,Offers!$C$7:$C$3000,F$10,Offers!$AI$7:$AI$3000,"yes"))=0,"—",SUMIFS(Review!$O$7:$O$600,Review!$B$7:$B$600,$B22,Review!$C$7:$C$600,F$10)) -> 7.96 | G22: =IF(IF($E$5="Local prices",COUNTIFS(Offers!$B$7:$B$3000,$B22,Offers!$C$7:$C$3000,G$10,Offers!$AH$7:$AH$3000,"yes"),COUNTIFS(Offers!$B$7:$B$3000,$B22,Offers!$C$7:$C$3000,G$10,Offers!$AI$7:$AI$3000,"yes"))=0,"—",SUMIFS(Review!$O$7:$O$600,Review!$B$7:$B$600,$B22,Review!$C$7:$C$600,G$10)) -> 6.35123 | H22: =IF(IF($E$5="Local prices",COUNTIFS(Offers!$B$7:$B$3000,$B22,Offers!$C$7:$C$3000,H$10,Offers!$AH$7:$AH$3000,"yes"),COUNTIFS(Offers!$B$7:$B$3000,$B22,Offers!$C$7:$C$3000,H$10,Offers!$AI$7:$AI$3000,"yes"))=0,"—",SUMIFS(Review!$O$7:$O$600,Review!$B$7:$B$600,$B22,Review!$C$7:$C$600,H$10)) -> 6.59
B23: PP dough box 600 × 400 × 100 mm | C23: =IF(IF($E$5="Local prices",COUNTIFS(Offers!$B$7:$B$3000,$B23,Offers!$C$7:$C$3000,C$10,Offers!$AH$7:$AH$3000,"yes"),COUNTIFS(Offers!$B$7:$B$3000,$B23,Offers!$C$7:$C$3000,C$10,Offers!$AI$7:$AI$3000,"yes"))=0,"—",SUMIFS(Review!$O$7:$O$600,Review!$B$7:$B$600,$B23,Review!$C$7:$C$600,C$10)) -> 10.898364 | D23: =IF(IF($E$5="Local prices",COUNTIFS(Offers!$B$7:$B$3000,$B23,Offers!$C$7:$C$3000,D$10,Offers!$AH$7:$AH$3000,"yes"),COUNTIFS(Offers!$B$7:$B$3000,$B23,Offers!$C$7:$C$3000,D$10,Offers!$AI$7:$AI$3000,"yes"))=0,"—",SUMIFS(Review!$O$7:$O$600,Review!$B$7:$B$600,$B23,Review!$C$7:$C$600,D$10)) -> 11.482401 | E23: =IF(IF($E$5="Local prices",COUNTIFS(Offers!$B$7:$B$3000,$B23,Offers!$C$7:$C$3000,E$10,Offers!$AH$7:$AH$3000,"yes"),COUNTIFS(Offers!$B$7:$B$3000,$B23,Offers!$C$7:$C$3000,E$10,Offers!$AI$7:$AI$3000,"yes"))=0,"—",SUMIFS(Review!$O$7:$O$600,Review!$B$7:$B$600,$B23,Review!$C$7:$C$600,E$10)) -> 21.28 | F23: =IF(IF($E$5="Local prices",COUNTIFS(Offers!$B$7:$B$3000,$B23,Offers!$C$7:$C$3000,F$10,Offers!$AH$7:$AH$3000,"yes"),COUNTIFS(Offers!$B$7:$B$3000,$B23,Offers!$C$7:$C$3000,F$10,Offers!$AI$7:$AI$3000,"yes"))=0,"—",SUMIFS(Review!$O$7:$O$600,Review!$B$7:$B$600,$B23,Review!$C$7:$C$600,F$10)) -> 21.18 | G23: =IF(IF($E$5="Local prices",COUNTIFS(Offers!$B$7:$B$3000,$B23,Offers!$C$7:$C$3000,G$10,Offers!$AH$7:$AH$3000,"yes"),COUNTIFS(Offers!$B$7:$B$3000,$B23,Offers!$C$7:$C$3000,G$10,Offers!$AI$7:$AI$3000,"yes"))=0,"—",SUMIFS(Review!$O$7:$O$600,Review!$B$7:$B$600,$B23,Review!$C$7:$C$600,G$10)) -> 17.221857 | H23: =IF(IF($E$5="Local prices",COUNTIFS(Offers!$B$7:$B$3000,$B23,Offers!$C$7:$C$3000,H$10,Offers!$AH$7:$AH$3000,"yes"),COUNTIFS(Offers!$B$7:$B$3000,$B23,Offers!$C$7:$C$3000,H$10,Offers!$AI$7:$AI$3000,"yes"))=0,"—",SUMIFS(Review!$O$7:$O$600,Review!$B$7:$B$600,$B23,Review!$C$7:$C$600,H$10)) -> 15.658333
B24: Lid for 600 × 400 mm dough box | C24: =IF(IF($E$5="Local prices",COUNTIFS(Offers!$B$7:$B$3000,$B24,Offers!$C$7:$C$3000,C$10,Offers!$AH$7:$AH$3000,"yes"),COUNTIFS(Offers!$B$7:$B$3000,$B24,Offers!$C$7:$C$3000,C$10,Offers!$AI$7:$AI$3000,"yes"))=0,"—",SUMIFS(Review!$O$7:$O$600,Review!$B$7:$B$600,$B24,Review!$C$7:$C$600,C$10)) -> 7.322936 | D24: =IF(IF($E$5="Local prices",COUNTIFS(Offers!$B$7:$B$3000,$B24,Offers!$C$7:$C$3000,D$10,Offers!$AH$7:$AH$3000,"yes"),COUNTIFS(Offers!$B$7:$B$3000,$B24,Offers!$C$7:$C$3000,D$10,Offers!$AI$7:$AI$3000,"yes"))=0,"—",SUMIFS(Review!$O$7:$O$600,Review!$B$7:$B$600,$B24,Review!$C$7:$C$600,D$10)) -> 7.989364 | E24: =IF(IF($E$5="Local prices",COUNTIFS(Offers!$B$7:$B$3000,$B24,Offers!$C$7:$C$3000,E$10,Offers!$AH$7:$AH$3000,"yes"),COUNTIFS(Offers!$B$7:$B$3000,$B24,Offers!$C$7:$C$3000,E$10,Offers!$AI$7:$AI$3000,"yes"))=0,"—",SUMIFS(Review!$O$7:$O$600,Review!$B$7:$B$600,$B24,Review!$C$7:$C$600,E$10)) -> 10.49 | F24: =IF(IF($E$5="Local prices",COUNTIFS(Offers!$B$7:$B$3000,$B24,Offers!$C$7:$C$3000,F$10,Offers!$AH$7:$AH$3000,"yes"),COUNTIFS(Offers!$B$7:$B$3000,$B24,Offers!$C$7:$C$3000,F$10,Offers!$AI$7:$AI$3000,"yes"))=0,"—",SUMIFS(Review!$O$7:$O$600,Review!$B$7:$B$600,$B24,Review!$C$7:$C$600,F$10)) -> 8.69 | G24: =IF(IF($E$5="Local prices",COUNTIFS(Offers!$B$7:$B$3000,$B24,Offers!$C$7:$C$3000,G$10,Offers!$AH$7:$AH$3000,"yes"),COUNTIFS(Offers!$B$7:$B$3000,$B24,Offers!$C$7:$C$3000,G$10,Offers!$AI$7:$AI$3000,"yes"))=0,"—",SUMIFS(Review!$O$7:$O$600,Review!$B$7:$B$600,$B24,Review!$C$7:$C$600,G$10)) -> 7.984895 | H24: =IF(IF($E$5="Local prices",COUNTIFS(Offers!$B$7:$B$3000,$B24,Offers!$C$7:$C$3000,H$10,Offers!$AH$7:$AH$3000,"yes"),COUNTIFS(Offers!$B$7:$B$3000,$B24,Offers!$C$7:$C$3000,H$10,Offers!$AI$7:$AI$3000,"yes"))=0,"—",SUMIFS(Review!$O$7:$O$600,Review!$B$7:$B$600,$B24,Review!$C$7:$C$600,H$10)) -> 11.382521 | J24: Current FX
B25: PE dough box 600 × 400 × 75 mm | C25: =IF(IF($E$5="Local prices",COUNTIFS(Offers!$B$7:$B$3000,$B25,Offers!$C$7:$C$3000,C$10,Offers!$AH$7:$AH$3000,"yes"),COUNTIFS(Offers!$B$7:$B$3000,$B25,Offers!$C$7:$C$3000,C$10,Offers!$AI$7:$AI$3000,"yes"))=0,"—",SUMIFS(Review!$O$7:$O$600,Review!$B$7:$B$600,$B25,Review!$C$7:$C$600,C$10)) -> 10.925678 | D25: =IF(IF($E$5="Local prices",COUNTIFS(Offers!$B$7:$B$3000,$B25,Offers!$C$7:$C$3000,D$10,Offers!$AH$7:$AH$3000,"yes"),COUNTIFS(Offers!$B$7:$B$3000,$B25,Offers!$C$7:$C$3000,D$10,Offers!$AI$7:$AI$3000,"yes"))=0,"—",SUMIFS(Review!$O$7:$O$600,Review!$B$7:$B$600,$B25,Review!$C$7:$C$600,D$10)) -> — | E25: =IF(IF($E$5="Local prices",COUNTIFS(Offers!$B$7:$B$3000,$B25,Offers!$C$7:$C$3000,E$10,Offers!$AH$7:$AH$3000,"yes"),COUNTIFS(Offers!$B$7:$B$3000,$B25,Offers!$C$7:$C$3000,E$10,Offers!$AI$7:$AI$3000,"yes"))=0,"—",SUMIFS(Review!$O$7:$O$600,Review!$B$7:$B$600,$B25,Review!$C$7:$C$600,E$10)) -> 12.8 | F25: =IF(IF($E$5="Local prices",COUNTIFS(Offers!$B$7:$B$3000,$B25,Offers!$C$7:$C$3000,F$10,Offers!$AH$7:$AH$3000,"yes"),COUNTIFS(Offers!$B$7:$B$3000,$B25,Offers!$C$7:$C$3000,F$10,Offers!$AI$7:$AI$3000,"yes"))=0,"—",SUMIFS(Review!$O$7:$O$600,Review!$B$7:$B$600,$B25,Review!$C$7:$C$600,F$10)) -> 11.395 | G25: =IF(IF($E$5="Local prices",COUNTIFS(Offers!$B$7:$B$3000,$B25,Offers!$C$7:$C$3000,G$10,Offers!$AH$7:$AH$3000,"yes"),COUNTIFS(Offers!$B$7:$B$3000,$B25,Offers!$C$7:$C$3000,G$10,Offers!$AI$7:$AI$3000,"yes"))=0,"—",SUMIFS(Review!$O$7:$O$600,Review!$B$7:$B$600,$B25,Review!$C$7:$C$600,G$10)) -> 10.557609 | H25: =IF(IF($E$5="Local prices",COUNTIFS(Offers!$B$7:$B$3000,$B25,Offers!$C$7:$C$3000,H$10,Offers!$AH$7:$AH$3000,"yes"),COUNTIFS(Offers!$B$7:$B$3000,$B25,Offers!$C$7:$C$3000,H$10,Offers!$AI$7:$AI$3000,"yes"))=0,"—",SUMIFS(Review!$O$7:$O$600,Review!$B$7:$B$600,$B25,Review!$C$7:$C$600,H$10)) -> 15.21 | J25: Erste rates are applied to analytical conversions. Historical prices and research dates remain unchanged.
B26: Front-load GN 1/1 thermobox, 80–90 L | C26: =IF(IF($E$5="Local prices",COUNTIFS(Offers!$B$7:$B$3000,$B26,Offers!$C$7:$C$3000,C$10,Offers!$AH$7:$AH$3000,"yes"),COUNTIFS(Offers!$B$7:$B$3000,$B26,Offers!$C$7:$C$3000,C$10,Offers!$AI$7:$AI$3000,"yes"))=0,"—",SUMIFS(Review!$O$7:$O$600,Review!$B$7:$B$600,$B26,Review!$C$7:$C$600,C$10)) -> — | D26: =IF(IF($E$5="Local prices",COUNTIFS(Offers!$B$7:$B$3000,$B26,Offers!$C$7:$C$3000,D$10,Offers!$AH$7:$AH$3000,"yes"),COUNTIFS(Offers!$B$7:$B$3000,$B26,Offers!$C$7:$C$3000,D$10,Offers!$AI$7:$AI$3000,"yes"))=0,"—",SUMIFS(Review!$O$7:$O$600,Review!$B$7:$B$600,$B26,Review!$C$7:$C$600,D$10)) -> — | E26: =IF(IF($E$5="Local prices",COUNTIFS(Offers!$B$7:$B$3000,$B26,Offers!$C$7:$C$3000,E$10,Offers!$AH$7:$AH$3000,"yes"),COUNTIFS(Offers!$B$7:$B$3000,$B26,Offers!$C$7:$C$3000,E$10,Offers!$AI$7:$AI$3000,"yes"))=0,"—",SUMIFS(Review!$O$7:$O$600,Review!$B$7:$B$600,$B26,Review!$C$7:$C$600,E$10)) -> 260.435 | F26: =IF(IF($E$5="Local prices",COUNTIFS(Offers!$B$7:$B$3000,$B26,Offers!$C$7:$C$3000,F$10,Offers!$AH$7:$AH$3000,"yes"),COUNTIFS(Offers!$B$7:$B$3000,$B26,Offers!$C$7:$C$3000,F$10,Offers!$AI$7:$AI$3000,"yes"))=0,"—",SUMIFS(Review!$O$7:$O$600,Review!$B$7:$B$600,$B26,Review!$C$7:$C$600,F$10)) -> 252.97 | G26: =IF(IF($E$5="Local prices",COUNTIFS(Offers!$B$7:$B$3000,$B26,Offers!$C$7:$C$3000,G$10,Offers!$AH$7:$AH$3000,"yes"),COUNTIFS(Offers!$B$7:$B$3000,$B26,Offers!$C$7:$C$3000,G$10,Offers!$AI$7:$AI$3000,"yes"))=0,"—",SUMIFS(Review!$O$7:$O$600,Review!$B$7:$B$600,$B26,Review!$C$7:$C$600,G$10)) -> 225.51513 | H26: =IF(IF($E$5="Local prices",COUNTIFS(Offers!$B$7:$B$3000,$B26,Offers!$C$7:$C$3000,H$10,Offers!$AH$7:$AH$3000,"yes"),COUNTIFS(Offers!$B$7:$B$3000,$B26,Offers!$C$7:$C$3000,H$10,Offers!$AI$7:$AI$3000,"yes"))=0,"—",SUMIFS(Review!$O$7:$O$600,Review!$B$7:$B$600,$B26,Review!$C$7:$C$600,H$10)) -> 207.12
B27: Service tray approx. 370 × 530 mm | C27: =IF(IF($E$5="Local prices",COUNTIFS(Offers!$B$7:$B$3000,$B27,Offers!$C$7:$C$3000,C$10,Offers!$AH$7:$AH$3000,"yes"),COUNTIFS(Offers!$B$7:$B$3000,$B27,Offers!$C$7:$C$3000,C$10,Offers!$AI$7:$AI$3000,"yes"))=0,"—",SUMIFS(Review!$O$7:$O$600,Review!$B$7:$B$600,$B27,Review!$C$7:$C$600,C$10)) -> — | D27: =IF(IF($E$5="Local prices",COUNTIFS(Offers!$B$7:$B$3000,$B27,Offers!$C$7:$C$3000,D$10,Offers!$AH$7:$AH$3000,"yes"),COUNTIFS(Offers!$B$7:$B$3000,$B27,Offers!$C$7:$C$3000,D$10,Offers!$AI$7:$AI$3000,"yes"))=0,"—",SUMIFS(Review!$O$7:$O$600,Review!$B$7:$B$600,$B27,Review!$C$7:$C$600,D$10)) -> — | E27: =IF(IF($E$5="Local prices",COUNTIFS(Offers!$B$7:$B$3000,$B27,Offers!$C$7:$C$3000,E$10,Offers!$AH$7:$AH$3000,"yes"),COUNTIFS(Offers!$B$7:$B$3000,$B27,Offers!$C$7:$C$3000,E$10,Offers!$AI$7:$AI$3000,"yes"))=0,"—",SUMIFS(Review!$O$7:$O$600,Review!$B$7:$B$600,$B27,Review!$C$7:$C$600,E$10)) -> 11.365 | F27: =IF(IF($E$5="Local prices",COUNTIFS(Offers!$B$7:$B$3000,$B27,Offers!$C$7:$C$3000,F$10,Offers!$AH$7:$AH$3000,"yes"),COUNTIFS(Offers!$B$7:$B$3000,$B27,Offers!$C$7:$C$3000,F$10,Offers!$AI$7:$AI$3000,"yes"))=0,"—",SUMIFS(Review!$O$7:$O$600,Review!$B$7:$B$600,$B27,Review!$C$7:$C$600,F$10)) -> 7.47 | G27: =IF(IF($E$5="Local prices",COUNTIFS(Offers!$B$7:$B$3000,$B27,Offers!$C$7:$C$3000,G$10,Offers!$AH$7:$AH$3000,"yes"),COUNTIFS(Offers!$B$7:$B$3000,$B27,Offers!$C$7:$C$3000,G$10,Offers!$AI$7:$AI$3000,"yes"))=0,"—",SUMIFS(Review!$O$7:$O$600,Review!$B$7:$B$600,$B27,Review!$C$7:$C$600,G$10)) -> 8.195142 | H27: =IF(IF($E$5="Local prices",COUNTIFS(Offers!$B$7:$B$3000,$B27,Offers!$C$7:$C$3000,H$10,Offers!$AH$7:$AH$3000,"yes"),COUNTIFS(Offers!$B$7:$B$3000,$B27,Offers!$C$7:$C$3000,H$10,Offers!$AI$7:$AI$3000,"yes"))=0,"—",SUMIFS(Review!$O$7:$O$600,Review!$B$7:$B$600,$B27,Review!$C$7:$C$600,H$10)) -> —
B28: Thermo tray + lid, 5–6 compartments | C28: =IF(IF($E$5="Local prices",COUNTIFS(Offers!$B$7:$B$3000,$B28,Offers!$C$7:$C$3000,C$10,Offers!$AH$7:$AH$3000,"yes"),COUNTIFS(Offers!$B$7:$B$3000,$B28,Offers!$C$7:$C$3000,C$10,Offers!$AI$7:$AI$3000,"yes"))=0,"—",SUMIFS(Review!$O$7:$O$600,Review!$B$7:$B$600,$B28,Review!$C$7:$C$600,C$10)) -> — | D28: =IF(IF($E$5="Local prices",COUNTIFS(Offers!$B$7:$B$3000,$B28,Offers!$C$7:$C$3000,D$10,Offers!$AH$7:$AH$3000,"yes"),COUNTIFS(Offers!$B$7:$B$3000,$B28,Offers!$C$7:$C$3000,D$10,Offers!$AI$7:$AI$3000,"yes"))=0,"—",SUMIFS(Review!$O$7:$O$600,Review!$B$7:$B$600,$B28,Review!$C$7:$C$600,D$10)) -> — | E28: =IF(IF($E$5="Local prices",COUNTIFS(Offers!$B$7:$B$3000,$B28,Offers!$C$7:$C$3000,E$10,Offers!$AH$7:$AH$3000,"yes"),COUNTIFS(Offers!$B$7:$B$3000,$B28,Offers!$C$7:$C$3000,E$10,Offers!$AI$7:$AI$3000,"yes"))=0,"—",SUMIFS(Review!$O$7:$O$600,Review!$B$7:$B$600,$B28,Review!$C$7:$C$600,E$10)) -> 26.19 | F28: =IF(IF($E$5="Local prices",COUNTIFS(Offers!$B$7:$B$3000,$B28,Offers!$C$7:$C$3000,F$10,Offers!$AH$7:$AH$3000,"yes"),COUNTIFS(Offers!$B$7:$B$3000,$B28,Offers!$C$7:$C$3000,F$10,Offers!$AI$7:$AI$3000,"yes"))=0,"—",SUMIFS(Review!$O$7:$O$600,Review!$B$7:$B$600,$B28,Review!$C$7:$C$600,F$10)) -> 29.74 | G28: =IF(IF($E$5="Local prices",COUNTIFS(Offers!$B$7:$B$3000,$B28,Offers!$C$7:$C$3000,G$10,Offers!$AH$7:$AH$3000,"yes"),COUNTIFS(Offers!$B$7:$B$3000,$B28,Offers!$C$7:$C$3000,G$10,Offers!$AI$7:$AI$3000,"yes"))=0,"—",SUMIFS(Review!$O$7:$O$600,Review!$B$7:$B$600,$B28,Review!$C$7:$C$600,G$10)) -> 99.00991 | H28: =IF(IF($E$5="Local prices",COUNTIFS(Offers!$B$7:$B$3000,$B28,Offers!$C$7:$C$3000,H$10,Offers!$AH$7:$AH$3000,"yes"),COUNTIFS(Offers!$B$7:$B$3000,$B28,Offers!$C$7:$C$3000,H$10,Offers!$AI$7:$AI$3000,"yes"))=0,"—",SUMIFS(Review!$O$7:$O$600,Review!$B$7:$B$600,$B28,Review!$C$7:$C$600,H$10)) -> — | J28: Your review
B29: GN 1/1 PP container, 65 mm | C29: =IF(IF($E$5="Local prices",COUNTIFS(Offers!$B$7:$B$3000,$B29,Offers!$C$7:$C$3000,C$10,Offers!$AH$7:$AH$3000,"yes"),COUNTIFS(Offers!$B$7:$B$3000,$B29,Offers!$C$7:$C$3000,C$10,Offers!$AI$7:$AI$3000,"yes"))=0,"—",SUMIFS(Review!$O$7:$O$600,Review!$B$7:$B$600,$B29,Review!$C$7:$C$600,C$10)) -> — | D29: =IF(IF($E$5="Local prices",COUNTIFS(Offers!$B$7:$B$3000,$B29,Offers!$C$7:$C$3000,D$10,Offers!$AH$7:$AH$3000,"yes"),COUNTIFS(Offers!$B$7:$B$3000,$B29,Offers!$C$7:$C$3000,D$10,Offers!$AI$7:$AI$3000,"yes"))=0,"—",SUMIFS(Review!$O$7:$O$600,Review!$B$7:$B$600,$B29,Review!$C$7:$C$600,D$10)) -> — | E29: =IF(IF($E$5="Local prices",COUNTIFS(Offers!$B$7:$B$3000,$B29,Offers!$C$7:$C$3000,E$10,Offers!$AH$7:$AH$3000,"yes"),COUNTIFS(Offers!$B$7:$B$3000,$B29,Offers!$C$7:$C$3000,E$10,Offers!$AI$7:$AI$3000,"yes"))=0,"—",SUMIFS(Review!$O$7:$O$600,Review!$B$7:$B$600,$B29,Review!$C$7:$C$600,E$10)) -> 12.23 | F29: =IF(IF($E$5="Local prices",COUNTIFS(Offers!$B$7:$B$3000,$B29,Offers!$C$7:$C$3000,F$10,Offers!$AH$7:$AH$3000,"yes"),COUNTIFS(Offers!$B$7:$B$3000,$B29,Offers!$C$7:$C$3000,F$10,Offers!$AI$7:$AI$3000,"yes"))=0,"—",SUMIFS(Review!$O$7:$O$600,Review!$B$7:$B$600,$B29,Review!$C$7:$C$600,F$10)) -> 8.505 | G29: =IF(IF($E$5="Local prices",COUNTIFS(Offers!$B$7:$B$3000,$B29,Offers!$C$7:$C$3000,G$10,Offers!$AH$7:$AH$3000,"yes"),COUNTIFS(Offers!$B$7:$B$3000,$B29,Offers!$C$7:$C$3000,G$10,Offers!$AI$7:$AI$3000,"yes"))=0,"—",SUMIFS(Review!$O$7:$O$600,Review!$B$7:$B$600,$B29,Review!$C$7:$C$600,G$10)) -> 7.596746 | H29: =IF(IF($E$5="Local prices",COUNTIFS(Offers!$B$7:$B$3000,$B29,Offers!$C$7:$C$3000,H$10,Offers!$AH$7:$AH$3000,"yes"),COUNTIFS(Offers!$B$7:$B$3000,$B29,Offers!$C$7:$C$3000,H$10,Offers!$AI$7:$AI$3000,"yes"))=0,"—",SUMIFS(Review!$O$7:$O$600,Review!$B$7:$B$600,$B29,Review!$C$7:$C$600,H$10)) -> — | J29: Record decisions, priorities and comments in Review. Add offer-specific comments in Offers.
B30: GN 1/3 PC container, 100 mm | C30: =IF(IF($E$5="Local prices",COUNTIFS(Offers!$B$7:$B$3000,$B30,Offers!$C$7:$C$3000,C$10,Offers!$AH$7:$AH$3000,"yes"),COUNTIFS(Offers!$B$7:$B$3000,$B30,Offers!$C$7:$C$3000,C$10,Offers!$AI$7:$AI$3000,"yes"))=0,"—",SUMIFS(Review!$O$7:$O$600,Review!$B$7:$B$600,$B30,Review!$C$7:$C$600,C$10)) -> — | D30: =IF(IF($E$5="Local prices",COUNTIFS(Offers!$B$7:$B$3000,$B30,Offers!$C$7:$C$3000,D$10,Offers!$AH$7:$AH$3000,"yes"),COUNTIFS(Offers!$B$7:$B$3000,$B30,Offers!$C$7:$C$3000,D$10,Offers!$AI$7:$AI$3000,"yes"))=0,"—",SUMIFS(Review!$O$7:$O$600,Review!$B$7:$B$600,$B30,Review!$C$7:$C$600,D$10)) -> — | E30: =IF(IF($E$5="Local prices",COUNTIFS(Offers!$B$7:$B$3000,$B30,Offers!$C$7:$C$3000,E$10,Offers!$AH$7:$AH$3000,"yes"),COUNTIFS(Offers!$B$7:$B$3000,$B30,Offers!$C$7:$C$3000,E$10,Offers!$AI$7:$AI$3000,"yes"))=0,"—",SUMIFS(Review!$O$7:$O$600,Review!$B$7:$B$600,$B30,Review!$C$7:$C$600,E$10)) -> 7.295 | F30: =IF(IF($E$5="Local prices",COUNTIFS(Offers!$B$7:$B$3000,$B30,Offers!$C$7:$C$3000,F$10,Offers!$AH$7:$AH$3000,"yes"),COUNTIFS(Offers!$B$7:$B$3000,$B30,Offers!$C$7:$C$3000,F$10,Offers!$AI$7:$AI$3000,"yes"))=0,"—",SUMIFS(Review!$O$7:$O$600,Review!$B$7:$B$600,$B30,Review!$C$7:$C$600,F$10)) -> 5.52 | G30: =IF(IF($E$5="Local prices",COUNTIFS(Offers!$B$7:$B$3000,$B30,Offers!$C$7:$C$3000,G$10,Offers!$AH$7:$AH$3000,"yes"),COUNTIFS(Offers!$B$7:$B$3000,$B30,Offers!$C$7:$C$3000,G$10,Offers!$AI$7:$AI$3000,"yes"))=0,"—",SUMIFS(Review!$O$7:$O$600,Review!$B$7:$B$600,$B30,Review!$C$7:$C$600,G$10)) -> 5.479942 | H30: =IF(IF($E$5="Local prices",COUNTIFS(Offers!$B$7:$B$3000,$B30,Offers!$C$7:$C$3000,H$10,Offers!$AH$7:$AH$3000,"yes"),COUNTIFS(Offers!$B$7:$B$3000,$B30,Offers!$C$7:$C$3000,H$10,Offers!$AI$7:$AI$3000,"yes"))=0,"—",SUMIFS(Review!$O$7:$O$600,Review!$B$7:$B$600,$B30,Review!$C$7:$C$600,H$10)) -> —
B31: GN 1/2 PP container, 150 mm | C31: =IF(IF($E$5="Local prices",COUNTIFS(Offers!$B$7:$B$3000,$B31,Offers!$C$7:$C$3000,C$10,Offers!$AH$7:$AH$3000,"yes"),COUNTIFS(Offers!$B$7:$B$3000,$B31,Offers!$C$7:$C$3000,C$10,Offers!$AI$7:$AI$3000,"yes"))=0,"—",SUMIFS(Review!$O$7:$O$600,Review!$B$7:$B$600,$B31,Review!$C$7:$C$600,C$10)) -> — | D31: =IF(IF($E$5="Local prices",COUNTIFS(Offers!$B$7:$B$3000,$B31,Offers!$C$7:$C$3000,D$10,Offers!$AH$7:$AH$3000,"yes"),COUNTIFS(Offers!$B$7:$B$3000,$B31,Offers!$C$7:$C$3000,D$10,Offers!$AI$7:$AI$3000,"yes"))=0,"—",SUMIFS(Review!$O$7:$O$600,Review!$B$7:$B$600,$B31,Review!$C$7:$C$600,D$10)) -> — | E31: =IF(IF($E$5="Local prices",COUNTIFS(Offers!$B$7:$B$3000,$B31,Offers!$C$7:$C$3000,E$10,Offers!$AH$7:$AH$3000,"yes"),COUNTIFS(Offers!$B$7:$B$3000,$B31,Offers!$C$7:$C$3000,E$10,Offers!$AI$7:$AI$3000,"yes"))=0,"—",SUMIFS(Review!$O$7:$O$600,Review!$B$7:$B$600,$B31,Review!$C$7:$C$600,E$10)) -> 6.99 | F31: =IF(IF($E$5="Local prices",COUNTIFS(Offers!$B$7:$B$3000,$B31,Offers!$C$7:$C$3000,F$10,Offers!$AH$7:$AH$3000,"yes"),COUNTIFS(Offers!$B$7:$B$3000,$B31,Offers!$C$7:$C$3000,F$10,Offers!$AI$7:$AI$3000,"yes"))=0,"—",SUMIFS(Review!$O$7:$O$600,Review!$B$7:$B$600,$B31,Review!$C$7:$C$600,F$10)) -> 9.94 | G31: =IF(IF($E$5="Local prices",COUNTIFS(Offers!$B$7:$B$3000,$B31,Offers!$C$7:$C$3000,G$10,Offers!$AH$7:$AH$3000,"yes"),COUNTIFS(Offers!$B$7:$B$3000,$B31,Offers!$C$7:$C$3000,G$10,Offers!$AI$7:$AI$3000,"yes"))=0,"—",SUMIFS(Review!$O$7:$O$600,Review!$B$7:$B$600,$B31,Review!$C$7:$C$600,G$10)) -> 6.0333 | H31: =IF(IF($E$5="Local prices",COUNTIFS(Offers!$B$7:$B$3000,$B31,Offers!$C$7:$C$3000,H$10,Offers!$AH$7:$AH$3000,"yes"),COUNTIFS(Offers!$B$7:$B$3000,$B31,Offers!$C$7:$C$3000,H$10,Offers!$AI$7:$AI$3000,"yes"))=0,"—",SUMIFS(Review!$O$7:$O$600,Review!$B$7:$B$600,$B31,Review!$C$7:$C$600,H$10)) -> —
B32: GN 1/1 PC lid | C32: =IF(IF($E$5="Local prices",COUNTIFS(Offers!$B$7:$B$3000,$B32,Offers!$C$7:$C$3000,C$10,Offers!$AH$7:$AH$3000,"yes"),COUNTIFS(Offers!$B$7:$B$3000,$B32,Offers!$C$7:$C$3000,C$10,Offers!$AI$7:$AI$3000,"yes"))=0,"—",SUMIFS(Review!$O$7:$O$600,Review!$B$7:$B$600,$B32,Review!$C$7:$C$600,C$10)) -> — | D32: =IF(IF($E$5="Local prices",COUNTIFS(Offers!$B$7:$B$3000,$B32,Offers!$C$7:$C$3000,D$10,Offers!$AH$7:$AH$3000,"yes"),COUNTIFS(Offers!$B$7:$B$3000,$B32,Offers!$C$7:$C$3000,D$10,Offers!$AI$7:$AI$3000,"yes"))=0,"—",SUMIFS(Review!$O$7:$O$600,Review!$B$7:$B$600,$B32,Review!$C$7:$C$600,D$10)) -> — | E32: =IF(IF($E$5="Local prices",COUNTIFS(Offers!$B$7:$B$3000,$B32,Offers!$C$7:$C$3000,E$10,Offers!$AH$7:$AH$3000,"yes"),COUNTIFS(Offers!$B$7:$B$3000,$B32,Offers!$C$7:$C$3000,E$10,Offers!$AI$7:$AI$3000,"yes"))=0,"—",SUMIFS(Review!$O$7:$O$600,Review!$B$7:$B$600,$B32,Review!$C$7:$C$600,E$10)) -> 10.39 | F32: =IF(IF($E$5="Local prices",COUNTIFS(Offers!$B$7:$B$3000,$B32,Offers!$C$7:$C$3000,F$10,Offers!$AH$7:$AH$3000,"yes"),COUNTIFS(Offers!$B$7:$B$3000,$B32,Offers!$C$7:$C$3000,F$10,Offers!$AI$7:$AI$3000,"yes"))=0,"—",SUMIFS(Review!$O$7:$O$600,Review!$B$7:$B$600,$B32,Review!$C$7:$C$600,F$10)) -> 9.245 | G32: =IF(IF($E$5="Local prices",COUNTIFS(Offers!$B$7:$B$3000,$B32,Offers!$C$7:$C$3000,G$10,Offers!$AH$7:$AH$3000,"yes"),COUNTIFS(Offers!$B$7:$B$3000,$B32,Offers!$C$7:$C$3000,G$10,Offers!$AI$7:$AI$3000,"yes"))=0,"—",SUMIFS(Review!$O$7:$O$600,Review!$B$7:$B$600,$B32,Review!$C$7:$C$600,G$10)) -> 10.826816 | H32: =IF(IF($E$5="Local prices",COUNTIFS(Offers!$B$7:$B$3000,$B32,Offers!$C$7:$C$3000,H$10,Offers!$AH$7:$AH$3000,"yes"),COUNTIFS(Offers!$B$7:$B$3000,$B32,Offers!$C$7:$C$3000,H$10,Offers!$AI$7:$AI$3000,"yes"))=0,"—",SUMIFS(Review!$O$7:$O$600,Review!$B$7:$B$600,$B32,Review!$C$7:$C$600,H$10)) -> — | J32: Match scope
B33: GN 1/6 PP container, 100 mm | C33: =IF(IF($E$5="Local prices",COUNTIFS(Offers!$B$7:$B$3000,$B33,Offers!$C$7:$C$3000,C$10,Offers!$AH$7:$AH$3000,"yes"),COUNTIFS(Offers!$B$7:$B$3000,$B33,Offers!$C$7:$C$3000,C$10,Offers!$AI$7:$AI$3000,"yes"))=0,"—",SUMIFS(Review!$O$7:$O$600,Review!$B$7:$B$600,$B33,Review!$C$7:$C$600,C$10)) -> — | D33: =IF(IF($E$5="Local prices",COUNTIFS(Offers!$B$7:$B$3000,$B33,Offers!$C$7:$C$3000,D$10,Offers!$AH$7:$AH$3000,"yes"),COUNTIFS(Offers!$B$7:$B$3000,$B33,Offers!$C$7:$C$3000,D$10,Offers!$AI$7:$AI$3000,"yes"))=0,"—",SUMIFS(Review!$O$7:$O$600,Review!$B$7:$B$600,$B33,Review!$C$7:$C$600,D$10)) -> — | E33: =IF(IF($E$5="Local prices",COUNTIFS(Offers!$B$7:$B$3000,$B33,Offers!$C$7:$C$3000,E$10,Offers!$AH$7:$AH$3000,"yes"),COUNTIFS(Offers!$B$7:$B$3000,$B33,Offers!$C$7:$C$3000,E$10,Offers!$AI$7:$AI$3000,"yes"))=0,"—",SUMIFS(Review!$O$7:$O$600,Review!$B$7:$B$600,$B33,Review!$C$7:$C$600,E$10)) -> 3.44 | F33: =IF(IF($E$5="Local prices",COUNTIFS(Offers!$B$7:$B$3000,$B33,Offers!$C$7:$C$3000,F$10,Offers!$AH$7:$AH$3000,"yes"),COUNTIFS(Offers!$B$7:$B$3000,$B33,Offers!$C$7:$C$3000,F$10,Offers!$AI$7:$AI$3000,"yes"))=0,"—",SUMIFS(Review!$O$7:$O$600,Review!$B$7:$B$600,$B33,Review!$C$7:$C$600,F$10)) -> 2.315 | G33: =IF(IF($E$5="Local prices",COUNTIFS(Offers!$B$7:$B$3000,$B33,Offers!$C$7:$C$3000,G$10,Offers!$AH$7:$AH$3000,"yes"),COUNTIFS(Offers!$B$7:$B$3000,$B33,Offers!$C$7:$C$3000,G$10,Offers!$AI$7:$AI$3000,"yes"))=0,"—",SUMIFS(Review!$O$7:$O$600,Review!$B$7:$B$600,$B33,Review!$C$7:$C$600,G$10)) -> 3.125868 | H33: =IF(IF($E$5="Local prices",COUNTIFS(Offers!$B$7:$B$3000,$B33,Offers!$C$7:$C$3000,H$10,Offers!$AH$7:$AH$3000,"yes"),COUNTIFS(Offers!$B$7:$B$3000,$B33,Offers!$C$7:$C$3000,H$10,Offers!$AI$7:$AI$3000,"yes"))=0,"—",SUMIFS(Review!$O$7:$O$600,Review!$B$7:$B$600,$B33,Review!$C$7:$C$600,H$10)) -> — | J33: All mapped includes near matches and incomplete specifications. Check their notes before deciding.
B34: GN 1/9 PP container, 100 mm | C34: =IF(IF($E$5="Local prices",COUNTIFS(Offers!$B$7:$B$3000,$B34,Offers!$C$7:$C$3000,C$10,Offers!$AH$7:$AH$3000,"yes"),COUNTIFS(Offers!$B$7:$B$3000,$B34,Offers!$C$7:$C$3000,C$10,Offers!$AI$7:$AI$3000,"yes"))=0,"—",SUMIFS(Review!$O$7:$O$600,Review!$B$7:$B$600,$B34,Review!$C$7:$C$600,C$10)) -> — | D34: =IF(IF($E$5="Local prices",COUNTIFS(Offers!$B$7:$B$3000,$B34,Offers!$C$7:$C$3000,D$10,Offers!$AH$7:$AH$3000,"yes"),COUNTIFS(Offers!$B$7:$B$3000,$B34,Offers!$C$7:$C$3000,D$10,Offers!$AI$7:$AI$3000,"yes"))=0,"—",SUMIFS(Review!$O$7:$O$600,Review!$B$7:$B$600,$B34,Review!$C$7:$C$600,D$10)) -> — | E34: =IF(IF($E$5="Local prices",COUNTIFS(Offers!$B$7:$B$3000,$B34,Offers!$C$7:$C$3000,E$10,Offers!$AH$7:$AH$3000,"yes"),COUNTIFS(Offers!$B$7:$B$3000,$B34,Offers!$C$7:$C$3000,E$10,Offers!$AI$7:$AI$3000,"yes"))=0,"—",SUMIFS(Review!$O$7:$O$600,Review!$B$7:$B$600,$B34,Review!$C$7:$C$600,E$10)) -> 3.5 | F34: =IF(IF($E$5="Local prices",COUNTIFS(Offers!$B$7:$B$3000,$B34,Offers!$C$7:$C$3000,F$10,Offers!$AH$7:$AH$3000,"yes"),COUNTIFS(Offers!$B$7:$B$3000,$B34,Offers!$C$7:$C$3000,F$10,Offers!$AI$7:$AI$3000,"yes"))=0,"—",SUMIFS(Review!$O$7:$O$600,Review!$B$7:$B$600,$B34,Review!$C$7:$C$600,F$10)) -> 2.79 | G34: =IF(IF($E$5="Local prices",COUNTIFS(Offers!$B$7:$B$3000,$B34,Offers!$C$7:$C$3000,G$10,Offers!$AH$7:$AH$3000,"yes"),COUNTIFS(Offers!$B$7:$B$3000,$B34,Offers!$C$7:$C$3000,G$10,Offers!$AI$7:$AI$3000,"yes"))=0,"—",SUMIFS(Review!$O$7:$O$600,Review!$B$7:$B$600,$B34,Review!$C$7:$C$600,G$10)) -> 2.825135 | H34: =IF(IF($E$5="Local prices",COUNTIFS(Offers!$B$7:$B$3000,$B34,Offers!$C$7:$C$3000,H$10,Offers!$AH$7:$AH$3000,"yes"),COUNTIFS(Offers!$B$7:$B$3000,$B34,Offers!$C$7:$C$3000,H$10,Offers!$AI$7:$AI$3000,"yes"))=0,"—",SUMIFS(Review!$O$7:$O$600,Review!$B$7:$B$600,$B34,Review!$C$7:$C$600,H$10)) -> —
B35: Squeeze bottle 250 ml, PP, single tip | C35: =IF(IF($E$5="Local prices",COUNTIFS(Offers!$B$7:$B$3000,$B35,Offers!$C$7:$C$3000,C$10,Offers!$AH$7:$AH$3000,"yes"),COUNTIFS(Offers!$B$7:$B$3000,$B35,Offers!$C$7:$C$3000,C$10,Offers!$AI$7:$AI$3000,"yes"))=0,"—",SUMIFS(Review!$O$7:$O$600,Review!$B$7:$B$600,$B35,Review!$C$7:$C$600,C$10)) -> — | D35: =IF(IF($E$5="Local prices",COUNTIFS(Offers!$B$7:$B$3000,$B35,Offers!$C$7:$C$3000,D$10,Offers!$AH$7:$AH$3000,"yes"),COUNTIFS(Offers!$B$7:$B$3000,$B35,Offers!$C$7:$C$3000,D$10,Offers!$AI$7:$AI$3000,"yes"))=0,"—",SUMIFS(Review!$O$7:$O$600,Review!$B$7:$B$600,$B35,Review!$C$7:$C$600,D$10)) -> — | E35: =IF(IF($E$5="Local prices",COUNTIFS(Offers!$B$7:$B$3000,$B35,Offers!$C$7:$C$3000,E$10,Offers!$AH$7:$AH$3000,"yes"),COUNTIFS(Offers!$B$7:$B$3000,$B35,Offers!$C$7:$C$3000,E$10,Offers!$AI$7:$AI$3000,"yes"))=0,"—",SUMIFS(Review!$O$7:$O$600,Review!$B$7:$B$600,$B35,Review!$C$7:$C$600,E$10)) -> 1.175 | F35: =IF(IF($E$5="Local prices",COUNTIFS(Offers!$B$7:$B$3000,$B35,Offers!$C$7:$C$3000,F$10,Offers!$AH$7:$AH$3000,"yes"),COUNTIFS(Offers!$B$7:$B$3000,$B35,Offers!$C$7:$C$3000,F$10,Offers!$AI$7:$AI$3000,"yes"))=0,"—",SUMIFS(Review!$O$7:$O$600,Review!$B$7:$B$600,$B35,Review!$C$7:$C$600,F$10)) -> 1.08 | G35: =IF(IF($E$5="Local prices",COUNTIFS(Offers!$B$7:$B$3000,$B35,Offers!$C$7:$C$3000,G$10,Offers!$AH$7:$AH$3000,"yes"),COUNTIFS(Offers!$B$7:$B$3000,$B35,Offers!$C$7:$C$3000,G$10,Offers!$AI$7:$AI$3000,"yes"))=0,"—",SUMIFS(Review!$O$7:$O$600,Review!$B$7:$B$600,$B35,Review!$C$7:$C$600,G$10)) -> 1.7397095 | H35: =IF(IF($E$5="Local prices",COUNTIFS(Offers!$B$7:$B$3000,$B35,Offers!$C$7:$C$3000,H$10,Offers!$AH$7:$AH$3000,"yes"),COUNTIFS(Offers!$B$7:$B$3000,$B35,Offers!$C$7:$C$3000,H$10,Offers!$AI$7:$AI$3000,"yes"))=0,"—",SUMIFS(Review!$O$7:$O$600,Review!$B$7:$B$600,$B35,Review!$C$7:$C$600,H$10)) -> —
B36: Squeeze bottle 750 ml, PP, single tip | C36: =IF(IF($E$5="Local prices",COUNTIFS(Offers!$B$7:$B$3000,$B36,Offers!$C$7:$C$3000,C$10,Offers!$AH$7:$AH$3000,"yes"),COUNTIFS(Offers!$B$7:$B$3000,$B36,Offers!$C$7:$C$3000,C$10,Offers!$AI$7:$AI$3000,"yes"))=0,"—",SUMIFS(Review!$O$7:$O$600,Review!$B$7:$B$600,$B36,Review!$C$7:$C$600,C$10)) -> — | D36: =IF(IF($E$5="Local prices",COUNTIFS(Offers!$B$7:$B$3000,$B36,Offers!$C$7:$C$3000,D$10,Offers!$AH$7:$AH$3000,"yes"),COUNTIFS(Offers!$B$7:$B$3000,$B36,Offers!$C$7:$C$3000,D$10,Offers!$AI$7:$AI$3000,"yes"))=0,"—",SUMIFS(Review!$O$7:$O$600,Review!$B$7:$B$600,$B36,Review!$C$7:$C$600,D$10)) -> — | E36: =IF(IF($E$5="Local prices",COUNTIFS(Offers!$B$7:$B$3000,$B36,Offers!$C$7:$C$3000,E$10,Offers!$AH$7:$AH$3000,"yes"),COUNTIFS(Offers!$B$7:$B$3000,$B36,Offers!$C$7:$C$3000,E$10,Offers!$AI$7:$AI$3000,"yes"))=0,"—",SUMIFS(Review!$O$7:$O$600,Review!$B$7:$B$600,$B36,Review!$C$7:$C$600,E$10)) -> 1.73 | F36: =IF(IF($E$5="Local prices",COUNTIFS(Offers!$B$7:$B$3000,$B36,Offers!$C$7:$C$3000,F$10,Offers!$AH$7:$AH$3000,"yes"),COUNTIFS(Offers!$B$7:$B$3000,$B36,Offers!$C$7:$C$3000,F$10,Offers!$AI$7:$AI$3000,"yes"))=0,"—",SUMIFS(Review!$O$7:$O$600,Review!$B$7:$B$600,$B36,Review!$C$7:$C$600,F$10)) -> 1.08 | G36: =IF(IF($E$5="Local prices",COUNTIFS(Offers!$B$7:$B$3000,$B36,Offers!$C$7:$C$3000,G$10,Offers!$AH$7:$AH$3000,"yes"),COUNTIFS(Offers!$B$7:$B$3000,$B36,Offers!$C$7:$C$3000,G$10,Offers!$AI$7:$AI$3000,"yes"))=0,"—",SUMIFS(Review!$O$7:$O$600,Review!$B$7:$B$600,$B36,Review!$C$7:$C$600,G$10)) -> 1.555871 | H36: =IF(IF($E$5="Local prices",COUNTIFS(Offers!$B$7:$B$3000,$B36,Offers!$C$7:$C$3000,H$10,Offers!$AH$7:$AH$3000,"yes"),COUNTIFS(Offers!$B$7:$B$3000,$B36,Offers!$C$7:$C$3000,H$10,Offers!$AI$7:$AI$3000,"yes"))=0,"—",SUMIFS(Review!$O$7:$O$600,Review!$B$7:$B$600,$B36,Review!$C$7:$C$600,H$10)) -> — | J36: Additional variants
B37: Red PE cutting board 400 × 300 × 20 mm | C37: =IF(IF($E$5="Local prices",COUNTIFS(Offers!$B$7:$B$3000,$B37,Offers!$C$7:$C$3000,C$10,Offers!$AH$7:$AH$3000,"yes"),COUNTIFS(Offers!$B$7:$B$3000,$B37,Offers!$C$7:$C$3000,C$10,Offers!$AI$7:$AI$3000,"yes"))=0,"—",SUMIFS(Review!$O$7:$O$600,Review!$B$7:$B$600,$B37,Review!$C$7:$C$600,C$10)) -> — | D37: =IF(IF($E$5="Local prices",COUNTIFS(Offers!$B$7:$B$3000,$B37,Offers!$C$7:$C$3000,D$10,Offers!$AH$7:$AH$3000,"yes"),COUNTIFS(Offers!$B$7:$B$3000,$B37,Offers!$C$7:$C$3000,D$10,Offers!$AI$7:$AI$3000,"yes"))=0,"—",SUMIFS(Review!$O$7:$O$600,Review!$B$7:$B$600,$B37,Review!$C$7:$C$600,D$10)) -> — | E37: =IF(IF($E$5="Local prices",COUNTIFS(Offers!$B$7:$B$3000,$B37,Offers!$C$7:$C$3000,E$10,Offers!$AH$7:$AH$3000,"yes"),COUNTIFS(Offers!$B$7:$B$3000,$B37,Offers!$C$7:$C$3000,E$10,Offers!$AI$7:$AI$3000,"yes"))=0,"—",SUMIFS(Review!$O$7:$O$600,Review!$B$7:$B$600,$B37,Review!$C$7:$C$600,E$10)) -> 20.96 | F37: =IF(IF($E$5="Local prices",COUNTIFS(Offers!$B$7:$B$3000,$B37,Offers!$C$7:$C$3000,F$10,Offers!$AH$7:$AH$3000,"yes"),COUNTIFS(Offers!$B$7:$B$3000,$B37,Offers!$C$7:$C$3000,F$10,Offers!$AI$7:$AI$3000,"yes"))=0,"—",SUMIFS(Review!$O$7:$O$600,Review!$B$7:$B$600,$B37,Review!$C$7:$C$600,F$10)) -> 6.58 | G37: =IF(IF($E$5="Local prices",COUNTIFS(Offers!$B$7:$B$3000,$B37,Offers!$C$7:$C$3000,G$10,Offers!$AH$7:$AH$3000,"yes"),COUNTIFS(Offers!$B$7:$B$3000,$B37,Offers!$C$7:$C$3000,G$10,Offers!$AI$7:$AI$3000,"yes"))=0,"—",SUMIFS(Review!$O$7:$O$600,Review!$B$7:$B$600,$B37,Review!$C$7:$C$600,G$10)) -> 36.612515 | H37: =IF(IF($E$5="Local prices",COUNTIFS(Offers!$B$7:$B$3000,$B37,Offers!$C$7:$C$3000,H$10,Offers!$AH$7:$AH$3000,"yes"),COUNTIFS(Offers!$B$7:$B$3000,$B37,Offers!$C$7:$C$3000,H$10,Offers!$AI$7:$AI$3000,"yes"))=0,"—",SUMIFS(Review!$O$7:$O$600,Review!$B$7:$B$600,$B37,Review!$C$7:$C$600,H$10)) -> — | J37: Additional variants have research for Austria and Czechia (basket additions) or for AT/DE/CZ/SK/RO (GN expansion of 2 Oct 2026). A dash in the other markets means no offer has been recorded.
B38: PP dough box 600 × 400 × 75 mm, no lid | C38: =IF(IF($E$5="Local prices",COUNTIFS(Offers!$B$7:$B$3000,$B38,Offers!$C$7:$C$3000,C$10,Offers!$AH$7:$AH$3000,"yes"),COUNTIFS(Offers!$B$7:$B$3000,$B38,Offers!$C$7:$C$3000,C$10,Offers!$AI$7:$AI$3000,"yes"))=0,"—",SUMIFS(Review!$O$7:$O$600,Review!$B$7:$B$600,$B38,Review!$C$7:$C$600,C$10)) -> — | D38: =IF(IF($E$5="Local prices",COUNTIFS(Offers!$B$7:$B$3000,$B38,Offers!$C$7:$C$3000,D$10,Offers!$AH$7:$AH$3000,"yes"),COUNTIFS(Offers!$B$7:$B$3000,$B38,Offers!$C$7:$C$3000,D$10,Offers!$AI$7:$AI$3000,"yes"))=0,"—",SUMIFS(Review!$O$7:$O$600,Review!$B$7:$B$600,$B38,Review!$C$7:$C$600,D$10)) -> — | E38: =IF(IF($E$5="Local prices",COUNTIFS(Offers!$B$7:$B$3000,$B38,Offers!$C$7:$C$3000,E$10,Offers!$AH$7:$AH$3000,"yes"),COUNTIFS(Offers!$B$7:$B$3000,$B38,Offers!$C$7:$C$3000,E$10,Offers!$AI$7:$AI$3000,"yes"))=0,"—",SUMIFS(Review!$O$7:$O$600,Review!$B$7:$B$600,$B38,Review!$C$7:$C$600,E$10)) -> 21.46 | F38: =IF(IF($E$5="Local prices",COUNTIFS(Offers!$B$7:$B$3000,$B38,Offers!$C$7:$C$3000,F$10,Offers!$AH$7:$AH$3000,"yes"),COUNTIFS(Offers!$B$7:$B$3000,$B38,Offers!$C$7:$C$3000,F$10,Offers!$AI$7:$AI$3000,"yes"))=0,"—",SUMIFS(Review!$O$7:$O$600,Review!$B$7:$B$600,$B38,Review!$C$7:$C$600,F$10)) -> 9.4 | G38: =IF(IF($E$5="Local prices",COUNTIFS(Offers!$B$7:$B$3000,$B38,Offers!$C$7:$C$3000,G$10,Offers!$AH$7:$AH$3000,"yes"),COUNTIFS(Offers!$B$7:$B$3000,$B38,Offers!$C$7:$C$3000,G$10,Offers!$AI$7:$AI$3000,"yes"))=0,"—",SUMIFS(Review!$O$7:$O$600,Review!$B$7:$B$600,$B38,Review!$C$7:$C$600,G$10)) -> 10.557609 | H38: =IF(IF($E$5="Local prices",COUNTIFS(Offers!$B$7:$B$3000,$B38,Offers!$C$7:$C$3000,H$10,Offers!$AH$7:$AH$3000,"yes"),COUNTIFS(Offers!$B$7:$B$3000,$B38,Offers!$C$7:$C$3000,H$10,Offers!$AI$7:$AI$3000,"yes"))=0,"—",SUMIFS(Review!$O$7:$O$600,Review!$B$7:$B$600,$B38,Review!$C$7:$C$600,H$10)) -> —
B39: GN 1/1 PC container, 100 mm | C39: =IF(IF($E$5="Local prices",COUNTIFS(Offers!$B$7:$B$3000,$B39,Offers!$C$7:$C$3000,C$10,Offers!$AH$7:$AH$3000,"yes"),COUNTIFS(Offers!$B$7:$B$3000,$B39,Offers!$C$7:$C$3000,C$10,Offers!$AI$7:$AI$3000,"yes"))=0,"—",SUMIFS(Review!$O$7:$O$600,Review!$B$7:$B$600,$B39,Review!$C$7:$C$600,C$10)) -> — | D39: =IF(IF($E$5="Local prices",COUNTIFS(Offers!$B$7:$B$3000,$B39,Offers!$C$7:$C$3000,D$10,Offers!$AH$7:$AH$3000,"yes"),COUNTIFS(Offers!$B$7:$B$3000,$B39,Offers!$C$7:$C$3000,D$10,Offers!$AI$7:$AI$3000,"yes"))=0,"—",SUMIFS(Review!$O$7:$O$600,Review!$B$7:$B$600,$B39,Review!$C$7:$C$600,D$10)) -> — | E39: =IF(IF($E$5="Local prices",COUNTIFS(Offers!$B$7:$B$3000,$B39,Offers!$C$7:$C$3000,E$10,Offers!$AH$7:$AH$3000,"yes"),COUNTIFS(Offers!$B$7:$B$3000,$B39,Offers!$C$7:$C$3000,E$10,Offers!$AI$7:$AI$3000,"yes"))=0,"—",SUMIFS(Review!$O$7:$O$600,Review!$B$7:$B$600,$B39,Review!$C$7:$C$600,E$10)) -> 17.545 | F39: =IF(IF($E$5="Local prices",COUNTIFS(Offers!$B$7:$B$3000,$B39,Offers!$C$7:$C$3000,F$10,Offers!$AH$7:$AH$3000,"yes"),COUNTIFS(Offers!$B$7:$B$3000,$B39,Offers!$C$7:$C$3000,F$10,Offers!$AI$7:$AI$3000,"yes"))=0,"—",SUMIFS(Review!$O$7:$O$600,Review!$B$7:$B$600,$B39,Review!$C$7:$C$600,F$10)) -> 13.62 | G39: =IF(IF($E$5="Local prices",COUNTIFS(Offers!$B$7:$B$3000,$B39,Offers!$C$7:$C$3000,G$10,Offers!$AH$7:$AH$3000,"yes"),COUNTIFS(Offers!$B$7:$B$3000,$B39,Offers!$C$7:$C$3000,G$10,Offers!$AI$7:$AI$3000,"yes"))=0,"—",SUMIFS(Review!$O$7:$O$600,Review!$B$7:$B$600,$B39,Review!$C$7:$C$600,G$10)) -> 11.83281 | H39: =IF(IF($E$5="Local prices",COUNTIFS(Offers!$B$7:$B$3000,$B39,Offers!$C$7:$C$3000,H$10,Offers!$AH$7:$AH$3000,"yes"),COUNTIFS(Offers!$B$7:$B$3000,$B39,Offers!$C$7:$C$3000,H$10,Offers!$AI$7:$AI$3000,"yes"))=0,"—",SUMIFS(Review!$O$7:$O$600,Review!$B$7:$B$600,$B39,Review!$C$7:$C$600,H$10)) -> —
B40: GN 1/6 PC container, 100 mm | C40: =IF(IF($E$5="Local prices",COUNTIFS(Offers!$B$7:$B$3000,$B40,Offers!$C$7:$C$3000,C$10,Offers!$AH$7:$AH$3000,"yes"),COUNTIFS(Offers!$B$7:$B$3000,$B40,Offers!$C$7:$C$3000,C$10,Offers!$AI$7:$AI$3000,"yes"))=0,"—",SUMIFS(Review!$O$7:$O$600,Review!$B$7:$B$600,$B40,Review!$C$7:$C$600,C$10)) -> — | D40: =IF(IF($E$5="Local prices",COUNTIFS(Offers!$B$7:$B$3000,$B40,Offers!$C$7:$C$3000,D$10,Offers!$AH$7:$AH$3000,"yes"),COUNTIFS(Offers!$B$7:$B$3000,$B40,Offers!$C$7:$C$3000,D$10,Offers!$AI$7:$AI$3000,"yes"))=0,"—",SUMIFS(Review!$O$7:$O$600,Review!$B$7:$B$600,$B40,Review!$C$7:$C$600,D$10)) -> — | E40: =IF(IF($E$5="Local prices",COUNTIFS(Offers!$B$7:$B$3000,$B40,Offers!$C$7:$C$3000,E$10,Offers!$AH$7:$AH$3000,"yes"),COUNTIFS(Offers!$B$7:$B$3000,$B40,Offers!$C$7:$C$3000,E$10,Offers!$AI$7:$AI$3000,"yes"))=0,"—",SUMIFS(Review!$O$7:$O$600,Review!$B$7:$B$600,$B40,Review!$C$7:$C$600,E$10)) -> 4.13 | F40: =IF(IF($E$5="Local prices",COUNTIFS(Offers!$B$7:$B$3000,$B40,Offers!$C$7:$C$3000,F$10,Offers!$AH$7:$AH$3000,"yes"),COUNTIFS(Offers!$B$7:$B$3000,$B40,Offers!$C$7:$C$3000,F$10,Offers!$AI$7:$AI$3000,"yes"))=0,"—",SUMIFS(Review!$O$7:$O$600,Review!$B$7:$B$600,$B40,Review!$C$7:$C$600,F$10)) -> 3.75 | G40: =IF(IF($E$5="Local prices",COUNTIFS(Offers!$B$7:$B$3000,$B40,Offers!$C$7:$C$3000,G$10,Offers!$AH$7:$AH$3000,"yes"),COUNTIFS(Offers!$B$7:$B$3000,$B40,Offers!$C$7:$C$3000,G$10,Offers!$AI$7:$AI$3000,"yes"))=0,"—",SUMIFS(Review!$O$7:$O$600,Review!$B$7:$B$600,$B40,Review!$C$7:$C$600,G$10)) -> 3.9164965 | H40: =IF(IF($E$5="Local prices",COUNTIFS(Offers!$B$7:$B$3000,$B40,Offers!$C$7:$C$3000,H$10,Offers!$AH$7:$AH$3000,"yes"),COUNTIFS(Offers!$B$7:$B$3000,$B40,Offers!$C$7:$C$3000,H$10,Offers!$AI$7:$AI$3000,"yes"))=0,"—",SUMIFS(Review!$O$7:$O$600,Review!$B$7:$B$600,$B40,Review!$C$7:$C$600,H$10)) -> —
B41: Red PE cutting board 530 × 325 × 15 mm | C41: =IF(IF($E$5="Local prices",COUNTIFS(Offers!$B$7:$B$3000,$B41,Offers!$C$7:$C$3000,C$10,Offers!$AH$7:$AH$3000,"yes"),COUNTIFS(Offers!$B$7:$B$3000,$B41,Offers!$C$7:$C$3000,C$10,Offers!$AI$7:$AI$3000,"yes"))=0,"—",SUMIFS(Review!$O$7:$O$600,Review!$B$7:$B$600,$B41,Review!$C$7:$C$600,C$10)) -> — | D41: =IF(IF($E$5="Local prices",COUNTIFS(Offers!$B$7:$B$3000,$B41,Offers!$C$7:$C$3000,D$10,Offers!$AH$7:$AH$3000,"yes"),COUNTIFS(Offers!$B$7:$B$3000,$B41,Offers!$C$7:$C$3000,D$10,Offers!$AI$7:$AI$3000,"yes"))=0,"—",SUMIFS(Review!$O$7:$O$600,Review!$B$7:$B$600,$B41,Review!$C$7:$C$600,D$10)) -> — | E41: =IF(IF($E$5="Local prices",COUNTIFS(Offers!$B$7:$B$3000,$B41,Offers!$C$7:$C$3000,E$10,Offers!$AH$7:$AH$3000,"yes"),COUNTIFS(Offers!$B$7:$B$3000,$B41,Offers!$C$7:$C$3000,E$10,Offers!$AI$7:$AI$3000,"yes"))=0,"—",SUMIFS(Review!$O$7:$O$600,Review!$B$7:$B$600,$B41,Review!$C$7:$C$600,E$10)) -> 25.53 | F41: =IF(IF($E$5="Local prices",COUNTIFS(Offers!$B$7:$B$3000,$B41,Offers!$C$7:$C$3000,F$10,Offers!$AH$7:$AH$3000,"yes"),COUNTIFS(Offers!$B$7:$B$3000,$B41,Offers!$C$7:$C$3000,F$10,Offers!$AI$7:$AI$3000,"yes"))=0,"—",SUMIFS(Review!$O$7:$O$600,Review!$B$7:$B$600,$B41,Review!$C$7:$C$600,F$10)) -> 24.05 | G41: =IF(IF($E$5="Local prices",COUNTIFS(Offers!$B$7:$B$3000,$B41,Offers!$C$7:$C$3000,G$10,Offers!$AH$7:$AH$3000,"yes"),COUNTIFS(Offers!$B$7:$B$3000,$B41,Offers!$C$7:$C$3000,G$10,Offers!$AI$7:$AI$3000,"yes"))=0,"—",SUMIFS(Review!$O$7:$O$600,Review!$B$7:$B$600,$B41,Review!$C$7:$C$600,G$10)) -> 37.709404 | H41: =IF(IF($E$5="Local prices",COUNTIFS(Offers!$B$7:$B$3000,$B41,Offers!$C$7:$C$3000,H$10,Offers!$AH$7:$AH$3000,"yes"),COUNTIFS(Offers!$B$7:$B$3000,$B41,Offers!$C$7:$C$3000,H$10,Offers!$AI$7:$AI$3000,"yes"))=0,"—",SUMIFS(Review!$O$7:$O$600,Review!$B$7:$B$600,$B41,Review!$C$7:$C$600,H$10)) -> —
B42: GN 1/3 PP lid | C42: =IF(IF($E$5="Local prices",COUNTIFS(Offers!$B$7:$B$3000,$B42,Offers!$C$7:$C$3000,C$10,Offers!$AH$7:$AH$3000,"yes"),COUNTIFS(Offers!$B$7:$B$3000,$B42,Offers!$C$7:$C$3000,C$10,Offers!$AI$7:$AI$3000,"yes"))=0,"—",SUMIFS(Review!$O$7:$O$600,Review!$B$7:$B$600,$B42,Review!$C$7:$C$600,C$10)) -> — | D42: =IF(IF($E$5="Local prices",COUNTIFS(Offers!$B$7:$B$3000,$B42,Offers!$C$7:$C$3000,D$10,Offers!$AH$7:$AH$3000,"yes"),COUNTIFS(Offers!$B$7:$B$3000,$B42,Offers!$C$7:$C$3000,D$10,Offers!$AI$7:$AI$3000,"yes"))=0,"—",SUMIFS(Review!$O$7:$O$600,Review!$B$7:$B$600,$B42,Review!$C$7:$C$600,D$10)) -> — | E42: =IF(IF($E$5="Local prices",COUNTIFS(Offers!$B$7:$B$3000,$B42,Offers!$C$7:$C$3000,E$10,Offers!$AH$7:$AH$3000,"yes"),COUNTIFS(Offers!$B$7:$B$3000,$B42,Offers!$C$7:$C$3000,E$10,Offers!$AI$7:$AI$3000,"yes"))=0,"—",SUMIFS(Review!$O$7:$O$600,Review!$B$7:$B$600,$B42,Review!$C$7:$C$600,E$10)) -> 3.27 | F42: =IF(IF($E$5="Local prices",COUNTIFS(Offers!$B$7:$B$3000,$B42,Offers!$C$7:$C$3000,F$10,Offers!$AH$7:$AH$3000,"yes"),COUNTIFS(Offers!$B$7:$B$3000,$B42,Offers!$C$7:$C$3000,F$10,Offers!$AI$7:$AI$3000,"yes"))=0,"—",SUMIFS(Review!$O$7:$O$600,Review!$B$7:$B$600,$B42,Review!$C$7:$C$600,F$10)) -> 3.17 | G42: =IF(IF($E$5="Local prices",COUNTIFS(Offers!$B$7:$B$3000,$B42,Offers!$C$7:$C$3000,G$10,Offers!$AH$7:$AH$3000,"yes"),COUNTIFS(Offers!$B$7:$B$3000,$B42,Offers!$C$7:$C$3000,G$10,Offers!$AI$7:$AI$3000,"yes"))=0,"—",SUMIFS(Review!$O$7:$O$600,Review!$B$7:$B$600,$B42,Review!$C$7:$C$600,G$10)) -> 2.7223655 | H42: =IF(IF($E$5="Local prices",COUNTIFS(Offers!$B$7:$B$3000,$B42,Offers!$C$7:$C$3000,H$10,Offers!$AH$7:$AH$3000,"yes"),COUNTIFS(Offers!$B$7:$B$3000,$B42,Offers!$C$7:$C$3000,H$10,Offers!$AI$7:$AI$3000,"yes"))=0,"—",SUMIFS(Review!$O$7:$O$600,Review!$B$7:$B$600,$B42,Review!$C$7:$C$600,H$10)) -> —
B43: Squeeze bottle 750 ml, PP/PE, wide covered tip | C43: =IF(IF($E$5="Local prices",COUNTIFS(Offers!$B$7:$B$3000,$B43,Offers!$C$7:$C$3000,C$10,Offers!$AH$7:$AH$3000,"yes"),COUNTIFS(Offers!$B$7:$B$3000,$B43,Offers!$C$7:$C$3000,C$10,Offers!$AI$7:$AI$3000,"yes"))=0,"—",SUMIFS(Review!$O$7:$O$600,Review!$B$7:$B$600,$B43,Review!$C$7:$C$600,C$10)) -> — | D43: =IF(IF($E$5="Local prices",COUNTIFS(Offers!$B$7:$B$3000,$B43,Offers!$C$7:$C$3000,D$10,Offers!$AH$7:$AH$3000,"yes"),COUNTIFS(Offers!$B$7:$B$3000,$B43,Offers!$C$7:$C$3000,D$10,Offers!$AI$7:$AI$3000,"yes"))=0,"—",SUMIFS(Review!$O$7:$O$600,Review!$B$7:$B$600,$B43,Review!$C$7:$C$600,D$10)) -> — | E43: =IF(IF($E$5="Local prices",COUNTIFS(Offers!$B$7:$B$3000,$B43,Offers!$C$7:$C$3000,E$10,Offers!$AH$7:$AH$3000,"yes"),COUNTIFS(Offers!$B$7:$B$3000,$B43,Offers!$C$7:$C$3000,E$10,Offers!$AI$7:$AI$3000,"yes"))=0,"—",SUMIFS(Review!$O$7:$O$600,Review!$B$7:$B$600,$B43,Review!$C$7:$C$600,E$10)) -> 1.73 | F43: =IF(IF($E$5="Local prices",COUNTIFS(Offers!$B$7:$B$3000,$B43,Offers!$C$7:$C$3000,F$10,Offers!$AH$7:$AH$3000,"yes"),COUNTIFS(Offers!$B$7:$B$3000,$B43,Offers!$C$7:$C$3000,F$10,Offers!$AI$7:$AI$3000,"yes"))=0,"—",SUMIFS(Review!$O$7:$O$600,Review!$B$7:$B$600,$B43,Review!$C$7:$C$600,F$10)) -> — | G43: =IF(IF($E$5="Local prices",COUNTIFS(Offers!$B$7:$B$3000,$B43,Offers!$C$7:$C$3000,G$10,Offers!$AH$7:$AH$3000,"yes"),COUNTIFS(Offers!$B$7:$B$3000,$B43,Offers!$C$7:$C$3000,G$10,Offers!$AI$7:$AI$3000,"yes"))=0,"—",SUMIFS(Review!$O$7:$O$600,Review!$B$7:$B$600,$B43,Review!$C$7:$C$600,G$10)) -> 2.435962 | H43: =IF(IF($E$5="Local prices",COUNTIFS(Offers!$B$7:$B$3000,$B43,Offers!$C$7:$C$3000,H$10,Offers!$AH$7:$AH$3000,"yes"),COUNTIFS(Offers!$B$7:$B$3000,$B43,Offers!$C$7:$C$3000,H$10,Offers!$AI$7:$AI$3000,"yes"))=0,"—",SUMIFS(Review!$O$7:$O$600,Review!$B$7:$B$600,$B43,Review!$C$7:$C$600,H$10)) -> —
B44: Red PE cutting board 300 × 200 × 20 mm | C44: =IF(IF($E$5="Local prices",COUNTIFS(Offers!$B$7:$B$3000,$B44,Offers!$C$7:$C$3000,C$10,Offers!$AH$7:$AH$3000,"yes"),COUNTIFS(Offers!$B$7:$B$3000,$B44,Offers!$C$7:$C$3000,C$10,Offers!$AI$7:$AI$3000,"yes"))=0,"—",SUMIFS(Review!$O$7:$O$600,Review!$B$7:$B$600,$B44,Review!$C$7:$C$600,C$10)) -> — | D44: =IF(IF($E$5="Local prices",COUNTIFS(Offers!$B$7:$B$3000,$B44,Offers!$C$7:$C$3000,D$10,Offers!$AH$7:$AH$3000,"yes"),COUNTIFS(Offers!$B$7:$B$3000,$B44,Offers!$C$7:$C$3000,D$10,Offers!$AI$7:$AI$3000,"yes"))=0,"—",SUMIFS(Review!$O$7:$O$600,Review!$B$7:$B$600,$B44,Review!$C$7:$C$600,D$10)) -> — | E44: =IF(IF($E$5="Local prices",COUNTIFS(Offers!$B$7:$B$3000,$B44,Offers!$C$7:$C$3000,E$10,Offers!$AH$7:$AH$3000,"yes"),COUNTIFS(Offers!$B$7:$B$3000,$B44,Offers!$C$7:$C$3000,E$10,Offers!$AI$7:$AI$3000,"yes"))=0,"—",SUMIFS(Review!$O$7:$O$600,Review!$B$7:$B$600,$B44,Review!$C$7:$C$600,E$10)) -> 9.3 | F44: =IF(IF($E$5="Local prices",COUNTIFS(Offers!$B$7:$B$3000,$B44,Offers!$C$7:$C$3000,F$10,Offers!$AH$7:$AH$3000,"yes"),COUNTIFS(Offers!$B$7:$B$3000,$B44,Offers!$C$7:$C$3000,F$10,Offers!$AI$7:$AI$3000,"yes"))=0,"—",SUMIFS(Review!$O$7:$O$600,Review!$B$7:$B$600,$B44,Review!$C$7:$C$600,F$10)) -> — | G44: =IF(IF($E$5="Local prices",COUNTIFS(Offers!$B$7:$B$3000,$B44,Offers!$C$7:$C$3000,G$10,Offers!$AH$7:$AH$3000,"yes"),COUNTIFS(Offers!$B$7:$B$3000,$B44,Offers!$C$7:$C$3000,G$10,Offers!$AI$7:$AI$3000,"yes"))=0,"—",SUMIFS(Review!$O$7:$O$600,Review!$B$7:$B$600,$B44,Review!$C$7:$C$600,G$10)) -> — | H44: =IF(IF($E$5="Local prices",COUNTIFS(Offers!$B$7:$B$3000,$B44,Offers!$C$7:$C$3000,H$10,Offers!$AH$7:$AH$3000,"yes"),COUNTIFS(Offers!$B$7:$B$3000,$B44,Offers!$C$7:$C$3000,H$10,Offers!$AI$7:$AI$3000,"yes"))=0,"—",SUMIFS(Review!$O$7:$O$600,Review!$B$7:$B$600,$B44,Review!$C$7:$C$600,H$10)) -> —
B45: PP dough box 400 × 300 × 100 mm, no lid | C45: =IF(IF($E$5="Local prices",COUNTIFS(Offers!$B$7:$B$3000,$B45,Offers!$C$7:$C$3000,C$10,Offers!$AH$7:$AH$3000,"yes"),COUNTIFS(Offers!$B$7:$B$3000,$B45,Offers!$C$7:$C$3000,C$10,Offers!$AI$7:$AI$3000,"yes"))=0,"—",SUMIFS(Review!$O$7:$O$600,Review!$B$7:$B$600,$B45,Review!$C$7:$C$600,C$10)) -> — | D45: =IF(IF($E$5="Local prices",COUNTIFS(Offers!$B$7:$B$3000,$B45,Offers!$C$7:$C$3000,D$10,Offers!$AH$7:$AH$3000,"yes"),COUNTIFS(Offers!$B$7:$B$3000,$B45,Offers!$C$7:$C$3000,D$10,Offers!$AI$7:$AI$3000,"yes"))=0,"—",SUMIFS(Review!$O$7:$O$600,Review!$B$7:$B$600,$B45,Review!$C$7:$C$600,D$10)) -> — | E45: =IF(IF($E$5="Local prices",COUNTIFS(Offers!$B$7:$B$3000,$B45,Offers!$C$7:$C$3000,E$10,Offers!$AH$7:$AH$3000,"yes"),COUNTIFS(Offers!$B$7:$B$3000,$B45,Offers!$C$7:$C$3000,E$10,Offers!$AI$7:$AI$3000,"yes"))=0,"—",SUMIFS(Review!$O$7:$O$600,Review!$B$7:$B$600,$B45,Review!$C$7:$C$600,E$10)) -> 11.97 | F45: =IF(IF($E$5="Local prices",COUNTIFS(Offers!$B$7:$B$3000,$B45,Offers!$C$7:$C$3000,F$10,Offers!$AH$7:$AH$3000,"yes"),COUNTIFS(Offers!$B$7:$B$3000,$B45,Offers!$C$7:$C$3000,F$10,Offers!$AI$7:$AI$3000,"yes"))=0,"—",SUMIFS(Review!$O$7:$O$600,Review!$B$7:$B$600,$B45,Review!$C$7:$C$600,F$10)) -> 11.09 | G45: =IF(IF($E$5="Local prices",COUNTIFS(Offers!$B$7:$B$3000,$B45,Offers!$C$7:$C$3000,G$10,Offers!$AH$7:$AH$3000,"yes"),COUNTIFS(Offers!$B$7:$B$3000,$B45,Offers!$C$7:$C$3000,G$10,Offers!$AI$7:$AI$3000,"yes"))=0,"—",SUMIFS(Review!$O$7:$O$600,Review!$B$7:$B$600,$B45,Review!$C$7:$C$600,G$10)) -> 11.369733 | H45: =IF(IF($E$5="Local prices",COUNTIFS(Offers!$B$7:$B$3000,$B45,Offers!$C$7:$C$3000,H$10,Offers!$AH$7:$AH$3000,"yes"),COUNTIFS(Offers!$B$7:$B$3000,$B45,Offers!$C$7:$C$3000,H$10,Offers!$AI$7:$AI$3000,"yes"))=0,"—",SUMIFS(Review!$O$7:$O$600,Review!$B$7:$B$600,$B45,Review!$C$7:$C$600,H$10)) -> —
B46: Ketchup pump dispenser 2 L, PP | C46: =IF(IF($E$5="Local prices",COUNTIFS(Offers!$B$7:$B$3000,$B46,Offers!$C$7:$C$3000,C$10,Offers!$AH$7:$AH$3000,"yes"),COUNTIFS(Offers!$B$7:$B$3000,$B46,Offers!$C$7:$C$3000,C$10,Offers!$AI$7:$AI$3000,"yes"))=0,"—",SUMIFS(Review!$O$7:$O$600,Review!$B$7:$B$600,$B46,Review!$C$7:$C$600,C$10)) -> — | D46: =IF(IF($E$5="Local prices",COUNTIFS(Offers!$B$7:$B$3000,$B46,Offers!$C$7:$C$3000,D$10,Offers!$AH$7:$AH$3000,"yes"),COUNTIFS(Offers!$B$7:$B$3000,$B46,Offers!$C$7:$C$3000,D$10,Offers!$AI$7:$AI$3000,"yes"))=0,"—",SUMIFS(Review!$O$7:$O$600,Review!$B$7:$B$600,$B46,Review!$C$7:$C$600,D$10)) -> — | E46: =IF(IF($E$5="Local prices",COUNTIFS(Offers!$B$7:$B$3000,$B46,Offers!$C$7:$C$3000,E$10,Offers!$AH$7:$AH$3000,"yes"),COUNTIFS(Offers!$B$7:$B$3000,$B46,Offers!$C$7:$C$3000,E$10,Offers!$AI$7:$AI$3000,"yes"))=0,"—",SUMIFS(Review!$O$7:$O$600,Review!$B$7:$B$600,$B46,Review!$C$7:$C$600,E$10)) -> 26.89 | F46: =IF(IF($E$5="Local prices",COUNTIFS(Offers!$B$7:$B$3000,$B46,Offers!$C$7:$C$3000,F$10,Offers!$AH$7:$AH$3000,"yes"),COUNTIFS(Offers!$B$7:$B$3000,$B46,Offers!$C$7:$C$3000,F$10,Offers!$AI$7:$AI$3000,"yes"))=0,"—",SUMIFS(Review!$O$7:$O$600,Review!$B$7:$B$600,$B46,Review!$C$7:$C$600,F$10)) -> 24.99 | G46: =IF(IF($E$5="Local prices",COUNTIFS(Offers!$B$7:$B$3000,$B46,Offers!$C$7:$C$3000,G$10,Offers!$AH$7:$AH$3000,"yes"),COUNTIFS(Offers!$B$7:$B$3000,$B46,Offers!$C$7:$C$3000,G$10,Offers!$AI$7:$AI$3000,"yes"))=0,"—",SUMIFS(Review!$O$7:$O$600,Review!$B$7:$B$600,$B46,Review!$C$7:$C$600,G$10)) -> 26.742355 | H46: =IF(IF($E$5="Local prices",COUNTIFS(Offers!$B$7:$B$3000,$B46,Offers!$C$7:$C$3000,H$10,Offers!$AH$7:$AH$3000,"yes"),COUNTIFS(Offers!$B$7:$B$3000,$B46,Offers!$C$7:$C$3000,H$10,Offers!$AI$7:$AI$3000,"yes"))=0,"—",SUMIFS(Review!$O$7:$O$600,Review!$B$7:$B$600,$B46,Review!$C$7:$C$600,H$10)) -> —
B47: GN 1/1 PC container, 150 mm | C47: =IF(IF($E$5="Local prices",COUNTIFS(Offers!$B$7:$B$3000,$B47,Offers!$C$7:$C$3000,C$10,Offers!$AH$7:$AH$3000,"yes"),COUNTIFS(Offers!$B$7:$B$3000,$B47,Offers!$C$7:$C$3000,C$10,Offers!$AI$7:$AI$3000,"yes"))=0,"—",SUMIFS(Review!$O$7:$O$600,Review!$B$7:$B$600,$B47,Review!$C$7:$C$600,C$10)) -> — | D47: =IF(IF($E$5="Local prices",COUNTIFS(Offers!$B$7:$B$3000,$B47,Offers!$C$7:$C$3000,D$10,Offers!$AH$7:$AH$3000,"yes"),COUNTIFS(Offers!$B$7:$B$3000,$B47,Offers!$C$7:$C$3000,D$10,Offers!$AI$7:$AI$3000,"yes"))=0,"—",SUMIFS(Review!$O$7:$O$600,Review!$B$7:$B$600,$B47,Review!$C$7:$C$600,D$10)) -> 15.897252 | E47: =IF(IF($E$5="Local prices",COUNTIFS(Offers!$B$7:$B$3000,$B47,Offers!$C$7:$C$3000,E$10,Offers!$AH$7:$AH$3000,"yes"),COUNTIFS(Offers!$B$7:$B$3000,$B47,Offers!$C$7:$C$3000,E$10,Offers!$AI$7:$AI$3000,"yes"))=0,"—",SUMIFS(Review!$O$7:$O$600,Review!$B$7:$B$600,$B47,Review!$C$7:$C$600,E$10)) -> 19.79 | F47: =IF(IF($E$5="Local prices",COUNTIFS(Offers!$B$7:$B$3000,$B47,Offers!$C$7:$C$3000,F$10,Offers!$AH$7:$AH$3000,"yes"),COUNTIFS(Offers!$B$7:$B$3000,$B47,Offers!$C$7:$C$3000,F$10,Offers!$AI$7:$AI$3000,"yes"))=0,"—",SUMIFS(Review!$O$7:$O$600,Review!$B$7:$B$600,$B47,Review!$C$7:$C$600,F$10)) -> 17.73 | G47: =IF(IF($E$5="Local prices",COUNTIFS(Offers!$B$7:$B$3000,$B47,Offers!$C$7:$C$3000,G$10,Offers!$AH$7:$AH$3000,"yes"),COUNTIFS(Offers!$B$7:$B$3000,$B47,Offers!$C$7:$C$3000,G$10,Offers!$AI$7:$AI$3000,"yes"))=0,"—",SUMIFS(Review!$O$7:$O$600,Review!$B$7:$B$600,$B47,Review!$C$7:$C$600,G$10)) -> 15.394936 | H47: =IF(IF($E$5="Local prices",COUNTIFS(Offers!$B$7:$B$3000,$B47,Offers!$C$7:$C$3000,H$10,Offers!$AH$7:$AH$3000,"yes"),COUNTIFS(Offers!$B$7:$B$3000,$B47,Offers!$C$7:$C$3000,H$10,Offers!$AI$7:$AI$3000,"yes"))=0,"—",SUMIFS(Review!$O$7:$O$600,Review!$B$7:$B$600,$B47,Review!$C$7:$C$600,H$10)) -> 16.42
B48: GN 1/1 PC container, 200 mm | C48: =IF(IF($E$5="Local prices",COUNTIFS(Offers!$B$7:$B$3000,$B48,Offers!$C$7:$C$3000,C$10,Offers!$AH$7:$AH$3000,"yes"),COUNTIFS(Offers!$B$7:$B$3000,$B48,Offers!$C$7:$C$3000,C$10,Offers!$AI$7:$AI$3000,"yes"))=0,"—",SUMIFS(Review!$O$7:$O$600,Review!$B$7:$B$600,$B48,Review!$C$7:$C$600,C$10)) -> — | D48: =IF(IF($E$5="Local prices",COUNTIFS(Offers!$B$7:$B$3000,$B48,Offers!$C$7:$C$3000,D$10,Offers!$AH$7:$AH$3000,"yes"),COUNTIFS(Offers!$B$7:$B$3000,$B48,Offers!$C$7:$C$3000,D$10,Offers!$AI$7:$AI$3000,"yes"))=0,"—",SUMIFS(Review!$O$7:$O$600,Review!$B$7:$B$600,$B48,Review!$C$7:$C$600,D$10)) -> 20.050622 | E48: =IF(IF($E$5="Local prices",COUNTIFS(Offers!$B$7:$B$3000,$B48,Offers!$C$7:$C$3000,E$10,Offers!$AH$7:$AH$3000,"yes"),COUNTIFS(Offers!$B$7:$B$3000,$B48,Offers!$C$7:$C$3000,E$10,Offers!$AI$7:$AI$3000,"yes"))=0,"—",SUMIFS(Review!$O$7:$O$600,Review!$B$7:$B$600,$B48,Review!$C$7:$C$600,E$10)) -> 25.9 | F48: =IF(IF($E$5="Local prices",COUNTIFS(Offers!$B$7:$B$3000,$B48,Offers!$C$7:$C$3000,F$10,Offers!$AH$7:$AH$3000,"yes"),COUNTIFS(Offers!$B$7:$B$3000,$B48,Offers!$C$7:$C$3000,F$10,Offers!$AI$7:$AI$3000,"yes"))=0,"—",SUMIFS(Review!$O$7:$O$600,Review!$B$7:$B$600,$B48,Review!$C$7:$C$600,F$10)) -> 22.43 | G48: =IF(IF($E$5="Local prices",COUNTIFS(Offers!$B$7:$B$3000,$B48,Offers!$C$7:$C$3000,G$10,Offers!$AH$7:$AH$3000,"yes"),COUNTIFS(Offers!$B$7:$B$3000,$B48,Offers!$C$7:$C$3000,G$10,Offers!$AI$7:$AI$3000,"yes"))=0,"—",SUMIFS(Review!$O$7:$O$600,Review!$B$7:$B$600,$B48,Review!$C$7:$C$600,G$10)) -> 18.506678 | H48: =IF(IF($E$5="Local prices",COUNTIFS(Offers!$B$7:$B$3000,$B48,Offers!$C$7:$C$3000,H$10,Offers!$AH$7:$AH$3000,"yes"),COUNTIFS(Offers!$B$7:$B$3000,$B48,Offers!$C$7:$C$3000,H$10,Offers!$AI$7:$AI$3000,"yes"))=0,"—",SUMIFS(Review!$O$7:$O$600,Review!$B$7:$B$600,$B48,Review!$C$7:$C$600,H$10)) -> 17.96
B49: GN 1/2 PC container, 65 mm | C49: =IF(IF($E$5="Local prices",COUNTIFS(Offers!$B$7:$B$3000,$B49,Offers!$C$7:$C$3000,C$10,Offers!$AH$7:$AH$3000,"yes"),COUNTIFS(Offers!$B$7:$B$3000,$B49,Offers!$C$7:$C$3000,C$10,Offers!$AI$7:$AI$3000,"yes"))=0,"—",SUMIFS(Review!$O$7:$O$600,Review!$B$7:$B$600,$B49,Review!$C$7:$C$600,C$10)) -> — | D49: =IF(IF($E$5="Local prices",COUNTIFS(Offers!$B$7:$B$3000,$B49,Offers!$C$7:$C$3000,D$10,Offers!$AH$7:$AH$3000,"yes"),COUNTIFS(Offers!$B$7:$B$3000,$B49,Offers!$C$7:$C$3000,D$10,Offers!$AI$7:$AI$3000,"yes"))=0,"—",SUMIFS(Review!$O$7:$O$600,Review!$B$7:$B$600,$B49,Review!$C$7:$C$600,D$10)) -> 6.14858 | E49: =IF(IF($E$5="Local prices",COUNTIFS(Offers!$B$7:$B$3000,$B49,Offers!$C$7:$C$3000,E$10,Offers!$AH$7:$AH$3000,"yes"),COUNTIFS(Offers!$B$7:$B$3000,$B49,Offers!$C$7:$C$3000,E$10,Offers!$AI$7:$AI$3000,"yes"))=0,"—",SUMIFS(Review!$O$7:$O$600,Review!$B$7:$B$600,$B49,Review!$C$7:$C$600,E$10)) -> 7.1 | F49: =IF(IF($E$5="Local prices",COUNTIFS(Offers!$B$7:$B$3000,$B49,Offers!$C$7:$C$3000,F$10,Offers!$AH$7:$AH$3000,"yes"),COUNTIFS(Offers!$B$7:$B$3000,$B49,Offers!$C$7:$C$3000,F$10,Offers!$AI$7:$AI$3000,"yes"))=0,"—",SUMIFS(Review!$O$7:$O$600,Review!$B$7:$B$600,$B49,Review!$C$7:$C$600,F$10)) -> 6.16 | G49: =IF(IF($E$5="Local prices",COUNTIFS(Offers!$B$7:$B$3000,$B49,Offers!$C$7:$C$3000,G$10,Offers!$AH$7:$AH$3000,"yes"),COUNTIFS(Offers!$B$7:$B$3000,$B49,Offers!$C$7:$C$3000,G$10,Offers!$AI$7:$AI$3000,"yes"))=0,"—",SUMIFS(Review!$O$7:$O$600,Review!$B$7:$B$600,$B49,Review!$C$7:$C$600,G$10)) -> 6.510093 | H49: =IF(IF($E$5="Local prices",COUNTIFS(Offers!$B$7:$B$3000,$B49,Offers!$C$7:$C$3000,H$10,Offers!$AH$7:$AH$3000,"yes"),COUNTIFS(Offers!$B$7:$B$3000,$B49,Offers!$C$7:$C$3000,H$10,Offers!$AI$7:$AI$3000,"yes"))=0,"—",SUMIFS(Review!$O$7:$O$600,Review!$B$7:$B$600,$B49,Review!$C$7:$C$600,H$10)) -> 6.15
... B91: GN 1/9 PP lid | C91: =IF(IF($E$5="Local prices",COUNTIFS(Offers!$B$7:$B$3000,$B91,Offers!$C$7:$C$3000,C$10,Offers!$AH$7:$AH$3000,"yes"),COUNTIFS(Offers!$B$7:$B$3000,$B91,Offers!$C$7:$C$3000,C$10,Offers!$AI$7:$AI$3000,"yes"))=0,"—",SUMIFS(Review!$O$7:$O$600,Review!$B$7:$B$600,$B91,Review!$C$7:$C$600,C$10)) -> — | D91: =IF(IF($E$5="Local prices",COUNTIFS(Offers!$B$7:$B$3000,$B91,Offers!$C$7:$C$3000,D$10,Offers!$AH$7:$AH$3000,"yes"),COUNTIFS(Offers!$B$7:$B$3000,$B91,Offers!$C$7:$C$3000,D$10,Offers!$AI$7:$AI$3000,"yes"))=0,"—",SUMIFS(Review!$O$7:$O$600,Review!$B$7:$B$600,$B91,Review!$C$7:$C$600,D$10)) -> 2.30027 | E91: =IF(IF($E$5="Local prices",COUNTIFS(Offers!$B$7:$B$3000,$B91,Offers!$C$7:$C$3000,E$10,Offers!$AH$7:$AH$3000,"yes"),COUNTIFS(Offers!$B$7:$B$3000,$B91,Offers!$C$7:$C$3000,E$10,Offers!$AI$7:$AI$3000,"yes"))=0,"—",SUMIFS(Review!$O$7:$O$600,Review!$B$7:$B$600,$B91,Review!$C$7:$C$600,E$10)) -> 2.125 | F91: =IF(IF($E$5="Local prices",COUNTIFS(Offers!$B$7:$B$3000,$B91,Offers!$C$7:$C$3000,F$10,Offers!$AH$7:$AH$3000,"yes"),COUNTIFS(Offers!$B$7:$B$3000,$B91,Offers!$C$7:$C$3000,F$10,Offers!$AI$7:$AI$3000,"yes"))=0,"—",SUMIFS(Review!$O$7:$O$600,Review!$B$7:$B$600,$B91,Review!$C$7:$C$600,F$10)) -> 1.79 | G91: =IF(IF($E$5="Local prices",COUNTIFS(Offers!$B$7:$B$3000,$B91,Offers!$C$7:$C$3000,G$10,Offers!$AH$7:$AH$3000,"yes"),COUNTIFS(Offers!$B$7:$B$3000,$B91,Offers!$C$7:$C$3000,G$10,Offers!$AI$7:$AI$3000,"yes"))=0,"—",SUMIFS(Review!$O$7:$O$600,Review!$B$7:$B$600,$B91,Review!$C$7:$C$600,G$10)) -> 1.6580265 | H91: =IF(IF($E$5="Local prices",COUNTIFS(Offers!$B$7:$B$3000,$B91,Offers!$C$7:$C$3000,H$10,Offers!$AH$7:$AH$3000,"yes"),COUNTIFS(Offers!$B$7:$B$3000,$B91,Offers!$C$7:$C$3000,H$10,Offers!$AI$7:$AI$3000,"yes"))=0,"—",SUMIFS(Review!$O$7:$O$600,Review!$B$7:$B$600,$B91,Review!$C$7:$C$600,H$10)) -> 1.585
B93: Research dates
B94: Market | C94: Oldest date | D94: Newest date
B95: Hungary | C95: =_xlfn.MINIFS(Offers!$AJ$7:$AJ$3000,Offers!$C$7:$C$3000,B95,Offers!$AJ$7:$AJ$3000,">0") -> 46181 | D95: =_xlfn.MAXIFS(Offers!$AJ$7:$AJ$3000,Offers!$C$7:$C$3000,B95) -> 46297
B96: Romania | C96: =_xlfn.MINIFS(Offers!$AJ$7:$AJ$3000,Offers!$C$7:$C$3000,B96,Offers!$AJ$7:$AJ$3000,">0") -> 46203 | D96: =_xlfn.MAXIFS(Offers!$AJ$7:$AJ$3000,Offers!$C$7:$C$3000,B96) -> 46297
B97: Austria | C97: =_xlfn.MINIFS(Offers!$AJ$7:$AJ$3000,Offers!$C$7:$C$3000,B97,Offers!$AJ$7:$AJ$3000,">0") -> 46295 | D97: =_xlfn.MAXIFS(Offers!$AJ$7:$AJ$3000,Offers!$C$7:$C$3000,B97) -> 46297
B98: Germany | C98: =_xlfn.MINIFS(Offers!$AJ$7:$AJ$3000,Offers!$C$7:$C$3000,B98,Offers!$AJ$7:$AJ$3000,">0") -> 46295 | D98: =_xlfn.MAXIFS(Offers!$AJ$7:$AJ$3000,Offers!$C$7:$C$3000,B98) -> 46297
B99: Czech | C99: =_xlfn.MINIFS(Offers!$AJ$7:$AJ$3000,Offers!$C$7:$C$3000,B99,Offers!$AJ$7:$AJ$3000,">0") -> 46295 | D99: =_xlfn.MAXIFS(Offers!$AJ$7:$AJ$3000,Offers!$C$7:$C$3000,B99) -> 46297
B100: Slovakia | C100: =_xlfn.MINIFS(Offers!$AJ$7:$AJ$3000,Offers!$C$7:$C$3000,B100,Offers!$AJ$7:$AJ$3000,">0") -> 46295 | D100: =_xlfn.MAXIFS(Offers!$AJ$7:$AJ$3000,Offers!$C$7:$C$3000,B100) -> 46297
B102: Research dates come from the supplied files, except rows re-checked live on 30 Sep 2026 (see Change log). The remaining future date in the Romania source is unchanged and highlighted.

Sheet Pricing
B2: Market-entry net prices per piece
B3: Goal: a price that makes a buyer who does not know YES Gastro choose it over the shop they already use. Rule: undercut the cheapest qualifying competitor by C6 — unless that cheapest offer is an outlier (more than C7 below the market median: typically a clearance price, a 6/12-pack or an out-of-stock listing), in which case the price is set C5 below the median and the outlier is left alone. The price never exceeds the median minus C5, is deepened by C8 where fewer than 3 offers exist, is rounded DOWN to the step in row 9, and never falls below cost x (1 + C10). Cost = column "EUR" of the Gastroplast price list (2026, EXW Budapest; list price plus the price list's own uplift, mostly +10%, cutting boards +30%). Markup over cost = entry price / cost - 1. Cheapest / median / max come from the Review sheet (EXACT + CLOSE offers under the Compare filter, net per piece, Erste mid-rates).
B5: Entry discount below median | C5: 0.25 | F5: Amber cells are inputs; every entry price follows them. Column D (cost) is taken from the Gastroplast price list and can be overwritten.
B6: Undercut below the cheapest competitor | C6: 0.05
B7: Outlier guard: ignore the cheapest if it is more than this below the median | C7: 0.35
B8: Extra discount when fewer than 3 offers | C8: 0.05
B9: Rounding step (EUR): below 10 / 10-100 / above 100 | C9: 0.05 | D9: 0.1 | E9: 1
B10: Minimum markup over cost (price never below cost x (1 + this)) | C10: 0
B11: Product prices exclude delivery: delivery is charged as a separate fee on the invoice (see the Competitor delivery and Delivery cost sheets).
B13: Product | C13: YES Gastro code | D13: My cost EUR (price list) | E13: Austria | O13: Germany | Y13: Czech | AJ13: Slovakia | AT13: Romania | BE13: Hungary
E14: Offers | F14: Cheapest EUR | G14: Median EUR | H14: Max EUR | I14: Basis | J14: Entry price EUR | K14: My cost EUR | L14: Markup over cost | M14: vs cheapest | N14: vs median | O14: Offers | P14: Cheapest EUR | Q14: Median EUR | R14: Max EUR | S14: Basis | T14: Entry price EUR | U14: My cost EUR | V14: Markup over cost | W14: vs cheapest | X14: vs median | Y14: Offers | Z14: Cheapest EUR | AA14: Median EUR | AB14: Max EUR | AC14: Basis | AD14: Entry price EUR | AE14: Entry price CZK | AF14: My cost EUR | AG14: Markup over cost | AH14: vs cheapest | AI14: vs median | AJ14: Offers | AK14: Cheapest EUR | AL14: Median EUR | AM14: Max EUR | AN14: Basis | AO14: Entry price EUR | AP14: My cost EUR | AQ14: Markup over cost | AR14: vs cheapest | AS14: vs median | AT14: Offers | AU14: Cheapest EUR | AV14: Median EUR | AW14: Max EUR | AX14: Basis | AY14: Entry price EUR | AZ14: Entry price RON | BA14: My cost EUR | BB14: Markup over cost | BC14: vs cheapest | BD14: vs median | BE14: Offers | BF14: Cheapest EUR | BG14: Median EUR | BH14: Max EUR | BI14: Basis | BJ14: Entry price EUR | BK14: Entry price HUF | BL14: My cost EUR | BM14: Markup over cost | BN14: vs cheapest | BO14: vs median
B15: GN 1/1 PC container, 65 mm | C15: GNP-1165 | D15: 6.776 | E15: =COUNTIFS(Offers!$B$7:$B$3000,$B15,Offers!$C$7:$C$3000,"Austria",Offers!$AI$7:$AI$3000,"yes") -> 9 | F15: =IF(E15=0,"—",SUMIFS(Review!$I$7:$I$600,Review!$B$7:$B$600,$B15,Review!$C$7:$C$600,"Austria")) -> 7.83 | G15: =IF(E15=0,"—",SUMIFS(Review!$J$7:$J$600,Review!$B$7:$B$600,$B15,Review!$C$7:$C$600,"Austria")) -> 14.07 | H15: =IF(E15=0,"—",SUMIFS(Review!$K$7:$K$600,Review!$B$7:$B$600,$B15,Review!$C$7:$C$600,"Austria")) -> 23 | I15: =IF(E15=0,"—",IF(F15<G15*(1-$C$7),"median (cheapest is an outlier)",IF(F15*(1-$C$6)<G15*(1-$C$5),"undercut cheapest","median"))) -> median (cheapest is an outlier) | J15: =IF(E15=0,"—",IF(AND(ISNUMBER($D15),$D15*(1+$C$10)>FLOOR(IF(F15<G15*(1-$C$7),G15*(1-$C$5-IF(E15<3,$C$8,0)),MIN(G15*(1-$C$5-IF(E15<3,$C$8,0)),F15*(1-$C$6-IF(E15<3,$C$8,0)))),IF(IF(F15<G15*(1-$C$7),G15*(1-$C$5-IF(E15<3,$C$8,0)),MIN(G15*(1-$C$5-IF(E15<3,$C$8,0)),F15*(1-$C$6-IF(E15<3,$C$8,0))))<10,$C$9,IF(IF(F15<G15*(1-$C$7),G15*(1-$C$5-IF(E15<3,$C$8,0)),MIN(G15*(1-$C$5-IF(E15<3,$C$8,0)),F15*(1-$C$6-IF(E15<3,$C$8,0))))<100,$D$9,$E$9)))),ROUND($D15*(1+$C$10),2),FLOOR(IF(F15<G15*(1-$C$7),G15*(1-$C$5-IF(E15<3,$C$8,0)),MIN(G15*(1-$C$5-IF(E15<3,$C$8,0)),F15*(1-$C$6-IF(E15<3,$C$8,0)))),IF(IF(F15<G15*(1-$C$7),G15*(1-$C$5-IF(E15<3,$C$8,0)),MIN(G15*(1-$C$5-IF(E15<3,$C$8,0)),F15*(1-$C$6-IF(E15<3,$C$8,0))))<10,$C$9,IF(IF(F15<G15*(1-$C$7),G15*(1-$C$5-IF(E15<3,$C$8,0)),MIN(G15*(1-$C$5-IF(E15<3,$C$8,0)),F15*(1-$C$6-IF(E15<3,$C$8,0))))<100,$D$9,$E$9))))) -> 10.5 | K15: =IF(ISNUMBER($D15),$D15,"n/a") -> 6.776 | L15: =IF(OR(E15=0,NOT(ISNUMBER($D15))),"—",J15/$D15-1) -> 0.54958678 | M15: =IF(E15=0,"—",J15/F15-1) -> 0.34099617 | N15: =IF(E15=0,"—",J15/G15-1) -> -0.25373134 | O15: =COUNTIFS(Offers!$B$7:$B$3000,$B15,Offers!$C$7:$C$3000,"Germany",Offers!$AI$7:$AI$3000,"yes") -> 8 | P15: =IF(O15=0,"—",SUMIFS(Review!$I$7:$I$600,Review!$B$7:$B$600,$B15,Review!$C$7:$C$600,"Germany")) -> 7.26 | Q15: =IF(O15=0,"—",SUMIFS(Review!$J$7:$J$600,Review!$B$7:$B$600,$B15,Review!$C$7:$C$600,"Germany")) -> 13.11 | R15: =IF(O15=0,"—",SUMIFS(Review!$K$7:$K$600,Review!$B$7:$B$600,$B15,Review!$C$7:$C$600,"Germany")) -> 22.43 | S15: =IF(O15=0,"—",IF(P15<Q15*(1-$C$7),"median (cheapest is an outlier)",IF(P15*(1-$C$6)<Q15*(1-$C$5),"undercut cheapest","median"))) -> median (cheapest is an outlier) | T15: =IF(O15=0,"—",IF(AND(ISNUMBER($D15),$D15*(1+$C$10)>FLOOR(IF(P15<Q15*(1-$C$7),Q15*(1-$C$5-IF(O15<3,$C$8,0)),MIN(Q15*(1-$C$5-IF(O15<3,$C$8,0)),P15*(1-$C$6-IF(O15<3,$C$8,0)))),IF(IF(P15<Q15*(1-$C$7),Q15*(1-$C$5-IF(O15<3,$C$8,0)),MIN(Q15*(1-$C$5-IF(O15<3,$C$8,0)),P15*(1-$C$6-IF(O15<3,$C$8,0))))<10,$C$9,IF(IF(P15<Q15*(1-$C$7),Q15*(1-$C$5-IF(O15<3,$C$8,0)),MIN(Q15*(1-$C$5-IF(O15<3,$C$8,0)),P15*(1-$C$6-IF(O15<3,$C$8,0))))<100,$D$9,$E$9)))),ROUND($D15*(1+$C$10),2),FLOOR(IF(P15<Q15*(1-$C$7),Q15*(1-$C$5-IF(O15<3,$C$8,0)),MIN(Q15*(1-$C$5-IF(O15<3,$C$8,0)),P15*(1-$C$6-IF(O15<3,$C$8,0)))),IF(IF(P15<Q15*(1-$C$7),Q15*(1-$C$5-IF(O15<3,$C$8,0)),MIN(Q15*(1-$C$5-IF(O15<3,$C$8,0)),P15*(1-$C$6-IF(O15<3,$C$8,0))))<10,$C$9,IF(IF(P15<Q15*(1-$C$7),Q15*(1-$C$5-IF(O15<3,$C$8,0)),MIN(Q15*(1-$C$5-IF(O15<3,$C$8,0)),P15*(1-$C$6-IF(O15<3,$C$8,0))))<100,$D$9,$E$9))))) -> 9.8 | U15: =IF(ISNUMBER($D15),$D15,"n/a") -> 6.776 | V15: =IF(OR(O15=0,NOT(ISNUMBER($D15))),"—",T15/$D15-1) -> 0.44628099 | W15: =IF(O15=0,"—",T15/P15-1) -> 0.34986226 | X15: =IF(O15=0,"—",T15/Q15-1) -> -0.25247902 | Y15: =COUNTIFS(Offers!$B$7:$B$3000,$B15,Offers!$C$7:$C$3000,"Czech",Offers!$AI$7:$AI$3000,"yes") -> 6 | Z15: =IF(Y15=0,"—",SUMIFS(Review!$I$7:$I$600,Review!$B$7:$B$600,$B15,Review!$C$7:$C$600,"Czech")) -> 7.804741 | AA15: =IF(Y15=0,"—",SUMIFS(Review!$J$7:$J$600,Review!$B$7:$B$600,$B15,Review!$C$7:$C$600,"Czech")) -> 12.148079 | AB15: =IF(Y15=0,"—",SUMIFS(Review!$K$7:$K$600,Review!$B$7:$B$600,$B15,Review!$C$7:$C$600,"Czech")) -> 16.986838 | AC15: =IF(Y15=0,"—",IF(Z15<AA15*(1-$C$7),"median (cheapest is an outlier)",IF(Z15*(1-$C$6)<AA15*(1-$C$5),"undercut cheapest","median"))) -> median (cheapest is an outlier) | AD15: =IF(Y15=0,"—",IF(AND(ISNUMBER($D15),$D15*(1+$C$10)>FLOOR(IF(Z15<AA15*(1-$C$7),AA15*(1-$C$5-IF(Y15<3,$C$8,0)),MIN(AA15*(1-$C$5-IF(Y15<3,$C$8,0)),Z15*(1-$C$6-IF(Y15<3,$C$8,0)))),IF(IF(Z15<AA15*(1-$C$7),AA15*(1-$C$5-IF(Y15<3,$C$8,0)),MIN(AA15*(1-$C$5-IF(Y15<3,$C$8,0)),Z15*(1-$C$6-IF(Y15<3,$C$8,0))))<10,$C$9,IF(IF(Z15<AA15*(1-$C$7),AA15*(1-$C$5-IF(Y15<3,$C$8,0)),MIN(AA15*(1-$C$5-IF(Y15<3,$C$8,0)),Z15*(1-$C$6-IF(Y15<3,$C$8,0))))<100,$D$9,$E$9)))),ROUND($D15*(1+$C$10),2),FLOOR(IF(Z15<AA15*(1-$C$7),AA15*(1-$C$5-IF(Y15<3,$C$8,0)),MIN(AA15*(1-$C$5-IF(Y15<3,$C$8,0)),Z15*(1-$C$6-IF(Y15<3,$C$8,0)))),IF(IF(Z15<AA15*(1-$C$7),AA15*(1-$C$5-IF(Y15<3,$C$8,0)),MIN(AA15*(1-$C$5-IF(Y15<3,$C$8,0)),Z15*(1-$C$6-IF(Y15<3,$C$8,0))))<10,$C$9,IF(IF(Z15<AA15*(1-$C$7),AA15*(1-$C$5-IF(Y15<3,$C$8,0)),MIN(AA15*(1-$C$5-IF(Y15<3,$C$8,0)),Z15*(1-$C$6-IF(Y15<3,$C$8,0))))<100,$D$9,$E$9))))) -> 9.1 | AE15: =IF(Y15=0,"—",FLOOR(AD15*Sources!$G$10,1)) -> 222 | AF15: =IF(ISNUMBER($D15),$D15,"n/a") -> 6.776 | AG15: =IF(OR(Y15=0,NOT(ISNUMBER($D15))),"—",AD15/$D15-1) -> 0.34297521 | AH15: =IF(Y15=0,"—",AD15/Z15-1) -> 0.16595797 | AI15: =IF(Y15=0,"—",AD15/AA15-1) -> -0.25091034 | AJ15: =COUNTIFS(Offers!$B$7:$B$3000,$B15,Offers!$C$7:$C$3000,"Slovakia",Offers!$AI$7:$AI$3000,"yes") -> 2 | AK15: =IF(AJ15=0,"—",SUMIFS(Review!$I$7:$I$600,Review!$B$7:$B$600,$B15,Review!$C$7:$C$600,"Slovakia")) -> 16.455285 | AL15: =IF(AJ15=0,"—",SUMIFS(Review!$J$7:$J$600,Review!$B$7:$B$600,$B15,Review!$C$7:$C$600,"Slovakia")) -> 18.467643 | AM15: =IF(AJ15=0,"—",SUMIFS(Review!$K$7:$K$600,Review!$B$7:$B$600,$B15,Review!$C$7:$C$600,"Slovakia")) -> 20.48 | AN15: =IF(AJ15=0,"—",IF(AK15<AL15*(1-$C$7),"median (cheapest is an outlier)",IF(AK15*(1-$C$6)<AL15*(1-$C$5),"undercut cheapest","median"))) -> median | AO15: =IF(AJ15=0,"—",IF(AND(ISNUMBER($D15),$D15*(1+$C$10)>FLOOR(IF(AK15<AL15*(1-$C$7),AL15*(1-$C$5-IF(AJ15<3,$C$8,0)),MIN(AL15*(1-$C$5-IF(AJ15<3,$C$8,0)),AK15*(1-$C$6-IF(AJ15<3,$C$8,0)))),IF(IF(AK15<AL15*(1-$C$7),AL15*(1-$C$5-IF(AJ15<3,$C$8,0)),MIN(AL15*(1-$C$5-IF(AJ15<3,$C$8,0)),AK15*(1-$C$6-IF(AJ15<3,$C$8,0))))<10,$C$9,IF(IF(AK15<AL15*(1-$C$7),AL15*(1-$C$5-IF(AJ15<3,$C$8,0)),MIN(AL15*(1-$C$5-IF(AJ15<3,$C$8,0)),AK15*(1-$C$6-IF(AJ15<3,$C$8,0))))<100,$D$9,$E$9)))),ROUND($D15*(1+$C$10),2),FLOOR(IF(AK15<AL15*(1-$C$7),AL15*(1-$C$5-IF(AJ15<3,$C$8,0)),MIN(AL15*(1-$C$5-IF(AJ15<3,$C$8,0)),AK15*(1-$C$6-IF(AJ15<3,$C$8,0)))),IF(IF(AK15<AL15*(1-$C$7),AL15*(1-$C$5-IF(AJ15<3,$C$8,0)),MIN(AL15*(1-$C$5-IF(AJ15<3,$C$8,0)),AK15*(1-$C$6-IF(AJ15<3,$C$8,0))))<10,$C$9,IF(IF(AK15<AL15*(1-$C$7),AL15*(1-$C$5-IF(AJ15<3,$C$8,0)),MIN(AL15*(1-$C$5-IF(AJ15<3,$C$8,0)),AK15*(1-$C$6-IF(AJ15<3,$C$8,0))))<100,$D$9,$E$9))))) -> 12.9 | AP15: =IF(ISNUMBER($D15),$D15,"n/a") -> 6.776 | AQ15: =IF(OR(AJ15=0,NOT(ISNUMBER($D15))),"—",AO15/$D15-1) -> 0.90377804 | AR15: =IF(AJ15=0,"—",AO15/AK15-1) -> -0.21605733 | AS15: =IF(AJ15=0,"—",AO15/AL15-1) -> -0.30148096 | AT15: =COUNTIFS(Offers!$B$7:$B$3000,$B15,Offers!$C$7:$C$3000,"Romania",Offers!$AI$7:$AI$3000,"yes") -> 11 | AU15: =IF(AT15=0,"—",SUMIFS(Review!$I$7:$I$600,Review!$B$7:$B$600,$B15,Review!$C$7:$C$600,"Romania")) -> 8 | AV15: =IF(AT15=0,"—",SUMIFS(Review!$J$7:$J$600,Review!$B$7:$B$600,$B15,Review!$C$7:$C$600,"Romania")) -> 10.029101 | AW15: =IF(AT15=0,"—",SUMIFS(Review!$K$7:$K$600,Review!$B$7:$B$600,$B15,Review!$C$7:$C$600,"Romania")) -> 17.413081 | AX15: =IF(AT15=0,"—",IF(AU15<AV15*(1-$C$7),"median (cheapest is an outlier)",IF(AU15*(1-$C$6)<AV15*(1-$C$5),"undercut cheapest","median"))) -> median | AY15: =IF(AT15=0,"—",IF(AND(ISNUMBER($D15),$D15*(1+$C$10)>FLOOR(IF(AU15<AV15*(1-$C$7),AV15*(1-$C$5-IF(AT15<3,$C$8,0)),MIN(AV15*(1-$C$5-IF(AT15<3,$C$8,0)),AU15*(1-$C$6-IF(AT15<3,$C$8,0)))),IF(IF(AU15<AV15*(1-$C$7),AV15*(1-$C$5-IF(AT15<3,$C$8,0)),MIN(AV15*(1-$C$5-IF(AT15<3,$C$8,0)),AU15*(1-$C$6-IF(AT15<3,$C$8,0))))<10,$C$9,IF(IF(AU15<AV15*(1-$C$7),AV15*(1-$C$5-IF(AT15<3,$C$8,0)),MIN(AV15*(1-$C$5-IF(AT15<3,$C$8,0)),AU15*(1-$C$6-IF(AT15<3,$C$8,0))))<100,$D$9,$E$9)))),ROUND($D15*(1+$C$10),2),FLOOR(IF(AU15<AV15*(1-$C$7),AV15*(1-$C$5-IF(AT15<3,$C$8,0)),MIN(AV15*(1-$C$5-IF(AT15<3,$C$8,0)),AU15*(1-$C$6-IF(AT15<3,$C$8,0)))),IF(IF(AU15<AV15*(1-$C$7),AV15*(1-$C$5-IF(AT15<3,$C$8,0)),MIN(AV15*(1-$C$5-IF(AT15<3,$C$8,0)),AU15*(1-$C$6-IF(AT15<3,$C$8,0))))<10,$C$9,IF(IF(AU15<AV15*(1-$C$7),AV15*(1-$C$5-IF(AT15<3,$C$8,0)),MIN(AV15*(1-$C$5-IF(AT15<3,$C$8,0)),AU15*(1-$C$6-IF(AT15<3,$C$8,0))))<100,$D$9,$E$9))))) -> 7.5 | AZ15: =IF(AT15=0,"—",FLOOR(AY15*Sources!$G$9,0.1)) -> 39.5 | BA15: =IF(ISNUMBER($D15),$D15,"n/a") -> 6.776 | BB15: =IF(OR(AT15=0,NOT(ISNUMBER($D15))),"—",AY15/$D15-1) -> 0.1068477 | BC15: =IF(AT15=0,"—",AY15/AU15-1) -> -0.0625 | BD15: =IF(AT15=0,"—",AY15/AV15-1) -> -0.25217624 | BE15: =COUNTIFS(Offers!$B$7:$B$3000,$B15,Offers!$C$7:$C$3000,"Hungary",Offers!$AI$7:$AI$3000,"yes") -> 6 | BF15: =IF(BE15=0,"—",SUMIFS(Review!$I$7:$I$600,Review!$B$7:$B$600,$B15,Review!$C$7:$C$600,"Hungary")) -> 6.883177 | BG15: =IF(BE15=0,"—",SUMIFS(Review!$J$7:$J$600,Review!$B$7:$B$600,$B15,Review!$C$7:$C$600,"Hungary")) -> 10.912021 | BH15: =IF(BE15=0,"—",SUMIFS(Review!$K$7:$K$600,Review!$B$7:$B$600,$B15,Review!$C$7:$C$600,"Hungary")) -> 19.764552 | BI15: =IF(BE15=0,"—",IF(BF15<BG15*(1-$C$7),"median (cheapest is an outlier)",IF(BF15*(1-$C$6)<BG15*(1-$C$5),"undercut cheapest","median"))) -> median (cheapest is an outlier) | BJ15: =IF(BE15=0,"—",IF(AND(ISNUMBER($D15),$D15*(1+$C$10)>FLOOR(IF(BF15<BG15*(1-$C$7),BG15*(1-$C$5-IF(BE15<3,$C$8,0)),MIN(BG15*(1-$C$5-IF(BE15<3,$C$8,0)),BF15*(1-$C$6-IF(BE15<3,$C$8,0)))),IF(IF(BF15<BG15*(1-$C$7),BG15*(1-$C$5-IF(BE15<3,$C$8,0)),MIN(BG15*(1-$C$5-IF(BE15<3,$C$8,0)),BF15*(1-$C$6-IF(BE15<3,$C$8,0))))<10,$C$9,IF(IF(BF15<BG15*(1-$C$7),BG15*(1-$C$5-IF(BE15<3,$C$8,0)),MIN(BG15*(1-$C$5-IF(BE15<3,$C$8,0)),BF15*(1-$C$6-IF(BE15<3,$C$8,0))))<100,$D$9,$E$9)))),ROUND($D15*(1+$C$10),2),FLOOR(IF(BF15<BG15*(1-$C$7),BG15*(1-$C$5-IF(BE15<3,$C$8,0)),MIN(BG15*(1-$C$5-IF(BE15<3,$C$8,0)),BF15*(1-$C$6-IF(BE15<3,$C$8,0)))),IF(IF(BF15<BG15*(1-$C$7),BG15*(1-$C$5-IF(BE15<3,$C$8,0)),MIN(BG15*(1-$C$5-IF(BE15<3,$C$8,0)),BF15*(1-$C$6-IF(BE15<3,$C$8,0))))<10,$C$9,IF(IF(BF15<BG15*(1-$C$7),BG15*(1-$C$5-IF(BE15<3,$C$8,0)),MIN(BG15*(1-$C$5-IF(BE15<3,$C$8,0)),BF15*(1-$C$6-IF(BE15<3,$C$8,0))))<100,$D$9,$E$9))))) -> 8.15 | BK15: =IF(BE15=0,"—",FLOOR(BJ15*Sources!$G$8,10)) -> 2980 | BL15: =IF(ISNUMBER($D15),$D15,"n/a") -> 6.776 | BM15: =IF(OR(BE15=0,NOT(ISNUMBER($D15))),"—",BJ15/$D15-1) -> 0.2027745 | BN15: =IF(BE15=0,"—",BJ15/BF15-1) -> 0.18404626 | BO15: =IF(BE15=0,"—",BJ15/BG15-1) -> -0.25311727
B16: GN 1/2 PC container, 150 mm | C16: GNP-12150 | D16: 5.324 | E16: =COUNTIFS(Offers!$B$7:$B$3000,$B16,Offers!$C$7:$C$3000,"Austria",Offers!$AI$7:$AI$3000,"yes") -> 9 | F16: =IF(E16=0,"—",SUMIFS(Review!$I$7:$I$600,Review!$B$7:$B$600,$B16,Review!$C$7:$C$600,"Austria")) -> 7.29 | G16: =IF(E16=0,"—",SUMIFS(Review!$J$7:$J$600,Review!$B$7:$B$600,$B16,Review!$C$7:$C$600,"Austria")) -> 10.9 | H16: =IF(E16=0,"—",SUMIFS(Review!$K$7:$K$600,Review!$B$7:$B$600,$B16,Review!$C$7:$C$600,"Austria")) -> 21 | I16: =IF(E16=0,"—",IF(F16<G16*(1-$C$7),"median (cheapest is an outlier)",IF(F16*(1-$C$6)<G16*(1-$C$5),"undercut cheapest","median"))) -> undercut cheapest | J16: =IF(E16=0,"—",IF(AND(ISNUMBER($D16),$D16*(1+$C$10)>FLOOR(IF(F16<G16*(1-$C$7),G16*(1-$C$5-IF(E16<3,$C$8,0)),MIN(G16*(1-$C$5-IF(E16<3,$C$8,0)),F16*(1-$C$6-IF(E16<3,$C$8,0)))),IF(IF(F16<G16*(1-$C$7),G16*(1-$C$5-IF(E16<3,$C$8,0)),MIN(G16*(1-$C$5-IF(E16<3,$C$8,0)),F16*(1-$C$6-IF(E16<3,$C$8,0))))<10,$C$9,IF(IF(F16<G16*(1-$C$7),G16*(1-$C$5-IF(E16<3,$C$8,0)),MIN(G16*(1-$C$5-IF(E16<3,$C$8,0)),F16*(1-$C$6-IF(E16<3,$C$8,0))))<100,$D$9,$E$9)))),ROUND($D16*(1+$C$10),2),FLOOR(IF(F16<G16*(1-$C$7),G16*(1-$C$5-IF(E16<3,$C$8,0)),MIN(G16*(1-$C$5-IF(E16<3,$C$8,0)),F16*(1-$C$6-IF(E16<3,$C$8,0)))),IF(IF(F16<G16*(1-$C$7),G16*(1-$C$5-IF(E16<3,$C$8,0)),MIN(G16*(1-$C$5-IF(E16<3,$C$8,0)),F16*(1-$C$6-IF(E16<3,$C$8,0))))<10,$C$9,IF(IF(F16<G16*(1-$C$7),G16*(1-$C$5-IF(E16<3,$C$8,0)),MIN(G16*(1-$C$5-IF(E16<3,$C$8,0)),F16*(1-$C$6-IF(E16<3,$C$8,0))))<100,$D$9,$E$9))))) -> 6.9 | K16: =IF(ISNUMBER($D16),$D16,"n/a") -> 5.324 | L16: =IF(OR(E16=0,NOT(ISNUMBER($D16))),"—",J16/$D16-1) -> 0.29601803 | M16: =IF(E16=0,"—",J16/F16-1) -> -0.053497942 | N16: =IF(E16=0,"—",J16/G16-1) -> -0.36697248 | O16: =COUNTIFS(Offers!$B$7:$B$3000,$B16,Offers!$C$7:$C$3000,"Germany",Offers!$AI$7:$AI$3000,"yes") -> 8 | P16: =IF(O16=0,"—",SUMIFS(Review!$I$7:$I$600,Review!$B$7:$B$600,$B16,Review!$C$7:$C$600,"Germany")) -> 5.82 | Q16: =IF(O16=0,"—",SUMIFS(Review!$J$7:$J$600,Review!$B$7:$B$600,$B16,Review!$C$7:$C$600,"Germany")) -> 9.35 | R16: =IF(O16=0,"—",SUMIFS(Review!$K$7:$K$600,Review!$B$7:$B$600,$B16,Review!$C$7:$C$600,"Germany")) -> 18.75 | S16: =IF(O16=0,"—",IF(P16<Q16*(1-$C$7),"median (cheapest is an outlier)",IF(P16*(1-$C$6)<Q16*(1-$C$5),"undercut cheapest","median"))) -> median (cheapest is an outlier) | T16: =IF(O16=0,"—",IF(AND(ISNUMBER($D16),$D16*(1+$C$10)>FLOOR(IF(P16<Q16*(1-$C$7),Q16*(1-$C$5-IF(O16<3,$C$8,0)),MIN(Q16*(1-$C$5-IF(O16<3,$C$8,0)),P16*(1-$C$6-IF(O16<3,$C$8,0)))),IF(IF(P16<Q16*(1-$C$7),Q16*(1-$C$5-IF(O16<3,$C$8,0)),MIN(Q16*(1-$C$5-IF(O16<3,$C$8,0)),P16*(1-$C$6-IF(O16<3,$C$8,0))))<10,$C$9,IF(IF(P16<Q16*(1-$C$7),Q16*(1-$C$5-IF(O16<3,$C$8,0)),MIN(Q16*(1-$C$5-IF(O16<3,$C$8,0)),P16*(1-$C$6-IF(O16<3,$C$8,0))))<100,$D$9,$E$9)))),ROUND($D16*(1+$C$10),2),FLOOR(IF(P16<Q16*(1-$C$7),Q16*(1-$C$5-IF(O16<3,$C$8,0)),MIN(Q16*(1-$C$5-IF(O16<3,$C$8,0)),P16*(1-$C$6-IF(O16<3,$C$8,0)))),IF(IF(P16<Q16*(1-$C$7),Q16*(1-$C$5-IF(O16<3,$C$8,0)),MIN(Q16*(1-$C$5-IF(O16<3,$C$8,0)),P16*(1-$C$6-IF(O16<3,$C$8,0))))<10,$C$9,IF(IF(P16<Q16*(1-$C$7),Q16*(1-$C$5-IF(O16<3,$C$8,0)),MIN(Q16*(1-$C$5-IF(O16<3,$C$8,0)),P16*(1-$C$6-IF(O16<3,$C$8,0))))<100,$D$9,$E$9))))) -> 7 | U16: =IF(ISNUMBER($D16),$D16,"n/a") -> 5.324 | V16: =IF(OR(O16=0,NOT(ISNUMBER($D16))),"—",T16/$D16-1) -> 0.3148009 | W16: =IF(O16=0,"—",T16/P16-1) -> 0.20274914 | X16: =IF(O16=0,"—",T16/Q16-1) -> -0.2513369 | Y16: =COUNTIFS(Offers!$B$7:$B$3000,$B16,Offers!$C$7:$C$3000,"Czech",Offers!$AI$7:$AI$3000,"yes") -> 6 | Z16: =IF(Y16=0,"—",SUMIFS(Review!$I$7:$I$600,Review!$B$7:$B$600,$B16,Review!$C$7:$C$600,"Czech")) -> 8.557292 | AA16: =IF(Y16=0,"—",SUMIFS(Review!$J$7:$J$600,Review!$B$7:$B$600,$B16,Review!$C$7:$C$600,"Czech")) -> 10.509296 | AB16: =IF(Y16=0,"—",SUMIFS(Review!$K$7:$K$600,Review!$B$7:$B$600,$B16,Review!$C$7:$C$600,"Czech")) -> 15.700787 | AC16: =IF(Y16=0,"—",IF(Z16<AA16*(1-$C$7),"median (cheapest is an outlier)",IF(Z16*(1-$C$6)<AA16*(1-$C$5),"undercut cheapest","median"))) -> median | AD16: =IF(Y16=0,"—",IF(AND(ISNUMBER($D16),$D16*(1+$C$10)>FLOOR(IF(Z16<AA16*(1-$C$7),AA16*(1-$C$5-IF(Y16<3,$C$8,0)),MIN(AA16*(1-$C$5-IF(Y16<3,$C$8,0)),Z16*(1-$C$6-IF(Y16<3,$C$8,0)))),IF(IF(Z16<AA16*(1-$C$7),AA16*(1-$C$5-IF(Y16<3,$C$8,0)),MIN(AA16*(1-$C$5-IF(Y16<3,$C$8,0)),Z16*(1-$C$6-IF(Y16<3,$C$8,0))))<10,$C$9,IF(IF(Z16<AA16*(1-$C$7),AA16*(1-$C$5-IF(Y16<3,$C$8,0)),MIN(AA16*(1-$C$5-IF(Y16<3,$C$8,0)),Z16*(1-$C$6-IF(Y16<3,$C$8,0))))<100,$D$9,$E$9)))),ROUND($D16*(1+$C$10),2),FLOOR(IF(Z16<AA16*(1-$C$7),AA16*(1-$C$5-IF(Y16<3,$C$8,0)),MIN(AA16*(1-$C$5-IF(Y16<3,$C$8,0)),Z16*(1-$C$6-IF(Y16<3,$C$8,0)))),IF(IF(Z16<AA16*(1-$C$7),AA16*(1-$C$5-IF(Y16<3,$C$8,0)),MIN(AA16*(1-$C$5-IF(Y16<3,$C$8,0)),Z16*(1-$C$6-IF(Y16<3,$C$8,0))))<10,$C$9,IF(IF(Z16<AA16*(1-$C$7),AA16*(1-$C$5-IF(Y16<3,$C$8,0)),MIN(AA16*(1-$C$5-IF(Y16<3,$C$8,0)),Z16*(1-$C$6-IF(Y16<3,$C$8,0))))<100,$D$9,$E$9))))) -> 7.85 | AE16: =IF(Y16=0,"—",FLOOR(AD16*Sources!$G$10,1)) -> 191 | AF16: =IF(ISNUMBER($D16),$D16,"n/a") -> 5.324 | AG16: =IF(OR(Y16=0,NOT(ISNUMBER($D16))),"—",AD16/$D16-1) -> 0.4744553 | AH16: =IF(Y16=0,"—",AD16/Z16-1) -> -0.082653718 | AI16: =IF(Y16=0,"—",AD16/AA16-1) -> -0.25304222 | AJ16: =COUNTIFS(Offers!$B$7:$B$3000,$B16,Offers!$C$7:$C$3000,"Slovakia",Offers!$AI$7:$AI$3000,"yes") -> 2 | AK16: =IF(AJ16=0,"—",SUMIFS(Review!$I$7:$I$600,Review!$B$7:$B$600,$B16,Review!$C$7:$C$600,"Slovakia")) -> 15.227642 | AL16: =IF(AJ16=0,"—",SUMIFS(Review!$J$7:$J$600,Review!$B$7:$B$600,$B16,Review!$C$7:$C$600,"Slovakia")) -> 15.688821 | AM16: =IF(AJ16=0,"—",SUMIFS(Review!$K$7:$K$600,Review!$B$7:$B$600,$B16,Review!$C$7:$C$600,"Slovakia")) -> 16.15 | AN16: =IF(AJ16=0,"—",IF(AK16<AL16*(1-$C$7),"median (cheapest is an outlier)",IF(AK16*(1-$C$6)<AL16*(1-$C$5),"undercut cheapest","median"))) -> median | AO16: =IF(AJ16=0,"—",IF(AND(ISNUMBER($D16),$D16*(1+$C$10)>FLOOR(IF(AK16<AL16*(1-$C$7),AL16*(1-$C$5-IF(AJ16<3,$C$8,0)),MIN(AL16*(1-$C$5-IF(AJ16<3,$C$8,0)),AK16*(1-$C$6-IF(AJ16<3,$C$8,0)))),IF(IF(AK16<AL16*(1-$C$7),AL16*(1-$C$5-IF(AJ16<3,$C$8,0)),MIN(AL16*(1-$C$5-IF(AJ16<3,$C$8,0)),AK16*(1-$C$6-IF(AJ16<3,$C$8,0))))<10,$C$9,IF(IF(AK16<AL16*(1-$C$7),AL16*(1-$C$5-IF(AJ16<3,$C$8,0)),MIN(AL16*(1-$C$5-IF(AJ16<3,$C$8,0)),AK16*(1-$C$6-IF(AJ16<3,$C$8,0))))<100,$D$9,$E$9)))),ROUND($D16*(1+$C$10),2),FLOOR(IF(AK16<AL16*(1-$C$7),AL16*(1-$C$5-IF(AJ16<3,$C$8,0)),MIN(AL16*(1-$C$5-IF(AJ16<3,$C$8,0)),AK16*(1-$C$6-IF(AJ16<3,$C$8,0)))),IF(IF(AK16<AL16*(1-$C$7),AL16*(1-$C$5-IF(AJ16<3,$C$8,0)),MIN(AL16*(1-$C$5-IF(AJ16<3,$C$8,0)),AK16*(1-$C$6-IF(AJ16<3,$C$8,0))))<10,$C$9,IF(IF(AK16<AL16*(1-$C$7),AL16*(1-$C$5-IF(AJ16<3,$C$8,0)),MIN(AL16*(1-$C$5-IF(AJ16<3,$C$8,0)),AK16*(1-$C$6-IF(AJ16<3,$C$8,0))))<100,$D$9,$E$9))))) -> 10.9 | AP16: =IF(ISNUMBER($D16),$D16,"n/a") -> 5.324 | AQ16: =IF(OR(AJ16=0,NOT(ISNUMBER($D16))),"—",AO16/$D16-1) -> 1.0473328 | AR16: =IF(AJ16=0,"—",AO16/AK16-1) -> -0.28419646 | AS16: =IF(AJ16=0,"—",AO16/AL16-1) -> -0.30523779 | AT16: =COUNTIFS(Offers!$B$7:$B$3000,$B16,Offers!$C$7:$C$3000,"Romania",Offers!$AI$7:$AI$3000,"yes") -> 9 | AU16: =IF(AT16=0,"—",SUMIFS(Review!$I$7:$I$600,Review!$B$7:$B$600,$B16,Review!$C$7:$C$600,"Romania")) -> 5 | AV16: =IF(AT16=0,"—",SUMIFS(Review!$J$7:$J$600,Review!$B$7:$B$600,$B16,Review!$C$7:$C$600,"Romania")) -> 10.87228 | AW16: =IF(AT16=0,"—",SUMIFS(Review!$K$7:$K$600,Review!$B$7:$B$600,$B16,Review!$C$7:$C$600,"Romania")) -> 16.912857 | AX16: =IF(AT16=0,"—",IF(AU16<AV16*(1-$C$7),"median (cheapest is an outlier)",IF(AU16*(1-$C$6)<AV16*(1-$C$5),"undercut cheapest","median"))) -> median (cheapest is an outlier) | AY16: =IF(AT16=0,"—",IF(AND(ISNUMBER($D16),$D16*(1+$C$10)>FLOOR(IF(AU16<AV16*(1-$C$7),AV16*(1-$C$5-IF(AT16<3,$C$8,0)),MIN(AV16*(1-$C$5-IF(AT16<3,$C$8,0)),AU16*(1-$C$6-IF(AT16<3,$C$8,0)))),IF(IF(AU16<AV16*(1-$C$7),AV16*(1-$C$5-IF(AT16<3,$C$8,0)),MIN(AV16*(1-$C$5-IF(AT16<3,$C$8,0)),AU16*(1-$C$6-IF(AT16<3,$C$8,0))))<10,$C$9,IF(IF(AU16<AV16*(1-$C$7),AV16*(1-$C$5-IF(AT16<3,$C$8,0)),MIN(AV16*(1-$C$5-IF(AT16<3,$C$8,0)),AU16*(1-$C$6-IF(AT16<3,$C$8,0))))<100,$D$9,$E$9)))),ROUND($D16*(1+$C$10),2),FLOOR(IF(AU16<AV16*(1-$C$7),AV16*(1-$C$5-IF(AT16<3,$C$8,0)),MIN(AV16*(1-$C$5-IF(AT16<3,$C$8,0)),AU16*(1-$C$6-IF(AT16<3,$C$8,0)))),IF(IF(AU16<AV16*(1-$C$7),AV16*(1-$C$5-IF(AT16<3,$C$8,0)),MIN(AV16*(1-$C$5-IF(AT16<3,$C$8,0)),AU16*(1-$C$6-IF(AT16<3,$C$8,0))))<10,$C$9,IF(IF(AU16<AV16*(1-$C$7),AV16*(1-$C$5-IF(AT16<3,$C$8,0)),MIN(AV16*(1-$C$5-IF(AT16<3,$C$8,0)),AU16*(1-$C$6-IF(AT16<3,$C$8,0))))<100,$D$9,$E$9))))) -> 8.15 | AZ16: =IF(AT16=0,"—",FLOOR(AY16*Sources!$G$9,0.1)) -> 43 | BA16: =IF(ISNUMBER($D16),$D16,"n/a") -> 5.324 | BB16: =IF(OR(AT16=0,NOT(ISNUMBER($D16))),"—",AY16/$D16-1) -> 0.53080391 | BC16: =IF(AT16=0,"—",AY16/AU16-1) -> 0.63 | BD16: =IF(AT16=0,"—",AY16/AV16-1) -> -0.25038722 | BE16: =COUNTIFS(Offers!$B$7:$B$3000,$B16,Offers!$C$7:$C$3000,"Hungary",Offers!$AI$7:$AI$3000,"yes") -> 6 | BF16: =IF(BE16=0,"—",SUMIFS(Review!$I$7:$I$600,Review!$B$7:$B$600,$B16,Review!$C$7:$C$600,"Hungary")) -> 6.391522 | BG16: =IF(BE16=0,"—",SUMIFS(Review!$J$7:$J$600,Review!$B$7:$B$600,$B16,Review!$C$7:$C$600,"Hungary")) -> 9.607768 | BH16: =IF(BE16=0,"—",SUMIFS(Review!$K$7:$K$600,Review!$B$7:$B$600,$B16,Review!$C$7:$C$600,"Hungary")) -> 15.678348 | BI16: =IF(BE16=0,"—",IF(BF16<BG16*(1-$C$7),"median (cheapest is an outlier)",IF(BF16*(1-$C$6)<BG16*(1-$C$5),"undercut cheapest","median"))) -> undercut cheapest | BJ16: =IF(BE16=0,"—",IF(AND(ISNUMBER($D16),$D16*(1+$C$10)>FLOOR(IF(BF16<BG16*(1-$C$7),BG16*(1-$C$5-IF(BE16<3,$C$8,0)),MIN(BG16*(1-$C$5-IF(BE16<3,$C$8,0)),BF16*(1-$C$6-IF(BE16<3,$C$8,0)))),IF(IF(BF16<BG16*(1-$C$7),BG16*(1-$C$5-IF(BE16<3,$C$8,0)),MIN(BG16*(1-$C$5-IF(BE16<3,$C$8,0)),BF16*(1-$C$6-IF(BE16<3,$C$8,0))))<10,$C$9,IF(IF(BF16<BG16*(1-$C$7),BG16*(1-$C$5-IF(BE16<3,$C$8,0)),MIN(BG16*(1-$C$5-IF(BE16<3,$C$8,0)),BF16*(1-$C$6-IF(BE16<3,$C$8,0))))<100,$D$9,$E$9)))),ROUND($D16*(1+$C$10),2),FLOOR(IF(BF16<BG16*(1-$C$7),BG16*(1-$C$5-IF(BE16<3,$C$8,0)),MIN(BG16*(1-$C$5-IF(BE16<3,$C$8,0)),BF16*(1-$C$6-IF(BE16<3,$C$8,0)))),IF(IF(BF16<BG16*(1-$C$7),BG16*(1-$C$5-IF(BE16<3,$C$8,0)),MIN(BG16*(1-$C$5-IF(BE16<3,$C$8,0)),BF16*(1-$C$6-IF(BE16<3,$C$8,0))))<10,$C$9,IF(IF(BF16<BG16*(1-$C$7),BG16*(1-$C$5-IF(BE16<3,$C$8,0)),MIN(BG16*(1-$C$5-IF(BE16<3,$C$8,0)),BF16*(1-$C$6-IF(BE16<3,$C$8,0))))<100,$D$9,$E$9))))) -> 6.05 | BK16: =IF(BE16=0,"—",FLOOR(BJ16*Sources!$G$8,10)) -> 2210 | BL16: =IF(ISNUMBER($D16),$D16,"n/a") -> 5.324 | BM16: =IF(OR(BE16=0,NOT(ISNUMBER($D16))),"—",BJ16/$D16-1) -> 0.13636364 | BN16: =IF(BE16=0,"—",BJ16/BF16-1) -> -0.053433595 | BO16: =IF(BE16=0,"—",BJ16/BG16-1) -> -0.3703012
B17: GN 1/3 PP container, 100 mm | C17: GNPP-13100 | D17: 1.375 | E17: =COUNTIFS(Offers!$B$7:$B$3000,$B17,Offers!$C$7:$C$3000,"Austria",Offers!$AI$7:$AI$3000,"yes") -> 10 | F17: =IF(E17=0,"—",SUMIFS(Review!$I$7:$I$600,Review!$B$7:$B$600,$B17,Review!$C$7:$C$600,"Austria")) -> 3.33 | G17: =IF(E17=0,"—",SUMIFS(Review!$J$7:$J$600,Review!$B$7:$B$600,$B17,Review!$C$7:$C$600,"Austria")) -> 5.305 | H17: =IF(E17=0,"—",SUMIFS(Review!$K$7:$K$600,Review!$B$7:$B$600,$B17,Review!$C$7:$C$600,"Austria")) -> 18.6 | I17: =IF(E17=0,"—",IF(F17<G17*(1-$C$7),"median (cheapest is an outlier)",IF(F17*(1-$C$6)<G17*(1-$C$5),"undercut cheapest","median"))) -> median (cheapest is an outlier) | J17: =IF(E17=0,"—",IF(AND(ISNUMBER($D17),$D17*(1+$C$10)>FLOOR(IF(F17<G17*(1-$C$7),G17*(1-$C$5-IF(E17<3,$C$8,0)),MIN(G17*(1-$C$5-IF(E17<3,$C$8,0)),F17*(1-$C$6-IF(E17<3,$C$8,0)))),IF(IF(F17<G17*(1-$C$7),G17*(1-$C$5-IF(E17<3,$C$8,0)),MIN(G17*(1-$C$5-IF(E17<3,$C$8,0)),F17*(1-$C$6-IF(E17<3,$C$8,0))))<10,$C$9,IF(IF(F17<G17*(1-$C$7),G17*(1-$C$5-IF(E17<3,$C$8,0)),MIN(G17*(1-$C$5-IF(E17<3,$C$8,0)),F17*(1-$C$6-IF(E17<3,$C$8,0))))<100,$D$9,$E$9)))),ROUND($D17*(1+$C$10),2),FLOOR(IF(F17<G17*(1-$C$7),G17*(1-$C$5-IF(E17<3,$C$8,0)),MIN(G17*(1-$C$5-IF(E17<3,$C$8,0)),F17*(1-$C$6-IF(E17<3,$C$8,0)))),IF(IF(F17<G17*(1-$C$7),G17*(1-$C$5-IF(E17<3,$C$8,0)),MIN(G17*(1-$C$5-IF(E17<3,$C$8,0)),F17*(1-$C$6-IF(E17<3,$C$8,0))))<10,$C$9,IF(IF(F17<G17*(1-$C$7),G17*(1-$C$5-IF(E17<3,$C$8,0)),MIN(G17*(1-$C$5-IF(E17<3,$C$8,0)),F17*(1-$C$6-IF(E17<3,$C$8,0))))<100,$D$9,$E$9))))) -> 3.95 | K17: =IF(ISNUMBER($D17),$D17,"n/a") -> 1.375 | L17: =IF(OR(E17=0,NOT(ISNUMBER($D17))),"—",J17/$D17-1) -> 1.8727273 | M17: =IF(E17=0,"—",J17/F17-1) -> 0.18618619 | N17: =IF(E17=0,"—",J17/G17-1) -> -0.25541942 | O17: =COUNTIFS(Offers!$B$7:$B$3000,$B17,Offers!$C$7:$C$3000,"Germany",Offers!$AI$7:$AI$3000,"yes") -> 8 | P17: =IF(O17=0,"—",SUMIFS(Review!$I$7:$I$600,Review!$B$7:$B$600,$B17,Review!$C$7:$C$600,"Germany")) -> 3.17 | Q17: =IF(O17=0,"—",SUMIFS(Review!$J$7:$J$600,Review!$B$7:$B$600,$B17,Review!$C$7:$C$600,"Germany")) -> 6.93 | R17: =IF(O17=0,"—",SUMIFS(Review!$K$7:$K$600,Review!$B$7:$B$600,$B17,Review!$C$7:$C$600,"Germany")) -> 18.6 | S17: =IF(O17=0,"—",IF(P17<Q17*(1-$C$7),"median (cheapest is an outlier)",IF(P17*(1-$C$6)<Q17*(1-$C$5),"undercut cheapest","median"))) -> median (cheapest is an outlier) | T17: =IF(O17=0,"—",IF(AND(ISNUMBER($D17),$D17*(1+$C$10)>FLOOR(IF(P17<Q17*(1-$C$7),Q17*(1-$C$5-IF(O17<3,$C$8,0)),MIN(Q17*(1-$C$5-IF(O17<3,$C$8,0)),P17*(1-$C$6-IF(O17<3,$C$8,0)))),IF(IF(P17<Q17*(1-$C$7),Q17*(1-$C$5-IF(O17<3,$C$8,0)),MIN(Q17*(1-$C$5-IF(O17<3,$C$8,0)),P17*(1-$C$6-IF(O17<3,$C$8,0))))<10,$C$9,IF(IF(P17<Q17*(1-$C$7),Q17*(1-$C$5-IF(O17<3,$C$8,0)),MIN(Q17*(1-$C$5-IF(O17<3,$C$8,0)),P17*(1-$C$6-IF(O17<3,$C$8,0))))<100,$D$9,$E$9)))),ROUND($D17*(1+$C$10),2),FLOOR(IF(P17<Q17*(1-$C$7),Q17*(1-$C$5-IF(O17<3,$C$8,0)),MIN(Q17*(1-$C$5-IF(O17<3,$C$8,0)),P17*(1-$C$6-IF(O17<3,$C$8,0)))),IF(IF(P17<Q17*(1-$C$7),Q17*(1-$C$5-IF(O17<3,$C$8,0)),MIN(Q17*(1-$C$5-IF(O17<3,$C$8,0)),P17*(1-$C$6-IF(O17<3,$C$8,0))))<10,$C$9,IF(IF(P17<Q17*(1-$C$7),Q17*(1-$C$5-IF(O17<3,$C$8,0)),MIN(Q17*(1-$C$5-IF(O17<3,$C$8,0)),P17*(1-$C$6-IF(O17<3,$C$8,0))))<100,$D$9,$E$9))))) -> 5.15 | U17: =IF(ISNUMBER($D17),$D17,"n/a") -> 1.375 | V17: =IF(OR(O17=0,NOT(ISNUMBER($D17))),"—",T17/$D17-1) -> 2.7454545 | W17: =IF(O17=0,"—",T17/P17-1) -> 0.62460568 | X17: =IF(O17=0,"—",T17/Q17-1) -> -0.25685426 | Y17: =COUNTIFS(Offers!$B$7:$B$3000,$B17,Offers!$C$7:$C$3000,"Czech",Offers!$AI$7:$AI$3000,"yes") -> 8 | Z17: =IF(Y17=0,"—",SUMIFS(Review!$I$7:$I$600,Review!$B$7:$B$600,$B17,Review!$C$7:$C$600,"Czech")) -> 3.234574 | AA17: =IF(Y17=0,"—",SUMIFS(Review!$J$7:$J$600,Review!$B$7:$B$600,$B17,Review!$C$7:$C$600,"Czech")) -> 4.15868 | AB17: =IF(Y17=0,"—",SUMIFS(Review!$K$7:$K$600,Review!$B$7:$B$600,$B17,Review!$C$7:$C$600,"Czech")) -> 6.182541 | AC17: =IF(Y17=0,"—",IF(Z17<AA17*(1-$C$7),"median (cheapest is an outlier)",IF(Z17*(1-$C$6)<AA17*(1-$C$5),"undercut cheapest","median"))) -> undercut cheapest | AD17: =IF(Y17=0,"—",IF(AND(ISNUMBER($D17),$D17*(1+$C$10)>FLOOR(IF(Z17<AA17*(1-$C$7),AA17*(1-$C$5-IF(Y17<3,$C$8,0)),MIN(AA17*(1-$C$5-IF(Y17<3,$C$8,0)),Z17*(1-$C$6-IF(Y17<3,$C$8,0)))),IF(IF(Z17<AA17*(1-$C$7),AA17*(1-$C$5-IF(Y17<3,$C$8,0)),MIN(AA17*(1-$C$5-IF(Y17<3,$C$8,0)),Z17*(1-$C$6-IF(Y17<3,$C$8,0))))<10,$C$9,IF(IF(Z17<AA17*(1-$C$7),AA17*(1-$C$5-IF(Y17<3,$C$8,0)),MIN(AA17*(1-$C$5-IF(Y17<3,$C$8,0)),Z17*(1-$C$6-IF(Y17<3,$C$8,0))))<100,$D$9,$E$9)))),ROUND($D17*(1+$C$10),2),FLOOR(IF(Z17<AA17*(1-$C$7),AA17*(1-$C$5-IF(Y17<3,$C$8,0)),MIN(AA17*(1-$C$5-IF(Y17<3,$C$8,0)),Z17*(1-$C$6-IF(Y17<3,$C$8,0)))),IF(IF(Z17<AA17*(1-$C$7),AA17*(1-$C$5-IF(Y17<3,$C$8,0)),MIN(AA17*(1-$C$5-IF(Y17<3,$C$8,0)),Z17*(1-$C$6-IF(Y17<3,$C$8,0))))<10,$C$9,IF(IF(Z17<AA17*(1-$C$7),AA17*(1-$C$5-IF(Y17<3,$C$8,0)),MIN(AA17*(1-$C$5-IF(Y17<3,$C$8,0)),Z17*(1-$C$6-IF(Y17<3,$C$8,0))))<100,$D$9,$E$9))))) -> 3.05 | AE17: =IF(Y17=0,"—",FLOOR(AD17*Sources!$G$10,1)) -> 74 | AF17: =IF(ISNUMBER($D17),$D17,"n/a") -> 1.375 | AG17: =IF(OR(Y17=0,NOT(ISNUMBER($D17))),"—",AD17/$D17-1) -> 1.2181818 | AH17: =IF(Y17=0,"—",AD17/Z17-1) -> -0.057062847 | AI17: =IF(Y17=0,"—",AD17/AA17-1) -> -0.26659421 | AJ17: =COUNTIFS(Offers!$B$7:$B$3000,$B17,Offers!$C$7:$C$3000,"Slovakia",Offers!$AI$7:$AI$3000,"yes") -> 2 | AK17: =IF(AJ17=0,"—",SUMIFS(Review!$I$7:$I$600,Review!$B$7:$B$600,$B17,Review!$C$7:$C$600,"Slovakia")) -> 6.373984 | AL17: =IF(AJ17=0,"—",SUMIFS(Review!$J$7:$J$600,Review!$B$7:$B$600,$B17,Review!$C$7:$C$600,"Slovakia")) -> 11.991992 | AM17: =IF(AJ17=0,"—",SUMIFS(Review!$K$7:$K$600,Review!$B$7:$B$600,$B17,Review!$C$7:$C$600,"Slovakia")) -> 17.61 | AN17: =IF(AJ17=0,"—",IF(AK17<AL17*(1-$C$7),"median (cheapest is an outlier)",IF(AK17*(1-$C$6)<AL17*(1-$C$5),"undercut cheapest","median"))) -> median (cheapest is an outlier) | AO17: =IF(AJ17=0,"—",IF(AND(ISNUMBER($D17),$D17*(1+$C$10)>FLOOR(IF(AK17<AL17*(1-$C$7),AL17*(1-$C$5-IF(AJ17<3,$C$8,0)),MIN(AL17*(1-$C$5-IF(AJ17<3,$C$8,0)),AK17*(1-$C$6-IF(AJ17<3,$C$8,0)))),IF(IF(AK17<AL17*(1-$C$7),AL17*(1-$C$5-IF(AJ17<3,$C$8,0)),MIN(AL17*(1-$C$5-IF(AJ17<3,$C$8,0)),AK17*(1-$C$6-IF(AJ17<3,$C$8,0))))<10,$C$9,IF(IF(AK17<AL17*(1-$C$7),AL17*(1-$C$5-IF(AJ17<3,$C$8,0)),MIN(AL17*(1-$C$5-IF(AJ17<3,$C$8,0)),AK17*(1-$C$6-IF(AJ17<3,$C$8,0))))<100,$D$9,$E$9)))),ROUND($D17*(1+$C$10),2),FLOOR(IF(AK17<AL17*(1-$C$7),AL17*(1-$C$5-IF(AJ17<3,$C$8,0)),MIN(AL17*(1-$C$5-IF(AJ17<3,$C$8,0)),AK17*(1-$C$6-IF(AJ17<3,$C$8,0)))),IF(IF(AK17<AL17*(1-$C$7),AL17*(1-$C$5-IF(AJ17<3,$C$8,0)),MIN(AL17*(1-$C$5-IF(AJ17<3,$C$8,0)),AK17*(1-$C$6-IF(AJ17<3,$C$8,0))))<10,$C$9,IF(IF(AK17<AL17*(1-$C$7),AL17*(1-$C$5-IF(AJ17<3,$C$8,0)),MIN(AL17*(1-$C$5-IF(AJ17<3,$C$8,0)),AK17*(1-$C$6-IF(AJ17<3,$C$8,0))))<100,$D$9,$E$9))))) -> 8.35 | AP17: =IF(ISNUMBER($D17),$D17,"n/a") -> 1.375 | AQ17: =IF(OR(AJ17=0,NOT(ISNUMBER($D17))),"—",AO17/$D17-1) -> 5.0727273 | AR17: =IF(AJ17=0,"—",AO17/AK17-1) -> 0.3100127 | AS17: =IF(AJ17=0,"—",AO17/AL17-1) -> -0.303702 | AT17: =COUNTIFS(Offers!$B$7:$B$3000,$B17,Offers!$C$7:$C$3000,"Romania",Offers!$AI$7:$AI$3000,"yes") -> 3 | AU17: =IF(AT17=0,"—",SUMIFS(Review!$I$7:$I$600,Review!$B$7:$B$600,$B17,Review!$C$7:$C$600,"Romania")) -> 6.004576 | AV17: =IF(AT17=0,"—",SUMIFS(Review!$J$7:$J$600,Review!$B$7:$B$600,$B17,Review!$C$7:$C$600,"Romania")) -> 6.404376 | AW17: =IF(AT17=0,"—",SUMIFS(Review!$K$7:$K$600,Review!$B$7:$B$600,$B17,Review!$C$7:$C$600,"Romania")) -> 6.751122 | AX17: =IF(AT17=0,"—",IF(AU17<AV17*(1-$C$7),"median (cheapest is an outlier)",IF(AU17*(1-$C$6)<AV17*(1-$C$5),"undercut cheapest","median"))) -> median | AY17: =IF(AT17=0,"—",IF(AND(ISNUMBER($D17),$D17*(1+$C$10)>FLOOR(IF(AU17<AV17*(1-$C$7),AV17*(1-$C$5-IF(AT17<3,$C$8,0)),MIN(AV17*(1-$C$5-IF(AT17<3,$C$8,0)),AU17*(1-$C$6-IF(AT17<3,$C$8,0)))),IF(IF(AU17<AV17*(1-$C$7),AV17*(1-$C$5-IF(AT17<3,$C$8,0)),MIN(AV17*(1-$C$5-IF(AT17<3,$C$8,0)),AU17*(1-$C$6-IF(AT17<3,$C$8,0))))<10,$C$9,IF(IF(AU17<AV17*(1-$C$7),AV17*(1-$C$5-IF(AT17<3,$C$8,0)),MIN(AV17*(1-$C$5-IF(AT17<3,$C$8,0)),AU17*(1-$C$6-IF(AT17<3,$C$8,0))))<100,$D$9,$E$9)))),ROUND($D17*(1+$C$10),2),FLOOR(IF(AU17<AV17*(1-$C$7),AV17*(1-$C$5-IF(AT17<3,$C$8,0)),MIN(AV17*(1-$C$5-IF(AT17<3,$C$8,0)),AU17*(1-$C$6-IF(AT17<3,$C$8,0)))),IF(IF(AU17<AV17*(1-$C$7),AV17*(1-$C$5-IF(AT17<3,$C$8,0)),MIN(AV17*(1-$C$5-IF(AT17<3,$C$8,0)),AU17*(1-$C$6-IF(AT17<3,$C$8,0))))<10,$C$9,IF(IF(AU17<AV17*(1-$C$7),AV17*(1-$C$5-IF(AT17<3,$C$8,0)),MIN(AV17*(1-$C$5-IF(AT17<3,$C$8,0)),AU17*(1-$C$6-IF(AT17<3,$C$8,0))))<100,$D$9,$E$9))))) -> 4.8 | AZ17: =IF(AT17=0,"—",FLOOR(AY17*Sources!$G$9,0.1)) -> 25.3 | BA17: =IF(ISNUMBER($D17),$D17,"n/a") -> 1.375 | BB17: =IF(OR(AT17=0,NOT(ISNUMBER($D17))),"—",AY17/$D17-1) -> 2.4909091 | BC17: =IF(AT17=0,"—",AY17/AU17-1) -> -0.20060967 | BD17: =IF(AT17=0,"—",AY17/AV17-1) -> -0.25051246 | BE17: =COUNTIFS(Offers!$B$7:$B$3000,$B17,Offers!$C$7:$C$3000,"Hungary",Offers!$AI$7:$AI$3000,"yes") -> 5 | BF17: =IF(BE17=0,"—",SUMIFS(Review!$I$7:$I$600,Review!$B$7:$B$600,$B17,Review!$C$7:$C$600,"Hungary")) -> 2.294392 | BG17: =IF(BE17=0,"—",SUMIFS(Review!$J$7:$J$600,Review!$B$7:$B$600,$B17,Review!$C$7:$C$600,"Hungary")) -> 4.247357 | BH17: =IF(BE17=0,"—",SUMIFS(Review!$K$7:$K$600,Review!$B$7:$B$600,$B17,Review!$C$7:$C$600,"Hungary")) -> 5.525662 | BI17: =IF(BE17=0,"—",IF(BF17<BG17*(1-$C$7),"median (cheapest is an outlier)",IF(BF17*(1-$C$6)<BG17*(1-$C$5),"undercut cheapest","median"))) -> median (cheapest is an outlier) | BJ17: =IF(BE17=0,"—",IF(AND(ISNUMBER($D17),$D17*(1+$C$10)>FLOOR(IF(BF17<BG17*(1-$C$7),BG17*(1-$C$5-IF(BE17<3,$C$8,0)),MIN(BG17*(1-$C$5-IF(BE17<3,$C$8,0)),BF17*(1-$C$6-IF(BE17<3,$C$8,0)))),IF(IF(BF17<BG17*(1-$C$7),BG17*(1-$C$5-IF(BE17<3,$C$8,0)),MIN(BG17*(1-$C$5-IF(BE17<3,$C$8,0)),BF17*(1-$C$6-IF(BE17<3,$C$8,0))))<10,$C$9,IF(IF(BF17<BG17*(1-$C$7),BG17*(1-$C$5-IF(BE17<3,$C$8,0)),MIN(BG17*(1-$C$5-IF(BE17<3,$C$8,0)),BF17*(1-$C$6-IF(BE17<3,$C$8,0))))<100,$D$9,$E$9)))),ROUND($D17*(1+$C$10),2),FLOOR(IF(BF17<BG17*(1-$C$7),BG17*(1-$C$5-IF(BE17<3,$C$8,0)),MIN(BG17*(1-$C$5-IF(BE17<3,$C$8,0)),BF17*(1-$C$6-IF(BE17<3,$C$8,0)))),IF(IF(BF17<BG17*(1-$C$7),BG17*(1-$C$5-IF(BE17<3,$C$8,0)),MIN(BG17*(1-$C$5-IF(BE17<3,$C$8,0)),BF17*(1-$C$6-IF(BE17<3,$C$8,0))))<10,$C$9,IF(IF(BF17<BG17*(1-$C$7),BG17*(1-$C$5-IF(BE17<3,$C$8,0)),MIN(BG17*(1-$C$5-IF(BE17<3,$C$8,0)),BF17*(1-$C$6-IF(BE17<3,$C$8,0))))<100,$D$9,$E$9))))) -> 3.15 | BK17: =IF(BE17=0,"—",FLOOR(BJ17*Sources!$G$8,10)) -> 1150 | BL17: =IF(ISNUMBER($D17),$D17,"n/a") -> 1.375 | BM17: =IF(OR(BE17=0,NOT(ISNUMBER($D17))),"—",BJ17/$D17-1) -> 1.2909091 | BN17: =IF(BE17=0,"—",BJ17/BF17-1) -> 0.37291274 | BO17: =IF(BE17=0,"—",BJ17/BG17-1) -> -0.25836232
B18: GN 1/1 PP lid | C18: GNPPL-11 | D18: 2.2 | E18: =COUNTIFS(Offers!$B$7:$B$3000,$B18,Offers!$C$7:$C$3000,"Austria",Offers!$AI$7:$AI$3000,"yes") -> 8 | F18: =IF(E18=0,"—",SUMIFS(Review!$I$7:$I$600,Review!$B$7:$B$600,$B18,Review!$C$7:$C$600,"Austria")) -> 2.46 | G18: =IF(E18=0,"—",SUMIFS(Review!$J$7:$J$600,Review!$B$7:$B$600,$B18,Review!$C$7:$C$600,"Austria")) -> 6.525 | H18: =IF(E18=0,"—",SUMIFS(Review!$K$7:$K$600,Review!$B$7:$B$600,$B18,Review!$C$7:$C$600,"Austria")) -> 16.66 | I18: =IF(E18=0,"—",IF(F18<G18*(1-$C$7),"median (cheapest is an outlier)",IF(F18*(1-$C$6)<G18*(1-$C$5),"undercut cheapest","median"))) -> median (cheapest is an outlier) | J18: =IF(E18=0,"—",IF(AND(ISNUMBER($D18),$D18*(1+$C$10)>FLOOR(IF(F18<G18*(1-$C$7),G18*(1-$C$5-IF(E18<3,$C$8,0)),MIN(G18*(1-$C$5-IF(E18<3,$C$8,0)),F18*(1-$C$6-IF(E18<3,$C$8,0)))),IF(IF(F18<G18*(1-$C$7),G18*(1-$C$5-IF(E18<3,$C$8,0)),MIN(G18*(1-$C$5-IF(E18<3,$C$8,0)),F18*(1-$C$6-IF(E18<3,$C$8,0))))<10,$C$9,IF(IF(F18<G18*(1-$C$7),G18*(1-$C$5-IF(E18<3,$C$8,0)),MIN(G18*(1-$C$5-IF(E18<3,$C$8,0)),F18*(1-$C$6-IF(E18<3,$C$8,0))))<100,$D$9,$E$9)))),ROUND($D18*(1+$C$10),2),FLOOR(IF(F18<G18*(1-$C$7),G18*(1-$C$5-IF(E18<3,$C$8,0)),MIN(G18*(1-$C$5-IF(E18<3,$C$8,0)),F18*(1-$C$6-IF(E18<3,$C$8,0)))),IF(IF(F18<G18*(1-$C$7),G18*(1-$C$5-IF(E18<3,$C$8,0)),MIN(G18*(1-$C$5-IF(E18<3,$C$8,0)),F18*(1-$C$6-IF(E18<3,$C$8,0))))<10,$C$9,IF(IF(F18<G18*(1-$C$7),G18*(1-$C$5-IF(E18<3,$C$8,0)),MIN(G18*(1-$C$5-IF(E18<3,$C$8,0)),F18*(1-$C$6-IF(E18<3,$C$8,0))))<100,$D$9,$E$9))))) -> 4.85 | K18: =IF(ISNUMBER($D18),$D18,"n/a") -> 2.2 | L18: =IF(OR(E18=0,NOT(ISNUMBER($D18))),"—",J18/$D18-1) -> 1.2045455 | M18: =IF(E18=0,"—",J18/F18-1) -> 0.97154472 | N18: =IF(E18=0,"—",J18/G18-1) -> -0.25670498 | O18: =COUNTIFS(Offers!$B$7:$B$3000,$B18,Offers!$C$7:$C$3000,"Germany",Offers!$AI$7:$AI$3000,"yes") -> 9 | P18: =IF(O18=0,"—",SUMIFS(Review!$I$7:$I$600,Review!$B$7:$B$600,$B18,Review!$C$7:$C$600,"Germany")) -> 2.33 | Q18: =IF(O18=0,"—",SUMIFS(Review!$J$7:$J$600,Review!$B$7:$B$600,$B18,Review!$C$7:$C$600,"Germany")) -> 7.5 | R18: =IF(O18=0,"—",SUMIFS(Review!$K$7:$K$600,Review!$B$7:$B$600,$B18,Review!$C$7:$C$600,"Germany")) -> 16.66 | S18: =IF(O18=0,"—",IF(P18<Q18*(1-$C$7),"median (cheapest is an outlier)",IF(P18*(1-$C$6)<Q18*(1-$C$5),"undercut cheapest","median"))) -> median (cheapest is an outlier) | T18: =IF(O18=0,"—",IF(AND(ISNUMBER($D18),$D18*(1+$C$10)>FLOOR(IF(P18<Q18*(1-$C$7),Q18*(1-$C$5-IF(O18<3,$C$8,0)),MIN(Q18*(1-$C$5-IF(O18<3,$C$8,0)),P18*(1-$C$6-IF(O18<3,$C$8,0)))),IF(IF(P18<Q18*(1-$C$7),Q18*(1-$C$5-IF(O18<3,$C$8,0)),MIN(Q18*(1-$C$5-IF(O18<3,$C$8,0)),P18*(1-$C$6-IF(O18<3,$C$8,0))))<10,$C$9,IF(IF(P18<Q18*(1-$C$7),Q18*(1-$C$5-IF(O18<3,$C$8,0)),MIN(Q18*(1-$C$5-IF(O18<3,$C$8,0)),P18*(1-$C$6-IF(O18<3,$C$8,0))))<100,$D$9,$E$9)))),ROUND($D18*(1+$C$10),2),FLOOR(IF(P18<Q18*(1-$C$7),Q18*(1-$C$5-IF(O18<3,$C$8,0)),MIN(Q18*(1-$C$5-IF(O18<3,$C$8,0)),P18*(1-$C$6-IF(O18<3,$C$8,0)))),IF(IF(P18<Q18*(1-$C$7),Q18*(1-$C$5-IF(O18<3,$C$8,0)),MIN(Q18*(1-$C$5-IF(O18<3,$C$8,0)),P18*(1-$C$6-IF(O18<3,$C$8,0))))<10,$C$9,IF(IF(P18<Q18*(1-$C$7),Q18*(1-$C$5-IF(O18<3,$C$8,0)),MIN(Q18*(1-$C$5-IF(O18<3,$C$8,0)),P18*(1-$C$6-IF(O18<3,$C$8,0))))<100,$D$9,$E$9))))) -> 5.6 | U18: =IF(ISNUMBER($D18),$D18,"n/a") -> 2.2 | V18: =IF(OR(O18=0,NOT(ISNUMBER($D18))),"—",T18/$D18-1) -> 1.5454545 | W18: =IF(O18=0,"—",T18/P18-1) -> 1.4034335 | X18: =IF(O18=0,"—",T18/Q18-1) -> -0.25333333 | Y18: =COUNTIFS(Offers!$B$7:$B$3000,$B18,Offers!$C$7:$C$3000,"Czech",Offers!$AI$7:$AI$3000,"yes") -> 8 | Z18: =IF(Y18=0,"—",SUMIFS(Review!$I$7:$I$600,Review!$B$7:$B$600,$B18,Review!$C$7:$C$600,"Czech")) -> 3.439294 | AA18: =IF(Y18=0,"—",SUMIFS(Review!$J$7:$J$600,Review!$B$7:$B$600,$B18,Review!$C$7:$C$600,"Czech")) -> 5.040613 | AB18: =IF(Y18=0,"—",SUMIFS(Review!$K$7:$K$600,Review!$B$7:$B$600,$B18,Review!$C$7:$C$600,"Czech")) -> 11.843455 | AC18: =IF(Y18=0,"—",IF(Z18<AA18*(1-$C$7),"median (cheapest is an outlier)",IF(Z18*(1-$C$6)<AA18*(1-$C$5),"undercut cheapest","median"))) -> undercut cheapest | AD18: =IF(Y18=0,"—",IF(AND(ISNUMBER($D18),$D18*(1+$C$10)>FLOOR(IF(Z18<AA18*(1-$C$7),AA18*(1-$C$5-IF(Y18<3,$C$8,0)),MIN(AA18*(1-$C$5-IF(Y18<3,$C$8,0)),Z18*(1-$C$6-IF(Y18<3,$C$8,0)))),IF(IF(Z18<AA18*(1-$C$7),AA18*(1-$C$5-IF(Y18<3,$C$8,0)),MIN(AA18*(1-$C$5-IF(Y18<3,$C$8,0)),Z18*(1-$C$6-IF(Y18<3,$C$8,0))))<10,$C$9,IF(IF(Z18<AA18*(1-$C$7),AA18*(1-$C$5-IF(Y18<3,$C$8,0)),MIN(AA18*(1-$C$5-IF(Y18<3,$C$8,0)),Z18*(1-$C$6-IF(Y18<3,$C$8,0))))<100,$D$9,$E$9)))),ROUND($D18*(1+$C$10),2),FLOOR(IF(Z18<AA18*(1-$C$7),AA18*(1-$C$5-IF(Y18<3,$C$8,0)),MIN(AA18*(1-$C$5-IF(Y18<3,$C$8,0)),Z18*(1-$C$6-IF(Y18<3,$C$8,0)))),IF(IF(Z18<AA18*(1-$C$7),AA18*(1-$C$5-IF(Y18<3,$C$8,0)),MIN(AA18*(1-$C$5-IF(Y18<3,$C$8,0)),Z18*(1-$C$6-IF(Y18<3,$C$8,0))))<10,$C$9,IF(IF(Z18<AA18*(1-$C$7),AA18*(1-$C$5-IF(Y18<3,$C$8,0)),MIN(AA18*(1-$C$5-IF(Y18<3,$C$8,0)),Z18*(1-$C$6-IF(Y18<3,$C$8,0))))<100,$D$9,$E$9))))) -> 3.25 | AE18: =IF(Y18=0,"—",FLOOR(AD18*Sources!$G$10,1)) -> 79 | AF18: =IF(ISNUMBER($D18),$D18,"n/a") -> 2.2 | AG18: =IF(OR(Y18=0,NOT(ISNUMBER($D18))),"—",AD18/$D18-1) -> 0.47727273 | AH18: =IF(Y18=0,"—",AD18/Z18-1) -> -0.055038621 | AI18: =IF(Y18=0,"—",AD18/AA18-1) -> -0.35523715 | AJ18: =COUNTIFS(Offers!$B$7:$B$3000,$B18,Offers!$C$7:$C$3000,"Slovakia",Offers!$AI$7:$AI$3000,"yes") -> 2 | AK18: =IF(AJ18=0,"—",SUMIFS(Review!$I$7:$I$600,Review!$B$7:$B$600,$B18,Review!$C$7:$C$600,"Slovakia")) -> 8.46 | AL18: =IF(AJ18=0,"—",SUMIFS(Review!$J$7:$J$600,Review!$B$7:$B$600,$B18,Review!$C$7:$C$600,"Slovakia")) -> 9.945447 | AM18: =IF(AJ18=0,"—",SUMIFS(Review!$K$7:$K$600,Review!$B$7:$B$600,$B18,Review!$C$7:$C$600,"Slovakia")) -> 11.430894 | AN18: =IF(AJ18=0,"—",IF(AK18<AL18*(1-$C$7),"median (cheapest is an outlier)",IF(AK18*(1-$C$6)<AL18*(1-$C$5),"undercut cheapest","median"))) -> median | AO18: =IF(AJ18=0,"—",IF(AND(ISNUMBER($D18),$D18*(1+$C$10)>FLOOR(IF(AK18<AL18*(1-$C$7),AL18*(1-$C$5-IF(AJ18<3,$C$8,0)),MIN(AL18*(1-$C$5-IF(AJ18<3,$C$8,0)),AK18*(1-$C$6-IF(AJ18<3,$C$8,0)))),IF(IF(AK18<AL18*(1-$C$7),AL18*(1-$C$5-IF(AJ18<3,$C$8,0)),MIN(AL18*(1-$C$5-IF(AJ18<3,$C$8,0)),AK18*(1-$C$6-IF(AJ18<3,$C$8,0))))<10,$C$9,IF(IF(AK18<AL18*(1-$C$7),AL18*(1-$C$5-IF(AJ18<3,$C$8,0)),MIN(AL18*(1-$C$5-IF(AJ18<3,$C$8,0)),AK18*(1-$C$6-IF(AJ18<3,$C$8,0))))<100,$D$9,$E$9)))),ROUND($D18*(1+$C$10),2),FLOOR(IF(AK18<AL18*(1-$C$7),AL18*(1-$C$5-IF(AJ18<3,$C$8,0)),MIN(AL18*(1-$C$5-IF(AJ18<3,$C$8,0)),AK18*(1-$C$6-IF(AJ18<3,$C$8,0)))),IF(IF(AK18<AL18*(1-$C$7),AL18*(1-$C$5-IF(AJ18<3,$C$8,0)),MIN(AL18*(1-$C$5-IF(AJ18<3,$C$8,0)),AK18*(1-$C$6-IF(AJ18<3,$C$8,0))))<10,$C$9,IF(IF(AK18<AL18*(1-$C$7),AL18*(1-$C$5-IF(AJ18<3,$C$8,0)),MIN(AL18*(1-$C$5-IF(AJ18<3,$C$8,0)),AK18*(1-$C$6-IF(AJ18<3,$C$8,0))))<100,$D$9,$E$9))))) -> 6.95 | AP18: =IF(ISNUMBER($D18),$D18,"n/a") -> 2.2 | AQ18: =IF(OR(AJ18=0,NOT(ISNUMBER($D18))),"—",AO18/$D18-1) -> 2.1590909 | AR18: =IF(AJ18=0,"—",AO18/AK18-1) -> -0.178487 | AS18: =IF(AJ18=0,"—",AO18/AL18-1) -> -0.30118777 | AT18: =COUNTIFS(Offers!$B$7:$B$3000,$B18,Offers!$C$7:$C$3000,"Romania",Offers!$AI$7:$AI$3000,"yes") -> 3 | AU18: =IF(AT18=0,"—",SUMIFS(Review!$I$7:$I$600,Review!$B$7:$B$600,$B18,Review!$C$7:$C$600,"Romania")) -> 4.367481 | AV18: =IF(AT18=0,"—",SUMIFS(Review!$J$7:$J$600,Review!$B$7:$B$600,$B18,Review!$C$7:$C$600,"Romania")) -> 4.50959 | AW18: =IF(AT18=0,"—",SUMIFS(Review!$K$7:$K$600,Review!$B$7:$B$600,$B18,Review!$C$7:$C$600,"Romania")) -> 5.231503 | AX18: =IF(AT18=0,"—",IF(AU18<AV18*(1-$C$7),"median (cheapest is an outlier)",IF(AU18*(1-$C$6)<AV18*(1-$C$5),"undercut cheapest","median"))) -> median | AY18: =IF(AT18=0,"—",IF(AND(ISNUMBER($D18),$D18*(1+$C$10)>FLOOR(IF(AU18<AV18*(1-$C$7),AV18*(1-$C$5-IF(AT18<3,$C$8,0)),MIN(AV18*(1-$C$5-IF(AT18<3,$C$8,0)),AU18*(1-$C$6-IF(AT18<3,$C$8,0)))),IF(IF(AU18<AV18*(1-$C$7),AV18*(1-$C$5-IF(AT18<3,$C$8,0)),MIN(AV18*(1-$C$5-IF(AT18<3,$C$8,0)),AU18*(1-$C$6-IF(AT18<3,$C$8,0))))<10,$C$9,IF(IF(AU18<AV18*(1-$C$7),AV18*(1-$C$5-IF(AT18<3,$C$8,0)),MIN(AV18*(1-$C$5-IF(AT18<3,$C$8,0)),AU18*(1-$C$6-IF(AT18<3,$C$8,0))))<100,$D$9,$E$9)))),ROUND($D18*(1+$C$10),2),FLOOR(IF(AU18<AV18*(1-$C$7),AV18*(1-$C$5-IF(AT18<3,$C$8,0)),MIN(AV18*(1-$C$5-IF(AT18<3,$C$8,0)),AU18*(1-$C$6-IF(AT18<3,$C$8,0)))),IF(IF(AU18<AV18*(1-$C$7),AV18*(1-$C$5-IF(AT18<3,$C$8,0)),MIN(AV18*(1-$C$5-IF(AT18<3,$C$8,0)),AU18*(1-$C$6-IF(AT18<3,$C$8,0))))<10,$C$9,IF(IF(AU18<AV18*(1-$C$7),AV18*(1-$C$5-IF(AT18<3,$C$8,0)),MIN(AV18*(1-$C$5-IF(AT18<3,$C$8,0)),AU18*(1-$C$6-IF(AT18<3,$C$8,0))))<100,$D$9,$E$9))))) -> 3.35 | AZ18: =IF(AT18=0,"—",FLOOR(AY18*Sources!$G$9,0.1)) -> 17.6 | BA18: =IF(ISNUMBER($D18),$D18,"n/a") -> 2.2 | BB18: =IF(OR(AT18=0,NOT(ISNUMBER($D18))),"—",AY18/$D18-1) -> 0.52272727 | BC18: =IF(AT18=0,"—",AY18/AU18-1) -> -0.23296747 | BD18: =IF(AT18=0,"—",AY18/AV18-1) -> -0.25713868 | BE18: =COUNTIFS(Offers!$B$7:$B$3000,$B18,Offers!$C$7:$C$3000,"Hungary",Offers!$AI$7:$AI$3000,"yes") -> 0 | BF18: =IF(BE18=0,"—",SUMIFS(Review!$I$7:$I$600,Review!$B$7:$B$600,$B18,Review!$C$7:$C$600,"Hungary")) -> — | BG18: =IF(BE18=0,"—",SUMIFS(Review!$J$7:$J$600,Review!$B$7:$B$600,$B18,Review!$C$7:$C$600,"Hungary")) -> — | BH18: =IF(BE18=0,"—",SUMIFS(Review!$K$7:$K$600,Review!$B$7:$B$600,$B18,Review!$C$7:$C$600,"Hungary")) -> — | BI18: =IF(BE18=0,"—",IF(BF18<BG18*(1-$C$7),"median (cheapest is an outlier)",IF(BF18*(1-$C$6)<BG18*(1-$C$5),"undercut cheapest","median"))) -> — | BJ18: =IF(BE18=0,"—",IF(AND(ISNUMBER($D18),$D18*(1+$C$10)>FLOOR(IF(BF18<BG18*(1-$C$7),BG18*(1-$C$5-IF(BE18<3,$C$8,0)),MIN(BG18*(1-$C$5-IF(BE18<3,$C$8,0)),BF18*(1-$C$6-IF(BE18<3,$C$8,0)))),IF(IF(BF18<BG18*(1-$C$7),BG18*(1-$C$5-IF(BE18<3,$C$8,0)),MIN(BG18*(1-$C$5-IF(BE18<3,$C$8,0)),BF18*(1-$C$6-IF(BE18<3,$C$8,0))))<10,$C$9,IF(IF(BF18<BG18*(1-$C$7),BG18*(1-$C$5-IF(BE18<3,$C$8,0)),MIN(BG18*(1-$C$5-IF(BE18<3,$C$8,0)),BF18*(1-$C$6-IF(BE18<3,$C$8,0))))<100,$D$9,$E$9)))),ROUND($D18*(1+$C$10),2),FLOOR(IF(BF18<BG18*(1-$C$7),BG18*(1-$C$5-IF(BE18<3,$C$8,0)),MIN(BG18*(1-$C$5-IF(BE18<3,$C$8,0)),BF18*(1-$C$6-IF(BE18<3,$C$8,0)))),IF(IF(BF18<BG18*(1-$C$7),BG18*(1-$C$5-IF(BE18<3,$C$8,0)),MIN(BG18*(1-$C$5-IF(BE18<3,$C$8,0)),BF18*(1-$C$6-IF(BE18<3,$C$8,0))))<10,$C$9,IF(IF(BF18<BG18*(1-$C$7),BG18*(1-$C$5-IF(BE18<3,$C$8,0)),MIN(BG18*(1-$C$5-IF(BE18<3,$C$8,0)),BF18*(1-$C$6-IF(BE18<3,$C$8,0))))<100,$D$9,$E$9))))) -> — | BK18: =IF(BE18=0,"—",FLOOR(BJ18*Sources!$G$8,10)) -> — | BL18: =IF(ISNUMBER($D18),$D18,"n/a") -> 2.2 | BM18: =IF(OR(BE18=0,NOT(ISNUMBER($D18))),"—",BJ18/$D18-1) -> — | BN18: =IF(BE18=0,"—",BJ18/BF18-1) -> — | BO18: =IF(BE18=0,"—",BJ18/BG18-1) -> —
B19: Squeeze bottle 500 ml, PP, single tip | C19: GPS-500 | D19: 0.55 | E19: =COUNTIFS(Offers!$B$7:$B$3000,$B19,Offers!$C$7:$C$3000,"Austria",Offers!$AI$7:$AI$3000,"yes") -> 7 | F19: =IF(E19=0,"—",SUMIFS(Review!$I$7:$I$600,Review!$B$7:$B$600,$B19,Review!$C$7:$C$600,"Austria")) -> 1.42 | G19: =IF(E19=0,"—",SUMIFS(Review!$J$7:$J$600,Review!$B$7:$B$600,$B19,Review!$C$7:$C$600,"Austria")) -> 2.32 | H19: =IF(E19=0,"—",SUMIFS(Review!$K$7:$K$600,Review!$B$7:$B$600,$B19,Review!$C$7:$C$600,"Austria")) -> 4.33 | I19: =IF(E19=0,"—",IF(F19<G19*(1-$C$7),"median (cheapest is an outlier)",IF(F19*(1-$C$6)<G19*(1-$C$5),"undercut cheapest","median"))) -> median (cheapest is an outlier) | J19: =IF(E19=0,"—",IF(AND(ISNUMBER($D19),$D19*(1+$C$10)>FLOOR(IF(F19<G19*(1-$C$7),G19*(1-$C$5-IF(E19<3,$C$8,0)),MIN(G19*(1-$C$5-IF(E19<3,$C$8,0)),F19*(1-$C$6-IF(E19<3,$C$8,0)))),IF(IF(F19<G19*(1-$C$7),G19*(1-$C$5-IF(E19<3,$C$8,0)),MIN(G19*(1-$C$5-IF(E19<3,$C$8,0)),F19*(1-$C$6-IF(E19<3,$C$8,0))))<10,$C$9,IF(IF(F19<G19*(1-$C$7),G19*(1-$C$5-IF(E19<3,$C$8,0)),MIN(G19*(1-$C$5-IF(E19<3,$C$8,0)),F19*(1-$C$6-IF(E19<3,$C$8,0))))<100,$D$9,$E$9)))),ROUND($D19*(1+$C$10),2),FLOOR(IF(F19<G19*(1-$C$7),G19*(1-$C$5-IF(E19<3,$C$8,0)),MIN(G19*(1-$C$5-IF(E19<3,$C$8,0)),F19*(1-$C$6-IF(E19<3,$C$8,0)))),IF(IF(F19<G19*(1-$C$7),G19*(1-$C$5-IF(E19<3,$C$8,0)),MIN(G19*(1-$C$5-IF(E19<3,$C$8,0)),F19*(1-$C$6-IF(E19<3,$C$8,0))))<10,$C$9,IF(IF(F19<G19*(1-$C$7),G19*(1-$C$5-IF(E19<3,$C$8,0)),MIN(G19*(1-$C$5-IF(E19<3,$C$8,0)),F19*(1-$C$6-IF(E19<3,$C$8,0))))<100,$D$9,$E$9))))) -> 1.7 | K19: =IF(ISNUMBER($D19),$D19,"n/a") -> 0.55 | L19: =IF(OR(E19=0,NOT(ISNUMBER($D19))),"—",J19/$D19-1) -> 2.0909091 | M19: =IF(E19=0,"—",J19/F19-1) -> 0.1971831 | N19: =IF(E19=0,"—",J19/G19-1) -> -0.26724138 | O19: =COUNTIFS(Offers!$B$7:$B$3000,$B19,Offers!$C$7:$C$3000,"Germany",Offers!$AI$7:$AI$3000,"yes") -> 8 | P19: =IF(O19=0,"—",SUMIFS(Review!$I$7:$I$600,Review!$B$7:$B$600,$B19,Review!$C$7:$C$600,"Germany")) -> 0.94 | Q19: =IF(O19=0,"—",SUMIFS(Review!$J$7:$J$600,Review!$B$7:$B$600,$B19,Review!$C$7:$C$600,"Germany")) -> 2.055 | R19: =IF(O19=0,"—",SUMIFS(Review!$K$7:$K$600,Review!$B$7:$B$600,$B19,Review!$C$7:$C$600,"Germany")) -> 4 | S19: =IF(O19=0,"—",IF(P19<Q19*(1-$C$7),"median (cheapest is an outlier)",IF(P19*(1-$C$6)<Q19*(1-$C$5),"undercut cheapest","median"))) -> median (cheapest is an outlier) | T19: =IF(O19=0,"—",IF(AND(ISNUMBER($D19),$D19*(1+$C$10)>FLOOR(IF(P19<Q19*(1-$C$7),Q19*(1-$C$5-IF(O19<3,$C$8,0)),MIN(Q19*(1-$C$5-IF(O19<3,$C$8,0)),P19*(1-$C$6-IF(O19<3,$C$8,0)))),IF(IF(P19<Q19*(1-$C$7),Q19*(1-$C$5-IF(O19<3,$C$8,0)),MIN(Q19*(1-$C$5-IF(O19<3,$C$8,0)),P19*(1-$C$6-IF(O19<3,$C$8,0))))<10,$C$9,IF(IF(P19<Q19*(1-$C$7),Q19*(1-$C$5-IF(O19<3,$C$8,0)),MIN(Q19*(1-$C$5-IF(O19<3,$C$8,0)),P19*(1-$C$6-IF(O19<3,$C$8,0))))<100,$D$9,$E$9)))),ROUND($D19*(1+$C$10),2),FLOOR(IF(P19<Q19*(1-$C$7),Q19*(1-$C$5-IF(O19<3,$C$8,0)),MIN(Q19*(1-$C$5-IF(O19<3,$C$8,0)),P19*(1-$C$6-IF(O19<3,$C$8,0)))),IF(IF(P19<Q19*(1-$C$7),Q19*(1-$C$5-IF(O19<3,$C$8,0)),MIN(Q19*(1-$C$5-IF(O19<3,$C$8,0)),P19*(1-$C$6-IF(O19<3,$C$8,0))))<10,$C$9,IF(IF(P19<Q19*(1-$C$7),Q19*(1-$C$5-IF(O19<3,$C$8,0)),MIN(Q19*(1-$C$5-IF(O19<3,$C$8,0)),P19*(1-$C$6-IF(O19<3,$C$8,0))))<100,$D$9,$E$9))))) -> 1.5 | U19: =IF(ISNUMBER($D19),$D19,"n/a") -> 0.55 | V19: =IF(OR(O19=0,NOT(ISNUMBER($D19))),"—",T19/$D19-1) -> 1.7272727 | W19: =IF(O19=0,"—",T19/P19-1) -> 0.59574468 | X19: =IF(O19=0,"—",T19/Q19-1) -> -0.27007299 | Y19: =COUNTIFS(Offers!$B$7:$B$3000,$B19,Offers!$C$7:$C$3000,"Czech",Offers!$AI$7:$AI$3000,"yes") -> 5 | Z19: =IF(Y19=0,"—",SUMIFS(Review!$I$7:$I$600,Review!$B$7:$B$600,$B19,Review!$C$7:$C$600,"Czech")) -> 1.392095 | AA19: =IF(Y19=0,"—",SUMIFS(Review!$J$7:$J$600,Review!$B$7:$B$600,$B19,Review!$C$7:$C$600,"Czech")) -> 4.708558 | AB19: =IF(Y19=0,"—",SUMIFS(Review!$K$7:$K$600,Review!$B$7:$B$600,$B19,Review!$C$7:$C$600,"Czech")) -> 14.41228 | AC19: =IF(Y19=0,"—",IF(Z19<AA19*(1-$C$7),"median (cheapest is an outlier)",IF(Z19*(1-$C$6)<AA19*(1-$C$5),"undercut cheapest","median"))) -> median (cheapest is an outlier) | AD19: =IF(Y19=0,"—",IF(AND(ISNUMBER($D19),$D19*(1+$C$10)>FLOOR(IF(Z19<AA19*(1-$C$7),AA19*(1-$C$5-IF(Y19<3,$C$8,0)),MIN(AA19*(1-$C$5-IF(Y19<3,$C$8,0)),Z19*(1-$C$6-IF(Y19<3,$C$8,0)))),IF(IF(Z19<AA19*(1-$C$7),AA19*(1-$C$5-IF(Y19<3,$C$8,0)),MIN(AA19*(1-$C$5-IF(Y19<3,$C$8,0)),Z19*(1-$C$6-IF(Y19<3,$C$8,0))))<10,$C$9,IF(IF(Z19<AA19*(1-$C$7),AA19*(1-$C$5-IF(Y19<3,$C$8,0)),MIN(AA19*(1-$C$5-IF(Y19<3,$C$8,0)),Z19*(1-$C$6-IF(Y19<3,$C$8,0))))<100,$D$9,$E$9)))),ROUND($D19*(1+$C$10),2),FLOOR(IF(Z19<AA19*(1-$C$7),AA19*(1-$C$5-IF(Y19<3,$C$8,0)),MIN(AA19*(1-$C$5-IF(Y19<3,$C$8,0)),Z19*(1-$C$6-IF(Y19<3,$C$8,0)))),IF(IF(Z19<AA19*(1-$C$7),AA19*(1-$C$5-IF(Y19<3,$C$8,0)),MIN(AA19*(1-$C$5-IF(Y19<3,$C$8,0)),Z19*(1-$C$6-IF(Y19<3,$C$8,0))))<10,$C$9,IF(IF(Z19<AA19*(1-$C$7),AA19*(1-$C$5-IF(Y19<3,$C$8,0)),MIN(AA19*(1-$C$5-IF(Y19<3,$C$8,0)),Z19*(1-$C$6-IF(Y19<3,$C$8,0))))<100,$D$9,$E$9))))) -> 3.5 | AE19: =IF(Y19=0,"—",FLOOR(AD19*Sources!$G$10,1)) -> 85 | AF19: =IF(ISNUMBER($D19),$D19,"n/a") -> 0.55 | AG19: =IF(OR(Y19=0,NOT(ISNUMBER($D19))),"—",AD19/$D19-1) -> 5.3636364 | AH19: =IF(Y19=0,"—",AD19/Z19-1) -> 1.5141962 | AI19: =IF(Y19=0,"—",AD19/AA19-1) -> -0.25667264 | AJ19: =COUNTIFS(Offers!$B$7:$B$3000,$B19,Offers!$C$7:$C$3000,"Slovakia",Offers!$AI$7:$AI$3000,"yes") -> 0 | AK19: =IF(AJ19=0,"—",SUMIFS(Review!$I$7:$I$600,Review!$B$7:$B$600,$B19,Review!$C$7:$C$600,"Slovakia")) -> — | AL19: =IF(AJ19=0,"—",SUMIFS(Review!$J$7:$J$600,Review!$B$7:$B$600,$B19,Review!$C$7:$C$600,"Slovakia")) -> — | AM19: =IF(AJ19=0,"—",SUMIFS(Review!$K$7:$K$600,Review!$B$7:$B$600,$B19,Review!$C$7:$C$600,"Slovakia")) -> — | AN19: =IF(AJ19=0,"—",IF(AK19<AL19*(1-$C$7),"median (cheapest is an outlier)",IF(AK19*(1-$C$6)<AL19*(1-$C$5),"undercut cheapest","median"))) -> — | AO19: =IF(AJ19=0,"—",IF(AND(ISNUMBER($D19),$D19*(1+$C$10)>FLOOR(IF(AK19<AL19*(1-$C$7),AL19*(1-$C$5-IF(AJ19<3,$C$8,0)),MIN(AL19*(1-$C$5-IF(AJ19<3,$C$8,0)),AK19*(1-$C$6-IF(AJ19<3,$C$8,0)))),IF(IF(AK19<AL19*(1-$C$7),AL19*(1-$C$5-IF(AJ19<3,$C$8,0)),MIN(AL19*(1-$C$5-IF(AJ19<3,$C$8,0)),AK19*(1-$C$6-IF(AJ19<3,$C$8,0))))<10,$C$9,IF(IF(AK19<AL19*(1-$C$7),AL19*(1-$C$5-IF(AJ19<3,$C$8,0)),MIN(AL19*(1-$C$5-IF(AJ19<3,$C$8,0)),AK19*(1-$C$6-IF(AJ19<3,$C$8,0))))<100,$D$9,$E$9)))),ROUND($D19*(1+$C$10),2),FLOOR(IF(AK19<AL19*(1-$C$7),AL19*(1-$C$5-IF(AJ19<3,$C$8,0)),MIN(AL19*(1-$C$5-IF(AJ19<3,$C$8,0)),AK19*(1-$C$6-IF(AJ19<3,$C$8,0)))),IF(IF(AK19<AL19*(1-$C$7),AL19*(1-$C$5-IF(AJ19<3,$C$8,0)),MIN(AL19*(1-$C$5-IF(AJ19<3,$C$8,0)),AK19*(1-$C$6-IF(AJ19<3,$C$8,0))))<10,$C$9,IF(IF(AK19<AL19*(1-$C$7),AL19*(1-$C$5-IF(AJ19<3,$C$8,0)),MIN(AL19*(1-$C$5-IF(AJ19<3,$C$8,0)),AK19*(1-$C$6-IF(AJ19<3,$C$8,0))))<100,$D$9,$E$9))))) -> — | AP19: =IF(ISNUMBER($D19),$D19,"n/a") -> 0.55 | AQ19: =IF(OR(AJ19=0,NOT(ISNUMBER($D19))),"—",AO19/$D19-1) -> — | AR19: =IF(AJ19=0,"—",AO19/AK19-1) -> — | AS19: =IF(AJ19=0,"—",AO19/AL19-1) -> — | AT19: =COUNTIFS(Offers!$B$7:$B$3000,$B19,Offers!$C$7:$C$3000,"Romania",Offers!$AI$7:$AI$3000,"yes") -> 0 | AU19: =IF(AT19=0,"—",SUMIFS(Review!$I$7:$I$600,Review!$B$7:$B$600,$B19,Review!$C$7:$C$600,"Romania")) -> — | AV19: =IF(AT19=0,"—",SUMIFS(Review!$J$7:$J$600,Review!$B$7:$B$600,$B19,Review!$C$7:$C$600,"Romania")) -> — | AW19: =IF(AT19=0,"—",SUMIFS(Review!$K$7:$K$600,Review!$B$7:$B$600,$B19,Review!$C$7:$C$600,"Romania")) -> — | AX19: =IF(AT19=0,"—",IF(AU19<AV19*(1-$C$7),"median (cheapest is an outlier)",IF(AU19*(1-$C$6)<AV19*(1-$C$5),"undercut cheapest","median"))) -> — | AY19: =IF(AT19=0,"—",IF(AND(ISNUMBER($D19),$D19*(1+$C$10)>FLOOR(IF(AU19<AV19*(1-$C$7),AV19*(1-$C$5-IF(AT19<3,$C$8,0)),MIN(AV19*(1-$C$5-IF(AT19<3,$C$8,0)),AU19*(1-$C$6-IF(AT19<3,$C$8,0)))),IF(IF(AU19<AV19*(1-$C$7),AV19*(1-$C$5-IF(AT19<3,$C$8,0)),MIN(AV19*(1-$C$5-IF(AT19<3,$C$8,0)),AU19*(1-$C$6-IF(AT19<3,$C$8,0))))<10,$C$9,IF(IF(AU19<AV19*(1-$C$7),AV19*(1-$C$5-IF(AT19<3,$C$8,0)),MIN(AV19*(1-$C$5-IF(AT19<3,$C$8,0)),AU19*(1-$C$6-IF(AT19<3,$C$8,0))))<100,$D$9,$E$9)))),ROUND($D19*(1+$C$10),2),FLOOR(IF(AU19<AV19*(1-$C$7),AV19*(1-$C$5-IF(AT19<3,$C$8,0)),MIN(AV19*(1-$C$5-IF(AT19<3,$C$8,0)),AU19*(1-$C$6-IF(AT19<3,$C$8,0)))),IF(IF(AU19<AV19*(1-$C$7),AV19*(1-$C$5-IF(AT19<3,$C$8,0)),MIN(AV19*(1-$C$5-IF(AT19<3,$C$8,0)),AU19*(1-$C$6-IF(AT19<3,$C$8,0))))<10,$C$9,IF(IF(AU19<AV19*(1-$C$7),AV19*(1-$C$5-IF(AT19<3,$C$8,0)),MIN(AV19*(1-$C$5-IF(AT19<3,$C$8,0)),AU19*(1-$C$6-IF(AT19<3,$C$8,0))))<100,$D$9,$E$9))))) -> — | AZ19: =IF(AT19=0,"—",FLOOR(AY19*Sources!$G$9,0.1)) -> — | BA19: =IF(ISNUMBER($D19),$D19,"n/a") -> 0.55 | BB19: =IF(OR(AT19=0,NOT(ISNUMBER($D19))),"—",AY19/$D19-1) -> — | BC19: =IF(AT19=0,"—",AY19/AU19-1) -> — | BD19: =IF(AT19=0,"—",AY19/AV19-1) -> — | BE19: =COUNTIFS(Offers!$B$7:$B$3000,$B19,Offers!$C$7:$C$3000,"Hungary",Offers!$AI$7:$AI$3000,"yes") -> 0 | BF19: =IF(BE19=0,"—",SUMIFS(Review!$I$7:$I$600,Review!$B$7:$B$600,$B19,Review!$C$7:$C$600,"Hungary")) -> — | BG19: =IF(BE19=0,"—",SUMIFS(Review!$J$7:$J$600,Review!$B$7:$B$600,$B19,Review!$C$7:$C$600,"Hungary")) -> — | BH19: =IF(BE19=0,"—",SUMIFS(Review!$K$7:$K$600,Review!$B$7:$B$600,$B19,Review!$C$7:$C$600,"Hungary")) -> — | BI19: =IF(BE19=0,"—",IF(BF19<BG19*(1-$C$7),"median (cheapest is an outlier)",IF(BF19*(1-$C$6)<BG19*(1-$C$5),"undercut cheapest","median"))) -> — | BJ19: =IF(BE19=0,"—",IF(AND(ISNUMBER($D19),$D19*(1+$C$10)>FLOOR(IF(BF19<BG19*(1-$C$7),BG19*(1-$C$5-IF(BE19<3,$C$8,0)),MIN(BG19*(1-$C$5-IF(BE19<3,$C$8,0)),BF19*(1-$C$6-IF(BE19<3,$C$8,0)))),IF(IF(BF19<BG19*(1-$C$7),BG19*(1-$C$5-IF(BE19<3,$C$8,0)),MIN(BG19*(1-$C$5-IF(BE19<3,$C$8,0)),BF19*(1-$C$6-IF(BE19<3,$C$8,0))))<10,$C$9,IF(IF(BF19<BG19*(1-$C$7),BG19*(1-$C$5-IF(BE19<3,$C$8,0)),MIN(BG19*(1-$C$5-IF(BE19<3,$C$8,0)),BF19*(1-$C$6-IF(BE19<3,$C$8,0))))<100,$D$9,$E$9)))),ROUND($D19*(1+$C$10),2),FLOOR(IF(BF19<BG19*(1-$C$7),BG19*(1-$C$5-IF(BE19<3,$C$8,0)),MIN(BG19*(1-$C$5-IF(BE19<3,$C$8,0)),BF19*(1-$C$6-IF(BE19<3,$C$8,0)))),IF(IF(BF19<BG19*(1-$C$7),BG19*(1-$C$5-IF(BE19<3,$C$8,0)),MIN(BG19*(1-$C$5-IF(BE19<3,$C$8,0)),BF19*(1-$C$6-IF(BE19<3,$C$8,0))))<10,$C$9,IF(IF(BF19<BG19*(1-$C$7),BG19*(1-$C$5-IF(BE19<3,$C$8,0)),MIN(BG19*(1-$C$5-IF(BE19<3,$C$8,0)),BF19*(1-$C$6-IF(BE19<3,$C$8,0))))<100,$D$9,$E$9))))) -> — | BK19: =IF(BE19=0,"—",FLOOR(BJ19*Sources!$G$8,10)) -> — | BL19: =IF(ISNUMBER($D19),$D19,"n/a") -> 0.55 | BM19: =IF(OR(BE19=0,NOT(ISNUMBER($D19))),"—",BJ19/$D19-1) -> — | BN19: =IF(BE19=0,"—",BJ19/BF19-1) -> — | BO19: =IF(BE19=0,"—",BJ19/BG19-1) -> —
B20: Squeeze bottle 1,000 ml, PP, single tip | C20: GPS-1000 | D20: 0.66 | E20: =COUNTIFS(Offers!$B$7:$B$3000,$B20,Offers!$C$7:$C$3000,"Austria",Offers!$AI$7:$AI$3000,"yes") -> 6 | F20: =IF(E20=0,"—",SUMIFS(Review!$I$7:$I$600,Review!$B$7:$B$600,$B20,Review!$C$7:$C$600,"Austria")) -> 1.95 | G20: =IF(E20=0,"—",SUMIFS(Review!$J$7:$J$600,Review!$B$7:$B$600,$B20,Review!$C$7:$C$600,"Austria")) -> 2.96 | H20: =IF(E20=0,"—",SUMIFS(Review!$K$7:$K$600,Review!$B$7:$B$600,$B20,Review!$C$7:$C$600,"Austria")) -> 7.59 | I20: =IF(E20=0,"—",IF(F20<G20*(1-$C$7),"median (cheapest is an outlier)",IF(F20*(1-$C$6)<G20*(1-$C$5),"undercut cheapest","median"))) -> undercut cheapest | J20: =IF(E20=0,"—",IF(AND(ISNUMBER($D20),$D20*(1+$C$10)>FLOOR(IF(F20<G20*(1-$C$7),G20*(1-$C$5-IF(E20<3,$C$8,0)),MIN(G20*(1-$C$5-IF(E20<3,$C$8,0)),F20*(1-$C$6-IF(E20<3,$C$8,0)))),IF(IF(F20<G20*(1-$C$7),G20*(1-$C$5-IF(E20<3,$C$8,0)),MIN(G20*(1-$C$5-IF(E20<3,$C$8,0)),F20*(1-$C$6-IF(E20<3,$C$8,0))))<10,$C$9,IF(IF(F20<G20*(1-$C$7),G20*(1-$C$5-IF(E20<3,$C$8,0)),MIN(G20*(1-$C$5-IF(E20<3,$C$8,0)),F20*(1-$C$6-IF(E20<3,$C$8,0))))<100,$D$9,$E$9)))),ROUND($D20*(1+$C$10),2),FLOOR(IF(F20<G20*(1-$C$7),G20*(1-$C$5-IF(E20<3,$C$8,0)),MIN(G20*(1-$C$5-IF(E20<3,$C$8,0)),F20*(1-$C$6-IF(E20<3,$C$8,0)))),IF(IF(F20<G20*(1-$C$7),G20*(1-$C$5-IF(E20<3,$C$8,0)),MIN(G20*(1-$C$5-IF(E20<3,$C$8,0)),F20*(1-$C$6-IF(E20<3,$C$8,0))))<10,$C$9,IF(IF(F20<G20*(1-$C$7),G20*(1-$C$5-IF(E20<3,$C$8,0)),MIN(G20*(1-$C$5-IF(E20<3,$C$8,0)),F20*(1-$C$6-IF(E20<3,$C$8,0))))<100,$D$9,$E$9))))) -> 1.85 | K20: =IF(ISNUMBER($D20),$D20,"n/a") -> 0.66 | L20: =IF(OR(E20=0,NOT(ISNUMBER($D20))),"—",J20/$D20-1) -> 1.8030303 | M20: =IF(E20=0,"—",J20/F20-1) -> -0.051282051 | N20: =IF(E20=0,"—",J20/G20-1) -> -0.375 | O20: =COUNTIFS(Offers!$B$7:$B$3000,$B20,Offers!$C$7:$C$3000,"Germany",Offers!$AI$7:$AI$3000,"yes") -> 8 | P20: =IF(O20=0,"—",SUMIFS(Review!$I$7:$I$600,Review!$B$7:$B$600,$B20,Review!$C$7:$C$600,"Germany")) -> 1.52 | Q20: =IF(O20=0,"—",SUMIFS(Review!$J$7:$J$600,Review!$B$7:$B$600,$B20,Review!$C$7:$C$600,"Germany")) -> 1.97 | R20: =IF(O20=0,"—",SUMIFS(Review!$K$7:$K$600,Review!$B$7:$B$600,$B20,Review!$C$7:$C$600,"Germany")) -> 5.33 | S20: =IF(O20=0,"—",IF(P20<Q20*(1-$C$7),"median (cheapest is an outlier)",IF(P20*(1-$C$6)<Q20*(1-$C$5),"undercut cheapest","median"))) -> undercut cheapest | T20: =IF(O20=0,"—",IF(AND(ISNUMBER($D20),$D20*(1+$C$10)>FLOOR(IF(P20<Q20*(1-$C$7),Q20*(1-$C$5-IF(O20<3,$C$8,0)),MIN(Q20*(1-$C$5-IF(O20<3,$C$8,0)),P20*(1-$C$6-IF(O20<3,$C$8,0)))),IF(IF(P20<Q20*(1-$C$7),Q20*(1-$C$5-IF(O20<3,$C$8,0)),MIN(Q20*(1-$C$5-IF(O20<3,$C$8,0)),P20*(1-$C$6-IF(O20<3,$C$8,0))))<10,$C$9,IF(IF(P20<Q20*(1-$C$7),Q20*(1-$C$5-IF(O20<3,$C$8,0)),MIN(Q20*(1-$C$5-IF(O20<3,$C$8,0)),P20*(1-$C$6-IF(O20<3,$C$8,0))))<100,$D$9,$E$9)))),ROUND($D20*(1+$C$10),2),FLOOR(IF(P20<Q20*(1-$C$7),Q20*(1-$C$5-IF(O20<3,$C$8,0)),MIN(Q20*(1-$C$5-IF(O20<3,$C$8,0)),P20*(1-$C$6-IF(O20<3,$C$8,0)))),IF(IF(P20<Q20*(1-$C$7),Q20*(1-$C$5-IF(O20<3,$C$8,0)),MIN(Q20*(1-$C$5-IF(O20<3,$C$8,0)),P20*(1-$C$6-IF(O20<3,$C$8,0))))<10,$C$9,IF(IF(P20<Q20*(1-$C$7),Q20*(1-$C$5-IF(O20<3,$C$8,0)),MIN(Q20*(1-$C$5-IF(O20<3,$C$8,0)),P20*(1-$C$6-IF(O20<3,$C$8,0))))<100,$D$9,$E$9))))) -> 1.4 | U20: =IF(ISNUMBER($D20),$D20,"n/a") -> 0.66 | V20: =IF(OR(O20=0,NOT(ISNUMBER($D20))),"—",T20/$D20-1) -> 1.1212121 | W20: =IF(O20=0,"—",T20/P20-1) -> -0.078947368 | X20: =IF(O20=0,"—",T20/Q20-1) -> -0.2893401 | Y20: =COUNTIFS(Offers!$B$7:$B$3000,$B20,Offers!$C$7:$C$3000,"Czech",Offers!$AI$7:$AI$3000,"yes") -> 5 | Z20: =IF(Y20=0,"—",SUMIFS(Review!$I$7:$I$600,Review!$B$7:$B$600,$B20,Review!$C$7:$C$600,"Czech")) -> 1.624248 | AA20: =IF(Y20=0,"—",SUMIFS(Review!$J$7:$J$600,Review!$B$7:$B$600,$B20,Review!$C$7:$C$600,"Czech")) -> 3.80779 | AB20: =IF(Y20=0,"—",SUMIFS(Review!$K$7:$K$600,Review!$B$7:$B$600,$B20,Review!$C$7:$C$600,"Czech")) -> 15.091951 | AC20: =IF(Y20=0,"—",IF(Z20<AA20*(1-$C$7),"median (cheapest is an outlier)",IF(Z20*(1-$C$6)<AA20*(1-$C$5),"undercut cheapest","median"))) -> median (cheapest is an outlier) | AD20: =IF(Y20=0,"—",IF(AND(ISNUMBER($D20),$D20*(1+$C$10)>FLOOR(IF(Z20<AA20*(1-$C$7),AA20*(1-$C$5-IF(Y20<3,$C$8,0)),MIN(AA20*(1-$C$5-IF(Y20<3,$C$8,0)),Z20*(1-$C$6-IF(Y20<3,$C$8,0)))),IF(IF(Z20<AA20*(1-$C$7),AA20*(1-$C$5-IF(Y20<3,$C$8,0)),MIN(AA20*(1-$C$5-IF(Y20<3,$C$8,0)),Z20*(1-$C$6-IF(Y20<3,$C$8,0))))<10,$C$9,IF(IF(Z20<AA20*(1-$C$7),AA20*(1-$C$5-IF(Y20<3,$C$8,0)),MIN(AA20*(1-$C$5-IF(Y20<3,$C$8,0)),Z20*(1-$C$6-IF(Y20<3,$C$8,0))))<100,$D$9,$E$9)))),ROUND($D20*(1+$C$10),2),FLOOR(IF(Z20<AA20*(1-$C$7),AA20*(1-$C$5-IF(Y20<3,$C$8,0)),MIN(AA20*(1-$C$5-IF(Y20<3,$C$8,0)),Z20*(1-$C$6-IF(Y20<3,$C$8,0)))),IF(IF(Z20<AA20*(1-$C$7),AA20*(1-$C$5-IF(Y20<3,$C$8,0)),MIN(AA20*(1-$C$5-IF(Y20<3,$C$8,0)),Z20*(1-$C$6-IF(Y20<3,$C$8,0))))<10,$C$9,IF(IF(Z20<AA20*(1-$C$7),AA20*(1-$C$5-IF(Y20<3,$C$8,0)),MIN(AA20*(1-$C$5-IF(Y20<3,$C$8,0)),Z20*(1-$C$6-IF(Y20<3,$C$8,0))))<100,$D$9,$E$9))))) -> 2.85 | AE20: =IF(Y20=0,"—",FLOOR(AD20*Sources!$G$10,1)) -> 69 | AF20: =IF(ISNUMBER($D20),$D20,"n/a") -> 0.66 | AG20: =IF(OR(Y20=0,NOT(ISNUMBER($D20))),"—",AD20/$D20-1) -> 3.3181818 | AH20: =IF(Y20=0,"—",AD20/Z20-1) -> 0.75465816 | AI20: =IF(Y20=0,"—",AD20/AA20-1) -> -0.25153435 | AJ20: =COUNTIFS(Offers!$B$7:$B$3000,$B20,Offers!$C$7:$C$3000,"Slovakia",Offers!$AI$7:$AI$3000,"yes") -> 1 | AK20: =IF(AJ20=0,"—",SUMIFS(Review!$I$7:$I$600,Review!$B$7:$B$600,$B20,Review!$C$7:$C$600,"Slovakia")) -> 1.28 | AL20: =IF(AJ20=0,"—",SUMIFS(Review!$J$7:$J$600,Review!$B$7:$B$600,$B20,Review!$C$7:$C$600,"Slovakia")) -> 1.28 | AM20: =IF(AJ20=0,"—",SUMIFS(Review!$K$7:$K$600,Review!$B$7:$B$600,$B20,Review!$C$7:$C$600,"Slovakia")) -> 1.28 | AN20: =IF(AJ20=0,"—",IF(AK20<AL20*(1-$C$7),"median (cheapest is an outlier)",IF(AK20*(1-$C$6)<AL20*(1-$C$5),"undercut cheapest","median"))) -> median | AO20: =IF(AJ20=0,"—",IF(AND(ISNUMBER($D20),$D20*(1+$C$10)>FLOOR(IF(AK20<AL20*(1-$C$7),AL20*(1-$C$5-IF(AJ20<3,$C$8,0)),MIN(AL20*(1-$C$5-IF(AJ20<3,$C$8,0)),AK20*(1-$C$6-IF(AJ20<3,$C$8,0)))),IF(IF(AK20<AL20*(1-$C$7),AL20*(1-$C$5-IF(AJ20<3,$C$8,0)),MIN(AL20*(1-$C$5-IF(AJ20<3,$C$8,0)),AK20*(1-$C$6-IF(AJ20<3,$C$8,0))))<10,$C$9,IF(IF(AK20<AL20*(1-$C$7),AL20*(1-$C$5-IF(AJ20<3,$C$8,0)),MIN(AL20*(1-$C$5-IF(AJ20<3,$C$8,0)),AK20*(1-$C$6-IF(AJ20<3,$C$8,0))))<100,$D$9,$E$9)))),ROUND($D20*(1+$C$10),2),FLOOR(IF(AK20<AL20*(1-$C$7),AL20*(1-$C$5-IF(AJ20<3,$C$8,0)),MIN(AL20*(1-$C$5-IF(AJ20<3,$C$8,0)),AK20*(1-$C$6-IF(AJ20<3,$C$8,0)))),IF(IF(AK20<AL20*(1-$C$7),AL20*(1-$C$5-IF(AJ20<3,$C$8,0)),MIN(AL20*(1-$C$5-IF(AJ20<3,$C$8,0)),AK20*(1-$C$6-IF(AJ20<3,$C$8,0))))<10,$C$9,IF(IF(AK20<AL20*(1-$C$7),AL20*(1-$C$5-IF(AJ20<3,$C$8,0)),MIN(AL20*(1-$C$5-IF(AJ20<3,$C$8,0)),AK20*(1-$C$6-IF(AJ20<3,$C$8,0))))<100,$D$9,$E$9))))) -> 0.85 | AP20: =IF(ISNUMBER($D20),$D20,"n/a") -> 0.66 | AQ20: =IF(OR(AJ20=0,NOT(ISNUMBER($D20))),"—",AO20/$D20-1) -> 0.28787879 | AR20: =IF(AJ20=0,"—",AO20/AK20-1) -> -0.3359375 | AS20: =IF(AJ20=0,"—",AO20/AL20-1) -> -0.3359375 | AT20: =COUNTIFS(Offers!$B$7:$B$3000,$B20,Offers!$C$7:$C$3000,"Romania",Offers!$AI$7:$AI$3000,"yes") -> 0 | AU20: =IF(AT20=0,"—",SUMIFS(Review!$I$7:$I$600,Review!$B$7:$B$600,$B20,Review!$C$7:$C$600,"Romania")) -> — | AV20: =IF(AT20=0,"—",SUMIFS(Review!$J$7:$J$600,Review!$B$7:$B$600,$B20,Review!$C$7:$C$600,"Romania")) -> — | AW20: =IF(AT20=0,"—",SUMIFS(Review!$K$7:$K$600,Review!$B$7:$B$600,$B20,Review!$C$7:$C$600,"Romania")) -> — | AX20: =IF(AT20=0,"—",IF(AU20<AV20*(1-$C$7),"median (cheapest is an outlier)",IF(AU20*(1-$C$6)<AV20*(1-$C$5),"undercut cheapest","median"))) -> — | AY20: =IF(AT20=0,"—",IF(AND(ISNUMBER($D20),$D20*(1+$C$10)>FLOOR(IF(AU20<AV20*(1-$C$7),AV20*(1-$C$5-IF(AT20<3,$C$8,0)),MIN(AV20*(1-$C$5-IF(AT20<3,$C$8,0)),AU20*(1-$C$6-IF(AT20<3,$C$8,0)))),IF(IF(AU20<AV20*(1-$C$7),AV20*(1-$C$5-IF(AT20<3,$C$8,0)),MIN(AV20*(1-$C$5-IF(AT20<3,$C$8,0)),AU20*(1-$C$6-IF(AT20<3,$C$8,0))))<10,$C$9,IF(IF(AU20<AV20*(1-$C$7),AV20*(1-$C$5-IF(AT20<3,$C$8,0)),MIN(AV20*(1-$C$5-IF(AT20<3,$C$8,0)),AU20*(1-$C$6-IF(AT20<3,$C$8,0))))<100,$D$9,$E$9)))),ROUND($D20*(1+$C$10),2),FLOOR(IF(AU20<AV20*(1-$C$7),AV20*(1-$C$5-IF(AT20<3,$C$8,0)),MIN(AV20*(1-$C$5-IF(AT20<3,$C$8,0)),AU20*(1-$C$6-IF(AT20<3,$C$8,0)))),IF(IF(AU20<AV20*(1-$C$7),AV20*(1-$C$5-IF(AT20<3,$C$8,0)),MIN(AV20*(1-$C$5-IF(AT20<3,$C$8,0)),AU20*(1-$C$6-IF(AT20<3,$C$8,0))))<10,$C$9,IF(IF(AU20<AV20*(1-$C$7),AV20*(1-$C$5-IF(AT20<3,$C$8,0)),MIN(AV20*(1-$C$5-IF(AT20<3,$C$8,0)),AU20*(1-$C$6-IF(AT20<3,$C$8,0))))<100,$D$9,$E$9))))) -> — | AZ20: =IF(AT20=0,"—",FLOOR(AY20*Sources!$G$9,0.1)) -> — | BA20: =IF(ISNUMBER($D20),$D20,"n/a") -> 0.66 | BB20: =IF(OR(AT20=0,NOT(ISNUMBER($D20))),"—",AY20/$D20-1) -> — | BC20: =IF(AT20=0,"—",AY20/AU20-1) -> — | BD20: =IF(AT20=0,"—",AY20/AV20-1) -> — | BE20: =COUNTIFS(Offers!$B$7:$B$3000,$B20,Offers!$C$7:$C$3000,"Hungary",Offers!$AI$7:$AI$3000,"yes") -> 0 | BF20: =IF(BE20=0,"—",SUMIFS(Review!$I$7:$I$600,Review!$B$7:$B$600,$B20,Review!$C$7:$C$600,"Hungary")) -> — | BG20: =IF(BE20=0,"—",SUMIFS(Review!$J$7:$J$600,Review!$B$7:$B$600,$B20,Review!$C$7:$C$600,"Hungary")) -> — | BH20: =IF(BE20=0,"—",SUMIFS(Review!$K$7:$K$600,Review!$B$7:$B$600,$B20,Review!$C$7:$C$600,"Hungary")) -> — | BI20: =IF(BE20=0,"—",IF(BF20<BG20*(1-$C$7),"median (cheapest is an outlier)",IF(BF20*(1-$C$6)<BG20*(1-$C$5),"undercut cheapest","median"))) -> — | BJ20: =IF(BE20=0,"—",IF(AND(ISNUMBER($D20),$D20*(1+$C$10)>FLOOR(IF(BF20<BG20*(1-$C$7),BG20*(1-$C$5-IF(BE20<3,$C$8,0)),MIN(BG20*(1-$C$5-IF(BE20<3,$C$8,0)),BF20*(1-$C$6-IF(BE20<3,$C$8,0)))),IF(IF(BF20<BG20*(1-$C$7),BG20*(1-$C$5-IF(BE20<3,$C$8,0)),MIN(BG20*(1-$C$5-IF(BE20<3,$C$8,0)),BF20*(1-$C$6-IF(BE20<3,$C$8,0))))<10,$C$9,IF(IF(BF20<BG20*(1-$C$7),BG20*(1-$C$5-IF(BE20<3,$C$8,0)),MIN(BG20*(1-$C$5-IF(BE20<3,$C$8,0)),BF20*(1-$C$6-IF(BE20<3,$C$8,0))))<100,$D$9,$E$9)))),ROUND($D20*(1+$C$10),2),FLOOR(IF(BF20<BG20*(1-$C$7),BG20*(1-$C$5-IF(BE20<3,$C$8,0)),MIN(BG20*(1-$C$5-IF(BE20<3,$C$8,0)),BF20*(1-$C$6-IF(BE20<3,$C$8,0)))),IF(IF(BF20<BG20*(1-$C$7),BG20*(1-$C$5-IF(BE20<3,$C$8,0)),MIN(BG20*(1-$C$5-IF(BE20<3,$C$8,0)),BF20*(1-$C$6-IF(BE20<3,$C$8,0))))<10,$C$9,IF(IF(BF20<BG20*(1-$C$7),BG20*(1-$C$5-IF(BE20<3,$C$8,0)),MIN(BG20*(1-$C$5-IF(BE20<3,$C$8,0)),BF20*(1-$C$6-IF(BE20<3,$C$8,0))))<100,$D$9,$E$9))))) -> — | BK20: =IF(BE20=0,"—",FLOOR(BJ20*Sources!$G$8,10)) -> — | BL20: =IF(ISNUMBER($D20),$D20,"n/a") -> 0.66 | BM20: =IF(OR(BE20=0,NOT(ISNUMBER($D20))),"—",BJ20/$D20-1) -> — | BN20: =IF(BE20=0,"—",BJ20/BF20-1) -> — | BO20: =IF(BE20=0,"—",BJ20/BG20-1) -> —
B21: Squeeze bottle 500 ml, triple tip | C21: GBT-500 | E21: =COUNTIFS(Offers!$B$7:$B$3000,$B21,Offers!$C$7:$C$3000,"Austria",Offers!$AI$7:$AI$3000,"yes") -> 0 | F21: =IF(E21=0,"—",SUMIFS(Review!$I$7:$I$600,Review!$B$7:$B$600,$B21,Review!$C$7:$C$600,"Austria")) -> — | G21: =IF(E21=0,"—",SUMIFS(Review!$J$7:$J$600,Review!$B$7:$B$600,$B21,Review!$C$7:$C$600,"Austria")) -> — | H21: =IF(E21=0,"—",SUMIFS(Review!$K$7:$K$600,Review!$B$7:$B$600,$B21,Review!$C$7:$C$600,"Austria")) -> — | I21: =IF(E21=0,"—",IF(F21<G21*(1-$C$7),"median (cheapest is an outlier)",IF(F21*(1-$C$6)<G21*(1-$C$5),"undercut cheapest","median"))) -> — | J21: =IF(E21=0,"—",IF(AND(ISNUMBER($D21),$D21*(1+$C$10)>FLOOR(IF(F21<G21*(1-$C$7),G21*(1-$C$5-IF(E21<3,$C$8,0)),MIN(G21*(1-$C$5-IF(E21<3,$C$8,0)),F21*(1-$C$6-IF(E21<3,$C$8,0)))),IF(IF(F21<G21*(1-$C$7),G21*(1-$C$5-IF(E21<3,$C$8,0)),MIN(G21*(1-$C$5-IF(E21<3,$C$8,0)),F21*(1-$C$6-IF(E21<3,$C$8,0))))<10,$C$9,IF(IF(F21<G21*(1-$C$7),G21*(1-$C$5-IF(E21<3,$C$8,0)),MIN(G21*(1-$C$5-IF(E21<3,$C$8,0)),F21*(1-$C$6-IF(E21<3,$C$8,0))))<100,$D$9,$E$9)))),ROUND($D21*(1+$C$10),2),FLOOR(IF(F21<G21*(1-$C$7),G21*(1-$C$5-IF(E21<3,$C$8,0)),MIN(G21*(1-$C$5-IF(E21<3,$C$8,0)),F21*(1-$C$6-IF(E21<3,$C$8,0)))),IF(IF(F21<G21*(1-$C$7),G21*(1-$C$5-IF(E21<3,$C$8,0)),MIN(G21*(1-$C$5-IF(E21<3,$C$8,0)),F21*(1-$C$6-IF(E21<3,$C$8,0))))<10,$C$9,IF(IF(F21<G21*(1-$C$7),G21*(1-$C$5-IF(E21<3,$C$8,0)),MIN(G21*(1-$C$5-IF(E21<3,$C$8,0)),F21*(1-$C$6-IF(E21<3,$C$8,0))))<100,$D$9,$E$9))))) -> — | K21: =IF(ISNUMBER($D21),$D21,"n/a") -> n/a | L21: =IF(OR(E21=0,NOT(ISNUMBER($D21))),"—",J21/$D21-1) -> — | M21: =IF(E21=0,"—",J21/F21-1) -> — | N21: =IF(E21=0,"—",J21/G21-1) -> — | O21: =COUNTIFS(Offers!$B$7:$B$3000,$B21,Offers!$C$7:$C$3000,"Germany",Offers!$AI$7:$AI$3000,"yes") -> 0 | P21: =IF(O21=0,"—",SUMIFS(Review!$I$7:$I$600,Review!$B$7:$B$600,$B21,Review!$C$7:$C$600,"Germany")) -> — | Q21: =IF(O21=0,"—",SUMIFS(Review!$J$7:$J$600,Review!$B$7:$B$600,$B21,Review!$C$7:$C$600,"Germany")) -> — | R21: =IF(O21=0,"—",SUMIFS(Review!$K$7:$K$600,Review!$B$7:$B$600,$B21,Review!$C$7:$C$600,"Germany")) -> — | S21: =IF(O21=0,"—",IF(P21<Q21*(1-$C$7),"median (cheapest is an outlier)",IF(P21*(1-$C$6)<Q21*(1-$C$5),"undercut cheapest","median"))) -> — | T21: =IF(O21=0,"—",IF(AND(ISNUMBER($D21),$D21*(1+$C$10)>FLOOR(IF(P21<Q21*(1-$C$7),Q21*(1-$C$5-IF(O21<3,$C$8,0)),MIN(Q21*(1-$C$5-IF(O21<3,$C$8,0)),P21*(1-$C$6-IF(O21<3,$C$8,0)))),IF(IF(P21<Q21*(1-$C$7),Q21*(1-$C$5-IF(O21<3,$C$8,0)),MIN(Q21*(1-$C$5-IF(O21<3,$C$8,0)),P21*(1-$C$6-IF(O21<3,$C$8,0))))<10,$C$9,IF(IF(P21<Q21*(1-$C$7),Q21*(1-$C$5-IF(O21<3,$C$8,0)),MIN(Q21*(1-$C$5-IF(O21<3,$C$8,0)),P21*(1-$C$6-IF(O21<3,$C$8,0))))<100,$D$9,$E$9)))),ROUND($D21*(1+$C$10),2),FLOOR(IF(P21<Q21*(1-$C$7),Q21*(1-$C$5-IF(O21<3,$C$8,0)),MIN(Q21*(1-$C$5-IF(O21<3,$C$8,0)),P21*(1-$C$6-IF(O21<3,$C$8,0)))),IF(IF(P21<Q21*(1-$C$7),Q21*(1-$C$5-IF(O21<3,$C$8,0)),MIN(Q21*(1-$C$5-IF(O21<3,$C$8,0)),P21*(1-$C$6-IF(O21<3,$C$8,0))))<10,$C$9,IF(IF(P21<Q21*(1-$C$7),Q21*(1-$C$5-IF(O21<3,$C$8,0)),MIN(Q21*(1-$C$5-IF(O21<3,$C$8,0)),P21*(1-$C$6-IF(O21<3,$C$8,0))))<100,$D$9,$E$9))))) -> — | U21: =IF(ISNUMBER($D21),$D21,"n/a") -> n/a | V21: =IF(OR(O21=0,NOT(ISNUMBER($D21))),"—",T21/$D21-1) -> — | W21: =IF(O21=0,"—",T21/P21-1) -> — | X21: =IF(O21=0,"—",T21/Q21-1) -> — | Y21: =COUNTIFS(Offers!$B$7:$B$3000,$B21,Offers!$C$7:$C$3000,"Czech",Offers!$AI$7:$AI$3000,"yes") -> 0 | Z21: =IF(Y21=0,"—",SUMIFS(Review!$I$7:$I$600,Review!$B$7:$B$600,$B21,Review!$C$7:$C$600,"Czech")) -> — | AA21: =IF(Y21=0,"—",SUMIFS(Review!$J$7:$J$600,Review!$B$7:$B$600,$B21,Review!$C$7:$C$600,"Czech")) -> — | AB21: =IF(Y21=0,"—",SUMIFS(Review!$K$7:$K$600,Review!$B$7:$B$600,$B21,Review!$C$7:$C$600,"Czech")) -> — | AC21: =IF(Y21=0,"—",IF(Z21<AA21*(1-$C$7),"median (cheapest is an outlier)",IF(Z21*(1-$C$6)<AA21*(1-$C$5),"undercut cheapest","median"))) -> — | AD21: =IF(Y21=0,"—",IF(AND(ISNUMBER($D21),$D21*(1+$C$10)>FLOOR(IF(Z21<AA21*(1-$C$7),AA21*(1-$C$5-IF(Y21<3,$C$8,0)),MIN(AA21*(1-$C$5-IF(Y21<3,$C$8,0)),Z21*(1-$C$6-IF(Y21<3,$C$8,0)))),IF(IF(Z21<AA21*(1-$C$7),AA21*(1-$C$5-IF(Y21<3,$C$8,0)),MIN(AA21*(1-$C$5-IF(Y21<3,$C$8,0)),Z21*(1-$C$6-IF(Y21<3,$C$8,0))))<10,$C$9,IF(IF(Z21<AA21*(1-$C$7),AA21*(1-$C$5-IF(Y21<3,$C$8,0)),MIN(AA21*(1-$C$5-IF(Y21<3,$C$8,0)),Z21*(1-$C$6-IF(Y21<3,$C$8,0))))<100,$D$9,$E$9)))),ROUND($D21*(1+$C$10),2),FLOOR(IF(Z21<AA21*(1-$C$7),AA21*(1-$C$5-IF(Y21<3,$C$8,0)),MIN(AA21*(1-$C$5-IF(Y21<3,$C$8,0)),Z21*(1-$C$6-IF(Y21<3,$C$8,0)))),IF(IF(Z21<AA21*(1-$C$7),AA21*(1-$C$5-IF(Y21<3,$C$8,0)),MIN(AA21*(1-$C$5-IF(Y21<3,$C$8,0)),Z21*(1-$C$6-IF(Y21<3,$C$8,0))))<10,$C$9,IF(IF(Z21<AA21*(1-$C$7),AA21*(1-$C$5-IF(Y21<3,$C$8,0)),MIN(AA21*(1-$C$5-IF(Y21<3,$C$8,0)),Z21*(1-$C$6-IF(Y21<3,$C$8,0))))<100,$D$9,$E$9))))) -> — | AE21: =IF(Y21=0,"—",FLOOR(AD21*Sources!$G$10,1)) -> — | AF21: =IF(ISNUMBER($D21),$D21,"n/a") -> n/a | AG21: =IF(OR(Y21=0,NOT(ISNUMBER($D21))),"—",AD21/$D21-1) -> — | AH21: =IF(Y21=0,"—",AD21/Z21-1) -> — | AI21: =IF(Y21=0,"—",AD21/AA21-1) -> — | AJ21: =COUNTIFS(Offers!$B$7:$B$3000,$B21,Offers!$C$7:$C$3000,"Slovakia",Offers!$AI$7:$AI$3000,"yes") -> 0 | AK21: =IF(AJ21=0,"—",SUMIFS(Review!$I$7:$I$600,Review!$B$7:$B$600,$B21,Review!$C$7:$C$600,"Slovakia")) -> — | AL21: =IF(AJ21=0,"—",SUMIFS(Review!$J$7:$J$600,Review!$B$7:$B$600,$B21,Review!$C$7:$C$600,"Slovakia")) -> — | AM21: =IF(AJ21=0,"—",SUMIFS(Review!$K$7:$K$600,Review!$B$7:$B$600,$B21,Review!$C$7:$C$600,"Slovakia")) -> — | AN21: =IF(AJ21=0,"—",IF(AK21<AL21*(1-$C$7),"median (cheapest is an outlier)",IF(AK21*(1-$C$6)<AL21*(1-$C$5),"undercut cheapest","median"))) -> — | AO21: =IF(AJ21=0,"—",IF(AND(ISNUMBER($D21),$D21*(1+$C$10)>FLOOR(IF(AK21<AL21*(1-$C$7),AL21*(1-$C$5-IF(AJ21<3,$C$8,0)),MIN(AL21*(1-$C$5-IF(AJ21<3,$C$8,0)),AK21*(1-$C$6-IF(AJ21<3,$C$8,0)))),IF(IF(AK21<AL21*(1-$C$7),AL21*(1-$C$5-IF(AJ21<3,$C$8,0)),MIN(AL21*(1-$C$5-IF(AJ21<3,$C$8,0)),AK21*(1-$C$6-IF(AJ21<3,$C$8,0))))<10,$C$9,IF(IF(AK21<AL21*(1-$C$7),AL21*(1-$C$5-IF(AJ21<3,$C$8,0)),MIN(AL21*(1-$C$5-IF(AJ21<3,$C$8,0)),AK21*(1-$C$6-IF(AJ21<3,$C$8,0))))<100,$D$9,$E$9)))),ROUND($D21*(1+$C$10),2),FLOOR(IF(AK21<AL21*(1-$C$7),AL21*(1-$C$5-IF(AJ21<3,$C$8,0)),MIN(AL21*(1-$C$5-IF(AJ21<3,$C$8,0)),AK21*(1-$C$6-IF(AJ21<3,$C$8,0)))),IF(IF(AK21<AL21*(1-$C$7),AL21*(1-$C$5-IF(AJ21<3,$C$8,0)),MIN(AL21*(1-$C$5-IF(AJ21<3,$C$8,0)),AK21*(1-$C$6-IF(AJ21<3,$C$8,0))))<10,$C$9,IF(IF(AK21<AL21*(1-$C$7),AL21*(1-$C$5-IF(AJ21<3,$C$8,0)),MIN(AL21*(1-$C$5-IF(AJ21<3,$C$8,0)),AK21*(1-$C$6-IF(AJ21<3,$C$8,0))))<100,$D$9,$E$9))))) -> — | AP21: =IF(ISNUMBER($D21),$D21,"n/a") -> n/a | AQ21: =IF(OR(AJ21=0,NOT(ISNUMBER($D21))),"—",AO21/$D21-1) -> — | AR21: =IF(AJ21=0,"—",AO21/AK21-1) -> — | AS21: =IF(AJ21=0,"—",AO21/AL21-1) -> — | AT21: =COUNTIFS(Offers!$B$7:$B$3000,$B21,Offers!$C$7:$C$3000,"Romania",Offers!$AI$7:$AI$3000,"yes") -> 0 | AU21: =IF(AT21=0,"—",SUMIFS(Review!$I$7:$I$600,Review!$B$7:$B$600,$B21,Review!$C$7:$C$600,"Romania")) -> — | AV21: =IF(AT21=0,"—",SUMIFS(Review!$J$7:$J$600,Review!$B$7:$B$600,$B21,Review!$C$7:$C$600,"Romania")) -> — | AW21: =IF(AT21=0,"—",SUMIFS(Review!$K$7:$K$600,Review!$B$7:$B$600,$B21,Review!$C$7:$C$600,"Romania")) -> — | AX21: =IF(AT21=0,"—",IF(AU21<AV21*(1-$C$7),"median (cheapest is an outlier)",IF(AU21*(1-$C$6)<AV21*(1-$C$5),"undercut cheapest","median"))) -> — | AY21: =IF(AT21=0,"—",IF(AND(ISNUMBER($D21),$D21*(1+$C$10)>FLOOR(IF(AU21<AV21*(1-$C$7),AV21*(1-$C$5-IF(AT21<3,$C$8,0)),MIN(AV21*(1-$C$5-IF(AT21<3,$C$8,0)),AU21*(1-$C$6-IF(AT21<3,$C$8,0)))),IF(IF(AU21<AV21*(1-$C$7),AV21*(1-$C$5-IF(AT21<3,$C$8,0)),MIN(AV21*(1-$C$5-IF(AT21<3,$C$8,0)),AU21*(1-$C$6-IF(AT21<3,$C$8,0))))<10,$C$9,IF(IF(AU21<AV21*(1-$C$7),AV21*(1-$C$5-IF(AT21<3,$C$8,0)),MIN(AV21*(1-$C$5-IF(AT21<3,$C$8,0)),AU21*(1-$C$6-IF(AT21<3,$C$8,0))))<100,$D$9,$E$9)))),ROUND($D21*(1+$C$10),2),FLOOR(IF(AU21<AV21*(1-$C$7),AV21*(1-$C$5-IF(AT21<3,$C$8,0)),MIN(AV21*(1-$C$5-IF(AT21<3,$C$8,0)),AU21*(1-$C$6-IF(AT21<3,$C$8,0)))),IF(IF(AU21<AV21*(1-$C$7),AV21*(1-$C$5-IF(AT21<3,$C$8,0)),MIN(AV21*(1-$C$5-IF(AT21<3,$C$8,0)),AU21*(1-$C$6-IF(AT21<3,$C$8,0))))<10,$C$9,IF(IF(AU21<AV21*(1-$C$7),AV21*(1-$C$5-IF(AT21<3,$C$8,0)),MIN(AV21*(1-$C$5-IF(AT21<3,$C$8,0)),AU21*(1-$C$6-IF(AT21<3,$C$8,0))))<100,$D$9,$E$9))))) -> — | AZ21: =IF(AT21=0,"—",FLOOR(AY21*Sources!$G$9,0.1)) -> — | BA21: =IF(ISNUMBER($D21),$D21,"n/a") -> n/a | BB21: =IF(OR(AT21=0,NOT(ISNUMBER($D21))),"—",AY21/$D21-1) -> — | BC21: =IF(AT21=0,"—",AY21/AU21-1) -> — | BD21: =IF(AT21=0,"—",AY21/AV21-1) -> — | BE21: =COUNTIFS(Offers!$B$7:$B$3000,$B21,Offers!$C$7:$C$3000,"Hungary",Offers!$AI$7:$AI$3000,"yes") -> 0 | BF21: =IF(BE21=0,"—",SUMIFS(Review!$I$7:$I$600,Review!$B$7:$B$600,$B21,Review!$C$7:$C$600,"Hungary")) -> — | BG21: =IF(BE21=0,"—",SUMIFS(Review!$J$7:$J$600,Review!$B$7:$B$600,$B21,Review!$C$7:$C$600,"Hungary")) -> — | BH21: =IF(BE21=0,"—",SUMIFS(Review!$K$7:$K$600,Review!$B$7:$B$600,$B21,Review!$C$7:$C$600,"Hungary")) -> — | BI21: =IF(BE21=0,"—",IF(BF21<BG21*(1-$C$7),"median (cheapest is an outlier)",IF(BF21*(1-$C$6)<BG21*(1-$C$5),"undercut cheapest","median"))) -> — | BJ21: =IF(BE21=0,"—",IF(AND(ISNUMBER($D21),$D21*(1+$C$10)>FLOOR(IF(BF21<BG21*(1-$C$7),BG21*(1-$C$5-IF(BE21<3,$C$8,0)),MIN(BG21*(1-$C$5-IF(BE21<3,$C$8,0)),BF21*(1-$C$6-IF(BE21<3,$C$8,0)))),IF(IF(BF21<BG21*(1-$C$7),BG21*(1-$C$5-IF(BE21<3,$C$8,0)),MIN(BG21*(1-$C$5-IF(BE21<3,$C$8,0)),BF21*(1-$C$6-IF(BE21<3,$C$8,0))))<10,$C$9,IF(IF(BF21<BG21*(1-$C$7),BG21*(1-$C$5-IF(BE21<3,$C$8,0)),MIN(BG21*(1-$C$5-IF(BE21<3,$C$8,0)),BF21*(1-$C$6-IF(BE21<3,$C$8,0))))<100,$D$9,$E$9)))),ROUND($D21*(1+$C$10),2),FLOOR(IF(BF21<BG21*(1-$C$7),BG21*(1-$C$5-IF(BE21<3,$C$8,0)),MIN(BG21*(1-$C$5-IF(BE21<3,$C$8,0)),BF21*(1-$C$6-IF(BE21<3,$C$8,0)))),IF(IF(BF21<BG21*(1-$C$7),BG21*(1-$C$5-IF(BE21<3,$C$8,0)),MIN(BG21*(1-$C$5-IF(BE21<3,$C$8,0)),BF21*(1-$C$6-IF(BE21<3,$C$8,0))))<10,$C$9,IF(IF(BF21<BG21*(1-$C$7),BG21*(1-$C$5-IF(BE21<3,$C$8,0)),MIN(BG21*(1-$C$5-IF(BE21<3,$C$8,0)),BF21*(1-$C$6-IF(BE21<3,$C$8,0))))<100,$D$9,$E$9))))) -> — | BK21: =IF(BE21=0,"—",FLOOR(BJ21*Sources!$G$8,10)) -> — | BL21: =IF(ISNUMBER($D21),$D21,"n/a") -> n/a | BM21: =IF(OR(BE21=0,NOT(ISNUMBER($D21))),"—",BJ21/$D21-1) -> — | BN21: =IF(BE21=0,"—",BJ21/BF21-1) -> — | BO21: =IF(BE21=0,"—",BJ21/BG21-1) -> —
B22: Sauce pump dispenser with stand | C22: GDK-01 | D22: 8.25 | E22: =COUNTIFS(Offers!$B$7:$B$3000,$B22,Offers!$C$7:$C$3000,"Austria",Offers!$AI$7:$AI$3000,"yes") -> 7 | F22: =IF(E22=0,"—",SUMIFS(Review!$I$7:$I$600,Review!$B$7:$B$600,$B22,Review!$C$7:$C$600,"Austria")) -> 19.76 | G22: =IF(E22=0,"—",SUMIFS(Review!$J$7:$J$600,Review!$B$7:$B$600,$B22,Review!$C$7:$C$600,"Austria")) -> 30.5 | H22: =IF(E22=0,"—",SUMIFS(Review!$K$7:$K$600,Review!$B$7:$B$600,$B22,Review!$C$7:$C$600,"Austria")) -> 93.66 | I22: =IF(E22=0,"—",IF(F22<G22*(1-$C$7),"median (cheapest is an outlier)",IF(F22*(1-$C$6)<G22*(1-$C$5),"undercut cheapest","median"))) -> median (cheapest is an outlier) | J22: =IF(E22=0,"—",IF(AND(ISNUMBER($D22),$D22*(1+$C$10)>FLOOR(IF(F22<G22*(1-$C$7),G22*(1-$C$5-IF(E22<3,$C$8,0)),MIN(G22*(1-$C$5-IF(E22<3,$C$8,0)),F22*(1-$C$6-IF(E22<3,$C$8,0)))),IF(IF(F22<G22*(1-$C$7),G22*(1-$C$5-IF(E22<3,$C$8,0)),MIN(G22*(1-$C$5-IF(E22<3,$C$8,0)),F22*(1-$C$6-IF(E22<3,$C$8,0))))<10,$C$9,IF(IF(F22<G22*(1-$C$7),G22*(1-$C$5-IF(E22<3,$C$8,0)),MIN(G22*(1-$C$5-IF(E22<3,$C$8,0)),F22*(1-$C$6-IF(E22<3,$C$8,0))))<100,$D$9,$E$9)))),ROUND($D22*(1+$C$10),2),FLOOR(IF(F22<G22*(1-$C$7),G22*(1-$C$5-IF(E22<3,$C$8,0)),MIN(G22*(1-$C$5-IF(E22<3,$C$8,0)),F22*(1-$C$6-IF(E22<3,$C$8,0)))),IF(IF(F22<G22*(1-$C$7),G22*(1-$C$5-IF(E22<3,$C$8,0)),MIN(G22*(1-$C$5-IF(E22<3,$C$8,0)),F22*(1-$C$6-IF(E22<3,$C$8,0))))<10,$C$9,IF(IF(F22<G22*(1-$C$7),G22*(1-$C$5-IF(E22<3,$C$8,0)),MIN(G22*(1-$C$5-IF(E22<3,$C$8,0)),F22*(1-$C$6-IF(E22<3,$C$8,0))))<100,$D$9,$E$9))))) -> 22.8 | K22: =IF(ISNUMBER($D22),$D22,"n/a") -> 8.25 | L22: =IF(OR(E22=0,NOT(ISNUMBER($D22))),"—",J22/$D22-1) -> 1.7636364 | M22: =IF(E22=0,"—",J22/F22-1) -> 0.15384615 | N22: =IF(E22=0,"—",J22/G22-1) -> -0.25245902 | O22: =COUNTIFS(Offers!$B$7:$B$3000,$B22,Offers!$C$7:$C$3000,"Germany",Offers!$AI$7:$AI$3000,"yes") -> 7 | P22: =IF(O22=0,"—",SUMIFS(Review!$I$7:$I$600,Review!$B$7:$B$600,$B22,Review!$C$7:$C$600,"Germany")) -> 18.09 | Q22: =IF(O22=0,"—",SUMIFS(Review!$J$7:$J$600,Review!$B$7:$B$600,$B22,Review!$C$7:$C$600,"Germany")) -> 27.49 | R22: =IF(O22=0,"—",SUMIFS(Review!$K$7:$K$600,Review!$B$7:$B$600,$B22,Review!$C$7:$C$600,"Germany")) -> 93.66 | S22: =IF(O22=0,"—",IF(P22<Q22*(1-$C$7),"median (cheapest is an outlier)",IF(P22*(1-$C$6)<Q22*(1-$C$5),"undercut cheapest","median"))) -> undercut cheapest | T22: =IF(O22=0,"—",IF(AND(ISNUMBER($D22),$D22*(1+$C$10)>FLOOR(IF(P22<Q22*(1-$C$7),Q22*(1-$C$5-IF(O22<3,$C$8,0)),MIN(Q22*(1-$C$5-IF(O22<3,$C$8,0)),P22*(1-$C$6-IF(O22<3,$C$8,0)))),IF(IF(P22<Q22*(1-$C$7),Q22*(1-$C$5-IF(O22<3,$C$8,0)),MIN(Q22*(1-$C$5-IF(O22<3,$C$8,0)),P22*(1-$C$6-IF(O22<3,$C$8,0))))<10,$C$9,IF(IF(P22<Q22*(1-$C$7),Q22*(1-$C$5-IF(O22<3,$C$8,0)),MIN(Q22*(1-$C$5-IF(O22<3,$C$8,0)),P22*(1-$C$6-IF(O22<3,$C$8,0))))<100,$D$9,$E$9)))),ROUND($D22*(1+$C$10),2),FLOOR(IF(P22<Q22*(1-$C$7),Q22*(1-$C$5-IF(O22<3,$C$8,0)),MIN(Q22*(1-$C$5-IF(O22<3,$C$8,0)),P22*(1-$C$6-IF(O22<3,$C$8,0)))),IF(IF(P22<Q22*(1-$C$7),Q22*(1-$C$5-IF(O22<3,$C$8,0)),MIN(Q22*(1-$C$5-IF(O22<3,$C$8,0)),P22*(1-$C$6-IF(O22<3,$C$8,0))))<10,$C$9,IF(IF(P22<Q22*(1-$C$7),Q22*(1-$C$5-IF(O22<3,$C$8,0)),MIN(Q22*(1-$C$5-IF(O22<3,$C$8,0)),P22*(1-$C$6-IF(O22<3,$C$8,0))))<100,$D$9,$E$9))))) -> 17.1 | U22: =IF(ISNUMBER($D22),$D22,"n/a") -> 8.25 | V22: =IF(OR(O22=0,NOT(ISNUMBER($D22))),"—",T22/$D22-1) -> 1.0727273 | W22: =IF(O22=0,"—",T22/P22-1) -> -0.054726368 | X22: =IF(O22=0,"—",T22/Q22-1) -> -0.37795562 | Y22: =COUNTIFS(Offers!$B$7:$B$3000,$B22,Offers!$C$7:$C$3000,"Czech",Offers!$AI$7:$AI$3000,"yes") -> 3 | Z22: =IF(Y22=0,"—",SUMIFS(Review!$I$7:$I$600,Review!$B$7:$B$600,$B22,Review!$C$7:$C$600,"Czech")) -> 26.04037 | AA22: =IF(Y22=0,"—",SUMIFS(Review!$J$7:$J$600,Review!$B$7:$B$600,$B22,Review!$C$7:$C$600,"Czech")) -> 40.84817 | AB22: =IF(Y22=0,"—",SUMIFS(Review!$K$7:$K$600,Review!$B$7:$B$600,$B22,Review!$C$7:$C$600,"Czech")) -> 48.929692 | AC22: =IF(Y22=0,"—",IF(Z22<AA22*(1-$C$7),"median (cheapest is an outlier)",IF(Z22*(1-$C$6)<AA22*(1-$C$5),"undercut cheapest","median"))) -> median (cheapest is an outlier) | AD22: =IF(Y22=0,"—",IF(AND(ISNUMBER($D22),$D22*(1+$C$10)>FLOOR(IF(Z22<AA22*(1-$C$7),AA22*(1-$C$5-IF(Y22<3,$C$8,0)),MIN(AA22*(1-$C$5-IF(Y22<3,$C$8,0)),Z22*(1-$C$6-IF(Y22<3,$C$8,0)))),IF(IF(Z22<AA22*(1-$C$7),AA22*(1-$C$5-IF(Y22<3,$C$8,0)),MIN(AA22*(1-$C$5-IF(Y22<3,$C$8,0)),Z22*(1-$C$6-IF(Y22<3,$C$8,0))))<10,$C$9,IF(IF(Z22<AA22*(1-$C$7),AA22*(1-$C$5-IF(Y22<3,$C$8,0)),MIN(AA22*(1-$C$5-IF(Y22<3,$C$8,0)),Z22*(1-$C$6-IF(Y22<3,$C$8,0))))<100,$D$9,$E$9)))),ROUND($D22*(1+$C$10),2),FLOOR(IF(Z22<AA22*(1-$C$7),AA22*(1-$C$5-IF(Y22<3,$C$8,0)),MIN(AA22*(1-$C$5-IF(Y22<3,$C$8,0)),Z22*(1-$C$6-IF(Y22<3,$C$8,0)))),IF(IF(Z22<AA22*(1-$C$7),AA22*(1-$C$5-IF(Y22<3,$C$8,0)),MIN(AA22*(1-$C$5-IF(Y22<3,$C$8,0)),Z22*(1-$C$6-IF(Y22<3,$C$8,0))))<10,$C$9,IF(IF(Z22<AA22*(1-$C$7),AA22*(1-$C$5-IF(Y22<3,$C$8,0)),MIN(AA22*(1-$C$5-IF(Y22<3,$C$8,0)),Z22*(1-$C$6-IF(Y22<3,$C$8,0))))<100,$D$9,$E$9))))) -> 30.6 | AE22: =IF(Y22=0,"—",FLOOR(AD22*Sources!$G$10,1)) -> 747 | AF22: =IF(ISNUMBER($D22),$D22,"n/a") -> 8.25 | AG22: =IF(OR(Y22=0,NOT(ISNUMBER($D22))),"—",AD22/$D22-1) -> 2.7090909 | AH22: =IF(Y22=0,"—",AD22/Z22-1) -> 0.17509851 | AI22: =IF(Y22=0,"—",AD22/AA22-1) -> -0.25088443 | AJ22: =COUNTIFS(Offers!$B$7:$B$3000,$B22,Offers!$C$7:$C$3000,"Slovakia",Offers!$AI$7:$AI$3000,"yes") -> 0 | AK22: =IF(AJ22=0,"—",SUMIFS(Review!$I$7:$I$600,Review!$B$7:$B$600,$B22,Review!$C$7:$C$600,"Slovakia")) -> — | AL22: =IF(AJ22=0,"—",SUMIFS(Review!$J$7:$J$600,Review!$B$7:$B$600,$B22,Review!$C$7:$C$600,"Slovakia")) -> — | AM22: =IF(AJ22=0,"—",SUMIFS(Review!$K$7:$K$600,Review!$B$7:$B$600,$B22,Review!$C$7:$C$600,"Slovakia")) -> — | AN22: =IF(AJ22=0,"—",IF(AK22<AL22*(1-$C$7),"median (cheapest is an outlier)",IF(AK22*(1-$C$6)<AL22*(1-$C$5),"undercut cheapest","median"))) -> — | AO22: =IF(AJ22=0,"—",IF(AND(ISNUMBER($D22),$D22*(1+$C$10)>FLOOR(IF(AK22<AL22*(1-$C$7),AL22*(1-$C$5-IF(AJ22<3,$C$8,0)),MIN(AL22*(1-$C$5-IF(AJ22<3,$C$8,0)),AK22*(1-$C$6-IF(AJ22<3,$C$8,0)))),IF(IF(AK22<AL22*(1-$C$7),AL22*(1-$C$5-IF(AJ22<3,$C$8,0)),MIN(AL22*(1-$C$5-IF(AJ22<3,$C$8,0)),AK22*(1-$C$6-IF(AJ22<3,$C$8,0))))<10,$C$9,IF(IF(AK22<AL22*(1-$C$7),AL22*(1-$C$5-IF(AJ22<3,$C$8,0)),MIN(AL22*(1-$C$5-IF(AJ22<3,$C$8,0)),AK22*(1-$C$6-IF(AJ22<3,$C$8,0))))<100,$D$9,$E$9)))),ROUND($D22*(1+$C$10),2),FLOOR(IF(AK22<AL22*(1-$C$7),AL22*(1-$C$5-IF(AJ22<3,$C$8,0)),MIN(AL22*(1-$C$5-IF(AJ22<3,$C$8,0)),AK22*(1-$C$6-IF(AJ22<3,$C$8,0)))),IF(IF(AK22<AL22*(1-$C$7),AL22*(1-$C$5-IF(AJ22<3,$C$8,0)),MIN(AL22*(1-$C$5-IF(AJ22<3,$C$8,0)),AK22*(1-$C$6-IF(AJ22<3,$C$8,0))))<10,$C$9,IF(IF(AK22<AL22*(1-$C$7),AL22*(1-$C$5-IF(AJ22<3,$C$8,0)),MIN(AL22*(1-$C$5-IF(AJ22<3,$C$8,0)),AK22*(1-$C$6-IF(AJ22<3,$C$8,0))))<100,$D$9,$E$9))))) -> — | AP22: =IF(ISNUMBER($D22),$D22,"n/a") -> 8.25 | AQ22: =IF(OR(AJ22=0,NOT(ISNUMBER($D22))),"—",AO22/$D22-1) -> — | AR22: =IF(AJ22=0,"—",AO22/AK22-1) -> — | AS22: =IF(AJ22=0,"—",AO22/AL22-1) -> — | AT22: =COUNTIFS(Offers!$B$7:$B$3000,$B22,Offers!$C$7:$C$3000,"Romania",Offers!$AI$7:$AI$3000,"yes") -> 1 | AU22: =IF(AT22=0,"—",SUMIFS(Review!$I$7:$I$600,Review!$B$7:$B$600,$B22,Review!$C$7:$C$600,"Romania")) -> 16.641903 | AV22: =IF(AT22=0,"—",SUMIFS(Review!$J$7:$J$600,Review!$B$7:$B$600,$B22,Review!$C$7:$C$600,"Romania")) -> 16.641903 | AW22: =IF(AT22=0,"—",SUMIFS(Review!$K$7:$K$600,Review!$B$7:$B$600,$B22,Review!$C$7:$C$600,"Romania")) -> 16.641903 | AX22: =IF(AT22=0,"—",IF(AU22<AV22*(1-$C$7),"median (cheapest is an outlier)",IF(AU22*(1-$C$6)<AV22*(1-$C$5),"undercut cheapest","median"))) -> median | AY22: =IF(AT22=0,"—",IF(AND(ISNUMBER($D22),$D22*(1+$C$10)>FLOOR(IF(AU22<AV22*(1-$C$7),AV22*(1-$C$5-IF(AT22<3,$C$8,0)),MIN(AV22*(1-$C$5-IF(AT22<3,$C$8,0)),AU22*(1-$C$6-IF(AT22<3,$C$8,0)))),IF(IF(AU22<AV22*(1-$C$7),AV22*(1-$C$5-IF(AT22<3,$C$8,0)),MIN(AV22*(1-$C$5-IF(AT22<3,$C$8,0)),AU22*(1-$C$6-IF(AT22<3,$C$8,0))))<10,$C$9,IF(IF(AU22<AV22*(1-$C$7),AV22*(1-$C$5-IF(AT22<3,$C$8,0)),MIN(AV22*(1-$C$5-IF(AT22<3,$C$8,0)),AU22*(1-$C$6-IF(AT22<3,$C$8,0))))<100,$D$9,$E$9)))),ROUND($D22*(1+$C$10),2),FLOOR(IF(AU22<AV22*(1-$C$7),AV22*(1-$C$5-IF(AT22<3,$C$8,0)),MIN(AV22*(1-$C$5-IF(AT22<3,$C$8,0)),AU22*(1-$C$6-IF(AT22<3,$C$8,0)))),IF(IF(AU22<AV22*(1-$C$7),AV22*(1-$C$5-IF(AT22<3,$C$8,0)),MIN(AV22*(1-$C$5-IF(AT22<3,$C$8,0)),AU22*(1-$C$6-IF(AT22<3,$C$8,0))))<10,$C$9,IF(IF(AU22<AV22*(1-$C$7),AV22*(1-$C$5-IF(AT22<3,$C$8,0)),MIN(AV22*(1-$C$5-IF(AT22<3,$C$8,0)),AU22*(1-$C$6-IF(AT22<3,$C$8,0))))<100,$D$9,$E$9))))) -> 11.6 | AZ22: =IF(AT22=0,"—",FLOOR(AY22*Sources!$G$9,0.1)) -> 61.2 | BA22: =IF(ISNUMBER($D22),$D22,"n/a") -> 8.25 | BB22: =IF(OR(AT22=0,NOT(ISNUMBER($D22))),"—",AY22/$D22-1) -> 0.40606061 | BC22: =IF(AT22=0,"—",AY22/AU22-1) -> -0.30296433 | BD22: =IF(AT22=0,"—",AY22/AV22-1) -> -0.30296433 | BE22: =COUNTIFS(Offers!$B$7:$B$3000,$B22,Offers!$C$7:$C$3000,"Hungary",Offers!$AI$7:$AI$3000,"yes") -> 0 | BF22: =IF(BE22=0,"—",SUMIFS(Review!$I$7:$I$600,Review!$B$7:$B$600,$B22,Review!$C$7:$C$600,"Hungary")) -> — | BG22: =IF(BE22=0,"—",SUMIFS(Review!$J$7:$J$600,Review!$B$7:$B$600,$B22,Review!$C$7:$C$600,"Hungary")) -> — | BH22: =IF(BE22=0,"—",SUMIFS(Review!$K$7:$K$600,Review!$B$7:$B$600,$B22,Review!$C$7:$C$600,"Hungary")) -> — | BI22: =IF(BE22=0,"—",IF(BF22<BG22*(1-$C$7),"median (cheapest is an outlier)",IF(BF22*(1-$C$6)<BG22*(1-$C$5),"undercut cheapest","median"))) -> — | BJ22: =IF(BE22=0,"—",IF(AND(ISNUMBER($D22),$D22*(1+$C$10)>FLOOR(IF(BF22<BG22*(1-$C$7),BG22*(1-$C$5-IF(BE22<3,$C$8,0)),MIN(BG22*(1-$C$5-IF(BE22<3,$C$8,0)),BF22*(1-$C$6-IF(BE22<3,$C$8,0)))),IF(IF(BF22<BG22*(1-$C$7),BG22*(1-$C$5-IF(BE22<3,$C$8,0)),MIN(BG22*(1-$C$5-IF(BE22<3,$C$8,0)),BF22*(1-$C$6-IF(BE22<3,$C$8,0))))<10,$C$9,IF(IF(BF22<BG22*(1-$C$7),BG22*(1-$C$5-IF(BE22<3,$C$8,0)),MIN(BG22*(1-$C$5-IF(BE22<3,$C$8,0)),BF22*(1-$C$6-IF(BE22<3,$C$8,0))))<100,$D$9,$E$9)))),ROUND($D22*(1+$C$10),2),FLOOR(IF(BF22<BG22*(1-$C$7),BG22*(1-$C$5-IF(BE22<3,$C$8,0)),MIN(BG22*(1-$C$5-IF(BE22<3,$C$8,0)),BF22*(1-$C$6-IF(BE22<3,$C$8,0)))),IF(IF(BF22<BG22*(1-$C$7),BG22*(1-$C$5-IF(BE22<3,$C$8,0)),MIN(BG22*(1-$C$5-IF(BE22<3,$C$8,0)),BF22*(1-$C$6-IF(BE22<3,$C$8,0))))<10,$C$9,IF(IF(BF22<BG22*(1-$C$7),BG22*(1-$C$5-IF(BE22<3,$C$8,0)),MIN(BG22*(1-$C$5-IF(BE22<3,$C$8,0)),BF22*(1-$C$6-IF(BE22<3,$C$8,0))))<100,$D$9,$E$9))))) -> — | BK22: =IF(BE22=0,"—",FLOOR(BJ22*Sources!$G$8,10)) -> — | BL22: =IF(ISNUMBER($D22),$D22,"n/a") -> 8.25 | BM22: =IF(OR(BE22=0,NOT(ISNUMBER($D22))),"—",BJ22/$D22-1) -> — | BN22: =IF(BE22=0,"—",BJ22/BF22-1) -> — | BO22: =IF(BE22=0,"—",BJ22/BG22-1) -> —
B23: PE cutting board 530 × 325 × 20 mm | C23: PE-53322/W | D23: 11.1 | E23: =COUNTIFS(Offers!$B$7:$B$3000,$B23,Offers!$C$7:$C$3000,"Austria",Offers!$AI$7:$AI$3000,"yes") -> 9 | F23: =IF(E23=0,"—",SUMIFS(Review!$I$7:$I$600,Review!$B$7:$B$600,$B23,Review!$C$7:$C$600,"Austria")) -> 18 | G23: =IF(E23=0,"—",SUMIFS(Review!$J$7:$J$600,Review!$B$7:$B$600,$B23,Review!$C$7:$C$600,"Austria")) -> 24.57 | H23: =IF(E23=0,"—",SUMIFS(Review!$K$7:$K$600,Review!$B$7:$B$600,$B23,Review!$C$7:$C$600,"Austria")) -> 34.99 | I23: =IF(E23=0,"—",IF(F23<G23*(1-$C$7),"median (cheapest is an outlier)",IF(F23*(1-$C$6)<G23*(1-$C$5),"undercut cheapest","median"))) -> undercut cheapest | J23: =IF(E23=0,"—",IF(AND(ISNUMBER($D23),$D23*(1+$C$10)>FLOOR(IF(F23<G23*(1-$C$7),G23*(1-$C$5-IF(E23<3,$C$8,0)),MIN(G23*(1-$C$5-IF(E23<3,$C$8,0)),F23*(1-$C$6-IF(E23<3,$C$8,0)))),IF(IF(F23<G23*(1-$C$7),G23*(1-$C$5-IF(E23<3,$C$8,0)),MIN(G23*(1-$C$5-IF(E23<3,$C$8,0)),F23*(1-$C$6-IF(E23<3,$C$8,0))))<10,$C$9,IF(IF(F23<G23*(1-$C$7),G23*(1-$C$5-IF(E23<3,$C$8,0)),MIN(G23*(1-$C$5-IF(E23<3,$C$8,0)),F23*(1-$C$6-IF(E23<3,$C$8,0))))<100,$D$9,$E$9)))),ROUND($D23*(1+$C$10),2),FLOOR(IF(F23<G23*(1-$C$7),G23*(1-$C$5-IF(E23<3,$C$8,0)),MIN(G23*(1-$C$5-IF(E23<3,$C$8,0)),F23*(1-$C$6-IF(E23<3,$C$8,0)))),IF(IF(F23<G23*(1-$C$7),G23*(1-$C$5-IF(E23<3,$C$8,0)),MIN(G23*(1-$C$5-IF(E23<3,$C$8,0)),F23*(1-$C$6-IF(E23<3,$C$8,0))))<10,$C$9,IF(IF(F23<G23*(1-$C$7),G23*(1-$C$5-IF(E23<3,$C$8,0)),MIN(G23*(1-$C$5-IF(E23<3,$C$8,0)),F23*(1-$C$6-IF(E23<3,$C$8,0))))<100,$D$9,$E$9))))) -> 17.1 | K23: =IF(ISNUMBER($D23),$D23,"n/a") -> 11.1 | L23: =IF(OR(E23=0,NOT(ISNUMBER($D23))),"—",J23/$D23-1) -> 0.54054054 | M23: =IF(E23=0,"—",J23/F23-1) -> -0.05 | N23: =IF(E23=0,"—",J23/G23-1) -> -0.3040293 | O23: =COUNTIFS(Offers!$B$7:$B$3000,$B23,Offers!$C$7:$C$3000,"Germany",Offers!$AI$7:$AI$3000,"yes") -> 10 | P23: =IF(O23=0,"—",SUMIFS(Review!$I$7:$I$600,Review!$B$7:$B$600,$B23,Review!$C$7:$C$600,"Germany")) -> 17.29 | Q23: =IF(O23=0,"—",SUMIFS(Review!$J$7:$J$600,Review!$B$7:$B$600,$B23,Review!$C$7:$C$600,"Germany")) -> 22.79 | R23: =IF(O23=0,"—",SUMIFS(Review!$K$7:$K$600,Review!$B$7:$B$600,$B23,Review!$C$7:$C$600,"Germany")) -> 34.99 | S23: =IF(O23=0,"—",IF(P23<Q23*(1-$C$7),"median (cheapest is an outlier)",IF(P23*(1-$C$6)<Q23*(1-$C$5),"undercut cheapest","median"))) -> undercut cheapest | T23: =IF(O23=0,"—",IF(AND(ISNUMBER($D23),$D23*(1+$C$10)>FLOOR(IF(P23<Q23*(1-$C$7),Q23*(1-$C$5-IF(O23<3,$C$8,0)),MIN(Q23*(1-$C$5-IF(O23<3,$C$8,0)),P23*(1-$C$6-IF(O23<3,$C$8,0)))),IF(IF(P23<Q23*(1-$C$7),Q23*(1-$C$5-IF(O23<3,$C$8,0)),MIN(Q23*(1-$C$5-IF(O23<3,$C$8,0)),P23*(1-$C$6-IF(O23<3,$C$8,0))))<10,$C$9,IF(IF(P23<Q23*(1-$C$7),Q23*(1-$C$5-IF(O23<3,$C$8,0)),MIN(Q23*(1-$C$5-IF(O23<3,$C$8,0)),P23*(1-$C$6-IF(O23<3,$C$8,0))))<100,$D$9,$E$9)))),ROUND($D23*(1+$C$10),2),FLOOR(IF(P23<Q23*(1-$C$7),Q23*(1-$C$5-IF(O23<3,$C$8,0)),MIN(Q23*(1-$C$5-IF(O23<3,$C$8,0)),P23*(1-$C$6-IF(O23<3,$C$8,0)))),IF(IF(P23<Q23*(1-$C$7),Q23*(1-$C$5-IF(O23<3,$C$8,0)),MIN(Q23*(1-$C$5-IF(O23<3,$C$8,0)),P23*(1-$C$6-IF(O23<3,$C$8,0))))<10,$C$9,IF(IF(P23<Q23*(1-$C$7),Q23*(1-$C$5-IF(O23<3,$C$8,0)),MIN(Q23*(1-$C$5-IF(O23<3,$C$8,0)),P23*(1-$C$6-IF(O23<3,$C$8,0))))<100,$D$9,$E$9))))) -> 16.4 | U23: =IF(ISNUMBER($D23),$D23,"n/a") -> 11.1 | V23: =IF(OR(O23=0,NOT(ISNUMBER($D23))),"—",T23/$D23-1) -> 0.47747748 | W23: =IF(O23=0,"—",T23/P23-1) -> -0.051474841 | X23: =IF(O23=0,"—",T23/Q23-1) -> -0.28038613 | Y23: =COUNTIFS(Offers!$B$7:$B$3000,$B23,Offers!$C$7:$C$3000,"Czech",Offers!$AI$7:$AI$3000,"yes") -> 5 | Z23: =IF(Y23=0,"—",SUMIFS(Review!$I$7:$I$600,Review!$B$7:$B$600,$B23,Review!$C$7:$C$600,"Czech")) -> 25.899933 | AA23: =IF(Y23=0,"—",SUMIFS(Review!$J$7:$J$600,Review!$B$7:$B$600,$B23,Review!$C$7:$C$600,"Czech")) -> 44.628937 | AB23: =IF(Y23=0,"—",SUMIFS(Review!$K$7:$K$600,Review!$B$7:$B$600,$B23,Review!$C$7:$C$600,"Czech")) -> 51.806007 | AC23: =IF(Y23=0,"—",IF(Z23<AA23*(1-$C$7),"median (cheapest is an outlier)",IF(Z23*(1-$C$6)<AA23*(1-$C$5),"undercut cheapest","median"))) -> median (cheapest is an outlier) | AD23: =IF(Y23=0,"—",IF(AND(ISNUMBER($D23),$D23*(1+$C$10)>FLOOR(IF(Z23<AA23*(1-$C$7),AA23*(1-$C$5-IF(Y23<3,$C$8,0)),MIN(AA23*(1-$C$5-IF(Y23<3,$C$8,0)),Z23*(1-$C$6-IF(Y23<3,$C$8,0)))),IF(IF(Z23<AA23*(1-$C$7),AA23*(1-$C$5-IF(Y23<3,$C$8,0)),MIN(AA23*(1-$C$5-IF(Y23<3,$C$8,0)),Z23*(1-$C$6-IF(Y23<3,$C$8,0))))<10,$C$9,IF(IF(Z23<AA23*(1-$C$7),AA23*(1-$C$5-IF(Y23<3,$C$8,0)),MIN(AA23*(1-$C$5-IF(Y23<3,$C$8,0)),Z23*(1-$C$6-IF(Y23<3,$C$8,0))))<100,$D$9,$E$9)))),ROUND($D23*(1+$C$10),2),FLOOR(IF(Z23<AA23*(1-$C$7),AA23*(1-$C$5-IF(Y23<3,$C$8,0)),MIN(AA23*(1-$C$5-IF(Y23<3,$C$8,0)),Z23*(1-$C$6-IF(Y23<3,$C$8,0)))),IF(IF(Z23<AA23*(1-$C$7),AA23*(1-$C$5-IF(Y23<3,$C$8,0)),MIN(AA23*(1-$C$5-IF(Y23<3,$C$8,0)),Z23*(1-$C$6-IF(Y23<3,$C$8,0))))<10,$C$9,IF(IF(Z23<AA23*(1-$C$7),AA23*(1-$C$5-IF(Y23<3,$C$8,0)),MIN(AA23*(1-$C$5-IF(Y23<3,$C$8,0)),Z23*(1-$C$6-IF(Y23<3,$C$8,0))))<100,$D$9,$E$9))))) -> 33.4 | AE23: =IF(Y23=0,"—",FLOOR(AD23*Sources!$G$10,1)) -> 815 | AF23: =IF(ISNUMBER($D23),$D23,"n/a") -> 11.1 | AG23: =IF(OR(Y23=0,NOT(ISNUMBER($D23))),"—",AD23/$D23-1) -> 2.009009 | AH23: =IF(Y23=0,"—",AD23/Z23-1) -> 0.28957863 | AI23: =IF(Y23=0,"—",AD23/AA23-1) -> -0.25160664 | AJ23: =COUNTIFS(Offers!$B$7:$B$3000,$B23,Offers!$C$7:$C$3000,"Slovakia",Offers!$AI$7:$AI$3000,"yes") -> 2 | AK23: =IF(AJ23=0,"—",SUMIFS(Review!$I$7:$I$600,Review!$B$7:$B$600,$B23,Review!$C$7:$C$600,"Slovakia")) -> 20.35 | AL23: =IF(AJ23=0,"—",SUMIFS(Review!$J$7:$J$600,Review!$B$7:$B$600,$B23,Review!$C$7:$C$600,"Slovakia")) -> 36.154675 | AM23: =IF(AJ23=0,"—",SUMIFS(Review!$K$7:$K$600,Review!$B$7:$B$600,$B23,Review!$C$7:$C$600,"Slovakia")) -> 51.95935 | AN23: =IF(AJ23=0,"—",IF(AK23<AL23*(1-$C$7),"median (cheapest is an outlier)",IF(AK23*(1-$C$6)<AL23*(1-$C$5),"undercut cheapest","median"))) -> median (cheapest is an outlier) | AO23: =IF(AJ23=0,"—",IF(AND(ISNUMBER($D23),$D23*(1+$C$10)>FLOOR(IF(AK23<AL23*(1-$C$7),AL23*(1-$C$5-IF(AJ23<3,$C$8,0)),MIN(AL23*(1-$C$5-IF(AJ23<3,$C$8,0)),AK23*(1-$C$6-IF(AJ23<3,$C$8,0)))),IF(IF(AK23<AL23*(1-$C$7),AL23*(1-$C$5-IF(AJ23<3,$C$8,0)),MIN(AL23*(1-$C$5-IF(AJ23<3,$C$8,0)),AK23*(1-$C$6-IF(AJ23<3,$C$8,0))))<10,$C$9,IF(IF(AK23<AL23*(1-$C$7),AL23*(1-$C$5-IF(AJ23<3,$C$8,0)),MIN(AL23*(1-$C$5-IF(AJ23<3,$C$8,0)),AK23*(1-$C$6-IF(AJ23<3,$C$8,0))))<100,$D$9,$E$9)))),ROUND($D23*(1+$C$10),2),FLOOR(IF(AK23<AL23*(1-$C$7),AL23*(1-$C$5-IF(AJ23<3,$C$8,0)),MIN(AL23*(1-$C$5-IF(AJ23<3,$C$8,0)),AK23*(1-$C$6-IF(AJ23<3,$C$8,0)))),IF(IF(AK23<AL23*(1-$C$7),AL23*(1-$C$5-IF(AJ23<3,$C$8,0)),MIN(AL23*(1-$C$5-IF(AJ23<3,$C$8,0)),AK23*(1-$C$6-IF(AJ23<3,$C$8,0))))<10,$C$9,IF(IF(AK23<AL23*(1-$C$7),AL23*(1-$C$5-IF(AJ23<3,$C$8,0)),MIN(AL23*(1-$C$5-IF(AJ23<3,$C$8,0)),AK23*(1-$C$6-IF(AJ23<3,$C$8,0))))<100,$D$9,$E$9))))) -> 25.3 | AP23: =IF(ISNUMBER($D23),$D23,"n/a") -> 11.1 | AQ23: =IF(OR(AJ23=0,NOT(ISNUMBER($D23))),"—",AO23/$D23-1) -> 1.2792793 | AR23: =IF(AJ23=0,"—",AO23/AK23-1) -> 0.24324324 | AS23: =IF(AJ23=0,"—",AO23/AL23-1) -> -0.30022881 | AT23: =COUNTIFS(Offers!$B$7:$B$3000,$B23,Offers!$C$7:$C$3000,"Romania",Offers!$AI$7:$AI$3000,"yes") -> 0 | AU23: =IF(AT23=0,"—",SUMIFS(Review!$I$7:$I$600,Review!$B$7:$B$600,$B23,Review!$C$7:$C$600,"Romania")) -> — | AV23: =IF(AT23=0,"—",SUMIFS(Review!$J$7:$J$600,Review!$B$7:$B$600,$B23,Review!$C$7:$C$600,"Romania")) -> — | AW23: =IF(AT23=0,"—",SUMIFS(Review!$K$7:$K$600,Review!$B$7:$B$600,$B23,Review!$C$7:$C$600,"Romania")) -> — | AX23: =IF(AT23=0,"—",IF(AU23<AV23*(1-$C$7),"median (cheapest is an outlier)",IF(AU23*(1-$C$6)<AV23*(1-$C$5),"undercut cheapest","median"))) -> — | AY23: =IF(AT23=0,"—",IF(AND(ISNUMBER($D23),$D23*(1+$C$10)>FLOOR(IF(AU23<AV23*(1-$C$7),AV23*(1-$C$5-IF(AT23<3,$C$8,0)),MIN(AV23*(1-$C$5-IF(AT23<3,$C$8,0)),AU23*(1-$C$6-IF(AT23<3,$C$8,0)))),IF(IF(AU23<AV23*(1-$C$7),AV23*(1-$C$5-IF(AT23<3,$C$8,0)),MIN(AV23*(1-$C$5-IF(AT23<3,$C$8,0)),AU23*(1-$C$6-IF(AT23<3,$C$8,0))))<10,$C$9,IF(IF(AU23<AV23*(1-$C$7),AV23*(1-$C$5-IF(AT23<3,$C$8,0)),MIN(AV23*(1-$C$5-IF(AT23<3,$C$8,0)),AU23*(1-$C$6-IF(AT23<3,$C$8,0))))<100,$D$9,$E$9)))),ROUND($D23*(1+$C$10),2),FLOOR(IF(AU23<AV23*(1-$C$7),AV23*(1-$C$5-IF(AT23<3,$C$8,0)),MIN(AV23*(1-$C$5-IF(AT23<3,$C$8,0)),AU23*(1-$C$6-IF(AT23<3,$C$8,0)))),IF(IF(AU23<AV23*(1-$C$7),AV23*(1-$C$5-IF(AT23<3,$C$8,0)),MIN(AV23*(1-$C$5-IF(AT23<3,$C$8,0)),AU23*(1-$C$6-IF(AT23<3,$C$8,0))))<10,$C$9,IF(IF(AU23<AV23*(1-$C$7),AV23*(1-$C$5-IF(AT23<3,$C$8,0)),MIN(AV23*(1-$C$5-IF(AT23<3,$C$8,0)),AU23*(1-$C$6-IF(AT23<3,$C$8,0))))<100,$D$9,$E$9))))) -> — | AZ23: =IF(AT23=0,"—",FLOOR(AY23*Sources!$G$9,0.1)) -> — | BA23: =IF(ISNUMBER($D23),$D23,"n/a") -> 11.1 | BB23: =IF(OR(AT23=0,NOT(ISNUMBER($D23))),"—",AY23/$D23-1) -> — | BC23: =IF(AT23=0,"—",AY23/AU23-1) -> — | BD23: =IF(AT23=0,"—",AY23/AV23-1) -> — | BE23: =COUNTIFS(Offers!$B$7:$B$3000,$B23,Offers!$C$7:$C$3000,"Hungary",Offers!$AI$7:$AI$3000,"yes") -> 0 | BF23: =IF(BE23=0,"—",SUMIFS(Review!$I$7:$I$600,Review!$B$7:$B$600,$B23,Review!$C$7:$C$600,"Hungary")) -> — | BG23: =IF(BE23=0,"—",SUMIFS(Review!$J$7:$J$600,Review!$B$7:$B$600,$B23,Review!$C$7:$C$600,"Hungary")) -> — | BH23: =IF(BE23=0,"—",SUMIFS(Review!$K$7:$K$600,Review!$B$7:$B$600,$B23,Review!$C$7:$C$600,"Hungary")) -> — | BI23: =IF(BE23=0,"—",IF(BF23<BG23*(1-$C$7),"median (cheapest is an outlier)",IF(BF23*(1-$C$6)<BG23*(1-$C$5),"undercut cheapest","median"))) -> — | BJ23: =IF(BE23=0,"—",IF(AND(ISNUMBER($D23),$D23*(1+$C$10)>FLOOR(IF(BF23<BG23*(1-$C$7),BG23*(1-$C$5-IF(BE23<3,$C$8,0)),MIN(BG23*(1-$C$5-IF(BE23<3,$C$8,0)),BF23*(1-$C$6-IF(BE23<3,$C$8,0)))),IF(IF(BF23<BG23*(1-$C$7),BG23*(1-$C$5-IF(BE23<3,$C$8,0)),MIN(BG23*(1-$C$5-IF(BE23<3,$C$8,0)),BF23*(1-$C$6-IF(BE23<3,$C$8,0))))<10,$C$9,IF(IF(BF23<BG23*(1-$C$7),BG23*(1-$C$5-IF(BE23<3,$C$8,0)),MIN(BG23*(1-$C$5-IF(BE23<3,$C$8,0)),BF23*(1-$C$6-IF(BE23<3,$C$8,0))))<100,$D$9,$E$9)))),ROUND($D23*(1+$C$10),2),FLOOR(IF(BF23<BG23*(1-$C$7),BG23*(1-$C$5-IF(BE23<3,$C$8,0)),MIN(BG23*(1-$C$5-IF(BE23<3,$C$8,0)),BF23*(1-$C$6-IF(BE23<3,$C$8,0)))),IF(IF(BF23<BG23*(1-$C$7),BG23*(1-$C$5-IF(BE23<3,$C$8,0)),MIN(BG23*(1-$C$5-IF(BE23<3,$C$8,0)),BF23*(1-$C$6-IF(BE23<3,$C$8,0))))<10,$C$9,IF(IF(BF23<BG23*(1-$C$7),BG23*(1-$C$5-IF(BE23<3,$C$8,0)),MIN(BG23*(1-$C$5-IF(BE23<3,$C$8,0)),BF23*(1-$C$6-IF(BE23<3,$C$8,0))))<100,$D$9,$E$9))))) -> — | BK23: =IF(BE23=0,"—",FLOOR(BJ23*Sources!$G$8,10)) -> — | BL23: =IF(ISNUMBER($D23),$D23,"n/a") -> 11.1 | BM23: =IF(OR(BE23=0,NOT(ISNUMBER($D23))),"—",BJ23/$D23-1) -> — | BN23: =IF(BE23=0,"—",BJ23/BF23-1) -> — | BO23: =IF(BE23=0,"—",BJ23/BG23-1) -> —
B24: PE cutting board 600 × 400 × 20 mm | C24: PE-60402/W | D24: 14.1 | E24: =COUNTIFS(Offers!$B$7:$B$3000,$B24,Offers!$C$7:$C$3000,"Austria",Offers!$AI$7:$AI$3000,"yes") -> 7 | F24: =IF(E24=0,"—",SUMIFS(Review!$I$7:$I$600,Review!$B$7:$B$600,$B24,Review!$C$7:$C$600,"Austria")) -> 27.9 | G24: =IF(E24=0,"—",SUMIFS(Review!$J$7:$J$600,Review!$B$7:$B$600,$B24,Review!$C$7:$C$600,"Austria")) -> 33.5 | H24: =IF(E24=0,"—",SUMIFS(Review!$K$7:$K$600,Review!$B$7:$B$600,$B24,Review!$C$7:$C$600,"Austria")) -> 49.39 | I24: =IF(E24=0,"—",IF(F24<G24*(1-$C$7),"median (cheapest is an outlier)",IF(F24*(1-$C$6)<G24*(1-$C$5),"undercut cheapest","median"))) -> median | J24: =IF(E24=0,"—",IF(AND(ISNUMBER($D24),$D24*(1+$C$10)>FLOOR(IF(F24<G24*(1-$C$7),G24*(1-$C$5-IF(E24<3,$C$8,0)),MIN(G24*(1-$C$5-IF(E24<3,$C$8,0)),F24*(1-$C$6-IF(E24<3,$C$8,0)))),IF(IF(F24<G24*(1-$C$7),G24*(1-$C$5-IF(E24<3,$C$8,0)),MIN(G24*(1-$C$5-IF(E24<3,$C$8,0)),F24*(1-$C$6-IF(E24<3,$C$8,0))))<10,$C$9,IF(IF(F24<G24*(1-$C$7),G24*(1-$C$5-IF(E24<3,$C$8,0)),MIN(G24*(1-$C$5-IF(E24<3,$C$8,0)),F24*(1-$C$6-IF(E24<3,$C$8,0))))<100,$D$9,$E$9)))),ROUND($D24*(1+$C$10),2),FLOOR(IF(F24<G24*(1-$C$7),G24*(1-$C$5-IF(E24<3,$C$8,0)),MIN(G24*(1-$C$5-IF(E24<3,$C$8,0)),F24*(1-$C$6-IF(E24<3,$C$8,0)))),IF(IF(F24<G24*(1-$C$7),G24*(1-$C$5-IF(E24<3,$C$8,0)),MIN(G24*(1-$C$5-IF(E24<3,$C$8,0)),F24*(1-$C$6-IF(E24<3,$C$8,0))))<10,$C$9,IF(IF(F24<G24*(1-$C$7),G24*(1-$C$5-IF(E24<3,$C$8,0)),MIN(G24*(1-$C$5-IF(E24<3,$C$8,0)),F24*(1-$C$6-IF(E24<3,$C$8,0))))<100,$D$9,$E$9))))) -> 25.1 | K24: =IF(ISNUMBER($D24),$D24,"n/a") -> 14.1 | L24: =IF(OR(E24=0,NOT(ISNUMBER($D24))),"—",J24/$D24-1) -> 0.78014184 | M24: =IF(E24=0,"—",J24/F24-1) -> -0.10035842 | N24: =IF(E24=0,"—",J24/G24-1) -> -0.25074627 | O24: =COUNTIFS(Offers!$B$7:$B$3000,$B24,Offers!$C$7:$C$3000,"Germany",Offers!$AI$7:$AI$3000,"yes") -> 10 | P24: =IF(O24=0,"—",SUMIFS(Review!$I$7:$I$600,Review!$B$7:$B$600,$B24,Review!$C$7:$C$600,"Germany")) -> 28.49 | Q24: =IF(O24=0,"—",SUMIFS(Review!$J$7:$J$600,Review!$B$7:$B$600,$B24,Review!$C$7:$C$600,"Germany")) -> 34.275 | R24: =IF(O24=0,"—",SUMIFS(Review!$K$7:$K$600,Review!$B$7:$B$600,$B24,Review!$C$7:$C$600,"Germany")) -> 57.99 | S24: =IF(O24=0,"—",IF(P24<Q24*(1-$C$7),"median (cheapest is an outlier)",IF(P24*(1-$C$6)<Q24*(1-$C$5),"undercut cheapest","median"))) -> median | T24: =IF(O24=0,"—",IF(AND(ISNUMBER($D24),$D24*(1+$C$10)>FLOOR(IF(P24<Q24*(1-$C$7),Q24*(1-$C$5-IF(O24<3,$C$8,0)),MIN(Q24*(1-$C$5-IF(O24<3,$C$8,0)),P24*(1-$C$6-IF(O24<3,$C$8,0)))),IF(IF(P24<Q24*(1-$C$7),Q24*(1-$C$5-IF(O24<3,$C$8,0)),MIN(Q24*(1-$C$5-IF(O24<3,$C$8,0)),P24*(1-$C$6-IF(O24<3,$C$8,0))))<10,$C$9,IF(IF(P24<Q24*(1-$C$7),Q24*(1-$C$5-IF(O24<3,$C$8,0)),MIN(Q24*(1-$C$5-IF(O24<3,$C$8,0)),P24*(1-$C$6-IF(O24<3,$C$8,0))))<100,$D$9,$E$9)))),ROUND($D24*(1+$C$10),2),FLOOR(IF(P24<Q24*(1-$C$7),Q24*(1-$C$5-IF(O24<3,$C$8,0)),MIN(Q24*(1-$C$5-IF(O24<3,$C$8,0)),P24*(1-$C$6-IF(O24<3,$C$8,0)))),IF(IF(P24<Q24*(1-$C$7),Q24*(1-$C$5-IF(O24<3,$C$8,0)),MIN(Q24*(1-$C$5-IF(O24<3,$C$8,0)),P24*(1-$C$6-IF(O24<3,$C$8,0))))<10,$C$9,IF(IF(P24<Q24*(1-$C$7),Q24*(1-$C$5-IF(O24<3,$C$8,0)),MIN(Q24*(1-$C$5-IF(O24<3,$C$8,0)),P24*(1-$C$6-IF(O24<3,$C$8,0))))<100,$D$9,$E$9))))) -> 25.7 | U24: =IF(ISNUMBER($D24),$D24,"n/a") -> 14.1 | V24: =IF(OR(O24=0,NOT(ISNUMBER($D24))),"—",T24/$D24-1) -> 0.82269504 | W24: =IF(O24=0,"—",T24/P24-1) -> -0.097929098 | X24: =IF(O24=0,"—",T24/Q24-1) -> -0.25018235 | Y24: =COUNTIFS(Offers!$B$7:$B$3000,$B24,Offers!$C$7:$C$3000,"Czech",Offers!$AI$7:$AI$3000,"yes") -> 6 | Z24: =IF(Y24=0,"—",SUMIFS(Review!$I$7:$I$600,Review!$B$7:$B$600,$B24,Review!$C$7:$C$600,"Czech")) -> 23.501844 | AA24: =IF(Y24=0,"—",SUMIFS(Review!$J$7:$J$600,Review!$B$7:$B$600,$B24,Review!$C$7:$C$600,"Czech")) -> 40.597592 | AB24: =IF(Y24=0,"—",SUMIFS(Review!$K$7:$K$600,Review!$B$7:$B$600,$B24,Review!$C$7:$C$600,"Czech")) -> 75.289426 | AC24: =IF(Y24=0,"—",IF(Z24<AA24*(1-$C$7),"median (cheapest is an outlier)",IF(Z24*(1-$C$6)<AA24*(1-$C$5),"undercut cheapest","median"))) -> median (cheapest is an outlier) | AD24: =IF(Y24=0,"—",IF(AND(ISNUMBER($D24),$D24*(1+$C$10)>FLOOR(IF(Z24<AA24*(1-$C$7),AA24*(1-$C$5-IF(Y24<3,$C$8,0)),MIN(AA24*(1-$C$5-IF(Y24<3,$C$8,0)),Z24*(1-$C$6-IF(Y24<3,$C$8,0)))),IF(IF(Z24<AA24*(1-$C$7),AA24*(1-$C$5-IF(Y24<3,$C$8,0)),MIN(AA24*(1-$C$5-IF(Y24<3,$C$8,0)),Z24*(1-$C$6-IF(Y24<3,$C$8,0))))<10,$C$9,IF(IF(Z24<AA24*(1-$C$7),AA24*(1-$C$5-IF(Y24<3,$C$8,0)),MIN(AA24*(1-$C$5-IF(Y24<3,$C$8,0)),Z24*(1-$C$6-IF(Y24<3,$C$8,0))))<100,$D$9,$E$9)))),ROUND($D24*(1+$C$10),2),FLOOR(IF(Z24<AA24*(1-$C$7),AA24*(1-$C$5-IF(Y24<3,$C$8,0)),MIN(AA24*(1-$C$5-IF(Y24<3,$C$8,0)),Z24*(1-$C$6-IF(Y24<3,$C$8,0)))),IF(IF(Z24<AA24*(1-$C$7),AA24*(1-$C$5-IF(Y24<3,$C$8,0)),MIN(AA24*(1-$C$5-IF(Y24<3,$C$8,0)),Z24*(1-$C$6-IF(Y24<3,$C$8,0))))<10,$C$9,IF(IF(Z24<AA24*(1-$C$7),AA24*(1-$C$5-IF(Y24<3,$C$8,0)),MIN(AA24*(1-$C$5-IF(Y24<3,$C$8,0)),Z24*(1-$C$6-IF(Y24<3,$C$8,0))))<100,$D$9,$E$9))))) -> 30.4 | AE24: =IF(Y24=0,"—",FLOOR(AD24*Sources!$G$10,1)) -> 742 | AF24: =IF(ISNUMBER($D24),$D24,"n/a") -> 14.1 | AG24: =IF(OR(Y24=0,NOT(ISNUMBER($D24))),"—",AD24/$D24-1) -> 1.1560284 | AH24: =IF(Y24=0,"—",AD24/Z24-1) -> 0.29351552 | AI24: =IF(Y24=0,"—",AD24/AA24-1) -> -0.25118712 | AJ24: =COUNTIFS(Offers!$B$7:$B$3000,$B24,Offers!$C$7:$C$3000,"Slovakia",Offers!$AI$7:$AI$3000,"yes") -> 1 | AK24: =IF(AJ24=0,"—",SUMIFS(Review!$I$7:$I$600,Review!$B$7:$B$600,$B24,Review!$C$7:$C$600,"Slovakia")) -> 32.85 | AL24: =IF(AJ24=0,"—",SUMIFS(Review!$J$7:$J$600,Review!$B$7:$B$600,$B24,Review!$C$7:$C$600,"Slovakia")) -> 32.85 | AM24: =IF(AJ24=0,"—",SUMIFS(Review!$K$7:$K$600,Review!$B$7:$B$600,$B24,Review!$C$7:$C$600,"Slovakia")) -> 32.85 | AN24: =IF(AJ24=0,"—",IF(AK24<AL24*(1-$C$7),"median (cheapest is an outlier)",IF(AK24*(1-$C$6)<AL24*(1-$C$5),"undercut cheapest","median"))) -> median | AO24: =IF(AJ24=0,"—",IF(AND(ISNUMBER($D24),$D24*(1+$C$10)>FLOOR(IF(AK24<AL24*(1-$C$7),AL24*(1-$C$5-IF(AJ24<3,$C$8,0)),MIN(AL24*(1-$C$5-IF(AJ24<3,$C$8,0)),AK24*(1-$C$6-IF(AJ24<3,$C$8,0)))),IF(IF(AK24<AL24*(1-$C$7),AL24*(1-$C$5-IF(AJ24<3,$C$8,0)),MIN(AL24*(1-$C$5-IF(AJ24<3,$C$8,0)),AK24*(1-$C$6-IF(AJ24<3,$C$8,0))))<10,$C$9,IF(IF(AK24<AL24*(1-$C$7),AL24*(1-$C$5-IF(AJ24<3,$C$8,0)),MIN(AL24*(1-$C$5-IF(AJ24<3,$C$8,0)),AK24*(1-$C$6-IF(AJ24<3,$C$8,0))))<100,$D$9,$E$9)))),ROUND($D24*(1+$C$10),2),FLOOR(IF(AK24<AL24*(1-$C$7),AL24*(1-$C$5-IF(AJ24<3,$C$8,0)),MIN(AL24*(1-$C$5-IF(AJ24<3,$C$8,0)),AK24*(1-$C$6-IF(AJ24<3,$C$8,0)))),IF(IF(AK24<AL24*(1-$C$7),AL24*(1-$C$5-IF(AJ24<3,$C$8,0)),MIN(AL24*(1-$C$5-IF(AJ24<3,$C$8,0)),AK24*(1-$C$6-IF(AJ24<3,$C$8,0))))<10,$C$9,IF(IF(AK24<AL24*(1-$C$7),AL24*(1-$C$5-IF(AJ24<3,$C$8,0)),MIN(AL24*(1-$C$5-IF(AJ24<3,$C$8,0)),AK24*(1-$C$6-IF(AJ24<3,$C$8,0))))<100,$D$9,$E$9))))) -> 22.9 | AP24: =IF(ISNUMBER($D24),$D24,"n/a") -> 14.1 | AQ24: =IF(OR(AJ24=0,NOT(ISNUMBER($D24))),"—",AO24/$D24-1) -> 0.62411348 | AR24: =IF(AJ24=0,"—",AO24/AK24-1) -> -0.30289193 | AS24: =IF(AJ24=0,"—",AO24/AL24-1) -> -0.30289193 | AT24: =COUNTIFS(Offers!$B$7:$B$3000,$B24,Offers!$C$7:$C$3000,"Romania",Offers!$AI$7:$AI$3000,"yes") -> 0 | AU24: =IF(AT24=0,"—",SUMIFS(Review!$I$7:$I$600,Review!$B$7:$B$600,$B24,Review!$C$7:$C$600,"Romania")) -> — | AV24: =IF(AT24=0,"—",SUMIFS(Review!$J$7:$J$600,Review!$B$7:$B$600,$B24,Review!$C$7:$C$600,"Romania")) -> — | AW24: =IF(AT24=0,"—",SUMIFS(Review!$K$7:$K$600,Review!$B$7:$B$600,$B24,Review!$C$7:$C$600,"Romania")) -> — | AX24: =IF(AT24=0,"—",IF(AU24<AV24*(1-$C$7),"median (cheapest is an outlier)",IF(AU24*(1-$C$6)<AV24*(1-$C$5),"undercut cheapest","median"))) -> — | AY24: =IF(AT24=0,"—",IF(AND(ISNUMBER($D24),$D24*(1+$C$10)>FLOOR(IF(AU24<AV24*(1-$C$7),AV24*(1-$C$5-IF(AT24<3,$C$8,0)),MIN(AV24*(1-$C$5-IF(AT24<3,$C$8,0)),AU24*(1-$C$6-IF(AT24<3,$C$8,0)))),IF(IF(AU24<AV24*(1-$C$7),AV24*(1-$C$5-IF(AT24<3,$C$8,0)),MIN(AV24*(1-$C$5-IF(AT24<3,$C$8,0)),AU24*(1-$C$6-IF(AT24<3,$C$8,0))))<10,$C$9,IF(IF(AU24<AV24*(1-$C$7),AV24*(1-$C$5-IF(AT24<3,$C$8,0)),MIN(AV24*(1-$C$5-IF(AT24<3,$C$8,0)),AU24*(1-$C$6-IF(AT24<3,$C$8,0))))<100,$D$9,$E$9)))),ROUND($D24*(1+$C$10),2),FLOOR(IF(AU24<AV24*(1-$C$7),AV24*(1-$C$5-IF(AT24<3,$C$8,0)),MIN(AV24*(1-$C$5-IF(AT24<3,$C$8,0)),AU24*(1-$C$6-IF(AT24<3,$C$8,0)))),IF(IF(AU24<AV24*(1-$C$7),AV24*(1-$C$5-IF(AT24<3,$C$8,0)),MIN(AV24*(1-$C$5-IF(AT24<3,$C$8,0)),AU24*(1-$C$6-IF(AT24<3,$C$8,0))))<10,$C$9,IF(IF(AU24<AV24*(1-$C$7),AV24*(1-$C$5-IF(AT24<3,$C$8,0)),MIN(AV24*(1-$C$5-IF(AT24<3,$C$8,0)),AU24*(1-$C$6-IF(AT24<3,$C$8,0))))<100,$D$9,$E$9))))) -> — | AZ24: =IF(AT24=0,"—",FLOOR(AY24*Sources!$G$9,0.1)) -> — | BA24: =IF(ISNUMBER($D24),$D24,"n/a") -> 14.1 | BB24: =IF(OR(AT24=0,NOT(ISNUMBER($D24))),"—",AY24/$D24-1) -> — | BC24: =IF(AT24=0,"—",AY24/AU24-1) -> — | BD24: =IF(AT24=0,"—",AY24/AV24-1) -> — | BE24: =COUNTIFS(Offers!$B$7:$B$3000,$B24,Offers!$C$7:$C$3000,"Hungary",Offers!$AI$7:$AI$3000,"yes") -> 0 | BF24: =IF(BE24=0,"—",SUMIFS(Review!$I$7:$I$600,Review!$B$7:$B$600,$B24,Review!$C$7:$C$600,"Hungary")) -> — | BG24: =IF(BE24=0,"—",SUMIFS(Review!$J$7:$J$600,Review!$B$7:$B$600,$B24,Review!$C$7:$C$600,"Hungary")) -> — | BH24: =IF(BE24=0,"—",SUMIFS(Review!$K$7:$K$600,Review!$B$7:$B$600,$B24,Review!$C$7:$C$600,"Hungary")) -> — | BI24: =IF(BE24=0,"—",IF(BF24<BG24*(1-$C$7),"median (cheapest is an outlier)",IF(BF24*(1-$C$6)<BG24*(1-$C$5),"undercut cheapest","median"))) -> — | BJ24: =IF(BE24=0,"—",IF(AND(ISNUMBER($D24),$D24*(1+$C$10)>FLOOR(IF(BF24<BG24*(1-$C$7),BG24*(1-$C$5-IF(BE24<3,$C$8,0)),MIN(BG24*(1-$C$5-IF(BE24<3,$C$8,0)),BF24*(1-$C$6-IF(BE24<3,$C$8,0)))),IF(IF(BF24<BG24*(1-$C$7),BG24*(1-$C$5-IF(BE24<3,$C$8,0)),MIN(BG24*(1-$C$5-IF(BE24<3,$C$8,0)),BF24*(1-$C$6-IF(BE24<3,$C$8,0))))<10,$C$9,IF(IF(BF24<BG24*(1-$C$7),BG24*(1-$C$5-IF(BE24<3,$C$8,0)),MIN(BG24*(1-$C$5-IF(BE24<3,$C$8,0)),BF24*(1-$C$6-IF(BE24<3,$C$8,0))))<100,$D$9,$E$9)))),ROUND($D24*(1+$C$10),2),FLOOR(IF(BF24<BG24*(1-$C$7),BG24*(1-$C$5-IF(BE24<3,$C$8,0)),MIN(BG24*(1-$C$5-IF(BE24<3,$C$8,0)),BF24*(1-$C$6-IF(BE24<3,$C$8,0)))),IF(IF(BF24<BG24*(1-$C$7),BG24*(1-$C$5-IF(BE24<3,$C$8,0)),MIN(BG24*(1-$C$5-IF(BE24<3,$C$8,0)),BF24*(1-$C$6-IF(BE24<3,$C$8,0))))<10,$C$9,IF(IF(BF24<BG24*(1-$C$7),BG24*(1-$C$5-IF(BE24<3,$C$8,0)),MIN(BG24*(1-$C$5-IF(BE24<3,$C$8,0)),BF24*(1-$C$6-IF(BE24<3,$C$8,0))))<100,$D$9,$E$9))))) -> — | BK24: =IF(BE24=0,"—",FLOOR(BJ24*Sources!$G$8,10)) -> — | BL24: =IF(ISNUMBER($D24),$D24,"n/a") -> 14.1 | BM24: =IF(OR(BE24=0,NOT(ISNUMBER($D24))),"—",BJ24/$D24-1) -> — | BN24: =IF(BE24=0,"—",BJ24/BF24-1) -> — | BO24: =IF(BE24=0,"—",BJ24/BG24-1) -> —
B25: PE cutting board 300 × 200 × 10 mm | C25: PE-30201/W | D25: 1.75 | E25: =COUNTIFS(Offers!$B$7:$B$3000,$B25,Offers!$C$7:$C$3000,"Austria",Offers!$AI$7:$AI$3000,"yes") -> 4 | F25: =IF(E25=0,"—",SUMIFS(Review!$I$7:$I$600,Review!$B$7:$B$600,$B25,Review!$C$7:$C$600,"Austria")) -> 7.41 | G25: =IF(E25=0,"—",SUMIFS(Review!$J$7:$J$600,Review!$B$7:$B$600,$B25,Review!$C$7:$C$600,"Austria")) -> 8.12 | H25: =IF(E25=0,"—",SUMIFS(Review!$K$7:$K$600,Review!$B$7:$B$600,$B25,Review!$C$7:$C$600,"Austria")) -> 15.76 | I25: =IF(E25=0,"—",IF(F25<G25*(1-$C$7),"median (cheapest is an outlier)",IF(F25*(1-$C$6)<G25*(1-$C$5),"undercut cheapest","median"))) -> median | J25: =IF(E25=0,"—",IF(AND(ISNUMBER($D25),$D25*(1+$C$10)>FLOOR(IF(F25<G25*(1-$C$7),G25*(1-$C$5-IF(E25<3,$C$8,0)),MIN(G25*(1-$C$5-IF(E25<3,$C$8,0)),F25*(1-$C$6-IF(E25<3,$C$8,0)))),IF(IF(F25<G25*(1-$C$7),G25*(1-$C$5-IF(E25<3,$C$8,0)),MIN(G25*(1-$C$5-IF(E25<3,$C$8,0)),F25*(1-$C$6-IF(E25<3,$C$8,0))))<10,$C$9,IF(IF(F25<G25*(1-$C$7),G25*(1-$C$5-IF(E25<3,$C$8,0)),MIN(G25*(1-$C$5-IF(E25<3,$C$8,0)),F25*(1-$C$6-IF(E25<3,$C$8,0))))<100,$D$9,$E$9)))),ROUND($D25*(1+$C$10),2),FLOOR(IF(F25<G25*(1-$C$7),G25*(1-$C$5-IF(E25<3,$C$8,0)),MIN(G25*(1-$C$5-IF(E25<3,$C$8,0)),F25*(1-$C$6-IF(E25<3,$C$8,0)))),IF(IF(F25<G25*(1-$C$7),G25*(1-$C$5-IF(E25<3,$C$8,0)),MIN(G25*(1-$C$5-IF(E25<3,$C$8,0)),F25*(1-$C$6-IF(E25<3,$C$8,0))))<10,$C$9,IF(IF(F25<G25*(1-$C$7),G25*(1-$C$5-IF(E25<3,$C$8,0)),MIN(G25*(1-$C$5-IF(E25<3,$C$8,0)),F25*(1-$C$6-IF(E25<3,$C$8,0))))<100,$D$9,$E$9))))) -> 6.05 | K25: =IF(ISNUMBER($D25),$D25,"n/a") -> 1.75 | L25: =IF(OR(E25=0,NOT(ISNUMBER($D25))),"—",J25/$D25-1) -> 2.4571429 | M25: =IF(E25=0,"—",J25/F25-1) -> -0.18353576 | N25: =IF(E25=0,"—",J25/G25-1) -> -0.25492611 | O25: =COUNTIFS(Offers!$B$7:$B$3000,$B25,Offers!$C$7:$C$3000,"Germany",Offers!$AI$7:$AI$3000,"yes") -> 5 | P25: =IF(O25=0,"—",SUMIFS(Review!$I$7:$I$600,Review!$B$7:$B$600,$B25,Review!$C$7:$C$600,"Germany")) -> 4.89 | Q25: =IF(O25=0,"—",SUMIFS(Review!$J$7:$J$600,Review!$B$7:$B$600,$B25,Review!$C$7:$C$600,"Germany")) -> 7.96 | R25: =IF(O25=0,"—",SUMIFS(Review!$K$7:$K$600,Review!$B$7:$B$600,$B25,Review!$C$7:$C$600,"Germany")) -> 15.76 | S25: =IF(O25=0,"—",IF(P25<Q25*(1-$C$7),"median (cheapest is an outlier)",IF(P25*(1-$C$6)<Q25*(1-$C$5),"undercut cheapest","median"))) -> median (cheapest is an outlier) | T25: =IF(O25=0,"—",IF(AND(ISNUMBER($D25),$D25*(1+$C$10)>FLOOR(IF(P25<Q25*(1-$C$7),Q25*(1-$C$5-IF(O25<3,$C$8,0)),MIN(Q25*(1-$C$5-IF(O25<3,$C$8,0)),P25*(1-$C$6-IF(O25<3,$C$8,0)))),IF(IF(P25<Q25*(1-$C$7),Q25*(1-$C$5-IF(O25<3,$C$8,0)),MIN(Q25*(1-$C$5-IF(O25<3,$C$8,0)),P25*(1-$C$6-IF(O25<3,$C$8,0))))<10,$C$9,IF(IF(P25<Q25*(1-$C$7),Q25*(1-$C$5-IF(O25<3,$C$8,0)),MIN(Q25*(1-$C$5-IF(O25<3,$C$8,0)),P25*(1-$C$6-IF(O25<3,$C$8,0))))<100,$D$9,$E$9)))),ROUND($D25*(1+$C$10),2),FLOOR(IF(P25<Q25*(1-$C$7),Q25*(1-$C$5-IF(O25<3,$C$8,0)),MIN(Q25*(1-$C$5-IF(O25<3,$C$8,0)),P25*(1-$C$6-IF(O25<3,$C$8,0)))),IF(IF(P25<Q25*(1-$C$7),Q25*(1-$C$5-IF(O25<3,$C$8,0)),MIN(Q25*(1-$C$5-IF(O25<3,$C$8,0)),P25*(1-$C$6-IF(O25<3,$C$8,0))))<10,$C$9,IF(IF(P25<Q25*(1-$C$7),Q25*(1-$C$5-IF(O25<3,$C$8,0)),MIN(Q25*(1-$C$5-IF(O25<3,$C$8,0)),P25*(1-$C$6-IF(O25<3,$C$8,0))))<100,$D$9,$E$9))))) -> 5.95 | U25: =IF(ISNUMBER($D25),$D25,"n/a") -> 1.75 | V25: =IF(OR(O25=0,NOT(ISNUMBER($D25))),"—",T25/$D25-1) -> 2.4 | W25: =IF(O25=0,"—",T25/P25-1) -> 0.21676892 | X25: =IF(O25=0,"—",T25/Q25-1) -> -0.25251256 | Y25: =COUNTIFS(Offers!$B$7:$B$3000,$B25,Offers!$C$7:$C$3000,"Czech",Offers!$AI$7:$AI$3000,"yes") -> 4 | Z25: =IF(Y25=0,"—",SUMIFS(Review!$I$7:$I$600,Review!$B$7:$B$600,$B25,Review!$C$7:$C$600,"Czech")) -> 3.891316 | AA25: =IF(Y25=0,"—",SUMIFS(Review!$J$7:$J$600,Review!$B$7:$B$600,$B25,Review!$C$7:$C$600,"Czech")) -> 6.35123 | AB25: =IF(Y25=0,"—",SUMIFS(Review!$K$7:$K$600,Review!$B$7:$B$600,$B25,Review!$C$7:$C$600,"Czech")) -> 8.393516 | AC25: =IF(Y25=0,"—",IF(Z25<AA25*(1-$C$7),"median (cheapest is an outlier)",IF(Z25*(1-$C$6)<AA25*(1-$C$5),"undercut cheapest","median"))) -> median (cheapest is an outlier) | AD25: =IF(Y25=0,"—",IF(AND(ISNUMBER($D25),$D25*(1+$C$10)>FLOOR(IF(Z25<AA25*(1-$C$7),AA25*(1-$C$5-IF(Y25<3,$C$8,0)),MIN(AA25*(1-$C$5-IF(Y25<3,$C$8,0)),Z25*(1-$C$6-IF(Y25<3,$C$8,0)))),IF(IF(Z25<AA25*(1-$C$7),AA25*(1-$C$5-IF(Y25<3,$C$8,0)),MIN(AA25*(1-$C$5-IF(Y25<3,$C$8,0)),Z25*(1-$C$6-IF(Y25<3,$C$8,0))))<10,$C$9,IF(IF(Z25<AA25*(1-$C$7),AA25*(1-$C$5-IF(Y25<3,$C$8,0)),MIN(AA25*(1-$C$5-IF(Y25<3,$C$8,0)),Z25*(1-$C$6-IF(Y25<3,$C$8,0))))<100,$D$9,$E$9)))),ROUND($D25*(1+$C$10),2),FLOOR(IF(Z25<AA25*(1-$C$7),AA25*(1-$C$5-IF(Y25<3,$C$8,0)),MIN(AA25*(1-$C$5-IF(Y25<3,$C$8,0)),Z25*(1-$C$6-IF(Y25<3,$C$8,0)))),IF(IF(Z25<AA25*(1-$C$7),AA25*(1-$C$5-IF(Y25<3,$C$8,0)),MIN(AA25*(1-$C$5-IF(Y25<3,$C$8,0)),Z25*(1-$C$6-IF(Y25<3,$C$8,0))))<10,$C$9,IF(IF(Z25<AA25*(1-$C$7),AA25*(1-$C$5-IF(Y25<3,$C$8,0)),MIN(AA25*(1-$C$5-IF(Y25<3,$C$8,0)),Z25*(1-$C$6-IF(Y25<3,$C$8,0))))<100,$D$9,$E$9))))) -> 4.75 | AE25: =IF(Y25=0,"—",FLOOR(AD25*Sources!$G$10,1)) -> 116 | AF25: =IF(ISNUMBER($D25),$D25,"n/a") -> 1.75 | AG25: =IF(OR(Y25=0,NOT(ISNUMBER($D25))),"—",AD25/$D25-1) -> 1.7142857 | AH25: =IF(Y25=0,"—",AD25/Z25-1) -> 0.22066674 | AI25: =IF(Y25=0,"—",AD25/AA25-1) -> -0.25211337 | AJ25: =COUNTIFS(Offers!$B$7:$B$3000,$B25,Offers!$C$7:$C$3000,"Slovakia",Offers!$AI$7:$AI$3000,"yes") -> 2 | AK25: =IF(AJ25=0,"—",SUMIFS(Review!$I$7:$I$600,Review!$B$7:$B$600,$B25,Review!$C$7:$C$600,"Slovakia")) -> 6.18 | AL25: =IF(AJ25=0,"—",SUMIFS(Review!$J$7:$J$600,Review!$B$7:$B$600,$B25,Review!$C$7:$C$600,"Slovakia")) -> 6.59 | AM25: =IF(AJ25=0,"—",SUMIFS(Review!$K$7:$K$600,Review!$B$7:$B$600,$B25,Review!$C$7:$C$600,"Slovakia")) -> 7 | AN25: =IF(AJ25=0,"—",IF(AK25<AL25*(1-$C$7),"median (cheapest is an outlier)",IF(AK25*(1-$C$6)<AL25*(1-$C$5),"undercut cheapest","median"))) -> median | AO25: =IF(AJ25=0,"—",IF(AND(ISNUMBER($D25),$D25*(1+$C$10)>FLOOR(IF(AK25<AL25*(1-$C$7),AL25*(1-$C$5-IF(AJ25<3,$C$8,0)),MIN(AL25*(1-$C$5-IF(AJ25<3,$C$8,0)),AK25*(1-$C$6-IF(AJ25<3,$C$8,0)))),IF(IF(AK25<AL25*(1-$C$7),AL25*(1-$C$5-IF(AJ25<3,$C$8,0)),MIN(AL25*(1-$C$5-IF(AJ25<3,$C$8,0)),AK25*(1-$C$6-IF(AJ25<3,$C$8,0))))<10,$C$9,IF(IF(AK25<AL25*(1-$C$7),AL25*(1-$C$5-IF(AJ25<3,$C$8,0)),MIN(AL25*(1-$C$5-IF(AJ25<3,$C$8,0)),AK25*(1-$C$6-IF(AJ25<3,$C$8,0))))<100,$D$9,$E$9)))),ROUND($D25*(1+$C$10),2),FLOOR(IF(AK25<AL25*(1-$C$7),AL25*(1-$C$5-IF(AJ25<3,$C$8,0)),MIN(AL25*(1-$C$5-IF(AJ25<3,$C$8,0)),AK25*(1-$C$6-IF(AJ25<3,$C$8,0)))),IF(IF(AK25<AL25*(1-$C$7),AL25*(1-$C$5-IF(AJ25<3,$C$8,0)),MIN(AL25*(1-$C$5-IF(AJ25<3,$C$8,0)),AK25*(1-$C$6-IF(AJ25<3,$C$8,0))))<10,$C$9,IF(IF(AK25<AL25*(1-$C$7),AL25*(1-$C$5-IF(AJ25<3,$C$8,0)),MIN(AL25*(1-$C$5-IF(AJ25<3,$C$8,0)),AK25*(1-$C$6-IF(AJ25<3,$C$8,0))))<100,$D$9,$E$9))))) -> 4.6 | AP25: =IF(ISNUMBER($D25),$D25,"n/a") -> 1.75 | AQ25: =IF(OR(AJ25=0,NOT(ISNUMBER($D25))),"—",AO25/$D25-1) -> 1.6285714 | AR25: =IF(AJ25=0,"—",AO25/AK25-1) -> -0.25566343 | AS25: =IF(AJ25=0,"—",AO25/AL25-1) -> -0.30197269 | AT25: =COUNTIFS(Offers!$B$7:$B$3000,$B25,Offers!$C$7:$C$3000,"Romania",Offers!$AI$7:$AI$3000,"yes") -> 0 | AU25: =IF(AT25=0,"—",SUMIFS(Review!$I$7:$I$600,Review!$B$7:$B$600,$B25,Review!$C$7:$C$600,"Romania")) -> — | AV25: =IF(AT25=0,"—",SUMIFS(Review!$J$7:$J$600,Review!$B$7:$B$600,$B25,Review!$C$7:$C$600,"Romania")) -> — | AW25: =IF(AT25=0,"—",SUMIFS(Review!$K$7:$K$600,Review!$B$7:$B$600,$B25,Review!$C$7:$C$600,"Romania")) -> — | AX25: =IF(AT25=0,"—",IF(AU25<AV25*(1-$C$7),"median (cheapest is an outlier)",IF(AU25*(1-$C$6)<AV25*(1-$C$5),"undercut cheapest","median"))) -> — | AY25: =IF(AT25=0,"—",IF(AND(ISNUMBER($D25),$D25*(1+$C$10)>FLOOR(IF(AU25<AV25*(1-$C$7),AV25*(1-$C$5-IF(AT25<3,$C$8,0)),MIN(AV25*(1-$C$5-IF(AT25<3,$C$8,0)),AU25*(1-$C$6-IF(AT25<3,$C$8,0)))),IF(IF(AU25<AV25*(1-$C$7),AV25*(1-$C$5-IF(AT25<3,$C$8,0)),MIN(AV25*(1-$C$5-IF(AT25<3,$C$8,0)),AU25*(1-$C$6-IF(AT25<3,$C$8,0))))<10,$C$9,IF(IF(AU25<AV25*(1-$C$7),AV25*(1-$C$5-IF(AT25<3,$C$8,0)),MIN(AV25*(1-$C$5-IF(AT25<3,$C$8,0)),AU25*(1-$C$6-IF(AT25<3,$C$8,0))))<100,$D$9,$E$9)))),ROUND($D25*(1+$C$10),2),FLOOR(IF(AU25<AV25*(1-$C$7),AV25*(1-$C$5-IF(AT25<3,$C$8,0)),MIN(AV25*(1-$C$5-IF(AT25<3,$C$8,0)),AU25*(1-$C$6-IF(AT25<3,$C$8,0)))),IF(IF(AU25<AV25*(1-$C$7),AV25*(1-$C$5-IF(AT25<3,$C$8,0)),MIN(AV25*(1-$C$5-IF(AT25<3,$C$8,0)),AU25*(1-$C$6-IF(AT25<3,$C$8,0))))<10,$C$9,IF(IF(AU25<AV25*(1-$C$7),AV25*(1-$C$5-IF(AT25<3,$C$8,0)),MIN(AV25*(1-$C$5-IF(AT25<3,$C$8,0)),AU25*(1-$C$6-IF(AT25<3,$C$8,0))))<100,$D$9,$E$9))))) -> — | AZ25: =IF(AT25=0,"—",FLOOR(AY25*Sources!$G$9,0.1)) -> — | BA25: =IF(ISNUMBER($D25),$D25,"n/a") -> 1.75 | BB25: =IF(OR(AT25=0,NOT(ISNUMBER($D25))),"—",AY25/$D25-1) -> — | BC25: =IF(AT25=0,"—",AY25/AU25-1) -> — | BD25: =IF(AT25=0,"—",AY25/AV25-1) -> — | BE25: =COUNTIFS(Offers!$B$7:$B$3000,$B25,Offers!$C$7:$C$3000,"Hungary",Offers!$AI$7:$AI$3000,"yes") -> 0 | BF25: =IF(BE25=0,"—",SUMIFS(Review!$I$7:$I$600,Review!$B$7:$B$600,$B25,Review!$C$7:$C$600,"Hungary")) -> — | BG25: =IF(BE25=0,"—",SUMIFS(Review!$J$7:$J$600,Review!$B$7:$B$600,$B25,Review!$C$7:$C$600,"Hungary")) -> — | BH25: =IF(BE25=0,"—",SUMIFS(Review!$K$7:$K$600,Review!$B$7:$B$600,$B25,Review!$C$7:$C$600,"Hungary")) -> — | BI25: =IF(BE25=0,"—",IF(BF25<BG25*(1-$C$7),"median (cheapest is an outlier)",IF(BF25*(1-$C$6)<BG25*(1-$C$5),"undercut cheapest","median"))) -> — | BJ25: =IF(BE25=0,"—",IF(AND(ISNUMBER($D25),$D25*(1+$C$10)>FLOOR(IF(BF25<BG25*(1-$C$7),BG25*(1-$C$5-IF(BE25<3,$C$8,0)),MIN(BG25*(1-$C$5-IF(BE25<3,$C$8,0)),BF25*(1-$C$6-IF(BE25<3,$C$8,0)))),IF(IF(BF25<BG25*(1-$C$7),BG25*(1-$C$5-IF(BE25<3,$C$8,0)),MIN(BG25*(1-$C$5-IF(BE25<3,$C$8,0)),BF25*(1-$C$6-IF(BE25<3,$C$8,0))))<10,$C$9,IF(IF(BF25<BG25*(1-$C$7),BG25*(1-$C$5-IF(BE25<3,$C$8,0)),MIN(BG25*(1-$C$5-IF(BE25<3,$C$8,0)),BF25*(1-$C$6-IF(BE25<3,$C$8,0))))<100,$D$9,$E$9)))),ROUND($D25*(1+$C$10),2),FLOOR(IF(BF25<BG25*(1-$C$7),BG25*(1-$C$5-IF(BE25<3,$C$8,0)),MIN(BG25*(1-$C$5-IF(BE25<3,$C$8,0)),BF25*(1-$C$6-IF(BE25<3,$C$8,0)))),IF(IF(BF25<BG25*(1-$C$7),BG25*(1-$C$5-IF(BE25<3,$C$8,0)),MIN(BG25*(1-$C$5-IF(BE25<3,$C$8,0)),BF25*(1-$C$6-IF(BE25<3,$C$8,0))))<10,$C$9,IF(IF(BF25<BG25*(1-$C$7),BG25*(1-$C$5-IF(BE25<3,$C$8,0)),MIN(BG25*(1-$C$5-IF(BE25<3,$C$8,0)),BF25*(1-$C$6-IF(BE25<3,$C$8,0))))<100,$D$9,$E$9))))) -> — | BK25: =IF(BE25=0,"—",FLOOR(BJ25*Sources!$G$8,10)) -> — | BL25: =IF(ISNUMBER($D25),$D25,"n/a") -> 1.75 | BM25: =IF(OR(BE25=0,NOT(ISNUMBER($D25))),"—",BJ25/$D25-1) -> — | BN25: =IF(BE25=0,"—",BJ25/BF25-1) -> — | BO25: =IF(BE25=0,"—",BJ25/BG25-1) -> —
