Workbook

Sheet Compare
B2: YES Gastro market comparison
B3: Original benchmark basket plus Austria and Czechia additions. Net prices per piece.
B5: Statistic | C5: Median | D5: View | E5: Net per piece EUR | G5: Match | H5: EXACT + CLOSE | J5: Product detail
J6: GN 1/1 PC container, 65 mm
B7: =IF(E5="Local prices","Local net prices per piece. Currency differs by country.","EUR net prices per piece. Erste Bank mid-rates published 30 Sep 2026 at 18:00 CEST.")
B8: A dash means no qualifying price. Green marks the lowest available EUR price for each product.
J9: Net price per piece in EUR
B10: Product | C10: Hungary | D10: Romania | E10: Austria | F10: Germany | G10: Czech | H10: Slovakia
C11: =IF($E$5="Local prices","HUF net/pc","EUR net/pc") | D11: =IF($E$5="Local prices","RON net/pc","EUR net/pc") | E11: =IF($E$5="Local prices","EUR net/pc","EUR net/pc") | F11: =IF($E$5="Local prices","EUR net/pc","EUR net/pc") | G11: =IF($E$5="Local prices","CZK net/pc","EUR net/pc") | H11: =IF($E$5="Local prices","EUR net/pc","EUR net/pc") | J11: Market | K11: Minimum | L11: Median | M11: Maximum
B12: GN 1/1 PC container, 65 mm | C12: =IF(IF($E$5="Local prices",COUNTIFS('Offers'!$B$7:$B$608,$B12,'Offers'!$C$7:$C$608,C$10,'Offers'!$AH$7:$AH$608,"yes"),COUNTIFS('Offers'!$B$7:$B$608,$B12,'Offers'!$C$7:$C$608,C$10,'Offers'!$AI$7:$AI$608,"yes"))=0,"—",SUMIFS('Review'!$O$7:$O$210,'Review'!$B$7:$B$210,$B12,'Review'!$C$7:$C$210,C$10)) | D12: =IF(IF($E$5="Local prices",COUNTIFS('Offers'!$B$7:$B$608,$B12,'Offers'!$C$7:$C$608,D$10,'Offers'!$AH$7:$AH$608,"yes"),COUNTIFS('Offers'!$B$7:$B$608,$B12,'Offers'!$C$7:$C$608,D$10,'Offers'!$AI$7:$AI$608,"yes"))=0,"—",SUMIFS('Review'!$O$7:$O$210,'Review'!$B$7:$B$210,$B12,'Review'!$C$7:$C$210,D$10)) | E12: =IF(IF($E$5="Local prices",COUNTIFS('Offers'!$B$7:$B$608,$B12,'Offers'!$C$7:$C$608,E$10,'Offers'!$AH$7:$AH$608,"yes"),COUNTIFS('Offers'!$B$7:$B$608,$B12,'Offers'!$C$7:$C$608,E$10,'Offers'!$AI$7:$AI$608,"yes"))=0,"—",SUMIFS('Review'!$O$7:$O$210,'Review'!$B$7:$B$210,$B12,'Review'!$C$7:$C$210,E$10)) | F12: =IF(IF($E$5="Local prices",COUNTIFS('Offers'!$B$7:$B$608,$B12,'Offers'!$C$7:$C$608,F$10,'Offers'!$AH$7:$AH$608,"yes"),COUNTIFS('Offers'!$B$7:$B$608,$B12,'Offers'!$C$7:$C$608,F$10,'Offers'!$AI$7:$AI$608,"yes"))=0,"—",SUMIFS('Review'!$O$7:$O$210,'Review'!$B$7:$B$210,$B12,'Review'!$C$7:$C$210,F$10)) | G12: =IF(IF($E$5="Local prices",COUNTIFS('Offers'!$B$7:$B$608,$B12,'Offers'!$C$7:$C$608,G$10,'Offers'!$AH$7:$AH$608,"yes"),COUNTIFS('Offers'!$B$7:$B$608,$B12,'Offers'!$C$7:$C$608,G$10,'Offers'!$AI$7:$AI$608,"yes"))=0,"—",SUMIFS('Review'!$O$7:$O$210,'Review'!$B$7:$B$210,$B12,'Review'!$C$7:$C$210,G$10)) | H12: =IF(IF($E$5="Local prices",COUNTIFS('Offers'!$B$7:$B$608,$B12,'Offers'!$C$7:$C$608,H$10,'Offers'!$AH$7:$AH$608,"yes"),COUNTIFS('Offers'!$B$7:$B$608,$B12,'Offers'!$C$7:$C$608,H$10,'Offers'!$AI$7:$AI$608,"yes"))=0,"—",SUMIFS('Review'!$O$7:$O$210,'Review'!$B$7:$B$210,$B12,'Review'!$C$7:$C$210,H$10)) | J12: Hungary | K12: =IF(COUNTIFS('Offers'!$B$7:$B$608,$J$6,'Offers'!$C$7:$C$608,$J12,'Offers'!$AI$7:$AI$608,"yes")=0,"—",SUMIFS('Review'!$I$7:$I$210,'Review'!$B$7:$B$210,$J$6,'Review'!$C$7:$C$210,$J12)) | L12: =IF(COUNTIFS('Offers'!$B$7:$B$608,$J$6,'Offers'!$C$7:$C$608,$J12,'Offers'!$AI$7:$AI$608,"yes")=0,"—",SUMIFS('Review'!$J$7:$J$210,'Review'!$B$7:$B$210,$J$6,'Review'!$C$7:$C$210,$J12)) | M12: =IF(COUNTIFS('Offers'!$B$7:$B$608,$J$6,'Offers'!$C$7:$C$608,$J12,'Offers'!$AI$7:$AI$608,"yes")=0,"—",SUMIFS('Review'!$K$7:$K$210,'Review'!$B$7:$B$210,$J$6,'Review'!$C$7:$C$210,$J12))
B13: GN 1/2 PC container, 150 mm | C13: =IF(IF($E$5="Local prices",COUNTIFS('Offers'!$B$7:$B$608,$B13,'Offers'!$C$7:$C$608,C$10,'Offers'!$AH$7:$AH$608,"yes"),COUNTIFS('Offers'!$B$7:$B$608,$B13,'Offers'!$C$7:$C$608,C$10,'Offers'!$AI$7:$AI$608,"yes"))=0,"—",SUMIFS('Review'!$O$7:$O$210,'Review'!$B$7:$B$210,$B13,'Review'!$C$7:$C$210,C$10)) | D13: =IF(IF($E$5="Local prices",COUNTIFS('Offers'!$B$7:$B$608,$B13,'Offers'!$C$7:$C$608,D$10,'Offers'!$AH$7:$AH$608,"yes"),COUNTIFS('Offers'!$B$7:$B$608,$B13,'Offers'!$C$7:$C$608,D$10,'Offers'!$AI$7:$AI$608,"yes"))=0,"—",SUMIFS('Review'!$O$7:$O$210,'Review'!$B$7:$B$210,$B13,'Review'!$C$7:$C$210,D$10)) | E13: =IF(IF($E$5="Local prices",COUNTIFS('Offers'!$B$7:$B$608,$B13,'Offers'!$C$7:$C$608,E$10,'Offers'!$AH$7:$AH$608,"yes"),COUNTIFS('Offers'!$B$7:$B$608,$B13,'Offers'!$C$7:$C$608,E$10,'Offers'!$AI$7:$AI$608,"yes"))=0,"—",SUMIFS('Review'!$O$7:$O$210,'Review'!$B$7:$B$210,$B13,'Review'!$C$7:$C$210,E$10)) | F13: =IF(IF($E$5="Local prices",COUNTIFS('Offers'!$B$7:$B$608,$B13,'Offers'!$C$7:$C$608,F$10,'Offers'!$AH$7:$AH$608,"yes"),COUNTIFS('Offers'!$B$7:$B$608,$B13,'Offers'!$C$7:$C$608,F$10,'Offers'!$AI$7:$AI$608,"yes"))=0,"—",SUMIFS('Review'!$O$7:$O$210,'Review'!$B$7:$B$210,$B13,'Review'!$C$7:$C$210,F$10)) | G13: =IF(IF($E$5="Local prices",COUNTIFS('Offers'!$B$7:$B$608,$B13,'Offers'!$C$7:$C$608,G$10,'Offers'!$AH$7:$AH$608,"yes"),COUNTIFS('Offers'!$B$7:$B$608,$B13,'Offers'!$C$7:$C$608,G$10,'Offers'!$AI$7:$AI$608,"yes"))=0,"—",SUMIFS('Review'!$O$7:$O$210,'Review'!$B$7:$B$210,$B13,'Review'!$C$7:$C$210,G$10)) | H13: =IF(IF($E$5="Local prices",COUNTIFS('Offers'!$B$7:$B$608,$B13,'Offers'!$C$7:$C$608,H$10,'Offers'!$AH$7:$AH$608,"yes"),COUNTIFS('Offers'!$B$7:$B$608,$B13,'Offers'!$C$7:$C$608,H$10,'Offers'!$AI$7:$AI$608,"yes"))=0,"—",SUMIFS('Review'!$O$7:$O$210,'Review'!$B$7:$B$210,$B13,'Review'!$C$7:$C$210,H$10)) | J13: Romania | K13: =IF(COUNTIFS('Offers'!$B$7:$B$608,$J$6,'Offers'!$C$7:$C$608,$J13,'Offers'!$AI$7:$AI$608,"yes")=0,"—",SUMIFS('Review'!$I$7:$I$210,'Review'!$B$7:$B$210,$J$6,'Review'!$C$7:$C$210,$J13)) | L13: =IF(COUNTIFS('Offers'!$B$7:$B$608,$J$6,'Offers'!$C$7:$C$608,$J13,'Offers'!$AI$7:$AI$608,"yes")=0,"—",SUMIFS('Review'!$J$7:$J$210,'Review'!$B$7:$B$210,$J$6,'Review'!$C$7:$C$210,$J13)) | M13: =IF(COUNTIFS('Offers'!$B$7:$B$608,$J$6,'Offers'!$C$7:$C$608,$J13,'Offers'!$AI$7:$AI$608,"yes")=0,"—",SUMIFS('Review'!$K$7:$K$210,'Review'!$B$7:$B$210,$J$6,'Review'!$C$7:$C$210,$J13))
B14: GN 1/3 PP container, 100 mm | C14: =IF(IF($E$5="Local prices",COUNTIFS('Offers'!$B$7:$B$608,$B14,'Offers'!$C$7:$C$608,C$10,'Offers'!$AH$7:$AH$608,"yes"),COUNTIFS('Offers'!$B$7:$B$608,$B14,'Offers'!$C$7:$C$608,C$10,'Offers'!$AI$7:$AI$608,"yes"))=0,"—",SUMIFS('Review'!$O$7:$O$210,'Review'!$B$7:$B$210,$B14,'Review'!$C$7:$C$210,C$10)) | D14: =IF(IF($E$5="Local prices",COUNTIFS('Offers'!$B$7:$B$608,$B14,'Offers'!$C$7:$C$608,D$10,'Offers'!$AH$7:$AH$608,"yes"),COUNTIFS('Offers'!$B$7:$B$608,$B14,'Offers'!$C$7:$C$608,D$10,'Offers'!$AI$7:$AI$608,"yes"))=0,"—",SUMIFS('Review'!$O$7:$O$210,'Review'!$B$7:$B$210,$B14,'Review'!$C$7:$C$210,D$10)) | E14: =IF(IF($E$5="Local prices",COUNTIFS('Offers'!$B$7:$B$608,$B14,'Offers'!$C$7:$C$608,E$10,'Offers'!$AH$7:$AH$608,"yes"),COUNTIFS('Offers'!$B$7:$B$608,$B14,'Offers'!$C$7:$C$608,E$10,'Offers'!$AI$7:$AI$608,"yes"))=0,"—",SUMIFS('Review'!$O$7:$O$210,'Review'!$B$7:$B$210,$B14,'Review'!$C$7:$C$210,E$10)) | F14: =IF(IF($E$5="Local prices",COUNTIFS('Offers'!$B$7:$B$608,$B14,'Offers'!$C$7:$C$608,F$10,'Offers'!$AH$7:$AH$608,"yes"),COUNTIFS('Offers'!$B$7:$B$608,$B14,'Offers'!$C$7:$C$608,F$10,'Offers'!$AI$7:$AI$608,"yes"))=0,"—",SUMIFS('Review'!$O$7:$O$210,'Review'!$B$7:$B$210,$B14,'Review'!$C$7:$C$210,F$10)) | G14: =IF(IF($E$5="Local prices",COUNTIFS('Offers'!$B$7:$B$608,$B14,'Offers'!$C$7:$C$608,G$10,'Offers'!$AH$7:$AH$608,"yes"),COUNTIFS('Offers'!$B$7:$B$608,$B14,'Offers'!$C$7:$C$608,G$10,'Offers'!$AI$7:$AI$608,"yes"))=0,"—",SUMIFS('Review'!$O$7:$O$210,'Review'!$B$7:$B$210,$B14,'Review'!$C$7:$C$210,G$10)) | H14: =IF(IF($E$5="Local prices",COUNTIFS('Offers'!$B$7:$B$608,$B14,'Offers'!$C$7:$C$608,H$10,'Offers'!$AH$7:$AH$608,"yes"),COUNTIFS('Offers'!$B$7:$B$608,$B14,'Offers'!$C$7:$C$608,H$10,'Offers'!$AI$7:$AI$608,"yes"))=0,"—",SUMIFS('Review'!$O$7:$O$210,'Review'!$B$7:$B$210,$B14,'Review'!$C$7:$C$210,H$10)) | J14: Austria | K14: =IF(COUNTIFS('Offers'!$B$7:$B$608,$J$6,'Offers'!$C$7:$C$608,$J14,'Offers'!$AI$7:$AI$608,"yes")=0,"—",SUMIFS('Review'!$I$7:$I$210,'Review'!$B$7:$B$210,$J$6,'Review'!$C$7:$C$210,$J14)) | L14: =IF(COUNTIFS('Offers'!$B$7:$B$608,$J$6,'Offers'!$C$7:$C$608,$J14,'Offers'!$AI$7:$AI$608,"yes")=0,"—",SUMIFS('Review'!$J$7:$J$210,'Review'!$B$7:$B$210,$J$6,'Review'!$C$7:$C$210,$J14)) | M14: =IF(COUNTIFS('Offers'!$B$7:$B$608,$J$6,'Offers'!$C$7:$C$608,$J14,'Offers'!$AI$7:$AI$608,"yes")=0,"—",SUMIFS('Review'!$K$7:$K$210,'Review'!$B$7:$B$210,$J$6,'Review'!$C$7:$C$210,$J14))
B15: GN 1/1 PP lid | C15: =IF(IF($E$5="Local prices",COUNTIFS('Offers'!$B$7:$B$608,$B15,'Offers'!$C$7:$C$608,C$10,'Offers'!$AH$7:$AH$608,"yes"),COUNTIFS('Offers'!$B$7:$B$608,$B15,'Offers'!$C$7:$C$608,C$10,'Offers'!$AI$7:$AI$608,"yes"))=0,"—",SUMIFS('Review'!$O$7:$O$210,'Review'!$B$7:$B$210,$B15,'Review'!$C$7:$C$210,C$10)) | D15: =IF(IF($E$5="Local prices",COUNTIFS('Offers'!$B$7:$B$608,$B15,'Offers'!$C$7:$C$608,D$10,'Offers'!$AH$7:$AH$608,"yes"),COUNTIFS('Offers'!$B$7:$B$608,$B15,'Offers'!$C$7:$C$608,D$10,'Offers'!$AI$7:$AI$608,"yes"))=0,"—",SUMIFS('Review'!$O$7:$O$210,'Review'!$B$7:$B$210,$B15,'Review'!$C$7:$C$210,D$10)) | E15: =IF(IF($E$5="Local prices",COUNTIFS('Offers'!$B$7:$B$608,$B15,'Offers'!$C$7:$C$608,E$10,'Offers'!$AH$7:$AH$608,"yes"),COUNTIFS('Offers'!$B$7:$B$608,$B15,'Offers'!$C$7:$C$608,E$10,'Offers'!$AI$7:$AI$608,"yes"))=0,"—",SUMIFS('Review'!$O$7:$O$210,'Review'!$B$7:$B$210,$B15,'Review'!$C$7:$C$210,E$10)) | F15: =IF(IF($E$5="Local prices",COUNTIFS('Offers'!$B$7:$B$608,$B15,'Offers'!$C$7:$C$608,F$10,'Offers'!$AH$7:$AH$608,"yes"),COUNTIFS('Offers'!$B$7:$B$608,$B15,'Offers'!$C$7:$C$608,F$10,'Offers'!$AI$7:$AI$608,"yes"))=0,"—",SUMIFS('Review'!$O$7:$O$210,'Review'!$B$7:$B$210,$B15,'Review'!$C$7:$C$210,F$10)) | G15: =IF(IF($E$5="Local prices",COUNTIFS('Offers'!$B$7:$B$608,$B15,'Offers'!$C$7:$C$608,G$10,'Offers'!$AH$7:$AH$608,"yes"),COUNTIFS('Offers'!$B$7:$B$608,$B15,'Offers'!$C$7:$C$608,G$10,'Offers'!$AI$7:$AI$608,"yes"))=0,"—",SUMIFS('Review'!$O$7:$O$210,'Review'!$B$7:$B$210,$B15,'Review'!$C$7:$C$210,G$10)) | H15: =IF(IF($E$5="Local prices",COUNTIFS('Offers'!$B$7:$B$608,$B15,'Offers'!$C$7:$C$608,H$10,'Offers'!$AH$7:$AH$608,"yes"),COUNTIFS('Offers'!$B$7:$B$608,$B15,'Offers'!$C$7:$C$608,H$10,'Offers'!$AI$7:$AI$608,"yes"))=0,"—",SUMIFS('Review'!$O$7:$O$210,'Review'!$B$7:$B$210,$B15,'Review'!$C$7:$C$210,H$10)) | J15: Germany | K15: =IF(COUNTIFS('Offers'!$B$7:$B$608,$J$6,'Offers'!$C$7:$C$608,$J15,'Offers'!$AI$7:$AI$608,"yes")=0,"—",SUMIFS('Review'!$I$7:$I$210,'Review'!$B$7:$B$210,$J$6,'Review'!$C$7:$C$210,$J15)) | L15: =IF(COUNTIFS('Offers'!$B$7:$B$608,$J$6,'Offers'!$C$7:$C$608,$J15,'Offers'!$AI$7:$AI$608,"yes")=0,"—",SUMIFS('Review'!$J$7:$J$210,'Review'!$B$7:$B$210,$J$6,'Review'!$C$7:$C$210,$J15)) | M15: =IF(COUNTIFS('Offers'!$B$7:$B$608,$J$6,'Offers'!$C$7:$C$608,$J15,'Offers'!$AI$7:$AI$608,"yes")=0,"—",SUMIFS('Review'!$K$7:$K$210,'Review'!$B$7:$B$210,$J$6,'Review'!$C$7:$C$210,$J15))
B16: Squeeze bottle 500 ml, PP, single tip | C16: =IF(IF($E$5="Local prices",COUNTIFS('Offers'!$B$7:$B$608,$B16,'Offers'!$C$7:$C$608,C$10,'Offers'!$AH$7:$AH$608,"yes"),COUNTIFS('Offers'!$B$7:$B$608,$B16,'Offers'!$C$7:$C$608,C$10,'Offers'!$AI$7:$AI$608,"yes"))=0,"—",SUMIFS('Review'!$O$7:$O$210,'Review'!$B$7:$B$210,$B16,'Review'!$C$7:$C$210,C$10)) | D16: =IF(IF($E$5="Local prices",COUNTIFS('Offers'!$B$7:$B$608,$B16,'Offers'!$C$7:$C$608,D$10,'Offers'!$AH$7:$AH$608,"yes"),COUNTIFS('Offers'!$B$7:$B$608,$B16,'Offers'!$C$7:$C$608,D$10,'Offers'!$AI$7:$AI$608,"yes"))=0,"—",SUMIFS('Review'!$O$7:$O$210,'Review'!$B$7:$B$210,$B16,'Review'!$C$7:$C$210,D$10)) | E16: =IF(IF($E$5="Local prices",COUNTIFS('Offers'!$B$7:$B$608,$B16,'Offers'!$C$7:$C$608,E$10,'Offers'!$AH$7:$AH$608,"yes"),COUNTIFS('Offers'!$B$7:$B$608,$B16,'Offers'!$C$7:$C$608,E$10,'Offers'!$AI$7:$AI$608,"yes"))=0,"—",SUMIFS('Review'!$O$7:$O$210,'Review'!$B$7:$B$210,$B16,'Review'!$C$7:$C$210,E$10)) | F16: =IF(IF($E$5="Local prices",COUNTIFS('Offers'!$B$7:$B$608,$B16,'Offers'!$C$7:$C$608,F$10,'Offers'!$AH$7:$AH$608,"yes"),COUNTIFS('Offers'!$B$7:$B$608,$B16,'Offers'!$C$7:$C$608,F$10,'Offers'!$AI$7:$AI$608,"yes"))=0,"—",SUMIFS('Review'!$O$7:$O$210,'Review'!$B$7:$B$210,$B16,'Review'!$C$7:$C$210,F$10)) | G16: =IF(IF($E$5="Local prices",COUNTIFS('Offers'!$B$7:$B$608,$B16,'Offers'!$C$7:$C$608,G$10,'Offers'!$AH$7:$AH$608,"yes"),COUNTIFS('Offers'!$B$7:$B$608,$B16,'Offers'!$C$7:$C$608,G$10,'Offers'!$AI$7:$AI$608,"yes"))=0,"—",SUMIFS('Review'!$O$7:$O$210,'Review'!$B$7:$B$210,$B16,'Review'!$C$7:$C$210,G$10)) | H16: =IF(IF($E$5="Local prices",COUNTIFS('Offers'!$B$7:$B$608,$B16,'Offers'!$C$7:$C$608,H$10,'Offers'!$AH$7:$AH$608,"yes"),COUNTIFS('Offers'!$B$7:$B$608,$B16,'Offers'!$C$7:$C$608,H$10,'Offers'!$AI$7:$AI$608,"yes"))=0,"—",SUMIFS('Review'!$O$7:$O$210,'Review'!$B$7:$B$210,$B16,'Review'!$C$7:$C$210,H$10)) | J16: Czech | K16: =IF(COUNTIFS('Offers'!$B$7:$B$608,$J$6,'Offers'!$C$7:$C$608,$J16,'Offers'!$AI$7:$AI$608,"yes")=0,"—",SUMIFS('Review'!$I$7:$I$210,'Review'!$B$7:$B$210,$J$6,'Review'!$C$7:$C$210,$J16)) | L16: =IF(COUNTIFS('Offers'!$B$7:$B$608,$J$6,'Offers'!$C$7:$C$608,$J16,'Offers'!$AI$7:$AI$608,"yes")=0,"—",SUMIFS('Review'!$J$7:$J$210,'Review'!$B$7:$B$210,$J$6,'Review'!$C$7:$C$210,$J16)) | M16: =IF(COUNTIFS('Offers'!$B$7:$B$608,$J$6,'Offers'!$C$7:$C$608,$J16,'Offers'!$AI$7:$AI$608,"yes")=0,"—",SUMIFS('Review'!$K$7:$K$210,'Review'!$B$7:$B$210,$J$6,'Review'!$C$7:$C$210,$J16))
B17: Squeeze bottle 1,000 ml, PP, single tip | C17: =IF(IF($E$5="Local prices",COUNTIFS('Offers'!$B$7:$B$608,$B17,'Offers'!$C$7:$C$608,C$10,'Offers'!$AH$7:$AH$608,"yes"),COUNTIFS('Offers'!$B$7:$B$608,$B17,'Offers'!$C$7:$C$608,C$10,'Offers'!$AI$7:$AI$608,"yes"))=0,"—",SUMIFS('Review'!$O$7:$O$210,'Review'!$B$7:$B$210,$B17,'Review'!$C$7:$C$210,C$10)) | D17: =IF(IF($E$5="Local prices",COUNTIFS('Offers'!$B$7:$B$608,$B17,'Offers'!$C$7:$C$608,D$10,'Offers'!$AH$7:$AH$608,"yes"),COUNTIFS('Offers'!$B$7:$B$608,$B17,'Offers'!$C$7:$C$608,D$10,'Offers'!$AI$7:$AI$608,"yes"))=0,"—",SUMIFS('Review'!$O$7:$O$210,'Review'!$B$7:$B$210,$B17,'Review'!$C$7:$C$210,D$10)) | E17: =IF(IF($E$5="Local prices",COUNTIFS('Offers'!$B$7:$B$608,$B17,'Offers'!$C$7:$C$608,E$10,'Offers'!$AH$7:$AH$608,"yes"),COUNTIFS('Offers'!$B$7:$B$608,$B17,'Offers'!$C$7:$C$608,E$10,'Offers'!$AI$7:$AI$608,"yes"))=0,"—",SUMIFS('Review'!$O$7:$O$210,'Review'!$B$7:$B$210,$B17,'Review'!$C$7:$C$210,E$10)) | F17: =IF(IF($E$5="Local prices",COUNTIFS('Offers'!$B$7:$B$608,$B17,'Offers'!$C$7:$C$608,F$10,'Offers'!$AH$7:$AH$608,"yes"),COUNTIFS('Offers'!$B$7:$B$608,$B17,'Offers'!$C$7:$C$608,F$10,'Offers'!$AI$7:$AI$608,"yes"))=0,"—",SUMIFS('Review'!$O$7:$O$210,'Review'!$B$7:$B$210,$B17,'Review'!$C$7:$C$210,F$10)) | G17: =IF(IF($E$5="Local prices",COUNTIFS('Offers'!$B$7:$B$608,$B17,'Offers'!$C$7:$C$608,G$10,'Offers'!$AH$7:$AH$608,"yes"),COUNTIFS('Offers'!$B$7:$B$608,$B17,'Offers'!$C$7:$C$608,G$10,'Offers'!$AI$7:$AI$608,"yes"))=0,"—",SUMIFS('Review'!$O$7:$O$210,'Review'!$B$7:$B$210,$B17,'Review'!$C$7:$C$210,G$10)) | H17: =IF(IF($E$5="Local prices",COUNTIFS('Offers'!$B$7:$B$608,$B17,'Offers'!$C$7:$C$608,H$10,'Offers'!$AH$7:$AH$608,"yes"),COUNTIFS('Offers'!$B$7:$B$608,$B17,'Offers'!$C$7:$C$608,H$10,'Offers'!$AI$7:$AI$608,"yes"))=0,"—",SUMIFS('Review'!$O$7:$O$210,'Review'!$B$7:$B$210,$B17,'Review'!$C$7:$C$210,H$10)) | J17: Slovakia | K17: =IF(COUNTIFS('Offers'!$B$7:$B$608,$J$6,'Offers'!$C$7:$C$608,$J17,'Offers'!$AI$7:$AI$608,"yes")=0,"—",SUMIFS('Review'!$I$7:$I$210,'Review'!$B$7:$B$210,$J$6,'Review'!$C$7:$C$210,$J17)) | L17: =IF(COUNTIFS('Offers'!$B$7:$B$608,$J$6,'Offers'!$C$7:$C$608,$J17,'Offers'!$AI$7:$AI$608,"yes")=0,"—",SUMIFS('Review'!$J$7:$J$210,'Review'!$B$7:$B$210,$J$6,'Review'!$C$7:$C$210,$J17)) | M17: =IF(COUNTIFS('Offers'!$B$7:$B$608,$J$6,'Offers'!$C$7:$C$608,$J17,'Offers'!$AI$7:$AI$608,"yes")=0,"—",SUMIFS('Review'!$K$7:$K$210,'Review'!$B$7:$B$210,$J$6,'Review'!$C$7:$C$210,$J17))
B18: Squeeze bottle 500 ml, triple tip | C18: =IF(IF($E$5="Local prices",COUNTIFS('Offers'!$B$7:$B$608,$B18,'Offers'!$C$7:$C$608,C$10,'Offers'!$AH$7:$AH$608,"yes"),COUNTIFS('Offers'!$B$7:$B$608,$B18,'Offers'!$C$7:$C$608,C$10,'Offers'!$AI$7:$AI$608,"yes"))=0,"—",SUMIFS('Review'!$O$7:$O$210,'Review'!$B$7:$B$210,$B18,'Review'!$C$7:$C$210,C$10)) | D18: =IF(IF($E$5="Local prices",COUNTIFS('Offers'!$B$7:$B$608,$B18,'Offers'!$C$7:$C$608,D$10,'Offers'!$AH$7:$AH$608,"yes"),COUNTIFS('Offers'!$B$7:$B$608,$B18,'Offers'!$C$7:$C$608,D$10,'Offers'!$AI$7:$AI$608,"yes"))=0,"—",SUMIFS('Review'!$O$7:$O$210,'Review'!$B$7:$B$210,$B18,'Review'!$C$7:$C$210,D$10)) | E18: =IF(IF($E$5="Local prices",COUNTIFS('Offers'!$B$7:$B$608,$B18,'Offers'!$C$7:$C$608,E$10,'Offers'!$AH$7:$AH$608,"yes"),COUNTIFS('Offers'!$B$7:$B$608,$B18,'Offers'!$C$7:$C$608,E$10,'Offers'!$AI$7:$AI$608,"yes"))=0,"—",SUMIFS('Review'!$O$7:$O$210,'Review'!$B$7:$B$210,$B18,'Review'!$C$7:$C$210,E$10)) | F18: =IF(IF($E$5="Local prices",COUNTIFS('Offers'!$B$7:$B$608,$B18,'Offers'!$C$7:$C$608,F$10,'Offers'!$AH$7:$AH$608,"yes"),COUNTIFS('Offers'!$B$7:$B$608,$B18,'Offers'!$C$7:$C$608,F$10,'Offers'!$AI$7:$AI$608,"yes"))=0,"—",SUMIFS('Review'!$O$7:$O$210,'Review'!$B$7:$B$210,$B18,'Review'!$C$7:$C$210,F$10)) | G18: =IF(IF($E$5="Local prices",COUNTIFS('Offers'!$B$7:$B$608,$B18,'Offers'!$C$7:$C$608,G$10,'Offers'!$AH$7:$AH$608,"yes"),COUNTIFS('Offers'!$B$7:$B$608,$B18,'Offers'!$C$7:$C$608,G$10,'Offers'!$AI$7:$AI$608,"yes"))=0,"—",SUMIFS('Review'!$O$7:$O$210,'Review'!$B$7:$B$210,$B18,'Review'!$C$7:$C$210,G$10)) | H18: =IF(IF($E$5="Local prices",COUNTIFS('Offers'!$B$7:$B$608,$B18,'Offers'!$C$7:$C$608,H$10,'Offers'!$AH$7:$AH$608,"yes"),COUNTIFS('Offers'!$B$7:$B$608,$B18,'Offers'!$C$7:$C$608,H$10,'Offers'!$AI$7:$AI$608,"yes"))=0,"—",SUMIFS('Review'!$O$7:$O$210,'Review'!$B$7:$B$210,$B18,'Review'!$C$7:$C$210,H$10))
B19: Sauce pump dispenser with stand | C19: =IF(IF($E$5="Local prices",COUNTIFS('Offers'!$B$7:$B$608,$B19,'Offers'!$C$7:$C$608,C$10,'Offers'!$AH$7:$AH$608,"yes"),COUNTIFS('Offers'!$B$7:$B$608,$B19,'Offers'!$C$7:$C$608,C$10,'Offers'!$AI$7:$AI$608,"yes"))=0,"—",SUMIFS('Review'!$O$7:$O$210,'Review'!$B$7:$B$210,$B19,'Review'!$C$7:$C$210,C$10)) | D19: =IF(IF($E$5="Local prices",COUNTIFS('Offers'!$B$7:$B$608,$B19,'Offers'!$C$7:$C$608,D$10,'Offers'!$AH$7:$AH$608,"yes"),COUNTIFS('Offers'!$B$7:$B$608,$B19,'Offers'!$C$7:$C$608,D$10,'Offers'!$AI$7:$AI$608,"yes"))=0,"—",SUMIFS('Review'!$O$7:$O$210,'Review'!$B$7:$B$210,$B19,'Review'!$C$7:$C$210,D$10)) | E19: =IF(IF($E$5="Local prices",COUNTIFS('Offers'!$B$7:$B$608,$B19,'Offers'!$C$7:$C$608,E$10,'Offers'!$AH$7:$AH$608,"yes"),COUNTIFS('Offers'!$B$7:$B$608,$B19,'Offers'!$C$7:$C$608,E$10,'Offers'!$AI$7:$AI$608,"yes"))=0,"—",SUMIFS('Review'!$O$7:$O$210,'Review'!$B$7:$B$210,$B19,'Review'!$C$7:$C$210,E$10)) | F19: =IF(IF($E$5="Local prices",COUNTIFS('Offers'!$B$7:$B$608,$B19,'Offers'!$C$7:$C$608,F$10,'Offers'!$AH$7:$AH$608,"yes"),COUNTIFS('Offers'!$B$7:$B$608,$B19,'Offers'!$C$7:$C$608,F$10,'Offers'!$AI$7:$AI$608,"yes"))=0,"—",SUMIFS('Review'!$O$7:$O$210,'Review'!$B$7:$B$210,$B19,'Review'!$C$7:$C$210,F$10)) | G19: =IF(IF($E$5="Local prices",COUNTIFS('Offers'!$B$7:$B$608,$B19,'Offers'!$C$7:$C$608,G$10,'Offers'!$AH$7:$AH$608,"yes"),COUNTIFS('Offers'!$B$7:$B$608,$B19,'Offers'!$C$7:$C$608,G$10,'Offers'!$AI$7:$AI$608,"yes"))=0,"—",SUMIFS('Review'!$O$7:$O$210,'Review'!$B$7:$B$210,$B19,'Review'!$C$7:$C$210,G$10)) | H19: =IF(IF($E$5="Local prices",COUNTIFS('Offers'!$B$7:$B$608,$B19,'Offers'!$C$7:$C$608,H$10,'Offers'!$AH$7:$AH$608,"yes"),COUNTIFS('Offers'!$B$7:$B$608,$B19,'Offers'!$C$7:$C$608,H$10,'Offers'!$AI$7:$AI$608,"yes"))=0,"—",SUMIFS('Review'!$O$7:$O$210,'Review'!$B$7:$B$210,$B19,'Review'!$C$7:$C$210,H$10))
B20: PE cutting board 530 × 325 × 20 mm | C20: =IF(IF($E$5="Local prices",COUNTIFS('Offers'!$B$7:$B$608,$B20,'Offers'!$C$7:$C$608,C$10,'Offers'!$AH$7:$AH$608,"yes"),COUNTIFS('Offers'!$B$7:$B$608,$B20,'Offers'!$C$7:$C$608,C$10,'Offers'!$AI$7:$AI$608,"yes"))=0,"—",SUMIFS('Review'!$O$7:$O$210,'Review'!$B$7:$B$210,$B20,'Review'!$C$7:$C$210,C$10)) | D20: =IF(IF($E$5="Local prices",COUNTIFS('Offers'!$B$7:$B$608,$B20,'Offers'!$C$7:$C$608,D$10,'Offers'!$AH$7:$AH$608,"yes"),COUNTIFS('Offers'!$B$7:$B$608,$B20,'Offers'!$C$7:$C$608,D$10,'Offers'!$AI$7:$AI$608,"yes"))=0,"—",SUMIFS('Review'!$O$7:$O$210,'Review'!$B$7:$B$210,$B20,'Review'!$C$7:$C$210,D$10)) | E20: =IF(IF($E$5="Local prices",COUNTIFS('Offers'!$B$7:$B$608,$B20,'Offers'!$C$7:$C$608,E$10,'Offers'!$AH$7:$AH$608,"yes"),COUNTIFS('Offers'!$B$7:$B$608,$B20,'Offers'!$C$7:$C$608,E$10,'Offers'!$AI$7:$AI$608,"yes"))=0,"—",SUMIFS('Review'!$O$7:$O$210,'Review'!$B$7:$B$210,$B20,'Review'!$C$7:$C$210,E$10)) | F20: =IF(IF($E$5="Local prices",COUNTIFS('Offers'!$B$7:$B$608,$B20,'Offers'!$C$7:$C$608,F$10,'Offers'!$AH$7:$AH$608,"yes"),COUNTIFS('Offers'!$B$7:$B$608,$B20,'Offers'!$C$7:$C$608,F$10,'Offers'!$AI$7:$AI$608,"yes"))=0,"—",SUMIFS('Review'!$O$7:$O$210,'Review'!$B$7:$B$210,$B20,'Review'!$C$7:$C$210,F$10)) | G20: =IF(IF($E$5="Local prices",COUNTIFS('Offers'!$B$7:$B$608,$B20,'Offers'!$C$7:$C$608,G$10,'Offers'!$AH$7:$AH$608,"yes"),COUNTIFS('Offers'!$B$7:$B$608,$B20,'Offers'!$C$7:$C$608,G$10,'Offers'!$AI$7:$AI$608,"yes"))=0,"—",SUMIFS('Review'!$O$7:$O$210,'Review'!$B$7:$B$210,$B20,'Review'!$C$7:$C$210,G$10)) | H20: =IF(IF($E$5="Local prices",COUNTIFS('Offers'!$B$7:$B$608,$B20,'Offers'!$C$7:$C$608,H$10,'Offers'!$AH$7:$AH$608,"yes"),COUNTIFS('Offers'!$B$7:$B$608,$B20,'Offers'!$C$7:$C$608,H$10,'Offers'!$AI$7:$AI$608,"yes"))=0,"—",SUMIFS('Review'!$O$7:$O$210,'Review'!$B$7:$B$210,$B20,'Review'!$C$7:$C$210,H$10)) | J20: Price basis
B21: PE cutting board 600 × 400 × 20 mm | C21: =IF(IF($E$5="Local prices",COUNTIFS('Offers'!$B$7:$B$608,$B21,'Offers'!$C$7:$C$608,C$10,'Offers'!$AH$7:$AH$608,"yes"),COUNTIFS('Offers'!$B$7:$B$608,$B21,'Offers'!$C$7:$C$608,C$10,'Offers'!$AI$7:$AI$608,"yes"))=0,"—",SUMIFS('Review'!$O$7:$O$210,'Review'!$B$7:$B$210,$B21,'Review'!$C$7:$C$210,C$10)) | D21: =IF(IF($E$5="Local prices",COUNTIFS('Offers'!$B$7:$B$608,$B21,'Offers'!$C$7:$C$608,D$10,'Offers'!$AH$7:$AH$608,"yes"),COUNTIFS('Offers'!$B$7:$B$608,$B21,'Offers'!$C$7:$C$608,D$10,'Offers'!$AI$7:$AI$608,"yes"))=0,"—",SUMIFS('Review'!$O$7:$O$210,'Review'!$B$7:$B$210,$B21,'Review'!$C$7:$C$210,D$10)) | E21: =IF(IF($E$5="Local prices",COUNTIFS('Offers'!$B$7:$B$608,$B21,'Offers'!$C$7:$C$608,E$10,'Offers'!$AH$7:$AH$608,"yes"),COUNTIFS('Offers'!$B$7:$B$608,$B21,'Offers'!$C$7:$C$608,E$10,'Offers'!$AI$7:$AI$608,"yes"))=0,"—",SUMIFS('Review'!$O$7:$O$210,'Review'!$B$7:$B$210,$B21,'Review'!$C$7:$C$210,E$10)) | F21: =IF(IF($E$5="Local prices",COUNTIFS('Offers'!$B$7:$B$608,$B21,'Offers'!$C$7:$C$608,F$10,'Offers'!$AH$7:$AH$608,"yes"),COUNTIFS('Offers'!$B$7:$B$608,$B21,'Offers'!$C$7:$C$608,F$10,'Offers'!$AI$7:$AI$608,"yes"))=0,"—",SUMIFS('Review'!$O$7:$O$210,'Review'!$B$7:$B$210,$B21,'Review'!$C$7:$C$210,F$10)) | G21: =IF(IF($E$5="Local prices",COUNTIFS('Offers'!$B$7:$B$608,$B21,'Offers'!$C$7:$C$608,G$10,'Offers'!$AH$7:$AH$608,"yes"),COUNTIFS('Offers'!$B$7:$B$608,$B21,'Offers'!$C$7:$C$608,G$10,'Offers'!$AI$7:$AI$608,"yes"))=0,"—",SUMIFS('Review'!$O$7:$O$210,'Review'!$B$7:$B$210,$B21,'Review'!$C$7:$C$210,G$10)) | H21: =IF(IF($E$5="Local prices",COUNTIFS('Offers'!$B$7:$B$608,$B21,'Offers'!$C$7:$C$608,H$10,'Offers'!$AH$7:$AH$608,"yes"),COUNTIFS('Offers'!$B$7:$B$608,$B21,'Offers'!$C$7:$C$608,H$10,'Offers'!$AI$7:$AI$608,"yes"))=0,"—",SUMIFS('Review'!$O$7:$O$210,'Review'!$B$7:$B$210,$B21,'Review'!$C$7:$C$210,H$10)) | J21: Hungary and Romania prices are net per piece, as confirmed by you.
B22: PE cutting board 300 × 200 × 10 mm | C22: =IF(IF($E$5="Local prices",COUNTIFS('Offers'!$B$7:$B$608,$B22,'Offers'!$C$7:$C$608,C$10,'Offers'!$AH$7:$AH$608,"yes"),COUNTIFS('Offers'!$B$7:$B$608,$B22,'Offers'!$C$7:$C$608,C$10,'Offers'!$AI$7:$AI$608,"yes"))=0,"—",SUMIFS('Review'!$O$7:$O$210,'Review'!$B$7:$B$210,$B22,'Review'!$C$7:$C$210,C$10)) | D22: =IF(IF($E$5="Local prices",COUNTIFS('Offers'!$B$7:$B$608,$B22,'Offers'!$C$7:$C$608,D$10,'Offers'!$AH$7:$AH$608,"yes"),COUNTIFS('Offers'!$B$7:$B$608,$B22,'Offers'!$C$7:$C$608,D$10,'Offers'!$AI$7:$AI$608,"yes"))=0,"—",SUMIFS('Review'!$O$7:$O$210,'Review'!$B$7:$B$210,$B22,'Review'!$C$7:$C$210,D$10)) | E22: =IF(IF($E$5="Local prices",COUNTIFS('Offers'!$B$7:$B$608,$B22,'Offers'!$C$7:$C$608,E$10,'Offers'!$AH$7:$AH$608,"yes"),COUNTIFS('Offers'!$B$7:$B$608,$B22,'Offers'!$C$7:$C$608,E$10,'Offers'!$AI$7:$AI$608,"yes"))=0,"—",SUMIFS('Review'!$O$7:$O$210,'Review'!$B$7:$B$210,$B22,'Review'!$C$7:$C$210,E$10)) | F22: =IF(IF($E$5="Local prices",COUNTIFS('Offers'!$B$7:$B$608,$B22,'Offers'!$C$7:$C$608,F$10,'Offers'!$AH$7:$AH$608,"yes"),COUNTIFS('Offers'!$B$7:$B$608,$B22,'Offers'!$C$7:$C$608,F$10,'Offers'!$AI$7:$AI$608,"yes"))=0,"—",SUMIFS('Review'!$O$7:$O$210,'Review'!$B$7:$B$210,$B22,'Review'!$C$7:$C$210,F$10)) | G22: =IF(IF($E$5="Local prices",COUNTIFS('Offers'!$B$7:$B$608,$B22,'Offers'!$C$7:$C$608,G$10,'Offers'!$AH$7:$AH$608,"yes"),COUNTIFS('Offers'!$B$7:$B$608,$B22,'Offers'!$C$7:$C$608,G$10,'Offers'!$AI$7:$AI$608,"yes"))=0,"—",SUMIFS('Review'!$O$7:$O$210,'Review'!$B$7:$B$210,$B22,'Review'!$C$7:$C$210,G$10)) | H22: =IF(IF($E$5="Local prices",COUNTIFS('Offers'!$B$7:$B$608,$B22,'Offers'!$C$7:$C$608,H$10,'Offers'!$AH$7:$AH$608,"yes"),COUNTIFS('Offers'!$B$7:$B$608,$B22,'Offers'!$C$7:$C$608,H$10,'Offers'!$AI$7:$AI$608,"yes"))=0,"—",SUMIFS('Review'!$O$7:$O$210,'Review'!$B$7:$B$210,$B22,'Review'!$C$7:$C$210,H$10))
B23: PP dough box 600 × 400 × 100 mm | C23: =IF(IF($E$5="Local prices",COUNTIFS('Offers'!$B$7:$B$608,$B23,'Offers'!$C$7:$C$608,C$10,'Offers'!$AH$7:$AH$608,"yes"),COUNTIFS('Offers'!$B$7:$B$608,$B23,'Offers'!$C$7:$C$608,C$10,'Offers'!$AI$7:$AI$608,"yes"))=0,"—",SUMIFS('Review'!$O$7:$O$210,'Review'!$B$7:$B$210,$B23,'Review'!$C$7:$C$210,C$10)) | D23: =IF(IF($E$5="Local prices",COUNTIFS('Offers'!$B$7:$B$608,$B23,'Offers'!$C$7:$C$608,D$10,'Offers'!$AH$7:$AH$608,"yes"),COUNTIFS('Offers'!$B$7:$B$608,$B23,'Offers'!$C$7:$C$608,D$10,'Offers'!$AI$7:$AI$608,"yes"))=0,"—",SUMIFS('Review'!$O$7:$O$210,'Review'!$B$7:$B$210,$B23,'Review'!$C$7:$C$210,D$10)) | E23: =IF(IF($E$5="Local prices",COUNTIFS('Offers'!$B$7:$B$608,$B23,'Offers'!$C$7:$C$608,E$10,'Offers'!$AH$7:$AH$608,"yes"),COUNTIFS('Offers'!$B$7:$B$608,$B23,'Offers'!$C$7:$C$608,E$10,'Offers'!$AI$7:$AI$608,"yes"))=0,"—",SUMIFS('Review'!$O$7:$O$210,'Review'!$B$7:$B$210,$B23,'Review'!$C$7:$C$210,E$10)) | F23: =IF(IF($E$5="Local prices",COUNTIFS('Offers'!$B$7:$B$608,$B23,'Offers'!$C$7:$C$608,F$10,'Offers'!$AH$7:$AH$608,"yes"),COUNTIFS('Offers'!$B$7:$B$608,$B23,'Offers'!$C$7:$C$608,F$10,'Offers'!$AI$7:$AI$608,"yes"))=0,"—",SUMIFS('Review'!$O$7:$O$210,'Review'!$B$7:$B$210,$B23,'Review'!$C$7:$C$210,F$10)) | G23: =IF(IF($E$5="Local prices",COUNTIFS('Offers'!$B$7:$B$608,$B23,'Offers'!$C$7:$C$608,G$10,'Offers'!$AH$7:$AH$608,"yes"),COUNTIFS('Offers'!$B$7:$B$608,$B23,'Offers'!$C$7:$C$608,G$10,'Offers'!$AI$7:$AI$608,"yes"))=0,"—",SUMIFS('Review'!$O$7:$O$210,'Review'!$B$7:$B$210,$B23,'Review'!$C$7:$C$210,G$10)) | H23: =IF(IF($E$5="Local prices",COUNTIFS('Offers'!$B$7:$B$608,$B23,'Offers'!$C$7:$C$608,H$10,'Offers'!$AH$7:$AH$608,"yes"),COUNTIFS('Offers'!$B$7:$B$608,$B23,'Offers'!$C$7:$C$608,H$10,'Offers'!$AI$7:$AI$608,"yes"))=0,"—",SUMIFS('Review'!$O$7:$O$210,'Review'!$B$7:$B$210,$B23,'Review'!$C$7:$C$210,H$10))
B24: Lid for 600 × 400 mm dough box | C24: =IF(IF($E$5="Local prices",COUNTIFS('Offers'!$B$7:$B$608,$B24,'Offers'!$C$7:$C$608,C$10,'Offers'!$AH$7:$AH$608,"yes"),COUNTIFS('Offers'!$B$7:$B$608,$B24,'Offers'!$C$7:$C$608,C$10,'Offers'!$AI$7:$AI$608,"yes"))=0,"—",SUMIFS('Review'!$O$7:$O$210,'Review'!$B$7:$B$210,$B24,'Review'!$C$7:$C$210,C$10)) | D24: =IF(IF($E$5="Local prices",COUNTIFS('Offers'!$B$7:$B$608,$B24,'Offers'!$C$7:$C$608,D$10,'Offers'!$AH$7:$AH$608,"yes"),COUNTIFS('Offers'!$B$7:$B$608,$B24,'Offers'!$C$7:$C$608,D$10,'Offers'!$AI$7:$AI$608,"yes"))=0,"—",SUMIFS('Review'!$O$7:$O$210,'Review'!$B$7:$B$210,$B24,'Review'!$C$7:$C$210,D$10)) | E24: =IF(IF($E$5="Local prices",COUNTIFS('Offers'!$B$7:$B$608,$B24,'Offers'!$C$7:$C$608,E$10,'Offers'!$AH$7:$AH$608,"yes"),COUNTIFS('Offers'!$B$7:$B$608,$B24,'Offers'!$C$7:$C$608,E$10,'Offers'!$AI$7:$AI$608,"yes"))=0,"—",SUMIFS('Review'!$O$7:$O$210,'Review'!$B$7:$B$210,$B24,'Review'!$C$7:$C$210,E$10)) | F24: =IF(IF($E$5="Local prices",COUNTIFS('Offers'!$B$7:$B$608,$B24,'Offers'!$C$7:$C$608,F$10,'Offers'!$AH$7:$AH$608,"yes"),COUNTIFS('Offers'!$B$7:$B$608,$B24,'Offers'!$C$7:$C$608,F$10,'Offers'!$AI$7:$AI$608,"yes"))=0,"—",SUMIFS('Review'!$O$7:$O$210,'Review'!$B$7:$B$210,$B24,'Review'!$C$7:$C$210,F$10)) | G24: =IF(IF($E$5="Local prices",COUNTIFS('Offers'!$B$7:$B$608,$B24,'Offers'!$C$7:$C$608,G$10,'Offers'!$AH$7:$AH$608,"yes"),COUNTIFS('Offers'!$B$7:$B$608,$B24,'Offers'!$C$7:$C$608,G$10,'Offers'!$AI$7:$AI$608,"yes"))=0,"—",SUMIFS('Review'!$O$7:$O$210,'Review'!$B$7:$B$210,$B24,'Review'!$C$7:$C$210,G$10)) | H24: =IF(IF($E$5="Local prices",COUNTIFS('Offers'!$B$7:$B$608,$B24,'Offers'!$C$7:$C$608,H$10,'Offers'!$AH$7:$AH$608,"yes"),COUNTIFS('Offers'!$B$7:$B$608,$B24,'Offers'!$C$7:$C$608,H$10,'Offers'!$AI$7:$AI$608,"yes"))=0,"—",SUMIFS('Review'!$O$7:$O$210,'Review'!$B$7:$B$210,$B24,'Review'!$C$7:$C$210,H$10)) | J24: Current FX
B25: PE dough box 600 × 400 × 75 mm | C25: =IF(IF($E$5="Local prices",COUNTIFS('Offers'!$B$7:$B$608,$B25,'Offers'!$C$7:$C$608,C$10,'Offers'!$AH$7:$AH$608,"yes"),COUNTIFS('Offers'!$B$7:$B$608,$B25,'Offers'!$C$7:$C$608,C$10,'Offers'!$AI$7:$AI$608,"yes"))=0,"—",SUMIFS('Review'!$O$7:$O$210,'Review'!$B$7:$B$210,$B25,'Review'!$C$7:$C$210,C$10)) | D25: =IF(IF($E$5="Local prices",COUNTIFS('Offers'!$B$7:$B$608,$B25,'Offers'!$C$7:$C$608,D$10,'Offers'!$AH$7:$AH$608,"yes"),COUNTIFS('Offers'!$B$7:$B$608,$B25,'Offers'!$C$7:$C$608,D$10,'Offers'!$AI$7:$AI$608,"yes"))=0,"—",SUMIFS('Review'!$O$7:$O$210,'Review'!$B$7:$B$210,$B25,'Review'!$C$7:$C$210,D$10)) | E25: =IF(IF($E$5="Local prices",COUNTIFS('Offers'!$B$7:$B$608,$B25,'Offers'!$C$7:$C$608,E$10,'Offers'!$AH$7:$AH$608,"yes"),COUNTIFS('Offers'!$B$7:$B$608,$B25,'Offers'!$C$7:$C$608,E$10,'Offers'!$AI$7:$AI$608,"yes"))=0,"—",SUMIFS('Review'!$O$7:$O$210,'Review'!$B$7:$B$210,$B25,'Review'!$C$7:$C$210,E$10)) | F25: =IF(IF($E$5="Local prices",COUNTIFS('Offers'!$B$7:$B$608,$B25,'Offers'!$C$7:$C$608,F$10,'Offers'!$AH$7:$AH$608,"yes"),COUNTIFS('Offers'!$B$7:$B$608,$B25,'Offers'!$C$7:$C$608,F$10,'Offers'!$AI$7:$AI$608,"yes"))=0,"—",SUMIFS('Review'!$O$7:$O$210,'Review'!$B$7:$B$210,$B25,'Review'!$C$7:$C$210,F$10)) | G25: =IF(IF($E$5="Local prices",COUNTIFS('Offers'!$B$7:$B$608,$B25,'Offers'!$C$7:$C$608,G$10,'Offers'!$AH$7:$AH$608,"yes"),COUNTIFS('Offers'!$B$7:$B$608,$B25,'Offers'!$C$7:$C$608,G$10,'Offers'!$AI$7:$AI$608,"yes"))=0,"—",SUMIFS('Review'!$O$7:$O$210,'Review'!$B$7:$B$210,$B25,'Review'!$C$7:$C$210,G$10)) | H25: =IF(IF($E$5="Local prices",COUNTIFS('Offers'!$B$7:$B$608,$B25,'Offers'!$C$7:$C$608,H$10,'Offers'!$AH$7:$AH$608,"yes"),COUNTIFS('Offers'!$B$7:$B$608,$B25,'Offers'!$C$7:$C$608,H$10,'Offers'!$AI$7:$AI$608,"yes"))=0,"—",SUMIFS('Review'!$O$7:$O$210,'Review'!$B$7:$B$210,$B25,'Review'!$C$7:$C$210,H$10)) | J25: Erste rates are applied to analytical conversions. Historical prices and research dates remain unchanged.
B26: Front-load GN 1/1 thermobox, 80–90 L | C26: =IF(IF($E$5="Local prices",COUNTIFS('Offers'!$B$7:$B$608,$B26,'Offers'!$C$7:$C$608,C$10,'Offers'!$AH$7:$AH$608,"yes"),COUNTIFS('Offers'!$B$7:$B$608,$B26,'Offers'!$C$7:$C$608,C$10,'Offers'!$AI$7:$AI$608,"yes"))=0,"—",SUMIFS('Review'!$O$7:$O$210,'Review'!$B$7:$B$210,$B26,'Review'!$C$7:$C$210,C$10)) | D26: =IF(IF($E$5="Local prices",COUNTIFS('Offers'!$B$7:$B$608,$B26,'Offers'!$C$7:$C$608,D$10,'Offers'!$AH$7:$AH$608,"yes"),COUNTIFS('Offers'!$B$7:$B$608,$B26,'Offers'!$C$7:$C$608,D$10,'Offers'!$AI$7:$AI$608,"yes"))=0,"—",SUMIFS('Review'!$O$7:$O$210,'Review'!$B$7:$B$210,$B26,'Review'!$C$7:$C$210,D$10)) | E26: =IF(IF($E$5="Local prices",COUNTIFS('Offers'!$B$7:$B$608,$B26,'Offers'!$C$7:$C$608,E$10,'Offers'!$AH$7:$AH$608,"yes"),COUNTIFS('Offers'!$B$7:$B$608,$B26,'Offers'!$C$7:$C$608,E$10,'Offers'!$AI$7:$AI$608,"yes"))=0,"—",SUMIFS('Review'!$O$7:$O$210,'Review'!$B$7:$B$210,$B26,'Review'!$C$7:$C$210,E$10)) | F26: =IF(IF($E$5="Local prices",COUNTIFS('Offers'!$B$7:$B$608,$B26,'Offers'!$C$7:$C$608,F$10,'Offers'!$AH$7:$AH$608,"yes"),COUNTIFS('Offers'!$B$7:$B$608,$B26,'Offers'!$C$7:$C$608,F$10,'Offers'!$AI$7:$AI$608,"yes"))=0,"—",SUMIFS('Review'!$O$7:$O$210,'Review'!$B$7:$B$210,$B26,'Review'!$C$7:$C$210,F$10)) | G26: =IF(IF($E$5="Local prices",COUNTIFS('Offers'!$B$7:$B$608,$B26,'Offers'!$C$7:$C$608,G$10,'Offers'!$AH$7:$AH$608,"yes"),COUNTIFS('Offers'!$B$7:$B$608,$B26,'Offers'!$C$7:$C$608,G$10,'Offers'!$AI$7:$AI$608,"yes"))=0,"—",SUMIFS('Review'!$O$7:$O$210,'Review'!$B$7:$B$210,$B26,'Review'!$C$7:$C$210,G$10)) | H26: =IF(IF($E$5="Local prices",COUNTIFS('Offers'!$B$7:$B$608,$B26,'Offers'!$C$7:$C$608,H$10,'Offers'!$AH$7:$AH$608,"yes"),COUNTIFS('Offers'!$B$7:$B$608,$B26,'Offers'!$C$7:$C$608,H$10,'Offers'!$AI$7:$AI$608,"yes"))=0,"—",SUMIFS('Review'!$O$7:$O$210,'Review'!$B$7:$B$210,$B26,'Review'!$C$7:$C$210,H$10))
B27: Service tray approx. 370 × 530 mm | C27: =IF(IF($E$5="Local prices",COUNTIFS('Offers'!$B$7:$B$608,$B27,'Offers'!$C$7:$C$608,C$10,'Offers'!$AH$7:$AH$608,"yes"),COUNTIFS('Offers'!$B$7:$B$608,$B27,'Offers'!$C$7:$C$608,C$10,'Offers'!$AI$7:$AI$608,"yes"))=0,"—",SUMIFS('Review'!$O$7:$O$210,'Review'!$B$7:$B$210,$B27,'Review'!$C$7:$C$210,C$10)) | D27: =IF(IF($E$5="Local prices",COUNTIFS('Offers'!$B$7:$B$608,$B27,'Offers'!$C$7:$C$608,D$10,'Offers'!$AH$7:$AH$608,"yes"),COUNTIFS('Offers'!$B$7:$B$608,$B27,'Offers'!$C$7:$C$608,D$10,'Offers'!$AI$7:$AI$608,"yes"))=0,"—",SUMIFS('Review'!$O$7:$O$210,'Review'!$B$7:$B$210,$B27,'Review'!$C$7:$C$210,D$10)) | E27: =IF(IF($E$5="Local prices",COUNTIFS('Offers'!$B$7:$B$608,$B27,'Offers'!$C$7:$C$608,E$10,'Offers'!$AH$7:$AH$608,"yes"),COUNTIFS('Offers'!$B$7:$B$608,$B27,'Offers'!$C$7:$C$608,E$10,'Offers'!$AI$7:$AI$608,"yes"))=0,"—",SUMIFS('Review'!$O$7:$O$210,'Review'!$B$7:$B$210,$B27,'Review'!$C$7:$C$210,E$10)) | F27: =IF(IF($E$5="Local prices",COUNTIFS('Offers'!$B$7:$B$608,$B27,'Offers'!$C$7:$C$608,F$10,'Offers'!$AH$7:$AH$608,"yes"),COUNTIFS('Offers'!$B$7:$B$608,$B27,'Offers'!$C$7:$C$608,F$10,'Offers'!$AI$7:$AI$608,"yes"))=0,"—",SUMIFS('Review'!$O$7:$O$210,'Review'!$B$7:$B$210,$B27,'Review'!$C$7:$C$210,F$10)) | G27: =IF(IF($E$5="Local prices",COUNTIFS('Offers'!$B$7:$B$608,$B27,'Offers'!$C$7:$C$608,G$10,'Offers'!$AH$7:$AH$608,"yes"),COUNTIFS('Offers'!$B$7:$B$608,$B27,'Offers'!$C$7:$C$608,G$10,'Offers'!$AI$7:$AI$608,"yes"))=0,"—",SUMIFS('Review'!$O$7:$O$210,'Review'!$B$7:$B$210,$B27,'Review'!$C$7:$C$210,G$10)) | H27: =IF(IF($E$5="Local prices",COUNTIFS('Offers'!$B$7:$B$608,$B27,'Offers'!$C$7:$C$608,H$10,'Offers'!$AH$7:$AH$608,"yes"),COUNTIFS('Offers'!$B$7:$B$608,$B27,'Offers'!$C$7:$C$608,H$10,'Offers'!$AI$7:$AI$608,"yes"))=0,"—",SUMIFS('Review'!$O$7:$O$210,'Review'!$B$7:$B$210,$B27,'Review'!$C$7:$C$210,H$10))
B28: Thermo tray + lid, 5–6 compartments | C28: =IF(IF($E$5="Local prices",COUNTIFS('Offers'!$B$7:$B$608,$B28,'Offers'!$C$7:$C$608,C$10,'Offers'!$AH$7:$AH$608,"yes"),COUNTIFS('Offers'!$B$7:$B$608,$B28,'Offers'!$C$7:$C$608,C$10,'Offers'!$AI$7:$AI$608,"yes"))=0,"—",SUMIFS('Review'!$O$7:$O$210,'Review'!$B$7:$B$210,$B28,'Review'!$C$7:$C$210,C$10)) | D28: =IF(IF($E$5="Local prices",COUNTIFS('Offers'!$B$7:$B$608,$B28,'Offers'!$C$7:$C$608,D$10,'Offers'!$AH$7:$AH$608,"yes"),COUNTIFS('Offers'!$B$7:$B$608,$B28,'Offers'!$C$7:$C$608,D$10,'Offers'!$AI$7:$AI$608,"yes"))=0,"—",SUMIFS('Review'!$O$7:$O$210,'Review'!$B$7:$B$210,$B28,'Review'!$C$7:$C$210,D$10)) | E28: =IF(IF($E$5="Local prices",COUNTIFS('Offers'!$B$7:$B$608,$B28,'Offers'!$C$7:$C$608,E$10,'Offers'!$AH$7:$AH$608,"yes"),COUNTIFS('Offers'!$B$7:$B$608,$B28,'Offers'!$C$7:$C$608,E$10,'Offers'!$AI$7:$AI$608,"yes"))=0,"—",SUMIFS('Review'!$O$7:$O$210,'Review'!$B$7:$B$210,$B28,'Review'!$C$7:$C$210,E$10)) | F28: =IF(IF($E$5="Local prices",COUNTIFS('Offers'!$B$7:$B$608,$B28,'Offers'!$C$7:$C$608,F$10,'Offers'!$AH$7:$AH$608,"yes"),COUNTIFS('Offers'!$B$7:$B$608,$B28,'Offers'!$C$7:$C$608,F$10,'Offers'!$AI$7:$AI$608,"yes"))=0,"—",SUMIFS('Review'!$O$7:$O$210,'Review'!$B$7:$B$210,$B28,'Review'!$C$7:$C$210,F$10)) | G28: =IF(IF($E$5="Local prices",COUNTIFS('Offers'!$B$7:$B$608,$B28,'Offers'!$C$7:$C$608,G$10,'Offers'!$AH$7:$AH$608,"yes"),COUNTIFS('Offers'!$B$7:$B$608,$B28,'Offers'!$C$7:$C$608,G$10,'Offers'!$AI$7:$AI$608,"yes"))=0,"—",SUMIFS('Review'!$O$7:$O$210,'Review'!$B$7:$B$210,$B28,'Review'!$C$7:$C$210,G$10)) | H28: =IF(IF($E$5="Local prices",COUNTIFS('Offers'!$B$7:$B$608,$B28,'Offers'!$C$7:$C$608,H$10,'Offers'!$AH$7:$AH$608,"yes"),COUNTIFS('Offers'!$B$7:$B$608,$B28,'Offers'!$C$7:$C$608,H$10,'Offers'!$AI$7:$AI$608,"yes"))=0,"—",SUMIFS('Review'!$O$7:$O$210,'Review'!$B$7:$B$210,$B28,'Review'!$C$7:$C$210,H$10)) | J28: Your review
B29: GN 1/1 PP container, 65 mm | C29: =IF(IF($E$5="Local prices",COUNTIFS('Offers'!$B$7:$B$608,$B29,'Offers'!$C$7:$C$608,C$10,'Offers'!$AH$7:$AH$608,"yes"),COUNTIFS('Offers'!$B$7:$B$608,$B29,'Offers'!$C$7:$C$608,C$10,'Offers'!$AI$7:$AI$608,"yes"))=0,"—",SUMIFS('Review'!$O$7:$O$210,'Review'!$B$7:$B$210,$B29,'Review'!$C$7:$C$210,C$10)) | D29: =IF(IF($E$5="Local prices",COUNTIFS('Offers'!$B$7:$B$608,$B29,'Offers'!$C$7:$C$608,D$10,'Offers'!$AH$7:$AH$608,"yes"),COUNTIFS('Offers'!$B$7:$B$608,$B29,'Offers'!$C$7:$C$608,D$10,'Offers'!$AI$7:$AI$608,"yes"))=0,"—",SUMIFS('Review'!$O$7:$O$210,'Review'!$B$7:$B$210,$B29,'Review'!$C$7:$C$210,D$10)) | E29: =IF(IF($E$5="Local prices",COUNTIFS('Offers'!$B$7:$B$608,$B29,'Offers'!$C$7:$C$608,E$10,'Offers'!$AH$7:$AH$608,"yes"),COUNTIFS('Offers'!$B$7:$B$608,$B29,'Offers'!$C$7:$C$608,E$10,'Offers'!$AI$7:$AI$608,"yes"))=0,"—",SUMIFS('Review'!$O$7:$O$210,'Review'!$B$7:$B$210,$B29,'Review'!$C$7:$C$210,E$10)) | F29: =IF(IF($E$5="Local prices",COUNTIFS('Offers'!$B$7:$B$608,$B29,'Offers'!$C$7:$C$608,F$10,'Offers'!$AH$7:$AH$608,"yes"),COUNTIFS('Offers'!$B$7:$B$608,$B29,'Offers'!$C$7:$C$608,F$10,'Offers'!$AI$7:$AI$608,"yes"))=0,"—",SUMIFS('Review'!$O$7:$O$210,'Review'!$B$7:$B$210,$B29,'Review'!$C$7:$C$210,F$10)) | G29: =IF(IF($E$5="Local prices",COUNTIFS('Offers'!$B$7:$B$608,$B29,'Offers'!$C$7:$C$608,G$10,'Offers'!$AH$7:$AH$608,"yes"),COUNTIFS('Offers'!$B$7:$B$608,$B29,'Offers'!$C$7:$C$608,G$10,'Offers'!$AI$7:$AI$608,"yes"))=0,"—",SUMIFS('Review'!$O$7:$O$210,'Review'!$B$7:$B$210,$B29,'Review'!$C$7:$C$210,G$10)) | H29: =IF(IF($E$5="Local prices",COUNTIFS('Offers'!$B$7:$B$608,$B29,'Offers'!$C$7:$C$608,H$10,'Offers'!$AH$7:$AH$608,"yes"),COUNTIFS('Offers'!$B$7:$B$608,$B29,'Offers'!$C$7:$C$608,H$10,'Offers'!$AI$7:$AI$608,"yes"))=0,"—",SUMIFS('Review'!$O$7:$O$210,'Review'!$B$7:$B$210,$B29,'Review'!$C$7:$C$210,H$10)) | J29: Record decisions, priorities and comments in Review. Add offer-specific comments in Offers.
B30: GN 1/3 PC container, 100 mm | C30: =IF(IF($E$5="Local prices",COUNTIFS('Offers'!$B$7:$B$608,$B30,'Offers'!$C$7:$C$608,C$10,'Offers'!$AH$7:$AH$608,"yes"),COUNTIFS('Offers'!$B$7:$B$608,$B30,'Offers'!$C$7:$C$608,C$10,'Offers'!$AI$7:$AI$608,"yes"))=0,"—",SUMIFS('Review'!$O$7:$O$210,'Review'!$B$7:$B$210,$B30,'Review'!$C$7:$C$210,C$10)) | D30: =IF(IF($E$5="Local prices",COUNTIFS('Offers'!$B$7:$B$608,$B30,'Offers'!$C$7:$C$608,D$10,'Offers'!$AH$7:$AH$608,"yes"),COUNTIFS('Offers'!$B$7:$B$608,$B30,'Offers'!$C$7:$C$608,D$10,'Offers'!$AI$7:$AI$608,"yes"))=0,"—",SUMIFS('Review'!$O$7:$O$210,'Review'!$B$7:$B$210,$B30,'Review'!$C$7:$C$210,D$10)) | E30: =IF(IF($E$5="Local prices",COUNTIFS('Offers'!$B$7:$B$608,$B30,'Offers'!$C$7:$C$608,E$10,'Offers'!$AH$7:$AH$608,"yes"),COUNTIFS('Offers'!$B$7:$B$608,$B30,'Offers'!$C$7:$C$608,E$10,'Offers'!$AI$7:$AI$608,"yes"))=0,"—",SUMIFS('Review'!$O$7:$O$210,'Review'!$B$7:$B$210,$B30,'Review'!$C$7:$C$210,E$10)) | F30: =IF(IF($E$5="Local prices",COUNTIFS('Offers'!$B$7:$B$608,$B30,'Offers'!$C$7:$C$608,F$10,'Offers'!$AH$7:$AH$608,"yes"),COUNTIFS('Offers'!$B$7:$B$608,$B30,'Offers'!$C$7:$C$608,F$10,'Offers'!$AI$7:$AI$608,"yes"))=0,"—",SUMIFS('Review'!$O$7:$O$210,'Review'!$B$7:$B$210,$B30,'Review'!$C$7:$C$210,F$10)) | G30: =IF(IF($E$5="Local prices",COUNTIFS('Offers'!$B$7:$B$608,$B30,'Offers'!$C$7:$C$608,G$10,'Offers'!$AH$7:$AH$608,"yes"),COUNTIFS('Offers'!$B$7:$B$608,$B30,'Offers'!$C$7:$C$608,G$10,'Offers'!$AI$7:$AI$608,"yes"))=0,"—",SUMIFS('Review'!$O$7:$O$210,'Review'!$B$7:$B$210,$B30,'Review'!$C$7:$C$210,G$10)) | H30: =IF(IF($E$5="Local prices",COUNTIFS('Offers'!$B$7:$B$608,$B30,'Offers'!$C$7:$C$608,H$10,'Offers'!$AH$7:$AH$608,"yes"),COUNTIFS('Offers'!$B$7:$B$608,$B30,'Offers'!$C$7:$C$608,H$10,'Offers'!$AI$7:$AI$608,"yes"))=0,"—",SUMIFS('Review'!$O$7:$O$210,'Review'!$B$7:$B$210,$B30,'Review'!$C$7:$C$210,H$10))
B31: GN 1/2 PP container, 150 mm | C31: =IF(IF($E$5="Local prices",COUNTIFS('Offers'!$B$7:$B$608,$B31,'Offers'!$C$7:$C$608,C$10,'Offers'!$AH$7:$AH$608,"yes"),COUNTIFS('Offers'!$B$7:$B$608,$B31,'Offers'!$C$7:$C$608,C$10,'Offers'!$AI$7:$AI$608,"yes"))=0,"—",SUMIFS('Review'!$O$7:$O$210,'Review'!$B$7:$B$210,$B31,'Review'!$C$7:$C$210,C$10)) | D31: =IF(IF($E$5="Local prices",COUNTIFS('Offers'!$B$7:$B$608,$B31,'Offers'!$C$7:$C$608,D$10,'Offers'!$AH$7:$AH$608,"yes"),COUNTIFS('Offers'!$B$7:$B$608,$B31,'Offers'!$C$7:$C$608,D$10,'Offers'!$AI$7:$AI$608,"yes"))=0,"—",SUMIFS('Review'!$O$7:$O$210,'Review'!$B$7:$B$210,$B31,'Review'!$C$7:$C$210,D$10)) | E31: =IF(IF($E$5="Local prices",COUNTIFS('Offers'!$B$7:$B$608,$B31,'Offers'!$C$7:$C$608,E$10,'Offers'!$AH$7:$AH$608,"yes"),COUNTIFS('Offers'!$B$7:$B$608,$B31,'Offers'!$C$7:$C$608,E$10,'Offers'!$AI$7:$AI$608,"yes"))=0,"—",SUMIFS('Review'!$O$7:$O$210,'Review'!$B$7:$B$210,$B31,'Review'!$C$7:$C$210,E$10)) | F31: =IF(IF($E$5="Local prices",COUNTIFS('Offers'!$B$7:$B$608,$B31,'Offers'!$C$7:$C$608,F$10,'Offers'!$AH$7:$AH$608,"yes"),COUNTIFS('Offers'!$B$7:$B$608,$B31,'Offers'!$C$7:$C$608,F$10,'Offers'!$AI$7:$AI$608,"yes"))=0,"—",SUMIFS('Review'!$O$7:$O$210,'Review'!$B$7:$B$210,$B31,'Review'!$C$7:$C$210,F$10)) | G31: =IF(IF($E$5="Local prices",COUNTIFS('Offers'!$B$7:$B$608,$B31,'Offers'!$C$7:$C$608,G$10,'Offers'!$AH$7:$AH$608,"yes"),COUNTIFS('Offers'!$B$7:$B$608,$B31,'Offers'!$C$7:$C$608,G$10,'Offers'!$AI$7:$AI$608,"yes"))=0,"—",SUMIFS('Review'!$O$7:$O$210,'Review'!$B$7:$B$210,$B31,'Review'!$C$7:$C$210,G$10)) | H31: =IF(IF($E$5="Local prices",COUNTIFS('Offers'!$B$7:$B$608,$B31,'Offers'!$C$7:$C$608,H$10,'Offers'!$AH$7:$AH$608,"yes"),COUNTIFS('Offers'!$B$7:$B$608,$B31,'Offers'!$C$7:$C$608,H$10,'Offers'!$AI$7:$AI$608,"yes"))=0,"—",SUMIFS('Review'!$O$7:$O$210,'Review'!$B$7:$B$210,$B31,'Review'!$C$7:$C$210,H$10))
B32: GN 1/1 PC lid | C32: =IF(IF($E$5="Local prices",COUNTIFS('Offers'!$B$7:$B$608,$B32,'Offers'!$C$7:$C$608,C$10,'Offers'!$AH$7:$AH$608,"yes"),COUNTIFS('Offers'!$B$7:$B$608,$B32,'Offers'!$C$7:$C$608,C$10,'Offers'!$AI$7:$AI$608,"yes"))=0,"—",SUMIFS('Review'!$O$7:$O$210,'Review'!$B$7:$B$210,$B32,'Review'!$C$7:$C$210,C$10)) | D32: =IF(IF($E$5="Local prices",COUNTIFS('Offers'!$B$7:$B$608,$B32,'Offers'!$C$7:$C$608,D$10,'Offers'!$AH$7:$AH$608,"yes"),COUNTIFS('Offers'!$B$7:$B$608,$B32,'Offers'!$C$7:$C$608,D$10,'Offers'!$AI$7:$AI$608,"yes"))=0,"—",SUMIFS('Review'!$O$7:$O$210,'Review'!$B$7:$B$210,$B32,'Review'!$C$7:$C$210,D$10)) | E32: =IF(IF($E$5="Local prices",COUNTIFS('Offers'!$B$7:$B$608,$B32,'Offers'!$C$7:$C$608,E$10,'Offers'!$AH$7:$AH$608,"yes"),COUNTIFS('Offers'!$B$7:$B$608,$B32,'Offers'!$C$7:$C$608,E$10,'Offers'!$AI$7:$AI$608,"yes"))=0,"—",SUMIFS('Review'!$O$7:$O$210,'Review'!$B$7:$B$210,$B32,'Review'!$C$7:$C$210,E$10)) | F32: =IF(IF($E$5="Local prices",COUNTIFS('Offers'!$B$7:$B$608,$B32,'Offers'!$C$7:$C$608,F$10,'Offers'!$AH$7:$AH$608,"yes"),COUNTIFS('Offers'!$B$7:$B$608,$B32,'Offers'!$C$7:$C$608,F$10,'Offers'!$AI$7:$AI$608,"yes"))=0,"—",SUMIFS('Review'!$O$7:$O$210,'Review'!$B$7:$B$210,$B32,'Review'!$C$7:$C$210,F$10)) | G32: =IF(IF($E$5="Local prices",COUNTIFS('Offers'!$B$7:$B$608,$B32,'Offers'!$C$7:$C$608,G$10,'Offers'!$AH$7:$AH$608,"yes"),COUNTIFS('Offers'!$B$7:$B$608,$B32,'Offers'!$C$7:$C$608,G$10,'Offers'!$AI$7:$AI$608,"yes"))=0,"—",SUMIFS('Review'!$O$7:$O$210,'Review'!$B$7:$B$210,$B32,'Review'!$C$7:$C$210,G$10)) | H32: =IF(IF($E$5="Local prices",COUNTIFS('Offers'!$B$7:$B$608,$B32,'Offers'!$C$7:$C$608,H$10,'Offers'!$AH$7:$AH$608,"yes"),COUNTIFS('Offers'!$B$7:$B$608,$B32,'Offers'!$C$7:$C$608,H$10,'Offers'!$AI$7:$AI$608,"yes"))=0,"—",SUMIFS('Review'!$O$7:$O$210,'Review'!$B$7:$B$210,$B32,'Review'!$C$7:$C$210,H$10)) | J32: Match scope
B33: GN 1/6 PP container, 100 mm | C33: =IF(IF($E$5="Local prices",COUNTIFS('Offers'!$B$7:$B$608,$B33,'Offers'!$C$7:$C$608,C$10,'Offers'!$AH$7:$AH$608,"yes"),COUNTIFS('Offers'!$B$7:$B$608,$B33,'Offers'!$C$7:$C$608,C$10,'Offers'!$AI$7:$AI$608,"yes"))=0,"—",SUMIFS('Review'!$O$7:$O$210,'Review'!$B$7:$B$210,$B33,'Review'!$C$7:$C$210,C$10)) | D33: =IF(IF($E$5="Local prices",COUNTIFS('Offers'!$B$7:$B$608,$B33,'Offers'!$C$7:$C$608,D$10,'Offers'!$AH$7:$AH$608,"yes"),COUNTIFS('Offers'!$B$7:$B$608,$B33,'Offers'!$C$7:$C$608,D$10,'Offers'!$AI$7:$AI$608,"yes"))=0,"—",SUMIFS('Review'!$O$7:$O$210,'Review'!$B$7:$B$210,$B33,'Review'!$C$7:$C$210,D$10)) | E33: =IF(IF($E$5="Local prices",COUNTIFS('Offers'!$B$7:$B$608,$B33,'Offers'!$C$7:$C$608,E$10,'Offers'!$AH$7:$AH$608,"yes"),COUNTIFS('Offers'!$B$7:$B$608,$B33,'Offers'!$C$7:$C$608,E$10,'Offers'!$AI$7:$AI$608,"yes"))=0,"—",SUMIFS('Review'!$O$7:$O$210,'Review'!$B$7:$B$210,$B33,'Review'!$C$7:$C$210,E$10)) | F33: =IF(IF($E$5="Local prices",COUNTIFS('Offers'!$B$7:$B$608,$B33,'Offers'!$C$7:$C$608,F$10,'Offers'!$AH$7:$AH$608,"yes"),COUNTIFS('Offers'!$B$7:$B$608,$B33,'Offers'!$C$7:$C$608,F$10,'Offers'!$AI$7:$AI$608,"yes"))=0,"—",SUMIFS('Review'!$O$7:$O$210,'Review'!$B$7:$B$210,$B33,'Review'!$C$7:$C$210,F$10)) | G33: =IF(IF($E$5="Local prices",COUNTIFS('Offers'!$B$7:$B$608,$B33,'Offers'!$C$7:$C$608,G$10,'Offers'!$AH$7:$AH$608,"yes"),COUNTIFS('Offers'!$B$7:$B$608,$B33,'Offers'!$C$7:$C$608,G$10,'Offers'!$AI$7:$AI$608,"yes"))=0,"—",SUMIFS('Review'!$O$7:$O$210,'Review'!$B$7:$B$210,$B33,'Review'!$C$7:$C$210,G$10)) | H33: =IF(IF($E$5="Local prices",COUNTIFS('Offers'!$B$7:$B$608,$B33,'Offers'!$C$7:$C$608,H$10,'Offers'!$AH$7:$AH$608,"yes"),COUNTIFS('Offers'!$B$7:$B$608,$B33,'Offers'!$C$7:$C$608,H$10,'Offers'!$AI$7:$AI$608,"yes"))=0,"—",SUMIFS('Review'!$O$7:$O$210,'Review'!$B$7:$B$210,$B33,'Review'!$C$7:$C$210,H$10)) | J33: All mapped includes near matches and incomplete specifications. Check their notes before deciding.
B34: GN 1/9 PP container, 100 mm | C34: =IF(IF($E$5="Local prices",COUNTIFS('Offers'!$B$7:$B$608,$B34,'Offers'!$C$7:$C$608,C$10,'Offers'!$AH$7:$AH$608,"yes"),COUNTIFS('Offers'!$B$7:$B$608,$B34,'Offers'!$C$7:$C$608,C$10,'Offers'!$AI$7:$AI$608,"yes"))=0,"—",SUMIFS('Review'!$O$7:$O$210,'Review'!$B$7:$B$210,$B34,'Review'!$C$7:$C$210,C$10)) | D34: =IF(IF($E$5="Local prices",COUNTIFS('Offers'!$B$7:$B$608,$B34,'Offers'!$C$7:$C$608,D$10,'Offers'!$AH$7:$AH$608,"yes"),COUNTIFS('Offers'!$B$7:$B$608,$B34,'Offers'!$C$7:$C$608,D$10,'Offers'!$AI$7:$AI$608,"yes"))=0,"—",SUMIFS('Review'!$O$7:$O$210,'Review'!$B$7:$B$210,$B34,'Review'!$C$7:$C$210,D$10)) | E34: =IF(IF($E$5="Local prices",COUNTIFS('Offers'!$B$7:$B$608,$B34,'Offers'!$C$7:$C$608,E$10,'Offers'!$AH$7:$AH$608,"yes"),COUNTIFS('Offers'!$B$7:$B$608,$B34,'Offers'!$C$7:$C$608,E$10,'Offers'!$AI$7:$AI$608,"yes"))=0,"—",SUMIFS('Review'!$O$7:$O$210,'Review'!$B$7:$B$210,$B34,'Review'!$C$7:$C$210,E$10)) | F34: =IF(IF($E$5="Local prices",COUNTIFS('Offers'!$B$7:$B$608,$B34,'Offers'!$C$7:$C$608,F$10,'Offers'!$AH$7:$AH$608,"yes"),COUNTIFS('Offers'!$B$7:$B$608,$B34,'Offers'!$C$7:$C$608,F$10,'Offers'!$AI$7:$AI$608,"yes"))=0,"—",SUMIFS('Review'!$O$7:$O$210,'Review'!$B$7:$B$210,$B34,'Review'!$C$7:$C$210,F$10)) | G34: =IF(IF($E$5="Local prices",COUNTIFS('Offers'!$B$7:$B$608,$B34,'Offers'!$C$7:$C$608,G$10,'Offers'!$AH$7:$AH$608,"yes"),COUNTIFS('Offers'!$B$7:$B$608,$B34,'Offers'!$C$7:$C$608,G$10,'Offers'!$AI$7:$AI$608,"yes"))=0,"—",SUMIFS('Review'!$O$7:$O$210,'Review'!$B$7:$B$210,$B34,'Review'!$C$7:$C$210,G$10)) | H34: =IF(IF($E$5="Local prices",COUNTIFS('Offers'!$B$7:$B$608,$B34,'Offers'!$C$7:$C$608,H$10,'Offers'!$AH$7:$AH$608,"yes"),COUNTIFS('Offers'!$B$7:$B$608,$B34,'Offers'!$C$7:$C$608,H$10,'Offers'!$AI$7:$AI$608,"yes"))=0,"—",SUMIFS('Review'!$O$7:$O$210,'Review'!$B$7:$B$210,$B34,'Review'!$C$7:$C$210,H$10))
B35: Squeeze bottle 250 ml, PP, single tip | C35: =IF(IF($E$5="Local prices",COUNTIFS('Offers'!$B$7:$B$608,$B35,'Offers'!$C$7:$C$608,C$10,'Offers'!$AH$7:$AH$608,"yes"),COUNTIFS('Offers'!$B$7:$B$608,$B35,'Offers'!$C$7:$C$608,C$10,'Offers'!$AI$7:$AI$608,"yes"))=0,"—",SUMIFS('Review'!$O$7:$O$210,'Review'!$B$7:$B$210,$B35,'Review'!$C$7:$C$210,C$10)) | D35: =IF(IF($E$5="Local prices",COUNTIFS('Offers'!$B$7:$B$608,$B35,'Offers'!$C$7:$C$608,D$10,'Offers'!$AH$7:$AH$608,"yes"),COUNTIFS('Offers'!$B$7:$B$608,$B35,'Offers'!$C$7:$C$608,D$10,'Offers'!$AI$7:$AI$608,"yes"))=0,"—",SUMIFS('Review'!$O$7:$O$210,'Review'!$B$7:$B$210,$B35,'Review'!$C$7:$C$210,D$10)) | E35: =IF(IF($E$5="Local prices",COUNTIFS('Offers'!$B$7:$B$608,$B35,'Offers'!$C$7:$C$608,E$10,'Offers'!$AH$7:$AH$608,"yes"),COUNTIFS('Offers'!$B$7:$B$608,$B35,'Offers'!$C$7:$C$608,E$10,'Offers'!$AI$7:$AI$608,"yes"))=0,"—",SUMIFS('Review'!$O$7:$O$210,'Review'!$B$7:$B$210,$B35,'Review'!$C$7:$C$210,E$10)) | F35: =IF(IF($E$5="Local prices",COUNTIFS('Offers'!$B$7:$B$608,$B35,'Offers'!$C$7:$C$608,F$10,'Offers'!$AH$7:$AH$608,"yes"),COUNTIFS('Offers'!$B$7:$B$608,$B35,'Offers'!$C$7:$C$608,F$10,'Offers'!$AI$7:$AI$608,"yes"))=0,"—",SUMIFS('Review'!$O$7:$O$210,'Review'!$B$7:$B$210,$B35,'Review'!$C$7:$C$210,F$10)) | G35: =IF(IF($E$5="Local prices",COUNTIFS('Offers'!$B$7:$B$608,$B35,'Offers'!$C$7:$C$608,G$10,'Offers'!$AH$7:$AH$608,"yes"),COUNTIFS('Offers'!$B$7:$B$608,$B35,'Offers'!$C$7:$C$608,G$10,'Offers'!$AI$7:$AI$608,"yes"))=0,"—",SUMIFS('Review'!$O$7:$O$210,'Review'!$B$7:$B$210,$B35,'Review'!$C$7:$C$210,G$10)) | H35: =IF(IF($E$5="Local prices",COUNTIFS('Offers'!$B$7:$B$608,$B35,'Offers'!$C$7:$C$608,H$10,'Offers'!$AH$7:$AH$608,"yes"),COUNTIFS('Offers'!$B$7:$B$608,$B35,'Offers'!$C$7:$C$608,H$10,'Offers'!$AI$7:$AI$608,"yes"))=0,"—",SUMIFS('Review'!$O$7:$O$210,'Review'!$B$7:$B$210,$B35,'Review'!$C$7:$C$210,H$10))
B36: Squeeze bottle 750 ml, PP, single tip | C36: =IF(IF($E$5="Local prices",COUNTIFS('Offers'!$B$7:$B$608,$B36,'Offers'!$C$7:$C$608,C$10,'Offers'!$AH$7:$AH$608,"yes"),COUNTIFS('Offers'!$B$7:$B$608,$B36,'Offers'!$C$7:$C$608,C$10,'Offers'!$AI$7:$AI$608,"yes"))=0,"—",SUMIFS('Review'!$O$7:$O$210,'Review'!$B$7:$B$210,$B36,'Review'!$C$7:$C$210,C$10)) | D36: =IF(IF($E$5="Local prices",COUNTIFS('Offers'!$B$7:$B$608,$B36,'Offers'!$C$7:$C$608,D$10,'Offers'!$AH$7:$AH$608,"yes"),COUNTIFS('Offers'!$B$7:$B$608,$B36,'Offers'!$C$7:$C$608,D$10,'Offers'!$AI$7:$AI$608,"yes"))=0,"—",SUMIFS('Review'!$O$7:$O$210,'Review'!$B$7:$B$210,$B36,'Review'!$C$7:$C$210,D$10)) | E36: =IF(IF($E$5="Local prices",COUNTIFS('Offers'!$B$7:$B$608,$B36,'Offers'!$C$7:$C$608,E$10,'Offers'!$AH$7:$AH$608,"yes"),COUNTIFS('Offers'!$B$7:$B$608,$B36,'Offers'!$C$7:$C$608,E$10,'Offers'!$AI$7:$AI$608,"yes"))=0,"—",SUMIFS('Review'!$O$7:$O$210,'Review'!$B$7:$B$210,$B36,'Review'!$C$7:$C$210,E$10)) | F36: =IF(IF($E$5="Local prices",COUNTIFS('Offers'!$B$7:$B$608,$B36,'Offers'!$C$7:$C$608,F$10,'Offers'!$AH$7:$AH$608,"yes"),COUNTIFS('Offers'!$B$7:$B$608,$B36,'Offers'!$C$7:$C$608,F$10,'Offers'!$AI$7:$AI$608,"yes"))=0,"—",SUMIFS('Review'!$O$7:$O$210,'Review'!$B$7:$B$210,$B36,'Review'!$C$7:$C$210,F$10)) | G36: =IF(IF($E$5="Local prices",COUNTIFS('Offers'!$B$7:$B$608,$B36,'Offers'!$C$7:$C$608,G$10,'Offers'!$AH$7:$AH$608,"yes"),COUNTIFS('Offers'!$B$7:$B$608,$B36,'Offers'!$C$7:$C$608,G$10,'Offers'!$AI$7:$AI$608,"yes"))=0,"—",SUMIFS('Review'!$O$7:$O$210,'Review'!$B$7:$B$210,$B36,'Review'!$C$7:$C$210,G$10)) | H36: =IF(IF($E$5="Local prices",COUNTIFS('Offers'!$B$7:$B$608,$B36,'Offers'!$C$7:$C$608,H$10,'Offers'!$AH$7:$AH$608,"yes"),COUNTIFS('Offers'!$B$7:$B$608,$B36,'Offers'!$C$7:$C$608,H$10,'Offers'!$AI$7:$AI$608,"yes"))=0,"—",SUMIFS('Review'!$O$7:$O$210,'Review'!$B$7:$B$210,$B36,'Review'!$C$7:$C$210,H$10)) | J36: Additional variants
B37: Red PE cutting board 400 × 300 × 20 mm | C37: =IF(IF($E$5="Local prices",COUNTIFS('Offers'!$B$7:$B$608,$B37,'Offers'!$C$7:$C$608,C$10,'Offers'!$AH$7:$AH$608,"yes"),COUNTIFS('Offers'!$B$7:$B$608,$B37,'Offers'!$C$7:$C$608,C$10,'Offers'!$AI$7:$AI$608,"yes"))=0,"—",SUMIFS('Review'!$O$7:$O$210,'Review'!$B$7:$B$210,$B37,'Review'!$C$7:$C$210,C$10)) | D37: =IF(IF($E$5="Local prices",COUNTIFS('Offers'!$B$7:$B$608,$B37,'Offers'!$C$7:$C$608,D$10,'Offers'!$AH$7:$AH$608,"yes"),COUNTIFS('Offers'!$B$7:$B$608,$B37,'Offers'!$C$7:$C$608,D$10,'Offers'!$AI$7:$AI$608,"yes"))=0,"—",SUMIFS('Review'!$O$7:$O$210,'Review'!$B$7:$B$210,$B37,'Review'!$C$7:$C$210,D$10)) | E37: =IF(IF($E$5="Local prices",COUNTIFS('Offers'!$B$7:$B$608,$B37,'Offers'!$C$7:$C$608,E$10,'Offers'!$AH$7:$AH$608,"yes"),COUNTIFS('Offers'!$B$7:$B$608,$B37,'Offers'!$C$7:$C$608,E$10,'Offers'!$AI$7:$AI$608,"yes"))=0,"—",SUMIFS('Review'!$O$7:$O$210,'Review'!$B$7:$B$210,$B37,'Review'!$C$7:$C$210,E$10)) | F37: =IF(IF($E$5="Local prices",COUNTIFS('Offers'!$B$7:$B$608,$B37,'Offers'!$C$7:$C$608,F$10,'Offers'!$AH$7:$AH$608,"yes"),COUNTIFS('Offers'!$B$7:$B$608,$B37,'Offers'!$C$7:$C$608,F$10,'Offers'!$AI$7:$AI$608,"yes"))=0,"—",SUMIFS('Review'!$O$7:$O$210,'Review'!$B$7:$B$210,$B37,'Review'!$C$7:$C$210,F$10)) | G37: =IF(IF($E$5="Local prices",COUNTIFS('Offers'!$B$7:$B$608,$B37,'Offers'!$C$7:$C$608,G$10,'Offers'!$AH$7:$AH$608,"yes"),COUNTIFS('Offers'!$B$7:$B$608,$B37,'Offers'!$C$7:$C$608,G$10,'Offers'!$AI$7:$AI$608,"yes"))=0,"—",SUMIFS('Review'!$O$7:$O$210,'Review'!$B$7:$B$210,$B37,'Review'!$C$7:$C$210,G$10)) | H37: =IF(IF($E$5="Local prices",COUNTIFS('Offers'!$B$7:$B$608,$B37,'Offers'!$C$7:$C$608,H$10,'Offers'!$AH$7:$AH$608,"yes"),COUNTIFS('Offers'!$B$7:$B$608,$B37,'Offers'!$C$7:$C$608,H$10,'Offers'!$AI$7:$AI$608,"yes"))=0,"—",SUMIFS('Review'!$O$7:$O$210,'Review'!$B$7:$B$210,$B37,'Review'!$C$7:$C$210,H$10)) | J37: New variants have research for Austria and Czechia. A dash in the other markets means no offer has been imported.
B38: PP dough box 600 × 400 × 75 mm, no lid | C38: =IF(IF($E$5="Local prices",COUNTIFS('Offers'!$B$7:$B$608,$B38,'Offers'!$C$7:$C$608,C$10,'Offers'!$AH$7:$AH$608,"yes"),COUNTIFS('Offers'!$B$7:$B$608,$B38,'Offers'!$C$7:$C$608,C$10,'Offers'!$AI$7:$AI$608,"yes"))=0,"—",SUMIFS('Review'!$O$7:$O$210,'Review'!$B$7:$B$210,$B38,'Review'!$C$7:$C$210,C$10)) | D38: =IF(IF($E$5="Local prices",COUNTIFS('Offers'!$B$7:$B$608,$B38,'Offers'!$C$7:$C$608,D$10,'Offers'!$AH$7:$AH$608,"yes"),COUNTIFS('Offers'!$B$7:$B$608,$B38,'Offers'!$C$7:$C$608,D$10,'Offers'!$AI$7:$AI$608,"yes"))=0,"—",SUMIFS('Review'!$O$7:$O$210,'Review'!$B$7:$B$210,$B38,'Review'!$C$7:$C$210,D$10)) | E38: =IF(IF($E$5="Local prices",COUNTIFS('Offers'!$B$7:$B$608,$B38,'Offers'!$C$7:$C$608,E$10,'Offers'!$AH$7:$AH$608,"yes"),COUNTIFS('Offers'!$B$7:$B$608,$B38,'Offers'!$C$7:$C$608,E$10,'Offers'!$AI$7:$AI$608,"yes"))=0,"—",SUMIFS('Review'!$O$7:$O$210,'Review'!$B$7:$B$210,$B38,'Review'!$C$7:$C$210,E$10)) | F38: =IF(IF($E$5="Local prices",COUNTIFS('Offers'!$B$7:$B$608,$B38,'Offers'!$C$7:$C$608,F$10,'Offers'!$AH$7:$AH$608,"yes"),COUNTIFS('Offers'!$B$7:$B$608,$B38,'Offers'!$C$7:$C$608,F$10,'Offers'!$AI$7:$AI$608,"yes"))=0,"—",SUMIFS('Review'!$O$7:$O$210,'Review'!$B$7:$B$210,$B38,'Review'!$C$7:$C$210,F$10)) | G38: =IF(IF($E$5="Local prices",COUNTIFS('Offers'!$B$7:$B$608,$B38,'Offers'!$C$7:$C$608,G$10,'Offers'!$AH$7:$AH$608,"yes"),COUNTIFS('Offers'!$B$7:$B$608,$B38,'Offers'!$C$7:$C$608,G$10,'Offers'!$AI$7:$AI$608,"yes"))=0,"—",SUMIFS('Review'!$O$7:$O$210,'Review'!$B$7:$B$210,$B38,'Review'!$C$7:$C$210,G$10)) | H38: =IF(IF($E$5="Local prices",COUNTIFS('Offers'!$B$7:$B$608,$B38,'Offers'!$C$7:$C$608,H$10,'Offers'!$AH$7:$AH$608,"yes"),COUNTIFS('Offers'!$B$7:$B$608,$B38,'Offers'!$C$7:$C$608,H$10,'Offers'!$AI$7:$AI$608,"yes"))=0,"—",SUMIFS('Review'!$O$7:$O$210,'Review'!$B$7:$B$210,$B38,'Review'!$C$7:$C$210,H$10))
B39: GN 1/1 PC container, 100 mm | C39: =IF(IF($E$5="Local prices",COUNTIFS('Offers'!$B$7:$B$608,$B39,'Offers'!$C$7:$C$608,C$10,'Offers'!$AH$7:$AH$608,"yes"),COUNTIFS('Offers'!$B$7:$B$608,$B39,'Offers'!$C$7:$C$608,C$10,'Offers'!$AI$7:$AI$608,"yes"))=0,"—",SUMIFS('Review'!$O$7:$O$210,'Review'!$B$7:$B$210,$B39,'Review'!$C$7:$C$210,C$10)) | D39: =IF(IF($E$5="Local prices",COUNTIFS('Offers'!$B$7:$B$608,$B39,'Offers'!$C$7:$C$608,D$10,'Offers'!$AH$7:$AH$608,"yes"),COUNTIFS('Offers'!$B$7:$B$608,$B39,'Offers'!$C$7:$C$608,D$10,'Offers'!$AI$7:$AI$608,"yes"))=0,"—",SUMIFS('Review'!$O$7:$O$210,'Review'!$B$7:$B$210,$B39,'Review'!$C$7:$C$210,D$10)) | E39: =IF(IF($E$5="Local prices",COUNTIFS('Offers'!$B$7:$B$608,$B39,'Offers'!$C$7:$C$608,E$10,'Offers'!$AH$7:$AH$608,"yes"),COUNTIFS('Offers'!$B$7:$B$608,$B39,'Offers'!$C$7:$C$608,E$10,'Offers'!$AI$7:$AI$608,"yes"))=0,"—",SUMIFS('Review'!$O$7:$O$210,'Review'!$B$7:$B$210,$B39,'Review'!$C$7:$C$210,E$10)) | F39: =IF(IF($E$5="Local prices",COUNTIFS('Offers'!$B$7:$B$608,$B39,'Offers'!$C$7:$C$608,F$10,'Offers'!$AH$7:$AH$608,"yes"),COUNTIFS('Offers'!$B$7:$B$608,$B39,'Offers'!$C$7:$C$608,F$10,'Offers'!$AI$7:$AI$608,"yes"))=0,"—",SUMIFS('Review'!$O$7:$O$210,'Review'!$B$7:$B$210,$B39,'Review'!$C$7:$C$210,F$10)) | G39: =IF(IF($E$5="Local prices",COUNTIFS('Offers'!$B$7:$B$608,$B39,'Offers'!$C$7:$C$608,G$10,'Offers'!$AH$7:$AH$608,"yes"),COUNTIFS('Offers'!$B$7:$B$608,$B39,'Offers'!$C$7:$C$608,G$10,'Offers'!$AI$7:$AI$608,"yes"))=0,"—",SUMIFS('Review'!$O$7:$O$210,'Review'!$B$7:$B$210,$B39,'Review'!$C$7:$C$210,G$10)) | H39: =IF(IF($E$5="Local prices",COUNTIFS('Offers'!$B$7:$B$608,$B39,'Offers'!$C$7:$C$608,H$10,'Offers'!$AH$7:$AH$608,"yes"),COUNTIFS('Offers'!$B$7:$B$608,$B39,'Offers'!$C$7:$C$608,H$10,'Offers'!$AI$7:$AI$608,"yes"))=0,"—",SUMIFS('Review'!$O$7:$O$210,'Review'!$B$7:$B$210,$B39,'Review'!$C$7:$C$210,H$10))
B40: GN 1/6 PC container, 100 mm | C40: =IF(IF($E$5="Local prices",COUNTIFS('Offers'!$B$7:$B$608,$B40,'Offers'!$C$7:$C$608,C$10,'Offers'!$AH$7:$AH$608,"yes"),COUNTIFS('Offers'!$B$7:$B$608,$B40,'Offers'!$C$7:$C$608,C$10,'Offers'!$AI$7:$AI$608,"yes"))=0,"—",SUMIFS('Review'!$O$7:$O$210,'Review'!$B$7:$B$210,$B40,'Review'!$C$7:$C$210,C$10)) | D40: =IF(IF($E$5="Local prices",COUNTIFS('Offers'!$B$7:$B$608,$B40,'Offers'!$C$7:$C$608,D$10,'Offers'!$AH$7:$AH$608,"yes"),COUNTIFS('Offers'!$B$7:$B$608,$B40,'Offers'!$C$7:$C$608,D$10,'Offers'!$AI$7:$AI$608,"yes"))=0,"—",SUMIFS('Review'!$O$7:$O$210,'Review'!$B$7:$B$210,$B40,'Review'!$C$7:$C$210,D$10)) | E40: =IF(IF($E$5="Local prices",COUNTIFS('Offers'!$B$7:$B$608,$B40,'Offers'!$C$7:$C$608,E$10,'Offers'!$AH$7:$AH$608,"yes"),COUNTIFS('Offers'!$B$7:$B$608,$B40,'Offers'!$C$7:$C$608,E$10,'Offers'!$AI$7:$AI$608,"yes"))=0,"—",SUMIFS('Review'!$O$7:$O$210,'Review'!$B$7:$B$210,$B40,'Review'!$C$7:$C$210,E$10)) | F40: =IF(IF($E$5="Local prices",COUNTIFS('Offers'!$B$7:$B$608,$B40,'Offers'!$C$7:$C$608,F$10,'Offers'!$AH$7:$AH$608,"yes"),COUNTIFS('Offers'!$B$7:$B$608,$B40,'Offers'!$C$7:$C$608,F$10,'Offers'!$AI$7:$AI$608,"yes"))=0,"—",SUMIFS('Review'!$O$7:$O$210,'Review'!$B$7:$B$210,$B40,'Review'!$C$7:$C$210,F$10)) | G40: =IF(IF($E$5="Local prices",COUNTIFS('Offers'!$B$7:$B$608,$B40,'Offers'!$C$7:$C$608,G$10,'Offers'!$AH$7:$AH$608,"yes"),COUNTIFS('Offers'!$B$7:$B$608,$B40,'Offers'!$C$7:$C$608,G$10,'Offers'!$AI$7:$AI$608,"yes"))=0,"—",SUMIFS('Review'!$O$7:$O$210,'Review'!$B$7:$B$210,$B40,'Review'!$C$7:$C$210,G$10)) | H40: =IF(IF($E$5="Local prices",COUNTIFS('Offers'!$B$7:$B$608,$B40,'Offers'!$C$7:$C$608,H$10,'Offers'!$AH$7:$AH$608,"yes"),COUNTIFS('Offers'!$B$7:$B$608,$B40,'Offers'!$C$7:$C$608,H$10,'Offers'!$AI$7:$AI$608,"yes"))=0,"—",SUMIFS('Review'!$O$7:$O$210,'Review'!$B$7:$B$210,$B40,'Review'!$C$7:$C$210,H$10))
B41: Red PE cutting board 530 × 325 × 15 mm | C41: =IF(IF($E$5="Local prices",COUNTIFS('Offers'!$B$7:$B$608,$B41,'Offers'!$C$7:$C$608,C$10,'Offers'!$AH$7:$AH$608,"yes"),COUNTIFS('Offers'!$B$7:$B$608,$B41,'Offers'!$C$7:$C$608,C$10,'Offers'!$AI$7:$AI$608,"yes"))=0,"—",SUMIFS('Review'!$O$7:$O$210,'Review'!$B$7:$B$210,$B41,'Review'!$C$7:$C$210,C$10)) | D41: =IF(IF($E$5="Local prices",COUNTIFS('Offers'!$B$7:$B$608,$B41,'Offers'!$C$7:$C$608,D$10,'Offers'!$AH$7:$AH$608,"yes"),COUNTIFS('Offers'!$B$7:$B$608,$B41,'Offers'!$C$7:$C$608,D$10,'Offers'!$AI$7:$AI$608,"yes"))=0,"—",SUMIFS('Review'!$O$7:$O$210,'Review'!$B$7:$B$210,$B41,'Review'!$C$7:$C$210,D$10)) | E41: =IF(IF($E$5="Local prices",COUNTIFS('Offers'!$B$7:$B$608,$B41,'Offers'!$C$7:$C$608,E$10,'Offers'!$AH$7:$AH$608,"yes"),COUNTIFS('Offers'!$B$7:$B$608,$B41,'Offers'!$C$7:$C$608,E$10,'Offers'!$AI$7:$AI$608,"yes"))=0,"—",SUMIFS('Review'!$O$7:$O$210,'Review'!$B$7:$B$210,$B41,'Review'!$C$7:$C$210,E$10)) | F41: =IF(IF($E$5="Local prices",COUNTIFS('Offers'!$B$7:$B$608,$B41,'Offers'!$C$7:$C$608,F$10,'Offers'!$AH$7:$AH$608,"yes"),COUNTIFS('Offers'!$B$7:$B$608,$B41,'Offers'!$C$7:$C$608,F$10,'Offers'!$AI$7:$AI$608,"yes"))=0,"—",SUMIFS('Review'!$O$7:$O$210,'Review'!$B$7:$B$210,$B41,'Review'!$C$7:$C$210,F$10)) | G41: =IF(IF($E$5="Local prices",COUNTIFS('Offers'!$B$7:$B$608,$B41,'Offers'!$C$7:$C$608,G$10,'Offers'!$AH$7:$AH$608,"yes"),COUNTIFS('Offers'!$B$7:$B$608,$B41,'Offers'!$C$7:$C$608,G$10,'Offers'!$AI$7:$AI$608,"yes"))=0,"—",SUMIFS('Review'!$O$7:$O$210,'Review'!$B$7:$B$210,$B41,'Review'!$C$7:$C$210,G$10)) | H41: =IF(IF($E$5="Local prices",COUNTIFS('Offers'!$B$7:$B$608,$B41,'Offers'!$C$7:$C$608,H$10,'Offers'!$AH$7:$AH$608,"yes"),COUNTIFS('Offers'!$B$7:$B$608,$B41,'Offers'!$C$7:$C$608,H$10,'Offers'!$AI$7:$AI$608,"yes"))=0,"—",SUMIFS('Review'!$O$7:$O$210,'Review'!$B$7:$B$210,$B41,'Review'!$C$7:$C$210,H$10))
B42: GN 1/3 PP lid | C42: =IF(IF($E$5="Local prices",COUNTIFS('Offers'!$B$7:$B$608,$B42,'Offers'!$C$7:$C$608,C$10,'Offers'!$AH$7:$AH$608,"yes"),COUNTIFS('Offers'!$B$7:$B$608,$B42,'Offers'!$C$7:$C$608,C$10,'Offers'!$AI$7:$AI$608,"yes"))=0,"—",SUMIFS('Review'!$O$7:$O$210,'Review'!$B$7:$B$210,$B42,'Review'!$C$7:$C$210,C$10)) | D42: =IF(IF($E$5="Local prices",COUNTIFS('Offers'!$B$7:$B$608,$B42,'Offers'!$C$7:$C$608,D$10,'Offers'!$AH$7:$AH$608,"yes"),COUNTIFS('Offers'!$B$7:$B$608,$B42,'Offers'!$C$7:$C$608,D$10,'Offers'!$AI$7:$AI$608,"yes"))=0,"—",SUMIFS('Review'!$O$7:$O$210,'Review'!$B$7:$B$210,$B42,'Review'!$C$7:$C$210,D$10)) | E42: =IF(IF($E$5="Local prices",COUNTIFS('Offers'!$B$7:$B$608,$B42,'Offers'!$C$7:$C$608,E$10,'Offers'!$AH$7:$AH$608,"yes"),COUNTIFS('Offers'!$B$7:$B$608,$B42,'Offers'!$C$7:$C$608,E$10,'Offers'!$AI$7:$AI$608,"yes"))=0,"—",SUMIFS('Review'!$O$7:$O$210,'Review'!$B$7:$B$210,$B42,'Review'!$C$7:$C$210,E$10)) | F42: =IF(IF($E$5="Local prices",COUNTIFS('Offers'!$B$7:$B$608,$B42,'Offers'!$C$7:$C$608,F$10,'Offers'!$AH$7:$AH$608,"yes"),COUNTIFS('Offers'!$B$7:$B$608,$B42,'Offers'!$C$7:$C$608,F$10,'Offers'!$AI$7:$AI$608,"yes"))=0,"—",SUMIFS('Review'!$O$7:$O$210,'Review'!$B$7:$B$210,$B42,'Review'!$C$7:$C$210,F$10)) | G42: =IF(IF($E$5="Local prices",COUNTIFS('Offers'!$B$7:$B$608,$B42,'Offers'!$C$7:$C$608,G$10,'Offers'!$AH$7:$AH$608,"yes"),COUNTIFS('Offers'!$B$7:$B$608,$B42,'Offers'!$C$7:$C$608,G$10,'Offers'!$AI$7:$AI$608,"yes"))=0,"—",SUMIFS('Review'!$O$7:$O$210,'Review'!$B$7:$B$210,$B42,'Review'!$C$7:$C$210,G$10)) | H42: =IF(IF($E$5="Local prices",COUNTIFS('Offers'!$B$7:$B$608,$B42,'Offers'!$C$7:$C$608,H$10,'Offers'!$AH$7:$AH$608,"yes"),COUNTIFS('Offers'!$B$7:$B$608,$B42,'Offers'!$C$7:$C$608,H$10,'Offers'!$AI$7:$AI$608,"yes"))=0,"—",SUMIFS('Review'!$O$7:$O$210,'Review'!$B$7:$B$210,$B42,'Review'!$C$7:$C$210,H$10))
B43: Squeeze bottle 750 ml, PP/PE, wide covered tip | C43: =IF(IF($E$5="Local prices",COUNTIFS('Offers'!$B$7:$B$608,$B43,'Offers'!$C$7:$C$608,C$10,'Offers'!$AH$7:$AH$608,"yes"),COUNTIFS('Offers'!$B$7:$B$608,$B43,'Offers'!$C$7:$C$608,C$10,'Offers'!$AI$7:$AI$608,"yes"))=0,"—",SUMIFS('Review'!$O$7:$O$210,'Review'!$B$7:$B$210,$B43,'Review'!$C$7:$C$210,C$10)) | D43: =IF(IF($E$5="Local prices",COUNTIFS('Offers'!$B$7:$B$608,$B43,'Offers'!$C$7:$C$608,D$10,'Offers'!$AH$7:$AH$608,"yes"),COUNTIFS('Offers'!$B$7:$B$608,$B43,'Offers'!$C$7:$C$608,D$10,'Offers'!$AI$7:$AI$608,"yes"))=0,"—",SUMIFS('Review'!$O$7:$O$210,'Review'!$B$7:$B$210,$B43,'Review'!$C$7:$C$210,D$10)) | E43: =IF(IF($E$5="Local prices",COUNTIFS('Offers'!$B$7:$B$608,$B43,'Offers'!$C$7:$C$608,E$10,'Offers'!$AH$7:$AH$608,"yes"),COUNTIFS('Offers'!$B$7:$B$608,$B43,'Offers'!$C$7:$C$608,E$10,'Offers'!$AI$7:$AI$608,"yes"))=0,"—",SUMIFS('Review'!$O$7:$O$210,'Review'!$B$7:$B$210,$B43,'Review'!$C$7:$C$210,E$10)) | F43: =IF(IF($E$5="Local prices",COUNTIFS('Offers'!$B$7:$B$608,$B43,'Offers'!$C$7:$C$608,F$10,'Offers'!$AH$7:$AH$608,"yes"),COUNTIFS('Offers'!$B$7:$B$608,$B43,'Offers'!$C$7:$C$608,F$10,'Offers'!$AI$7:$AI$608,"yes"))=0,"—",SUMIFS('Review'!$O$7:$O$210,'Review'!$B$7:$B$210,$B43,'Review'!$C$7:$C$210,F$10)) | G43: =IF(IF($E$5="Local prices",COUNTIFS('Offers'!$B$7:$B$608,$B43,'Offers'!$C$7:$C$608,G$10,'Offers'!$AH$7:$AH$608,"yes"),COUNTIFS('Offers'!$B$7:$B$608,$B43,'Offers'!$C$7:$C$608,G$10,'Offers'!$AI$7:$AI$608,"yes"))=0,"—",SUMIFS('Review'!$O$7:$O$210,'Review'!$B$7:$B$210,$B43,'Review'!$C$7:$C$210,G$10)) | H43: =IF(IF($E$5="Local prices",COUNTIFS('Offers'!$B$7:$B$608,$B43,'Offers'!$C$7:$C$608,H$10,'Offers'!$AH$7:$AH$608,"yes"),COUNTIFS('Offers'!$B$7:$B$608,$B43,'Offers'!$C$7:$C$608,H$10,'Offers'!$AI$7:$AI$608,"yes"))=0,"—",SUMIFS('Review'!$O$7:$O$210,'Review'!$B$7:$B$210,$B43,'Review'!$C$7:$C$210,H$10))
B44: Red PE cutting board 300 × 200 × 20 mm | C44: =IF(IF($E$5="Local prices",COUNTIFS('Offers'!$B$7:$B$608,$B44,'Offers'!$C$7:$C$608,C$10,'Offers'!$AH$7:$AH$608,"yes"),COUNTIFS('Offers'!$B$7:$B$608,$B44,'Offers'!$C$7:$C$608,C$10,'Offers'!$AI$7:$AI$608,"yes"))=0,"—",SUMIFS('Review'!$O$7:$O$210,'Review'!$B$7:$B$210,$B44,'Review'!$C$7:$C$210,C$10)) | D44: =IF(IF($E$5="Local prices",COUNTIFS('Offers'!$B$7:$B$608,$B44,'Offers'!$C$7:$C$608,D$10,'Offers'!$AH$7:$AH$608,"yes"),COUNTIFS('Offers'!$B$7:$B$608,$B44,'Offers'!$C$7:$C$608,D$10,'Offers'!$AI$7:$AI$608,"yes"))=0,"—",SUMIFS('Review'!$O$7:$O$210,'Review'!$B$7:$B$210,$B44,'Review'!$C$7:$C$210,D$10)) | E44: =IF(IF($E$5="Local prices",COUNTIFS('Offers'!$B$7:$B$608,$B44,'Offers'!$C$7:$C$608,E$10,'Offers'!$AH$7:$AH$608,"yes"),COUNTIFS('Offers'!$B$7:$B$608,$B44,'Offers'!$C$7:$C$608,E$10,'Offers'!$AI$7:$AI$608,"yes"))=0,"—",SUMIFS('Review'!$O$7:$O$210,'Review'!$B$7:$B$210,$B44,'Review'!$C$7:$C$210,E$10)) | F44: =IF(IF($E$5="Local prices",COUNTIFS('Offers'!$B$7:$B$608,$B44,'Offers'!$C$7:$C$608,F$10,'Offers'!$AH$7:$AH$608,"yes"),COUNTIFS('Offers'!$B$7:$B$608,$B44,'Offers'!$C$7:$C$608,F$10,'Offers'!$AI$7:$AI$608,"yes"))=0,"—",SUMIFS('Review'!$O$7:$O$210,'Review'!$B$7:$B$210,$B44,'Review'!$C$7:$C$210,F$10)) | G44: =IF(IF($E$5="Local prices",COUNTIFS('Offers'!$B$7:$B$608,$B44,'Offers'!$C$7:$C$608,G$10,'Offers'!$AH$7:$AH$608,"yes"),COUNTIFS('Offers'!$B$7:$B$608,$B44,'Offers'!$C$7:$C$608,G$10,'Offers'!$AI$7:$AI$608,"yes"))=0,"—",SUMIFS('Review'!$O$7:$O$210,'Review'!$B$7:$B$210,$B44,'Review'!$C$7:$C$210,G$10)) | H44: =IF(IF($E$5="Local prices",COUNTIFS('Offers'!$B$7:$B$608,$B44,'Offers'!$C$7:$C$608,H$10,'Offers'!$AH$7:$AH$608,"yes"),COUNTIFS('Offers'!$B$7:$B$608,$B44,'Offers'!$C$7:$C$608,H$10,'Offers'!$AI$7:$AI$608,"yes"))=0,"—",SUMIFS('Review'!$O$7:$O$210,'Review'!$B$7:$B$210,$B44,'Review'!$C$7:$C$210,H$10))
B45: PP dough box 400 × 300 × 100 mm, no lid | C45: =IF(IF($E$5="Local prices",COUNTIFS('Offers'!$B$7:$B$608,$B45,'Offers'!$C$7:$C$608,C$10,'Offers'!$AH$7:$AH$608,"yes"),COUNTIFS('Offers'!$B$7:$B$608,$B45,'Offers'!$C$7:$C$608,C$10,'Offers'!$AI$7:$AI$608,"yes"))=0,"—",SUMIFS('Review'!$O$7:$O$210,'Review'!$B$7:$B$210,$B45,'Review'!$C$7:$C$210,C$10)) | D45: =IF(IF($E$5="Local prices",COUNTIFS('Offers'!$B$7:$B$608,$B45,'Offers'!$C$7:$C$608,D$10,'Offers'!$AH$7:$AH$608,"yes"),COUNTIFS('Offers'!$B$7:$B$608,$B45,'Offers'!$C$7:$C$608,D$10,'Offers'!$AI$7:$AI$608,"yes"))=0,"—",SUMIFS('Review'!$O$7:$O$210,'Review'!$B$7:$B$210,$B45,'Review'!$C$7:$C$210,D$10)) | E45: =IF(IF($E$5="Local prices",COUNTIFS('Offers'!$B$7:$B$608,$B45,'Offers'!$C$7:$C$608,E$10,'Offers'!$AH$7:$AH$608,"yes"),COUNTIFS('Offers'!$B$7:$B$608,$B45,'Offers'!$C$7:$C$608,E$10,'Offers'!$AI$7:$AI$608,"yes"))=0,"—",SUMIFS('Review'!$O$7:$O$210,'Review'!$B$7:$B$210,$B45,'Review'!$C$7:$C$210,E$10)) | F45: =IF(IF($E$5="Local prices",COUNTIFS('Offers'!$B$7:$B$608,$B45,'Offers'!$C$7:$C$608,F$10,'Offers'!$AH$7:$AH$608,"yes"),COUNTIFS('Offers'!$B$7:$B$608,$B45,'Offers'!$C$7:$C$608,F$10,'Offers'!$AI$7:$AI$608,"yes"))=0,"—",SUMIFS('Review'!$O$7:$O$210,'Review'!$B$7:$B$210,$B45,'Review'!$C$7:$C$210,F$10)) | G45: =IF(IF($E$5="Local prices",COUNTIFS('Offers'!$B$7:$B$608,$B45,'Offers'!$C$7:$C$608,G$10,'Offers'!$AH$7:$AH$608,"yes"),COUNTIFS('Offers'!$B$7:$B$608,$B45,'Offers'!$C$7:$C$608,G$10,'Offers'!$AI$7:$AI$608,"yes"))=0,"—",SUMIFS('Review'!$O$7:$O$210,'Review'!$B$7:$B$210,$B45,'Review'!$C$7:$C$210,G$10)) | H45: =IF(IF($E$5="Local prices",COUNTIFS('Offers'!$B$7:$B$608,$B45,'Offers'!$C$7:$C$608,H$10,'Offers'!$AH$7:$AH$608,"yes"),COUNTIFS('Offers'!$B$7:$B$608,$B45,'Offers'!$C$7:$C$608,H$10,'Offers'!$AI$7:$AI$608,"yes"))=0,"—",SUMIFS('Review'!$O$7:$O$210,'Review'!$B$7:$B$210,$B45,'Review'!$C$7:$C$210,H$10))
B48: Research dates
B49: Market | C49: Oldest date | D49: Newest date
B50: Hungary | C50: =_xlfn.MINIFS('Offers'!$AJ$7:$AJ$608,'Offers'!$C$7:$C$608,B50,'Offers'!$AJ$7:$AJ$608,">0") | D50: =_xlfn.MAXIFS('Offers'!$AJ$7:$AJ$608,'Offers'!$C$7:$C$608,B50)
B51: Romania | C51: =_xlfn.MINIFS('Offers'!$AJ$7:$AJ$608,'Offers'!$C$7:$C$608,B51,'Offers'!$AJ$7:$AJ$608,">0") | D51: =_xlfn.MAXIFS('Offers'!$AJ$7:$AJ$608,'Offers'!$C$7:$C$608,B51)
B52: Austria | C52: =_xlfn.MINIFS('Offers'!$AJ$7:$AJ$608,'Offers'!$C$7:$C$608,B52,'Offers'!$AJ$7:$AJ$608,">0") | D52: =_xlfn.MAXIFS('Offers'!$AJ$7:$AJ$608,'Offers'!$C$7:$C$608,B52)
B53: Germany | C53: =_xlfn.MINIFS('Offers'!$AJ$7:$AJ$608,'Offers'!$C$7:$C$608,B53,'Offers'!$AJ$7:$AJ$608,">0") | D53: =_xlfn.MAXIFS('Offers'!$AJ$7:$AJ$608,'Offers'!$C$7:$C$608,B53)
B54: Czech | C54: =_xlfn.MINIFS('Offers'!$AJ$7:$AJ$608,'Offers'!$C$7:$C$608,B54,'Offers'!$AJ$7:$AJ$608,">0") | D54: =_xlfn.MAXIFS('Offers'!$AJ$7:$AJ$608,'Offers'!$C$7:$C$608,B54)
B55: Slovakia | C55: =_xlfn.MINIFS('Offers'!$AJ$7:$AJ$608,'Offers'!$C$7:$C$608,B55,'Offers'!$AJ$7:$AJ$608,">0") | D55: =_xlfn.MAXIFS('Offers'!$AJ$7:$AJ$608,'Offers'!$C$7:$C$608,B55)
B57: Research dates come from the supplied files, except rows re-checked live on 30 Sep 2026 (see Change log). The remaining future date in the Romania source is unchanged and highlighted.

Sheet Review
B2: Market review
B3: Net price per piece. Filter by product or country, then record your decision.
B5: Amber = your decisions and comments. Prices follow the match filter on Compare.
B6: Product | C6: Country | D6: Currency | E6: Price basis | F6: Min local | G6: Median local | H6: Max local | I6: Min EUR | J6: Median EUR | K6: Max EUR | L6: Your decision | M6: Priority | N6: Your comments | O6: Selected statistic
B7: GN 1/1 PC container, 65 mm | C7: Hungary | D7: HUF | E7: Net per piece | F7: =IF(COUNTIFS('Offers'!$B$7:$B$608,$B7,'Offers'!$C$7:$C$608,$C7,'Offers'!$AH$7:$AH$608,"yes")=0,"",SUMIFS('Offers'!$H$7:$H$608,'Offers'!$B$7:$B$608,$B7,'Offers'!$C$7:$C$608,$C7,'Offers'!$AF$7:$AF$608,1)) | G7: =IF(COUNTIFS('Offers'!$B$7:$B$608,$B7,'Offers'!$C$7:$C$608,$C7,'Offers'!$AH$7:$AH$608,"yes")=0,"",(SUMIFS('Offers'!$H$7:$H$608,'Offers'!$B$7:$B$608,$B7,'Offers'!$C$7:$C$608,$C7,'Offers'!$AF$7:$AF$608,ROUNDUP(COUNTIFS('Offers'!$B$7:$B$608,$B7,'Offers'!$C$7:$C$608,$C7,'Offers'!$AH$7:$AH$608,"yes")/2,0))+SUMIFS('Offers'!$H$7:$H$608,'Offers'!$B$7:$B$608,$B7,'Offers'!$C$7:$C$608,$C7,'Offers'!$AF$7:$AF$608,INT(COUNTIFS('Offers'!$B$7:$B$608,$B7,'Offers'!$C$7:$C$608,$C7,'Offers'!$AH$7:$AH$608,"yes")/2)+1))/2) | H7: =IF(COUNTIFS('Offers'!$B$7:$B$608,$B7,'Offers'!$C$7:$C$608,$C7,'Offers'!$AH$7:$AH$608,"yes")=0,"",SUMIFS('Offers'!$H$7:$H$608,'Offers'!$B$7:$B$608,$B7,'Offers'!$C$7:$C$608,$C7,'Offers'!$AF$7:$AF$608,COUNTIFS('Offers'!$B$7:$B$608,$B7,'Offers'!$C$7:$C$608,$C7,'Offers'!$AH$7:$AH$608,"yes"))) | I7: =IF(COUNTIFS('Offers'!$B$7:$B$608,$B7,'Offers'!$C$7:$C$608,$C7,'Offers'!$AI$7:$AI$608,"yes")=0,"",SUMIFS('Offers'!$I$7:$I$608,'Offers'!$B$7:$B$608,$B7,'Offers'!$C$7:$C$608,$C7,'Offers'!$AG$7:$AG$608,1)) | J7: =IF(COUNTIFS('Offers'!$B$7:$B$608,$B7,'Offers'!$C$7:$C$608,$C7,'Offers'!$AI$7:$AI$608,"yes")=0,"",(SUMIFS('Offers'!$I$7:$I$608,'Offers'!$B$7:$B$608,$B7,'Offers'!$C$7:$C$608,$C7,'Offers'!$AG$7:$AG$608,ROUNDUP(COUNTIFS('Offers'!$B$7:$B$608,$B7,'Offers'!$C$7:$C$608,$C7,'Offers'!$AI$7:$AI$608,"yes")/2,0))+SUMIFS('Offers'!$I$7:$I$608,'Offers'!$B$7:$B$608,$B7,'Offers'!$C$7:$C$608,$C7,'Offers'!$AG$7:$AG$608,INT(COUNTIFS('Offers'!$B$7:$B$608,$B7,'Offers'!$C$7:$C$608,$C7,'Offers'!$AI$7:$AI$608,"yes")/2)+1))/2) | K7: =IF(COUNTIFS('Offers'!$B$7:$B$608,$B7,'Offers'!$C$7:$C$608,$C7,'Offers'!$AI$7:$AI$608,"yes")=0,"",SUMIFS('Offers'!$I$7:$I$608,'Offers'!$B$7:$B$608,$B7,'Offers'!$C$7:$C$608,$C7,'Offers'!$AG$7:$AG$608,COUNTIFS('Offers'!$B$7:$B$608,$B7,'Offers'!$C$7:$C$608,$C7,'Offers'!$AI$7:$AI$608,"yes"))) | O7: =IF('Compare'!$E$5="Local prices",IF(F7="","",IF('Compare'!$C$5="Minimum",F7,IF('Compare'!$C$5="Maximum",H7,G7))),IF(I7="","",IF('Compare'!$C$5="Minimum",I7,IF('Compare'!$C$5="Maximum",K7,J7))))
B8: GN 1/1 PC container, 65 mm | C8: Romania | D8: RON | E8: Net per piece | F8: =IF(COUNTIFS('Offers'!$B$7:$B$608,$B8,'Offers'!$C$7:$C$608,$C8,'Offers'!$AH$7:$AH$608,"yes")=0,"",SUMIFS('Offers'!$H$7:$H$608,'Offers'!$B$7:$B$608,$B8,'Offers'!$C$7:$C$608,$C8,'Offers'!$AF$7:$AF$608,1)) | G8: =IF(COUNTIFS('Offers'!$B$7:$B$608,$B8,'Offers'!$C$7:$C$608,$C8,'Offers'!$AH$7:$AH$608,"yes")=0,"",(SUMIFS('Offers'!$H$7:$H$608,'Offers'!$B$7:$B$608,$B8,'Offers'!$C$7:$C$608,$C8,'Offers'!$AF$7:$AF$608,ROUNDUP(COUNTIFS('Offers'!$B$7:$B$608,$B8,'Offers'!$C$7:$C$608,$C8,'Offers'!$AH$7:$AH$608,"yes")/2,0))+SUMIFS('Offers'!$H$7:$H$608,'Offers'!$B$7:$B$608,$B8,'Offers'!$C$7:$C$608,$C8,'Offers'!$AF$7:$AF$608,INT(COUNTIFS('Offers'!$B$7:$B$608,$B8,'Offers'!$C$7:$C$608,$C8,'Offers'!$AH$7:$AH$608,"yes")/2)+1))/2) | H8: =IF(COUNTIFS('Offers'!$B$7:$B$608,$B8,'Offers'!$C$7:$C$608,$C8,'Offers'!$AH$7:$AH$608,"yes")=0,"",SUMIFS('Offers'!$H$7:$H$608,'Offers'!$B$7:$B$608,$B8,'Offers'!$C$7:$C$608,$C8,'Offers'!$AF$7:$AF$608,COUNTIFS('Offers'!$B$7:$B$608,$B8,'Offers'!$C$7:$C$608,$C8,'Offers'!$AH$7:$AH$608,"yes"))) | I8: =IF(COUNTIFS('Offers'!$B$7:$B$608,$B8,'Offers'!$C$7:$C$608,$C8,'Offers'!$AI$7:$AI$608,"yes")=0,"",SUMIFS('Offers'!$I$7:$I$608,'Offers'!$B$7:$B$608,$B8,'Offers'!$C$7:$C$608,$C8,'Offers'!$AG$7:$AG$608,1)) | J8: =IF(COUNTIFS('Offers'!$B$7:$B$608,$B8,'Offers'!$C$7:$C$608,$C8,'Offers'!$AI$7:$AI$608,"yes")=0,"",(SUMIFS('Offers'!$I$7:$I$608,'Offers'!$B$7:$B$608,$B8,'Offers'!$C$7:$C$608,$C8,'Offers'!$AG$7:$AG$608,ROUNDUP(COUNTIFS('Offers'!$B$7:$B$608,$B8,'Offers'!$C$7:$C$608,$C8,'Offers'!$AI$7:$AI$608,"yes")/2,0))+SUMIFS('Offers'!$I$7:$I$608,'Offers'!$B$7:$B$608,$B8,'Offers'!$C$7:$C$608,$C8,'Offers'!$AG$7:$AG$608,INT(COUNTIFS('Offers'!$B$7:$B$608,$B8,'Offers'!$C$7:$C$608,$C8,'Offers'!$AI$7:$AI$608,"yes")/2)+1))/2) | K8: =IF(COUNTIFS('Offers'!$B$7:$B$608,$B8,'Offers'!$C$7:$C$608,$C8,'Offers'!$AI$7:$AI$608,"yes")=0,"",SUMIFS('Offers'!$I$7:$I$608,'Offers'!$B$7:$B$608,$B8,'Offers'!$C$7:$C$608,$C8,'Offers'!$AG$7:$AG$608,COUNTIFS('Offers'!$B$7:$B$608,$B8,'Offers'!$C$7:$C$608,$C8,'Offers'!$AI$7:$AI$608,"yes"))) | O8: =IF('Compare'!$E$5="Local prices",IF(F8="","",IF('Compare'!$C$5="Minimum",F8,IF('Compare'!$C$5="Maximum",H8,G8))),IF(I8="","",IF('Compare'!$C$5="Minimum",I8,IF('Compare'!$C$5="Maximum",K8,J8))))
B9: GN 1/1 PC container, 65 mm | C9: Austria | D9: EUR | E9: Net per piece | F9: =IF(COUNTIFS('Offers'!$B$7:$B$608,$B9,'Offers'!$C$7:$C$608,$C9,'Offers'!$AH$7:$AH$608,"yes")=0,"",SUMIFS('Offers'!$H$7:$H$608,'Offers'!$B$7:$B$608,$B9,'Offers'!$C$7:$C$608,$C9,'Offers'!$AF$7:$AF$608,1)) | G9: =IF(COUNTIFS('Offers'!$B$7:$B$608,$B9,'Offers'!$C$7:$C$608,$C9,'Offers'!$AH$7:$AH$608,"yes")=0,"",(SUMIFS('Offers'!$H$7:$H$608,'Offers'!$B$7:$B$608,$B9,'Offers'!$C$7:$C$608,$C9,'Offers'!$AF$7:$AF$608,ROUNDUP(COUNTIFS('Offers'!$B$7:$B$608,$B9,'Offers'!$C$7:$C$608,$C9,'Offers'!$AH$7:$AH$608,"yes")/2,0))+SUMIFS('Offers'!$H$7:$H$608,'Offers'!$B$7:$B$608,$B9,'Offers'!$C$7:$C$608,$C9,'Offers'!$AF$7:$AF$608,INT(COUNTIFS('Offers'!$B$7:$B$608,$B9,'Offers'!$C$7:$C$608,$C9,'Offers'!$AH$7:$AH$608,"yes")/2)+1))/2) | H9: =IF(COUNTIFS('Offers'!$B$7:$B$608,$B9,'Offers'!$C$7:$C$608,$C9,'Offers'!$AH$7:$AH$608,"yes")=0,"",SUMIFS('Offers'!$H$7:$H$608,'Offers'!$B$7:$B$608,$B9,'Offers'!$C$7:$C$608,$C9,'Offers'!$AF$7:$AF$608,COUNTIFS('Offers'!$B$7:$B$608,$B9,'Offers'!$C$7:$C$608,$C9,'Offers'!$AH$7:$AH$608,"yes"))) | I9: =IF(COUNTIFS('Offers'!$B$7:$B$608,$B9,'Offers'!$C$7:$C$608,$C9,'Offers'!$AI$7:$AI$608,"yes")=0,"",SUMIFS('Offers'!$I$7:$I$608,'Offers'!$B$7:$B$608,$B9,'Offers'!$C$7:$C$608,$C9,'Offers'!$AG$7:$AG$608,1)) | J9: =IF(COUNTIFS('Offers'!$B$7:$B$608,$B9,'Offers'!$C$7:$C$608,$C9,'Offers'!$AI$7:$AI$608,"yes")=0,"",(SUMIFS('Offers'!$I$7:$I$608,'Offers'!$B$7:$B$608,$B9,'Offers'!$C$7:$C$608,$C9,'Offers'!$AG$7:$AG$608,ROUNDUP(COUNTIFS('Offers'!$B$7:$B$608,$B9,'Offers'!$C$7:$C$608,$C9,'Offers'!$AI$7:$AI$608,"yes")/2,0))+SUMIFS('Offers'!$I$7:$I$608,'Offers'!$B$7:$B$608,$B9,'Offers'!$C$7:$C$608,$C9,'Offers'!$AG$7:$AG$608,INT(COUNTIFS('Offers'!$B$7:$B$608,$B9,'Offers'!$C$7:$C$608,$C9,'Offers'!$AI$7:$AI$608,"yes")/2)+1))/2) | K9: =IF(COUNTIFS('Offers'!$B$7:$B$608,$B9,'Offers'!$C$7:$C$608,$C9,'Offers'!$AI$7:$AI$608,"yes")=0,"",SUMIFS('Offers'!$I$7:$I$608,'Offers'!$B$7:$B$608,$B9,'Offers'!$C$7:$C$608,$C9,'Offers'!$AG$7:$AG$608,COUNTIFS('Offers'!$B$7:$B$608,$B9,'Offers'!$C$7:$C$608,$C9,'Offers'!$AI$7:$AI$608,"yes"))) | O9: =IF('Compare'!$E$5="Local prices",IF(F9="","",IF('Compare'!$C$5="Minimum",F9,IF('Compare'!$C$5="Maximum",H9,G9))),IF(I9="","",IF('Compare'!$C$5="Minimum",I9,IF('Compare'!$C$5="Maximum",K9,J9))))
B10: GN 1/1 PC container, 65 mm | C10: Germany | D10: EUR | E10: Net per piece | F10: =IF(COUNTIFS('Offers'!$B$7:$B$608,$B10,'Offers'!$C$7:$C$608,$C10,'Offers'!$AH$7:$AH$608,"yes")=0,"",SUMIFS('Offers'!$H$7:$H$608,'Offers'!$B$7:$B$608,$B10,'Offers'!$C$7:$C$608,$C10,'Offers'!$AF$7:$AF$608,1)) | G10: =IF(COUNTIFS('Offers'!$B$7:$B$608,$B10,'Offers'!$C$7:$C$608,$C10,'Offers'!$AH$7:$AH$608,"yes")=0,"",(SUMIFS('Offers'!$H$7:$H$608,'Offers'!$B$7:$B$608,$B10,'Offers'!$C$7:$C$608,$C10,'Offers'!$AF$7:$AF$608,ROUNDUP(COUNTIFS('Offers'!$B$7:$B$608,$B10,'Offers'!$C$7:$C$608,$C10,'Offers'!$AH$7:$AH$608,"yes")/2,0))+SUMIFS('Offers'!$H$7:$H$608,'Offers'!$B$7:$B$608,$B10,'Offers'!$C$7:$C$608,$C10,'Offers'!$AF$7:$AF$608,INT(COUNTIFS('Offers'!$B$7:$B$608,$B10,'Offers'!$C$7:$C$608,$C10,'Offers'!$AH$7:$AH$608,"yes")/2)+1))/2) | H10: =IF(COUNTIFS('Offers'!$B$7:$B$608,$B10,'Offers'!$C$7:$C$608,$C10,'Offers'!$AH$7:$AH$608,"yes")=0,"",SUMIFS('Offers'!$H$7:$H$608,'Offers'!$B$7:$B$608,$B10,'Offers'!$C$7:$C$608,$C10,'Offers'!$AF$7:$AF$608,COUNTIFS('Offers'!$B$7:$B$608,$B10,'Offers'!$C$7:$C$608,$C10,'Offers'!$AH$7:$AH$608,"yes"))) | I10: =IF(COUNTIFS('Offers'!$B$7:$B$608,$B10,'Offers'!$C$7:$C$608,$C10,'Offers'!$AI$7:$AI$608,"yes")=0,"",SUMIFS('Offers'!$I$7:$I$608,'Offers'!$B$7:$B$608,$B10,'Offers'!$C$7:$C$608,$C10,'Offers'!$AG$7:$AG$608,1)) | J10: =IF(COUNTIFS('Offers'!$B$7:$B$608,$B10,'Offers'!$C$7:$C$608,$C10,'Offers'!$AI$7:$AI$608,"yes")=0,"",(SUMIFS('Offers'!$I$7:$I$608,'Offers'!$B$7:$B$608,$B10,'Offers'!$C$7:$C$608,$C10,'Offers'!$AG$7:$AG$608,ROUNDUP(COUNTIFS('Offers'!$B$7:$B$608,$B10,'Offers'!$C$7:$C$608,$C10,'Offers'!$AI$7:$AI$608,"yes")/2,0))+SUMIFS('Offers'!$I$7:$I$608,'Offers'!$B$7:$B$608,$B10,'Offers'!$C$7:$C$608,$C10,'Offers'!$AG$7:$AG$608,INT(COUNTIFS('Offers'!$B$7:$B$608,$B10,'Offers'!$C$7:$C$608,$C10,'Offers'!$AI$7:$AI$608,"yes")/2)+1))/2) | K10: =IF(COUNTIFS('Offers'!$B$7:$B$608,$B10,'Offers'!$C$7:$C$608,$C10,'Offers'!$AI$7:$AI$608,"yes")=0,"",SUMIFS('Offers'!$I$7:$I$608,'Offers'!$B$7:$B$608,$B10,'Offers'!$C$7:$C$608,$C10,'Offers'!$AG$7:$AG$608,COUNTIFS('Offers'!$B$7:$B$608,$B10,'Offers'!$C$7:$C$608,$C10,'Offers'!$AI$7:$AI$608,"yes"))) | O10: =IF('Compare'!$E$5="Local prices",IF(F10="","",IF('Compare'!$C$5="Minimum",F10,IF('Compare'!$C$5="Maximum",H10,G10))),IF(I10="","",IF('Compare'!$C$5="Minimum",I10,IF('Compare'!$C$5="Maximum",K10,J10))))
B11: GN 1/1 PC container, 65 mm | C11: Czech | D11: CZK | E11: Net per piece | F11: =IF(COUNTIFS('Offers'!$B$7:$B$608,$B11,'Offers'!$C$7:$C$608,$C11,'Offers'!$AH$7:$AH$608,"yes")=0,"",SUMIFS('Offers'!$H$7:$H$608,'Offers'!$B$7:$B$608,$B11,'Offers'!$C$7:$C$608,$C11,'Offers'!$AF$7:$AF$608,1)) | G11: =IF(COUNTIFS('Offers'!$B$7:$B$608,$B11,'Offers'!$C$7:$C$608,$C11,'Offers'!$AH$7:$AH$608,"yes")=0,"",(SUMIFS('Offers'!$H$7:$H$608,'Offers'!$B$7:$B$608,$B11,'Offers'!$C$7:$C$608,$C11,'Offers'!$AF$7:$AF$608,ROUNDUP(COUNTIFS('Offers'!$B$7:$B$608,$B11,'Offers'!$C$7:$C$608,$C11,'Offers'!$AH$7:$AH$608,"yes")/2,0))+SUMIFS('Offers'!$H$7:$H$608,'Offers'!$B$7:$B$608,$B11,'Offers'!$C$7:$C$608,$C11,'Offers'!$AF$7:$AF$608,INT(COUNTIFS('Offers'!$B$7:$B$608,$B11,'Offers'!$C$7:$C$608,$C11,'Offers'!$AH$7:$AH$608,"yes")/2)+1))/2) | H11: =IF(COUNTIFS('Offers'!$B$7:$B$608,$B11,'Offers'!$C$7:$C$608,$C11,'Offers'!$AH$7:$AH$608,"yes")=0,"",SUMIFS('Offers'!$H$7:$H$608,'Offers'!$B$7:$B$608,$B11,'Offers'!$C$7:$C$608,$C11,'Offers'!$AF$7:$AF$608,COUNTIFS('Offers'!$B$7:$B$608,$B11,'Offers'!$C$7:$C$608,$C11,'Offers'!$AH$7:$AH$608,"yes"))) | I11: =IF(COUNTIFS('Offers'!$B$7:$B$608,$B11,'Offers'!$C$7:$C$608,$C11,'Offers'!$AI$7:$AI$608,"yes")=0,"",SUMIFS('Offers'!$I$7:$I$608,'Offers'!$B$7:$B$608,$B11,'Offers'!$C$7:$C$608,$C11,'Offers'!$AG$7:$AG$608,1)) | J11: =IF(COUNTIFS('Offers'!$B$7:$B$608,$B11,'Offers'!$C$7:$C$608,$C11,'Offers'!$AI$7:$AI$608,"yes")=0,"",(SUMIFS('Offers'!$I$7:$I$608,'Offers'!$B$7:$B$608,$B11,'Offers'!$C$7:$C$608,$C11,'Offers'!$AG$7:$AG$608,ROUNDUP(COUNTIFS('Offers'!$B$7:$B$608,$B11,'Offers'!$C$7:$C$608,$C11,'Offers'!$AI$7:$AI$608,"yes")/2,0))+SUMIFS('Offers'!$I$7:$I$608,'Offers'!$B$7:$B$608,$B11,'Offers'!$C$7:$C$608,$C11,'Offers'!$AG$7:$AG$608,INT(COUNTIFS('Offers'!$B$7:$B$608,$B11,'Offers'!$C$7:$C$608,$C11,'Offers'!$AI$7:$AI$608,"yes")/2)+1))/2) | K11: =IF(COUNTIFS('Offers'!$B$7:$B$608,$B11,'Offers'!$C$7:$C$608,$C11,'Offers'!$AI$7:$AI$608,"yes")=0,"",SUMIFS('Offers'!$I$7:$I$608,'Offers'!$B$7:$B$608,$B11,'Offers'!$C$7:$C$608,$C11,'Offers'!$AG$7:$AG$608,COUNTIFS('Offers'!$B$7:$B$608,$B11,'Offers'!$C$7:$C$608,$C11,'Offers'!$AI$7:$AI$608,"yes"))) | O11: =IF('Compare'!$E$5="Local prices",IF(F11="","",IF('Compare'!$C$5="Minimum",F11,IF('Compare'!$C$5="Maximum",H11,G11))),IF(I11="","",IF('Compare'!$C$5="Minimum",I11,IF('Compare'!$C$5="Maximum",K11,J11))))
B12: GN 1/1 PC container, 65 mm | C12: Slovakia | D12: EUR | E12: Net per piece | F12: =IF(COUNTIFS('Offers'!$B$7:$B$608,$B12,'Offers'!$C$7:$C$608,$C12,'Offers'!$AH$7:$AH$608,"yes")=0,"",SUMIFS('Offers'!$H$7:$H$608,'Offers'!$B$7:$B$608,$B12,'Offers'!$C$7:$C$608,$C12,'Offers'!$AF$7:$AF$608,1)) | G12: =IF(COUNTIFS('Offers'!$B$7:$B$608,$B12,'Offers'!$C$7:$C$608,$C12,'Offers'!$AH$7:$AH$608,"yes")=0,"",(SUMIFS('Offers'!$H$7:$H$608,'Offers'!$B$7:$B$608,$B12,'Offers'!$C$7:$C$608,$C12,'Offers'!$AF$7:$AF$608,ROUNDUP(COUNTIFS('Offers'!$B$7:$B$608,$B12,'Offers'!$C$7:$C$608,$C12,'Offers'!$AH$7:$AH$608,"yes")/2,0))+SUMIFS('Offers'!$H$7:$H$608,'Offers'!$B$7:$B$608,$B12,'Offers'!$C$7:$C$608,$C12,'Offers'!$AF$7:$AF$608,INT(COUNTIFS('Offers'!$B$7:$B$608,$B12,'Offers'!$C$7:$C$608,$C12,'Offers'!$AH$7:$AH$608,"yes")/2)+1))/2) | H12: =IF(COUNTIFS('Offers'!$B$7:$B$608,$B12,'Offers'!$C$7:$C$608,$C12,'Offers'!$AH$7:$AH$608,"yes")=0,"",SUMIFS('Offers'!$H$7:$H$608,'Offers'!$B$7:$B$608,$B12,'Offers'!$C$7:$C$608,$C12,'Offers'!$AF$7:$AF$608,COUNTIFS('Offers'!$B$7:$B$608,$B12,'Offers'!$C$7:$C$608,$C12,'Offers'!$AH$7:$AH$608,"yes"))) | I12: =IF(COUNTIFS('Offers'!$B$7:$B$608,$B12,'Offers'!$C$7:$C$608,$C12,'Offers'!$AI$7:$AI$608,"yes")=0,"",SUMIFS('Offers'!$I$7:$I$608,'Offers'!$B$7:$B$608,$B12,'Offers'!$C$7:$C$608,$C12,'Offers'!$AG$7:$AG$608,1)) | J12: =IF(COUNTIFS('Offers'!$B$7:$B$608,$B12,'Offers'!$C$7:$C$608,$C12,'Offers'!$AI$7:$AI$608,"yes")=0,"",(SUMIFS('Offers'!$I$7:$I$608,'Offers'!$B$7:$B$608,$B12,'Offers'!$C$7:$C$608,$C12,'Offers'!$AG$7:$AG$608,ROUNDUP(COUNTIFS('Offers'!$B$7:$B$608,$B12,'Offers'!$C$7:$C$608,$C12,'Offers'!$AI$7:$AI$608,"yes")/2,0))+SUMIFS('Offers'!$I$7:$I$608,'Offers'!$B$7:$B$608,$B12,'Offers'!$C$7:$C$608,$C12,'Offers'!$AG$7:$AG$608,INT(COUNTIFS('Offers'!$B$7:$B$608,$B12,'Offers'!$C$7:$C$608,$C12,'Offers'!$AI$7:$AI$608,"yes")/2)+1))/2) | K12: =IF(COUNTIFS('Offers'!$B$7:$B$608,$B12,'Offers'!$C$7:$C$608,$C12,'Offers'!$AI$7:$AI$608,"yes")=0,"",SUMIFS('Offers'!$I$7:$I$608,'Offers'!$B$7:$B$608,$B12,'Offers'!$C$7:$C$608,$C12,'Offers'!$AG$7:$AG$608,COUNTIFS('Offers'!$B$7:$B$608,$B12,'Offers'!$C$7:$C$608,$C12,'Offers'!$AI$7:$AI$608,"yes"))) | O12: =IF('Compare'!$E$5="Local prices",IF(F12="","",IF('Compare'!$C$5="Minimum",F12,IF('Compare'!$C$5="Maximum",H12,G12))),IF(I12="","",IF('Compare'!$C$5="Minimum",I12,IF('Compare'!$C$5="Maximum",K12,J12))))
B13: GN 1/2 PC container, 150 mm | C13: Hungary | D13: HUF | E13: Net per piece | F13: =IF(COUNTIFS('Offers'!$B$7:$B$608,$B13,'Offers'!$C$7:$C$608,$C13,'Offers'!$AH$7:$AH$608,"yes")=0,"",SUMIFS('Offers'!$H$7:$H$608,'Offers'!$B$7:$B$608,$B13,'Offers'!$C$7:$C$608,$C13,'Offers'!$AF$7:$AF$608,1)) | G13: =IF(COUNTIFS('Offers'!$B$7:$B$608,$B13,'Offers'!$C$7:$C$608,$C13,'Offers'!$AH$7:$AH$608,"yes")=0,"",(SUMIFS('Offers'!$H$7:$H$608,'Offers'!$B$7:$B$608,$B13,'Offers'!$C$7:$C$608,$C13,'Offers'!$AF$7:$AF$608,ROUNDUP(COUNTIFS('Offers'!$B$7:$B$608,$B13,'Offers'!$C$7:$C$608,$C13,'Offers'!$AH$7:$AH$608,"yes")/2,0))+SUMIFS('Offers'!$H$7:$H$608,'Offers'!$B$7:$B$608,$B13,'Offers'!$C$7:$C$608,$C13,'Offers'!$AF$7:$AF$608,INT(COUNTIFS('Offers'!$B$7:$B$608,$B13,'Offers'!$C$7:$C$608,$C13,'Offers'!$AH$7:$AH$608,"yes")/2)+1))/2) | H13: =IF(COUNTIFS('Offers'!$B$7:$B$608,$B13,'Offers'!$C$7:$C$608,$C13,'Offers'!$AH$7:$AH$608,"yes")=0,"",SUMIFS('Offers'!$H$7:$H$608,'Offers'!$B$7:$B$608,$B13,'Offers'!$C$7:$C$608,$C13,'Offers'!$AF$7:$AF$608,COUNTIFS('Offers'!$B$7:$B$608,$B13,'Offers'!$C$7:$C$608,$C13,'Offers'!$AH$7:$AH$608,"yes"))) | I13: =IF(COUNTIFS('Offers'!$B$7:$B$608,$B13,'Offers'!$C$7:$C$608,$C13,'Offers'!$AI$7:$AI$608,"yes")=0,"",SUMIFS('Offers'!$I$7:$I$608,'Offers'!$B$7:$B$608,$B13,'Offers'!$C$7:$C$608,$C13,'Offers'!$AG$7:$AG$608,1)) | J13: =IF(COUNTIFS('Offers'!$B$7:$B$608,$B13,'Offers'!$C$7:$C$608,$C13,'Offers'!$AI$7:$AI$608,"yes")=0,"",(SUMIFS('Offers'!$I$7:$I$608,'Offers'!$B$7:$B$608,$B13,'Offers'!$C$7:$C$608,$C13,'Offers'!$AG$7:$AG$608,ROUNDUP(COUNTIFS('Offers'!$B$7:$B$608,$B13,'Offers'!$C$7:$C$608,$C13,'Offers'!$AI$7:$AI$608,"yes")/2,0))+SUMIFS('Offers'!$I$7:$I$608,'Offers'!$B$7:$B$608,$B13,'Offers'!$C$7:$C$608,$C13,'Offers'!$AG$7:$AG$608,INT(COUNTIFS('Offers'!$B$7:$B$608,$B13,'Offers'!$C$7:$C$608,$C13,'Offers'!$AI$7:$AI$608,"yes")/2)+1))/2) | K13: =IF(COUNTIFS('Offers'!$B$7:$B$608,$B13,'Offers'!$C$7:$C$608,$C13,'Offers'!$AI$7:$AI$608,"yes")=0,"",SUMIFS('Offers'!$I$7:$I$608,'Offers'!$B$7:$B$608,$B13,'Offers'!$C$7:$C$608,$C13,'Offers'!$AG$7:$AG$608,COUNTIFS('Offers'!$B$7:$B$608,$B13,'Offers'!$C$7:$C$608,$C13,'Offers'!$AI$7:$AI$608,"yes"))) | O13: =IF('Compare'!$E$5="Local prices",IF(F13="","",IF('Compare'!$C$5="Minimum",F13,IF('Compare'!$C$5="Maximum",H13,G13))),IF(I13="","",IF('Compare'!$C$5="Minimum",I13,IF('Compare'!$C$5="Maximum",K13,J13))))
B14: GN 1/2 PC container, 150 mm | C14: Romania | D14: RON | E14: Net per piece | F14: =IF(COUNTIFS('Offers'!$B$7:$B$608,$B14,'Offers'!$C$7:$C$608,$C14,'Offers'!$AH$7:$AH$608,"yes")=0,"",SUMIFS('Offers'!$H$7:$H$608,'Offers'!$B$7:$B$608,$B14,'Offers'!$C$7:$C$608,$C14,'Offers'!$AF$7:$AF$608,1)) | G14: =IF(COUNTIFS('Offers'!$B$7:$B$608,$B14,'Offers'!$C$7:$C$608,$C14,'Offers'!$AH$7:$AH$608,"yes")=0,"",(SUMIFS('Offers'!$H$7:$H$608,'Offers'!$B$7:$B$608,$B14,'Offers'!$C$7:$C$608,$C14,'Offers'!$AF$7:$AF$608,ROUNDUP(COUNTIFS('Offers'!$B$7:$B$608,$B14,'Offers'!$C$7:$C$608,$C14,'Offers'!$AH$7:$AH$608,"yes")/2,0))+SUMIFS('Offers'!$H$7:$H$608,'Offers'!$B$7:$B$608,$B14,'Offers'!$C$7:$C$608,$C14,'Offers'!$AF$7:$AF$608,INT(COUNTIFS('Offers'!$B$7:$B$608,$B14,'Offers'!$C$7:$C$608,$C14,'Offers'!$AH$7:$AH$608,"yes")/2)+1))/2) | H14: =IF(COUNTIFS('Offers'!$B$7:$B$608,$B14,'Offers'!$C$7:$C$608,$C14,'Offers'!$AH$7:$AH$608,"yes")=0,"",SUMIFS('Offers'!$H$7:$H$608,'Offers'!$B$7:$B$608,$B14,'Offers'!$C$7:$C$608,$C14,'Offers'!$AF$7:$AF$608,COUNTIFS('Offers'!$B$7:$B$608,$B14,'Offers'!$C$7:$C$608,$C14,'Offers'!$AH$7:$AH$608,"yes"))) | I14: =IF(COUNTIFS('Offers'!$B$7:$B$608,$B14,'Offers'!$C$7:$C$608,$C14,'Offers'!$AI$7:$AI$608,"yes")=0,"",SUMIFS('Offers'!$I$7:$I$608,'Offers'!$B$7:$B$608,$B14,'Offers'!$C$7:$C$608,$C14,'Offers'!$AG$7:$AG$608,1)) | J14: =IF(COUNTIFS('Offers'!$B$7:$B$608,$B14,'Offers'!$C$7:$C$608,$C14,'Offers'!$AI$7:$AI$608,"yes")=0,"",(SUMIFS('Offers'!$I$7:$I$608,'Offers'!$B$7:$B$608,$B14,'Offers'!$C$7:$C$608,$C14,'Offers'!$AG$7:$AG$608,ROUNDUP(COUNTIFS('Offers'!$B$7:$B$608,$B14,'Offers'!$C$7:$C$608,$C14,'Offers'!$AI$7:$AI$608,"yes")/2,0))+SUMIFS('Offers'!$I$7:$I$608,'Offers'!$B$7:$B$608,$B14,'Offers'!$C$7:$C$608,$C14,'Offers'!$AG$7:$AG$608,INT(COUNTIFS('Offers'!$B$7:$B$608,$B14,'Offers'!$C$7:$C$608,$C14,'Offers'!$AI$7:$AI$608,"yes")/2)+1))/2) | K14: =IF(COUNTIFS('Offers'!$B$7:$B$608,$B14,'Offers'!$C$7:$C$608,$C14,'Offers'!$AI$7:$AI$608,"yes")=0,"",SUMIFS('Offers'!$I$7:$I$608,'Offers'!$B$7:$B$608,$B14,'Offers'!$C$7:$C$608,$C14,'Offers'!$AG$7:$AG$608,COUNTIFS('Offers'!$B$7:$B$608,$B14,'Offers'!$C$7:$C$608,$C14,'Offers'!$AI$7:$AI$608,"yes"))) | O14: =IF('Compare'!$E$5="Local prices",IF(F14="","",IF('Compare'!$C$5="Minimum",F14,IF('Compare'!$C$5="Maximum",H14,G14))),IF(I14="","",IF('Compare'!$C$5="Minimum",I14,IF('Compare'!$C$5="Maximum",K14,J14))))
B15: GN 1/2 PC container, 150 mm | C15: Austria | D15: EUR | E15: Net per piece | F15: =IF(COUNTIFS('Offers'!$B$7:$B$608,$B15,'Offers'!$C$7:$C$608,$C15,'Offers'!$AH$7:$AH$608,"yes")=0,"",SUMIFS('Offers'!$H$7:$H$608,'Offers'!$B$7:$B$608,$B15,'Offers'!$C$7:$C$608,$C15,'Offers'!$AF$7:$AF$608,1)) | G15: =IF(COUNTIFS('Offers'!$B$7:$B$608,$B15,'Offers'!$C$7:$C$608,$C15,'Offers'!$AH$7:$AH$608,"yes")=0,"",(SUMIFS('Offers'!$H$7:$H$608,'Offers'!$B$7:$B$608,$B15,'Offers'!$C$7:$C$608,$C15,'Offers'!$AF$7:$AF$608,ROUNDUP(COUNTIFS('Offers'!$B$7:$B$608,$B15,'Offers'!$C$7:$C$608,$C15,'Offers'!$AH$7:$AH$608,"yes")/2,0))+SUMIFS('Offers'!$H$7:$H$608,'Offers'!$B$7:$B$608,$B15,'Offers'!$C$7:$C$608,$C15,'Offers'!$AF$7:$AF$608,INT(COUNTIFS('Offers'!$B$7:$B$608,$B15,'Offers'!$C$7:$C$608,$C15,'Offers'!$AH$7:$AH$608,"yes")/2)+1))/2) | H15: =IF(COUNTIFS('Offers'!$B$7:$B$608,$B15,'Offers'!$C$7:$C$608,$C15,'Offers'!$AH$7:$AH$608,"yes")=0,"",SUMIFS('Offers'!$H$7:$H$608,'Offers'!$B$7:$B$608,$B15,'Offers'!$C$7:$C$608,$C15,'Offers'!$AF$7:$AF$608,COUNTIFS('Offers'!$B$7:$B$608,$B15,'Offers'!$C$7:$C$608,$C15,'Offers'!$AH$7:$AH$608,"yes"))) | I15: =IF(COUNTIFS('Offers'!$B$7:$B$608,$B15,'Offers'!$C$7:$C$608,$C15,'Offers'!$AI$7:$AI$608,"yes")=0,"",SUMIFS('Offers'!$I$7:$I$608,'Offers'!$B$7:$B$608,$B15,'Offers'!$C$7:$C$608,$C15,'Offers'!$AG$7:$AG$608,1)) | J15: =IF(COUNTIFS('Offers'!$B$7:$B$608,$B15,'Offers'!$C$7:$C$608,$C15,'Offers'!$AI$7:$AI$608,"yes")=0,"",(SUMIFS('Offers'!$I$7:$I$608,'Offers'!$B$7:$B$608,$B15,'Offers'!$C$7:$C$608,$C15,'Offers'!$AG$7:$AG$608,ROUNDUP(COUNTIFS('Offers'!$B$7:$B$608,$B15,'Offers'!$C$7:$C$608,$C15,'Offers'!$AI$7:$AI$608,"yes")/2,0))+SUMIFS('Offers'!$I$7:$I$608,'Offers'!$B$7:$B$608,$B15,'Offers'!$C$7:$C$608,$C15,'Offers'!$AG$7:$AG$608,INT(COUNTIFS('Offers'!$B$7:$B$608,$B15,'Offers'!$C$7:$C$608,$C15,'Offers'!$AI$7:$AI$608,"yes")/2)+1))/2) | K15: =IF(COUNTIFS('Offers'!$B$7:$B$608,$B15,'Offers'!$C$7:$C$608,$C15,'Offers'!$AI$7:$AI$608,"yes")=0,"",SUMIFS('Offers'!$I$7:$I$608,'Offers'!$B$7:$B$608,$B15,'Offers'!$C$7:$C$608,$C15,'Offers'!$AG$7:$AG$608,COUNTIFS('Offers'!$B$7:$B$608,$B15,'Offers'!$C$7:$C$608,$C15,'Offers'!$AI$7:$AI$608,"yes"))) | O15: =IF('Compare'!$E$5="Local prices",IF(F15="","",IF('Compare'!$C$5="Minimum",F15,IF('Compare'!$C$5="Maximum",H15,G15))),IF(I15="","",IF('Compare'!$C$5="Minimum",I15,IF('Compare'!$C$5="Maximum",K15,J15))))
B16: GN 1/2 PC container, 150 mm | C16: Germany | D16: EUR | E16: Net per piece | F16: =IF(COUNTIFS('Offers'!$B$7:$B$608,$B16,'Offers'!$C$7:$C$608,$C16,'Offers'!$AH$7:$AH$608,"yes")=0,"",SUMIFS('Offers'!$H$7:$H$608,'Offers'!$B$7:$B$608,$B16,'Offers'!$C$7:$C$608,$C16,'Offers'!$AF$7:$AF$608,1)) | G16: =IF(COUNTIFS('Offers'!$B$7:$B$608,$B16,'Offers'!$C$7:$C$608,$C16,'Offers'!$AH$7:$AH$608,"yes")=0,"",(SUMIFS('Offers'!$H$7:$H$608,'Offers'!$B$7:$B$608,$B16,'Offers'!$C$7:$C$608,$C16,'Offers'!$AF$7:$AF$608,ROUNDUP(COUNTIFS('Offers'!$B$7:$B$608,$B16,'Offers'!$C$7:$C$608,$C16,'Offers'!$AH$7:$AH$608,"yes")/2,0))+SUMIFS('Offers'!$H$7:$H$608,'Offers'!$B$7:$B$608,$B16,'Offers'!$C$7:$C$608,$C16,'Offers'!$AF$7:$AF$608,INT(COUNTIFS('Offers'!$B$7:$B$608,$B16,'Offers'!$C$7:$C$608,$C16,'Offers'!$AH$7:$AH$608,"yes")/2)+1))/2) | H16: =IF(COUNTIFS('Offers'!$B$7:$B$608,$B16,'Offers'!$C$7:$C$608,$C16,'Offers'!$AH$7:$AH$608,"yes")=0,"",SUMIFS('Offers'!$H$7:$H$608,'Offers'!$B$7:$B$608,$B16,'Offers'!$C$7:$C$608,$C16,'Offers'!$AF$7:$AF$608,COUNTIFS('Offers'!$B$7:$B$608,$B16,'Offers'!$C$7:$C$608,$C16,'Offers'!$AH$7:$AH$608,"yes"))) | I16: =IF(COUNTIFS('Offers'!$B$7:$B$608,$B16,'Offers'!$C$7:$C$608,$C16,'Offers'!$AI$7:$AI$608,"yes")=0,"",SUMIFS('Offers'!$I$7:$I$608,'Offers'!$B$7:$B$608,$B16,'Offers'!$C$7:$C$608,$C16,'Offers'!$AG$7:$AG$608,1)) | J16: =IF(COUNTIFS('Offers'!$B$7:$B$608,$B16,'Offers'!$C$7:$C$608,$C16,'Offers'!$AI$7:$AI$608,"yes")=0,"",(SUMIFS('Offers'!$I$7:$I$608,'Offers'!$B$7:$B$608,$B16,'Offers'!$C$7:$C$608,$C16,'Offers'!$AG$7:$AG$608,ROUNDUP(COUNTIFS('Offers'!$B$7:$B$608,$B16,'Offers'!$C$7:$C$608,$C16,'Offers'!$AI$7:$AI$608,"yes")/2,0))+SUMIFS('Offers'!$I$7:$I$608,'Offers'!$B$7:$B$608,$B16,'Offers'!$C$7:$C$608,$C16,'Offers'!$AG$7:$AG$608,INT(COUNTIFS('Offers'!$B$7:$B$608,$B16,'Offers'!$C$7:$C$608,$C16,'Offers'!$AI$7:$AI$608,"yes")/2)+1))/2) | K16: =IF(COUNTIFS('Offers'!$B$7:$B$608,$B16,'Offers'!$C$7:$C$608,$C16,'Offers'!$AI$7:$AI$608,"yes")=0,"",SUMIFS('Offers'!$I$7:$I$608,'Offers'!$B$7:$B$608,$B16,'Offers'!$C$7:$C$608,$C16,'Offers'!$AG$7:$AG$608,COUNTIFS('Offers'!$B$7:$B$608,$B16,'Offers'!$C$7:$C$608,$C16,'Offers'!$AI$7:$AI$608,"yes"))) | O16: =IF('Compare'!$E$5="Local prices",IF(F16="","",IF('Compare'!$C$5="Minimum",F16,IF('Compare'!$C$5="Maximum",H16,G16))),IF(I16="","",IF('Compare'!$C$5="Minimum",I16,IF('Compare'!$C$5="Maximum",K16,J16))))
B17: GN 1/2 PC container, 150 mm | C17: Czech | D17: CZK | E17: Net per piece | F17: =IF(COUNTIFS('Offers'!$B$7:$B$608,$B17,'Offers'!$C$7:$C$608,$C17,'Offers'!$AH$7:$AH$608,"yes")=0,"",SUMIFS('Offers'!$H$7:$H$608,'Offers'!$B$7:$B$608,$B17,'Offers'!$C$7:$C$608,$C17,'Offers'!$AF$7:$AF$608,1)) | G17: =IF(COUNTIFS('Offers'!$B$7:$B$608,$B17,'Offers'!$C$7:$C$608,$C17,'Offers'!$AH$7:$AH$608,"yes")=0,"",(SUMIFS('Offers'!$H$7:$H$608,'Offers'!$B$7:$B$608,$B17,'Offers'!$C$7:$C$608,$C17,'Offers'!$AF$7:$AF$608,ROUNDUP(COUNTIFS('Offers'!$B$7:$B$608,$B17,'Offers'!$C$7:$C$608,$C17,'Offers'!$AH$7:$AH$608,"yes")/2,0))+SUMIFS('Offers'!$H$7:$H$608,'Offers'!$B$7:$B$608,$B17,'Offers'!$C$7:$C$608,$C17,'Offers'!$AF$7:$AF$608,INT(COUNTIFS('Offers'!$B$7:$B$608,$B17,'Offers'!$C$7:$C$608,$C17,'Offers'!$AH$7:$AH$608,"yes")/2)+1))/2) | H17: =IF(COUNTIFS('Offers'!$B$7:$B$608,$B17,'Offers'!$C$7:$C$608,$C17,'Offers'!$AH$7:$AH$608,"yes")=0,"",SUMIFS('Offers'!$H$7:$H$608,'Offers'!$B$7:$B$608,$B17,'Offers'!$C$7:$C$608,$C17,'Offers'!$AF$7:$AF$608,COUNTIFS('Offers'!$B$7:$B$608,$B17,'Offers'!$C$7:$C$608,$C17,'Offers'!$AH$7:$AH$608,"yes"))) | I17: =IF(COUNTIFS('Offers'!$B$7:$B$608,$B17,'Offers'!$C$7:$C$608,$C17,'Offers'!$AI$7:$AI$608,"yes")=0,"",SUMIFS('Offers'!$I$7:$I$608,'Offers'!$B$7:$B$608,$B17,'Offers'!$C$7:$C$608,$C17,'Offers'!$AG$7:$AG$608,1)) | J17: =IF(COUNTIFS('Offers'!$B$7:$B$608,$B17,'Offers'!$C$7:$C$608,$C17,'Offers'!$AI$7:$AI$608,"yes")=0,"",(SUMIFS('Offers'!$I$7:$I$608,'Offers'!$B$7:$B$608,$B17,'Offers'!$C$7:$C$608,$C17,'Offers'!$AG$7:$AG$608,ROUNDUP(COUNTIFS('Offers'!$B$7:$B$608,$B17,'Offers'!$C$7:$C$608,$C17,'Offers'!$AI$7:$AI$608,"yes")/2,0))+SUMIFS('Offers'!$I$7:$I$608,'Offers'!$B$7:$B$608,$B17,'Offers'!$C$7:$C$608,$C17,'Offers'!$AG$7:$AG$608,INT(COUNTIFS('Offers'!$B$7:$B$608,$B17,'Offers'!$C$7:$C$608,$C17,'Offers'!$AI$7:$AI$608,"yes")/2)+1))/2) | K17: =IF(COUNTIFS('Offers'!$B$7:$B$608,$B17,'Offers'!$C$7:$C$608,$C17,'Offers'!$AI$7:$AI$608,"yes")=0,"",SUMIFS('Offers'!$I$7:$I$608,'Offers'!$B$7:$B$608,$B17,'Offers'!$C$7:$C$608,$C17,'Offers'!$AG$7:$AG$608,COUNTIFS('Offers'!$B$7:$B$608,$B17,'Offers'!$C$7:$C$608,$C17,'Offers'!$AI$7:$AI$608,"yes"))) | O17: =IF('Compare'!$E$5="Local prices",IF(F17="","",IF('Compare'!$C$5="Minimum",F17,IF('Compare'!$C$5="Maximum",H17,G17))),IF(I17="","",IF('Compare'!$C$5="Minimum",I17,IF('Compare'!$C$5="Maximum",K17,J17))))
B18: GN 1/2 PC container, 150 mm | C18: Slovakia | D18: EUR | E18: Net per piece | F18: =IF(COUNTIFS('Offers'!$B$7:$B$608,$B18,'Offers'!$C$7:$C$608,$C18,'Offers'!$AH$7:$AH$608,"yes")=0,"",SUMIFS('Offers'!$H$7:$H$608,'Offers'!$B$7:$B$608,$B18,'Offers'!$C$7:$C$608,$C18,'Offers'!$AF$7:$AF$608,1)) | G18: =IF(COUNTIFS('Offers'!$B$7:$B$608,$B18,'Offers'!$C$7:$C$608,$C18,'Offers'!$AH$7:$AH$608,"yes")=0,"",(SUMIFS('Offers'!$H$7:$H$608,'Offers'!$B$7:$B$608,$B18,'Offers'!$C$7:$C$608,$C18,'Offers'!$AF$7:$AF$608,ROUNDUP(COUNTIFS('Offers'!$B$7:$B$608,$B18,'Offers'!$C$7:$C$608,$C18,'Offers'!$AH$7:$AH$608,"yes")/2,0))+SUMIFS('Offers'!$H$7:$H$608,'Offers'!$B$7:$B$608,$B18,'Offers'!$C$7:$C$608,$C18,'Offers'!$AF$7:$AF$608,INT(COUNTIFS('Offers'!$B$7:$B$608,$B18,'Offers'!$C$7:$C$608,$C18,'Offers'!$AH$7:$AH$608,"yes")/2)+1))/2) | H18: =IF(COUNTIFS('Offers'!$B$7:$B$608,$B18,'Offers'!$C$7:$C$608,$C18,'Offers'!$AH$7:$AH$608,"yes")=0,"",SUMIFS('Offers'!$H$7:$H$608,'Offers'!$B$7:$B$608,$B18,'Offers'!$C$7:$C$608,$C18,'Offers'!$AF$7:$AF$608,COUNTIFS('Offers'!$B$7:$B$608,$B18,'Offers'!$C$7:$C$608,$C18,'Offers'!$AH$7:$AH$608,"yes"))) | I18: =IF(COUNTIFS('Offers'!$B$7:$B$608,$B18,'Offers'!$C$7:$C$608,$C18,'Offers'!$AI$7:$AI$608,"yes")=0,"",SUMIFS('Offers'!$I$7:$I$608,'Offers'!$B$7:$B$608,$B18,'Offers'!$C$7:$C$608,$C18,'Offers'!$AG$7:$AG$608,1)) | J18: =IF(COUNTIFS('Offers'!$B$7:$B$608,$B18,'Offers'!$C$7:$C$608,$C18,'Offers'!$AI$7:$AI$608,"yes")=0,"",(SUMIFS('Offers'!$I$7:$I$608,'Offers'!$B$7:$B$608,$B18,'Offers'!$C$7:$C$608,$C18,'Offers'!$AG$7:$AG$608,ROUNDUP(COUNTIFS('Offers'!$B$7:$B$608,$B18,'Offers'!$C$7:$C$608,$C18,'Offers'!$AI$7:$AI$608,"yes")/2,0))+SUMIFS('Offers'!$I$7:$I$608,'Offers'!$B$7:$B$608,$B18,'Offers'!$C$7:$C$608,$C18,'Offers'!$AG$7:$AG$608,INT(COUNTIFS('Offers'!$B$7:$B$608,$B18,'Offers'!$C$7:$C$608,$C18,'Offers'!$AI$7:$AI$608,"yes")/2)+1))/2) | K18: =IF(COUNTIFS('Offers'!$B$7:$B$608,$B18,'Offers'!$C$7:$C$608,$C18,'Offers'!$AI$7:$AI$608,"yes")=0,"",SUMIFS('Offers'!$I$7:$I$608,'Offers'!$B$7:$B$608,$B18,'Offers'!$C$7:$C$608,$C18,'Offers'!$AG$7:$AG$608,COUNTIFS('Offers'!$B$7:$B$608,$B18,'Offers'!$C$7:$C$608,$C18,'Offers'!$AI$7:$AI$608,"yes"))) | O18: =IF('Compare'!$E$5="Local prices",IF(F18="","",IF('Compare'!$C$5="Minimum",F18,IF('Compare'!$C$5="Maximum",H18,G18))),IF(I18="","",IF('Compare'!$C$5="Minimum",I18,IF('Compare'!$C$5="Maximum",K18,J18))))
... B210: PP dough box 400 × 300 × 100 mm, no lid | C210: Slovakia | D210: EUR | E210: Net per piece | F210: =IF(COUNTIFS('Offers'!$B$7:$B$608,$B210,'Offers'!$C$7:$C$608,$C210,'Offers'!$AH$7:$AH$608,"yes")=0,"",SUMIFS('Offers'!$H$7:$H$608,'Offers'!$B$7:$B$608,$B210,'Offers'!$C$7:$C$608,$C210,'Offers'!$AF$7:$AF$608,1)) | G210: =IF(COUNTIFS('Offers'!$B$7:$B$608,$B210,'Offers'!$C$7:$C$608,$C210,'Offers'!$AH$7:$AH$608,"yes")=0,"",(SUMIFS('Offers'!$H$7:$H$608,'Offers'!$B$7:$B$608,$B210,'Offers'!$C$7:$C$608,$C210,'Offers'!$AF$7:$AF$608,ROUNDUP(COUNTIFS('Offers'!$B$7:$B$608,$B210,'Offers'!$C$7:$C$608,$C210,'Offers'!$AH$7:$AH$608,"yes")/2,0))+SUMIFS('Offers'!$H$7:$H$608,'Offers'!$B$7:$B$608,$B210,'Offers'!$C$7:$C$608,$C210,'Offers'!$AF$7:$AF$608,INT(COUNTIFS('Offers'!$B$7:$B$608,$B210,'Offers'!$C$7:$C$608,$C210,'Offers'!$AH$7:$AH$608,"yes")/2)+1))/2) | H210: =IF(COUNTIFS('Offers'!$B$7:$B$608,$B210,'Offers'!$C$7:$C$608,$C210,'Offers'!$AH$7:$AH$608,"yes")=0,"",SUMIFS('Offers'!$H$7:$H$608,'Offers'!$B$7:$B$608,$B210,'Offers'!$C$7:$C$608,$C210,'Offers'!$AF$7:$AF$608,COUNTIFS('Offers'!$B$7:$B$608,$B210,'Offers'!$C$7:$C$608,$C210,'Offers'!$AH$7:$AH$608,"yes"))) | I210: =IF(COUNTIFS('Offers'!$B$7:$B$608,$B210,'Offers'!$C$7:$C$608,$C210,'Offers'!$AI$7:$AI$608,"yes")=0,"",SUMIFS('Offers'!$I$7:$I$608,'Offers'!$B$7:$B$608,$B210,'Offers'!$C$7:$C$608,$C210,'Offers'!$AG$7:$AG$608,1)) | J210: =IF(COUNTIFS('Offers'!$B$7:$B$608,$B210,'Offers'!$C$7:$C$608,$C210,'Offers'!$AI$7:$AI$608,"yes")=0,"",(SUMIFS('Offers'!$I$7:$I$608,'Offers'!$B$7:$B$608,$B210,'Offers'!$C$7:$C$608,$C210,'Offers'!$AG$7:$AG$608,ROUNDUP(COUNTIFS('Offers'!$B$7:$B$608,$B210,'Offers'!$C$7:$C$608,$C210,'Offers'!$AI$7:$AI$608,"yes")/2,0))+SUMIFS('Offers'!$I$7:$I$608,'Offers'!$B$7:$B$608,$B210,'Offers'!$C$7:$C$608,$C210,'Offers'!$AG$7:$AG$608,INT(COUNTIFS('Offers'!$B$7:$B$608,$B210,'Offers'!$C$7:$C$608,$C210,'Offers'!$AI$7:$AI$608,"yes")/2)+1))/2) | K210: =IF(COUNTIFS('Offers'!$B$7:$B$608,$B210,'Offers'!$C$7:$C$608,$C210,'Offers'!$AI$7:$AI$608,"yes")=0,"",SUMIFS('Offers'!$I$7:$I$608,'Offers'!$B$7:$B$608,$B210,'Offers'!$C$7:$C$608,$C210,'Offers'!$AG$7:$AG$608,COUNTIFS('Offers'!$B$7:$B$608,$B210,'Offers'!$C$7:$C$608,$C210,'Offers'!$AI$7:$AI$608,"yes"))) | O210: =IF('Compare'!$E$5="Local prices",IF(F210="","",IF('Compare'!$C$5="Minimum",F210,IF('Compare'!$C$5="Maximum",H210,G210))),IF(I210="","",IF('Compare'!$C$5="Minimum",I210,IF('Compare'!$C$5="Maximum",K210,J210))))

Sheet Offers
B2: Benchmark offers
B3: Filter by product name, country, competitor or match quality.
B5: Amber = your comments. Source prices are preserved; analysis columns use current net-per-piece conversions.
B6: Product | C6: Country | D6: Competitor | E6: Product name (source) | F6: Listed price (source) | G6: Currency (source) | H6: Selected net/pc local | I6: Selected net/pc EUR | J6: Master match | K6: Date checked (source) | L6: Your comment | M6: Notes (source) | N6: URL (source) | O6: Brand (source) | P6: VAT (source) | Q6: VAT rate (source) | R6: Pack size (source) | S6: Price basis (source) | T6: Match (source) | U6: Matching note | V6: Net/pc saved (source) | W6: Historical FX saved (source) | X6: Source file | Y6: Checked by (source) | Z6: In stock? (source) | AA6: Reliability (source) | AB6: Native currency | AC6: Source eligible | AD6: Net/pc local calculation | AE6: Included by filter | AF6: Local calculation order | AG6: EUR calculation order | AH6: Local price available | AI6: EUR price available | AJ6: Research date calculation | AK6: Date issue
B7: GN 1/1 PC container, 65 mm | C7: Hungary | D7: Attase | E7: GN 1/1 65mm - Polycarbonate | F7: 3990 | G7: HUF | H7: =IF(AND(AE7="yes",ISNUMBER(AD7)),AD7,"") | I7: =IF(AND(AE7="yes",ISNUMBER(AD7),ISNUMBER(INDEX('Sources'!$G$7:$G$10,MATCH(AB7,'Sources'!$B$7:$B$10,0)))),AD7/INDEX('Sources'!$G$7:$G$10,MATCH(AB7,'Sources'!$B$7:$B$10,0)),"") | J7: EXACT | K7: 08.06.2026 | M7: Source sheet: GN Containers; size: GN 1/1 65mm; material: Polycarbonate | N7: https://www.attase.hu/konyhai-eszkozok/gn-edeny/polikarbonat-gn-edenyek | U7: GN size, depth and material agree. Colour is unrestricted in the benchmark. | W7: 3990 | X7: YES Gastro Hungary Market Research.xlsx | AA7: Direct | AB7: HUF | AC7: yes | AD7: =IF(ISNUMBER(F7),IF(G7=AB7,F7,IF(AND(ISNUMBER(INDEX('Sources'!$G$7:$G$10,MATCH(G7,'Sources'!$B$7:$B$10,0))),ISNUMBER(INDEX('Sources'!$G$7:$G$10,MATCH(AB7,'Sources'!$B$7:$B$10,0)))),F7/INDEX('Sources'!$G$7:$G$10,MATCH(G7,'Sources'!$B$7:$B$10,0))*INDEX('Sources'!$G$7:$G$10,MATCH(AB7,'Sources'!$B$7:$B$10,0)),"")),"") | AE7: =IF(AND(AC7="yes",ISNUMBER(F7),IF('Compare'!$H$5="All mapped",TRUE,IF('Compare'!$H$5="EXACT only",J7="EXACT",OR(J7="EXACT",J7="CLOSE")))),"yes","no") | AF7: =IF(ISNUMBER(H7),COUNTIFS($B$7:$B$608,B7,$C$7:$C$608,C7,$H$7:$H$608,"<"&H7,$AH$7:$AH$608,"yes")+COUNTIFS($B$7:B7,B7,$C$7:C7,C7,$H$7:H7,H7,$AH$7:AH7,"yes"),"") | AG7: =IF(ISNUMBER(I7),COUNTIFS($B$7:$B$608,B7,$C$7:$C$608,C7,$I$7:$I$608,"<"&I7,$AI$7:$AI$608,"yes")+COUNTIFS($B$7:B7,B7,$C$7:C7,C7,$I$7:I7,I7,$AI$7:AI7,"yes"),"") | AH7: =IF(ISNUMBER(H7),"yes","no") | AI7: =IF(ISNUMBER(I7),"yes","no") | AJ7: 46181
B8: GN 1/1 PC container, 65 mm | C8: Hungary | D8: Gammo | E8: GN 1/1 65mm - Polycarbonate | F8: 2520 | G8: HUF | H8: =IF(AND(AE8="yes",ISNUMBER(AD8)),AD8,"") | I8: =IF(AND(AE8="yes",ISNUMBER(AD8),ISNUMBER(INDEX('Sources'!$G$7:$G$10,MATCH(AB8,'Sources'!$B$7:$B$10,0)))),AD8/INDEX('Sources'!$G$7:$G$10,MATCH(AB8,'Sources'!$B$7:$B$10,0)),"") | J8: EXACT | K8: 08.06.2026 | M8: Source sheet: GN Containers; size: GN 1/1 65mm; material: Polycarbonate | N8: https://gammo.hu/edeny-tepsi/gasztronorm-gn-edeny | U8: GN size, depth and material agree. Colour is unrestricted in the benchmark. | W8: 2520 | X8: YES Gastro Hungary Market Research.xlsx | AA8: Direct | AB8: HUF | AC8: yes | AD8: =IF(ISNUMBER(F8),IF(G8=AB8,F8,IF(AND(ISNUMBER(INDEX('Sources'!$G$7:$G$10,MATCH(G8,'Sources'!$B$7:$B$10,0))),ISNUMBER(INDEX('Sources'!$G$7:$G$10,MATCH(AB8,'Sources'!$B$7:$B$10,0)))),F8/INDEX('Sources'!$G$7:$G$10,MATCH(G8,'Sources'!$B$7:$B$10,0))*INDEX('Sources'!$G$7:$G$10,MATCH(AB8,'Sources'!$B$7:$B$10,0)),"")),"") | AE8: =IF(AND(AC8="yes",ISNUMBER(F8),IF('Compare'!$H$5="All mapped",TRUE,IF('Compare'!$H$5="EXACT only",J8="EXACT",OR(J8="EXACT",J8="CLOSE")))),"yes","no") | AF8: =IF(ISNUMBER(H8),COUNTIFS($B$7:$B$608,B8,$C$7:$C$608,C8,$H$7:$H$608,"<"&H8,$AH$7:$AH$608,"yes")+COUNTIFS($B$7:B8,B8,$C$7:C8,C8,$H$7:H8,H8,$AH$7:AH8,"yes"),"") | AG8: =IF(ISNUMBER(I8),COUNTIFS($B$7:$B$608,B8,$C$7:$C$608,C8,$I$7:$I$608,"<"&I8,$AI$7:$AI$608,"yes")+COUNTIFS($B$7:B8,B8,$C$7:C8,C8,$I$7:I8,I8,$AI$7:AI8,"yes"),"") | AH8: =IF(ISNUMBER(H8),"yes","no") | AI8: =IF(ISNUMBER(I8),"yes","no") | AJ8: 46181
B9: GN 1/1 PC container, 65 mm | C9: Hungary | D9: Gasztronagyker | E9: GN 1/1 65mm - Polycarbonate | F9: 3543 | G9: HUF | H9: =IF(AND(AE9="yes",ISNUMBER(AD9)),AD9,"") | I9: =IF(AND(AE9="yes",ISNUMBER(AD9),ISNUMBER(INDEX('Sources'!$G$7:$G$10,MATCH(AB9,'Sources'!$B$7:$B$10,0)))),AD9/INDEX('Sources'!$G$7:$G$10,MATCH(AB9,'Sources'!$B$7:$B$10,0)),"") | J9: EXACT | K9: 08.06.2026 | M9: Source sheet: GN Containers; size: GN 1/1 65mm; material: Polycarbonate | N9: https://www.gasztronagyker.hu/gn-edenyek | U9: GN size, depth and material agree. Colour is unrestricted in the benchmark. | W9: 3543 | X9: YES Gastro Hungary Market Research.xlsx | AA9: Direct | AB9: HUF | AC9: yes | AD9: =IF(ISNUMBER(F9),IF(G9=AB9,F9,IF(AND(ISNUMBER(INDEX('Sources'!$G$7:$G$10,MATCH(G9,'Sources'!$B$7:$B$10,0))),ISNUMBER(INDEX('Sources'!$G$7:$G$10,MATCH(AB9,'Sources'!$B$7:$B$10,0)))),F9/INDEX('Sources'!$G$7:$G$10,MATCH(G9,'Sources'!$B$7:$B$10,0))*INDEX('Sources'!$G$7:$G$10,MATCH(AB9,'Sources'!$B$7:$B$10,0)),"")),"") | AE9: =IF(AND(AC9="yes",ISNUMBER(F9),IF('Compare'!$H$5="All mapped",TRUE,IF('Compare'!$H$5="EXACT only",J9="EXACT",OR(J9="EXACT",J9="CLOSE")))),"yes","no") | AF9: =IF(ISNUMBER(H9),COUNTIFS($B$7:$B$608,B9,$C$7:$C$608,C9,$H$7:$H$608,"<"&H9,$AH$7:$AH$608,"yes")+COUNTIFS($B$7:B9,B9,$C$7:C9,C9,$H$7:H9,H9,$AH$7:AH9,"yes"),"") | AG9: =IF(ISNUMBER(I9),COUNTIFS($B$7:$B$608,B9,$C$7:$C$608,C9,$I$7:$I$608,"<"&I9,$AI$7:$AI$608,"yes")+COUNTIFS($B$7:B9,B9,$C$7:C9,C9,$I$7:I9,I9,$AI$7:AI9,"yes"),"") | AH9: =IF(ISNUMBER(H9),"yes","no") | AI9: =IF(ISNUMBER(I9),"yes","no") | AJ9: 46181
B10: GN 1/1 PC container, 65 mm | C10: Hungary | D10: HFSE | E10: GN 1/1 65mm - Polycarbonate | F10: 4000 | G10: HUF | H10: =IF(AND(AE10="yes",ISNUMBER(AD10)),AD10,"") | I10: =IF(AND(AE10="yes",ISNUMBER(AD10),ISNUMBER(INDEX('Sources'!$G$7:$G$10,MATCH(AB10,'Sources'!$B$7:$B$10,0)))),AD10/INDEX('Sources'!$G$7:$G$10,MATCH(AB10,'Sources'!$B$7:$B$10,0)),"") | J10: EXACT | K10: 08.06.2026 | M10: Source sheet: GN Containers; size: GN 1/1 65mm; material: Polycarbonate | N10: https://hfse.hu/termekkategoria/konyhai-eszkozok/gn-edenyek/ | U10: GN size, depth and material agree. Colour is unrestricted in the benchmark. | W10: 4000 | X10: YES Gastro Hungary Market Research.xlsx | AA10: Direct | AB10: HUF | AC10: yes | AD10: =IF(ISNUMBER(F10),IF(G10=AB10,F10,IF(AND(ISNUMBER(INDEX('Sources'!$G$7:$G$10,MATCH(G10,'Sources'!$B$7:$B$10,0))),ISNUMBER(INDEX('Sources'!$G$7:$G$10,MATCH(AB10,'Sources'!$B$7:$B$10,0)))),F10/INDEX('Sources'!$G$7:$G$10,MATCH(G10,'Sources'!$B$7:$B$10,0))*INDEX('Sources'!$G$7:$G$10,MATCH(AB10,'Sources'!$B$7:$B$10,0)),"")),"") | AE10: =IF(AND(AC10="yes",ISNUMBER(F10),IF('Compare'!$H$5="All mapped",TRUE,IF('Compare'!$H$5="EXACT only",J10="EXACT",OR(J10="EXACT",J10="CLOSE")))),"yes","no") | AF10: =IF(ISNUMBER(H10),COUNTIFS($B$7:$B$608,B10,$C$7:$C$608,C10,$H$7:$H$608,"<"&H10,$AH$7:$AH$608,"yes")+COUNTIFS($B$7:B10,B10,$C$7:C10,C10,$H$7:H10,H10,$AH$7:AH10,"yes"),"") | AG10: =IF(ISNUMBER(I10),COUNTIFS($B$7:$B$608,B10,$C$7:$C$608,C10,$I$7:$I$608,"<"&I10,$AI$7:$AI$608,"yes")+COUNTIFS($B$7:B10,B10,$C$7:C10,C10,$I$7:I10,I10,$AI$7:AI10,"yes"),"") | AH10: =IF(ISNUMBER(H10),"yes","no") | AI10: =IF(ISNUMBER(I10),"yes","no") | AJ10: 46181
B11: GN 1/1 PC container, 65 mm | C11: Hungary | D11: Hunnia | E11: GN 1/1 65mm - Polycarbonate | F11: 6872 | G11: HUF | H11: =IF(AND(AE11="yes",ISNUMBER(AD11)),AD11,"") | I11: =IF(AND(AE11="yes",ISNUMBER(AD11),ISNUMBER(INDEX('Sources'!$G$7:$G$10,MATCH(AB11,'Sources'!$B$7:$B$10,0)))),AD11/INDEX('Sources'!$G$7:$G$10,MATCH(AB11,'Sources'!$B$7:$B$10,0)),"") | J11: EXACT | K11: 08.06.2026 | M11: Source sheet: GN Containers; size: GN 1/1 65mm; material: Polycarbonate | N11: https://hunniakristaly.hu/nagy-konyha/gn-edenyek-rozsdamentes-acelbol-polipropilenb-l-polikarbonat/gn-edenyek-torhetetlen-viztiszta-polikarbonatbol | U11: GN size, depth and material agree. Colour is unrestricted in the benchmark. | W11: 6872 | X11: YES Gastro Hungary Market Research.xlsx | AA11: Direct | AB11: HUF | AC11: yes | AD11: =IF(ISNUMBER(F11),IF(G11=AB11,F11,IF(AND(ISNUMBER(INDEX('Sources'!$G$7:$G$10,MATCH(G11,'Sources'!$B$7:$B$10,0))),ISNUMBER(INDEX('Sources'!$G$7:$G$10,MATCH(AB11,'Sources'!$B$7:$B$10,0)))),F11/INDEX('Sources'!$G$7:$G$10,MATCH(G11,'Sources'!$B$7:$B$10,0))*INDEX('Sources'!$G$7:$G$10,MATCH(AB11,'Sources'!$B$7:$B$10,0)),"")),"") | AE11: =IF(AND(AC11="yes",ISNUMBER(F11),IF('Compare'!$H$5="All mapped",TRUE,IF('Compare'!$H$5="EXACT only",J11="EXACT",OR(J11="EXACT",J11="CLOSE")))),"yes","no") | AF11: =IF(ISNUMBER(H11),COUNTIFS($B$7:$B$608,B11,$C$7:$C$608,C11,$H$7:$H$608,"<"&H11,$AH$7:$AH$608,"yes")+COUNTIFS($B$7:B11,B11,$C$7:C11,C11,$H$7:H11,H11,$AH$7:AH11,"yes"),"") | AG11: =IF(ISNUMBER(I11),COUNTIFS($B$7:$B$608,B11,$C$7:$C$608,C11,$I$7:$I$608,"<"&I11,$AI$7:$AI$608,"yes")+COUNTIFS($B$7:B11,B11,$C$7:C11,C11,$I$7:I11,I11,$AI$7:AI11,"yes"),"") | AH11: =IF(ISNUMBER(H11),"yes","no") | AI11: =IF(ISNUMBER(I11),"yes","no") | AJ11: 46181
B12: GN 1/1 PC container, 65 mm | C12: Hungary | D12: Inox-Pláza | E12: GN 1/1 65mm - Polycarbonate | F12: 3700 | G12: HUF | H12: =IF(AND(AE12="yes",ISNUMBER(AD12)),AD12,"") | I12: =IF(AND(AE12="yes",ISNUMBER(AD12),ISNUMBER(INDEX('Sources'!$G$7:$G$10,MATCH(AB12,'Sources'!$B$7:$B$10,0)))),AD12/INDEX('Sources'!$G$7:$G$10,MATCH(AB12,'Sources'!$B$7:$B$10,0)),"") | J12: EXACT | K12: 08.06.2026 | M12: Source sheet: GN Containers; size: GN 1/1 65mm; material: Polycarbonate | N12: https://www.inoxplaza.hu/edenyzet/gn-edeny | U12: GN size, depth and material agree. Colour is unrestricted in the benchmark. | W12: 3700 | X12: YES Gastro Hungary Market Research.xlsx | AA12: Direct | AB12: HUF | AC12: yes | AD12: =IF(ISNUMBER(F12),IF(G12=AB12,F12,IF(AND(ISNUMBER(INDEX('Sources'!$G$7:$G$10,MATCH(G12,'Sources'!$B$7:$B$10,0))),ISNUMBER(INDEX('Sources'!$G$7:$G$10,MATCH(AB12,'Sources'!$B$7:$B$10,0)))),F12/INDEX('Sources'!$G$7:$G$10,MATCH(G12,'Sources'!$B$7:$B$10,0))*INDEX('Sources'!$G$7:$G$10,MATCH(AB12,'Sources'!$B$7:$B$10,0)),"")),"") | AE12: =IF(AND(AC12="yes",ISNUMBER(F12),IF('Compare'!$H$5="All mapped",TRUE,IF('Compare'!$H$5="EXACT only",J12="EXACT",OR(J12="EXACT",J12="CLOSE")))),"yes","no") | AF12: =IF(ISNUMBER(H12),COUNTIFS($B$7:$B$608,B12,$C$7:$C$608,C12,$H$7:$H$608,"<"&H12,$AH$7:$AH$608,"yes")+COUNTIFS($B$7:B12,B12,$C$7:C12,C12,$H$7:H12,H12,$AH$7:AH12,"yes"),"") | AG12: =IF(ISNUMBER(I12),COUNTIFS($B$7:$B$608,B12,$C$7:$C$608,C12,$I$7:$I$608,"<"&I12,$AI$7:$AI$608,"yes")+COUNTIFS($B$7:B12,B12,$C$7:C12,C12,$I$7:I12,I12,$AI$7:AI12,"yes"),"") | AH12: =IF(ISNUMBER(H12),"yes","no") | AI12: =IF(ISNUMBER(I12),"yes","no") | AJ12: 46181
B13: GN 1/1 PC container, 65 mm | C13: Romania | D13: FiMax | E13: GN 1/1 65mm - Polycarbonate | F13: 67.56 | G13: RON | H13: =IF(AND(AE13="yes",ISNUMBER(AD13)),AD13,"") | I13: =IF(AND(AE13="yes",ISNUMBER(AD13),ISNUMBER(INDEX('Sources'!$G$7:$G$10,MATCH(AB13,'Sources'!$B$7:$B$10,0)))),AD13/INDEX('Sources'!$G$7:$G$10,MATCH(AB13,'Sources'!$B$7:$B$10,0)),"") | J13: EXACT | K13: 1.07.2026 | M13: PC | N13: https://www.fimax.ro/categorie/echipamente-catering-autoservire-si-cuve-inox-gastronorm/cuve-gastronorm-gn/cuve-gn-policarbonat-transparent/ | U13: GN size, depth and material agree. Colour is unrestricted in the benchmark. | W13: 13.512 | X13: YES Gastro Romania Market Research.xlsx | Y13: Gabi | AB13: RON | AC13: yes | AD13: =IF(ISNUMBER(F13),IF(G13=AB13,F13,IF(AND(ISNUMBER(INDEX('Sources'!$G$7:$G$10,MATCH(G13,'Sources'!$B$7:$B$10,0))),ISNUMBER(INDEX('Sources'!$G$7:$G$10,MATCH(AB13,'Sources'!$B$7:$B$10,0)))),F13/INDEX('Sources'!$G$7:$G$10,MATCH(G13,'Sources'!$B$7:$B$10,0))*INDEX('Sources'!$G$7:$G$10,MATCH(AB13,'Sources'!$B$7:$B$10,0)),"")),"") | AE13: =IF(AND(AC13="yes",ISNUMBER(F13),IF('Compare'!$H$5="All mapped",TRUE,IF('Compare'!$H$5="EXACT only",J13="EXACT",OR(J13="EXACT",J13="CLOSE")))),"yes","no") | AF13: =IF(ISNUMBER(H13),COUNTIFS($B$7:$B$608,B13,$C$7:$C$608,C13,$H$7:$H$608,"<"&H13,$AH$7:$AH$608,"yes")+COUNTIFS($B$7:B13,B13,$C$7:C13,C13,$H$7:H13,H13,$AH$7:AH13,"yes"),"") | AG13: =IF(ISNUMBER(I13),COUNTIFS($B$7:$B$608,B13,$C$7:$C$608,C13,$I$7:$I$608,"<"&I13,$AI$7:$AI$608,"yes")+COUNTIFS($B$7:B13,B13,$C$7:C13,C13,$I$7:I13,I13,$AI$7:AI13,"yes"),"") | AH13: =IF(ISNUMBER(H13),"yes","no") | AI13: =IF(ISNUMBER(I13),"yes","no") | AJ13: 46204
B14: GN 1/1 PC container, 65 mm | C14: Romania | D14: FiMax | E14: GN 1/1 65 mm - Polycarbonate Black | F14: 62.43 | G14: RON | H14: =IF(AND(AE14="yes",ISNUMBER(AD14)),AD14,"") | I14: =IF(AND(AE14="yes",ISNUMBER(AD14),ISNUMBER(INDEX('Sources'!$G$7:$G$10,MATCH(AB14,'Sources'!$B$7:$B$10,0)))),AD14/INDEX('Sources'!$G$7:$G$10,MATCH(AB14,'Sources'!$B$7:$B$10,0)),"") | J14: EXACT | K14: 4.07.2026 | M14: PC | N14: https://www.fimax.ro/categorie/echipamente-catering-autoservire-si-cuve-inox-gastronorm/cuve-gastronorm-gn/cuve-gn-policarbonat-negru/ | U14: GN size, depth and material agree. Colour is unrestricted in the benchmark. | W14: 12.486 | X14: YES Gastro Romania Market Research.xlsx | Y14: Gabi | AB14: RON | AC14: yes | AD14: =IF(ISNUMBER(F14),IF(G14=AB14,F14,IF(AND(ISNUMBER(INDEX('Sources'!$G$7:$G$10,MATCH(G14,'Sources'!$B$7:$B$10,0))),ISNUMBER(INDEX('Sources'!$G$7:$G$10,MATCH(AB14,'Sources'!$B$7:$B$10,0)))),F14/INDEX('Sources'!$G$7:$G$10,MATCH(G14,'Sources'!$B$7:$B$10,0))*INDEX('Sources'!$G$7:$G$10,MATCH(AB14,'Sources'!$B$7:$B$10,0)),"")),"") | AE14: =IF(AND(AC14="yes",ISNUMBER(F14),IF('Compare'!$H$5="All mapped",TRUE,IF('Compare'!$H$5="EXACT only",J14="EXACT",OR(J14="EXACT",J14="CLOSE")))),"yes","no") | AF14: =IF(ISNUMBER(H14),COUNTIFS($B$7:$B$608,B14,$C$7:$C$608,C14,$H$7:$H$608,"<"&H14,$AH$7:$AH$608,"yes")+COUNTIFS($B$7:B14,B14,$C$7:C14,C14,$H$7:H14,H14,$AH$7:AH14,"yes"),"") | AG14: =IF(ISNUMBER(I14),COUNTIFS($B$7:$B$608,B14,$C$7:$C$608,C14,$I$7:$I$608,"<"&I14,$AI$7:$AI$608,"yes")+COUNTIFS($B$7:B14,B14,$C$7:C14,C14,$I$7:I14,I14,$AI$7:AI14,"yes"),"") | AH14: =IF(ISNUMBER(H14),"yes","no") | AI14: =IF(ISNUMBER(I14),"yes","no") | AJ14: 46207
B15: GN 1/1 PC container, 65 mm | C15: Romania | D15: Gastrozone | E15: GN 1/1 65 mm - Polycarbonate | F15: 91.9 | G15: RON | H15: =IF(AND(AE15="yes",ISNUMBER(AD15)),AD15,"") | I15: =IF(AND(AE15="yes",ISNUMBER(AD15),ISNUMBER(INDEX('Sources'!$G$7:$G$10,MATCH(AB15,'Sources'!$B$7:$B$10,0)))),AD15/INDEX('Sources'!$G$7:$G$10,MATCH(AB15,'Sources'!$B$7:$B$10,0)),"") | J15: EXACT | K15: 30.09.2026 | M15: PC. Live check 30.09.2026: ARAVEN GN 1/1 PC 65 mm, 8.6 l - 111.20 lei incl. TVA / 91.90 lei fără TVA (on order, 3-5 weeks). Previously recorded 132.98 RON = 109.90 x 1.21, i.e. a VAT-inclusive figure treated as net. | N15: https://www.gastrozone.ro/araven-gn-containere-1-1-policarbonat-adancime-65-mm-capacitate-8-6-l.html | O15: Araven | U15: GN size, depth and material agree. Colour is unrestricted in the benchmark. | W15: 26.596 | X15: YES Gastro Romania Market Research.xlsx | Y15: Gabi | AB15: RON | AC15: yes | AD15: =IF(ISNUMBER(F15),IF(G15=AB15,F15,IF(AND(ISNUMBER(INDEX('Sources'!$G$7:$G$10,MATCH(G15,'Sources'!$B$7:$B$10,0))),ISNUMBER(INDEX('Sources'!$G$7:$G$10,MATCH(AB15,'Sources'!$B$7:$B$10,0)))),F15/INDEX('Sources'!$G$7:$G$10,MATCH(G15,'Sources'!$B$7:$B$10,0))*INDEX('Sources'!$G$7:$G$10,MATCH(AB15,'Sources'!$B$7:$B$10,0)),"")),"") | AE15: =IF(AND(AC15="yes",ISNUMBER(F15),IF('Compare'!$H$5="All mapped",TRUE,IF('Compare'!$H$5="EXACT only",J15="EXACT",OR(J15="EXACT",J15="CLOSE")))),"yes","no") | AF15: =IF(ISNUMBER(H15),COUNTIFS($B$7:$B$608,B15,$C$7:$C$608,C15,$H$7:$H$608,"<"&H15,$AH$7:$AH$608,"yes")+COUNTIFS($B$7:B15,B15,$C$7:C15,C15,$H$7:H15,H15,$AH$7:AH15,"yes"),"") | AG15: =IF(ISNUMBER(I15),COUNTIFS($B$7:$B$608,B15,$C$7:$C$608,C15,$I$7:$I$608,"<"&I15,$AI$7:$AI$608,"yes")+COUNTIFS($B$7:B15,B15,$C$7:C15,C15,$I$7:I15,I15,$AI$7:AI15,"yes"),"") | AH15: =IF(ISNUMBER(H15),"yes","no") | AI15: =IF(ISNUMBER(I15),"yes","no") | AJ15: 46295
B16: GN 1/1 PC container, 65 mm | C16: Romania | D16: Hendi | E16: GN 1/1 65 mm - Polycarbonate | F16: 52.68 | G16: RON | H16: =IF(AND(AE16="yes",ISNUMBER(AD16)),AD16,"") | I16: =IF(AND(AE16="yes",ISNUMBER(AD16),ISNUMBER(INDEX('Sources'!$G$7:$G$10,MATCH(AB16,'Sources'!$B$7:$B$10,0)))),AD16/INDEX('Sources'!$G$7:$G$10,MATCH(AB16,'Sources'!$B$7:$B$10,0)),"") | J16: EXACT | K16: 30.06.2029 | M16: PC | N16: https://www.hendi.ro/tavi-gastronorm/containere-gn?filter=25819/l/478606|25820/l/478616 | O16: Hendi | U16: GN size, depth and material agree. Colour is unrestricted in the benchmark. | W16: 10.536 | X16: YES Gastro Romania Market Research.xlsx | Y16: Gabi | AB16: RON | AC16: yes | AD16: =IF(ISNUMBER(F16),IF(G16=AB16,F16,IF(AND(ISNUMBER(INDEX('Sources'!$G$7:$G$10,MATCH(G16,'Sources'!$B$7:$B$10,0))),ISNUMBER(INDEX('Sources'!$G$7:$G$10,MATCH(AB16,'Sources'!$B$7:$B$10,0)))),F16/INDEX('Sources'!$G$7:$G$10,MATCH(G16,'Sources'!$B$7:$B$10,0))*INDEX('Sources'!$G$7:$G$10,MATCH(AB16,'Sources'!$B$7:$B$10,0)),"")),"") | AE16: =IF(AND(AC16="yes",ISNUMBER(F16),IF('Compare'!$H$5="All mapped",TRUE,IF('Compare'!$H$5="EXACT only",J16="EXACT",OR(J16="EXACT",J16="CLOSE")))),"yes","no") | AF16: =IF(ISNUMBER(H16),COUNTIFS($B$7:$B$608,B16,$C$7:$C$608,C16,$H$7:$H$608,"<"&H16,$AH$7:$AH$608,"yes")+COUNTIFS($B$7:B16,B16,$C$7:C16,C16,$H$7:H16,H16,$AH$7:AH16,"yes"),"") | AG16: =IF(ISNUMBER(I16),COUNTIFS($B$7:$B$608,B16,$C$7:$C$608,C16,$I$7:$I$608,"<"&I16,$AI$7:$AI$608,"yes")+COUNTIFS($B$7:B16,B16,$C$7:C16,C16,$I$7:I16,I16,$AI$7:AI16,"yes"),"") | AH16: =IF(ISNUMBER(H16),"yes","no") | AI16: =IF(ISNUMBER(I16),"yes","no") | AJ16: 47299 | AK16: After research workbook date; source unchanged
B17: GN 1/1 PC container, 65 mm | C17: Romania | D17: Hendi | E17: GN 1/1 65 mm - Polycarbonate Black | F17: 68.9 | G17: RON | H17: =IF(AND(AE17="yes",ISNUMBER(AD17)),AD17,"") | I17: =IF(AND(AE17="yes",ISNUMBER(AD17),ISNUMBER(INDEX('Sources'!$G$7:$G$10,MATCH(AB17,'Sources'!$B$7:$B$10,0)))),AD17/INDEX('Sources'!$G$7:$G$10,MATCH(AB17,'Sources'!$B$7:$B$10,0)),"") | J17: EXACT | K17: 4.07.2026 | M17: PC | N17: https://www.hendi.ro/tavi-gastronorm/containere-gn?filter=25819/l/478606|25820/l/478616 | O17: Hendi | U17: GN size, depth and material agree. Colour is unrestricted in the benchmark. | W17: 13.78 | X17: YES Gastro Romania Market Research.xlsx | Y17: Gabi | AB17: RON | AC17: yes | AD17: =IF(ISNUMBER(F17),IF(G17=AB17,F17,IF(AND(ISNUMBER(INDEX('Sources'!$G$7:$G$10,MATCH(G17,'Sources'!$B$7:$B$10,0))),ISNUMBER(INDEX('Sources'!$G$7:$G$10,MATCH(AB17,'Sources'!$B$7:$B$10,0)))),F17/INDEX('Sources'!$G$7:$G$10,MATCH(G17,'Sources'!$B$7:$B$10,0))*INDEX('Sources'!$G$7:$G$10,MATCH(AB17,'Sources'!$B$7:$B$10,0)),"")),"") | AE17: =IF(AND(AC17="yes",ISNUMBER(F17),IF('Compare'!$H$5="All mapped",TRUE,IF('Compare'!$H$5="EXACT only",J17="EXACT",OR(J17="EXACT",J17="CLOSE")))),"yes","no") | AF17: =IF(ISNUMBER(H17),COUNTIFS($B$7:$B$608,B17,$C$7:$C$608,C17,$H$7:$H$608,"<"&H17,$AH$7:$AH$608,"yes")+COUNTIFS($B$7:B17,B17,$C$7:C17,C17,$H$7:H17,H17,$AH$7:AH17,"yes"),"") | AG17: =IF(ISNUMBER(I17),COUNTIFS($B$7:$B$608,B17,$C$7:$C$608,C17,$I$7:$I$608,"<"&I17,$AI$7:$AI$608,"yes")+COUNTIFS($B$7:B17,B17,$C$7:C17,C17,$I$7:I17,I17,$AI$7:AI17,"yes"),"") | AH17: =IF(ISNUMBER(H17),"yes","no") | AI17: =IF(ISNUMBER(I17),"yes","no") | AJ17: 46207
B18: GN 1/1 PC container, 65 mm | C18: Romania | D18: Lancom | E18: GN 1/1 65mm - Polycarbonate | F18: 8 | G18: EUR | H18: =IF(AND(AE18="yes",ISNUMBER(AD18)),AD18,"") | I18: =IF(AND(AE18="yes",ISNUMBER(AD18),ISNUMBER(INDEX('Sources'!$G$7:$G$10,MATCH(AB18,'Sources'!$B$7:$B$10,0)))),AD18/INDEX('Sources'!$G$7:$G$10,MATCH(AB18,'Sources'!$B$7:$B$10,0)),"") | J18: EXACT | K18: 2026-09-12 00:00:00 | M18: PC. Live check 30.09.2026: 8.00 € / buc fara TVA; Lancom prices in EUR and invoices in RON at the BNR rate. Previously recorded as 42.05 RON (the EUR price converted at about 5.26). | N18: https://www.lancom.ro/tava-gastronorm-gn-11-65-policarbonat-6936 | O18: GastroPlast | U18: GN size, depth and material agree. Colour is unrestricted in the benchmark. | W18: 8.41 | X18: YES Gastro Romania Market Research.xlsx | Y18: Gabi | AB18: RON | AC18: yes | AD18: =IF(ISNUMBER(F18),IF(G18=AB18,F18,IF(AND(ISNUMBER(INDEX('Sources'!$G$7:$G$10,MATCH(G18,'Sources'!$B$7:$B$10,0))),ISNUMBER(INDEX('Sources'!$G$7:$G$10,MATCH(AB18,'Sources'!$B$7:$B$10,0)))),F18/INDEX('Sources'!$G$7:$G$10,MATCH(G18,'Sources'!$B$7:$B$10,0))*INDEX('Sources'!$G$7:$G$10,MATCH(AB18,'Sources'!$B$7:$B$10,0)),"")),"") | AE18: =IF(AND(AC18="yes",ISNUMBER(F18),IF('Compare'!$H$5="All mapped",TRUE,IF('Compare'!$H$5="EXACT only",J18="EXACT",OR(J18="EXACT",J18="CLOSE")))),"yes","no") | AF18: =IF(ISNUMBER(H18),COUNTIFS($B$7:$B$608,B18,$C$7:$C$608,C18,$H$7:$H$608,"<"&H18,$AH$7:$AH$608,"yes")+COUNTIFS($B$7:B18,B18,$C$7:C18,C18,$H$7:H18,H18,$AH$7:AH18,"yes"),"") | AG18: =IF(ISNUMBER(I18),COUNTIFS($B$7:$B$608,B18,$C$7:$C$608,C18,$I$7:$I$608,"<"&I18,$AI$7:$AI$608,"yes")+COUNTIFS($B$7:B18,B18,$C$7:C18,C18,$I$7:I18,I18,$AI$7:AI18,"yes"),"") | AH18: =IF(ISNUMBER(H18),"yes","no") | AI18: =IF(ISNUMBER(I18),"yes","no") | AJ18: 46277
B19: GN 1/1 PC container, 65 mm | C19: Romania | D19: Lancom | E19: GN 1/1 65mm - Polycarbonate Black | F19: 8 | G19: EUR | H19: =IF(AND(AE19="yes",ISNUMBER(AD19)),AD19,"") | I19: =IF(AND(AE19="yes",ISNUMBER(AD19),ISNUMBER(INDEX('Sources'!$G$7:$G$10,MATCH(AB19,'Sources'!$B$7:$B$10,0)))),AD19/INDEX('Sources'!$G$7:$G$10,MATCH(AB19,'Sources'!$B$7:$B$10,0)),"") | J19: EXACT | K19: 2026-09-12 00:00:00 | M19: PC. Live check 30.09.2026: 8.00 € / buc fara TVA; Lancom prices in EUR and invoices in RON at the BNR rate. Previously recorded as 42.05 RON (the EUR price converted at about 5.26). | N19: https://www.lancom.ro/tava-policarbonat-gn-1-1-65-mm-neagra-6937 | O19: GastroPlast | U19: GN size, depth and material agree. Colour is unrestricted in the benchmark. | W19: 8.41 | X19: YES Gastro Romania Market Research.xlsx | Y19: Gabi | AB19: RON | AC19: yes | AD19: =IF(ISNUMBER(F19),IF(G19=AB19,F19,IF(AND(ISNUMBER(INDEX('Sources'!$G$7:$G$10,MATCH(G19,'Sources'!$B$7:$B$10,0))),ISNUMBER(INDEX('Sources'!$G$7:$G$10,MATCH(AB19,'Sources'!$B$7:$B$10,0)))),F19/INDEX('Sources'!$G$7:$G$10,MATCH(G19,'Sources'!$B$7:$B$10,0))*INDEX('Sources'!$G$7:$G$10,MATCH(AB19,'Sources'!$B$7:$B$10,0)),"")),"") | AE19: =IF(AND(AC19="yes",ISNUMBER(F19),IF('Compare'!$H$5="All mapped",TRUE,IF('Compare'!$H$5="EXACT only",J19="EXACT",OR(J19="EXACT",J19="CLOSE")))),"yes","no") | AF19: =IF(ISNUMBER(H19),COUNTIFS($B$7:$B$608,B19,$C$7:$C$608,C19,$H$7:$H$608,"<"&H19,$AH$7:$AH$608,"yes")+COUNTIFS($B$7:B19,B19,$C$7:C19,C19,$H$7:H19,H19,$AH$7:AH19,"yes"),"") | AG19: =IF(ISNUMBER(I19),COUNTIFS($B$7:$B$608,B19,$C$7:$C$608,C19,$I$7:$I$608,"<"&I19,$AI$7:$AI$608,"yes")+COUNTIFS($B$7:B19,B19,$C$7:C19,C19,$I$7:I19,I19,$AI$7:AI19,"yes"),"") | AH19: =IF(ISNUMBER(H19),"yes","no") | AI19: =IF(ISNUMBER(I19),"yes","no") | AJ19: 46277
B20: GN 1/1 PC container, 65 mm | C20: Romania | D20: Pro-cucina | E20: GN 1/1 65 mm - Polycarbonate Black | F20: 8 | G20: EUR | H20: =IF(AND(AE20="yes",ISNUMBER(AD20)),AD20,"") | I20: =IF(AND(AE20="yes",ISNUMBER(AD20),ISNUMBER(INDEX('Sources'!$G$7:$G$10,MATCH(AB20,'Sources'!$B$7:$B$10,0)))),AD20/INDEX('Sources'!$G$7:$G$10,MATCH(AB20,'Sources'!$B$7:$B$10,0)),"") | J20: EXACT | K20: 4.07.2026 | M20: PC | N20: https://pro-cucina.ro/tavi-gn/ | U20: GN size, depth and material agree. Colour is unrestricted in the benchmark. | W20: 8 | X20: YES Gastro Romania Market Research.xlsx | Y20: Gabi | AB20: RON | AC20: yes | AD20: =IF(ISNUMBER(F20),IF(G20=AB20,F20,IF(AND(ISNUMBER(INDEX('Sources'!$G$7:$G$10,MATCH(G20,'Sources'!$B$7:$B$10,0))),ISNUMBER(INDEX('Sources'!$G$7:$G$10,MATCH(AB20,'Sources'!$B$7:$B$10,0)))),F20/INDEX('Sources'!$G$7:$G$10,MATCH(G20,'Sources'!$B$7:$B$10,0))*INDEX('Sources'!$G$7:$G$10,MATCH(AB20,'Sources'!$B$7:$B$10,0)),"")),"") | AE20: =IF(AND(AC20="yes",ISNUMBER(F20),IF('Compare'!$H$5="All mapped",TRUE,IF('Compare'!$H$5="EXACT only",J20="EXACT",OR(J20="EXACT",J20="CLOSE")))),"yes","no") | AF20: =IF(ISNUMBER(H20),COUNTIFS($B$7:$B$608,B20,$C$7:$C$608,C20,$H$7:$H$608,"<"&H20,$AH$7:$AH$608,"yes")+COUNTIFS($B$7:B20,B20,$C$7:C20,C20,$H$7:H20,H20,$AH$7:AH20,"yes"),"") | AG20: =IF(ISNUMBER(I20),COUNTIFS($B$7:$B$608,B20,$C$7:$C$608,C20,$I$7:$I$608,"<"&I20,$AI$7:$AI$608,"yes")+COUNTIFS($B$7:B20,B20,$C$7:C20,C20,$I$7:I20,I20,$AI$7:AI20,"yes"),"") | AH20: =IF(ISNUMBER(H20),"yes","no") | AI20: =IF(ISNUMBER(I20),"yes","no") | AJ20: 46207
B21: GN 1/1 PC container, 65 mm | C21: Romania | D21: gastroprofesional | E21: GN 1/1 65mm - Polycarbonate Black | F21: 52.93 | G21: RON | H21: =IF(AND(AE21="yes",ISNUMBER(AD21)),AD21,"") | I21: =IF(AND(AE21="yes",ISNUMBER(AD21),ISNUMBER(INDEX('Sources'!$G$7:$G$10,MATCH(AB21,'Sources'!$B$7:$B$10,0)))),AD21/INDEX('Sources'!$G$7:$G$10,MATCH(AB21,'Sources'!$B$7:$B$10,0)),"") | J21: EXACT | K21: 2.07.2026 | M21: PC | N21: https://gastroprofesional.ro/accesorii-horeca/tavi-si-cuve-profesionale/tavi-gn-si-cuve-policarbonat?q=Standard+t%C4%83vi+%5C/+recipiente-GN+1%5C/1 | U21: GN size, depth and material agree. Colour is unrestricted in the benchmark. | W21: 10.586 | X21: YES Gastro Romania Market Research.xlsx | Y21: Gabi | AB21: RON | AC21: yes | AD21: =IF(ISNUMBER(F21),IF(G21=AB21,F21,IF(AND(ISNUMBER(INDEX('Sources'!$G$7:$G$10,MATCH(G21,'Sources'!$B$7:$B$10,0))),ISNUMBER(INDEX('Sources'!$G$7:$G$10,MATCH(AB21,'Sources'!$B$7:$B$10,0)))),F21/INDEX('Sources'!$G$7:$G$10,MATCH(G21,'Sources'!$B$7:$B$10,0))*INDEX('Sources'!$G$7:$G$10,MATCH(AB21,'Sources'!$B$7:$B$10,0)),"")),"") | AE21: =IF(AND(AC21="yes",ISNUMBER(F21),IF('Compare'!$H$5="All mapped",TRUE,IF('Compare'!$H$5="EXACT only",J21="EXACT",OR(J21="EXACT",J21="CLOSE")))),"yes","no") | AF21: =IF(ISNUMBER(H21),COUNTIFS($B$7:$B$608,B21,$C$7:$C$608,C21,$H$7:$H$608,"<"&H21,$AH$7:$AH$608,"yes")+COUNTIFS($B$7:B21,B21,$C$7:C21,C21,$H$7:H21,H21,$AH$7:AH21,"yes"),"") | AG21: =IF(ISNUMBER(I21),COUNTIFS($B$7:$B$608,B21,$C$7:$C$608,C21,$I$7:$I$608,"<"&I21,$AI$7:$AI$608,"yes")+COUNTIFS($B$7:B21,B21,$C$7:C21,C21,$I$7:I21,I21,$AI$7:AI21,"yes"),"") | AH21: =IF(ISNUMBER(H21),"yes","no") | AI21: =IF(ISNUMBER(I21),"yes","no") | AJ21: 46205
B22: GN 1/1 PC container, 65 mm | C22: Romania | D22: mmgastro | E22: GN 1/1 65mm - Polycarbonate | F22: 42.98 | G22: RON | H22: =IF(AND(AE22="yes",ISNUMBER(AD22)),AD22,"") | I22: =IF(AND(AE22="yes",ISNUMBER(AD22),ISNUMBER(INDEX('Sources'!$G$7:$G$10,MATCH(AB22,'Sources'!$B$7:$B$10,0)))),AD22/INDEX('Sources'!$G$7:$G$10,MATCH(AB22,'Sources'!$B$7:$B$10,0)),"") | J22: EXACT | K22: 1.07.2026 | M22: PC | N22: https://mmgastro.ro/ro/search?text=gn+1%2F1+policarbonat | O22: Yato-YG | U22: GN size, depth and material agree. Colour is unrestricted in the benchmark. | W22: 8.596 | X22: YES Gastro Romania Market Research.xlsx | Y22: Gabi | AB22: RON | AC22: yes | AD22: =IF(ISNUMBER(F22),IF(G22=AB22,F22,IF(AND(ISNUMBER(INDEX('Sources'!$G$7:$G$10,MATCH(G22,'Sources'!$B$7:$B$10,0))),ISNUMBER(INDEX('Sources'!$G$7:$G$10,MATCH(AB22,'Sources'!$B$7:$B$10,0)))),F22/INDEX('Sources'!$G$7:$G$10,MATCH(G22,'Sources'!$B$7:$B$10,0))*INDEX('Sources'!$G$7:$G$10,MATCH(AB22,'Sources'!$B$7:$B$10,0)),"")),"") | AE22: =IF(AND(AC22="yes",ISNUMBER(F22),IF('Compare'!$H$5="All mapped",TRUE,IF('Compare'!$H$5="EXACT only",J22="EXACT",OR(J22="EXACT",J22="CLOSE")))),"yes","no") | AF22: =IF(ISNUMBER(H22),COUNTIFS($B$7:$B$608,B22,$C$7:$C$608,C22,$H$7:$H$608,"<"&H22,$AH$7:$AH$608,"yes")+COUNTIFS($B$7:B22,B22,$C$7:C22,C22,$H$7:H22,H22,$AH$7:AH22,"yes"),"") | AG22: =IF(ISNUMBER(I22),COUNTIFS($B$7:$B$608,B22,$C$7:$C$608,C22,$I$7:$I$608,"<"&I22,$AI$7:$AI$608,"yes")+COUNTIFS($B$7:B22,B22,$C$7:C22,C22,$I$7:I22,I22,$AI$7:AI22,"yes"),"") | AH22: =IF(ISNUMBER(H22),"yes","no") | AI22: =IF(ISNUMBER(I22),"yes","no") | AJ22: 46204
B23: GN 1/1 PC container, 65 mm | C23: Romania | D23: mmgastro | E23: GN 1/1 65 mm - Polycarbonate Black | F23: 63.38 | G23: RON | H23: =IF(AND(AE23="yes",ISNUMBER(AD23)),AD23,"") | I23: =IF(AND(AE23="yes",ISNUMBER(AD23),ISNUMBER(INDEX('Sources'!$G$7:$G$10,MATCH(AB23,'Sources'!$B$7:$B$10,0)))),AD23/INDEX('Sources'!$G$7:$G$10,MATCH(AB23,'Sources'!$B$7:$B$10,0)),"") | J23: EXACT | K23: 4.07.2026 | M23: PC | N23: https://mmgastro.ro/ro/menu/categorii/vase-gastronomice/vase-gn-din-policarbonat-11707?filter_text=&filter_producer=&filter_price=&filter_traits[47062]=70730&filter_traits[21]=76590&filter_traits[47060]=&filter_traits[69787]=&filter_traits[73752]= | O23: Hendi | U23: GN size, depth and material agree. Colour is unrestricted in the benchmark. | W23: 12.676 | X23: YES Gastro Romania Market Research.xlsx | Y23: Gabi | AB23: RON | AC23: yes | AD23: =IF(ISNUMBER(F23),IF(G23=AB23,F23,IF(AND(ISNUMBER(INDEX('Sources'!$G$7:$G$10,MATCH(G23,'Sources'!$B$7:$B$10,0))),ISNUMBER(INDEX('Sources'!$G$7:$G$10,MATCH(AB23,'Sources'!$B$7:$B$10,0)))),F23/INDEX('Sources'!$G$7:$G$10,MATCH(G23,'Sources'!$B$7:$B$10,0))*INDEX('Sources'!$G$7:$G$10,MATCH(AB23,'Sources'!$B$7:$B$10,0)),"")),"") | AE23: =IF(AND(AC23="yes",ISNUMBER(F23),IF('Compare'!$H$5="All mapped",TRUE,IF('Compare'!$H$5="EXACT only",J23="EXACT",OR(J23="EXACT",J23="CLOSE")))),"yes","no") | AF23: =IF(ISNUMBER(H23),COUNTIFS($B$7:$B$608,B23,$C$7:$C$608,C23,$H$7:$H$608,"<"&H23,$AH$7:$AH$608,"yes")+COUNTIFS($B$7:B23,B23,$C$7:C23,C23,$H$7:H23,H23,$AH$7:AH23,"yes"),"") | AG23: =IF(ISNUMBER(I23),COUNTIFS($B$7:$B$608,B23,$C$7:$C$608,C23,$I$7:$I$608,"<"&I23,$AI$7:$AI$608,"yes")+COUNTIFS($B$7:B23,B23,$C$7:C23,C23,$I$7:I23,I23,$AI$7:AI23,"yes"),"") | AH23: =IF(ISNUMBER(H23),"yes","no") | AI23: =IF(ISNUMBER(I23),"yes","no") | AJ23: 46207
B24: GN 1/1 PC container, 65 mm | C24: Romania | D24: pro-cucina | E24: GN 1/1 65mm - Polycarbonate | F24: 8 | G24: EUR | H24: =IF(AND(AE24="yes",ISNUMBER(AD24)),AD24,"") | I24: =IF(AND(AE24="yes",ISNUMBER(AD24),ISNUMBER(INDEX('Sources'!$G$7:$G$10,MATCH(AB24,'Sources'!$B$7:$B$10,0)))),AD24/INDEX('Sources'!$G$7:$G$10,MATCH(AB24,'Sources'!$B$7:$B$10,0)),"") | J24: EXACT | K24: 1.07.2026 | M24: PC | N24: https://pro-cucina.ro/tavi-gn/page/1/ | U24: GN size, depth and material agree. Colour is unrestricted in the benchmark. | W24: 8 | X24: YES Gastro Romania Market Research.xlsx | Y24: Gabi | AB24: RON | AC24: yes | AD24: =IF(ISNUMBER(F24),IF(G24=AB24,F24,IF(AND(ISNUMBER(INDEX('Sources'!$G$7:$G$10,MATCH(G24,'Sources'!$B$7:$B$10,0))),ISNUMBER(INDEX('Sources'!$G$7:$G$10,MATCH(AB24,'Sources'!$B$7:$B$10,0)))),F24/INDEX('Sources'!$G$7:$G$10,MATCH(G24,'Sources'!$B$7:$B$10,0))*INDEX('Sources'!$G$7:$G$10,MATCH(AB24,'Sources'!$B$7:$B$10,0)),"")),"") | AE24: =IF(AND(AC24="yes",ISNUMBER(F24),IF('Compare'!$H$5="All mapped",TRUE,IF('Compare'!$H$5="EXACT only",J24="EXACT",OR(J24="EXACT",J24="CLOSE")))),"yes","no") | AF24: =IF(ISNUMBER(H24),COUNTIFS($B$7:$B$608,B24,$C$7:$C$608,C24,$H$7:$H$608,"<"&H24,$AH$7:$AH$608,"yes")+COUNTIFS($B$7:B24,B24,$C$7:C24,C24,$H$7:H24,H24,$AH$7:AH24,"yes"),"") | AG24: =IF(ISNUMBER(I24),COUNTIFS($B$7:$B$608,B24,$C$7:$C$608,C24,$I$7:$I$608,"<"&I24,$AI$7:$AI$608,"yes")+COUNTIFS($B$7:B24,B24,$C$7:C24,C24,$I$7:I24,I24,$AI$7:AI24,"yes"),"") | AH24: =IF(ISNUMBER(H24),"yes","no") | AI24: =IF(ISNUMBER(I24),"yes","no") | AJ24: 46204
B25: GN 1/1 PC container, 65 mm | C25: Austria | D25: GastroHero Österreich | E25: Schneider Polycarbonat GN 1/1 Behälter 65 mm, 8,5 l | F25: 20.69 | G25: EUR | H25: =IF(AND(AE25="yes",ISNUMBER(AD25)),AD25,"") | I25: =IF(AND(AE25="yes",ISNUMBER(AD25),ISNUMBER(INDEX('Sources'!$G$7:$G$10,MATCH(AB25,'Sources'!$B$7:$B$10,0)))),AD25/INDEX('Sources'!$G$7:$G$10,MATCH(AB25,'Sources'!$B$7:$B$10,0)),"") | J25: EXACT | K25: 2026-09-30 | M25: Sale price (normal 21.39); minimum order quantity 4 pcs | N25: https://www.gastro-hero.at/products/schneider-polycarbonat-gn-11-behaelter-65-mm-85-l-530100 | O25: Schneider | P25: excl. | R25: 1 | T25: EXACT | U25: Existing benchmark assignment and match quality retained. | V25: 20.69 | X25: YES Gastro Austria Market Research.xlsx | AB25: EUR | AC25: yes | AD25: =IF(ISNUMBER(V25),V25,"") | AE25: =IF(AND(AC25="yes",ISNUMBER(F25),IF('Compare'!$H$5="All mapped",TRUE,IF('Compare'!$H$5="EXACT only",J25="EXACT",OR(J25="EXACT",J25="CLOSE")))),"yes","no") | AF25: =IF(ISNUMBER(H25),COUNTIFS($B$7:$B$608,B25,$C$7:$C$608,C25,$H$7:$H$608,"<"&H25,$AH$7:$AH$608,"yes")+COUNTIFS($B$7:B25,B25,$C$7:C25,C25,$H$7:H25,H25,$AH$7:AH25,"yes"),"") | AG25: =IF(ISNUMBER(I25),COUNTIFS($B$7:$B$608,B25,$C$7:$C$608,C25,$I$7:$I$608,"<"&I25,$AI$7:$AI$608,"yes")+COUNTIFS($B$7:B25,B25,$C$7:C25,C25,$I$7:I25,I25,$AI$7:AI25,"yes"),"") | AH25: =IF(ISNUMBER(H25),"yes","no") | AI25: =IF(ISNUMBER(I25),"yes","no") | AJ25: 46295
B26: GN 1/1 PC container, 65 mm | C26: Austria | D26: Gastrodax | E26: Hendi Gastronorm-Behälter 1/1, GN 1/1, 9L, Transparent, 530x325x(H)65mm – Polycarbonat | F26: 22.43 | G26: EUR | H26: =IF(AND(AE26="yes",ISNUMBER(AD26)),AD26,"") | I26: =IF(AND(AE26="yes",ISNUMBER(AD26),ISNUMBER(INDEX('Sources'!$G$7:$G$10,MATCH(AB26,'Sources'!$B$7:$B$10,0)))),AD26/INDEX('Sources'!$G$7:$G$10,MATCH(AB26,'Sources'!$B$7:$B$10,0)),"") | J26: EXACT | K26: 2026-09-30 | N26: https://www.gastrodax.de/hendi-gastronorm-behaelter-polykarbonat-transparent-gn-1-1-9-l-530-x-325-x-h-65-mm | O26: Hendi | P26: excl. | R26: 1 | T26: EXACT | U26: Existing benchmark assignment and match quality retained. | V26: 22.43 | X26: YES Gastro Austria Market Research.xlsx | AB26: EUR | AC26: yes | AD26: =IF(ISNUMBER(V26),V26,"") | AE26: =IF(AND(AC26="yes",ISNUMBER(F26),IF('Compare'!$H$5="All mapped",TRUE,IF('Compare'!$H$5="EXACT only",J26="EXACT",OR(J26="EXACT",J26="CLOSE")))),"yes","no") | AF26: =IF(ISNUMBER(H26),COUNTIFS($B$7:$B$608,B26,$C$7:$C$608,C26,$H$7:$H$608,"<"&H26,$AH$7:$AH$608,"yes")+COUNTIFS($B$7:B26,B26,$C$7:C26,C26,$H$7:H26,H26,$AH$7:AH26,"yes"),"") | AG26: =IF(ISNUMBER(I26),COUNTIFS($B$7:$B$608,B26,$C$7:$C$608,C26,$I$7:$I$608,"<"&I26,$AI$7:$AI$608,"yes")+COUNTIFS($B$7:B26,B26,$C$7:C26,C26,$I$7:I26,I26,$AI$7:AI26,"yes"),"") | AH26: =IF(ISNUMBER(H26),"yes","no") | AI26: =IF(ISNUMBER(I26),"yes","no") | AJ26: 46295
B27: GN 1/1 PC container, 65 mm | C27: Austria | D27: Gastroladen.at (Harotec GmbH) | E27: Vogue Polycarbonat GN-Behälter GN1/1 65mm | F27: 12.49 | G27: EUR | H27: =IF(AND(AE27="yes",ISNUMBER(AD27)),AD27,"") | I27: =IF(AND(AE27="yes",ISNUMBER(AD27),ISNUMBER(INDEX('Sources'!$G$7:$G$10,MATCH(AB27,'Sources'!$B$7:$B$10,0)))),AD27/INDEX('Sources'!$G$7:$G$10,MATCH(AB27,'Sources'!$B$7:$B$10,0)),"") | J27: EXACT | K27: 2026-09-30 | M27: Currently 'zurzeit nicht am Lager' (out of stock) | N27: https://www.gastroladen.at/3020@GN-U224/Vogue-Polycarbonat-GN-Beh%C3%A4lter-GN1-1-65mm.htm | O27: Vogue | P27: incl. | R27: 1 | T27: EXACT | U27: Existing benchmark assignment and match quality retained. | V27: 10.41 | X27: YES Gastro Austria Market Research.xlsx | AB27: EUR | AC27: yes | AD27: =IF(ISNUMBER(V27),V27,"") | AE27: =IF(AND(AC27="yes",ISNUMBER(F27),IF('Compare'!$H$5="All mapped",TRUE,IF('Compare'!$H$5="EXACT only",J27="EXACT",OR(J27="EXACT",J27="CLOSE")))),"yes","no") | AF27: =IF(ISNUMBER(H27),COUNTIFS($B$7:$B$608,B27,$C$7:$C$608,C27,$H$7:$H$608,"<"&H27,$AH$7:$AH$608,"yes")+COUNTIFS($B$7:B27,B27,$C$7:C27,C27,$H$7:H27,H27,$AH$7:AH27,"yes"),"") | AG27: =IF(ISNUMBER(I27),COUNTIFS($B$7:$B$608,B27,$C$7:$C$608,C27,$I$7:$I$608,"<"&I27,$AI$7:$AI$608,"yes")+COUNTIFS($B$7:B27,B27,$C$7:C27,C27,$I$7:I27,I27,$AI$7:AI27,"yes"),"") | AH27: =IF(ISNUMBER(H27),"yes","no") | AI27: =IF(ISNUMBER(I27),"yes","no") | AJ27: 46295
B28: GN 1/1 PC container, 65 mm | C28: Austria | D28: Intergastro (AT shop) | E28: Gastronormbehälter GN 1/1 x 65 mm GN 94 Polycarbonat transparent | F28: 14.07 | G28: EUR | H28: =IF(AND(AE28="yes",ISNUMBER(AD28)),AD28,"") | I28: =IF(AND(AE28="yes",ISNUMBER(AD28),ISNUMBER(INDEX('Sources'!$G$7:$G$10,MATCH(AB28,'Sources'!$B$7:$B$10,0)))),AD28/INDEX('Sources'!$G$7:$G$10,MATCH(AB28,'Sources'!$B$7:$B$10,0)),"") | J28: EXACT | K28: 2026-09-30 | M28: Gross 16.88 incl. 20% VAT; tier prices from 3 pcs | N28: https://www.intergastro.at/gastronormbehaelter-gn-1-1-x-65-mm-gn-94-polycarbonat-transparent-252042 | O28: WAS Germany | P28: excl. | R28: 1 | T28: EXACT | U28: Existing benchmark assignment and match quality retained. | V28: 14.07 | X28: YES Gastro Austria Market Research.xlsx | AB28: EUR | AC28: yes | AD28: =IF(ISNUMBER(V28),V28,"") | AE28: =IF(AND(AC28="yes",ISNUMBER(F28),IF('Compare'!$H$5="All mapped",TRUE,IF('Compare'!$H$5="EXACT only",J28="EXACT",OR(J28="EXACT",J28="CLOSE")))),"yes","no") | AF28: =IF(ISNUMBER(H28),COUNTIFS($B$7:$B$608,B28,$C$7:$C$608,C28,$H$7:$H$608,"<"&H28,$AH$7:$AH$608,"yes")+COUNTIFS($B$7:B28,B28,$C$7:C28,C28,$H$7:H28,H28,$AH$7:AH28,"yes"),"") | AG28: =IF(ISNUMBER(I28),COUNTIFS($B$7:$B$608,B28,$C$7:$C$608,C28,$I$7:$I$608,"<"&I28,$AI$7:$AI$608,"yes")+COUNTIFS($B$7:B28,B28,$C$7:C28,C28,$I$7:I28,I28,$AI$7:AI28,"yes"),"") | AH28: =IF(ISNUMBER(H28),"yes","no") | AI28: =IF(ISNUMBER(I28),"yes","no") | AJ28: 46295
B29: GN 1/1 PC container, 65 mm | C29: Austria | D29: shopbuero.com | E29: GN-Behälter - GN 1/1 (530 x 325 mm) - 65 mm - Inhalt 9,0 l - Polycarbonat | F29: 13.9 | G29: EUR | H29: =IF(AND(AE29="yes",ISNUMBER(AD29)),AD29,"") | I29: =IF(AND(AE29="yes",ISNUMBER(AD29),ISNUMBER(INDEX('Sources'!$G$7:$G$10,MATCH(AB29,'Sources'!$B$7:$B$10,0)))),AD29/INDEX('Sources'!$G$7:$G$10,MATCH(AB29,'Sources'!$B$7:$B$10,0)),"") | J29: EXACT | K29: 2026-09-30 | M29: Regular price 22.55 | N29: https://shopbuero.com/gn-behaelter-gn-1-1-530-x-325-mm-65-mm-inhalt-9-0-l-polycarbonat/530100-C | O29: Schneider | P29: excl. | R29: 1 | T29: EXACT | U29: Existing benchmark assignment and match quality retained. | V29: 13.9 | X29: YES Gastro Austria Market Research.xlsx | AB29: EUR | AC29: yes | AD29: =IF(ISNUMBER(V29),V29,"") | AE29: =IF(AND(AC29="yes",ISNUMBER(F29),IF('Compare'!$H$5="All mapped",TRUE,IF('Compare'!$H$5="EXACT only",J29="EXACT",OR(J29="EXACT",J29="CLOSE")))),"yes","no") | AF29: =IF(ISNUMBER(H29),COUNTIFS($B$7:$B$608,B29,$C$7:$C$608,C29,$H$7:$H$608,"<"&H29,$AH$7:$AH$608,"yes")+COUNTIFS($B$7:B29,B29,$C$7:C29,C29,$H$7:H29,H29,$AH$7:AH29,"yes"),"") | AG29: =IF(ISNUMBER(I29),COUNTIFS($B$7:$B$608,B29,$C$7:$C$608,C29,$I$7:$I$608,"<"&I29,$AI$7:$AI$608,"yes")+COUNTIFS($B$7:B29,B29,$C$7:C29,C29,$I$7:I29,I29,$AI$7:AI29,"yes"),"") | AH29: =IF(ISNUMBER(H29),"yes","no") | AI29: =IF(ISNUMBER(I29),"yes","no") | AJ29: 46295
B30: GN 1/1 PC container, 65 mm | C30: Germany | D30: GGM Gastro | E30: (6 Stück) Polycarbonat-Behälter GN 1/1 - Transparent - Höhe: 65mm | F30: 44.99 | G30: EUR | H30: =IF(AND(AE30="yes",ISNUMBER(AD30)),AD30,"") | I30: =IF(AND(AE30="yes",ISNUMBER(AD30),ISNUMBER(INDEX('Sources'!$G$7:$G$10,MATCH(AB30,'Sources'!$B$7:$B$10,0)))),AD30/INDEX('Sources'!$G$7:$G$10,MATCH(AB30,'Sources'!$B$7:$B$10,0)),"") | J30: EXACT | K30: 2026-09-30 | M30: RRP 87.99 | N30: https://www.ggmgastro.com/de-de-eur/6-stueck-polycarbonat-behaelter-gn-1-1-transparent-hoehe-65mm-gpcp1165 | O30: GGM | P30: excl. | R30: 6 | S30: set of 6 | T30: EXACT | U30: Existing benchmark assignment and match quality retained. | V30: 7.5 | X30: YES Gastro Germany Market Research.xlsx | AB30: EUR | AC30: yes | AD30: =IF(ISNUMBER(V30),V30,"") | AE30: =IF(AND(AC30="yes",ISNUMBER(F30),IF('Compare'!$H$5="All mapped",TRUE,IF('Compare'!$H$5="EXACT only",J30="EXACT",OR(J30="EXACT",J30="CLOSE")))),"yes","no") | AF30: =IF(ISNUMBER(H30),COUNTIFS($B$7:$B$608,B30,$C$7:$C$608,C30,$H$7:$H$608,"<"&H30,$AH$7:$AH$608,"yes")+COUNTIFS($B$7:B30,B30,$C$7:C30,C30,$H$7:H30,H30,$AH$7:AH30,"yes"),"") | AG30: =IF(ISNUMBER(I30),COUNTIFS($B$7:$B$608,B30,$C$7:$C$608,C30,$I$7:$I$608,"<"&I30,$AI$7:$AI$608,"yes")+COUNTIFS($B$7:B30,B30,$C$7:C30,C30,$I$7:I30,I30,$AI$7:AI30,"yes"),"") | AH30: =IF(ISNUMBER(H30),"yes","no") | AI30: =IF(ISNUMBER(I30),"yes","no") | AJ30: 46295
B31: GN 1/1 PC container, 65 mm | C31: Germany | D31: GastroHero | E31: Schneider Polycarbonat GN 1/1 Behälter 65 mm, 8,5 l | F31: 14.29 | G31: EUR | H31: =IF(AND(AE31="yes",ISNUMBER(AD31)),AD31,"") | I31: =IF(AND(AE31="yes",ISNUMBER(AD31),ISNUMBER(INDEX('Sources'!$G$7:$G$10,MATCH(AB31,'Sources'!$B$7:$B$10,0)))),AD31/INDEX('Sources'!$G$7:$G$10,MATCH(AB31,'Sources'!$B$7:$B$10,0)),"") | J31: EXACT | K31: 2026-09-30 | M31: Min. order qty 4 | N31: https://www.gastro-hero.de/products/schneider-polycarbonat-gn-11-behaelter-65-mm-85-l-530100 | O31: Schneider | P31: excl. | R31: 1 | T31: EXACT | U31: Existing benchmark assignment and match quality retained. | V31: 14.29 | X31: YES Gastro Germany Market Research.xlsx | AB31: EUR | AC31: yes | AD31: =IF(ISNUMBER(V31),V31,"") | AE31: =IF(AND(AC31="yes",ISNUMBER(F31),IF('Compare'!$H$5="All mapped",TRUE,IF('Compare'!$H$5="EXACT only",J31="EXACT",OR(J31="EXACT",J31="CLOSE")))),"yes","no") | AF31: =IF(ISNUMBER(H31),COUNTIFS($B$7:$B$608,B31,$C$7:$C$608,C31,$H$7:$H$608,"<"&H31,$AH$7:$AH$608,"yes")+COUNTIFS($B$7:B31,B31,$C$7:C31,C31,$H$7:H31,H31,$AH$7:AH31,"yes"),"") | AG31: =IF(ISNUMBER(I31),COUNTIFS($B$7:$B$608,B31,$C$7:$C$608,C31,$I$7:$I$608,"<"&I31,$AI$7:$AI$608,"yes")+COUNTIFS($B$7:B31,B31,$C$7:C31,C31,$I$7:I31,I31,$AI$7:AI31,"yes"),"") | AH31: =IF(ISNUMBER(H31),"yes","no") | AI31: =IF(ISNUMBER(I31),"yes","no") | AJ31: 46295
B32: GN 1/1 PC container, 65 mm | C32: Germany | D32: Gastrodax [substitute] | E32: Hendi Gastronorm-Behälter 1/1, GN 1/1, 9L, Transparent, 530x325x(H)65mm – Polycarbonat | F32: 22.43 | G32: EUR | H32: =IF(AND(AE32="yes",ISNUMBER(AD32)),AD32,"") | I32: =IF(AND(AE32="yes",ISNUMBER(AD32),ISNUMBER(INDEX('Sources'!$G$7:$G$10,MATCH(AB32,'Sources'!$B$7:$B$10,0)))),AD32/INDEX('Sources'!$G$7:$G$10,MATCH(AB32,'Sources'!$B$7:$B$10,0)),"") | J32: EXACT | K32: 2026-09-30 | N32: https://www.gastrodax.de/hendi-gastronorm-behaelter-polykarbonat-transparent-gn-1-1-9-l-530-x-325-x-h-65-mm | O32: Hendi | P32: excl. | R32: 1 | T32: EXACT | U32: Existing benchmark assignment and match quality retained. | V32: 22.43 | X32: YES Gastro Germany Market Research.xlsx | AB32: EUR | AC32: yes | AD32: =IF(ISNUMBER(V32),V32,"") | AE32: =IF(AND(AC32="yes",ISNUMBER(F32),IF('Compare'!$H$5="All mapped",TRUE,IF('Compare'!$H$5="EXACT only",J32="EXACT",OR(J32="EXACT",J32="CLOSE")))),"yes","no") | AF32: =IF(ISNUMBER(H32),COUNTIFS($B$7:$B$608,B32,$C$7:$C$608,C32,$H$7:$H$608,"<"&H32,$AH$7:$AH$608,"yes")+COUNTIFS($B$7:B32,B32,$C$7:C32,C32,$H$7:H32,H32,$AH$7:AH32,"yes"),"") | AG32: =IF(ISNUMBER(I32),COUNTIFS($B$7:$B$608,B32,$C$7:$C$608,C32,$I$7:$I$608,"<"&I32,$AI$7:$AI$608,"yes")+COUNTIFS($B$7:B32,B32,$C$7:C32,C32,$I$7:I32,I32,$AI$7:AI32,"yes"),"") | AH32: =IF(ISNUMBER(H32),"yes","no") | AI32: =IF(ISNUMBER(I32),"yes","no") | AJ32: 46295
B33: GN 1/1 PC container, 65 mm | C33: Germany | D33: Gastroladen.de (Harotec GmbH) [substitute] | E33: Vogue Polycarbonat GN-Behälter GN1/1 65mm | F33: 12.39 | G33: EUR | H33: =IF(AND(AE33="yes",ISNUMBER(AD33)),AD33,"") | I33: =IF(AND(AE33="yes",ISNUMBER(AD33),ISNUMBER(INDEX('Sources'!$G$7:$G$10,MATCH(AB33,'Sources'!$B$7:$B$10,0)))),AD33/INDEX('Sources'!$G$7:$G$10,MATCH(AB33,'Sources'!$B$7:$B$10,0)),"") | J33: EXACT | K33: 2026-09-30 | N33: https://www.gastroladen.de/3020@GN-U224/Vogue-Polycarbonat-GN-Beh%C3%A4lter-GN1-1-65mm.htm | O33: Vogue | P33: incl. | R33: 1 | T33: EXACT | U33: Existing benchmark assignment and match quality retained. | V33: 10.41 | X33: YES Gastro Germany Market Research.xlsx | AB33: EUR | AC33: yes | AD33: =IF(ISNUMBER(V33),V33,"") | AE33: =IF(AND(AC33="yes",ISNUMBER(F33),IF('Compare'!$H$5="All mapped",TRUE,IF('Compare'!$H$5="EXACT only",J33="EXACT",OR(J33="EXACT",J33="CLOSE")))),"yes","no") | AF33: =IF(ISNUMBER(H33),COUNTIFS($B$7:$B$608,B33,$C$7:$C$608,C33,$H$7:$H$608,"<"&H33,$AH$7:$AH$608,"yes")+COUNTIFS($B$7:B33,B33,$C$7:C33,C33,$H$7:H33,H33,$AH$7:AH33,"yes"),"") | AG33: =IF(ISNUMBER(I33),COUNTIFS($B$7:$B$608,B33,$C$7:$C$608,C33,$I$7:$I$608,"<"&I33,$AI$7:$AI$608,"yes")+COUNTIFS($B$7:B33,B33,$C$7:C33,C33,$I$7:I33,I33,$AI$7:AI33,"yes"),"") | AH33: =IF(ISNUMBER(H33),"yes","no") | AI33: =IF(ISNUMBER(I33),"yes","no") | AJ33: 46295
B34: GN 1/1 PC container, 65 mm | C34: Germany | D34: Intergastro | E34: Gastronormbehälter GN 1/1 x 65 mm GN 94 Polycarbonat transparent | F34: 14.07 | G34: EUR | H34: =IF(AND(AE34="yes",ISNUMBER(AD34)),AD34,"") | I34: =IF(AND(AE34="yes",ISNUMBER(AD34),ISNUMBER(INDEX('Sources'!$G$7:$G$10,MATCH(AB34,'Sources'!$B$7:$B$10,0)))),AD34/INDEX('Sources'!$G$7:$G$10,MATCH(AB34,'Sources'!$B$7:$B$10,0)),"") | J34: EXACT | K34: 2026-09-30 | M34: Gross 16.74 incl. 19% VAT; tier prices from 3 pcs | N34: https://www.intergastro.de/gastronormbehaelter-gn-1-1-x-65-mm-gn-94-polycarbonat-transparent-252042 | O34: WAS Germany | P34: excl. | R34: 1 | T34: EXACT | U34: Existing benchmark assignment and match quality retained. | V34: 14.07 | X34: YES Gastro Germany Market Research.xlsx | AB34: EUR | AC34: yes | AD34: =IF(ISNUMBER(V34),V34,"") | AE34: =IF(AND(AC34="yes",ISNUMBER(F34),IF('Compare'!$H$5="All mapped",TRUE,IF('Compare'!$H$5="EXACT only",J34="EXACT",OR(J34="EXACT",J34="CLOSE")))),"yes","no") | AF34: =IF(ISNUMBER(H34),COUNTIFS($B$7:$B$608,B34,$C$7:$C$608,C34,$H$7:$H$608,"<"&H34,$AH$7:$AH$608,"yes")+COUNTIFS($B$7:B34,B34,$C$7:C34,C34,$H$7:H34,H34,$AH$7:AH34,"yes"),"") | AG34: =IF(ISNUMBER(I34),COUNTIFS($B$7:$B$608,B34,$C$7:$C$608,C34,$I$7:$I$608,"<"&I34,$AI$7:$AI$608,"yes")+COUNTIFS($B$7:B34,B34,$C$7:C34,C34,$I$7:I34,I34,$AI$7:AI34,"yes"),"") | AH34: =IF(ISNUMBER(H34),"yes","no") | AI34: =IF(ISNUMBER(I34),"yes","no") | AJ34: 46295
B35: GN 1/1 PC container, 65 mm | C35: Germany | D35: Nisbets | E35: Vogue Polycarbonat GN-Behälter GN1/1 65mm | F35: 7.26 | G35: EUR | H35: =IF(AND(AE35="yes",ISNUMBER(AD35)),AD35,"") | I35: =IF(AND(AE35="yes",ISNUMBER(AD35),ISNUMBER(INDEX('Sources'!$G$7:$G$10,MATCH(AB35,'Sources'!$B$7:$B$10,0)))),AD35/INDEX('Sources'!$G$7:$G$10,MATCH(AB35,'Sources'!$B$7:$B$10,0)),"") | J35: EXACT | K35: 2026-09-30 | M35: Reduced web price (UVP 15.29, -53%); 'Nicht vorrätig' (out of stock) on 2026-09-30 | N35: https://www.nisbets.de/vogue-polycarbonat-gn-behlter-65mm/u224 | O35: Vogue | P35: excl. | R35: 1 | T35: EXACT | U35: Existing benchmark assignment and match quality retained. | V35: 7.26 | X35: YES Gastro Germany Market Research.xlsx | AB35: EUR | AC35: yes | AD35: =IF(ISNUMBER(V35),V35,"") | AE35: =IF(AND(AC35="yes",ISNUMBER(F35),IF('Compare'!$H$5="All mapped",TRUE,IF('Compare'!$H$5="EXACT only",J35="EXACT",OR(J35="EXACT",J35="CLOSE")))),"yes","no") | AF35: =IF(ISNUMBER(H35),COUNTIFS($B$7:$B$608,B35,$C$7:$C$608,C35,$H$7:$H$608,"<"&H35,$AH$7:$AH$608,"yes")+COUNTIFS($B$7:B35,B35,$C$7:C35,C35,$H$7:H35,H35,$AH$7:AH35,"yes"),"") | AG35: =IF(ISNUMBER(I35),COUNTIFS($B$7:$B$608,B35,$C$7:$C$608,C35,$I$7:$I$608,"<"&I35,$AI$7:$AI$608,"yes")+COUNTIFS($B$7:B35,B35,$C$7:C35,C35,$I$7:I35,I35,$AI$7:AI35,"yes"),"") | AH35: =IF(ISNUMBER(H35),"yes","no") | AI35: =IF(ISNUMBER(I35),"yes","no") | AJ35: 46295
B36: GN 1/1 PC container, 65 mm | C36: Czech | D36: GGM Gastro (CZ storefront) | E36: (6 ks) Gastronádoba GN GN 1/1 - polykarbonát - čirá - Výška: 65 mm | F36: 1143.69 | G36: CZK | H36: =IF(AND(AE36="yes",ISNUMBER(AD36)),AD36,"") | I36: =IF(AND(AE36="yes",ISNUMBER(AD36),ISNUMBER(INDEX('Sources'!$G$7:$G$10,MATCH(AB36,'Sources'!$B$7:$B$10,0)))),AD36/INDEX('Sources'!$G$7:$G$10,MATCH(AB36,'Sources'!$B$7:$B$10,0)),"") | J36: EXACT | K36: 2026-09-30 | M36: Net CZK price as displayed; page footnote: "* čistá cena | hrubá cena vč. 19% DPH" (German VAT 19% used on the CZ storefront). SKU GPCP1165, pack of 6; gross 1,360.99 CZK; delivery 5-6 weeks. | N36: https://www.ggmgastro.com/cs-cz-czk/6-ks-gastronadoba-gn-gn-1-1-polykarbonat-cira-vyska-65-mm-gpcp1165 | O36: GGM | P36: excl. | Q36: 0.19 | R36: 6 | S36: per pack | T36: EXACT | U36: Existing benchmark assignment and match quality retained. | X36: YES Gastro Czech Market Research.xlsx | AB36: CZK | AC36: yes | AD36: =IF(OR(F36="",Q36="",R36=""),"",ROUND(IF(P36="incl.",F36/(1+Q36),F36)/IF(S36="per pack",R36,1),2)) | AE36: =IF(AND(AC36="yes",ISNUMBER(F36),IF('Compare'!$H$5="All mapped",TRUE,IF('Compare'!$H$5="EXACT only",J36="EXACT",OR(J36="EXACT",J36="CLOSE")))),"yes","no") | AF36: =IF(ISNUMBER(H36),COUNTIFS($B$7:$B$608,B36,$C$7:$C$608,C36,$H$7:$H$608,"<"&H36,$AH$7:$AH$608,"yes")+COUNTIFS($B$7:B36,B36,$C$7:C36,C36,$H$7:H36,H36,$AH$7:AH36,"yes"),"") | AG36: =IF(ISNUMBER(I36),COUNTIFS($B$7:$B$608,B36,$C$7:$C$608,C36,$I$7:$I$608,"<"&I36,$AI$7:$AI$608,"yes")+COUNTIFS($B$7:B36,B36,$C$7:C36,C36,$I$7:I36,I36,$AI$7:AI36,"yes"),"") | AH36: =IF(ISNUMBER(H36),"yes","no") | AI36: =IF(ISNUMBER(I36),"yes","no") | AJ36: 46295
B37: GN 1/1 PC container, 65 mm | C37: Czech | D37: Gastro Novotný | E37: Gastronádoba PC 1/1 100 | F37: 289 | G37: CZK | H37: =IF(AND(AE37="yes",ISNUMBER(AD37)),AD37,"") | I37: =IF(AND(AE37="yes",ISNUMBER(AD37),ISNUMBER(INDEX('Sources'!$G$7:$G$10,MATCH(AB37,'Sources'!$B$7:$B$10,0)))),AD37/INDEX('Sources'!$G$7:$G$10,MATCH(AB37,'Sources'!$B$7:$B$10,0)),"") | J37: APPROX | K37: 2026-09-30 | M37: Polycarbonate GN 1/1 but 100 mm deep (no 65 mm PC listed; PC range 1/1 = 100 and 200 mm only). 349.69 CZK incl. VAT. Availability "Na dotaz". | N37: https://eshop.gastronovotny.cz/gastronadoba-pc-1-1-100--0835126/ | P37: excl. | Q37: 0.21 | R37: 1 | S37: per piece | T37: APPROX | U37: Existing benchmark assignment and match quality retained. | X37: YES Gastro Czech Market Research.xlsx | AB37: CZK | AC37: yes | AD37: =IF(OR(F37="",Q37="",R37=""),"",ROUND(IF(P37="incl.",F37/(1+Q37),F37)/IF(S37="per pack",R37,1),2)) | AE37: =IF(AND(AC37="yes",ISNUMBER(F37),IF('Compare'!$H$5="All mapped",TRUE,IF('Compare'!$H$5="EXACT only",J37="EXACT",OR(J37="EXACT",J37="CLOSE")))),"yes","no") | AF37: =IF(ISNUMBER(H37),COUNTIFS($B$7:$B$608,B37,$C$7:$C$608,C37,$H$7:$H$608,"<"&H37,$AH$7:$AH$608,"yes")+COUNTIFS($B$7:B37,B37,$C$7:C37,C37,$H$7:H37,H37,$AH$7:AH37,"yes"),"") | AG37: =IF(ISNUMBER(I37),COUNTIFS($B$7:$B$608,B37,$C$7:$C$608,C37,$I$7:$I$608,"<"&I37,$AI$7:$AI$608,"yes")+COUNTIFS($B$7:B37,B37,$C$7:C37,C37,$I$7:I37,I37,$AI$7:AI37,"yes"),"") | AH37: =IF(ISNUMBER(H37),"yes","no") | AI37: =IF(ISNUMBER(I37),"yes","no") | AJ37: 46295
B38: GN 1/1 PC container, 65 mm | C38: Czech | D38: Gastromania | E38: Gastronádoba z polykarbonátu GN 1/1 65 mm | HENDI, Profi Line | F38: 262 | G38: CZK | H38: =IF(AND(AE38="yes",ISNUMBER(AD38)),AD38,"") | I38: =IF(AND(AE38="yes",ISNUMBER(AD38),ISNUMBER(INDEX('Sources'!$G$7:$G$10,MATCH(AB38,'Sources'!$B$7:$B$10,0)))),AD38/INDEX('Sources'!$G$7:$G$10,MATCH(AB38,'Sources'!$B$7:$B$10,0)),"") | J38: EXACT | K38: 2026-09-30 | M38: PC, 9 l. Current price 262 CZK excl. / 317 incl. is an "Outlet" discount from 368 excl. / 445 incl. (30-day low shown 445). Regular-priced alternative: Stalgast Bufet PC GN 1/1 65 mm 286 excl. / 346 incl. | N38: https://www.gastromania.cz/gastronadoby-polykarbonatove/gastronadoba-z-polykarbonatu-gn-1-1-65-mm-hendi-profi-line | O38: Hendi | P38: excl. | Q38: 0.21 | R38: 1 | S38: per piece | T38: EXACT | U38: Existing benchmark assignment and match quality retained. | X38: YES Gastro Czech Market Research.xlsx | AB38: CZK | AC38: yes | AD38: =IF(OR(F38="",Q38="",R38=""),"",ROUND(IF(P38="incl.",F38/(1+Q38),F38)/IF(S38="per pack",R38,1),2)) | AE38: =IF(AND(AC38="yes",ISNUMBER(F38),IF('Compare'!$H$5="All mapped",TRUE,IF('Compare'!$H$5="EXACT only",J38="EXACT",OR(J38="EXACT",J38="CLOSE")))),"yes","no") | AF38: =IF(ISNUMBER(H38),COUNTIFS($B$7:$B$608,B38,$C$7:$C$608,C38,$H$7:$H$608,"<"&H38,$AH$7:$AH$608,"yes")+COUNTIFS($B$7:B38,B38,$C$7:C38,C38,$H$7:H38,H38,$AH$7:AH38,"yes"),"") | AG38: =IF(ISNUMBER(I38),COUNTIFS($B$7:$B$608,B38,$C$7:$C$608,C38,$I$7:$I$608,"<"&I38,$AI$7:$AI$608,"yes")+COUNTIFS($B$7:B38,B38,$C$7:C38,C38,$I$7:I38,I38,$AI$7:AI38,"yes"),"") | AH38: =IF(ISNUMBER(H38),"yes","no") | AI38: =IF(ISNUMBER(I38),"yes","no") | AJ38: 46295
B39: GN 1/1 PC container, 65 mm | C39: Czech | D39: Gastrozone | E39: ARAVEN Gastronádoba GN 1/1, polykarbonát, hloubka: 65 mm, objem: 8,6 L | F39: 502 | G39: CZK | H39: =IF(AND(AE39="yes",ISNUMBER(AD39)),AD39,"") | I39: =IF(AND(AE39="yes",ISNUMBER(AD39),ISNUMBER(INDEX('Sources'!$G$7:$G$10,MATCH(AB39,'Sources'!$B$7:$B$10,0)))),AD39/INDEX('Sources'!$G$7:$G$10,MATCH(AB39,'Sources'!$B$7:$B$10,0)),"") | J39: EXACT | K39: 2026-09-30 | M39: 414.88 CZK bez DPH; availability "Na objednávku (3-5 týdnů)". In-stock alternative: ARAVEN PC GN 1/1 65 mm with integrated label 601 CZK. | N39: https://www.gastrozone.cz/araven-gn-box-1-1-polykarbonat-hloubka-65-mm-objem-8-6-l.html | O39: Araven | P39: incl. | Q39: 0.21 | R39: 1 | S39: per piece | T39: EXACT | U39: Existing benchmark assignment and match quality retained. | X39: YES Gastro Czech Market Research.xlsx | AB39: CZK | AC39: yes | AD39: =IF(OR(F39="",Q39="",R39=""),"",ROUND(IF(P39="incl.",F39/(1+Q39),F39)/IF(S39="per pack",R39,1),2)) | AE39: =IF(AND(AC39="yes",ISNUMBER(F39),IF('Compare'!$H$5="All mapped",TRUE,IF('Compare'!$H$5="EXACT only",J39="EXACT",OR(J39="EXACT",J39="CLOSE")))),"yes","no") | AF39: =IF(ISNUMBER(H39),COUNTIFS($B$7:$B$608,B39,$C$7:$C$608,C39,$H$7:$H$608,"<"&H39,$AH$7:$AH$608,"yes")+COUNTIFS($B$7:B39,B39,$C$7:C39,C39,$H$7:H39,H39,$AH$7:AH39,"yes"),"") | AG39: =IF(ISNUMBER(I39),COUNTIFS($B$7:$B$608,B39,$C$7:$C$608,C39,$I$7:$I$608,"<"&I39,$AI$7:$AI$608,"yes")+COUNTIFS($B$7:B39,B39,$C$7:C39,C39,$I$7:I39,I39,$AI$7:AI39,"yes"),"") | AH39: =IF(ISNUMBER(H39),"yes","no") | AI39: =IF(ISNUMBER(I39),"yes","no") | AJ39: 46295
B40: GN 1/1 PC container, 65 mm | C40: Czech | D40: TOMGAST | E40: Gastronádoba polykarbonátová GN 1/1 65 mm | F40: 401 | G40: CZK | H40: =IF(AND(AE40="yes",ISNUMBER(AD40)),AD40,"") | I40: =IF(AND(AE40="yes",ISNUMBER(AD40),ISNUMBER(INDEX('Sources'!$G$7:$G$10,MATCH(AB40,'Sources'!$B$7:$B$10,0)))),AD40/INDEX('Sources'!$G$7:$G$10,MATCH(AB40,'Sources'!$B$7:$B$10,0)),"") | J40: EXACT | K40: 2026-09-30 | M40: Code R-M211065; site shows 331 CZK bez DPH; in stock | N40: https://www.tomgast.cz/gastronadoba-polykarbonatova-gn-1-1-65-mm/ | O40: Cambro | P40: incl. | Q40: 0.21 | R40: 1 | S40: per piece | T40: EXACT | U40: Existing benchmark assignment and match quality retained. | X40: YES Gastro Czech Market Research.xlsx | AB40: CZK | AC40: yes | AD40: =IF(OR(F40="",Q40="",R40=""),"",ROUND(IF(P40="incl.",F40/(1+Q40),F40)/IF(S40="per pack",R40,1),2)) | AE40: =IF(AND(AC40="yes",ISNUMBER(F40),IF('Compare'!$H$5="All mapped",TRUE,IF('Compare'!$H$5="EXACT only",J40="EXACT",OR(J40="EXACT",J40="CLOSE")))),"yes","no") | AF40: =IF(ISNUMBER(H40),COUNTIFS($B$7:$B$608,B40,$C$7:$C$608,C40,$H$7:$H$608,"<"&H40,$AH$7:$AH$608,"yes")+COUNTIFS($B$7:B40,B40,$C$7:C40,C40,$H$7:H40,H40,$AH$7:AH40,"yes"),"") | AG40: =IF(ISNUMBER(I40),COUNTIFS($B$7:$B$608,B40,$C$7:$C$608,C40,$I$7:$I$608,"<"&I40,$AI$7:$AI$608,"yes")+COUNTIFS($B$7:B40,B40,$C$7:C40,C40,$I$7:I40,I40,$AI$7:AI40,"yes"),"") | AH40: =IF(ISNUMBER(H40),"yes","no") | AI40: =IF(ISNUMBER(I40),"yes","no") | AJ40: 46295
B41: GN 1/1 PC container, 65 mm | C41: Slovakia | D41: Gastromania.sk (GASTROMANIA CZ s.r.o., CZ) | E41: Polykarbonátová gastronádoba GN1/1 65 mm | CONTACTO, 8211/065 | F41: 20.48 | G41: EUR | H41: =IF(AND(AE41="yes",ISNUMBER(AD41)),AD41,"") | I41: =IF(AND(AE41="yes",ISNUMBER(AD41),ISNUMBER(INDEX('Sources'!$G$7:$G$10,MATCH(AB41,'Sources'!$B$7:$B$10,0)))),AD41/INDEX('Sources'!$G$7:$G$10,MATCH(AB41,'Sources'!$B$7:$B$10,0)),"") | J41: EXACT | K41: 2026-09-30 | M41: Listed 'Cena bez DPH' 20.48 EUR / 'Cena s DPH' 25.19 EUR. PC, GN 1/1, 65 mm, 8,5 l. Promo price; base 22,75 bez DPH / 27,98 s DPH. Availability 30 days. | N41: https://gastromania.sk/gastronadoby-polykarbonatove/polykarbonatova-gastronadoba-gn1-1-65-mm-contacto-8211-065 | O41: Contacto | P41: excl. | Q41: n/a | R41: 1 | S41: per piece | T41: EXACT | U41: Existing benchmark assignment and match quality retained. | V41: 20.48 | X41: YES Gastro Slovakia Market Research.xlsx | AB41: EUR | AC41: yes | AD41: =IF(ISNUMBER(V41),V41,"") | AE41: =IF(AND(AC41="yes",ISNUMBER(F41),IF('Compare'!$H$5="All mapped",TRUE,IF('Compare'!$H$5="EXACT only",J41="EXACT",OR(J41="EXACT",J41="CLOSE")))),"yes","no") | AF41: =IF(ISNUMBER(H41),COUNTIFS($B$7:$B$608,B41,$C$7:$C$608,C41,$H$7:$H$608,"<"&H41,$AH$7:$AH$608,"yes")+COUNTIFS($B$7:B41,B41,$C$7:C41,C41,$H$7:H41,H41,$AH$7:AH41,"yes"),"") | AG41: =IF(ISNUMBER(I41),COUNTIFS($B$7:$B$608,B41,$C$7:$C$608,C41,$I$7:$I$608,"<"&I41,$AI$7:$AI$608,"yes")+COUNTIFS($B$7:B41,B41,$C$7:C41,C41,$I$7:I41,I41,$AI$7:AI41,"yes"),"") | AH41: =IF(ISNUMBER(H41),"yes","no") | AI41: =IF(ISNUMBER(I41),"yes","no") | AJ41: 46295
B42: GN 1/1 PC container, 65 mm | C42: Slovakia | D42: Gastrozone.sk (GASTROZONE, spol. s r.o., CZ) | E42: ARAVEN Gastronádoba GN 1/1, polykarbonát, Hĺbka: 65 mm, Objem: 8,6 L | F42: 20.24 | G42: EUR | H42: =IF(AND(AE42="yes",ISNUMBER(AD42)),AD42,"") | I42: =IF(AND(AE42="yes",ISNUMBER(AD42),ISNUMBER(INDEX('Sources'!$G$7:$G$10,MATCH(AB42,'Sources'!$B$7:$B$10,0)))),AD42/INDEX('Sources'!$G$7:$G$10,MATCH(AB42,'Sources'!$B$7:$B$10,0)),"") | J42: EXACT | K42: 2026-09-30 | M42: Page shows 20,24 EUR / 16,46 EUR bez DPH. Availability: to order (3-5 weeks). | N42: https://www.gastrozone.sk/araven-gn-box-1-1-polykarbonat-hloubka-65-mm-objem-8-6-l.html | O42: Araven | P42: incl. | Q42: 0.23 | R42: 1 | S42: per piece | T42: EXACT | U42: Existing benchmark assignment and match quality retained. | V42: 16.455285 | X42: YES Gastro Slovakia Market Research.xlsx | AB42: EUR | AC42: yes | AD42: =IF(ISNUMBER(V42),V42,"") | AE42: =IF(AND(AC42="yes",ISNUMBER(F42),IF('Compare'!$H$5="All mapped",TRUE,IF('Compare'!$H$5="EXACT only",J42="EXACT",OR(J42="EXACT",J42="CLOSE")))),"yes","no") | AF42: =IF(ISNUMBER(H42),COUNTIFS($B$7:$B$608,B42,$C$7:$C$608,C42,$H$7:$H$608,"<"&H42,$AH$7:$AH$608,"yes")+COUNTIFS($B$7:B42,B42,$C$7:C42,C42,$H$7:H42,H42,$AH$7:AH42,"yes"),"") | AG42: =IF(ISNUMBER(I42),COUNTIFS($B$7:$B$608,B42,$C$7:$C$608,C42,$I$7:$I$608,"<"&I42,$AI$7:$AI$608,"yes")+COUNTIFS($B$7:B42,B42,$C$7:C42,C42,$I$7:I42,I42,$AI$7:AI42,"yes"),"") | AH42: =IF(ISNUMBER(H42),"yes","no") | AI42: =IF(ISNUMBER(I42),"yes","no") | AJ42: 46295
B43: GN 1/2 PC container, 150 mm | C43: Hungary | D43: Attase | E43: GN 1/2 150 - Polycarbonate | F43: 3129 | G43: HUF | H43: =IF(AND(AE43="yes",ISNUMBER(AD43)),AD43,"") | I43: =IF(AND(AE43="yes",ISNUMBER(AD43),ISNUMBER(INDEX('Sources'!$G$7:$G$10,MATCH(AB43,'Sources'!$B$7:$B$10,0)))),AD43/INDEX('Sources'!$G$7:$G$10,MATCH(AB43,'Sources'!$B$7:$B$10,0)),"") | J43: EXACT | K43: 08.06.2026 | M43: Source sheet: GN Containers; size: GN 1/2 150; material: Polycarbonate | N43: https://www.attase.hu/konyhai-eszkozok/gn-edeny/polikarbonat-gn-edenyek | U43: GN size, depth and material agree. Colour is unrestricted in the benchmark. | W43: 3129 | X43: YES Gastro Hungary Market Research.xlsx | AA43: Direct | AB43: HUF | AC43: yes | AD43: =IF(ISNUMBER(F43),IF(G43=AB43,F43,IF(AND(ISNUMBER(INDEX('Sources'!$G$7:$G$10,MATCH(G43,'Sources'!$B$7:$B$10,0))),ISNUMBER(INDEX('Sources'!$G$7:$G$10,MATCH(AB43,'Sources'!$B$7:$B$10,0)))),F43/INDEX('Sources'!$G$7:$G$10,MATCH(G43,'Sources'!$B$7:$B$10,0))*INDEX('Sources'!$G$7:$G$10,MATCH(AB43,'Sources'!$B$7:$B$10,0)),"")),"") | AE43: =IF(AND(AC43="yes",ISNUMBER(F43),IF('Compare'!$H$5="All mapped",TRUE,IF('Compare'!$H$5="EXACT only",J43="EXACT",OR(J43="EXACT",J43="CLOSE")))),"yes","no") | AF43: =IF(ISNUMBER(H43),COUNTIFS($B$7:$B$608,B43,$C$7:$C$608,C43,$H$7:$H$608,"<"&H43,$AH$7:$AH$608,"yes")+COUNTIFS($B$7:B43,B43,$C$7:C43,C43,$H$7:H43,H43,$AH$7:AH43,"yes"),"") | AG43: =IF(ISNUMBER(I43),COUNTIFS($B$7:$B$608,B43,$C$7:$C$608,C43,$I$7:$I$608,"<"&I43,$AI$7:$AI$608,"yes")+COUNTIFS($B$7:B43,B43,$C$7:C43,C43,$I$7:I43,I43,$AI$7:AI43,"yes"),"") | AH43: =IF(ISNUMBER(H43),"yes","no") | AI43: =IF(ISNUMBER(I43),"yes","no") | AJ43: 46181
B44: GN 1/2 PC container, 150 mm | C44: Hungary | D44: Gammo | E44: GN 1/2 150 - Polycarbonate | F44: 2340 | G44: HUF | H44: =IF(AND(AE44="yes",ISNUMBER(AD44)),AD44,"") | I44: =IF(AND(AE44="yes",ISNUMBER(AD44),ISNUMBER(INDEX('Sources'!$G$7:$G$10,MATCH(AB44,'Sources'!$B$7:$B$10,0)))),AD44/INDEX('Sources'!$G$7:$G$10,MATCH(AB44,'Sources'!$B$7:$B$10,0)),"") | J44: EXACT | K44: 08.06.2026 | M44: Source sheet: GN Containers; size: GN 1/2 150; material: Polycarbonate | N44: https://gammo.hu/edeny-tepsi/gasztronorm-gn-edeny | U44: GN size, depth and material agree. Colour is unrestricted in the benchmark. | W44: 2340 | X44: YES Gastro Hungary Market Research.xlsx | AA44: Direct | AB44: HUF | AC44: yes | AD44: =IF(ISNUMBER(F44),IF(G44=AB44,F44,IF(AND(ISNUMBER(INDEX('Sources'!$G$7:$G$10,MATCH(G44,'Sources'!$B$7:$B$10,0))),ISNUMBER(INDEX('Sources'!$G$7:$G$10,MATCH(AB44,'Sources'!$B$7:$B$10,0)))),F44/INDEX('Sources'!$G$7:$G$10,MATCH(G44,'Sources'!$B$7:$B$10,0))*INDEX('Sources'!$G$7:$G$10,MATCH(AB44,'Sources'!$B$7:$B$10,0)),"")),"") | AE44: =IF(AND(AC44="yes",ISNUMBER(F44),IF('Compare'!$H$5="All mapped",TRUE,IF('Compare'!$H$5="EXACT only",J44="EXACT",OR(J44="EXACT",J44="CLOSE")))),"yes","no") | AF44: =IF(ISNUMBER(H44),COUNTIFS($B$7:$B$608,B44,$C$7:$C$608,C44,$H$7:$H$608,"<"&H44,$AH$7:$AH$608,"yes")+COUNTIFS($B$7:B44,B44,$C$7:C44,C44,$H$7:H44,H44,$AH$7:AH44,"yes"),"") | AG44: =IF(ISNUMBER(I44),COUNTIFS($B$7:$B$608,B44,$C$7:$C$608,C44,$I$7:$I$608,"<"&I44,$AI$7:$AI$608,"yes")+COUNTIFS($B$7:B44,B44,$C$7:C44,C44,$I$7:I44,I44,$AI$7:AI44,"yes"),"") | AH44: =IF(ISNUMBER(H44),"yes","no") | AI44: =IF(ISNUMBER(I44),"yes","no") | AJ44: 46181
B45: GN 1/2 PC container, 150 mm | C45: Hungary | D45: Gasztronagyker | E45: GN 1/2 150 - Polycarbonate | F45: 5740 | G45: HUF | H45: =IF(AND(AE45="yes",ISNUMBER(AD45)),AD45,"") | I45: =IF(AND(AE45="yes",ISNUMBER(AD45),ISNUMBER(INDEX('Sources'!$G$7:$G$10,MATCH(AB45,'Sources'!$B$7:$B$10,0)))),AD45/INDEX('Sources'!$G$7:$G$10,MATCH(AB45,'Sources'!$B$7:$B$10,0)),"") | J45: EXACT | K45: 08.06.2026 | M45: Source sheet: GN Containers; size: GN 1/2 150; material: Polycarbonate | N45: https://www.gasztronagyker.hu/gn-edenyek | U45: GN size, depth and material agree. Colour is unrestricted in the benchmark. | W45: 5740 | X45: YES Gastro Hungary Market Research.xlsx | AA45: Direct | AB45: HUF | AC45: yes | AD45: =IF(ISNUMBER(F45),IF(G45=AB45,F45,IF(AND(ISNUMBER(INDEX('Sources'!$G$7:$G$10,MATCH(G45,'Sources'!$B$7:$B$10,0))),ISNUMBER(INDEX('Sources'!$G$7:$G$10,MATCH(AB45,'Sources'!$B$7:$B$10,0)))),F45/INDEX('Sources'!$G$7:$G$10,MATCH(G45,'Sources'!$B$7:$B$10,0))*INDEX('Sources'!$G$7:$G$10,MATCH(AB45,'Sources'!$B$7:$B$10,0)),"")),"") | AE45: =IF(AND(AC45="yes",ISNUMBER(F45),IF('Compare'!$H$5="All mapped",TRUE,IF('Compare'!$H$5="EXACT only",J45="EXACT",OR(J45="EXACT",J45="CLOSE")))),"yes","no") | AF45: =IF(ISNUMBER(H45),COUNTIFS($B$7:$B$608,B45,$C$7:$C$608,C45,$H$7:$H$608,"<"&H45,$AH$7:$AH$608,"yes")+COUNTIFS($B$7:B45,B45,$C$7:C45,C45,$H$7:H45,H45,$AH$7:AH45,"yes"),"") | AG45: =IF(ISNUMBER(I45),COUNTIFS($B$7:$B$608,B45,$C$7:$C$608,C45,$I$7:$I$608,"<"&I45,$AI$7:$AI$608,"yes")+COUNTIFS($B$7:B45,B45,$C$7:C45,C45,$I$7:I45,I45,$AI$7:AI45,"yes"),"") | AH45: =IF(ISNUMBER(H45),"yes","no") | AI45: =IF(ISNUMBER(I45),"yes","no") | AJ45: 46181
B46: GN 1/2 PC container, 150 mm | C46: Hungary | D46: HFSE | E46: GN 1/2 150 - Polycarbonate | F46: 3535 | G46: HUF | H46: =IF(AND(AE46="yes",ISNUMBER(AD46)),AD46,"") | I46: =IF(AND(AE46="yes",ISNUMBER(AD46),ISNUMBER(INDEX('Sources'!$G$7:$G$10,MATCH(AB46,'Sources'!$B$7:$B$10,0)))),AD46/INDEX('Sources'!$G$7:$G$10,MATCH(AB46,'Sources'!$B$7:$B$10,0)),"") | J46: EXACT | K46: 08.06.2026 | M46: Source sheet: GN Containers; size: GN 1/2 150; material: Polycarbonate | N46: https://hfse.hu/termekkategoria/konyhai-eszkozok/gn-edenyek/ | U46: GN size, depth and material agree. Colour is unrestricted in the benchmark. | W46: 3535 | X46: YES Gastro Hungary Market Research.xlsx | AA46: Direct | AB46: HUF | AC46: yes | AD46: =IF(ISNUMBER(F46),IF(G46=AB46,F46,IF(AND(ISNUMBER(INDEX('Sources'!$G$7:$G$10,MATCH(G46,'Sources'!$B$7:$B$10,0))),ISNUMBER(INDEX('Sources'!$G$7:$G$10,MATCH(AB46,'Sources'!$B$7:$B$10,0)))),F46/INDEX('Sources'!$G$7:$G$10,MATCH(G46,'Sources'!$B$7:$B$10,0))*INDEX('Sources'!$G$7:$G$10,MATCH(AB46,'Sources'!$B$7:$B$10,0)),"")),"") | AE46: =IF(AND(AC46="yes",ISNUMBER(F46),IF('Compare'!$H$5="All mapped",TRUE,IF('Compare'!$H$5="EXACT only",J46="EXACT",OR(J46="EXACT",J46="CLOSE")))),"yes","no") | AF46: =IF(ISNUMBER(H46),COUNTIFS($B$7:$B$608,B46,$C$7:$C$608,C46,$H$7:$H$608,"<"&H46,$AH$7:$AH$608,"yes")+COUNTIFS($B$7:B46,B46,$C$7:C46,C46,$H$7:H46,H46,$AH$7:AH46,"yes"),"") | AG46: =IF(ISNUMBER(I46),COUNTIFS($B$7:$B$608,B46,$C$7:$C$608,C46,$I$7:$I$608,"<"&I46,$AI$7:$AI$608,"yes")+COUNTIFS($B$7:B46,B46,$C$7:C46,C46,$I$7:I46,I46,$AI$7:AI46,"yes"),"") | AH46: =IF(ISNUMBER(H46),"yes","no") | AI46: =IF(ISNUMBER(I46),"yes","no") | AJ46: 46181
B47: GN 1/2 PC container, 150 mm | C47: Hungary | D47: Hunnia | E47: GN 1/2 150 - Polycarbonate | F47: 5419 | G47: HUF | H47: =IF(AND(AE47="yes",ISNUMBER(AD47)),AD47,"") | I47: =IF(AND(AE47="yes",ISNUMBER(AD47),ISNUMBER(INDEX('Sources'!$G$7:$G$10,MATCH(AB47,'Sources'!$B$7:$B$10,0)))),AD47/INDEX('Sources'!$G$7:$G$10,MATCH(AB47,'Sources'!$B$7:$B$10,0)),"") | J47: EXACT | K47: 08.06.2026 | M47: Source sheet: GN Containers; size: GN 1/2 150; material: Polycarbonate | N47: https://hunniakristaly.hu/nagy-konyha/gn-edenyek-rozsdamentes-acelbol-polipropilenb-l-polikarbonat/gn-edenyek-torhetetlen-viztiszta-polikarbonatbol | U47: GN size, depth and material agree. Colour is unrestricted in the benchmark. | W47: 5419 | X47: YES Gastro Hungary Market Research.xlsx | AA47: Direct | AB47: HUF | AC47: yes | AD47: =IF(ISNUMBER(F47),IF(G47=AB47,F47,IF(AND(ISNUMBER(INDEX('Sources'!$G$7:$G$10,MATCH(G47,'Sources'!$B$7:$B$10,0))),ISNUMBER(INDEX('Sources'!$G$7:$G$10,MATCH(AB47,'Sources'!$B$7:$B$10,0)))),F47/INDEX('Sources'!$G$7:$G$10,MATCH(G47,'Sources'!$B$7:$B$10,0))*INDEX('Sources'!$G$7:$G$10,MATCH(AB47,'Sources'!$B$7:$B$10,0)),"")),"") | AE47: =IF(AND(AC47="yes",ISNUMBER(F47),IF('Compare'!$H$5="All mapped",TRUE,IF('Compare'!$H$5="EXACT only",J47="EXACT",OR(J47="EXACT",J47="CLOSE")))),"yes","no") | AF47: =IF(ISNUMBER(H47),COUNTIFS($B$7:$B$608,B47,$C$7:$C$608,C47,$H$7:$H$608,"<"&H47,$AH$7:$AH$608,"yes")+COUNTIFS($B$7:B47,B47,$C$7:C47,C47,$H$7:H47,H47,$AH$7:AH47,"yes"),"") | AG47: =IF(ISNUMBER(I47),COUNTIFS($B$7:$B$608,B47,$C$7:$C$608,C47,$I$7:$I$608,"<"&I47,$AI$7:$AI$608,"yes")+COUNTIFS($B$7:B47,B47,$C$7:C47,C47,$I$7:I47,I47,$AI$7:AI47,"yes"),"") | AH47: =IF(ISNUMBER(H47),"yes","no") | AI47: =IF(ISNUMBER(I47),"yes","no") | AJ47: 46181
B48: GN 1/2 PC container, 150 mm | C48: Hungary | D48: Inox-Pláza | E48: GN 1/2 150 - Polycarbonate | F48: 3500 | G48: HUF | H48: =IF(AND(AE48="yes",ISNUMBER(AD48)),AD48,"") | I48: =IF(AND(AE48="yes",ISNUMBER(AD48),ISNUMBER(INDEX('Sources'!$G$7:$G$10,MATCH(AB48,'Sources'!$B$7:$B$10,0)))),AD48/INDEX('Sources'!$G$7:$G$10,MATCH(AB48,'Sources'!$B$7:$B$10,0)),"") | J48: EXACT | K48: 08.06.2026 | M48: Source sheet: GN Containers; size: GN 1/2 150; material: Polycarbonate | N48: https://www.inoxplaza.hu/edenyzet/gn-edeny | U48: GN size, depth and material agree. Colour is unrestricted in the benchmark. | W48: 3500 | X48: YES Gastro Hungary Market Research.xlsx | AA48: Direct | AB48: HUF | AC48: yes | AD48: =IF(ISNUMBER(F48),IF(G48=AB48,F48,IF(AND(ISNUMBER(INDEX('Sources'!$G$7:$G$10,MATCH(G48,'Sources'!$B$7:$B$10,0))),ISNUMBER(INDEX('Sources'!$G$7:$G$10,MATCH(AB48,'Sources'!$B$7:$B$10,0)))),F48/INDEX('Sources'!$G$7:$G$10,MATCH(G48,'Sources'!$B$7:$B$10,0))*INDEX('Sources'!$G$7:$G$10,MATCH(AB48,'Sources'!$B$7:$B$10,0)),"")),"") | AE48: =IF(AND(AC48="yes",ISNUMBER(F48),IF('Compare'!$H$5="All mapped",TRUE,IF('Compare'!$H$5="EXACT only",J48="EXACT",OR(J48="EXACT",J48="CLOSE")))),"yes","no") | AF48: =IF(ISNUMBER(H48),COUNTIFS($B$7:$B$608,B48,$C$7:$C$608,C48,$H$7:$H$608,"<"&H48,$AH$7:$AH$608,"yes")+COUNTIFS($B$7:B48,B48,$C$7:C48,C48,$H$7:H48,H48,$AH$7:AH48,"yes"),"") | AG48: =IF(ISNUMBER(I48),COUNTIFS($B$7:$B$608,B48,$C$7:$C$608,C48,$I$7:$I$608,"<"&I48,$AI$7:$AI$608,"yes")+COUNTIFS($B$7:B48,B48,$C$7:C48,C48,$I$7:I48,I48,$AI$7:AI48,"yes"),"") | AH48: =IF(ISNUMBER(H48),"yes","no") | AI48: =IF(ISNUMBER(I48),"yes","no") | AJ48: 46181
B49: GN 1/2 PC container, 150 mm | C49: Romania | D49: FiMax | E49: GN 1/2 150mm - Polycarbonate | F49: 57.38 | G49: RON | H49: =IF(AND(AE49="yes",ISNUMBER(AD49)),AD49,"") | I49: =IF(AND(AE49="yes",ISNUMBER(AD49),ISNUMBER(INDEX('Sources'!$G$7:$G$10,MATCH(AB49,'Sources'!$B$7:$B$10,0)))),AD49/INDEX('Sources'!$G$7:$G$10,MATCH(AB49,'Sources'!$B$7:$B$10,0)),"") | J49: EXACT | K49: 2.07.2026 | M49: PC | N49: https://www.fimax.ro/categorie/echipamente-catering-autoservire-si-cuve-inox-gastronorm/cuve-gastronorm-gn/cuve-gn-policarbonat-transparent/ | U49: GN size, depth and material agree. Colour is unrestricted in the benchmark. | W49: 11.476 | X49: YES Gastro Romania Market Research.xlsx | Y49: Gabi | AB49: RON | AC49: yes | AD49: =IF(ISNUMBER(F49),IF(G49=AB49,F49,IF(AND(ISNUMBER(INDEX('Sources'!$G$7:$G$10,MATCH(G49,'Sources'!$B$7:$B$10,0))),ISNUMBER(INDEX('Sources'!$G$7:$G$10,MATCH(AB49,'Sources'!$B$7:$B$10,0)))),F49/INDEX('Sources'!$G$7:$G$10,MATCH(G49,'Sources'!$B$7:$B$10,0))*INDEX('Sources'!$G$7:$G$10,MATCH(AB49,'Sources'!$B$7:$B$10,0)),"")),"") | AE49: =IF(AND(AC49="yes",ISNUMBER(F49),IF('Compare'!$H$5="All mapped",TRUE,IF('Compare'!$H$5="EXACT only",J49="EXACT",OR(J49="EXACT",J49="CLOSE")))),"yes","no") | AF49: =IF(ISNUMBER(H49),COUNTIFS($B$7:$B$608,B49,$C$7:$C$608,C49,$H$7:$H$608,"<"&H49,$AH$7:$AH$608,"yes")+COUNTIFS($B$7:B49,B49,$C$7:C49,C49,$H$7:H49,H49,$AH$7:AH49,"yes"),"") | AG49: =IF(ISNUMBER(I49),COUNTIFS($B$7:$B$608,B49,$C$7:$C$608,C49,$I$7:$I$608,"<"&I49,$AI$7:$AI$608,"yes")+COUNTIFS($B$7:B49,B49,$C$7:C49,C49,$I$7:I49,I49,$AI$7:AI49,"yes"),"") | AH49: =IF(ISNUMBER(H49),"yes","no") | AI49: =IF(ISNUMBER(I49),"yes","no") | AJ49: 46205
B50: GN 1/2 PC container, 150 mm | C50: Romania | D50: FiMax | E50: GN 1/2 150mm - Polycarbonate Black | F50: 58.52 | G50: RON | H50: =IF(AND(AE50="yes",ISNUMBER(AD50)),AD50,"") | I50: =IF(AND(AE50="yes",ISNUMBER(AD50),ISNUMBER(INDEX('Sources'!$G$7:$G$10,MATCH(AB50,'Sources'!$B$7:$B$10,0)))),AD50/INDEX('Sources'!$G$7:$G$10,MATCH(AB50,'Sources'!$B$7:$B$10,0)),"") | J50: EXACT | K50: 5.07.2026 | M50: PC | N50: https://www.fimax.ro/categorie/echipamente-catering-autoservire-si-cuve-inox-gastronorm/cuve-gastronorm-gn/cuve-gn-policarbonat-negru/ | U50: GN size, depth and material agree. Colour is unrestricted in the benchmark. | W50: 11.704 | X50: YES Gastro Romania Market Research.xlsx | Y50: Gabi | AB50: RON | AC50: yes | AD50: =IF(ISNUMBER(F50),IF(G50=AB50,F50,IF(AND(ISNUMBER(INDEX('Sources'!$G$7:$G$10,MATCH(G50,'Sources'!$B$7:$B$10,0))),ISNUMBER(INDEX('Sources'!$G$7:$G$10,MATCH(AB50,'Sources'!$B$7:$B$10,0)))),F50/INDEX('Sources'!$G$7:$G$10,MATCH(G50,'Sources'!$B$7:$B$10,0))*INDEX('Sources'!$G$7:$G$10,MATCH(AB50,'Sources'!$B$7:$B$10,0)),"")),"") | AE50: =IF(AND(AC50="yes",ISNUMBER(F50),IF('Compare'!$H$5="All mapped",TRUE,IF('Compare'!$H$5="EXACT only",J50="EXACT",OR(J50="EXACT",J50="CLOSE")))),"yes","no") | AF50: =IF(ISNUMBER(H50),COUNTIFS($B$7:$B$608,B50,$C$7:$C$608,C50,$H$7:$H$608,"<"&H50,$AH$7:$AH$608,"yes")+COUNTIFS($B$7:B50,B50,$C$7:C50,C50,$H$7:H50,H50,$AH$7:AH50,"yes"),"") | AG50: =IF(ISNUMBER(I50),COUNTIFS($B$7:$B$608,B50,$C$7:$C$608,C50,$I$7:$I$608,"<"&I50,$AI$7:$AI$608,"yes")+COUNTIFS($B$7:B50,B50,$C$7:C50,C50,$I$7:I50,I50,$AI$7:AI50,"yes"),"") | AH50: =IF(ISNUMBER(H50),"yes","no") | AI50: =IF(ISNUMBER(I50),"yes","no") | AJ50: 46208
B51: GN 1/2 PC container, 150 mm | C51: Romania | D51: Gastrozone | E51: GN 1/2 150 mm - Polycarbonate | F51: 85.04 | G51: RON | H51: =IF(AND(AE51="yes",ISNUMBER(AD51)),AD51,"") | I51: =IF(AND(AE51="yes",ISNUMBER(AD51),ISNUMBER(INDEX('Sources'!$G$7:$G$10,MATCH(AB51,'Sources'!$B$7:$B$10,0)))),AD51/INDEX('Sources'!$G$7:$G$10,MATCH(AB51,'Sources'!$B$7:$B$10,0)),"") | J51: EXACT | K51: 30.09.2026 | M51: PC. Live check 30.09.2026: ARAVEN GN 1/2 PC 150 mm, 8 l - 102.90 lei incl. TVA = 85.04 lei net (on order, 3-5 weeks). Replaces the impossible source date 30.06.2028 (source price 85.27 RON net). | N51: https://www.gastrozone.ro/cautare/?text=gn+1/2+150mm+policarbonat | O51: Araven | U51: GN size, depth and material agree. Colour is unrestricted in the benchmark. | W51: 17.054 | X51: YES Gastro Romania Market Research.xlsx | Y51: Gabi | AB51: RON | AC51: yes | AD51: =IF(ISNUMBER(F51),IF(G51=AB51,F51,IF(AND(ISNUMBER(INDEX('Sources'!$G$7:$G$10,MATCH(G51,'Sources'!$B$7:$B$10,0))),ISNUMBER(INDEX('Sources'!$G$7:$G$10,MATCH(AB51,'Sources'!$B$7:$B$10,0)))),F51/INDEX('Sources'!$G$7:$G$10,MATCH(G51,'Sources'!$B$7:$B$10,0))*INDEX('Sources'!$G$7:$G$10,MATCH(AB51,'Sources'!$B$7:$B$10,0)),"")),"") | AE51: =IF(AND(AC51="yes",ISNUMBER(F51),IF('Compare'!$H$5="All mapped",TRUE,IF('Compare'!$H$5="EXACT only",J51="EXACT",OR(J51="EXACT",J51="CLOSE")))),"yes","no") | AF51: =IF(ISNUMBER(H51),COUNTIFS($B$7:$B$608,B51,$C$7:$C$608,C51,$H$7:$H$608,"<"&H51,$AH$7:$AH$608,"yes")+COUNTIFS($B$7:B51,B51,$C$7:C51,C51,$H$7:H51,H51,$AH$7:AH51,"yes"),"") | AG51: =IF(ISNUMBER(I51),COUNTIFS($B$7:$B$608,B51,$C$7:$C$608,C51,$I$7:$I$608,"<"&I51,$AI$7:$AI$608,"yes")+COUNTIFS($B$7:B51,B51,$C$7:C51,C51,$I$7:I51,I51,$AI$7:AI51,"yes"),"") | AH51: =IF(ISNUMBER(H51),"yes","no") | AI51: =IF(ISNUMBER(I51),"yes","no") | AJ51: 46295
B52: GN 1/2 PC container, 150 mm | C52: Romania | D52: Gastrozone | E52: GN 1/2 150mm - Polycarbonate Black | F52: 79.52 | G52: RON | H52: =IF(AND(AE52="yes",ISNUMBER(AD52)),AD52,"") | I52: =IF(AND(AE52="yes",ISNUMBER(AD52),ISNUMBER(INDEX('Sources'!$G$7:$G$10,MATCH(AB52,'Sources'!$B$7:$B$10,0)))),AD52/INDEX('Sources'!$G$7:$G$10,MATCH(AB52,'Sources'!$B$7:$B$10,0)),"") | J52: EXACT | K52: 5.07.2026 | M52: PC | N52: https://www.gastrozone.ro/vase-gastro/marime=gn-1-2/inalta=150/material=policarbonat/ | O52: APS | U52: GN size, depth and material agree. Colour is unrestricted in the benchmark. | W52: 15.904 | X52: YES Gastro Romania Market Research.xlsx | Y52: Gabi | AB52: RON | AC52: yes | AD52: =IF(ISNUMBER(F52),IF(G52=AB52,F52,IF(AND(ISNUMBER(INDEX('Sources'!$G$7:$G$10,MATCH(G52,'Sources'!$B$7:$B$10,0))),ISNUMBER(INDEX('Sources'!$G$7:$G$10,MATCH(AB52,'Sources'!$B$7:$B$10,0)))),F52/INDEX('Sources'!$G$7:$G$10,MATCH(G52,'Sources'!$B$7:$B$10,0))*INDEX('Sources'!$G$7:$G$10,MATCH(AB52,'Sources'!$B$7:$B$10,0)),"")),"") | AE52: =IF(AND(AC52="yes",ISNUMBER(F52),IF('Compare'!$H$5="All mapped",TRUE,IF('Compare'!$H$5="EXACT only",J52="EXACT",OR(J52="EXACT",J52="CLOSE")))),"yes","no") | AF52: =IF(ISNUMBER(H52),COUNTIFS($B$7:$B$608,B52,$C$7:$C$608,C52,$H$7:$H$608,"<"&H52,$AH$7:$AH$608,"yes")+COUNTIFS($B$7:B52,B52,$C$7:C52,C52,$H$7:H52,H52,$AH$7:AH52,"yes"),"") | AG52: =IF(ISNUMBER(I52),COUNTIFS($B$7:$B$608,B52,$C$7:$C$608,C52,$I$7:$I$608,"<"&I52,$AI$7:$AI$608,"yes")+COUNTIFS($B$7:B52,B52,$C$7:C52,C52,$I$7:I52,I52,$AI$7:AI52,"yes"),"") | AH52: =IF(ISNUMBER(H52),"yes","no") | AI52: =IF(ISNUMBER(I52),"yes","no") | AJ52: 46208
B53: GN 1/2 PC container, 150 mm | C53: Romania | D53: Hendi | E53: GN 1/2 150 mm - Polycarbonate | F53: 89.26 | G53: RON | H53: =IF(AND(AE53="yes",ISNUMBER(AD53)),AD53,"") | I53: =IF(AND(AE53="yes",ISNUMBER(AD53),ISNUMBER(INDEX('Sources'!$G$7:$G$10,MATCH(AB53,'Sources'!$B$7:$B$10,0)))),AD53/INDEX('Sources'!$G$7:$G$10,MATCH(AB53,'Sources'!$B$7:$B$10,0)),"") | J53: EXACT | K53: 30.06.2026 | M53: PC | N53: https://www.hendi.ro/tavi-gastronorm/containere-gn?filter=25820/l/478616 | O53: Hendi | U53: GN size, depth and material agree. Colour is unrestricted in the benchmark. | W53: 17.852 | X53: YES Gastro Romania Market Research.xlsx | Y53: Gabi | AB53: RON | AC53: yes | AD53: =IF(ISNUMBER(F53),IF(G53=AB53,F53,IF(AND(ISNUMBER(INDEX('Sources'!$G$7:$G$10,MATCH(G53,'Sources'!$B$7:$B$10,0))),ISNUMBER(INDEX('Sources'!$G$7:$G$10,MATCH(AB53,'Sources'!$B$7:$B$10,0)))),F53/INDEX('Sources'!$G$7:$G$10,MATCH(G53,'Sources'!$B$7:$B$10,0))*INDEX('Sources'!$G$7:$G$10,MATCH(AB53,'Sources'!$B$7:$B$10,0)),"")),"") | AE53: =IF(AND(AC53="yes",ISNUMBER(F53),IF('Compare'!$H$5="All mapped",TRUE,IF('Compare'!$H$5="EXACT only",J53="EXACT",OR(J53="EXACT",J53="CLOSE")))),"yes","no") | AF53: =IF(ISNUMBER(H53),COUNTIFS($B$7:$B$608,B53,$C$7:$C$608,C53,$H$7:$H$608,"<"&H53,$AH$7:$AH$608,"yes")+COUNTIFS($B$7:B53,B53,$C$7:C53,C53,$H$7:H53,H53,$AH$7:AH53,"yes"),"") | AG53: =IF(ISNUMBER(I53),COUNTIFS($B$7:$B$608,B53,$C$7:$C$608,C53,$I$7:$I$608,"<"&I53,$AI$7:$AI$608,"yes")+COUNTIFS($B$7:B53,B53,$C$7:C53,C53,$I$7:I53,I53,$AI$7:AI53,"yes"),"") | AH53: =IF(ISNUMBER(H53),"yes","no") | AI53: =IF(ISNUMBER(I53),"yes","no") | AJ53: 46203
B54: GN 1/2 PC container, 150 mm | C54: Romania | D54: Hendi | E54: GN 1/2 150mm - Polycarbonate Black | F54: 54.9 | G54: RON | H54: =IF(AND(AE54="yes",ISNUMBER(AD54)),AD54,"") | I54: =IF(AND(AE54="yes",ISNUMBER(AD54),ISNUMBER(INDEX('Sources'!$G$7:$G$10,MATCH(AB54,'Sources'!$B$7:$B$10,0)))),AD54/INDEX('Sources'!$G$7:$G$10,MATCH(AB54,'Sources'!$B$7:$B$10,0)),"") | J54: EXACT | K54: 5.07.2026 | M54: PC | N54: https://www.hendi.ro/tavi-gastronorm/containere-gn?filter=25819/l/478607|25820/l/478616|25821/l/478668;478669 | O54: Hendi | U54: GN size, depth and material agree. Colour is unrestricted in the benchmark. | W54: 10.98 | X54: YES Gastro Romania Market Research.xlsx | Y54: Gabi | AB54: RON | AC54: yes | AD54: =IF(ISNUMBER(F54),IF(G54=AB54,F54,IF(AND(ISNUMBER(INDEX('Sources'!$G$7:$G$10,MATCH(G54,'Sources'!$B$7:$B$10,0))),ISNUMBER(INDEX('Sources'!$G$7:$G$10,MATCH(AB54,'Sources'!$B$7:$B$10,0)))),F54/INDEX('Sources'!$G$7:$G$10,MATCH(G54,'Sources'!$B$7:$B$10,0))*INDEX('Sources'!$G$7:$G$10,MATCH(AB54,'Sources'!$B$7:$B$10,0)),"")),"") | AE54: =IF(AND(AC54="yes",ISNUMBER(F54),IF('Compare'!$H$5="All mapped",TRUE,IF('Compare'!$H$5="EXACT only",J54="EXACT",OR(J54="EXACT",J54="CLOSE")))),"yes","no") | AF54: =IF(ISNUMBER(H54),COUNTIFS($B$7:$B$608,B54,$C$7:$C$608,C54,$H$7:$H$608,"<"&H54,$AH$7:$AH$608,"yes")+COUNTIFS($B$7:B54,B54,$C$7:C54,C54,$H$7:H54,H54,$AH$7:AH54,"yes"),"") | AG54: =IF(ISNUMBER(I54),COUNTIFS($B$7:$B$608,B54,$C$7:$C$608,C54,$I$7:$I$608,"<"&I54,$AI$7:$AI$608,"yes")+COUNTIFS($B$7:B54,B54,$C$7:C54,C54,$I$7:I54,I54,$AI$7:AI54,"yes"),"") | AH54: =IF(ISNUMBER(H54),"yes","no") | AI54: =IF(ISNUMBER(I54),"yes","no") | AJ54: 46208
B55: GN 1/2 PC container, 150 mm | C55: Romania | D55: Lancom | E55: GN 1/2 150mm - Polycarbonate | F55: 5 | G55: EUR | H55: =IF(AND(AE55="yes",ISNUMBER(AD55)),AD55,"") | I55: =IF(AND(AE55="yes",ISNUMBER(AD55),ISNUMBER(INDEX('Sources'!$G$7:$G$10,MATCH(AB55,'Sources'!$B$7:$B$10,0)))),AD55/INDEX('Sources'!$G$7:$G$10,MATCH(AB55,'Sources'!$B$7:$B$10,0)),"") | J55: EXACT | K55: 2026-09-12 00:00:00 | M55: PC. Live check 30.09.2026: 5.00 € / buc fara TVA (discounted from 6.24 €); Lancom prices in EUR and invoices in RON at the BNR rate. Previously recorded as 26.28 RON (the EUR price converted at about 5.26). | N55: https://www.lancom.ro/tava-gastronorm-gn-12-150-policarbonat-6940 | O55: GastroPlast | U55: GN size, depth and material agree. Colour is unrestricted in the benchmark. | W55: 5.256 | X55: YES Gastro Romania Market Research.xlsx | Y55: Gabi | AB55: RON | AC55: yes | AD55: =IF(ISNUMBER(F55),IF(G55=AB55,F55,IF(AND(ISNUMBER(INDEX('Sources'!$G$7:$G$10,MATCH(G55,'Sources'!$B$7:$B$10,0))),ISNUMBER(INDEX('Sources'!$G$7:$G$10,MATCH(AB55,'Sources'!$B$7:$B$10,0)))),F55/INDEX('Sources'!$G$7:$G$10,MATCH(G55,'Sources'!$B$7:$B$10,0))*INDEX('Sources'!$G$7:$G$10,MATCH(AB55,'Sources'!$B$7:$B$10,0)),"")),"") | AE55: =IF(AND(AC55="yes",ISNUMBER(F55),IF('Compare'!$H$5="All mapped",TRUE,IF('Compare'!$H$5="EXACT only",J55="EXACT",OR(J55="EXACT",J55="CLOSE")))),"yes","no") | AF55: =IF(ISNUMBER(H55),COUNTIFS($B$7:$B$608,B55,$C$7:$C$608,C55,$H$7:$H$608,"<"&H55,$AH$7:$AH$608,"yes")+COUNTIFS($B$7:B55,B55,$C$7:C55,C55,$H$7:H55,H55,$AH$7:AH55,"yes"),"") | AG55: =IF(ISNUMBER(I55),COUNTIFS($B$7:$B$608,B55,$C$7:$C$608,C55,$I$7:$I$608,"<"&I55,$AI$7:$AI$608,"yes")+COUNTIFS($B$7:B55,B55,$C$7:C55,C55,$I$7:I55,I55,$AI$7:AI55,"yes"),"") | AH55: =IF(ISNUMBER(H55),"yes","no") | AI55: =IF(ISNUMBER(I55),"yes","no") | AJ55: 46277
B56: GN 1/2 PC container, 150 mm | C56: Romania | D56: Pro-cucina | E56: GN 1/2 150mm - Polycarbonate | F56: 6 | G56: EUR | H56: =IF(AND(AE56="yes",ISNUMBER(AD56)),AD56,"") | I56: =IF(AND(AE56="yes",ISNUMBER(AD56),ISNUMBER(INDEX('Sources'!$G$7:$G$10,MATCH(AB56,'Sources'!$B$7:$B$10,0)))),AD56/INDEX('Sources'!$G$7:$G$10,MATCH(AB56,'Sources'!$B$7:$B$10,0)),"") | J56: EXACT | K56: 2.07.2026 | M56: PC | N56: https://pro-cucina.ro/tavi-gn/ | U56: GN size, depth and material agree. Colour is unrestricted in the benchmark. | W56: 6 | X56: YES Gastro Romania Market Research.xlsx | Y56: Gabi | AB56: RON | AC56: yes | AD56: =IF(ISNUMBER(F56),IF(G56=AB56,F56,IF(AND(ISNUMBER(INDEX('Sources'!$G$7:$G$10,MATCH(G56,'Sources'!$B$7:$B$10,0))),ISNUMBER(INDEX('Sources'!$G$7:$G$10,MATCH(AB56,'Sources'!$B$7:$B$10,0)))),F56/INDEX('Sources'!$G$7:$G$10,MATCH(G56,'Sources'!$B$7:$B$10,0))*INDEX('Sources'!$G$7:$G$10,MATCH(AB56,'Sources'!$B$7:$B$10,0)),"")),"") | AE56: =IF(AND(AC56="yes",ISNUMBER(F56),IF('Compare'!$H$5="All mapped",TRUE,IF('Compare'!$H$5="EXACT only",J56="EXACT",OR(J56="EXACT",J56="CLOSE")))),"yes","no") | AF56: =IF(ISNUMBER(H56),COUNTIFS($B$7:$B$608,B56,$C$7:$C$608,C56,$H$7:$H$608,"<"&H56,$AH$7:$AH$608,"yes")+COUNTIFS($B$7:B56,B56,$C$7:C56,C56,$H$7:H56,H56,$AH$7:AH56,"yes"),"") | AG56: =IF(ISNUMBER(I56),COUNTIFS($B$7:$B$608,B56,$C$7:$C$608,C56,$I$7:$I$608,"<"&I56,$AI$7:$AI$608,"yes")+COUNTIFS($B$7:B56,B56,$C$7:C56,C56,$I$7:I56,I56,$AI$7:AI56,"yes"),"") | AH56: =IF(ISNUMBER(H56),"yes","no") | AI56: =IF(ISNUMBER(I56),"yes","no") | AJ56: 46205
B57: GN 1/2 PC container, 150 mm | C57: Romania | D57: mmgastro | E57: GN 1/2 150mm - Polycarbonate | F57: 35.79 | G57: RON | H57: =IF(AND(AE57="yes",ISNUMBER(AD57)),AD57,"") | I57: =IF(AND(AE57="yes",ISNUMBER(AD57),ISNUMBER(INDEX('Sources'!$G$7:$G$10,MATCH(AB57,'Sources'!$B$7:$B$10,0)))),AD57/INDEX('Sources'!$G$7:$G$10,MATCH(AB57,'Sources'!$B$7:$B$10,0)),"") | J57: EXACT | K57: 2.07.2026 | M57: PC | N57: https://mmgastro.ro/ro/menu/categorii/vase-gastronomice/vase-gn-din-policarbonat-11707?filter_text=&filter_producer=&filter_price=&filter_traits[47062]=70733&filter_traits[21]=&filter_traits[47060]=50734&filter_traits[69787]=&filter_traits[73752]= | O57: Forgast | U57: GN size, depth and material agree. Colour is unrestricted in the benchmark. | W57: 7.158 | X57: YES Gastro Romania Market Research.xlsx | Y57: Gabi | AB57: RON | AC57: yes | AD57: =IF(ISNUMBER(F57),IF(G57=AB57,F57,IF(AND(ISNUMBER(INDEX('Sources'!$G$7:$G$10,MATCH(G57,'Sources'!$B$7:$B$10,0))),ISNUMBER(INDEX('Sources'!$G$7:$G$10,MATCH(AB57,'Sources'!$B$7:$B$10,0)))),F57/INDEX('Sources'!$G$7:$G$10,MATCH(G57,'Sources'!$B$7:$B$10,0))*INDEX('Sources'!$G$7:$G$10,MATCH(AB57,'Sources'!$B$7:$B$10,0)),"")),"") | AE57: =IF(AND(AC57="yes",ISNUMBER(F57),IF('Compare'!$H$5="All mapped",TRUE,IF('Compare'!$H$5="EXACT only",J57="EXACT",OR(J57="EXACT",J57="CLOSE")))),"yes","no") | AF57: =IF(ISNUMBER(H57),COUNTIFS($B$7:$B$608,B57,$C$7:$C$608,C57,$H$7:$H$608,"<"&H57,$AH$7:$AH$608,"yes")+COUNTIFS($B$7:B57,B57,$C$7:C57,C57,$H$7:H57,H57,$AH$7:AH57,"yes"),"") | AG57: =IF(ISNUMBER(I57),COUNTIFS($B$7:$B$608,B57,$C$7:$C$608,C57,$I$7:$I$608,"<"&I57,$AI$7:$AI$608,"yes")+COUNTIFS($B$7:B57,B57,$C$7:C57,C57,$I$7:I57,I57,$AI$7:AI57,"yes"),"") | AH57: =IF(ISNUMBER(H57),"yes","no") | AI57: =IF(ISNUMBER(I57),"yes","no") | AJ57: 46205
B58: GN 1/2 PC container, 150 mm | C58: Austria | D58: ALLPAX Österreich | E58: PC GN 1/2 Höhe 150 mm schwarz | F58: 7.29 | G58: EUR | H58: =IF(AND(AE58="yes",ISNUMBER(AD58)),AD58,"") | I58: =IF(AND(AE58="yes",ISNUMBER(AD58),ISNUMBER(INDEX('Sources'!$G$7:$G$10,MATCH(AB58,'Sources'!$B$7:$B$10,0)))),AD58/INDEX('Sources'!$G$7:$G$10,MATCH(AB58,'Sources'!$B$7:$B$10,0)),"") | J58: EXACT | K58: 2026-09-30 | M58: 'jetzt' price; regular 10.35 | N58: https://www.allpax.at/product_info.php/info/PC-GN-1-2-Hoehe-150-mm-schwarz.html | P58: excl. | R58: 1 | T58: EXACT | U58: Existing benchmark assignment and match quality retained. | V58: 7.29 | X58: YES Gastro Austria Market Research.xlsx | AB58: EUR | AC58: yes | AD58: =IF(ISNUMBER(V58),V58,"") | AE58: =IF(AND(AC58="yes",ISNUMBER(F58),IF('Compare'!$H$5="All mapped",TRUE,IF('Compare'!$H$5="EXACT only",J58="EXACT",OR(J58="EXACT",J58="CLOSE")))),"yes","no") | AF58: =IF(ISNUMBER(H58),COUNTIFS($B$7:$B$608,B58,$C$7:$C$608,C58,$H$7:$H$608,"<"&H58,$AH$7:$AH$608,"yes")+COUNTIFS($B$7:B58,B58,$C$7:C58,C58,$H$7:H58,H58,$AH$7:AH58,"yes"),"") | AG58: =IF(ISNUMBER(I58),COUNTIFS($B$7:$B$608,B58,$C$7:$C$608,C58,$I$7:$I$608,"<"&I58,$AI$7:$AI$608,"yes")+COUNTIFS($B$7:B58,B58,$C$7:C58,C58,$I$7:I58,I58,$AI$7:AI58,"yes"),"") | AH58: =IF(ISNUMBER(H58),"yes","no") | AI58: =IF(ISNUMBER(I58),"yes","no") | AJ58: 46295
B59: GN 1/2 PC container, 150 mm | C59: Austria | D59: GastroHero Österreich | E59: Vogue GN-Behälter 1/2 Polycarbonat - Tiefe 150 mm | F59: 9.99 | G59: EUR | H59: =IF(AND(AE59="yes",ISNUMBER(AD59)),AD59,"") | I59: =IF(AND(AE59="yes",ISNUMBER(AD59),ISNUMBER(INDEX('Sources'!$G$7:$G$10,MATCH(AB59,'Sources'!$B$7:$B$10,0)))),AD59/INDEX('Sources'!$G$7:$G$10,MATCH(AB59,'Sources'!$B$7:$B$10,0)),"") | J59: EXACT | K59: 2026-09-30 | M59: Sale price (normal 11.89); min. qty 4. Schneider equivalent 17.39 | N59: https://www.gastro-hero.at/products/vogue-gn-behaelter-12-polycarbonat-tiefe-150-mm-u230 | O59: Vogue | P59: excl. | R59: 1 | T59: EXACT | U59: Existing benchmark assignment and match quality retained. | V59: 9.99 | X59: YES Gastro Austria Market Research.xlsx | AB59: EUR | AC59: yes | AD59: =IF(ISNUMBER(V59),V59,"") | AE59: =IF(AND(AC59="yes",ISNUMBER(F59),IF('Compare'!$H$5="All mapped",TRUE,IF('Compare'!$H$5="EXACT only",J59="EXACT",OR(J59="EXACT",J59="CLOSE")))),"yes","no") | AF59: =IF(ISNUMBER(H59),COUNTIFS($B$7:$B$608,B59,$C$7:$C$608,C59,$H$7:$H$608,"<"&H59,$AH$7:$AH$608,"yes")+COUNTIFS($B$7:B59,B59,$C$7:C59,C59,$H$7:H59,H59,$AH$7:AH59,"yes"),"") | AG59: =IF(ISNUMBER(I59),COUNTIFS($B$7:$B$608,B59,$C$7:$C$608,C59,$I$7:$I$608,"<"&I59,$AI$7:$AI$608,"yes")+COUNTIFS($B$7:B59,B59,$C$7:C59,C59,$I$7:I59,I59,$AI$7:AI59,"yes"),"") | AH59: =IF(ISNUMBER(H59),"yes","no") | AI59: =IF(ISNUMBER(I59),"yes","no") | AJ59: 46295
B60: GN 1/2 PC container, 150 mm | C60: Austria | D60: Gastrodax | E60: Hendi Gastronorm-Behälter 1/2, GN 1/2, 9,5L, Transparent, 325x265x(H)150mm – Polycarbonat | F60: 18.75 | G60: EUR | H60: =IF(AND(AE60="yes",ISNUMBER(AD60)),AD60,"") | I60: =IF(AND(AE60="yes",ISNUMBER(AD60),ISNUMBER(INDEX('Sources'!$G$7:$G$10,MATCH(AB60,'Sources'!$B$7:$B$10,0)))),AD60/INDEX('Sources'!$G$7:$G$10,MATCH(AB60,'Sources'!$B$7:$B$10,0)),"") | J60: EXACT | K60: 2026-09-30 | N60: https://www.gastrodax.de/hendi-gastronorm-behaelter-gn-1-2-9-5-l-polykarbonat-transparent-325-x-265-x-h-150-mm | O60: Hendi | P60: excl. | R60: 1 | T60: EXACT | U60: Existing benchmark assignment and match quality retained. | V60: 18.75 | X60: YES Gastro Austria Market Research.xlsx | AB60: EUR | AC60: yes | AD60: =IF(ISNUMBER(V60),V60,"") | AE60: =IF(AND(AC60="yes",ISNUMBER(F60),IF('Compare'!$H$5="All mapped",TRUE,IF('Compare'!$H$5="EXACT only",J60="EXACT",OR(J60="EXACT",J60="CLOSE")))),"yes","no") | AF60: =IF(ISNUMBER(H60),COUNTIFS($B$7:$B$608,B60,$C$7:$C$608,C60,$H$7:$H$608,"<"&H60,$AH$7:$AH$608,"yes")+COUNTIFS($B$7:B60,B60,$C$7:C60,C60,$H$7:H60,H60,$AH$7:AH60,"yes"),"") | AG60: =IF(ISNUMBER(I60),COUNTIFS($B$7:$B$608,B60,$C$7:$C$608,C60,$I$7:$I$608,"<"&I60,$AI$7:$AI$608,"yes")+COUNTIFS($B$7:B60,B60,$C$7:C60,C60,$I$7:I60,I60,$AI$7:AI60,"yes"),"") | AH60: =IF(ISNUMBER(H60),"yes","no") | AI60: =IF(ISNUMBER(I60),"yes","no") | AJ60: 46295
B61: GN 1/2 PC container, 150 mm | C61: Austria | D61: Gastroladen.at (Harotec GmbH) | E61: Vogue Polycarbonat GN-Behälter GN1/2 150mm | F61: 10.09 | G61: EUR | H61: =IF(AND(AE61="yes",ISNUMBER(AD61)),AD61,"") | I61: =IF(AND(AE61="yes",ISNUMBER(AD61),ISNUMBER(INDEX('Sources'!$G$7:$G$10,MATCH(AB61,'Sources'!$B$7:$B$10,0)))),AD61/INDEX('Sources'!$G$7:$G$10,MATCH(AB61,'Sources'!$B$7:$B$10,0)),"") | J61: EXACT | K61: 2026-09-30 | N61: https://www.gastroladen.at/3020@GN-U230/Vogue-Polycarbonat-GN-Beh%C3%A4lter-GN1-2-150mm.htm | O61: Vogue | P61: incl. | R61: 1 | T61: EXACT | U61: Existing benchmark assignment and match quality retained. | V61: 8.41 | X61: YES Gastro Austria Market Research.xlsx | AB61: EUR | AC61: yes | AD61: =IF(ISNUMBER(V61),V61,"") | AE61: =IF(AND(AC61="yes",ISNUMBER(F61),IF('Compare'!$H$5="All mapped",TRUE,IF('Compare'!$H$5="EXACT only",J61="EXACT",OR(J61="EXACT",J61="CLOSE")))),"yes","no") | AF61: =IF(ISNUMBER(H61),COUNTIFS($B$7:$B$608,B61,$C$7:$C$608,C61,$H$7:$H$608,"<"&H61,$AH$7:$AH$608,"yes")+COUNTIFS($B$7:B61,B61,$C$7:C61,C61,$H$7:H61,H61,$AH$7:AH61,"yes"),"") | AG61: =IF(ISNUMBER(I61),COUNTIFS($B$7:$B$608,B61,$C$7:$C$608,C61,$I$7:$I$608,"<"&I61,$AI$7:$AI$608,"yes")+COUNTIFS($B$7:B61,B61,$C$7:C61,C61,$I$7:I61,I61,$AI$7:AI61,"yes"),"") | AH61: =IF(ISNUMBER(H61),"yes","no") | AI61: =IF(ISNUMBER(I61),"yes","no") | AJ61: 46295
B62: GN 1/2 PC container, 150 mm | C62: Austria | D62: Intergastro (AT shop) | E62: Gastronorm Behälter GN 1/2 GN 96 BLACK Polycarbonat schwarz H 150 mm | F62: 10.17 | G62: EUR | H62: =IF(AND(AE62="yes",ISNUMBER(AD62)),AD62,"") | I62: =IF(AND(AE62="yes",ISNUMBER(AD62),ISNUMBER(INDEX('Sources'!$G$7:$G$10,MATCH(AB62,'Sources'!$B$7:$B$10,0)))),AD62/INDEX('Sources'!$G$7:$G$10,MATCH(AB62,'Sources'!$B$7:$B$10,0)),"") | J62: EXACT | K62: 2026-09-30 | M62: Black PC; gross 12.20 | N62: https://www.intergastro.at/gastronorm-behaelter-gn-1-2-gn-96-black-polycarbonat-schwarz-h-150-mm-1016774 | O62: WAS Germany | P62: excl. | R62: 1 | T62: EXACT | U62: Existing benchmark assignment and match quality retained. | V62: 10.17 | X62: YES Gastro Austria Market Research.xlsx | AB62: EUR | AC62: yes | AD62: =IF(ISNUMBER(V62),V62,"") | AE62: =IF(AND(AC62="yes",ISNUMBER(F62),IF('Compare'!$H$5="All mapped",TRUE,IF('Compare'!$H$5="EXACT only",J62="EXACT",OR(J62="EXACT",J62="CLOSE")))),"yes","no") | AF62: =IF(ISNUMBER(H62),COUNTIFS($B$7:$B$608,B62,$C$7:$C$608,C62,$H$7:$H$608,"<"&H62,$AH$7:$AH$608,"yes")+COUNTIFS($B$7:B62,B62,$C$7:C62,C62,$H$7:H62,H62,$AH$7:AH62,"yes"),"") | AG62: =IF(ISNUMBER(I62),COUNTIFS($B$7:$B$608,B62,$C$7:$C$608,C62,$I$7:$I$608,"<"&I62,$AI$7:$AI$608,"yes")+COUNTIFS($B$7:B62,B62,$C$7:C62,C62,$I$7:I62,I62,$AI$7:AI62,"yes"),"") | AH62: =IF(ISNUMBER(H62),"yes","no") | AI62: =IF(ISNUMBER(I62),"yes","no") | AJ62: 46295
B63: GN 1/2 PC container, 150 mm | C63: Austria | D63: Jungheinrich PROFISHOP Austria | E63: Stalgast ARAVEN Gastronormbehälter mit Deckel, Polypropylen, GN 1/2 (150 mm) | F63: 37.9 | G63: EUR | H63: =IF(AND(AE63="yes",ISNUMBER(AD63)),AD63,"") | I63: =IF(AND(AE63="yes",ISNUMBER(AD63),ISNUMBER(INDEX('Sources'!$G$7:$G$10,MATCH(AB63,'Sources'!$B$7:$B$10,0)))),AD63/INDEX('Sources'!$G$7:$G$10,MATCH(AB63,'Sources'!$B$7:$B$10,0)),"") | J63: APPROX | K63: 2026-09-30 | M63: Polypropylene (not polycarbonate) and includes lid; no PC GN 1/2 150 mm found | N63: https://www.jh-profishop.at/p/stalgast-araven-gastronormbehaelter-mit-deckel-polypropylen-gn-1-2-150-mm-928334-347849/ | O63: Stalgast / Araven | P63: excl. | R63: 1 | T63: APPROX | U63: Existing benchmark assignment and match quality retained. | V63: 37.9 | X63: YES Gastro Austria Market Research.xlsx | AB63: EUR | AC63: yes | AD63: =IF(ISNUMBER(V63),V63,"") | AE63: =IF(AND(AC63="yes",ISNUMBER(F63),IF('Compare'!$H$5="All mapped",TRUE,IF('Compare'!$H$5="EXACT only",J63="EXACT",OR(J63="EXACT",J63="CLOSE")))),"yes","no") | AF63: =IF(ISNUMBER(H63),COUNTIFS($B$7:$B$608,B63,$C$7:$C$608,C63,$H$7:$H$608,"<"&H63,$AH$7:$AH$608,"yes")+COUNTIFS($B$7:B63,B63,$C$7:C63,C63,$H$7:H63,H63,$AH$7:AH63,"yes"),"") | AG63: =IF(ISNUMBER(I63),COUNTIFS($B$7:$B$608,B63,$C$7:$C$608,C63,$I$7:$I$608,"<"&I63,$AI$7:$AI$608,"yes")+COUNTIFS($B$7:B63,B63,$C$7:C63,C63,$I$7:I63,I63,$AI$7:AI63,"yes"),"") | AH63: =IF(ISNUMBER(H63),"yes","no") | AI63: =IF(ISNUMBER(I63),"yes","no") | AJ63: 46295
B64: GN 1/2 PC container, 150 mm | C64: Austria | D64: shopbuero.com | E64: GN-Behälter - GN 1/2 (325 x 265 mm) - 150 mm - Inhalt 9,0 l - Polycarbonat | F64: 10.9 | G64: EUR | H64: =IF(AND(AE64="yes",ISNUMBER(AD64)),AD64,"") | I64: =IF(AND(AE64="yes",ISNUMBER(AD64),ISNUMBER(INDEX('Sources'!$G$7:$G$10,MATCH(AB64,'Sources'!$B$7:$B$10,0)))),AD64/INDEX('Sources'!$G$7:$G$10,MATCH(AB64,'Sources'!$B$7:$B$10,0)),"") | J64: EXACT | K64: 2026-09-30 | M64: Regular price 17.20 | N64: https://shopbuero.com/gn-behaelter-gn-1-2-325-x-265-mm-150-mm-inhalt-9-0-l-polycarbonat/530112-C | O64: Schneider | P64: excl. | R64: 1 | T64: EXACT | U64: Existing benchmark assignment and match quality retained. | V64: 10.9 | X64: YES Gastro Austria Market Research.xlsx | AB64: EUR | AC64: yes | AD64: =IF(ISNUMBER(V64),V64,"") | AE64: =IF(AND(AC64="yes",ISNUMBER(F64),IF('Compare'!$H$5="All mapped",TRUE,IF('Compare'!$H$5="EXACT only",J64="EXACT",OR(J64="EXACT",J64="CLOSE")))),"yes","no") | AF64: =IF(ISNUMBER(H64),COUNTIFS($B$7:$B$608,B64,$C$7:$C$608,C64,$H$7:$H$608,"<"&H64,$AH$7:$AH$608,"yes")+COUNTIFS($B$7:B64,B64,$C$7:C64,C64,$H$7:H64,H64,$AH$7:AH64,"yes"),"") | AG64: =IF(ISNUMBER(I64),COUNTIFS($B$7:$B$608,B64,$C$7:$C$608,C64,$I$7:$I$608,"<"&I64,$AI$7:$AI$608,"yes")+COUNTIFS($B$7:B64,B64,$C$7:C64,C64,$I$7:I64,I64,$AI$7:AI64,"yes"),"") | AH64: =IF(ISNUMBER(H64),"yes","no") | AI64: =IF(ISNUMBER(I64),"yes","no") | AJ64: 46295
B65: GN 1/2 PC container, 150 mm | C65: Germany | D65: ALLPAX | E65: PC GN 1/2 Höhe 150 mm schwarz | F65: 7.29 | G65: EUR | H65: =IF(AND(AE65="yes",ISNUMBER(AD65)),AD65,"") | I65: =IF(AND(AE65="yes",ISNUMBER(AD65),ISNUMBER(INDEX('Sources'!$G$7:$G$10,MATCH(AB65,'Sources'!$B$7:$B$10,0)))),AD65/INDEX('Sources'!$G$7:$G$10,MATCH(AB65,'Sources'!$B$7:$B$10,0)),"") | J65: EXACT | K65: 2026-09-30 | M65: 'jetzt' price; regular 10.35 | N65: https://www.allpax.de/product_info.php/info/PC-GN-1-2-Hoehe-150-mm-schwarz.html | P65: excl. | R65: 1 | T65: EXACT | U65: Existing benchmark assignment and match quality retained. | V65: 7.29 | X65: YES Gastro Germany Market Research.xlsx | AB65: EUR | AC65: yes | AD65: =IF(ISNUMBER(V65),V65,"") | AE65: =IF(AND(AC65="yes",ISNUMBER(F65),IF('Compare'!$H$5="All mapped",TRUE,IF('Compare'!$H$5="EXACT only",J65="EXACT",OR(J65="EXACT",J65="CLOSE")))),"yes","no") | AF65: =IF(ISNUMBER(H65),COUNTIFS($B$7:$B$608,B65,$C$7:$C$608,C65,$H$7:$H$608,"<"&H65,$AH$7:$AH$608,"yes")+COUNTIFS($B$7:B65,B65,$C$7:C65,C65,$H$7:H65,H65,$AH$7:AH65,"yes"),"") | AG65: =IF(ISNUMBER(I65),COUNTIFS($B$7:$B$608,B65,$C$7:$C$608,C65,$I$7:$I$608,"<"&I65,$AI$7:$AI$608,"yes")+COUNTIFS($B$7:B65,B65,$C$7:C65,C65,$I$7:I65,I65,$AI$7:AI65,"yes"),"") | AH65: =IF(ISNUMBER(H65),"yes","no") | AI65: =IF(ISNUMBER(I65),"yes","no") | AJ65: 46295
B66: GN 1/2 PC container, 150 mm | C66: Germany | D66: GGM Gastro | E66: (6 Stück) CAMBRO CAMVIEW Copolymer-Behälter GN 1/2 - Höhe 150mm - BPA-frei | F66: 56.99 | G66: EUR | H66: =IF(AND(AE66="yes",ISNUMBER(AD66)),AD66,"") | I66: =IF(AND(AE66="yes",ISNUMBER(AD66),ISNUMBER(INDEX('Sources'!$G$7:$G$10,MATCH(AB66,'Sources'!$B$7:$B$10,0)))),AD66/INDEX('Sources'!$G$7:$G$10,MATCH(AB66,'Sources'!$B$7:$B$10,0)),"") | J66: APPROX | K66: 2026-09-30 | M66: Copolyester (Tritan-type), not polycarbonate; no PC GN 1/2 150 mm found in GGM sitemap | N66: https://www.ggmgastro.com/de-de-eur/6-stueck-cambro-camview-r-copolymer-behaelter-gn-1-2-transparent-hoehe-150mm-bpa-frei-26cv135 | O66: Cambro | P66: excl. | R66: 6 | S66: set of 6 | T66: APPROX | U66: Existing benchmark assignment and match quality retained. | V66: 9.5 | X66: YES Gastro Germany Market Research.xlsx | AB66: EUR | AC66: yes | AD66: =IF(ISNUMBER(V66),V66,"") | AE66: =IF(AND(AC66="yes",ISNUMBER(F66),IF('Compare'!$H$5="All mapped",TRUE,IF('Compare'!$H$5="EXACT only",J66="EXACT",OR(J66="EXACT",J66="CLOSE")))),"yes","no") | AF66: =IF(ISNUMBER(H66),COUNTIFS($B$7:$B$608,B66,$C$7:$C$608,C66,$H$7:$H$608,"<"&H66,$AH$7:$AH$608,"yes")+COUNTIFS($B$7:B66,B66,$C$7:C66,C66,$H$7:H66,H66,$AH$7:AH66,"yes"),"") | AG66: =IF(ISNUMBER(I66),COUNTIFS($B$7:$B$608,B66,$C$7:$C$608,C66,$I$7:$I$608,"<"&I66,$AI$7:$AI$608,"yes")+COUNTIFS($B$7:B66,B66,$C$7:C66,C66,$I$7:I66,I66,$AI$7:AI66,"yes"),"") | AH66: =IF(ISNUMBER(H66),"yes","no") | AI66: =IF(ISNUMBER(I66),"yes","no") | AJ66: 46295
B67: GN 1/2 PC container, 150 mm | C67: Germany | D67: GastroHero | E67: Vogue GN-Behälter 1/2 Polycarbonat - Tiefe 150 mm | F67: 9.59 | G67: EUR | H67: =IF(AND(AE67="yes",ISNUMBER(AD67)),AD67,"") | I67: =IF(AND(AE67="yes",ISNUMBER(AD67),ISNUMBER(INDEX('Sources'!$G$7:$G$10,MATCH(AB67,'Sources'!$B$7:$B$10,0)))),AD67/INDEX('Sources'!$G$7:$G$10,MATCH(AB67,'Sources'!$B$7:$B$10,0)),"") | J67: EXACT | K67: 2026-09-30 | M67: Min. qty 4. (Schneider equivalent available too) | N67: https://www.gastro-hero.de/products/vogue-gn-behaelter-12-polycarbonat-tiefe-150-mm-u230 | O67: Vogue | P67: excl. | R67: 1 | T67: EXACT | U67: Existing benchmark assignment and match quality retained. | V67: 9.59 | X67: YES Gastro Germany Market Research.xlsx | AB67: EUR | AC67: yes | AD67: =IF(ISNUMBER(V67),V67,"") | AE67: =IF(AND(AC67="yes",ISNUMBER(F67),IF('Compare'!$H$5="All mapped",TRUE,IF('Compare'!$H$5="EXACT only",J67="EXACT",OR(J67="EXACT",J67="CLOSE")))),"yes","no") | AF67: =IF(ISNUMBER(H67),COUNTIFS($B$7:$B$608,B67,$C$7:$C$608,C67,$H$7:$H$608,"<"&H67,$AH$7:$AH$608,"yes")+COUNTIFS($B$7:B67,B67,$C$7:C67,C67,$H$7:H67,H67,$AH$7:AH67,"yes"),"") | AG67: =IF(ISNUMBER(I67),COUNTIFS($B$7:$B$608,B67,$C$7:$C$608,C67,$I$7:$I$608,"<"&I67,$AI$7:$AI$608,"yes")+COUNTIFS($B$7:B67,B67,$C$7:C67,C67,$I$7:I67,I67,$AI$7:AI67,"yes"),"") | AH67: =IF(ISNUMBER(H67),"yes","no") | AI67: =IF(ISNUMBER(I67),"yes","no") | AJ67: 46295
B68: GN 1/2 PC container, 150 mm | C68: Germany | D68: Gastrodax [substitute] | E68: Hendi Gastronorm-Behälter 1/2, GN 1/2, 9,5L, Transparent, 325x265x(H)150mm – Polycarbonat | F68: 18.75 | G68: EUR | H68: =IF(AND(AE68="yes",ISNUMBER(AD68)),AD68,"") | I68: =IF(AND(AE68="yes",ISNUMBER(AD68),ISNUMBER(INDEX('Sources'!$G$7:$G$10,MATCH(AB68,'Sources'!$B$7:$B$10,0)))),AD68/INDEX('Sources'!$G$7:$G$10,MATCH(AB68,'Sources'!$B$7:$B$10,0)),"") | J68: EXACT | K68: 2026-09-30 | N68: https://www.gastrodax.de/hendi-gastronorm-behaelter-gn-1-2-9-5-l-polykarbonat-transparent-325-x-265-x-h-150-mm | O68: Hendi | P68: excl. | R68: 1 | T68: EXACT | U68: Existing benchmark assignment and match quality retained. | V68: 18.75 | X68: YES Gastro Germany Market Research.xlsx | AB68: EUR | AC68: yes | AD68: =IF(ISNUMBER(V68),V68,"") | AE68: =IF(AND(AC68="yes",ISNUMBER(F68),IF('Compare'!$H$5="All mapped",TRUE,IF('Compare'!$H$5="EXACT only",J68="EXACT",OR(J68="EXACT",J68="CLOSE")))),"yes","no") | AF68: =IF(ISNUMBER(H68),COUNTIFS($B$7:$B$608,B68,$C$7:$C$608,C68,$H$7:$H$608,"<"&H68,$AH$7:$AH$608,"yes")+COUNTIFS($B$7:B68,B68,$C$7:C68,C68,$H$7:H68,H68,$AH$7:AH68,"yes"),"") | AG68: =IF(ISNUMBER(I68),COUNTIFS($B$7:$B$608,B68,$C$7:$C$608,C68,$I$7:$I$608,"<"&I68,$AI$7:$AI$608,"yes")+COUNTIFS($B$7:B68,B68,$C$7:C68,C68,$I$7:I68,I68,$AI$7:AI68,"yes"),"") | AH68: =IF(ISNUMBER(H68),"yes","no") | AI68: =IF(ISNUMBER(I68),"yes","no") | AJ68: 46295
